Workbook

Sheet Cover
F8: ASML Holding NV
F9: (Ticker: ASML-NL) | N9: Table of Contents
F11: ASML Holding N.V. is a Dutch multinational to the | N11: Assumptions
F12: global semiconductor industry headquartered in
F13: Veldhoven, the Netherlands, and a leading supplier.
F14: The company provides chipmakers with advanced
F15: lithography systems as well as related software
F16: and services that enable the mass production of
F17: integrated circuit patterns on silicon.
E34: Created By: Divij Budhiraja

Sheet Summary
B2: ASML HOLDING NV — VALUATION SUMMARY
B3: Confidential | For Discussion Purposes Only | All figures in €mm unless stated otherwise
B5: Current Price | D5: Market Cap | F5: Enterprise Value | H5: WACC | J5: LTM Revenue | L5: LTM EBIT Margin | N5: Levered Beta
B6: €652.00 | D6: €471,835mm | F6: €469,412mm | H6: 0.1 | J6: €28,263mm | L6: 0.319 | N6: 1.69x
B8: VALUATION FOOTBALL FIELD
B9: Methodology | C9: Low | D9: Range Width | E9: High | F9: Base Case
B10: DCF — Perpetuity Growth | C10: 418.4 | D10: =F10-C10 -> 136.39 | E10: 878.94 | F10: 554.79
B11: DCF — Exit Multiple | C11: 546.45 | D11: =F11-C11 -> 136.6 | E11: 840.99 | F11: 683.05
B12: Comps — EV/EBITDA | C12: 862.27 | D12: =F12-C12 -> 98.46 | E12: 1059.19 | F12: 960.73
B13: Comps — EV/Revenue | C13: 907.57 | D13: =F13-C13 -> 101.99 | E13: 1111.54 | F13: 1009.56
B14: Current Share Price | C14: 652
B17: REVENUE GROWTH SCENARIOS (€mm)
B18: Scenario | C18: 2024A | D18: 2025E | E18: 2026E | F18: 2027E | G18: 2028E | H18: 2029E
B19: Bull Case | C19: 28262.9 | D19: 33915.5 | E19: 40020.3 | F19: 46023.3 | G19: 51546.1 | H19: 56700.7
B20: Base Case | C20: 28262.9 | D20: 32502.3 | E20: 36402.6 | F20: 40042.9 | G20: 43246.3 | H20: 45841.1
B21: Bear Case | C21: 28262.9 | D21: 29676 | E21: 30566.3 | F21: 31789 | G21: 33378.4 | H21: 34713.6
B22: Bull / Base / Bear Growth | D22: 20% / 15% / 5% | E22: 18% / 12% / 3% | F22: 15% / 10% / 4% | G22: 12% / 8% / 5% | H22: 10% / 6% / 4%
B25: KEY FINANCIAL SUMMARY (€mm)
C26: 2022A | D26: 2023A | E26: 2024A | F26: 2025E | G26: 2026E | H26: 2027E | I26: 2028E | J26: 2029E
B27: Revenue | C27: 21173.4 | D27: 27558.5 | E27: 28262.9 | F27: 33915.5 | G27: 40020.3 | H27: 46023.3 | I27: 51546.1 | J27: 56700.7
B28: % Growth | D28: 0.302 | E28: 0.026 | F28: 0.2 | G28: 0.18 | H28: 0.15 | I28: 0.12 | J28: 0.1
B29: Gross Profit | C29: 11114.6 | D29: 14622.2 | E29: 15067.7 | F29: 18653.5 | G29: 22411.3 | H29: 26233.3 | I29: 29896.7 | J29: 32886.4
B30: % Margin | C30: 0.525 | D30: 0.531 | E30: 0.533 | F30: 0.55 | G30: 0.56 | H30: 0.57 | I30: 0.58 | J30: 0.58
B31: EBIT | C31: 6500.7 | D31: 9042.3 | E31: 9022.6 | F31: 11416 | G31: 14235.4 | H31: 17223.8 | I31: 20174.2 | J31: 22537.6
B32: % Margin | C32: 0.307 | D32: 0.328 | E32: 0.319 | F32: 0.337 | G32: 0.356 | H32: 0.374 | I32: 0.391 | J32: 0.397
B33: Net Income | C33: 5624.2 | D33: 7839 | E33: 7571.6 | F33: 9736.5 | G33: 12125.9 | H33: 14735.7 | I33: 17350.8 | J33: 19531.5
B34: % Margin | C34: 0.266 | D34: 0.284 | E34: 0.268 | F34: 0.287 | G34: 0.303 | H34: 0.32 | I34: 0.337 | J34: 0.344
B35: Unlevered FCF | E35: 8400.6 | F35: 9922.2 | G35: 11663.9 | H35: 13918.6 | I35: 16136.6 | J35: 17380.6
B36: FCF Conversion | E36: 1.129 | F36: 1.054 | G36: 0.993 | H36: 0.98 | I36: 0.97 | J36: 0.935
B39: DCF KEY ASSUMPTIONS | E39: ENTERPRISE VALUE TO EQUITY BRIDGE
B40: Risk-Free Rate | C40: 0.0291 | F40: Perpetuity Growth | G40: Exit Multiple
B41: Equity Risk Premium | C41: 0.0423 | E41: Sum of PV of FCF | F41: 53401 | G41: 53401
B42: Levered Beta | C42: 1.69x | E42: PV of Terminal Value | F42: 154372 | G42: 204817
B43: Cost of Equity (Ke) | C43: 0.1006 | E43: Enterprise Value | F43: 207773 | G43: 258219
B44: Pre-Tax Cost of Debt | C44: 0.0239 | E44: Less: Total Debt | F44: -4994 | G44: -4994
B45: After-Tax Cost of Debt | C45: 0.0197 | E45: Plus: Cash & Equivalents | F45: 12741 | G45: 12741
B46: Equity Weight | C46: 0.994 | E46: Plus: Equity Investments | F46: 2677 | G46: 2677
B47: Debt Weight | C47: 0.006 | E47: Equity Value | F47: 218198 | G47: 268643
B48: WACC | C48: 0.1001 | E48: Shares Outstanding (mm) | F48: 393.3 | G48: 393.3
B49: Perpetual Growth Rate | C49: 0.025 | E49: Implied Share Price (€) | F49: 554.79 | G49: 683.05
B50: Exit EV/EBITDA Multiple | C50: 15.0x | E50: Current Share Price (€) | F50: 652 | G50: 652
B53: COMPARABLE COMPANIES ANALYSIS — TRADING MULTIPLES | J53: 2024A | K53: 2025E | L53: 2026E | M53: 2027E | N53: 2028E
B54: Company | C54: EV/Revenue | D54: EV/EBITDA | E54: EV/EBIT | F54: P/E (FY1) | G54: P/E (FY2) | H54: Gross Margin | I54: Revenue | J54: 28263 | K54: 33916 | L54: 40020 | M54: 46023 | N54: 51546
B55: ASML Holding NV | C55: 16.6x | D55: 46.9x | E55: 52.0x | F55: 41.7x | G55: 32.6x | H55: 0.512 | I55: EBIT | J55: 9023 | K55: 11416 | L55: 14235 | M55: 17224 | N55: 20174
B56: KLA Corporation | C56: 14.1x | D56: 31.1x | E56: 32.9x | F56: 39.1x | G56: 31.1x | H56: 0.614 | I56: Net Income | J56: 7572 | K56: 9737 | L56: 12126 | M56: 14736 | N56: 17351
B57: Applied Materials | C57: 8.7x | D57: 27.5x | E57: 29.0x | F57: 33.3x | G57: 26.8x | H57: 0.477 | I57: Unlevered FCF | J57: 8401 | K57: 9922 | L57: 11664 | M57: 13919 | N57: 16137
I58: EBIT Margin | J58: 0.319 | K58: 0.337 | L58: 0.356 | M58: 0.374 | N58: 0.391
B59: Peer Mean (excl. ASML) | C59: 11.4x | D59: 29.3x | E59: 31.0x | F59: 36.2x | G59: 29.0x | H59: 0.546
B60: Peer Median | C60: 11.4x | D60: 29.3x | E60: 31.0x | F60: 36.2x | G60: 29.0x | H60: 0.546
B61: ASML Premium / (Discount) | C61: 0.457 | D61: 0.601 | E61: 0.679 | F61: 0.152 | G61: 0.125 | H61: -0.062
B64: MARGIN EXPANSION ANALYSIS
B65: Metric | C65: 2024A | D65: 2025E | E65: 2026E | F65: 2027E | G65: 2028E | H65: 2029E
B66: Gross Margin | C66: 0.533 | D66: 0.55 | E66: 0.56 | F66: 0.57 | G66: 0.58 | H66: 0.58
B67: EBIT Margin | C67: 0.319 | D67: 0.337 | E67: 0.356 | F67: 0.374 | G67: 0.391 | H67: 0.397
B68: Net Income Margin | C68: 0.268 | D68: 0.287 | E68: 0.303 | F68: 0.32 | G68: 0.337 | H68: 0.344
B69: FCF Yield (UFCF/Rev) | C69: 0.297 | D69: 0.293 | E69: 0.291 | F69: 0.302 | G69: 0.313 | H69: 0.307
B70: R&D % of Revenue | C70: 0.139 | D70: 0.14 | E70: 0.135 | F70: 0.13 | G70: 0.125 | H70: 0.12
B71: SG&A % of Revenue | C71: 0.039 | D71: 0.04 | E71: 0.038 | F71: 0.036 | G71: 0.035 | H71: 0.035
B74: SENSITIVITY ANALYSIS — IMPLIED SHARE PRICE (€)
B75: Perpetuity Growth Method (WACC \ Growth Rate)
B76: WACC \ g | C76: 0.015 | D76: 0.02 | E76: 0.025 | F76: 0.03 | G76: 0.035
B77: 0.08 | C77: 649 | D77: 692 | E77: 743 | F77: 804 | G77: 879
B78: 0.09 | C78: 567 | D78: 598 | E78: 634 | F78: 676 | G78: 725
B79: 0.1 | C79: 505 | D79: 528 | E79: 555 | F79: 585 | G79: 619
B80: 0.11 | C80: 457 | D80: 475 | E80: 495 | F80: 517 | G80: 543
B81: 0.12 | C81: 418 | D81: 433 | E81: 448 | F81: 465 | G81: 485
B83: Exit Multiple Method (WACC \ EV/EBITDA)
B84: WACC \ EV/EBITDA | C84: 12.0x | D84: 13.5x | E84: 15.0x | F84: 16.5x | G84: 18.0x
B85: 0.08 | C85: 615 | D85: 671 | E85: 728 | F85: 784 | G85: 841
B86: 0.09 | C86: 596 | D86: 651 | E86: 705 | F86: 759 | G86: 813
B87: 0.1 | C87: 579 | D87: 631 | E87: 683 | F87: 735 | G87: 787
B88: 0.11 | C88: 562 | D88: 612 | E88: 662 | F88: 712 | G88: 762
B89: 0.12 | C89: 546 | D89: 594 | E89: 642 | F89: 691 | G89: 739
B91: VALUATION CONCLUSION
B92: Methodology | C92: Low | D92: Base Case | E92: High | F92: Weight
B93: DCF — Perpetuity Growth | C93: €418 | D93: €555 | E93: €879 | F93: 0.35
B94: DCF — Exit Multiple | C94: €546 | D94: €683 | E94: €841 | F94: 0.35
B95: Comps — EV/EBITDA | C95: €862 | D95: €961 | E95: €1,059 | F95: 0.2
B96: Comps — EV/Revenue | C96: €908 | D96: €1,010 | E96: €1,112 | F96: 0.1
B98: Weighted Implied Share Price | D98: €709
B99: Current Share Price | D99: €652
B100: Implied Upside / (Downside) | D100: 0.087
B103: Note: This analysis is for discussion purposes only. Valuation ranges reflect sensitivity to key assumptions including WACC (8-12%), terminal growth (1.5-3.5%), and exit multiples (12-18x). Active scenario: Bull Case.

Sheet Assumptions and Inputs
B2: MODEL ASSUMPTIONS AND OTHER INPUTS
B6: SCENARIO SELECTOR
B8: Active Scenario (1=Base, 2=Bull, 3=Bear) | E8: 2
B10: Scenario Definitions:
B11: 1 = Base Case | E11: Management guidance, consensus estimates, normalized growth
B12: 2 = Bull Case | E12: Upside from AI/HPC demand, market share gains, margin expansion
B13: 3 = Bear Case | E13: Cyclical downturn, China restrictions, slower adoption
B16: REVENUE ASSUMPTIONS
E17: 2024A | F17: 2025E | G17: 2026E | H17: 2027E | I17: 2028E | J17: 2029E
B18: Revenue Growth Rate - Base | F18: 0.15 | G18: 0.12 | H18: 0.1 | I18: 0.08 | J18: 0.06
B19: Revenue Growth Rate - Bull | F19: 0.2 | G19: 0.18 | H19: 0.15 | I19: 0.12 | J19: 0.1
B20: Revenue Growth Rate - Bear | F20: 0.05 | G20: 0.03 | H20: 0.04 | I20: 0.05 | J20: 0.04
B21: Selected Revenue Growth | F21: =IF($E$8=1,F18,IF($E$8=2,F19,F20)) -> 0.2 | G21: =IF($E$8=1,G18,IF($E$8=2,G19,G20)) -> 0.18 | H21: =IF($E$8=1,H18,IF($E$8=2,H19,H20)) -> 0.15 | I21: =IF($E$8=1,I18,IF($E$8=2,I19,I20)) -> 0.12 | J21: =IF($E$8=1,J18,IF($E$8=2,J19,J20)) -> 0.1
B24: MARGIN ASSUMPTIONS
E25: 2024A | F25: 2025E | G25: 2026E | H25: 2027E | I25: 2028E | J25: 2029E
B26: COGS % of Revenue - Base | E26: ='3-Statement Model'!G11/'3-Statement Model'!G10*-1 -> 0.46687353 | F26: 0.465 | G26: 0.46 | H26: 0.455 | I26: 0.45 | J26: 0.45
B27: COGS % of Revenue - Bull | F27: 0.45 | G27: 0.44 | H27: 0.43 | I27: 0.42 | J27: 0.42
B28: COGS % of Revenue - Bear | F28: 0.5 | G28: 0.51 | H28: 0.52 | I28: 0.52 | J28: 0.52
B29: Selected COGS % | E29: =E26 -> 0.46687353 | F29: =IF($E$8=1,F26,IF($E$8=2,F27,F28)) -> 0.45 | G29: =IF($E$8=1,G26,IF($E$8=2,G27,G28)) -> 0.44 | H29: =IF($E$8=1,H26,IF($E$8=2,H27,H28)) -> 0.43 | I29: =IF($E$8=1,I26,IF($E$8=2,I27,I28)) -> 0.42 | J29: =IF($E$8=1,J26,IF($E$8=2,J27,J28)) -> 0.42
B31: R&D % of Revenue | E31: ='3-Statement Model'!G14/'3-Statement Model'!G10*-1 -> 0.13949029 | F31: 0.14 | G31: 0.135 | H31: 0.13 | I31: 0.125 | J31: 0.12
B32: SG&A % of Revenue | E32: ='3-Statement Model'!G15/'3-Statement Model'!G10*-1 -> 0.039482856 | F32: 0.04 | G32: 0.038 | H32: 0.036 | I32: 0.035 | J32: 0.035
B34: TAX & OTHER
E35: 2024A | F35: 2025E | G35: 2026E | H35: 2027E | I35: 2028E | J35: 2029E
B36: Effective Tax Rate | E36: ='3-Statement Model'!G24/'3-Statement Model'!G22*-1 -> 0.18585774 | F36: 0.175 | G36: 0.18 | H36: 0.18 | I36: 0.18 | J36: 0.18
B37: Interest Rate on Cash | F37: 0.025 | G37: 0.025 | H37: 0.025 | I37: 0.025 | J37: 0.025
B38: Interest Rate on Debt | F38: 0.04 | G38: 0.04 | H38: 0.04 | I38: 0.04 | J38: 0.04
B39: Equity in Affiliates Growth | F39: 0.05 | G39: 0.05 | H39: 0.05 | I39: 0.05 | J39: 0.05
B40: Other Income (Expense) | E40: ='3-Statement Model'!G21 -> -8.9 | F40: 0 | G40: 0 | H40: 0 | I40: 0 | J40: 0
B43: WORKING CAPITAL ASSUMPTIONS
E44: 2024A | F44: 2025E | G44: 2026E | H44: 2027E | I44: 2028E | J44: 2029E
B45: Days Sales Outstanding (DSO) | E45: 62 | F45: 60 | G45: 60 | H45: 60 | I45: 60 | J45: 60
B46: Days Inventory Outstanding (DIO) | E46: 324 | F46: 310 | G46: 300 | H46: 290 | I46: 280 | J46: 270
B47: Days Payable Outstanding (DPO) | E47: 97 | F47: 95 | G47: 95 | H47: 95 | I47: 95 | J47: 95
B48: Other Receivables % of Revenue | E48: ='3-Statement Model'!G37/'3-Statement Model'!G10 -> 0.022832052 | F48: 0.023 | G48: 0.023 | H48: 0.023 | I48: 0.023 | J48: 0.023
B49: Other Current Assets % of Revenue | E49: ='3-Statement Model'!G39/'3-Statement Model'!G10 -> 0.029912005 | F49: 0.03 | G49: 0.03 | H49: 0.03 | I49: 0.03 | J49: 0.03
B50: Other Current Liabilities % of Revenue | E50: ='3-Statement Model'!G55/'3-Statement Model'!G10 -> 0.53741124 | F50: 0.52 | G50: 0.5 | H50: 0.48 | I50: 0.46 | J50: 0.44
B52: CAPEX & D&A ASSUMPTIONS
E53: 2024A | F53: 2025E | G53: 2026E | H53: 2027E | I53: 2028E | J53: 2029E
B54: CapEx % of Revenue | E54: ='3-Statement Model'!G92/'3-Statement Model'!G10*-1 -> 0.073704397 | F54: 0.065 | G54: 0.06 | H54: 0.055 | I54: 0.05 | J54: 0.05
B55: D&A % of Prior Year Net PP&E | E55: ='3-Statement Model'!G16/'3-Statement Model'!F42*-1 -> 0.1701438 | F55: 0.14 | G55: 0.135 | H55: 0.13 | I55: 0.125 | J55: 0.12
B57: Intangibles Amortization (flat) | E57: -126 | F57: -120 | G57: -115 | H57: -110 | I57: -105 | J57: -100
B60: CAPITAL STRUCTURE & SHAREHOLDER RETURNS
E61: 2024A | F61: 2025E | G61: 2026E | H61: 2027E | I61: 2028E | J61: 2029E
B62: Dividend per Share (€) | E62: 6.4 | F62: 7 | G62: 7.5 | H62: 8 | I62: 8.5 | J62: 9
B63: Share Repurchases (€mm) | E63: -500 | F63: -2000 | G63: -2500 | H63: -3000 | I63: -3000 | J63: -3000
B64: Stock Issuances (€mm) | E64: 124 | F64: 130 | G64: 135 | H64: 140 | I64: 145 | J64: 150
B66: Shares Outstanding (mm) - Beginning | E66: 393.4 | F66: =E68 -> 393.6 | G66: =F68 -> 393.68667 | H66: =G68 -> 393.77667 | I66: =H68 -> 393.87 | J66: =I68 -> 393.96667
B67: Shares Outstanding (mm) - Ending | E67: 393.3 | F67: =F66+F64/750 -> 393.77333 | G67: =G66+G64/750 -> 393.86667 | H67: =H66+H64/750 -> 393.96333 | I67: =I66+I64/750 -> 394.06333 | J67: =J66+J64/750 -> 394.16667
B68: Avg Shares Outstanding (mm) | E68: 393.6 | F68: =(F66+F67)/2 -> 393.68667 | G68: =(G66+G67)/2 -> 393.77667 | H68: =(H66+H67)/2 -> 393.87 | I68: =(I66+I67)/2 -> 393.96667 | J68: =(J66+J67)/2 -> 394.06667
B70: DEBT SCHEDULE INPUTS
E71: 2024A | F71: 2025E | G71: 2026E | H71: 2027E | I71: 2028E | J71: 2029E
B72: LT Debt Issuance / (Repayment) | E72: -3.2 | F72: -500 | G72: -300 | H72: 0 | I72: 0 | J72: 0
B73: ST Debt Change | E73: 1032.1 | F73: 0 | G73: 0 | H73: 0 | I73: 0 | J73: 0
B76: OTHER BALANCE SHEET ASSUMPTIONS
E77: 2024A | F77: 2025E | G77: 2026E | H77: 2027E | I77: 2028E | J77: 2029E
B78: LT Investments Growth | F78: 0.05 | G78: 0.05 | H78: 0.05 | I78: 0.05 | J78: 0.05
B79: Deferred Tax Assets Growth | F79: 0.03 | G79: 0.03 | H79: 0.03 | I79: 0.03 | J79: 0.03
B80: Other Non-Current Assets % Revenue | E80: ='3-Statement Model'!G47/'3-Statement Model'!G10 -> 0.027980144 | F80: 0.028 | G80: 0.028 | H80: 0.028 | I80: 0.028 | J80: 0.028
B81: Income Tax Payable % of Tax Expense | E81: ='3-Statement Model'!G54/'3-Statement Model'!G24 -> -0.16857075 | F81: 0.17 | G81: 0.17 | H81: 0.17 | I81: 0.17 | J81: 0.17
B82: Deferred Tax Liabilities Growth | F82: 0 | G82: 0 | H82: 0 | I82: 0 | J82: 0
B83: Other Non-Current Liabilities % Revenue | E83: ='3-Statement Model'!G60/'3-Statement Model'!G10 -> 0.20689667 | F83: 0.2 | G83: 0.19 | H83: 0.18 | I83: 0.17 | J83: 0.16
B85: SBC & Other Non-Cash Items | E85: 767.5 | F85: 800 | G85: 850 | H85: 900 | I85: 950 | J85: 1000
B86: Other Comprehensive Income (flat) | E86: 454.1 | F86: 450 | G86: 450 | H86: 450 | I86: 450 | J86: 450

Sheet 3-Statement Model
B4: INCOME STATEMENT
B6: All figures in millions of euros | E6: 2022A | F6: 2023A | G6: 2024A | H6: 2025E | I6: 2026E | J6: 2027E | K6: 2028E | L6: 2029E
B7: unless stated otherwise
B10: Revenue | E10: 21173.4 | F10: 27558.5 | G10: 28262.9 | H10: =G10*(1+'Assumptions and Inputs'!F21) -> 33915.48 | I10: =H10*(1+'Assumptions and Inputs'!G21) -> 40020.266 | J10: =I10*(1+'Assumptions and Inputs'!H21) -> 46023.306 | K10: =J10*(1+'Assumptions and Inputs'!I21) -> 51546.103 | L10: =K10*(1+'Assumptions and Inputs'!J21) -> 56700.713
B11: COGS (excl. D&A) | E11: -10058.8 | F11: -12936.3 | G11: -13195.2 | H11: =-H10*'Assumptions and Inputs'!F29 -> -15261.966 | I11: =-I10*'Assumptions and Inputs'!G29 -> -17608.917 | J11: =-J10*'Assumptions and Inputs'!H29 -> -19790.022 | K11: =-K10*'Assumptions and Inputs'!I29 -> -21649.363 | L11: =-L10*'Assumptions and Inputs'!J29 -> -23814.3
B12: Gross Profit (excl. D&A) | E12: =E10+E11 -> 11114.6 | F12: =F10+F11 -> 14622.2 | G12: =G10+G11 -> 15067.7 | H12: =H10+H11 -> 18653.514 | I12: =I10+I11 -> 22411.349 | J12: =J10+J11 -> 26233.285 | K12: =K10+K11 -> 29896.74 | L12: =L10+L11 -> 32886.414
B14: R&D Expense | E14: -3071.6 | F14: -3724.9 | G14: -3942.4 | H14: =-H10*'Assumptions and Inputs'!F31 -> -4748.1672 | I14: =-I10*'Assumptions and Inputs'!G31 -> -5402.736 | J14: =-J10*'Assumptions and Inputs'!H31 -> -5983.0298 | K14: =-K10*'Assumptions and Inputs'!I31 -> -6443.2629 | L14: =-L10*'Assumptions and Inputs'!J31 -> -6804.0856
B15: SG&A Expense | E15: -901.6 | F15: -1068.8 | G15: -1115.9 | H15: =-H10*'Assumptions and Inputs'!F32 -> -1356.6192 | I15: =-I10*'Assumptions and Inputs'!G32 -> -1520.7701 | J15: =-J10*'Assumptions and Inputs'!H32 -> -1656.839 | K15: =-K10*'Assumptions and Inputs'!I32 -> -1804.1136 | L15: =-L10*'Assumptions and Inputs'!J32 -> -1984.525
B16: D&A Expense | E16: -640.7 | F16: -786.2 | G16: -986.8 | H16: =-G42*'Assumptions and Inputs'!F55+'Assumptions and Inputs'!F57 -> -1132.76 | I16: =-H42*'Assumptions and Inputs'!G55+'Assumptions and Inputs'!G57 -> -1252.4757 | J16: =-I42*'Assumptions and Inputs'!H55+'Assumptions and Inputs'!H57 -> -1369.6332 | K16: =-J42*'Assumptions and Inputs'!I55+'Assumptions and Inputs'!I57 -> -1475.1419 | L16: =-K42*'Assumptions and Inputs'!J55+'Assumptions and Inputs'!J57 -> -1560.1958
B17: EBIT | E17: =E12+E14+E15+E16 -> 6500.7 | F17: =F12+F14+F15+F16 -> 9042.3 | G17: =G12+G14+G15+G16 -> 9022.6 | H17: =H12+H14+H15+H16 -> 11415.968 | I17: =I12+I14+I15+I16 -> 14235.367 | J17: =J12+J14+J15+J16 -> 17223.783 | K17: =K12+K14+K15+K16 -> 20174.221 | L17: =L12+L14+L15+L16 -> 22537.607
B19: Interest Income | E19: 16.2 | F19: 193.9 | G19: 182.4 | H19: =G35*'Assumptions and Inputs'!F37 -> 318.5325 | I19: =H35*'Assumptions and Inputs'!G37 -> 470.0257 | J19: =I35*'Assumptions and Inputs'!H37 -> 650.17308 | K19: =J35*'Assumptions and Inputs'!I37 -> 874.08025 | L19: =K35*'Assumptions and Inputs'!J37 -> 1154.4996
B20: Interest Expense | E20: -60.8 | F20: -152.1 | G20: -153.7 | H20: =-(G53+G58)*'Assumptions and Inputs'!F38 -> -199.744 | I20: =-(H53+H58)*'Assumptions and Inputs'!G38 -> -199.744 | J20: =-(I53+I58)*'Assumptions and Inputs'!H38 -> -199.744 | K20: =-(J53+J58)*'Assumptions and Inputs'!I38 -> -199.744 | L20: =-(K53+K58)*'Assumptions and Inputs'!J38 -> -199.744
B21: Other Income (Expense) | E21: 0 | F21: -0.6 | G21: -8.9 | H21: ='Assumptions and Inputs'!F40 -> 0 | I21: ='Assumptions and Inputs'!G40 -> 0 | J21: ='Assumptions and Inputs'!H40 -> 0 | K21: ='Assumptions and Inputs'!I40 -> 0 | L21: ='Assumptions and Inputs'!J40 -> 0
B22: EBT | E22: =E17+E19+E20+E21 -> 6456.1 | F22: =F17+F19+F20+F21 -> 9083.5 | G22: =G17+G19+G20+G21 -> 9042.4 | H22: =H17+H19+H20+H21 -> 11534.756 | I22: =I17+I19+I20+I21 -> 14505.649 | J22: =J17+J19+J20+J21 -> 17674.212 | K22: =K17+K19+K20+K21 -> 20848.558 | L22: =L17+L19+L20+L21 -> 23492.363
B24: Income Taxes | E24: -969.9 | F24: -1435.8 | G24: -1680.6 | H24: =-H22*'Assumptions and Inputs'!F36 -> -2018.5823 | I24: =-I22*'Assumptions and Inputs'!G36 -> -2611.0168 | J24: =-J22*'Assumptions and Inputs'!H36 -> -3181.3581 | K24: =-K22*'Assumptions and Inputs'!I36 -> -3752.7404 | L24: =-L22*'Assumptions and Inputs'!J36 -> -4228.6253
B25: Equity in Affiliates | E25: 138 | F25: 191.3 | G25: 209.8 | H25: =G25*(1+'Assumptions and Inputs'!F39) -> 220.29 | I25: =H25*(1+'Assumptions and Inputs'!G39) -> 231.3045 | J25: =I25*(1+'Assumptions and Inputs'!H39) -> 242.86973 | K25: =J25*(1+'Assumptions and Inputs'!I39) -> 255.01321 | L25: =K25*(1+'Assumptions and Inputs'!J39) -> 267.76387
B26: Net Income | E26: =E22+E24+E25 -> 5624.2 | F26: =F22+F24+F25 -> 7839 | G26: =G22+G24+G25 -> 7571.6 | H26: =H22+H24+H25 -> 9736.4638 | I26: =I22+I24+I25 -> 12125.937 | J26: =J22+J24+J25 -> 14735.723 | K26: =K22+K24+K25 -> 17350.831 | L26: =L22+L24+L25 -> 19531.502
B29: BALANCE STATEMENT
B31: All figures in millions of euros | E31: 2022A | F31: 2023A | G31: 2024A | H31: 2025E | I31: 2026E | J31: 2027E | K31: 2028E | L31: 2029E
B32: unless stated otherwise
B34: Assets
B35: Cash & Short-Term Investments | E35: 7376 | F35: 7010.1 | G35: 12741.3 | H35: =G35+H106 -> 18801.028 | I35: =H35+I106 -> 26006.923 | J35: =I35+J106 -> 34963.21 | K35: =J35+K106 -> 46179.985 | L35: =K35+L106 -> 58729.412
B36: Accounts Receivable | E36: 5455.7 | F36: 4574.2 | G36: 4798.1 | H36: =H10*'Assumptions and Inputs'!F45/365 -> 5575.1474 | I36: =I10*'Assumptions and Inputs'!G45/365 -> 6578.6739 | J36: =J10*'Assumptions and Inputs'!H45/365 -> 7565.475 | K36: =K10*'Assumptions and Inputs'!I45/365 -> 8473.332 | L36: =L10*'Assumptions and Inputs'!J45/365 -> 9320.6652
B37: Other Receivables | E37: 1591.3 | F37: 2682.6 | G37: 645.3 | H37: =H10*'Assumptions and Inputs'!F48 -> 780.05604 | I37: =I10*'Assumptions and Inputs'!G48 -> 920.46613 | J37: =J10*'Assumptions and Inputs'!H48 -> 1058.536 | K37: =K10*'Assumptions and Inputs'!I48 -> 1185.5604 | L37: =L10*'Assumptions and Inputs'!J48 -> 1304.1164
B38: Inventories | E38: 7679.6 | F38: 9542.6 | G38: 11707.3 | H38: =-H11*'Assumptions and Inputs'!F46/365 -> 12962.218 | I38: =-I11*'Assumptions and Inputs'!G46/365 -> 14473.083 | J38: =-J11*'Assumptions and Inputs'!H46/365 -> 15723.579 | K38: =-K11*'Assumptions and Inputs'!I46/365 -> 16607.731 | L38: =-L11*'Assumptions and Inputs'!J46/365 -> 17616.057
B39: Other Current Assets | E39: 962.3 | F39: 584.4 | G39: 845.4 | H39: =H10*'Assumptions and Inputs'!F49 -> 1017.4644 | I39: =I10*'Assumptions and Inputs'!G49 -> 1200.608 | J39: =J10*'Assumptions and Inputs'!H49 -> 1380.6992 | K39: =K10*'Assumptions and Inputs'!I49 -> 1546.3831 | L39: =L10*'Assumptions and Inputs'!J49 -> 1701.0214
B40: Total Current Assets | E40: =SUM(E35:E39) -> 23064.9 | F40: =SUM(F35:F39) -> 24393.9 | G40: =SUM(G35:G39) -> 30737.4 | H40: =SUM(H35:H39) -> 39135.914 | I40: =SUM(I35:I39) -> 49179.754 | J40: =SUM(J35:J39) -> 60691.499 | K40: =SUM(K35:K39) -> 73992.991 | L40: =SUM(L35:L39) -> 88671.272
B42: Net PP&E | E42: 4136.9 | F42: 5799.8 | G42: 7234 | H42: =G42-G42*'Assumptions and Inputs'!F55-H92 -> 8425.7462 | I42: =H42-H42*'Assumptions and Inputs'!G55-I92 -> 9689.4864 | J42: =I42-I42*'Assumptions and Inputs'!H55-J92 -> 10961.135 | K42: =J42-J42*'Assumptions and Inputs'!I55-K92 -> 12168.298 | L42: =K42-K42*'Assumptions and Inputs'!J55-L92 -> 13543.138
B43: Goodwill | E43: 4555.6 | F43: 4588.6 | G43: 4588.6 | H43: =G43 -> 4588.6 | I43: =H43 -> 4588.6 | J43: =I43 -> 4588.6 | K43: =J43 -> 4588.6 | L43: =K43 -> 4588.6
B44: Other Intangible Assets | E44: 842.4 | F44: 741.7 | G44: 621.3 | H44: =G44+'Assumptions and Inputs'!F57 -> 501.3 | I44: =H44+'Assumptions and Inputs'!G57 -> 386.3 | J44: =I44+'Assumptions and Inputs'!H57 -> 276.3 | K44: =J44+'Assumptions and Inputs'!I57 -> 171.3 | L44: =K44+'Assumptions and Inputs'!J57 -> 71.3
B45: Long-Term Investments | E45: 1288 | F45: 1920.7 | G45: 2676.8 | H45: =G45*(1+'Assumptions and Inputs'!F78) -> 2810.64 | I45: =H45*(1+'Assumptions and Inputs'!G78) -> 2951.172 | J45: =I45*(1+'Assumptions and Inputs'!H78) -> 3098.7306 | K45: =J45*(1+'Assumptions and Inputs'!I78) -> 3253.6671 | L45: =K45*(1+'Assumptions and Inputs'!J78) -> 3416.3505
B46: Deferred Tax Assets | E46: 1672.8 | F46: 1872.3 | G46: 1940.7 | H46: =G46*(1+'Assumptions and Inputs'!F79) -> 1998.921 | I46: =H46*(1+'Assumptions and Inputs'!G79) -> 2058.8886 | J46: =I46*(1+'Assumptions and Inputs'!H79) -> 2120.6553 | K46: =J46*(1+'Assumptions and Inputs'!I79) -> 2184.2749 | L46: =K46*(1+'Assumptions and Inputs'!J79) -> 2249.8032
B47: Other Non-Current Assets | E47: 739.8 | F47: 640.5 | G47: 790.8 | H47: =H10*'Assumptions and Inputs'!F80 -> 949.63344 | I47: =I10*'Assumptions and Inputs'!G80 -> 1120.5675 | J47: =J10*'Assumptions and Inputs'!H80 -> 1288.6526 | K47: =K10*'Assumptions and Inputs'!I80 -> 1443.2909 | L47: =L10*'Assumptions and Inputs'!J80 -> 1587.62
B48: Total Non-Current Assets | E48: =SUM(E42:E47) -> 13235.5 | F48: =SUM(F42:F47) -> 15563.6 | G48: =SUM(G42:G47) -> 17852.2 | H48: =SUM(H42:H47) -> 19274.841 | I48: =SUM(I42:I47) -> 20795.015 | J48: =SUM(J42:J47) -> 22334.074 | K48: =SUM(K42:K47) -> 23809.431 | L48: =SUM(L42:L47) -> 25456.812
B49: Total Assets | E49: =E40+E48 -> 36300.4 | F49: =F40+F48 -> 39957.5 | G49: =G40+G48 -> 48589.6 | H49: =H40+H48 -> 58410.754 | I49: =I40+I48 -> 69974.768 | J49: =J40+J48 -> 83025.573 | K49: =K40+K48 -> 97802.423 | L49: =L40+L48 -> 114128.08
B51: Liabilities
B52: Accounts Payable | E52: 2565.2 | F52: 2347.3 | G52: 3500.4 | H52: =-H11*'Assumptions and Inputs'!F47/365 -> 3972.2925 | I52: =-I11*'Assumptions and Inputs'!G47/365 -> 4583.1428 | J52: =-J11*'Assumptions and Inputs'!H47/365 -> 5150.8276 | K52: =-K11*'Assumptions and Inputs'!I47/365 -> 5634.7658 | L52: =-L11*'Assumptions and Inputs'!J47/365 -> 6198.2424
B53: Short-Term Debt | E53: 793.8 | F53: 46.8 | G53: 1078.9 | H53: =G53+'Assumptions and Inputs'!F74 -> 1078.9 | I53: =H53+'Assumptions and Inputs'!G74 -> 1078.9 | J53: =I53+'Assumptions and Inputs'!H74 -> 1078.9 | K53: =J53+'Assumptions and Inputs'!I74 -> 1078.9 | L53: =K53+'Assumptions and Inputs'!J74 -> 1078.9
B54: Income Tax Payable | E54: 315.3 | F54: 308.9 | G54: 283.3 | H54: =-H24*'Assumptions and Inputs'!F81 -> 343.15899 | I54: =-I24*'Assumptions and Inputs'!G81 -> 443.87286 | J54: =-J24*'Assumptions and Inputs'!H81 -> 540.83088 | K54: =-K24*'Assumptions and Inputs'!I81 -> 637.96587 | L54: =-L24*'Assumptions and Inputs'!J81 -> 718.86631
B55: Other Current Liabilities | E55: 14309.3 | F55: 13571.7 | G55: 15188.8 | H55: =H10*'Assumptions and Inputs'!F50 -> 17636.05 | I55: =I10*'Assumptions and Inputs'!G50 -> 20010.133 | J55: =J10*'Assumptions and Inputs'!H50 -> 22091.187 | K55: =K10*'Assumptions and Inputs'!I50 -> 23711.207 | L55: =L10*'Assumptions and Inputs'!J50 -> 24948.314
B56: Total Current Liabilities | E56: =SUM(E52:E55) -> 17983.6 | F56: =SUM(F52:F55) -> 16274.7 | G56: =SUM(G52:G55) -> 20051.4 | H56: =SUM(H52:H55) -> 23030.401 | I56: =SUM(I52:I55) -> 26116.049 | J56: =SUM(J52:J55) -> 28861.746 | K56: =SUM(K52:K55) -> 31062.839 | L56: =SUM(L52:L55) -> 32944.323
B58: Long-Term Debt | E58: 3665.7 | F58: 4812.7 | G58: 3914.7 | H58: =G58+'Assumptions and Inputs'!F73 -> 3914.7 | I58: =H58+'Assumptions and Inputs'!G73 -> 3914.7 | J58: =I58+'Assumptions and Inputs'!H73 -> 3914.7 | K58: =J58+'Assumptions and Inputs'!I73 -> 3914.7 | L58: =K58+'Assumptions and Inputs'!J73 -> 3914.7
B59: Deferred Tax Liabilities | E59: 267 | F59: 372.2 | G59: 299.2 | H59: =G59*(1+'Assumptions and Inputs'!F82) -> 299.2 | I59: =H59*(1+'Assumptions and Inputs'!G82) -> 299.2 | J59: =I59*(1+'Assumptions and Inputs'!H82) -> 299.2 | K59: =J59*(1+'Assumptions and Inputs'!I82) -> 299.2 | L59: =K59*(1+'Assumptions and Inputs'!J82) -> 299.2
B60: Other Non-Current Liabilities | E60: 5573.3 | F60: 5045.5 | G60: 5847.5 | H60: =H10*'Assumptions and Inputs'!F83 -> 6783.096 | I60: =I10*'Assumptions and Inputs'!G83 -> 7603.8506 | J60: =J10*'Assumptions and Inputs'!H83 -> 8284.1951 | K60: =K10*'Assumptions and Inputs'!I83 -> 8762.8375 | L60: =L10*'Assumptions and Inputs'!J83 -> 9072.1141
B61: Total Non-Current Liabilities | E61: =SUM(E58:E60) -> 9506 | F61: =SUM(F58:F60) -> 10230.4 | G61: =SUM(G58:G60) -> 10061.4 | H61: =SUM(H58:H60) -> 10996.996 | I61: =SUM(I58:I60) -> 11817.751 | J61: =SUM(J58:J60) -> 12498.095 | K61: =SUM(K58:K60) -> 12976.738 | L61: =SUM(L58:L60) -> 13286.014
B62: Total Liabilities | E62: =E56+E61 -> 27489.6 | F62: =F56+F61 -> 26505.1 | G62: =G56+G61 -> 30112.8 | H62: =H56+H61 -> 34027.397 | I62: =I56+I61 -> 37933.8 | J62: =J56+J61 -> 41359.841 | K62: =K56+K61 -> 44039.577 | L62: =L56+L61 -> 46230.337
B64: Shareholders' Equity | H64: =G65+'Assumptions and Inputs'!F64+'Assumptions and Inputs'!F85 -> 5014.4 | I64: =H65+'Assumptions and Inputs'!G64+'Assumptions and Inputs'!G85 -> 5999.4 | J64: =I65+'Assumptions and Inputs'!H64+'Assumptions and Inputs'!H85 -> 7039.4 | K64: =J65+'Assumptions and Inputs'!I64+'Assumptions and Inputs'!I85 -> 8134.4 | L64: =K65+'Assumptions and Inputs'!J64+'Assumptions and Inputs'!J85 -> 9284.4
B65: Common Stock & APIC | E65: 3977.1 | F65: 4034.1 | G65: 4084.4 | H65: =G65+'Assumptions and Inputs'!F64+'Assumptions and Inputs'!F85 -> 5014.4 | I65: =H65+'Assumptions and Inputs'!G64+'Assumptions and Inputs'!G85 -> 5999.4 | J65: =I65+'Assumptions and Inputs'!H64+'Assumptions and Inputs'!H85 -> 7039.4 | K65: =J65+'Assumptions and Inputs'!I64+'Assumptions and Inputs'!I85 -> 8134.4 | L65: =K65+'Assumptions and Inputs'!J64+'Assumptions and Inputs'!J85 -> 9284.4
B66: Retained Earnings | E66: 9046.7 | F66: 12379.5 | G66: 14414.3 | H66: =G66+H26-(-H99) -> 21394.957 | I66: =H66+I26-(-I99) -> 30567.569 | J66: =I66+J26-(-J99) -> 42152.332 | K66: =J66+K26-(-K99) -> 56154.446 | L66: =K66+L26-(-L99) -> 72139.347
B67: Treasury Stock | E67: -4641.3 | F67: -3306.2 | G67: -476 | H67: =G67+'Assumptions and Inputs'!F63 -> -2476 | I67: =H67+'Assumptions and Inputs'!G63 -> -4976 | J67: =I67+'Assumptions and Inputs'!H63 -> -7976 | K67: =J67+'Assumptions and Inputs'!I63 -> -10976 | L67: =K67+'Assumptions and Inputs'!J63 -> -13976
B68: Other Comprehensive Income | E68: 428.3 | F68: 345 | G68: 454.1 | H68: ='Assumptions and Inputs'!F86 -> 450 | I68: ='Assumptions and Inputs'!G86 -> 450 | J68: ='Assumptions and Inputs'!H86 -> 450 | K68: ='Assumptions and Inputs'!I86 -> 450 | L68: ='Assumptions and Inputs'!J86 -> 450
B69: Total Shareholders' Equity | E69: =SUM(E65:E68) -> 8810.8 | F69: =SUM(F65:F68) -> 13452.4 | G69: =SUM(G65:G68) -> 18476.8 | H69: =SUM(H65:H68) -> 24383.357 | I69: =SUM(I65:I68) -> 32040.969 | J69: =SUM(J65:J68) -> 41665.732 | K69: =SUM(K65:K68) -> 53762.846 | L69: =SUM(L65:L68) -> 67897.747
H70: =H62+H69 -> 58410.754 | I70: =I62+I69 -> 69974.768 | J70: =J62+J69 -> 83025.573 | K70: =K62+K69 -> 97802.423 | L70: =L62+L69 -> 114128.08
B71: Total Liabilities & Equity | E71: =E62+E69 -> 36300.4 | F71: =F62+F69 -> 39957.5 | G71: =G62+G69 -> 48589.6 | H71: =H62+H69 -> 58410.754 | I71: =I62+I69 -> 69974.768 | J71: =J62+J69 -> 83025.573 | K71: =K62+K69 -> 97802.423 | L71: =L62+L69 -> 114128.08
B72: Balance Check | E72: =E49-E71 -> 0 | F72: =F49-F71 -> 0 | G72: =G49-G71 -> 0 | H72: =H49-H71 -> 0 | I72: =I49-I71 -> 0 | J72: =J49-J71 -> 0 | K72: =K49-K71 -> 0 | L72: =L49-L71 -> 0
B74: CASH FLOW STATEMENT
B76: All figures in millions of euros | E76: 2022A | F76: 2023A | G76: 2024A | H76: 2025E | I76: 2026E | J76: 2027E | K76: 2028E | L76: 2029E
B77: unless stated otherwise
B79: Operating Activities
B80: Net Income | E80: 5624.2 | F80: 7839 | G80: 7571.6 | H80: =H26 -> 9736.4638 | I80: =I26 -> 12125.937 | J80: =J26 -> 14735.723 | K80: =K26 -> 17350.831 | L80: =L26 -> 19531.502
B81: D&A | E81: 583.6 | F81: 739.8 | G81: 918.6 | H81: =-H16 -> 1132.76 | I81: =-I16 -> 1252.4757 | J81: =-J16 -> 1369.6332 | K81: =-K16 -> 1475.1419 | L81: =-L16 -> 1560.1958
B82: Deferred Taxes | E82: -564.2 | F82: -133.6 | G82: -144.8 | H82: =-(H46-G46) -> -58.221 | I82: =-(I46-H46) -> -59.96763 | J82: =-(J46-I46) -> -61.766659 | K82: =-(K46-J46) -> -63.619659 | L82: =-(L46-K46) -> -65.528248
B83: Stock-Based Compensation & Other | E83: 402 | F83: 661.8 | G83: 767.5 | H83: ='Assumptions and Inputs'!F85 -> 800 | I83: ='Assumptions and Inputs'!G85 -> 850 | J83: ='Assumptions and Inputs'!H85 -> 900 | K83: ='Assumptions and Inputs'!I85 -> 950 | L83: ='Assumptions and Inputs'!J85 -> 1000
B84: Changes in Working Capital:
B85: (Increase) / Decrease in Receivables | E85: -2125.8 | F85: 871.3 | G85: 898.8 | H85: =G36-H36 -> -777.0474 | I85: =H36-I36 -> -1003.5265 | J85: =I36-J36 -> -986.80109 | K85: =J36-K36 -> -907.857 | L85: =K36-L36 -> -847.3332
B86: (Increase) / Decrease in Inventories | E86: -2080.9 | F86: -1646.9 | G86: -1860.9 | H86: =G38-H38 -> -1254.9177 | I86: =H38-I38 -> -1510.8649 | J86: =I38-J38 -> -1250.4963 | K86: =J38-K38 -> -884.15185 | L86: =K38-L38 -> -1008.3265
B87: Increase / (Decrease) in Accounts Payable | E87: 406.2 | F87: -261.7 | G87: 1127.6 | H87: =H52-G52 -> 471.89252 | I87: =I52-H52 -> 610.85032 | J87: =J52-I52 -> 567.68474 | K87: =K52-J52 -> 483.93822 | L87: =L52-K52 -> 563.47658
B88: Other Working Capital Changes | E88: 6241.7 | F88: -2626.3 | G88: 1887.8 | H88: =(G37-H37)+(G39-H39)+(H54-G54)+(H55-G55)+(H60-G60) -> 3135.8842 | I88: =(H37-I37)+(H39-I39)+(I54-H54)+(I55-H55)+(I60-H60) -> 2971.9984 | J88: =(I37-J37)+(I39-J39)+(J54-I54)+(J55-I55)+(J60-I60) -> 2540.1953 | K88: =(J37-K37)+(J39-K39)+(K54-J54)+(K55-J55)+(K60-J60) -> 1903.0895 | L88: =(K37-L37)+(K39-L39)+(L54-K54)+(L55-K55)+(L60-K60) -> 1354.0892
B89: Cash Flow from Operations | E89: =SUM(E80:E88) -> 8486.8 | F89: =SUM(F80:F88) -> 5443.4 | G89: =SUM(G80:G88) -> 11166.2 | H89: =SUM(H80:H88) -> 13186.814 | I89: =SUM(I80:I88) -> 15236.902 | J89: =SUM(J80:J88) -> 17814.172 | K89: =SUM(K80:K88) -> 20307.372 | L89: =SUM(L80:L88) -> 22088.075
B91: Investing Activities
B92: Capital Expenditures | E92: -1319.3 | F92: -2196.2 | G92: -2083.1 | H92: =-H10*'Assumptions and Inputs'!F54 -> -2204.5062 | I92: =-I10*'Assumptions and Inputs'!G54 -> -2401.216 | J92: =-J10*'Assumptions and Inputs'!H54 -> -2531.2818 | K92: =-K10*'Assumptions and Inputs'!I54 -> -2577.3052 | L92: =-L10*'Assumptions and Inputs'!J54 -> -2835.0357
B93: Acquisitions | E93: 0 | F93: -33.6 | G93: 0 | H93: 0 | I93: 0 | J93: 0 | K93: 0 | L93: 0
B94: Purchase / Sale of Investments | E94: 530.4 | F94: 102 | G94: 0 | H94: =-(H45-G45) -> -133.84 | I94: =-(I45-H45) -> -140.532 | J94: =-(J45-I45) -> -147.5586 | K94: =-(K45-J45) -> -154.93653 | L94: =-(L45-K45) -> -162.68336
B95: Other Investing Activities | E95: -240 | F95: -561.5 | G95: -526.2 | H95: =-(H47-G47) -> -158.83344 | I95: =-(I47-H47) -> -170.93402 | J95: =-(J47-I47) -> -168.08512 | K95: =-(K47-J47) -> -154.63831 | L95: =-(L47-K47) -> -144.32909
B96: Cash Flow from Investing | E96: =SUM(E92:E95) -> -1028.9 | F96: =SUM(F92:F95) -> -2689.3 | G96: =SUM(G92:G95) -> -2609.3 | H96: =SUM(H92:H95) -> -2497.1796 | I96: =SUM(I92:I95) -> -2712.682 | J96: =SUM(J92:J95) -> -2846.9256 | K96: =SUM(K92:K95) -> -2886.88 | L96: =SUM(L92:L95) -> -3142.0481
B98: Financing Activities
B99: Dividends Paid | E99: -2559.8 | F99: -2348.3 | G99: -2452.9 | H99: =-'Assumptions and Inputs'!F62*'Assumptions and Inputs'!F68 -> -2755.8067 | I99: =-'Assumptions and Inputs'!G62*'Assumptions and Inputs'!G68 -> -2953.325 | J99: =-'Assumptions and Inputs'!H62*'Assumptions and Inputs'!H68 -> -3150.96 | K99: =-'Assumptions and Inputs'!I62*'Assumptions and Inputs'!I68 -> -3348.7167 | L99: =-'Assumptions and Inputs'!J62*'Assumptions and Inputs'!J68 -> -3546.6
B100: Share Repurchases | E100: -4639.7 | F100: -1000 | G100: -500 | H100: ='Assumptions and Inputs'!F63 -> -2000 | I100: ='Assumptions and Inputs'!G63 -> -2500 | J100: ='Assumptions and Inputs'!H63 -> -3000 | K100: ='Assumptions and Inputs'!I63 -> -3000 | L100: ='Assumptions and Inputs'!J63 -> -3000
B101: Stock Issuances | E101: 81.8 | F101: 99.4 | G101: 124 | H101: ='Assumptions and Inputs'!F64 -> 130 | I101: ='Assumptions and Inputs'!G64 -> 135 | J101: ='Assumptions and Inputs'!H64 -> 140 | K101: ='Assumptions and Inputs'!I64 -> 145 | L101: ='Assumptions and Inputs'!J64 -> 150
B102: Debt Issuance / (Repayment) | E102: -20.6 | F102: 245 | G102: -3.2 | H102: ='Assumptions and Inputs'!F73+'Assumptions and Inputs'!F74 -> 0 | I102: ='Assumptions and Inputs'!G73+'Assumptions and Inputs'!G74 -> 0 | J102: ='Assumptions and Inputs'!H73+'Assumptions and Inputs'!H74 -> 0 | K102: ='Assumptions and Inputs'!I73+'Assumptions and Inputs'!I74 -> 0 | L102: ='Assumptions and Inputs'!J73+'Assumptions and Inputs'!J74 -> 0
B103: Cash Flow from Financing | E103: =SUM(E99:E102) -> -7138.3 | F103: =SUM(F99:F102) -> -3003.9 | G103: =SUM(G99:G102) -> -2832.1 | H103: =SUM(H99:H102) -> -4625.8067 | I103: =SUM(I99:I102) -> -5318.325 | J103: =SUM(J99:J102) -> -6010.96 | K103: =SUM(K99:K102) -> -6203.7167 | L103: =SUM(L99:L102) -> -6396.6
B105: Effect of Exchange Rate | E105: -3.1 | F105: -13.8 | G105: 6.4 | H105: ='Assumptions and Inputs'!F86-G68 -> -4.1 | I105: ='Assumptions and Inputs'!G86-'Assumptions and Inputs'!F86 -> 0 | J105: ='Assumptions and Inputs'!H86-'Assumptions and Inputs'!G86 -> 0 | K105: ='Assumptions and Inputs'!I86-'Assumptions and Inputs'!H86 -> 0 | L105: ='Assumptions and Inputs'!J86-'Assumptions and Inputs'!I86 -> 0
B106: Net Change in Cash | E106: =E89+E96+E103+E105 -> 316.5 | F106: =F89+F96+F103+F105 -> -263.6 | G106: =G89+G96+G103+G105 -> 5731.2 | H106: =H89+H96+H103+H105 -> 6059.7281 | I106: =I89+I96+I103+I105 -> 7205.8951 | J106: =J89+J96+J103+J105 -> 8956.2869 | K106: =K89+K96+K103+K105 -> 11216.775 | L106: =L89+L96+L103+L105 -> 12549.427

Sheet DCF
B2: ASML HOLDING NV - DISCOUNTED CASH FLOW ANALYSIS
B7: SECTION 1: WACC CALCULATION
B9: Cost of Equity (CAPM)
B10: Risk-Free Rate (Rf) | E10: 0.0291
B11: Equity Risk Premium (ERP) | E11: 0.0423
B12: Beta (Levered) | E12: 1.69
B13: Cost of Equity (Ke) | E13: =E10+E12*E11 -> 0.100587
B15: Cost of Debt
B16: Pre-Tax Cost of Debt (Kd) | E16: 0.0239
B17: Tax Rate | E17: 0.175
B18: After-Tax Cost of Debt | E18: =E16*(1-E17) -> 0.0197175
B20: Capital Structure
B21: Weight of Equity | E21: 0.9942
B22: Weight of Debt | E22: =1-E21 -> 0.0058
B24: WACC Calculation
B25: Weighted Average Cost of Capital | E25: =E13*E21+E18*E22 -> 0.10011796
B27: Terminal Value Assumptions
B28: Perpetual Growth Rate (g) | E28: 0.025
B29: Exit Multiple (EV/EBITDA) | E29: 15
B32: SECTION 2: FREE CASH FLOW SCHEDULE
E34: Projection Period
E35: 2024A | F35: 2025E | G35: 2026E | H35: 2027E | I35: 2028E | J35: 2029E
B37: Revenue | E37: ='3-Statement Model'!G10 -> 28262.9 | F37: ='3-Statement Model'!H10 -> 33915.48 | G37: ='3-Statement Model'!I10 -> 40020.266 | H37: ='3-Statement Model'!J10 -> 46023.306 | I37: ='3-Statement Model'!K10 -> 51546.103 | J37: ='3-Statement Model'!L10 -> 56700.713
B38: % Growth | F38: =F37/E37-1 -> 0.2 | G38: =G37/F37-1 -> 0.18 | H38: =H37/G37-1 -> 0.15 | I38: =I37/H37-1 -> 0.12 | J38: =J37/I37-1 -> 0.1
B40: EBIT | E40: ='3-Statement Model'!G17 -> 9022.6 | F40: ='3-Statement Model'!H17 -> 11415.968 | G40: ='3-Statement Model'!I17 -> 14235.367 | H40: ='3-Statement Model'!J17 -> 17223.783 | I40: ='3-Statement Model'!K17 -> 20174.221 | J40: ='3-Statement Model'!L17 -> 22537.607
B41: % Margin | E41: =E40/E37 -> 0.31923829 | F41: =F40/F37 -> 0.3366005 | G41: =G40/G37 -> 0.35570396 | H41: =H40/H37 -> 0.37424044 | I41: =I40/I37 -> 0.39138209 | J41: =J40/J37 -> 0.39748367
B42: Less: Taxes on EBIT | E42: =-E40*$E$17 -> -1578.955 | F42: =-F40*$E$17 -> -1997.7943 | G42: =-G40*$E$17 -> -2491.1893 | H42: =-H40*$E$17 -> -3014.1619 | I42: =-I40*$E$17 -> -3530.4888 | J42: =-J40*$E$17 -> -3944.0813
B43: NOPAT (EBIT × (1-t)) | E43: =E40+E42 -> 7443.645 | F43: =F40+F42 -> 9418.1733 | G43: =G40+G42 -> 11744.178 | H43: =H40+H42 -> 14209.621 | I43: =I40+I42 -> 16643.733 | J43: =J40+J42 -> 18593.526
B45: Plus: D&A | E45: =-'3-Statement Model'!G16 -> 986.8 | F45: =-'3-Statement Model'!H16 -> 1132.76 | G45: =-'3-Statement Model'!I16 -> 1252.4757 | H45: =-'3-Statement Model'!J16 -> 1369.6332 | I45: =-'3-Statement Model'!K16 -> 1475.1419 | J45: =-'3-Statement Model'!L16 -> 1560.1958
B46: Less: CapEx | E46: ='3-Statement Model'!G92 -> -2083.1 | F46: ='3-Statement Model'!H92 -> -2204.5062 | G46: ='3-Statement Model'!I92 -> -2401.216 | H46: ='3-Statement Model'!J92 -> -2531.2818 | I46: ='3-Statement Model'!K92 -> -2577.3052 | J46: ='3-Statement Model'!L92 -> -2835.0357
B47: Less: Change in NWC | E47: ='3-Statement Model'!G85+'3-Statement Model'!G86+'3-Statement Model'!G87+'3-Statement Model'!G88 -> 2053.3 | F47: ='3-Statement Model'!H85+'3-Statement Model'!H86+'3-Statement Model'!H87+'3-Statement Model'!H88 -> 1575.8116 | G47: ='3-Statement Model'!I85+'3-Statement Model'!I86+'3-Statement Model'!I87+'3-Statement Model'!I88 -> 1068.4572 | H47: ='3-Statement Model'!J85+'3-Statement Model'!J86+'3-Statement Model'!J87+'3-Statement Model'!J88 -> 870.58266 | I47: ='3-Statement Model'!K85+'3-Statement Model'!K86+'3-Statement Model'!K87+'3-Statement Model'!K88 -> 595.0189 | J47: ='3-Statement Model'!L85+'3-Statement Model'!L86+'3-Statement Model'!L87+'3-Statement Model'!L88 -> 61.906058
B49: Unlevered Free Cash Flow | E49: =E43+E45+E46+E47 -> 8400.645 | F49: =F43+F45+F46+F47 -> 9922.2386 | G49: =G43+G45+G46+G47 -> 11663.895 | H49: =H43+H45+H46+H47 -> 13918.555 | I49: =I43+I45+I46+I47 -> 16136.588 | J49: =J43+J45+J46+J47 -> 17380.592
B50: % Conversion (UFCF/NOPAT) | E50: =E49/E43 -> 1.128566 | F50: =F49/F43 -> 1.0535205 | G50: =G49/G43 -> 0.99316402 | H50: =H49/H43 -> 0.97951628 | I50: =I49/I43 -> 0.96952941 | J50: =J49/J43 -> 0.9347658
B53: SECTION 3: DISCOUNTING & PRESENT VALUE
B55: Discount Period (Mid-Year Convention) | F55: =0.5 -> 0.5 | G55: =F55+1 -> 1.5 | H55: =G55+1 -> 2.5 | I55: =H55+1 -> 3.5 | J55: =I55+1 -> 4.5
B56: Discount Factor | F56: =1/(1+$E$25)^F55 -> 0.95341147 | G56: =1/(1+$E$25)^G55 -> 0.86664477 | H56: =1/(1+$E$25)^H55 -> 0.7877744 | I56: =1/(1+$E$25)^I55 -> 0.71608176 | J56: =1/(1+$E$25)^J55 -> 0.65091362
B58: Present Value of FCF | F58: =F49*F56 -> 9459.9762 | G58: =G49*G56 -> 10108.454 | H58: =H49*H56 -> 10964.681 | I58: =I49*I56 -> 11555.117 | J58: =J49*J56 -> 11313.264
B60: Sum of PV of FCF | F60: =SUM(F58:J58) -> 53401.492
B63: SECTION 4: TERMINAL VALUE CALCULATION
B65: Method 1: Perpetuity Growth Method
B66: Terminal Year FCF (2029E) | E66: =J49 -> 17380.592
B67: Perpetual Growth Rate | E67: =E28 -> 0.025
B68: Terminal Value (Perpetuity) | E68: =E66*(1+E67)/($E$25-E67) -> 237161.76
B69: PV of Terminal Value | E69: =E68/(1+$E$25)^J55 -> 154371.82
B70: Implied Exit Multiple (EV/EBITDA) | E70: =E68/('3-Statement Model'!L17+'3-Statement Model'!L16) -> 11.305578
B72: Method 2: Exit Multiple Method
B73: Terminal Year EBITDA (2029E) | E73: ='3-Statement Model'!L17+'3-Statement Model'!L16 -> 20977.412
B74: Exit EV/EBITDA Multiple | E74: =E29 -> 15
B75: Terminal Value (Exit Multiple) | E75: =E73*E74 -> 314661.17
B76: PV of Terminal Value | E76: =E75/(1+$E$25)^J55 -> 204817.24
B77: Implied Perpetuity Growth Rate | E77: =(E66-E75*$E$25)/(E75+E66) -> -0.042532726
B80: SECTION 5: ENTERPRISE VALUE TO EQUITY VALUE
B82: Perpetuity Growth Method | E82: Exit Multiple Method | F82: Exit Multiple Method
B83: Sum of PV of FCF | E83: =F60 -> 53401.492 | F83: =F60 -> 53401.492
B84: PV of Terminal Value | E84: =E69 -> 154371.82 | F84: =E76 -> 204817.24
B85: Enterprise Value | E85: =E83+E84 -> 207773.31 | F85: =F83+F84 -> 258218.74
B87: Less: Total Debt | E87: =-('3-Statement Model'!G53+'3-Statement Model'!G58) -> -4993.6 | F87: =E87 -> -4993.6
B88: Plus: Cash & Equivalents | E88: ='3-Statement Model'!G35 -> 12741.3 | F88: =E88 -> 12741.3
B89: Less: Minority Interest | E89: 0 | F89: =E89 -> 0
B90: Less: Preferred Stock | E90: 0 | F90: =E90 -> 0
B91: Plus: Equity Investments | E91: ='3-Statement Model'!G45 -> 2676.8 | F91: =E91 -> 2676.8
B92: Equity Value | E92: =SUM(E85:E91) -> 218197.81 | F92: =SUM(F85:F91) -> 268643.24
B94: Shares Outstanding (mm) | E94: ='Assumptions and Inputs'!E67 -> 393.3 | F94: =E94 -> 393.3
B95: Implied Share Price (€) | E95: =E92/E94 -> 554.78722 | F95: =F92/F94 -> 683.04916
B97: Current Share Price (€) | E97: 652
B98: Implied Upside / (Downside) | E98: =E95/E97-1 -> -0.14909936 | F98: =F95/E97-1 -> 0.047621415
B101: SECTION 6: SENSITIVITY ANALYSIS
B103: Implied Share Price - Perpetuity Growth Method
B104: WACC \ Growth Rate | C104: 0.015 | D104: 0.02 | E104: 0.025 | F104: 0.03 | G104: 0.035
B105: =$E$25-0.02 -> 0.080117957 | C105: =($F$60+($E$66*(1+C$104)/($B105-C$104))/(1+$B105)^$J$55+$E$87+$E$88+$E$89+$E$90+$E$91)/$E$94 -> 649.23456 | D105: =($F$60+($E$66*(1+D$104)/($B105-D$104))/(1+$B105)^$J$55+$E$87+$E$88+$E$89+$E$90+$E$91)/$E$94 -> 692.3325 | E105: =($F$60+($E$66*(1+E$104)/($B105-E$104))/(1+$B105)^$J$55+$E$87+$E$88+$E$89+$E$90+$E$91)/$E$94 -> 743.24966 | F105: =($F$60+($E$66*(1+F$104)/($B105-F$104))/(1+$B105)^$J$55+$E$87+$E$88+$E$89+$E$90+$E$91)/$E$94 -> 804.32628 | G105: =($F$60+($E$66*(1+G$104)/($B105-G$104))/(1+$B105)^$J$55+$E$87+$E$88+$E$89+$E$90+$E$91)/$E$94 -> 878.94
B106: =$E$25-0.01 -> 0.090117957 | C106: =($F$60+($E$66*(1+C$104)/($B106-C$104))/(1+$B106)^$J$55+$E$87+$E$88+$E$89+$E$90+$E$91)/$E$94 -> 567.26192 | D106: =($F$60+($E$66*(1+D$104)/($B106-D$104))/(1+$B106)^$J$55+$E$87+$E$88+$E$89+$E$90+$E$91)/$E$94 -> 598.27754 | E106: =($F$60+($E$66*(1+E$104)/($B106-E$104))/(1+$B106)^$J$55+$E$87+$E$88+$E$89+$E$90+$E$91)/$E$94 -> 634.05614 | F106: =($F$60+($E$66*(1+F$104)/($B106-F$104))/(1+$B106)^$J$55+$E$87+$E$88+$E$89+$E$90+$E$91)/$E$94 -> 675.78614 | G106: =($F$60+($E$66*(1+G$104)/($B106-G$104))/(1+$B106)^$J$55+$E$87+$E$88+$E$89+$E$90+$E$91)/$E$94 -> 725.08718
B107: =$E$25 -> 0.10011796 | C107: =($F$60+($E$66*(1+C$104)/($B107-C$104))/(1+$B107)^$J$55+$E$87+$E$88+$E$89+$E$90+$E$91)/$E$94 -> 505.29485 | D107: =($F$60+($E$66*(1+D$104)/($B107-D$104))/(1+$B107)^$J$55+$E$87+$E$88+$E$89+$E$90+$E$91)/$E$94 -> 528.49667 | E107: =($F$60+($E$66*(1+E$104)/($B107-E$104))/(1+$B107)^$J$55+$E$87+$E$88+$E$89+$E$90+$E$91)/$E$94 -> 554.78722 | F107: =($F$60+($E$66*(1+F$104)/($B107-F$104))/(1+$B107)^$J$55+$E$87+$E$88+$E$89+$E$90+$E$91)/$E$94 -> 584.82724 | G107: =($F$60+($E$66*(1+G$104)/($B107-G$104))/(1+$B107)^$J$55+$E$87+$E$88+$E$89+$E$90+$E$91)/$E$94 -> 619.48043
B108: =$E$25+0.01 -> 0.11011796 | C108: =($F$60+($E$66*(1+C$104)/($B108-C$104))/(1+$B108)^$J$55+$E$87+$E$88+$E$89+$E$90+$E$91)/$E$94 -> 456.98522 | D108: =($F$60+($E$66*(1+D$104)/($B108-D$104))/(1+$B108)^$J$55+$E$87+$E$88+$E$89+$E$90+$E$91)/$E$94 -> 474.8684 | E108: =($F$60+($E$66*(1+E$104)/($B108-E$104))/(1+$B108)^$J$55+$E$87+$E$88+$E$89+$E$90+$E$91)/$E$94 -> 494.85258 | F108: =($F$60+($E$66*(1+F$104)/($B108-F$104))/(1+$B108)^$J$55+$E$87+$E$88+$E$89+$E$90+$E$91)/$E$94 -> 517.33109 | G108: =($F$60+($E$66*(1+G$104)/($B108-G$104))/(1+$B108)^$J$55+$E$87+$E$88+$E$89+$E$90+$E$91)/$E$94 -> 542.80204
B109: =$E$25+0.02 -> 0.12011796 | C109: =($F$60+($E$66*(1+C$104)/($B109-C$104))/(1+$B109)^$J$55+$E$87+$E$88+$E$89+$E$90+$E$91)/$E$94 -> 418.40284 | D109: =($F$60+($E$66*(1+D$104)/($B109-D$104))/(1+$B109)^$J$55+$E$87+$E$88+$E$89+$E$90+$E$91)/$E$94 -> 432.51841 | E109: =($F$60+($E$66*(1+E$104)/($B109-E$104))/(1+$B109)^$J$55+$E$87+$E$88+$E$89+$E$90+$E$91)/$E$94 -> 448.118 | F109: =($F$60+($E$66*(1+F$104)/($B109-F$104))/(1+$B109)^$J$55+$E$87+$E$88+$E$89+$E$90+$E$91)/$E$94 -> 465.4486 | G109: =($F$60+($E$66*(1+G$104)/($B109-G$104))/(1+$B109)^$J$55+$E$87+$E$88+$E$89+$E$90+$E$91)/$E$94 -> 484.81527
B111: Implied Share Price - Exit Multiple Method
B112: WACC \ EV/EBITDA | C112: 12 | D112: 13.5 | E112: 15 | F112: 16.5 | G112: 18
B113: =$E$25-0.02 -> 0.080117957 | C113: =($F$60+($E$73*C$112)/(1+$B113)^$J$55+$E$87+$E$88+$E$89+$E$90+$E$91)/$E$94 -> 614.75226 | D113: =($F$60+($E$73*D$112)/(1+$B113)^$J$55+$E$87+$E$88+$E$89+$E$90+$E$91)/$E$94 -> 671.31089 | E113: =($F$60+($E$73*E$112)/(1+$B113)^$J$55+$E$87+$E$88+$E$89+$E$90+$E$91)/$E$94 -> 727.86951 | F113: =($F$60+($E$73*F$112)/(1+$B113)^$J$55+$E$87+$E$88+$E$89+$E$90+$E$91)/$E$94 -> 784.42814 | G113: =($F$60+($E$73*G$112)/(1+$B113)^$J$55+$E$87+$E$88+$E$89+$E$90+$E$91)/$E$94 -> 840.98677
B114: =$E$25-0.01 -> 0.090117957 | C114: =($F$60+($E$73*C$112)/(1+$B114)^$J$55+$E$87+$E$88+$E$89+$E$90+$E$91)/$E$94 -> 596.37192 | D114: =($F$60+($E$73*D$112)/(1+$B114)^$J$55+$E$87+$E$88+$E$89+$E$90+$E$91)/$E$94 -> 650.63301 | E114: =($F$60+($E$73*E$112)/(1+$B114)^$J$55+$E$87+$E$88+$E$89+$E$90+$E$91)/$E$94 -> 704.8941 | F114: =($F$60+($E$73*F$112)/(1+$B114)^$J$55+$E$87+$E$88+$E$89+$E$90+$E$91)/$E$94 -> 759.15518 | G114: =($F$60+($E$73*G$112)/(1+$B114)^$J$55+$E$87+$E$88+$E$89+$E$90+$E$91)/$E$94 -> 813.41627
B115: =$E$25 -> 0.10011796 | C115: =($F$60+($E$73*C$112)/(1+$B115)^$J$55+$E$87+$E$88+$E$89+$E$90+$E$91)/$E$94 -> 578.89597 | D115: =($F$60+($E$73*D$112)/(1+$B115)^$J$55+$E$87+$E$88+$E$89+$E$90+$E$91)/$E$94 -> 630.97257 | E115: =($F$60+($E$73*E$112)/(1+$B115)^$J$55+$E$87+$E$88+$E$89+$E$90+$E$91)/$E$94 -> 683.04916 | F115: =($F$60+($E$73*F$112)/(1+$B115)^$J$55+$E$87+$E$88+$E$89+$E$90+$E$91)/$E$94 -> 735.12576 | G115: =($F$60+($E$73*G$112)/(1+$B115)^$J$55+$E$87+$E$88+$E$89+$E$90+$E$91)/$E$94 -> 787.20235
B116: =$E$25+0.01 -> 0.11011796 | C116: =($F$60+($E$73*C$112)/(1+$B116)^$J$55+$E$87+$E$88+$E$89+$E$90+$E$91)/$E$94 -> 562.27229 | D116: =($F$60+($E$73*D$112)/(1+$B116)^$J$55+$E$87+$E$88+$E$89+$E$90+$E$91)/$E$94 -> 612.27093 | E116: =($F$60+($E$73*E$112)/(1+$B116)^$J$55+$E$87+$E$88+$E$89+$E$90+$E$91)/$E$94 -> 662.26956 | F116: =($F$60+($E$73*F$112)/(1+$B116)^$J$55+$E$87+$E$88+$E$89+$E$90+$E$91)/$E$94 -> 712.2682 | G116: =($F$60+($E$73*G$112)/(1+$B116)^$J$55+$E$87+$E$88+$E$89+$E$90+$E$91)/$E$94 -> 762.26683
B117: =$E$25+0.02 -> 0.12011796 | C117: =($F$60+($E$73*C$112)/(1+$B117)^$J$55+$E$87+$E$88+$E$89+$E$90+$E$91)/$E$94 -> 546.45219 | D117: =($F$60+($E$73*D$112)/(1+$B117)^$J$55+$E$87+$E$88+$E$89+$E$90+$E$91)/$E$94 -> 594.47331 | E117: =($F$60+($E$73*E$112)/(1+$B117)^$J$55+$E$87+$E$88+$E$89+$E$90+$E$91)/$E$94 -> 642.49443 | F117: =($F$60+($E$73*F$112)/(1+$B117)^$J$55+$E$87+$E$88+$E$89+$E$90+$E$91)/$E$94 -> 690.51555 | G117: =($F$60+($E$73*G$112)/(1+$B117)^$J$55+$E$87+$E$88+$E$89+$E$90+$E$91)/$E$94 -> 738.53668
B119: Valuation Summary Range
B120: Metric | C120: Low | D120: Base Case | E120: High | F120: Current Price
B121: Perpetuity Growth Method | C121: =MIN(C105:G109) -> 418.40284 | D121: =E95 -> 554.78722 | E121: =MAX(C105:G109) -> 878.94 | F121: =E97 -> 652
B122: Exit Multiple Method | C122: =MIN(C113:G117) -> 546.45219 | D122: =F95 -> 683.04916 | E122: =MAX(C113:G117) -> 840.98677 | F122: =E97 -> 652
B124: Implied Valuation Range | C124: =MIN(C121:C122) -> 418.40284 | D124: =AVERAGE(D121:D122) -> 618.91819 | E124: =MAX(E121:E122) -> 878.94 | F124: =E97 -> 652

Sheet Comps Analysis
B2: ASML HOLDING NV - COMPARABLE COMPANIES ANALYSIS
B7: SECTION 1: MARKET DATA & CAPITALIZATION
B9: Company | C9: Ticker | D9: Share Price (€) | E9: Shares Out (mm) | F9: Market Cap (€mm) | G9: Cash & ST Inv (€mm) | H9: Total Debt (€mm) | I9: Enterprise Value (€mm) | J9: LTM Revenue (€mm) | K9: LTM EBITDA (€mm) | L9: LTM EBIT (€mm) | M9: Net Debt / EBITDA
B10: ASML Holding NV | C10: ASML-NL | D10: 1215.6 | E10: 388.15 | F10: =D10*E10 -> 471835.14 | G10: 5128.2 | H10: 2704.7 | I10: =F10-G10+H10 -> 469411.64 | J10: 28262.9 | K10: 10009.4 | L10: 9022.6 | M10: =(H10-G10)/K10 -> -0.2421224
B11: KLA Corporation | C11: KLAC-US | D11: 1200.3 | E11: 131.39 | F11: =D11*E11 -> 157707.42 | G11: 4433.96 | H11: 5201.99 | I11: =F11-G11+H11 -> 158475.45 | J11: 11243.45 | K11: 5102.35 | L11: 4814.98 | M11: =(H11-G11)/K11 -> 0.15052476
B12: Applied Materials Inc | C12: AMAT-US | D12: 270.94 | E12: 792.94 | F12: =D12*E12 -> 214839.16 | G12: 7427.66 | H12: 6108.13 | I12: =F12-G12+H12 -> 213519.63 | J12: 24526.38 | K12: 7762.35 | L12: 7360.33 | M12: =(H12-G12)/K12 -> -0.16999105
B14: Mean | D14: =AVERAGE(D11:D12) -> 735.62 | E14: =AVERAGE(E11:E12) -> 462.165 | F14: =AVERAGE(F11:F12) -> 186273.29 | G14: =AVERAGE(G11:G12) -> 5930.81 | H14: =AVERAGE(H11:H12) -> 5655.06 | I14: =AVERAGE(I11:I12) -> 185997.54 | J14: =AVERAGE(J11:J12) -> 17884.915 | K14: =AVERAGE(K11:K12) -> 6432.35 | ... M14: =AVERAGE(M11:M12) -> -0.0097331442
B15: Median | D15: =MEDIAN(D11:D12) -> 735.62 | E15: =MEDIAN(E11:E12) -> 462.165 | F15: =MEDIAN(F11:F12) -> 186273.29 | G15: =MEDIAN(G11:G12) -> 5930.81 | H15: =MEDIAN(H11:H12) -> 5655.06 | I15: =MEDIAN(I11:I12) -> 185997.54 | J15: =MEDIAN(J11:J12) -> 17884.915 | K15: =MEDIAN(K11:K12) -> 6432.35 | ... M15: =MEDIAN(M11:M12) -> -0.0097331442
B17: SECTION 2: TRADING MULTIPLES
B19: Company | C19: Ticker | D19: EV / Revenue | E19: EV / EBITDA | F19: EV / EBIT | G19: P / E (FY1) | H19: P / E (FY2) | I19: P / FCF (FY1) | J19: P / FCF (FY2) | K19: Dividend Yield (%) | L19: FCF Yield (%)
B20: ASML Holding NV | C20: ASML-NL | D20: =I10/J10 -> 16.608757 | E20: =I10/K10 -> 46.897081 | F20: =I10/L10 -> 52.026205 | G20: 41.7 | H20: 32.6 | I20: 49.5 | J20: 36.5 | K20: 0.62 | L20: 3.41
B21: KLA Corporation | C21: KLAC-US | D21: =I11/J11 -> 14.094913 | E21: =I11/K11 -> 31.059305 | F21: =I11/L11 -> 32.913002 | G21: 39.1 | H21: 31.1 | I21: 42.5 | J21: 35 | K21: 0.53 | L21: 3.12
B22: Applied Materials Inc | C22: AMAT-US | D22: =I12/J12 -> 8.7057133 | E22: =I12/K12 -> 27.507087 | F22: =I12/L12 -> 29.009519 | G22: 33.3 | H22: 26.8 | I22: 51.7 | J22: 46.5 | K22: 0.57 | L22: 3.08
B24: Mean | D24: =AVERAGE(D21:D22) -> 11.400313 | E24: =AVERAGE(E21:E22) -> 29.283196 | F24: =AVERAGE(F21:F22) -> 30.961261 | G24: =AVERAGE(G21:G22) -> 36.2 | H24: =AVERAGE(H21:H22) -> 28.95 | I24: =AVERAGE(I21:I22) -> 47.1 | J24: =AVERAGE(J21:J22) -> 40.75 | K24: =AVERAGE(K21:K22) -> 0.55 | L24: =AVERAGE(L21:L22) -> 3.1
B25: Median | D25: =MEDIAN(D21:D22) -> 11.400313 | E25: =MEDIAN(E21:E22) -> 29.283196 | F25: =MEDIAN(F21:F22) -> 30.961261 | G25: =MEDIAN(G21:G22) -> 36.2 | H25: =MEDIAN(H21:H22) -> 28.95 | I25: =MEDIAN(I21:I22) -> 47.1 | J25: =MEDIAN(J21:J22) -> 40.75 | K25: =MEDIAN(K21:K22) -> 0.55 | L25: =MEDIAN(L21:L22) -> 3.1
B27: SECTION 3: OPERATING METRICS & MARGINS
B29: Company | C29: Ticker | D29: Revenue Growth (YoY %) | E29: Gross Margin (%) | F29: EBITDA Margin (%) | G29: EBIT Margin (%) | H29: Net Income Margin (%) | I29: ROE (%) | J29: ROIC (%) | K29: Asset Turnover (x) | L29: D/E Ratio (x) | M29: Current Ratio (x)
B30: ASML Holding NV | C30: ASML-NL | D30: 0.029 | E30: 0.512 | F30: =K10/J10 -> 0.35415332 | G30: =L10/J10 -> 0.31923829 | H30: 0.258 | I30: 0.565 | J30: 0.318 | K30: 0.63 | L30: 0.15 | M30: 1.52
B31: KLA Corporation | C31: KLAC-US | D31: 0.172 | E31: 0.614 | F31: =K11/J11 -> 0.45380644 | G31: =L11/J11 -> 0.42824756 | H31: 0.282 | I31: 0.893 | J31: 0.261 | K31: 0.52 | L31: 4.75 | M31: 2.43
B32: Applied Materials Inc | C32: AMAT-US | D32: 0.029 | E32: 0.477 | F32: =K12/J12 -> 0.31648984 | G32: =L12/J12 -> 0.30009851 | H32: 0.254 | I32: 0.407 | J32: 0.268 | K32: 0.72 | L32: 0.35 | M32: 2.86
B34: Mean | D34: =AVERAGE(D31:D32) -> 0.1005 | E34: =AVERAGE(E31:E32) -> 0.5455 | F34: =AVERAGE(F31:F32) -> 0.38514814 | G34: =AVERAGE(G31:G32) -> 0.36417303 | H34: =AVERAGE(H31:H32) -> 0.268 | I34: =AVERAGE(I31:I32) -> 0.65 | J34: =AVERAGE(J31:J32) -> 0.2645 | K34: =AVERAGE(K31:K32) -> 0.62 | ... M34: =AVERAGE(M31:M32) -> 2.645
B35: Median | D35: =MEDIAN(D31:D32) -> 0.1005 | E35: =MEDIAN(E31:E32) -> 0.5455 | F35: =MEDIAN(F31:F32) -> 0.38514814 | G35: =MEDIAN(G31:G32) -> 0.36417303 | H35: =MEDIAN(H31:H32) -> 0.268 | I35: =MEDIAN(I31:I32) -> 0.65 | J35: =MEDIAN(J31:J32) -> 0.2645 | K35: =MEDIAN(K31:K32) -> 0.62 | ... M35: =MEDIAN(M31:M32) -> 2.645
