Workbook
Name CovenantThreshold: "'Credit Scoring'!$B$62"
Name DistressMultiple: "'Credit Scoring'!$B$63"
Name NewIssuePremium: "'Credit Scoring'!$B$64"
Name PortfolioDuration: "Portfolio!$M$20"
Name PortfolioMV: "Portfolio!$G$20"
Name PortfolioSpread: "Portfolio!$L$20"
Name PortfolioYTM: "Portfolio!$I$20"
Name RiskFreeRate: "'Credit Scoring'!$B$65"

Sheet Cover
B2: CREDIT PORTFOLIO CONSTRUCTION & ANALYSIS
B3: Active Credit Portfolio · Benchmark Comparison · Performance Attribution
B4: Debt Capital Markets · Leveraged Finance · March 2026
B7: INVESTMENT GRADE (4 issuers · BBB+ to A · Microsoft, Johnson & Johnson, Rolls-Royce, Ford)
B8: CROSSOVER (4 issuers · BB+ to BBB− · Vodafone, Telecom Italia, Marks & Spencer, Telefonica)
B9: HIGH YIELD (4 issuers · BB to B · Carnival Corporation, Kraft Heinz, Bombardier, Coty)
B10: STRATEGY DESCRIPTION
B11: 1 | C11: This model provides an institutional-grade credit portfolio construction and management framework, designed to build, analyse, and track a concentrated high-conviction bond portfolio across investment grade, crossover, and high yield issuers — mirroring the workflow of a portfolio manager at a credit-focused hedge fund or asset manager.
B12: 2 | C12: The 12-issuer portfolio is constructed to express specific active views vs. a blended IG/HY benchmark: long duration, overweight high yield for carry capture, concentrated sector bets in telecom and industrials, and overweight credits with imminent upgrade potential based on our shadow rating analysis.
B13: 3 | C13: Portfolio construction is driven by a proprietary shadow rating model that identifies mispriced credits where our fundamental view diverges from agency ratings, enabling systematic capture of alpha through credit selection rather than broad market beta exposure.
B14: 4 | C14: Benchmark comparison tracks portfolio characteristics (yield, spread, duration, rating distribution) vs. a blended IG/HY index, highlighting active bets with explicit overweight/underweight positioning by sector, rating bucket, and duration — the key levers of credit alpha generation.
B15: 5 | C15: Performance attribution decomposes total return into carry (income), spread return (credit selection), and rate return (duration positioning), with explicit alpha calculation vs. benchmark — enabling clear identification of which active bets are contributing to outperformance.
B18: METHODOLOGY
B19: Credit Metric Definitions | C19: Net Debt/EBITDA (leverage) · EBITDA/Interest (coverage) · FCF/Total Debt (cash generation) · EBIT Margin (profitability) · Cash/ST Debt (liquidity). All from most recent annual reports (FY2024/2025).
B20: Shadow Rating Methodology | C20: Each issuer scored 1–5 on six metrics using rating-agency-calibrated thresholds. Weighted composite (Leverage 25% · Coverage 25% · FCF/Debt 20% · Margin 15% · D/E 10% · Liquidity 5%) mapped to shadow rating B+ through A.
B21: Spread Analysis Approach | C21: Fair value spreads derived from a rating- and maturity-adjusted reference grid (0–3y · 3–7y · 7+y), with sector adjustments (sector technicals) and issuer-specific adjustments (event risk, M&A, litigation). Mispricing = Market Spread − FV Spread.
B22: Data Sources | C22: Financials: company annual reports. Ratings: S&P Global and Moody's published ratings. Benchmark rates: government bond yields (UST / Bund / Gilt). Spread data: Bloomberg / ICE BofA indices (user-input yellow cells).
B23: Key Assumptions | C23: Distress EV: 5.0× EBITDA · HY covenant: Net Debt/EBITDA ≤ 5.0× · New issue premium: 20–25 bps · Stress: EBITDA −20% · Severe: EBITDA −35%, Debt +10% · All financials in reporting currency billions.
B25: WORKBOOK STRUCTURE
B26: Tab 1 — Portfolio | C26: Position sizing, weights, portfolio characteristics, rating distribution vs. benchmark
B27: Tab 2 — Benchmark vs Portfolio | C27: Sector allocation, active positioning summary, overweight/underweight signals
B28: Tab 3 — Performance Attribution | C28: Return decomposition (carry, spread, rate), alpha calculation, key performance metrics
B29: Tab 4 — Credit Universe | C29: 12-issuer master dashboard: shadow ratings, bond data, spreads, mispricing signals
B30: Tab 5 — Credit Scoring | C30: Shadow rating engine: raw metrics → derived ratios → weighted scores → ratings
B31: Tab 6 — Spread Analysis | C31: Fair value spread grid, sector/issuer adjustments, top 3 mispriced bond analysis
B32: Tab 7 — Scenario Analysis | C32: Stress testing: Base / Stress / Severe scenarios, rating migration, distance to distress
B33: Tab 8 — Relative Value | C33: 12×12 spread differential matrix, top 3 relative value pair trade opportunities
B35: DISCLAIMER
B36: For illustrative and educational purposes only. Not investment advice. All financial data sourced from publicly available company filings. The analytical views expressed are those of the model author. Past performance is not indicative of future results.

Sheet Portfolio
B2: CREDIT PORTFOLIO CONSTRUCTION
B3: Position sizing, portfolio weights, and aggregate portfolio characteristics vs. benchmark
B6: PORTFOLIO HOLDINGS — Enter Position Size (Face Value $M) in Yellow Cells
B7: Issuer | C7: Ticker | D7: Shadow Rating | E7: Face Value ($M) | F7: Market Price | G7: Market Value ($M) | H7: Weight (%) | I7: YTM (%) | J7: Spread (bps) | K7: Duration (yrs) | L7: Contrib. Spread | M7: Contrib. Duration
B8: Microsoft Corp | C8: MSFT | D8: ='Credit Scoring'!I22 -> A | E8: 15 | F8: ='Credit Universe'!K5 -> 101.25 | G8: =E8*F8/100 -> 15.1875 | H8: =G8/$G$20 -> 0.15990629 | I8: ='Credit Universe'!L5 -> 3.4567901 | J8: ='Credit Universe'!N5 -> -104.32099 | K8: 6.5 | L8: =H8*J8 -> -16.681582 | M8: =H8*K8 -> 1.0393909
B9: Johnson & Johnson | C9: JNJ | D9: ='Credit Scoring'!I23 -> A | E9: 15 | F9: ='Credit Universe'!K6 -> 102.1 | G9: =E9*F9/100 -> 15.315 | H9: =G9/$G$20 -> 0.16124872 | I9: ='Credit Universe'!L6 -> 3.3300686 | J9: ='Credit Universe'!N6 -> -116.99314 | K9: 7.2 | L9: =H9*J9 -> -18.864994 | M9: =H9*K9 -> 1.1609908
B10: Vodafone Group | C10: VOD | D10: ='Credit Scoring'!I24 -> BBB- | E10: 10 | F10: ='Credit Universe'!K7 -> 95.5 | G10: =E10*F10/100 -> 9.55 | H10: =G10/$G$20 -> 0.10055013 | I10: ='Credit Universe'!L7 -> 5.104712 | J10: ='Credit Universe'!N7 -> 90.471204 | K10: 5.8 | L10: =H10*J10 -> 9.0968914 | M10: =H10*K10 -> 0.58319076
B11: Rolls-Royce Holdings | C11: RR/ | D11: ='Credit Scoring'!I25 -> A | E11: 10 | F11: ='Credit Universe'!K8 -> 99.25 | G11: =E11*F11/100 -> 9.925 | H11: =G11/$G$20 -> 0.10449843 | I11: ='Credit Universe'!L8 -> 5.7934509 | J11: ='Credit Universe'!N8 -> 159.34509 | K11: 5.2 | L11: =H11*J11 -> 16.651312 | M11: =H11*K11 -> 0.54339186
B12: Ford Motor Company | C12: F | D12: ='Credit Scoring'!I26 -> BBB | E12: 8 | F12: ='Credit Universe'!K9 -> 92 | G12: =E12*F12/100 -> 7.36 | H12: =G12/$G$20 -> 0.077492038 | I12: ='Credit Universe'!L9 -> 6.6304348 | J12: ='Credit Universe'!N9 -> 213.04348 | K12: 3.8 | L12: =H12*J12 -> 16.509173 | M12: =H12*K12 -> 0.29446974
B13: Telecom Italia | C13: TIT | D13: ='Credit Scoring'!I27 -> BBB- | E13: 6 | F13: ='Credit Universe'!K10 -> 88.5 | G13: =E13*F13/100 -> 5.31 | H13: =G13/$G$20 -> 0.055907978 | I13: ='Credit Universe'!L10 -> 5.9322034 | J13: ='Credit Universe'!N10 -> 213.22034 | K13: 4.5 | L13: =H13*J13 -> 11.920718 | M13: =H13*K13 -> 0.2515859
B14: Marks & Spencer | C14: MKS | D14: ='Credit Scoring'!I28 -> BBB- | E14: 6 | F14: ='Credit Universe'!K11 -> 97.25 | G14: =E14*F14/100 -> 5.835 | H14: =G14/$G$20 -> 0.061435603 | I14: ='Credit Universe'!L11 -> 4.6272494 | J14: ='Credit Universe'!N11 -> 42.724936 | K14: 4.2 | L14: =H14*J14 -> 2.6248322 | M14: =H14*K14 -> 0.25802953
B15: Telefonica SA | C15: TEF | D15: ='Credit Scoring'!I29 -> BBB- | E15: 8 | F15: ='Credit Universe'!K12 -> 94 | G15: =E15*F15/100 -> 7.52 | H15: =G15/$G$20 -> 0.079176647 | I15: ='Credit Universe'!L12 -> 5.2074468 | J15: ='Credit Universe'!N12 -> 140.74468 | K15: 5.5 | L15: =H15*J15 -> 11.143692 | M15: =H15*K15 -> 0.43547156
B16: Carnival Corporation | C16: CCL | D16: ='Credit Scoring'!I30 -> BB | E16: 5 | F16: ='Credit Universe'!K13 -> 85.5 | G16: =E16*F16/100 -> 4.275 | H16: =G16/$G$20 -> 0.04501066 | I16: ='Credit Universe'!L13 -> 8.9181287 | J16: ='Credit Universe'!N13 -> 441.81287 | K16: 4.8 | L16: =H16*J16 -> 19.886289 | M16: =H16*K16 -> 0.21605117
B17: Kraft Heinz Company | C17: KHC | D17: ='Credit Scoring'!I31 -> BBB- | E17: 8 | F17: ='Credit Universe'!K14 -> 93.25 | G17: =E17*F17/100 -> 7.46 | H17: =G17/$G$20 -> 0.078544919 | I17: ='Credit Universe'!L14 -> 5.3619303 | J17: ='Credit Universe'!N14 -> 86.193029 | K17: 5 | L17: =H17*J17 -> 6.7700245 | M17: =H17*K17 -> 0.39272459
B18: Bombardier Inc | C18: BBD | D18: ='Credit Scoring'!I32 -> BB+ | E18: 5 | F18: ='Credit Universe'!K15 -> 82 | G18: =E18*F18/100 -> 4.1 | H18: =G18/$G$20 -> 0.043168119 | I18: ='Credit Universe'!L15 -> 9.6036585 | J18: ='Credit Universe'!N15 -> 510.36585 | K18: 4.2 | L18: =H18*J18 -> 22.031534 | M18: =H18*K18 -> 0.1813061
B19: Coty Inc | C19: COTY | D19: ='Credit Scoring'!I33 -> BB | E19: 4 | F19: ='Credit Universe'!K16 -> 78.5 | G19: =E19*F19/100 -> 3.14 | H19: =G19/$G$20 -> 0.033060462 | I19: ='Credit Universe'!L16 -> 8.2802548 | J19: ='Credit Universe'!N16 -> 378.02548 | K19: 3.5 | L19: =H19*J19 -> 12.497697 | M19: =H19*K19 -> 0.11571162
B20: PORTFOLIO TOTAL | E20: =SUM(E8:E19) -> 100 | G20: =SUM(G8:G19) -> 94.9775 | H20: =SUM(H8:H19) -> 1 | I20: =SUMPRODUCT(H8:H19,I8:I19) -> 5.2613514 | L20: =SUM(L8:L19) -> 93.585586 | M20: =SUM(M8:M19) -> 5.4723145
B22: PORTFOLIO CHARACTERISTICS SUMMARY | H22: RATING DISTRIBUTION (% of Portfolio MV)
B23: Metric | C23: Portfolio | D23: Benchmark | E23: vs. Benchmark | F23: Signal | H23: Rating | I23: Portfolio Wt | J23: Benchmark Wt | K23: Over/Under | L23: Visual
B24: Yield to Maturity (%) | C24: =I20 -> 5.2613514 | D24: 6.5 | E24: =C24-D24 -> -1.2386486 | F24: YTM vs. benchmark | H24: A | I24: =SUMIF($D$8:$D$19,"A",$H$8:$H$19) -> 0.42565344 | J24: 0.15 | K24: =I24-J24 -> 0.27565344 | L24: =IF(K24>0.02,"▲ OW",IF(K24<-0.02,"▼ UW","— Neutral")) -> ▲ OW
B25: Spread to Benchmark (bps) | C25: =L20 -> 93.585586 | D25: 250 | E25: =C25-D25 -> -156.41441 | F25: Spread pickup | H25: BBB+ | I25: =SUMIF($D$8:$D$19,"BBB+",$H$8:$H$19) -> 0 | J25: 0.2 | K25: =I25-J25 -> -0.2 | L25: =IF(K25>0.02,"▲ OW",IF(K25<-0.02,"▼ UW","— Neutral")) -> ▼ UW
B26: Modified Duration (yrs) | C26: =M20 -> 5.4723145 | D26: 5 | E26: =C26-D26 -> 0.4723145 | F26: Duration positioning | H26: BBB | I26: =SUMIF($D$8:$D$19,"BBB",$H$8:$H$19) -> 0.077492038 | J26: 0.2 | K26: =I26-J26 -> -0.12250796 | L26: =IF(K26>0.02,"▲ OW",IF(K26<-0.02,"▼ UW","— Neutral")) -> ▼ UW
B27: Average Price ($) | C27: =SUMPRODUCT(H8:H19,F8:F19) -> 95.430111 | D27: 95 | E27: =C27-D27 -> 0.43011108 | F27: Discount/premium | H27: BBB- | I27: =SUMIF($D$8:$D$19,"BBB-",$H$8:$H$19) -> 0.37561528 | J27: 0.15 | K27: =I27-J27 -> 0.22561528 | L27: =IF(K27>0.02,"▲ OW",IF(K27<-0.02,"▼ UW","— Neutral")) -> ▲ OW
B28: Number of Holdings | C28: 12 | D28: 1500 | E28: =C28-D28 -> -1488 | F28: Concentration | H28: BB+ | I28: =SUMIF($D$8:$D$19,"BB+",$H$8:$H$19) -> 0.043168119 | J28: 0.1 | K28: =I28-J28 -> -0.056831881 | L28: =IF(K28>0.02,"▲ OW",IF(K28<-0.02,"▼ UW","— Neutral")) -> ▼ UW
B29: Portfolio Size ($M) | C29: =G20 -> 94.9775 | D29: 500 | E29: =C29-D29 -> -405.0225 | F29: Scale | H29: BB | I29: =SUMIF($D$8:$D$19,"BB",$H$8:$H$19) -> 0.078071122 | J29: 0.12 | K29: =I29-J29 -> -0.041928878 | L29: =IF(K29>0.02,"▲ OW",IF(K29<-0.02,"▼ UW","— Neutral")) -> ▼ UW
H30: B+ | I30: =SUMIF($D$8:$D$19,"B+",$H$8:$H$19) -> 0 | J30: 0.08 | K30: =I30-J30 -> -0.08 | L30: =IF(K30>0.02,"▲ OW",IF(K30<-0.02,"▼ UW","— Neutral")) -> ▼ UW

Sheet Benchmark vs Portfolio
B2: BENCHMARK COMPARISON — PORTFOLIO vs. INDEX
B3: Active positioning vs. blended IG/HY benchmark — sector, rating, and duration exposures
B6: SECTOR ALLOCATION | I6: ACTIVE BET SUMMARY
B7: Sector | C7: Portfolio Wt (%) | D7: Benchmark Wt (%) | E7: Over/Under (%) | F7: Bet Description | I7: Active Bet | J7: Direction | K7: Size (%) | L7: Rationale
B8: Technology | C8: =SUMIF(Portfolio!$C$8:$C$19,"MSFT",Portfolio!$H$8:$H$19) -> 0.15990629 | D8: 0.12 | E8: =C8-D8 -> 0.039906294 | F8: =IF(E8>0.03,"OVERWEIGHT — active long",IF(E8<-0.03,"UNDERWEIGHT — active short","NEUTRAL — index weight")) -> OVERWEIGHT — active long | I8: Long Duration | J8: OW | K8: +0.5 yrs vs. BM | L8: Rates expected to decline; position for spread tightening on duration extension
B9: Healthcare | C9: =SUMIF(Portfolio!$C$8:$C$19,"JNJ",Portfolio!$H$8:$H$19) -> 0.16124872 | D9: 0.1 | E9: =C9-D9 -> 0.061248717 | F9: =IF(E9>0.03,"OVERWEIGHT — active long",IF(E9<-0.03,"UNDERWEIGHT — active short","NEUTRAL — index weight")) -> OVERWEIGHT — active long | I9: Long HY / Short IG | J9: OW HY | K9: +8% HY vs. BM | L9: Carry capture in stable macro environment; shadow ratings support undervalued HY credits
B10: Telecom | C10: {=SUMPRODUCT(((Portfolio!$C$8:$C$19="VOD")+(Portfolio!$C$8:$C$19="TIT")+(Portfolio!$C$8:$C$19="TEF"))*Portfolio!$H$8:$H$19)} -> 0.23563476 | D10: 0.15 | E10: =C10-D10 -> 0.085634756 | F10: =IF(E10>0.03,"OVERWEIGHT — active long",IF(E10<-0.03,"UNDERWEIGHT — active short","NEUTRAL — index weight")) -> OVERWEIGHT — active long | I10: Long Telecom | J10: OW | K10: +5% vs. BM | L10: Sector cheap on post-restructuring stories (TIT, TEF); spread compression catalyst imminent
B11: Industrials | C11: {=SUMPRODUCT(((Portfolio!$C$8:$C$19="RR/")+(Portfolio!$C$8:$C$19="BBD"))*Portfolio!$H$8:$H$19)} -> 0.14766655 | D11: 0.18 | E11: =C11-D11 -> -0.032333447 | F11: =IF(E11>0.03,"OVERWEIGHT — active long",IF(E11<-0.03,"UNDERWEIGHT — active short","NEUTRAL — index weight")) -> UNDERWEIGHT — active short | I11: Short Consumer Discretionary | J11: UW | K11: -4% vs. BM | L11: Defensive positioning; consumer spending risks in discretionary leisure (ex-CCL position is diversification)
B12: Auto | C12: =SUMIF(Portfolio!$C$8:$C$19,"F",Portfolio!$H$8:$H$19) -> 0.077492038 | D12: 0.08 | E12: =C12-D12 -> -0.0025079624 | F12: =IF(E12>0.03,"OVERWEIGHT — active long",IF(E12<-0.03,"UNDERWEIGHT — active short","NEUTRAL — index weight")) -> NEUTRAL — index weight | I12: Long Upgrade Candidates | J12: OW BB+ | K12: 0.03 | L12: Bombardier, Kraft Heinz, Rolls-Royce — shadow ratings suggest upgrades ahead of agency action
B13: Consumer / Retail | C13: {=SUMPRODUCT(((Portfolio!$C$8:$C$19="MKS")+(Portfolio!$C$8:$C$19="KHC")+(Portfolio!$C$8:$C$19="COTY"))*Portfolio!$H$8:$H$19)} -> 0.17304098 | D13: 0.22 | E13: =C13-D13 -> -0.046959017 | F13: =IF(E13>0.03,"OVERWEIGHT — active long",IF(E13<-0.03,"UNDERWEIGHT — active short","NEUTRAL — index weight")) -> UNDERWEIGHT — active short | I13: Concentrated Portfolio | J13: Active | K13: 12 names | L13: High-conviction concentrated bets vs. diversified index; alpha from credit selection, not beta exposure
B14: Leisure | C14: =SUMIF(Portfolio!$C$8:$C$19,"CCL",Portfolio!$H$8:$H$19) -> 0.04501066 | D14: 0.15 | E14: =C14-D14 -> -0.10498934 | F14: =IF(E14>0.03,"OVERWEIGHT — active long",IF(E14<-0.03,"UNDERWEIGHT — active short","NEUTRAL — index weight")) -> UNDERWEIGHT — active short
B15: TOTAL | C15: =SUM(C8:C14) -> 1 | D15: =SUM(D8:D14) -> 1

Sheet Performance Attribution
B2: PERFORMANCE ATTRIBUTION & RETURN DECOMPOSITION
B3: Portfolio total return breakdown: carry, spread return, rate return — with benchmark comparison and alpha calculation
B6: RETURN DECOMPOSITION (Period: Enter in Yellow)
B7: Analysis Period: | C7: Q1 2026 | E7: Days in Period: | F7: 90
B8: Return Component | C8: Portfolio (%) | D8: Benchmark (%) | E8: Excess (%) | F8: Contribution ($M) | G8: Attribution
B9: Carry (Coupon Income) | C9: =Portfolio!$I$20/100*$F$7/365 -> 0.012973195 | D9: 0.016 | E9: =C9-D9 -> -0.0030268048 | F9: =Portfolio!$G$20*C9 -> 1.2321616 | G9: Income from portfolio yield
B10: Spread Return | C10: 0.008 | D10: 0.005 | E10: =C10-D10 -> 0.003 | F10: =Portfolio!$G$20*C10 -> 0.75982 | G10: Spread tightening vs. benchmark
B11: Rate Return (Duration) | C11: -0.003 | D11: -0.004 | E11: =C11-D11 -> 0.001 | F11: =Portfolio!$G$20*C11 -> -0.2849325 | G11: Interest rate move × duration
B12: Residual / Selection | C12: 0.002 | D12: 0 | E12: =C12-D12 -> 0.002 | F12: =Portfolio!$G$20*C12 -> 0.189955 | G12: Security selection alpha
B13: TOTAL RETURN | C13: =SUM(C9:C12) -> 0.019973195 | D13: =SUM(D9:D12) -> 0.017 | E13: =C13-D13 -> 0.0029731952 | F13: =Portfolio!$G$20*C13 -> 1.8970041 | G13: Total return for period
B15: KEY PERFORMANCE METRICS
B16: Metric | C16: Value | D16: Benchmark | E16: vs. BM | F16: Interpretation
B17: Information Ratio | C17: =E13/0.005 -> 0.59463903 | D17: 0 | E17: =C17-D17 -> 0.59463903 | F17: Alpha divided by tracking error (annualized)
B18: Sharpe Ratio (YTM basis) | C18: =(Portfolio!$I$20-4.5)/3 -> 0.25378379 | D18: 0.67 | E18: =C18-D18 -> -0.41621621 | F18: Return above risk-free rate / volatility proxy
B19: Yield Pickup vs. BM (bps) | C19: =(Portfolio!$I$20-6.5)*100 -> -123.86486 | D19: 0 | F19: Additional yield earned vs. benchmark
B20: Duration Difference (yrs) | C20: =Portfolio!$M$20-5 -> 0.4723145 | D20: 0 | F20: Duration extension/reduction vs. benchmark
B21: Spread Pickup (bps) | C21: =Portfolio!$L$20-250 -> -156.41441 | D21: 0 | F21: Weighted average spread above benchmark
B22: Hit Rate (%) | C22: 0.75 | D22: 0.5 | E22: =C21-D21 -> -156.41441 | F22: Proportion of positions outperforming (estimate)
B23: Max Drawdown (%) | C23: -0.025 | D23: -3.2 | E23: =C22-D22 -> 0.25 | F23: Largest peak-to-trough decline (estimate)

Sheet Credit Universe
A1: CREDIT UNIVERSE — MASTER DASHBOARD
A2: All 12 corporate issuers: shadow ratings, bond data, spread analysis and mispricing signals. Yellow cells = user inputs.
A3: ← IG Issuers (rows 5–8) | Crossover (rows 9–12) | High Yield (rows 13–16)
A4: Company | B4: Ticker | C4: Country | D4: Sector | E4: S&P Rating | F4: Moody's Rating | G4: Shadow Rating | H4: Bond ISIN | I4: Maturity | J4: Coupon (%) | K4: Mkt Price | L4: YTM (%) | M4: Benchmark Rate (%) | N4: Mkt Spread (bps) | O4: FV Spread (bps) | P4: Mispricing (bps) | Q4: Signal | R4: Credit View
A5: Microsoft Corp | B5: MSFT | C5: USA | D5: Technology | E5: AA- | F5: Aa2 | G5: ='Credit Scoring'!$I$22 -> A | H5: US594918BW38 | I5: 2030 | J5: 3.5 | K5: 101.25 | L5: =IF(K5="","",J5/K5*100) -> 3.4567901 | M5: 4.5 | N5: =IF(OR(L5="",M5=""),"",(L5-M5)*100) -> -104.32099 | O5: ='Spread Analysis'!$J$16 -> 65 | P5: =IF(OR(N5="",O5=""),"",N5-O5) -> -169.32099 | Q5: =IF(P5="","",IF(P5>15,"Too Wide",IF(P5<-15,"Too Tight","Fair"))) -> Too Tight | R5: Bull
A6: Johnson & Johnson | B6: JNJ | C6: USA | D6: Healthcare | E6: AA- | F6: Aa3 | G6: ='Credit Scoring'!$I$23 -> A | H6: US478160CN59 | I6: 2031 | J6: 3.4 | K6: 102.1 | L6: =IF(K6="","",J6/K6*100) -> 3.3300686 | M6: 4.5 | N6: =IF(OR(L6="",M6=""),"",(L6-M6)*100) -> -116.99314 | O6: ='Spread Analysis'!$J$17 -> 70 | P6: =IF(OR(N6="",O6=""),"",N6-O6) -> -186.99314 | Q6: =IF(P6="","",IF(P6>15,"Too Wide",IF(P6<-15,"Too Tight","Fair"))) -> Too Tight | R6: Neutral
A7: Vodafone Group | B7: VOD | C7: UK | D7: Telecom | E7: BBB | F7: Baa2 | G7: ='Credit Scoring'!$I$24 -> BBB- | H7: XS1629774230 | I7: 2028 | J7: 4.875 | K7: 95.5 | L7: =IF(K7="","",J7/K7*100) -> 5.104712 | M7: 4.2 | N7: =IF(OR(L7="",M7=""),"",(L7-M7)*100) -> 90.471204 | O7: ='Spread Analysis'!$J$18 -> 250 | P7: =IF(OR(N7="",O7=""),"",N7-O7) -> -159.5288 | Q7: =IF(P7="","",IF(P7>15,"Too Wide",IF(P7<-15,"Too Tight","Fair"))) -> Too Tight | R7: Bull
A8: Rolls-Royce Holdings | B8: RR/ | C8: UK | D8: Industrials | E8: BBB- | F8: Baa3 | G8: ='Credit Scoring'!$I$25 -> A | H8: XS2010039035 | I8: 2027 | J8: 5.75 | K8: 99.25 | L8: =IF(K8="","",J8/K8*100) -> 5.7934509 | M8: 4.2 | N8: =IF(OR(L8="",M8=""),"",(L8-M8)*100) -> 159.34509 | O8: ='Spread Analysis'!$J$19 -> 80 | P8: =IF(OR(N8="",O8=""),"",N8-O8) -> 79.345088 | Q8: =IF(P8="","",IF(P8>15,"Too Wide",IF(P8<-15,"Too Tight","Fair"))) -> Too Wide | R8: Bull
A9: Ford Motor Company | B9: F | C9: USA | D9: Auto | E9: BB+ | F9: Ba1 | G9: ='Credit Scoring'!$I$26 -> BBB | H9: US345370DA14 | I9: 2027 | J9: 6.1 | K9: 92 | L9: =IF(K9="","",J9/K9*100) -> 6.6304348 | M9: 4.5 | N9: =IF(OR(L9="",M9=""),"",(L9-M9)*100) -> 213.04348 | O9: ='Spread Analysis'!$J$20 -> 195 | P9: =IF(OR(N9="",O9=""),"",N9-O9) -> 18.043478 | Q9: =IF(P9="","",IF(P9>15,"Too Wide",IF(P9<-15,"Too Tight","Fair"))) -> Too Wide | R9: Neutral
A10: Telecom Italia | B10: TIT | C10: Italy | D10: Telecom | E10: BB | F10: Ba2 | G10: ='Credit Scoring'!$I$27 -> BBB- | H10: XS1497606365 | I10: 2027 | J10: 5.25 | K10: 88.5 | L10: =IF(K10="","",J10/K10*100) -> 5.9322034 | M10: 3.8 | N10: =IF(OR(L10="",M10=""),"",(L10-M10)*100) -> 213.22034 | O10: ='Spread Analysis'!$J$21 -> 235 | P10: =IF(OR(N10="",O10=""),"",N10-O10) -> -21.779661 | Q10: =IF(P10="","",IF(P10>15,"Too Wide",IF(P10<-15,"Too Tight","Fair"))) -> Too Tight | R10: Bull
A11: Marks & Spencer | B11: MKS | C11: UK | D11: Retail | E11: BBB- | F11: Baa3 | G11: ='Credit Scoring'!$I$28 -> BBB- | H11: XS2055079067 | I11: 2027 | J11: 4.5 | K11: 97.25 | L11: =IF(K11="","",J11/K11*100) -> 4.6272494 | M11: 4.2 | N11: =IF(OR(L11="",M11=""),"",(L11-M11)*100) -> 42.724936 | O11: ='Spread Analysis'!$J$22 -> 210 | P11: =IF(OR(N11="",O11=""),"",N11-O11) -> -167.27506 | Q11: =IF(P11="","",IF(P11>15,"Too Wide",IF(P11<-15,"Too Tight","Fair"))) -> Too Tight | R11: Neutral
A12: Telefonica SA | B12: TEF | C12: Spain | D12: Telecom | E12: BBB- | F12: Baa3 | G12: ='Credit Scoring'!$I$29 -> BBB- | H12: XS1795406658 | I12: 2029 | J12: 4.895 | K12: 94 | L12: =IF(K12="","",J12/K12*100) -> 5.2074468 | M12: 3.8 | N12: =IF(OR(L12="",M12=""),"",(L12-M12)*100) -> 140.74468 | O12: ='Spread Analysis'!$J$23 -> 245 | P12: =IF(OR(N12="",O12=""),"",N12-O12) -> -104.25532 | Q12: =IF(P12="","",IF(P12>15,"Too Wide",IF(P12<-15,"Too Tight","Fair"))) -> Too Tight | R12: Neutral
A13: Carnival Corporation | B13: CCL | C13: USA | D13: Leisure | E13: B+ | F13: B1 | G13: ='Credit Scoring'!$I$30 -> BB | H13: US143658BR95 | I13: 2028 | J13: 7.625 | K13: 85.5 | L13: =IF(K13="","",J13/K13*100) -> 8.9181287 | M13: 4.5 | N13: =IF(OR(L13="",M13=""),"",(L13-M13)*100) -> 441.81287 | O13: ='Spread Analysis'!$J$24 -> 405 | P13: =IF(OR(N13="",O13=""),"",N13-O13) -> 36.812865 | Q13: =IF(P13="","",IF(P13>15,"Too Wide",IF(P13<-15,"Too Tight","Fair"))) -> Too Wide | R13: Bear
A14: Kraft Heinz Company | B14: KHC | C14: USA | D14: Consumer | E14: BBB- | F14: Baa3 | G14: ='Credit Scoring'!$I$31 -> BBB- | H14: US50077LAV62 | I14: 2027 | J14: 5 | K14: 93.25 | L14: =IF(K14="","",J14/K14*100) -> 5.3619303 | M14: 4.5 | N14: =IF(OR(L14="",M14=""),"",(L14-M14)*100) -> 86.193029 | O14: ='Spread Analysis'!$J$25 -> 215 | P14: =IF(OR(N14="",O14=""),"",N14-O14) -> -128.80697 | Q14: =IF(P14="","",IF(P14>15,"Too Wide",IF(P14<-15,"Too Tight","Fair"))) -> Too Tight | R14: Bull
A15: Bombardier Inc | B15: BBD | C15: Canada | D15: Industrials | E15: B | F15: B2 | G15: ='Credit Scoring'!$I$32 -> BB+ | H15: USC10602AK68 | I15: 2028 | J15: 7.875 | K15: 82 | L15: =IF(K15="","",J15/K15*100) -> 9.6036585 | M15: 4.5 | N15: =IF(OR(L15="",M15=""),"",(L15-M15)*100) -> 510.36585 | O15: ='Spread Analysis'!$J$26 -> 305 | P15: =IF(OR(N15="",O15=""),"",N15-O15) -> 205.36585 | Q15: =IF(P15="","",IF(P15>15,"Too Wide",IF(P15<-15,"Too Tight","Fair"))) -> Too Wide | R15: Bull
A16: Coty Inc | B16: COTY | C16: USA | D16: Consumer | E16: B | F16: B2 | G16: ='Credit Scoring'!$I$33 -> BB | H16: US222070AC28 | I16: 2027 | J16: 6.5 | K16: 78.5 | L16: =IF(K16="","",J16/K16*100) -> 8.2802548 | M16: 4.5 | N16: =IF(OR(L16="",M16=""),"",(L16-M16)*100) -> 378.02548 | O16: ='Spread Analysis'!$J$27 -> 385 | P16: =IF(OR(N16="",O16=""),"",N16-O16) -> -6.9745223 | Q16: =IF(P16="","",IF(P16>15,"Too Wide",IF(P16<-15,"Too Tight","Fair"))) -> Fair | R16: Bear
A17: Tier Colour Guide: | B17: Green left border = IG (rows 5-8) | C17: Amber = Crossover (rows 9-12) | D17: Red = High Yield (rows 13-16)
A18: INPUT LEGEND
A19: Yellow cells | B19: User inputs — fill from annual reports, Bloomberg, or broker data
A20: White cells | B20: Formula-driven — do not edit
A21: Green signal | B21: Too Wide — bond trading cheap vs fair value (potential buy)
A22: Red signal | B22: Too Tight — bond trading rich vs fair value (potential avoid/short)
A23: Grey signal | B23: Fair — bond trading within ±15 bps of fair value estimate

Sheet Credit Scoring
A1: CREDIT SCORING MODEL — SHADOW RATING ENGINE
A2: Proprietary scoring model: raw financial metrics → derived ratios → weighted scores → composite rating → shadow rating
A4: SECTION 1 — RAW FINANCIAL METRICS INPUT (Yellow = user input, fill from annual reports) | B4: ← USER INPUTS (fill from annual reports) | J4: ← FORMULA-DERIVED RATIOS (auto-calculated)
A5: Company | B5: Revenue (bn) | C5: EBITDA (bn) | D5: EBIT (bn) | E5: Total Debt (bn) | F5: Cash & Equiv (bn) | G5: Interest Exp (bn) | H5: Capex (bn) | I5: FCF (bn) | J5: Net Debt/EBITDA | K5: EBITDA/Interest | L5: FCF/Debt (%) | M5: Debt/Equity | N5: EBIT Margin (%) | O5: Cash/ST Debt
A6: Microsoft Corp | B6: 245.1 | C6: 130.1 | D6: 109.4 | E6: 79.4 | F6: 18.3 | G6: 1.9 | H6: 21.7 | I6: 74.1 | J6: =(E6-F6)/C6 -> 0.46963874 | K6: =IF(G6=0,"N/A",C6/G6) -> 68.473684 | L6: =IF(E6=0,"N/A",I6/E6*100) -> 93.324937 | M6: =E6/MAX(C6*6-E6,0.01) -> 0.11323446 | N6: =IF(B6=0,"N/A",D6/B6*100) -> 44.634843 | O6: =IF(E6=0,"N/A",F6/(E6*0.2)) -> 1.1523929
A7: Johnson & Johnson | B7: 88.2 | C7: 25.8 | D7: 22.1 | E7: 27.9 | F7: 21.9 | G7: 0.5 | H7: 3.3 | I7: 18.8 | J7: =(E7-F7)/C7 -> 0.23255814 | K7: =IF(G7=0,"N/A",C7/G7) -> 51.6 | L7: =IF(E7=0,"N/A",I7/E7*100) -> 67.383513 | M7: =E7/MAX(C7*6-E7,0.01) -> 0.21985816 | N7: =IF(B7=0,"N/A",D7/B7*100) -> 25.056689 | O7: =IF(E7=0,"N/A",F7/(E7*0.2)) -> 3.9247312
A8: Vodafone Group | B8: 45.6 | C8: 14.8 | D8: 5.1 | E8: 52.1 | F8: 5.2 | G8: 2.7 | H8: 5.9 | I8: 5.3 | J8: =(E8-F8)/C8 -> 3.1689189 | K8: =IF(G8=0,"N/A",C8/G8) -> 5.4814815 | L8: =IF(E8=0,"N/A",I8/E8*100) -> 10.172745 | M8: =E8/MAX(C8*6-E8,0.01) -> 1.4196185 | N8: =IF(B8=0,"N/A",D8/B8*100) -> 11.184211 | O8: =IF(E8=0,"N/A",F8/(E8*0.2)) -> 0.49904031
A9: Rolls-Royce Holdings | B9: 18.7 | C9: 2.8 | D9: 1.9 | E9: 3.2 | F9: 2.4 | G9: 0.2 | H9: 0.9 | I9: 1.4 | J9: =(E9-F9)/C9 -> 0.28571429 | K9: =IF(G9=0,"N/A",C9/G9) -> 14 | L9: =IF(E9=0,"N/A",I9/E9*100) -> 43.75 | M9: =E9/MAX(C9*6-E9,0.01) -> 0.23529412 | N9: =IF(B9=0,"N/A",D9/B9*100) -> 10.160428 | O9: =IF(E9=0,"N/A",F9/(E9*0.2)) -> 3.75
A10: Ford Motor Company | B10: 185 | C10: 10.2 | D10: 6.4 | E10: 22 | F10: 29.3 | G10: 1.5 | H10: 7.1 | I10: 2.8 | J10: =(E10-F10)/C10 -> -0.71568627 | K10: =IF(G10=0,"N/A",C10/G10) -> 6.8 | L10: =IF(E10=0,"N/A",I10/E10*100) -> 12.727273 | M10: =E10/MAX(C10*6-E10,0.01) -> 0.56122449 | N10: =IF(B10=0,"N/A",D10/B10*100) -> 3.4594595 | O10: =IF(E10=0,"N/A",F10/(E10*0.2)) -> 6.6590909
A11: Telecom Italia | B11: 14.2 | C11: 5.1 | D11: 1.8 | E11: 14.2 | F11: 3.2 | G11: 1.8 | H11: 2.2 | I11: 1.2 | J11: =(E11-F11)/C11 -> 2.1568627 | K11: =IF(G11=0,"N/A",C11/G11) -> 2.8333333 | L11: =IF(E11=0,"N/A",I11/E11*100) -> 8.4507042 | M11: =E11/MAX(C11*6-E11,0.01) -> 0.86585366 | N11: =IF(B11=0,"N/A",D11/B11*100) -> 12.676056 | O11: =IF(E11=0,"N/A",F11/(E11*0.2)) -> 1.1267606
A12: Marks & Spencer | B12: 13.7 | C12: 1.3 | D12: 0.8 | E12: 4.1 | F12: 1.1 | G12: 0.2 | H12: 0.7 | I12: 0.6 | J12: =(E12-F12)/C12 -> 2.3076923 | K12: =IF(G12=0,"N/A",C12/G12) -> 6.5 | L12: =IF(E12=0,"N/A",I12/E12*100) -> 14.634146 | M12: =E12/MAX(C12*6-E12,0.01) -> 1.1081081 | N12: =IF(B12=0,"N/A",D12/B12*100) -> 5.8394161 | O12: =IF(E12=0,"N/A",F12/(E12*0.2)) -> 1.3414634
A13: Telefonica SA | B13: 41.4 | C13: 13 | D13: 6.1 | E13: 40.2 | F13: 7.3 | G13: 2.5 | H13: 5.6 | I13: 4.1 | J13: =(E13-F13)/C13 -> 2.5307692 | K13: =IF(G13=0,"N/A",C13/G13) -> 5.2 | L13: =IF(E13=0,"N/A",I13/E13*100) -> 10.199005 | M13: =E13/MAX(C13*6-E13,0.01) -> 1.0634921 | N13: =IF(B13=0,"N/A",D13/B13*100) -> 14.7343 | O13: =IF(E13=0,"N/A",F13/(E13*0.2)) -> 0.9079602
A14: Carnival Corporation | B14: 22.4 | C14: 5.8 | D14: 2.6 | E14: 35.9 | F14: 1.7 | G14: 1.8 | H14: 2.6 | I14: 1.4 | J14: =(E14-F14)/C14 -> 5.8965517 | K14: =IF(G14=0,"N/A",C14/G14) -> 3.2222222 | L14: =IF(E14=0,"N/A",I14/E14*100) -> 3.8997214 | M14: =E14/MAX(C14*6-E14,0.01) -> 3590 | N14: =IF(B14=0,"N/A",D14/B14*100) -> 11.607143 | O14: =IF(E14=0,"N/A",F14/(E14*0.2)) -> 0.2367688
A15: Kraft Heinz Company | B15: 25.8 | C15: 5.9 | D15: 3.5 | E15: 21.1 | F15: 0.9 | G15: 1.4 | H15: 0.8 | I15: 3.3 | J15: =(E15-F15)/C15 -> 3.4237288 | K15: =IF(G15=0,"N/A",C15/G15) -> 4.2142857 | L15: =IF(E15=0,"N/A",I15/E15*100) -> 15.63981 | M15: =E15/MAX(C15*6-E15,0.01) -> 1.4755245 | N15: =IF(B15=0,"N/A",D15/B15*100) -> 13.565891 | O15: =IF(E15=0,"N/A",F15/(E15*0.2)) -> 0.21327014
A16: Bombardier Inc | B16: 7.9 | C16: 1.8 | D16: 0.8 | E16: 8.4 | F16: 1.8 | G16: 0.8 | H16: 0.3 | I16: 0.7 | J16: =(E16-F16)/C16 -> 3.6666667 | K16: =IF(G16=0,"N/A",C16/G16) -> 2.25 | L16: =IF(E16=0,"N/A",I16/E16*100) -> 8.3333333 | M16: =E16/MAX(C16*6-E16,0.01) -> 3.5 | N16: =IF(B16=0,"N/A",D16/B16*100) -> 10.126582 | O16: =IF(E16=0,"N/A",F16/(E16*0.2)) -> 1.0714286
A17: Coty Inc | B17: 5.6 | C17: 0.9 | D17: 0.4 | E17: 4.8 | F17: 0.5 | G17: 0.4 | H17: 0.2 | I17: 0.3 | J17: =(E17-F17)/C17 -> 4.7777778 | K17: =IF(G17=0,"N/A",C17/G17) -> 2.25 | L17: =IF(E17=0,"N/A",I17/E17*100) -> 6.25 | M17: =E17/MAX(C17*6-E17,0.01) -> 8 | N17: =IF(B17=0,"N/A",D17/B17*100) -> 7.1428571 | O17: =IF(E17=0,"N/A",F17/(E17*0.2)) -> 0.52083333
A19: SECTION 2 — CREDIT SCORING (1–5 per metric, thresholds reflect rating agency logic)
A20: WEIGHTS → | B20: Net Debt/EBITDA (25%) | C20: EBITDA/Interest (25%) | D20: FCF/Debt % (20%) | E20: Debt/Equity (10%) | F20: EBIT Margin % (15%) | G20: Liquidity (5%) | H20: Composite Score | I20: Shadow Rating
A21: Company | B21: ND/EBITDA Score | C21: Coverage Score | D21: FCF/Debt Score | E21: D/E Score | F21: Margin Score | G21: Liquidity Score | H21: Composite Score | I21: Shadow Rating
A22: Microsoft Corp | B22: =IF(J6<1,5,IF(J6<2,4,IF(J6<3,3,IF(J6<4,2,1)))) -> 5 | C22: =IF(K6>10,5,IF(K6>7,4,IF(K6>4,3,IF(K6>2,2,1)))) -> 5 | D22: =IF(L6>20,5,IF(L6>15,4,IF(L6>10,3,IF(L6>5,2,1)))) -> 5 | E22: =IF(M6<0.5,5,IF(M6<1,4,IF(M6<2,3,IF(M6<3,2,1)))) -> 5 | F22: =IF(N6>20,5,IF(N6>15,4,IF(N6>10,3,IF(N6>5,2,1)))) -> 5 | G22: =IF(O6>3,5,IF(O6>2,4,IF(O6>1.5,3,IF(O6>1,2,1)))) -> 2 | H22: =B22*0.25+C22*0.25+D22*0.2+E22*0.1+F22*0.15+G22*0.05 -> 4.85 | I22: =IF(H22>=4.5,"A",IF(H22>=3.8,"BBB+",IF(H22>=3.2,"BBB",IF(H22>=2.6,"BBB-",IF(H22>=2,"BB+",IF(H22>=1.5,"BB","B+")))))) -> A
A23: Johnson & Johnson | B23: =IF(J7<1,5,IF(J7<2,4,IF(J7<3,3,IF(J7<4,2,1)))) -> 5 | C23: =IF(K7>10,5,IF(K7>7,4,IF(K7>4,3,IF(K7>2,2,1)))) -> 5 | D23: =IF(L7>20,5,IF(L7>15,4,IF(L7>10,3,IF(L7>5,2,1)))) -> 5 | E23: =IF(M7<0.5,5,IF(M7<1,4,IF(M7<2,3,IF(M7<3,2,1)))) -> 5 | F23: =IF(N7>20,5,IF(N7>15,4,IF(N7>10,3,IF(N7>5,2,1)))) -> 5 | G23: =IF(O7>3,5,IF(O7>2,4,IF(O7>1.5,3,IF(O7>1,2,1)))) -> 5 | H23: =B23*0.25+C23*0.25+D23*0.2+E23*0.1+F23*0.15+G23*0.05 -> 5 | I23: =IF(H23>=4.5,"A",IF(H23>=3.8,"BBB+",IF(H23>=3.2,"BBB",IF(H23>=2.6,"BBB-",IF(H23>=2,"BB+",IF(H23>=1.5,"BB","B+")))))) -> A
A24: Vodafone Group | B24: =IF(J8<1,5,IF(J8<2,4,IF(J8<3,3,IF(J8<4,2,1)))) -> 2 | C24: =IF(K8>10,5,IF(K8>7,4,IF(K8>4,3,IF(K8>2,2,1)))) -> 3 | D24: =IF(L8>20,5,IF(L8>15,4,IF(L8>10,3,IF(L8>5,2,1)))) -> 3 | E24: =IF(M8<0.5,5,IF(M8<1,4,IF(M8<2,3,IF(M8<3,2,1)))) -> 3 | F24: =IF(N8>20,5,IF(N8>15,4,IF(N8>10,3,IF(N8>5,2,1)))) -> 3 | G24: =IF(O8>3,5,IF(O8>2,4,IF(O8>1.5,3,IF(O8>1,2,1)))) -> 1 | H24: =B24*0.25+C24*0.25+D24*0.2+E24*0.1+F24*0.15+G24*0.05 -> 2.65 | I24: =IF(H24>=4.5,"A",IF(H24>=3.8,"BBB+",IF(H24>=3.2,"BBB",IF(H24>=2.6,"BBB-",IF(H24>=2,"BB+",IF(H24>=1.5,"BB","B+")))))) -> BBB-
A25: Rolls-Royce Holdings | B25: =IF(J9<1,5,IF(J9<2,4,IF(J9<3,3,IF(J9<4,2,1)))) -> 5 | C25: =IF(K9>10,5,IF(K9>7,4,IF(K9>4,3,IF(K9>2,2,1)))) -> 5 | D25: =IF(L9>20,5,IF(L9>15,4,IF(L9>10,3,IF(L9>5,2,1)))) -> 5 | E25: =IF(M9<0.5,5,IF(M9<1,4,IF(M9<2,3,IF(M9<3,2,1)))) -> 5 | F25: =IF(N9>20,5,IF(N9>15,4,IF(N9>10,3,IF(N9>5,2,1)))) -> 3 | G25: =IF(O9>3,5,IF(O9>2,4,IF(O9>1.5,3,IF(O9>1,2,1)))) -> 5 | H25: =B25*0.25+C25*0.25+D25*0.2+E25*0.1+F25*0.15+G25*0.05 -> 4.7 | I25: =IF(H25>=4.5,"A",IF(H25>=3.8,"BBB+",IF(H25>=3.2,"BBB",IF(H25>=2.6,"BBB-",IF(H25>=2,"BB+",IF(H25>=1.5,"BB","B+")))))) -> A
A26: Ford Motor Company | B26: =IF(J10<1,5,IF(J10<2,4,IF(J10<3,3,IF(J10<4,2,1)))) -> 5 | C26: =IF(K10>10,5,IF(K10>7,4,IF(K10>4,3,IF(K10>2,2,1)))) -> 3 | D26: =IF(L10>20,5,IF(L10>15,4,IF(L10>10,3,IF(L10>5,2,1)))) -> 3 | E26: =IF(M10<0.5,5,IF(M10<1,4,IF(M10<2,3,IF(M10<3,2,1)))) -> 4 | F26: =IF(N10>20,5,IF(N10>15,4,IF(N10>10,3,IF(N10>5,2,1)))) -> 1 | G26: =IF(O10>3,5,IF(O10>2,4,IF(O10>1.5,3,IF(O10>1,2,1)))) -> 5 | H26: =B26*0.25+C26*0.25+D26*0.2+E26*0.1+F26*0.15+G26*0.05 -> 3.4 | I26: =IF(H26>=4.5,"A",IF(H26>=3.8,"BBB+",IF(H26>=3.2,"BBB",IF(H26>=2.6,"BBB-",IF(H26>=2,"BB+",IF(H26>=1.5,"BB","B+")))))) -> BBB
A27: Telecom Italia | B27: =IF(J11<1,5,IF(J11<2,4,IF(J11<3,3,IF(J11<4,2,1)))) -> 3 | C27: =IF(K11>10,5,IF(K11>7,4,IF(K11>4,3,IF(K11>2,2,1)))) -> 2 | D27: =IF(L11>20,5,IF(L11>15,4,IF(L11>10,3,IF(L11>5,2,1)))) -> 2 | E27: =IF(M11<0.5,5,IF(M11<1,4,IF(M11<2,3,IF(M11<3,2,1)))) -> 4 | F27: =IF(N11>20,5,IF(N11>15,4,IF(N11>10,3,IF(N11>5,2,1)))) -> 3 | G27: =IF(O11>3,5,IF(O11>2,4,IF(O11>1.5,3,IF(O11>1,2,1)))) -> 2 | H27: =B27*0.25+C27*0.25+D27*0.2+E27*0.1+F27*0.15+G27*0.05 -> 2.6 | I27: =IF(H27>=4.5,"A",IF(H27>=3.8,"BBB+",IF(H27>=3.2,"BBB",IF(H27>=2.6,"BBB-",IF(H27>=2,"BB+",IF(H27>=1.5,"BB","B+")))))) -> BBB-
A28: Marks & Spencer | B28: =IF(J12<1,5,IF(J12<2,4,IF(J12<3,3,IF(J12<4,2,1)))) -> 3 | C28: =IF(K12>10,5,IF(K12>7,4,IF(K12>4,3,IF(K12>2,2,1)))) -> 3 | D28: =IF(L12>20,5,IF(L12>15,4,IF(L12>10,3,IF(L12>5,2,1)))) -> 3 | E28: =IF(M12<0.5,5,IF(M12<1,4,IF(M12<2,3,IF(M12<3,2,1)))) -> 3 | F28: =IF(N12>20,5,IF(N12>15,4,IF(N12>10,3,IF(N12>5,2,1)))) -> 2 | G28: =IF(O12>3,5,IF(O12>2,4,IF(O12>1.5,3,IF(O12>1,2,1)))) -> 2 | H28: =B28*0.25+C28*0.25+D28*0.2+E28*0.1+F28*0.15+G28*0.05 -> 2.8 | I28: =IF(H28>=4.5,"A",IF(H28>=3.8,"BBB+",IF(H28>=3.2,"BBB",IF(H28>=2.6,"BBB-",IF(H28>=2,"BB+",IF(H28>=1.5,"BB","B+")))))) -> BBB-
A29: Telefonica SA | B29: =IF(J13<1,5,IF(J13<2,4,IF(J13<3,3,IF(J13<4,2,1)))) -> 3 | C29: =IF(K13>10,5,IF(K13>7,4,IF(K13>4,3,IF(K13>2,2,1)))) -> 3 | D29: =IF(L13>20,5,IF(L13>15,4,IF(L13>10,3,IF(L13>5,2,1)))) -> 3 | E29: =IF(M13<0.5,5,IF(M13<1,4,IF(M13<2,3,IF(M13<3,2,1)))) -> 3 | F29: =IF(N13>20,5,IF(N13>15,4,IF(N13>10,3,IF(N13>5,2,1)))) -> 3 | G29: =IF(O13>3,5,IF(O13>2,4,IF(O13>1.5,3,IF(O13>1,2,1)))) -> 1 | H29: =B29*0.25+C29*0.25+D29*0.2+E29*0.1+F29*0.15+G29*0.05 -> 2.9 | I29: =IF(H29>=4.5,"A",IF(H29>=3.8,"BBB+",IF(H29>=3.2,"BBB",IF(H29>=2.6,"BBB-",IF(H29>=2,"BB+",IF(H29>=1.5,"BB","B+")))))) -> BBB-
A30: Carnival Corporation | B30: =IF(J14<1,5,IF(J14<2,4,IF(J14<3,3,IF(J14<4,2,1)))) -> 1 | C30: =IF(K14>10,5,IF(K14>7,4,IF(K14>4,3,IF(K14>2,2,1)))) -> 2 | D30: =IF(L14>20,5,IF(L14>15,4,IF(L14>10,3,IF(L14>5,2,1)))) -> 1 | E30: =IF(M14<0.5,5,IF(M14<1,4,IF(M14<2,3,IF(M14<3,2,1)))) -> 1 | F30: =IF(N14>20,5,IF(N14>15,4,IF(N14>10,3,IF(N14>5,2,1)))) -> 3 | G30: =IF(O14>3,5,IF(O14>2,4,IF(O14>1.5,3,IF(O14>1,2,1)))) -> 1 | H30: =B30*0.25+C30*0.25+D30*0.2+E30*0.1+F30*0.15+G30*0.05 -> 1.55 | I30: =IF(H30>=4.5,"A",IF(H30>=3.8,"BBB+",IF(H30>=3.2,"BBB",IF(H30>=2.6,"BBB-",IF(H30>=2,"BB+",IF(H30>=1.5,"BB","B+")))))) -> BB
A31: Kraft Heinz Company | B31: =IF(J15<1,5,IF(J15<2,4,IF(J15<3,3,IF(J15<4,2,1)))) -> 2 | C31: =IF(K15>10,5,IF(K15>7,4,IF(K15>4,3,IF(K15>2,2,1)))) -> 3 | D31: =IF(L15>20,5,IF(L15>15,4,IF(L15>10,3,IF(L15>5,2,1)))) -> 4 | E31: =IF(M15<0.5,5,IF(M15<1,4,IF(M15<2,3,IF(M15<3,2,1)))) -> 3 | F31: =IF(N15>20,5,IF(N15>15,4,IF(N15>10,3,IF(N15>5,2,1)))) -> 3 | G31: =IF(O15>3,5,IF(O15>2,4,IF(O15>1.5,3,IF(O15>1,2,1)))) -> 1 | H31: =B31*0.25+C31*0.25+D31*0.2+E31*0.1+F31*0.15+G31*0.05 -> 2.85 | I31: =IF(H31>=4.5,"A",IF(H31>=3.8,"BBB+",IF(H31>=3.2,"BBB",IF(H31>=2.6,"BBB-",IF(H31>=2,"BB+",IF(H31>=1.5,"BB","B+")))))) -> BBB-
A32: Bombardier Inc | B32: =IF(J16<1,5,IF(J16<2,4,IF(J16<3,3,IF(J16<4,2,1)))) -> 2 | C32: =IF(K16>10,5,IF(K16>7,4,IF(K16>4,3,IF(K16>2,2,1)))) -> 2 | D32: =IF(L16>20,5,IF(L16>15,4,IF(L16>10,3,IF(L16>5,2,1)))) -> 2 | E32: =IF(M16<0.5,5,IF(M16<1,4,IF(M16<2,3,IF(M16<3,2,1)))) -> 1 | F32: =IF(N16>20,5,IF(N16>15,4,IF(N16>10,3,IF(N16>5,2,1)))) -> 3 | G32: =IF(O16>3,5,IF(O16>2,4,IF(O16>1.5,3,IF(O16>1,2,1)))) -> 2 | H32: =B32*0.25+C32*0.25+D32*0.2+E32*0.1+F32*0.15+G32*0.05 -> 2.05 | I32: =IF(H32>=4.5,"A",IF(H32>=3.8,"BBB+",IF(H32>=3.2,"BBB",IF(H32>=2.6,"BBB-",IF(H32>=2,"BB+",IF(H32>=1.5,"BB","B+")))))) -> BB+
A33: Coty Inc | B33: =IF(J17<1,5,IF(J17<2,4,IF(J17<3,3,IF(J17<4,2,1)))) -> 1 | C33: =IF(K17>10,5,IF(K17>7,4,IF(K17>4,3,IF(K17>2,2,1)))) -> 2 | D33: =IF(L17>20,5,IF(L17>15,4,IF(L17>10,3,IF(L17>5,2,1)))) -> 2 | E33: =IF(M17<0.5,5,IF(M17<1,4,IF(M17<2,3,IF(M17<3,2,1)))) -> 1 | F33: =IF(N17>20,5,IF(N17>15,4,IF(N17>10,3,IF(N17>5,2,1)))) -> 2 | G33: =IF(O17>3,5,IF(O17>2,4,IF(O17>1.5,3,IF(O17>1,2,1)))) -> 1 | H33: =B33*0.25+C33*0.25+D33*0.2+E33*0.1+F33*0.15+G33*0.05 -> 1.6 | I33: =IF(H33>=4.5,"A",IF(H33>=3.8,"BBB+",IF(H33>=3.2,"BBB",IF(H33>=2.6,"BBB-",IF(H33>=2,"BB+",IF(H33>=1.5,"BB","B+")))))) -> BB
A35: SECTION 3 — SHADOW RATING CONVERSION TABLE
A36: Score Range | B36: Shadow Rating | C36: Interpretation | D36: IG / HY
A37: 4.50 – 5.00 | B37: A | C37: Very strong credit, minimal default risk | D37: Investment Grade
A38: 3.80 – 4.49 | B38: BBB+ | C38: Strong credit, low default risk | D38: Investment Grade
A39: 3.20 – 3.79 | B39: BBB | C39: Adequate protection, some vulnerability | D39: Investment Grade
A40: 2.60 – 3.19 | B40: BBB- | C40: Lower medium grade, crossover risk | D40: Investment Grade / Crossover
A41: 2.00 – 2.59 | B41: BB+ | C41: Speculative, less vulnerable | D41: High Yield / Crossover
A42: 1.50 – 1.99 | B42: BB | C42: Speculative, facing ongoing uncertainties | D42: High Yield
A43: 1.00 – 1.49 | B43: B+ | C43: Speculative, more vulnerable to adverse conditions | D43: High Yield
A45: SECTION 4 — RATING COMPARISON: SHADOW vs. AGENCY RATINGS
A46: Company | B46: Shadow Rating | C46: S&P Rating | D46: Moody's Rating | E46: S&P Notches Diff | F46: Moody's Notches Diff | G46: Flag | K46: Rating | L46: Numeric
A47: Microsoft Corp | B47: =I22 -> A | C47: ='Credit Universe'!E5 -> AA- | D47: ='Credit Universe'!F5 -> Aa2 | E47: =IF(OR(C47="",B47=""),"N/A",IFERROR(VLOOKUP(B47,$K$46:$L$67,2,FALSE)-VLOOKUP(C47,$K$46:$L$67,2,FALSE),"N/A")) -> -2 | F47: =IF(OR(D47="",B47=""),"N/A",IFERROR(VLOOKUP(B47,$K$46:$L$67,2,FALSE)-VLOOKUP(D47,$K$46:$L$67,2,FALSE),"N/A")) -> N/A | G47: =IF(OR(E47="N/A",F47="N/A"),"",IF(OR(ABS(E47)>=2,ABS(F47)>=2),"⚑ INVESTIGATE","")) | K47: AA+ | L47: 21
A48: Johnson & Johnson | B48: =I23 -> A | C48: ='Credit Universe'!E6 -> AA- | D48: ='Credit Universe'!F6 -> Aa3 | E48: =IF(OR(C48="",B48=""),"N/A",IFERROR(VLOOKUP(B48,$K$46:$L$67,2,FALSE)-VLOOKUP(C48,$K$46:$L$67,2,FALSE),"N/A")) -> -2 | F48: =IF(OR(D48="",B48=""),"N/A",IFERROR(VLOOKUP(B48,$K$46:$L$67,2,FALSE)-VLOOKUP(D48,$K$46:$L$67,2,FALSE),"N/A")) -> N/A | G48: =IF(OR(E48="N/A",F48="N/A"),"",IF(OR(ABS(E48)>=2,ABS(F48)>=2),"⚑ INVESTIGATE","")) | K48: AA | L48: 20
A49: Vodafone Group | B49: =I24 -> BBB- | C49: ='Credit Universe'!E7 -> BBB | D49: ='Credit Universe'!F7 -> Baa2 | E49: =IF(OR(C49="",B49=""),"N/A",IFERROR(VLOOKUP(B49,$K$46:$L$67,2,FALSE)-VLOOKUP(C49,$K$46:$L$67,2,FALSE),"N/A")) -> -1 | F49: =IF(OR(D49="",B49=""),"N/A",IFERROR(VLOOKUP(B49,$K$46:$L$67,2,FALSE)-VLOOKUP(D49,$K$46:$L$67,2,FALSE),"N/A")) -> N/A | G49: =IF(OR(E49="N/A",F49="N/A"),"",IF(OR(ABS(E49)>=2,ABS(F49)>=2),"⚑ INVESTIGATE","")) | K49: AA- | L49: 19
A50: Rolls-Royce Holdings | B50: =I25 -> A | C50: ='Credit Universe'!E8 -> BBB- | D50: ='Credit Universe'!F8 -> Baa3 | E50: =IF(OR(C50="",B50=""),"N/A",IFERROR(VLOOKUP(B50,$K$46:$L$67,2,FALSE)-VLOOKUP(C50,$K$46:$L$67,2,FALSE),"N/A")) -> 4 | F50: =IF(OR(D50="",B50=""),"N/A",IFERROR(VLOOKUP(B50,$K$46:$L$67,2,FALSE)-VLOOKUP(D50,$K$46:$L$67,2,FALSE),"N/A")) -> N/A | G50: =IF(OR(E50="N/A",F50="N/A"),"",IF(OR(ABS(E50)>=2,ABS(F50)>=2),"⚑ INVESTIGATE","")) | K50: A+ | L50: 18
A51: Ford Motor Company | B51: =I26 -> BBB | C51: ='Credit Universe'!E9 -> BB+ | D51: ='Credit Universe'!F9 -> Ba1 | E51: =IF(OR(C51="",B51=""),"N/A",IFERROR(VLOOKUP(B51,$K$46:$L$67,2,FALSE)-VLOOKUP(C51,$K$46:$L$67,2,FALSE),"N/A")) -> 2 | F51: =IF(OR(D51="",B51=""),"N/A",IFERROR(VLOOKUP(B51,$K$46:$L$67,2,FALSE)-VLOOKUP(D51,$K$46:$L$67,2,FALSE),"N/A")) -> N/A | G51: =IF(OR(E51="N/A",F51="N/A"),"",IF(OR(ABS(E51)>=2,ABS(F51)>=2),"⚑ INVESTIGATE","")) | K51: A | L51: 17
A52: Telecom Italia | B52: =I27 -> BBB- | C52: ='Credit Universe'!E10 -> BB | D52: ='Credit Universe'!F10 -> Ba2 | E52: =IF(OR(C52="",B52=""),"N/A",IFERROR(VLOOKUP(B52,$K$46:$L$67,2,FALSE)-VLOOKUP(C52,$K$46:$L$67,2,FALSE),"N/A")) -> 2 | F52: =IF(OR(D52="",B52=""),"N/A",IFERROR(VLOOKUP(B52,$K$46:$L$67,2,FALSE)-VLOOKUP(D52,$K$46:$L$67,2,FALSE),"N/A")) -> N/A | G52: =IF(OR(E52="N/A",F52="N/A"),"",IF(OR(ABS(E52)>=2,ABS(F52)>=2),"⚑ INVESTIGATE","")) | K52: A- | L52: 16
A53: Marks & Spencer | B53: =I28 -> BBB- | C53: ='Credit Universe'!E11 -> BBB- | D53: ='Credit Universe'!F11 -> Baa3 | E53: =IF(OR(C53="",B53=""),"N/A",IFERROR(VLOOKUP(B53,$K$46:$L$67,2,FALSE)-VLOOKUP(C53,$K$46:$L$67,2,FALSE),"N/A")) -> 0 | F53: =IF(OR(D53="",B53=""),"N/A",IFERROR(VLOOKUP(B53,$K$46:$L$67,2,FALSE)-VLOOKUP(D53,$K$46:$L$67,2,FALSE),"N/A")) -> N/A | G53: =IF(OR(E53="N/A",F53="N/A"),"",IF(OR(ABS(E53)>=2,ABS(F53)>=2),"⚑ INVESTIGATE","")) | K53: BBB+ | L53: 15
A54: Telefonica SA | B54: =I29 -> BBB- | C54: ='Credit Universe'!E12 -> BBB- | D54: ='Credit Universe'!F12 -> Baa3 | E54: =IF(OR(C54="",B54=""),"N/A",IFERROR(VLOOKUP(B54,$K$46:$L$67,2,FALSE)-VLOOKUP(C54,$K$46:$L$67,2,FALSE),"N/A")) -> 0 | F54: =IF(OR(D54="",B54=""),"N/A",IFERROR(VLOOKUP(B54,$K$46:$L$67,2,FALSE)-VLOOKUP(D54,$K$46:$L$67,2,FALSE),"N/A")) -> N/A | G54: =IF(OR(E54="N/A",F54="N/A"),"",IF(OR(ABS(E54)>=2,ABS(F54)>=2),"⚑ INVESTIGATE","")) | K54: BBB | L54: 14
A55: Carnival Corporation | B55: =I30 -> BB | C55: ='Credit Universe'!E13 -> B+ | D55: ='Credit Universe'!F13 -> B1 | E55: =IF(OR(C55="",B55=""),"N/A",IFERROR(VLOOKUP(B55,$K$46:$L$67,2,FALSE)-VLOOKUP(C55,$K$46:$L$67,2,FALSE),"N/A")) -> 2 | F55: =IF(OR(D55="",B55=""),"N/A",IFERROR(VLOOKUP(B55,$K$46:$L$67,2,FALSE)-VLOOKUP(D55,$K$46:$L$67,2,FALSE),"N/A")) -> N/A | G55: =IF(OR(E55="N/A",F55="N/A"),"",IF(OR(ABS(E55)>=2,ABS(F55)>=2),"⚑ INVESTIGATE","")) | K55: BBB- | L55: 13
A56: Kraft Heinz Company | B56: =I31 -> BBB- | C56: ='Credit Universe'!E14 -> BBB- | D56: ='Credit Universe'!F14 -> Baa3 | E56: =IF(OR(C56="",B56=""),"N/A",IFERROR(VLOOKUP(B56,$K$46:$L$67,2,FALSE)-VLOOKUP(C56,$K$46:$L$67,2,FALSE),"N/A")) -> 0 | F56: =IF(OR(D56="",B56=""),"N/A",IFERROR(VLOOKUP(B56,$K$46:$L$67,2,FALSE)-VLOOKUP(D56,$K$46:$L$67,2,FALSE),"N/A")) -> N/A | G56: =IF(OR(E56="N/A",F56="N/A"),"",IF(OR(ABS(E56)>=2,ABS(F56)>=2),"⚑ INVESTIGATE","")) | K56: BB+ | L56: 12
A57: Bombardier Inc | B57: =I32 -> BB+ | C57: ='Credit Universe'!E15 -> B | D57: ='Credit Universe'!F15 -> B2 | E57: =IF(OR(C57="",B57=""),"N/A",IFERROR(VLOOKUP(B57,$K$46:$L$67,2,FALSE)-VLOOKUP(C57,$K$46:$L$67,2,FALSE),"N/A")) -> 4 | F57: =IF(OR(D57="",B57=""),"N/A",IFERROR(VLOOKUP(B57,$K$46:$L$67,2,FALSE)-VLOOKUP(D57,$K$46:$L$67,2,FALSE),"N/A")) -> N/A | G57: =IF(OR(E57="N/A",F57="N/A"),"",IF(OR(ABS(E57)>=2,ABS(F57)>=2),"⚑ INVESTIGATE","")) | K57: BB | L57: 11
A58: Coty Inc | B58: =I33 -> BB | C58: ='Credit Universe'!E16 -> B | D58: ='Credit Universe'!F16 -> B2 | E58: =IF(OR(C58="",B58=""),"N/A",IFERROR(VLOOKUP(B58,$K$46:$L$67,2,FALSE)-VLOOKUP(C58,$K$46:$L$67,2,FALSE),"N/A")) -> 3 | F58: =IF(OR(D58="",B58=""),"N/A",IFERROR(VLOOKUP(B58,$K$46:$L$67,2,FALSE)-VLOOKUP(D58,$K$46:$L$67,2,FALSE),"N/A")) -> N/A | G58: =IF(OR(E58="N/A",F58="N/A"),"",IF(OR(ABS(E58)>=2,ABS(F58)>=2),"⚑ INVESTIGATE","")) | K58: BB- | L58: 10
K59: B+ | L59: 9
A60: KEY ASSUMPTIONS (Named Ranges) | K60: B | L60: 8
A61: Named Range | B61: Value | C61: Description | K61: B- | L61: 7
A62: CovenantThreshold | B62: 5 | C62: Net Debt/EBITDA covenant threshold for HY issuers | K62: CCC+ | L62: 6
A63: DistressMultiple | B63: 5 | C63: EV/EBITDA multiple used in distress recovery analysis | K63: CCC | L63: 5
A64: NewIssuePremium | B64: 22.5 | C64: New issue concession/premium (bps) added to fair value spread | K64: CCC- | L64: 4
A65: RiskFreeRate | B65: 4.5 | C65: Base risk-free rate assumption (%) — update with current UST 10Y | K65: CC | L65: 3
K66: C | L66: 2
A67: SCORING THRESHOLDS REFERENCE (for manual verification) | K67: D | L67: 1
A68: Score | B68: Net Debt/EBITDA | C68: EBITDA/Interest | D68: FCF/Debt (%) | E68: EBIT Margin (%) | F68: Liquidity (Cash/ST Debt)
A69: 5 | B69: < 1.0x | C69: > 10.0x | D69: > 20% | E69: > 20% | F69: > 3.0x
A70: 4 | B70: 1.0 – 2.0x | C70: 7.0 – 10.0x | D70: 15 – 20% | E70: 15 – 20% | F70: 2.0 – 3.0x
A71: 3 | B71: 2.0 – 3.0x | C71: 4.0 – 7.0x | D71: 10 – 15% | E71: 10 – 15% | F71: 1.5 – 2.0x
A72: 2 | B72: 3.0 – 4.0x | C72: 2.0 – 4.0x | D72: 5 – 10% | E72: 5 – 10% | F72: 1.0 – 1.5x
A73: 1 | B73: > 4.0x | C73: < 2.0x | D73: < 5% | E73: < 5% | F73: < 1.0x

Sheet Spread Analysis
A1: SPREAD ANALYSIS & FAIR VALUE ESTIMATION
A2: Rating/maturity-adjusted fair value spreads, sector/issuer adjustments, mispricing analysis, and top 3 trade ideas
A4: SECTION 1 — SPREAD REFERENCE GRID (bps) — Fill from Bloomberg/ICE BofA indices | Yellow = user input
A5: Shadow Rating | B5: 0–3 Year (bps) | C5: 3–7 Year (bps) | D5: 7+ Year (bps)
A6: A | B6: 65 | C6: 80 | D6: 95
A7: BBB+ | B7: 95 | C7: 115 | D7: 135
A8: BBB | B8: 125 | C8: 150 | D8: 175
A9: BBB- | B9: 165 | C9: 195 | D9: 225
A10: BB+ | B10: 225 | C10: 265 | D10: 300
A11: BB | B11: 310 | C11: 360 | D11: 410
A12: B+ | B12: 450 | C12: 520 | D12: 590
A14: SECTION 2 — FAIR VALUE SPREAD CALCULATION PER ISSUER
A15: Company | B15: Shadow Rating | C15: Bond Maturity (yrs) | D15: Maturity Bucket | E15: Grid Spread (bps) | F15: Sector Adj (bps) | G15: Issuer Adj (bps) | H15: FV Spread (bps) | J15: FV Spread (linked to Credit Universe)
A16: Microsoft Corp | B16: ='Credit Scoring'!I22 -> A | C16: 5 | D16: =IF(C16<=3,"0-3yr",IF(C16<=7,"3-7yr","7+yr")) -> 3-7yr | E16: =IFERROR(IF(D16="0-3yr",VLOOKUP(B16,$A$6:$D$12,2,FALSE),IF(D16="3-7yr",VLOOKUP(B16,$A$6:$D$12,3,FALSE),VLOOKUP(B16,$A$6:$D$12,4,FALSE))),"N/A") -> 80 | F16: -5 | G16: -10 | H16: =IF(E16="N/A","N/A",E16+F16+G16) -> 65 | J16: =H16 -> 65
A17: Johnson & Johnson | B17: ='Credit Scoring'!I23 -> A | C17: 7 | D17: =IF(C17<=3,"0-3yr",IF(C17<=7,"3-7yr","7+yr")) -> 3-7yr | E17: =IFERROR(IF(D17="0-3yr",VLOOKUP(B17,$A$6:$D$12,2,FALSE),IF(D17="3-7yr",VLOOKUP(B17,$A$6:$D$12,3,FALSE),VLOOKUP(B17,$A$6:$D$12,4,FALSE))),"N/A") -> 80 | F17: -5 | G17: -5 | H17: =IF(E17="N/A","N/A",E17+F17+G17) -> 70 | J17: =H17 -> 70
A18: Vodafone Group | B18: ='Credit Scoring'!I24 -> BBB- | C18: 8 | D18: =IF(C18<=3,"0-3yr",IF(C18<=7,"3-7yr","7+yr")) -> 7+yr | E18: =IFERROR(IF(D18="0-3yr",VLOOKUP(B18,$A$6:$D$12,2,FALSE),IF(D18="3-7yr",VLOOKUP(B18,$A$6:$D$12,3,FALSE),VLOOKUP(B18,$A$6:$D$12,4,FALSE))),"N/A") -> 225 | F18: 10 | G18: 15 | H18: =IF(E18="N/A","N/A",E18+F18+G18) -> 250 | J18: =H18 -> 250
A19: Rolls-Royce Holdings | B19: ='Credit Scoring'!I25 -> A | C19: 6 | D19: =IF(C19<=3,"0-3yr",IF(C19<=7,"3-7yr","7+yr")) -> 3-7yr | E19: =IFERROR(IF(D19="0-3yr",VLOOKUP(B19,$A$6:$D$12,2,FALSE),IF(D19="3-7yr",VLOOKUP(B19,$A$6:$D$12,3,FALSE),VLOOKUP(B19,$A$6:$D$12,4,FALSE))),"N/A") -> 80 | F19: 5 | G19: -5 | H19: =IF(E19="N/A","N/A",E19+F19+G19) -> 80 | J19: =H19 -> 80
A20: Ford Motor Company | B20: ='Credit Scoring'!I26 -> BBB | C20: 4 | D20: =IF(C20<=3,"0-3yr",IF(C20<=7,"3-7yr","7+yr")) -> 3-7yr | E20: =IFERROR(IF(D20="0-3yr",VLOOKUP(B20,$A$6:$D$12,2,FALSE),IF(D20="3-7yr",VLOOKUP(B20,$A$6:$D$12,3,FALSE),VLOOKUP(B20,$A$6:$D$12,4,FALSE))),"N/A") -> 150 | F20: 20 | G20: 25 | H20: =IF(E20="N/A","N/A",E20+F20+G20) -> 195 | J20: =H20 -> 195
A21: Telecom Italia | B21: ='Credit Scoring'!I27 -> BBB- | C21: 7 | D21: =IF(C21<=3,"0-3yr",IF(C21<=7,"3-7yr","7+yr")) -> 3-7yr | E21: =IFERROR(IF(D21="0-3yr",VLOOKUP(B21,$A$6:$D$12,2,FALSE),IF(D21="3-7yr",VLOOKUP(B21,$A$6:$D$12,3,FALSE),VLOOKUP(B21,$A$6:$D$12,4,FALSE))),"N/A") -> 195 | F21: 10 | G21: 30 | H21: =IF(E21="N/A","N/A",E21+F21+G21) -> 235 | J21: =H21 -> 235
A22: Marks & Spencer | B22: ='Credit Scoring'!I28 -> BBB- | C22: 5 | D22: =IF(C22<=3,"0-3yr",IF(C22<=7,"3-7yr","7+yr")) -> 3-7yr | E22: =IFERROR(IF(D22="0-3yr",VLOOKUP(B22,$A$6:$D$12,2,FALSE),IF(D22="3-7yr",VLOOKUP(B22,$A$6:$D$12,3,FALSE),VLOOKUP(B22,$A$6:$D$12,4,FALSE))),"N/A") -> 195 | F22: 10 | G22: 5 | H22: =IF(E22="N/A","N/A",E22+F22+G22) -> 210 | J22: =H22 -> 210
A23: Telefonica SA | B23: ='Credit Scoring'!I29 -> BBB- | C23: 8 | D23: =IF(C23<=3,"0-3yr",IF(C23<=7,"3-7yr","7+yr")) -> 7+yr | E23: =IFERROR(IF(D23="0-3yr",VLOOKUP(B23,$A$6:$D$12,2,FALSE),IF(D23="3-7yr",VLOOKUP(B23,$A$6:$D$12,3,FALSE),VLOOKUP(B23,$A$6:$D$12,4,FALSE))),"N/A") -> 225 | F23: 10 | G23: 10 | H23: =IF(E23="N/A","N/A",E23+F23+G23) -> 245 | J23: =H23 -> 245
A24: Carnival Corporation | B24: ='Credit Scoring'!I30 -> BB | C24: 7 | D24: =IF(C24<=3,"0-3yr",IF(C24<=7,"3-7yr","7+yr")) -> 3-7yr | E24: =IFERROR(IF(D24="0-3yr",VLOOKUP(B24,$A$6:$D$12,2,FALSE),IF(D24="3-7yr",VLOOKUP(B24,$A$6:$D$12,3,FALSE),VLOOKUP(B24,$A$6:$D$12,4,FALSE))),"N/A") -> 360 | F24: 25 | G24: 20 | H24: =IF(E24="N/A","N/A",E24+F24+G24) -> 405 | J24: =H24 -> 405
A25: Kraft Heinz Company | B25: ='Credit Scoring'!I31 -> BBB- | C25: 6 | D25: =IF(C25<=3,"0-3yr",IF(C25<=7,"3-7yr","7+yr")) -> 3-7yr | E25: =IFERROR(IF(D25="0-3yr",VLOOKUP(B25,$A$6:$D$12,2,FALSE),IF(D25="3-7yr",VLOOKUP(B25,$A$6:$D$12,3,FALSE),VLOOKUP(B25,$A$6:$D$12,4,FALSE))),"N/A") -> 195 | F25: 5 | G25: 15 | H25: =IF(E25="N/A","N/A",E25+F25+G25) -> 215 | J25: =H25 -> 215
A26: Bombardier Inc | B26: ='Credit Scoring'!I32 -> BB+ | C26: 5 | D26: =IF(C26<=3,"0-3yr",IF(C26<=7,"3-7yr","7+yr")) -> 3-7yr | E26: =IFERROR(IF(D26="0-3yr",VLOOKUP(B26,$A$6:$D$12,2,FALSE),IF(D26="3-7yr",VLOOKUP(B26,$A$6:$D$12,3,FALSE),VLOOKUP(B26,$A$6:$D$12,4,FALSE))),"N/A") -> 265 | F26: 5 | G26: 35 | H26: =IF(E26="N/A","N/A",E26+F26+G26) -> 305 | J26: =H26 -> 305
A27: Coty Inc | B27: ='Credit Scoring'!I33 -> BB | C27: 5 | D27: =IF(C27<=3,"0-3yr",IF(C27<=7,"3-7yr","7+yr")) -> 3-7yr | E27: =IFERROR(IF(D27="0-3yr",VLOOKUP(B27,$A$6:$D$12,2,FALSE),IF(D27="3-7yr",VLOOKUP(B27,$A$6:$D$12,3,FALSE),VLOOKUP(B27,$A$6:$D$12,4,FALSE))),"N/A") -> 360 | F27: 5 | G27: 20 | H27: =IF(E27="N/A","N/A",E27+F27+G27) -> 385 | J27: =H27 -> 385
A29: SECTION 3 — MISPRICING ANALYSIS
A30: Company | B30: Mkt Spread (bps) | C30: FV Spread (bps) | D30: Diff (bps) | E30: Magnitude | F30: Direction
A31: Microsoft Corp | B31: ='Credit Universe'!N5 -> -104.32099 | C31: =H16 -> 65 | D31: =IF(OR(B31="",C31="","N/A"),"",B31-C31) -> -169.32099 | E31: =IF(D31="","",IF(ABS(D31)>30,"Significant",IF(ABS(D31)>15,"Moderate","Marginal"))) -> Significant | F31: =IF(D31="","",IF(D31>15,"Too Wide",IF(D31<-15,"Too Tight","Fair"))) -> Too Tight
A32: Johnson & Johnson | B32: ='Credit Universe'!N6 -> -116.99314 | C32: =H17 -> 70 | D32: =IF(OR(B32="",C32="","N/A"),"",B32-C32) -> -186.99314 | E32: =IF(D32="","",IF(ABS(D32)>30,"Significant",IF(ABS(D32)>15,"Moderate","Marginal"))) -> Significant | F32: =IF(D32="","",IF(D32>15,"Too Wide",IF(D32<-15,"Too Tight","Fair"))) -> Too Tight
A33: Vodafone Group | B33: ='Credit Universe'!N7 -> 90.471204 | C33: =H18 -> 250 | D33: =IF(OR(B33="",C33="","N/A"),"",B33-C33) -> -159.5288 | E33: =IF(D33="","",IF(ABS(D33)>30,"Significant",IF(ABS(D33)>15,"Moderate","Marginal"))) -> Significant | F33: =IF(D33="","",IF(D33>15,"Too Wide",IF(D33<-15,"Too Tight","Fair"))) -> Too Tight
A34: Rolls-Royce Holdings | B34: ='Credit Universe'!N8 -> 159.34509 | C34: =H19 -> 80 | D34: =IF(OR(B34="",C34="","N/A"),"",B34-C34) -> 79.345088 | E34: =IF(D34="","",IF(ABS(D34)>30,"Significant",IF(ABS(D34)>15,"Moderate","Marginal"))) -> Significant | F34: =IF(D34="","",IF(D34>15,"Too Wide",IF(D34<-15,"Too Tight","Fair"))) -> Too Wide
A35: Ford Motor Company | B35: ='Credit Universe'!N9 -> 213.04348 | C35: =H20 -> 195 | D35: =IF(OR(B35="",C35="","N/A"),"",B35-C35) -> 18.043478 | E35: =IF(D35="","",IF(ABS(D35)>30,"Significant",IF(ABS(D35)>15,"Moderate","Marginal"))) -> Moderate | F35: =IF(D35="","",IF(D35>15,"Too Wide",IF(D35<-15,"Too Tight","Fair"))) -> Too Wide
A36: Telecom Italia | B36: ='Credit Universe'!N10 -> 213.22034 | C36: =H21 -> 235 | D36: =IF(OR(B36="",C36="","N/A"),"",B36-C36) -> -21.779661 | E36: =IF(D36="","",IF(ABS(D36)>30,"Significant",IF(ABS(D36)>15,"Moderate","Marginal"))) -> Moderate | F36: =IF(D36="","",IF(D36>15,"Too Wide",IF(D36<-15,"Too Tight","Fair"))) -> Too Tight
A37: Marks & Spencer | B37: ='Credit Universe'!N11 -> 42.724936 | C37: =H22 -> 210 | D37: =IF(OR(B37="",C37="","N/A"),"",B37-C37) -> -167.27506 | E37: =IF(D37="","",IF(ABS(D37)>30,"Significant",IF(ABS(D37)>15,"Moderate","Marginal"))) -> Significant | F37: =IF(D37="","",IF(D37>15,"Too Wide",IF(D37<-15,"Too Tight","Fair"))) -> Too Tight
A38: Telefonica SA | B38: ='Credit Universe'!N12 -> 140.74468 | C38: =H23 -> 245 | D38: =IF(OR(B38="",C38="","N/A"),"",B38-C38) -> -104.25532 | E38: =IF(D38="","",IF(ABS(D38)>30,"Significant",IF(ABS(D38)>15,"Moderate","Marginal"))) -> Significant | F38: =IF(D38="","",IF(D38>15,"Too Wide",IF(D38<-15,"Too Tight","Fair"))) -> Too Tight
A39: Carnival Corporation | B39: ='Credit Universe'!N13 -> 441.81287 | C39: =H24 -> 405 | D39: =IF(OR(B39="",C39="","N/A"),"",B39-C39) -> 36.812865 | E39: =IF(D39="","",IF(ABS(D39)>30,"Significant",IF(ABS(D39)>15,"Moderate","Marginal"))) -> Significant | F39: =IF(D39="","",IF(D39>15,"Too Wide",IF(D39<-15,"Too Tight","Fair"))) -> Too Wide
A40: Kraft Heinz Company | B40: ='Credit Universe'!N14 -> 86.193029 | C40: =H25 -> 215 | D40: =IF(OR(B40="",C40="","N/A"),"",B40-C40) -> -128.80697 | E40: =IF(D40="","",IF(ABS(D40)>30,"Significant",IF(ABS(D40)>15,"Moderate","Marginal"))) -> Significant | F40: =IF(D40="","",IF(D40>15,"Too Wide",IF(D40<-15,"Too Tight","Fair"))) -> Too Tight
A41: Bombardier Inc | B41: ='Credit Universe'!N15 -> 510.36585 | C41: =H26 -> 305 | D41: =IF(OR(B41="",C41="","N/A"),"",B41-C41) -> 205.36585 | E41: =IF(D41="","",IF(ABS(D41)>30,"Significant",IF(ABS(D41)>15,"Moderate","Marginal"))) -> Significant | F41: =IF(D41="","",IF(D41>15,"Too Wide",IF(D41<-15,"Too Tight","Fair"))) -> Too Wide
A42: Coty Inc | B42: ='Credit Universe'!N16 -> 378.02548 | C42: =H27 -> 385 | D42: =IF(OR(B42="",C42="","N/A"),"",B42-C42) -> -6.9745223 | E42: =IF(D42="","",IF(ABS(D42)>30,"Significant",IF(ABS(D42)>15,"Moderate","Marginal"))) -> Marginal | F42: =IF(D42="","",IF(D42>15,"Too Wide",IF(D42<-15,"Too Tight","Fair"))) -> Fair
A44: SECTION 4 — TOP 3 MISPRICED BONDS: CREDIT VIEW & TRADE THESIS
A45: TRADE 1: BOMBARDIER INC — TOO WIDE | BUY | BB-rated bonds trading ~70-110bps through fair value
A46: Signal: | B46: Too Wide — market over-discounting legacy balance sheet risk | C46: Direction: | D46: OUTPERFORM — expect 60-100 bps tightening over 12-18 months
A47: Shadow Rating: | B47: BB | C47: Market Spread (est.): | D47: 380–420 bps
A48: Fair Value Spread: | B48: ~310 bps | C48: Mispricing (bps): | D48: ~70–110 bps wide
A49: Credit View: | B49: Bombardier has completed a dramatic deleveraging story, exiting commercial aviation and rail to focus on business jets — a high-margin, capital-light model with strong order backlogs. Net Debt/EBITDA has declined from >9x to approximately 4.5x and is on a clear downward trajectory with strong FCF generation. The market continues to price in legacy balance sheet risk that is structurally diminishing. Catalyst: further debt paydown and potential upgrade to BB+ over 12-18 months would compress spreads 60-100 bps.
A51: TRADE 2: TELECOM ITALIA — TOO WIDE | SELECTIVE BUY on short-dated paper | BB bonds 60-120bps wide
A52: Signal: | B52: Too Wide — sovereign contagion and restructuring execution risk over-priced in short end | C52: Direction: | D52: SELECTIVE BUY — short-dated 2026-2027 bonds; avoid long-dated
A53: Shadow Rating: | B53: BB | C53: Market Spread (est.): | D53: 420–480 bps
A54: Fair Value Spread: | B54: ~360 bps | C54: Mispricing (bps): | D54: ~60–120 bps wide
A55: Credit View: | B55: The sale of Telecom Italia's fixed-line network to KKR-backed NetCo, completed in 2024, structurally transformed the credit by removing its most capital-intensive segment. The remaining ServiceCo has lower debt, cleaner cash flows, and exposure to higher-margin enterprise and mobile. Market spreads remain elevated due to Italian sovereign contagion and execution uncertainty, but short-dated bonds over-compensate for that risk. Catalyst: improving ServiceCo operating momentum, potential Moody's rating stabilisation, and Italian sovereign spread compression.
A57: TRADE 3: KRAFT HEINZ — TOO WIDE | RELATIVE VALUE BUY vs. consumer staples peers | BBB- bonds 20-55bps wide
A58: Signal: | B58: Too Wide — excessive brand erosion and volume decline risk priced in relative to actual fundamentals | C58: Direction: | D58: RELATIVE VALUE BUY — prefer vs. Coty, Carnival on risk-adjusted basis
A59: Shadow Rating: | B59: BBB- | C59: Market Spread (est.): | D59: 195–230 bps
A60: Fair Value Spread: | B60: ~175 bps | C60: Mispricing (bps): | D60: ~20–55 bps wide
A61: Credit View: | B61: Kraft Heinz trades at a meaningful spread premium to comparably-rated consumer staples peers (Mondelez, Conagra), reflecting market concerns about secular volume declines and the $15bn 2019 goodwill impairment overhang. However, the credit has stabilised: Net Debt/EBITDA has declined from 4.5x to ~3.5x, FCF generation is consistently $2.5-3bn annually, and the bond portfolio is well-laddered with no near-term refinancing pressure. Catalyst: incremental debt paydown and a potential Moody's upgrade from Baa3 to Baa2 would compress spreads 30-50 bps.

Sheet Scenario Analysis
A1: SCENARIO ANALYSIS & STRESS TESTING
A2: Base / Stress / Severe stress scenarios — shadow rating migration, key ratios, distance to distress
A3: Scenarios: Base = current financials | Stress = EBITDA −20%, Debt unchanged | Severe = EBITDA −35%, Debt +10% | Covenant threshold: Net Debt/EBITDA 5.0x
B4: BASE CASE | G4: STRESS (EBITDA -20%) | L4: SEVERE (EBITDA -35%, DEBT +10%) | Q4: DISTANCE TO DISTRESS
A5: Company | B5: Base ND/EBITDA | C5: Base Coverage | D5: Base FCF/Debt% | E5: Base Score | F5: Base Rating | G5: Stress ND/EBITDA | H5: Stress Coverage | I5: Stress FCF/Debt% | J5: Stress Score | K5: Stress Rating | L5: Severe ND/EBITDA | M5: Severe Coverage | N5: Severe FCF/Debt% | O5: Severe Score | P5: Severe Rating | Q5: Dist. to Distress (x) | R5: Distress Flag
A6: Microsoft Corp | B6: =('Credit Scoring'!E6-'Credit Scoring'!F6)/'Credit Scoring'!C6 -> 0.46963874 | C6: =IF('Credit Scoring'!G6=0,"N/A",'Credit Scoring'!C6/'Credit Scoring'!G6) -> 68.473684 | D6: =IF('Credit Scoring'!E6=0,"N/A",'Credit Scoring'!I6/'Credit Scoring'!E6*100) -> 93.324937 | E6: ='Credit Scoring'!H22 -> 4.85 | F6: ='Credit Scoring'!I22 -> A | G6: =('Credit Scoring'!E6-'Credit Scoring'!F6)/('Credit Scoring'!C6*0.8) -> 0.58704842 | H6: =IF('Credit Scoring'!G6=0,"N/A",('Credit Scoring'!C6*0.8)/'Credit Scoring'!G6) -> 54.778947 | I6: =IF('Credit Scoring'!E6=0,"N/A",('Credit Scoring'!I6*0.8)/'Credit Scoring'!E6*100) -> 74.65995 | J6: =IF(G6<1,5,IF(G6<2,4,IF(G6<3,3,IF(G6<4,2,1))))*0.25+IF(H6>10,5,IF(H6>7,4,IF(H6>4,3,IF(H6>2,2,1))))*0.25+IF(I6>20,5,IF(I6>15,4,IF(I6>10,3,IF(I6>5,2,1))))*0.2+'Credit Scoring'!E22*0.1+'Credit Scoring'!F22*0.15+'Credit Scoring'!G22*0.05 -> 4.85 | K6: =IF(J6>=4.5,"A",IF(J6>=3.8,"BBB+",IF(J6>=3.2,"BBB",IF(J6>=2.6,"BBB-",IF(J6>=2,"BB+",IF(J6>=1.5,"BB","B+")))))) -> A | L6: =(('Credit Scoring'!E6*1.1)-'Credit Scoring'!F6)/('Credit Scoring'!C6*0.65) -> 0.81641341 | M6: =IF('Credit Scoring'!G6=0,"N/A",('Credit Scoring'!C6*0.65)/'Credit Scoring'!G6) -> 44.507895 | N6: =IF(('Credit Scoring'!E6*1.1)=0,"N/A",('Credit Scoring'!I6*0.65)/('Credit Scoring'!E6*1.1)*100) -> 55.146554 | O6: =IF(L6<1,5,IF(L6<2,4,IF(L6<3,3,IF(L6<4,2,1))))*0.25+IF(M6>10,5,IF(M6>7,4,IF(M6>4,3,IF(M6>2,2,1))))*0.25+IF(N6>20,5,IF(N6>15,4,IF(N6>10,3,IF(N6>5,2,1))))*0.2+'Credit Scoring'!E22*0.1+'Credit Scoring'!F22*0.15+'Credit Scoring'!G22*0.05 -> 4.85 | P6: =IF(O6>=4.5,"A",IF(O6>=3.8,"BBB+",IF(O6>=3.2,"BBB",IF(O6>=2.6,"BBB-",IF(O6>=2,"BB+",IF(O6>=1.5,"BB","B+")))))) -> A | Q6: =('Credit Scoring'!$B$62*'Credit Scoring'!C6-('Credit Scoring'!E6-'Credit Scoring'!F6))/'Credit Scoring'!C6 -> 4.5303613 | R6: =IF(Q6>2,"Safe",IF(Q6>1,"Watch","⚑ DISTRESS RISK")) -> Safe
A7: Johnson & Johnson | B7: =('Credit Scoring'!E7-'Credit Scoring'!F7)/'Credit Scoring'!C7 -> 0.23255814 | C7: =IF('Credit Scoring'!G7=0,"N/A",'Credit Scoring'!C7/'Credit Scoring'!G7) -> 51.6 | D7: =IF('Credit Scoring'!E7=0,"N/A",'Credit Scoring'!I7/'Credit Scoring'!E7*100) -> 67.383513 | E7: ='Credit Scoring'!H23 -> 5 | F7: ='Credit Scoring'!I23 -> A | G7: =('Credit Scoring'!E7-'Credit Scoring'!F7)/('Credit Scoring'!C7*0.8) -> 0.29069767 | H7: =IF('Credit Scoring'!G7=0,"N/A",('Credit Scoring'!C7*0.8)/'Credit Scoring'!G7) -> 41.28 | I7: =IF('Credit Scoring'!E7=0,"N/A",('Credit Scoring'!I7*0.8)/'Credit Scoring'!E7*100) -> 53.90681 | J7: =IF(G7<1,5,IF(G7<2,4,IF(G7<3,3,IF(G7<4,2,1))))*0.25+IF(H7>10,5,IF(H7>7,4,IF(H7>4,3,IF(H7>2,2,1))))*0.25+IF(I7>20,5,IF(I7>15,4,IF(I7>10,3,IF(I7>5,2,1))))*0.2+'Credit Scoring'!E23*0.1+'Credit Scoring'!F23*0.15+'Credit Scoring'!G23*0.05 -> 5 | K7: =IF(J7>=4.5,"A",IF(J7>=3.8,"BBB+",IF(J7>=3.2,"BBB",IF(J7>=2.6,"BBB-",IF(J7>=2,"BB+",IF(J7>=1.5,"BB","B+")))))) -> A | L7: =(('Credit Scoring'!E7*1.1)-'Credit Scoring'!F7)/('Credit Scoring'!C7*0.65) -> 0.52415027 | M7: =IF('Credit Scoring'!G7=0,"N/A",('Credit Scoring'!C7*0.65)/'Credit Scoring'!G7) -> 33.54 | N7: =IF(('Credit Scoring'!E7*1.1)=0,"N/A",('Credit Scoring'!I7*0.65)/('Credit Scoring'!E7*1.1)*100) -> 39.81753 | O7: =IF(L7<1,5,IF(L7<2,4,IF(L7<3,3,IF(L7<4,2,1))))*0.25+IF(M7>10,5,IF(M7>7,4,IF(M7>4,3,IF(M7>2,2,1))))*0.25+IF(N7>20,5,IF(N7>15,4,IF(N7>10,3,IF(N7>5,2,1))))*0.2+'Credit Scoring'!E23*0.1+'Credit Scoring'!F23*0.15+'Credit Scoring'!G23*0.05 -> 5 | P7: =IF(O7>=4.5,"A",IF(O7>=3.8,"BBB+",IF(O7>=3.2,"BBB",IF(O7>=2.6,"BBB-",IF(O7>=2,"BB+",IF(O7>=1.5,"BB","B+")))))) -> A | Q7: =('Credit Scoring'!$B$62*'Credit Scoring'!C7-('Credit Scoring'!E7-'Credit Scoring'!F7))/'Credit Scoring'!C7 -> 4.7674419 | R7: =IF(Q7>2,"Safe",IF(Q7>1,"Watch","⚑ DISTRESS RISK")) -> Safe
A8: Vodafone Group | B8: =('Credit Scoring'!E8-'Credit Scoring'!F8)/'Credit Scoring'!C8 -> 3.1689189 | C8: =IF('Credit Scoring'!G8=0,"N/A",'Credit Scoring'!C8/'Credit Scoring'!G8) -> 5.4814815 | D8: =IF('Credit Scoring'!E8=0,"N/A",'Credit Scoring'!I8/'Credit Scoring'!E8*100) -> 10.172745 | E8: ='Credit Scoring'!H24 -> 2.65 | F8: ='Credit Scoring'!I24 -> BBB- | G8: =('Credit Scoring'!E8-'Credit Scoring'!F8)/('Credit Scoring'!C8*0.8) -> 3.9611486 | H8: =IF('Credit Scoring'!G8=0,"N/A",('Credit Scoring'!C8*0.8)/'Credit Scoring'!G8) -> 4.3851852 | I8: =IF('Credit Scoring'!E8=0,"N/A",('Credit Scoring'!I8*0.8)/'Credit Scoring'!E8*100) -> 8.1381958 | J8: =IF(G8<1,5,IF(G8<2,4,IF(G8<3,3,IF(G8<4,2,1))))*0.25+IF(H8>10,5,IF(H8>7,4,IF(H8>4,3,IF(H8>2,2,1))))*0.25+IF(I8>20,5,IF(I8>15,4,IF(I8>10,3,IF(I8>5,2,1))))*0.2+'Credit Scoring'!E24*0.1+'Credit Scoring'!F24*0.15+'Credit Scoring'!G24*0.05 -> 2.45 | K8: =IF(J8>=4.5,"A",IF(J8>=3.8,"BBB+",IF(J8>=3.2,"BBB",IF(J8>=2.6,"BBB-",IF(J8>=2,"BB+",IF(J8>=1.5,"BB","B+")))))) -> BB+ | L8: =(('Credit Scoring'!E8*1.1)-'Credit Scoring'!F8)/('Credit Scoring'!C8*0.65) -> 5.4168399 | M8: =IF('Credit Scoring'!G8=0,"N/A",('Credit Scoring'!C8*0.65)/'Credit Scoring'!G8) -> 3.562963 | N8: =IF(('Credit Scoring'!E8*1.1)=0,"N/A",('Credit Scoring'!I8*0.65)/('Credit Scoring'!E8*1.1)*100) -> 6.0111673 | O8: =IF(L8<1,5,IF(L8<2,4,IF(L8<3,3,IF(L8<4,2,1))))*0.25+IF(M8>10,5,IF(M8>7,4,IF(M8>4,3,IF(M8>2,2,1))))*0.25+IF(N8>20,5,IF(N8>15,4,IF(N8>10,3,IF(N8>5,2,1))))*0.2+'Credit Scoring'!E24*0.1+'Credit Scoring'!F24*0.15+'Credit Scoring'!G24*0.05 -> 1.95 | P8: =IF(O8>=4.5,"A",IF(O8>=3.8,"BBB+",IF(O8>=3.2,"BBB",IF(O8>=2.6,"BBB-",IF(O8>=2,"BB+",IF(O8>=1.5,"BB","B+")))))) -> BB | Q8: =('Credit Scoring'!$B$62*'Credit Scoring'!C8-('Credit Scoring'!E8-'Credit Scoring'!F8))/'Credit Scoring'!C8 -> 1.8310811 | R8: =IF(Q8>2,"Safe",IF(Q8>1,"Watch","⚑ DISTRESS RISK")) -> Watch
A9: Rolls-Royce Holdings | B9: =('Credit Scoring'!E9-'Credit Scoring'!F9)/'Credit Scoring'!C9 -> 0.28571429 | C9: =IF('Credit Scoring'!G9=0,"N/A",'Credit Scoring'!C9/'Credit Scoring'!G9) -> 14 | D9: =IF('Credit Scoring'!E9=0,"N/A",'Credit Scoring'!I9/'Credit Scoring'!E9*100) -> 43.75 | E9: ='Credit Scoring'!H25 -> 4.7 | F9: ='Credit Scoring'!I25 -> A | G9: =('Credit Scoring'!E9-'Credit Scoring'!F9)/('Credit Scoring'!C9*0.8) -> 0.35714286 | H9: =IF('Credit Scoring'!G9=0,"N/A",('Credit Scoring'!C9*0.8)/'Credit Scoring'!G9) -> 11.2 | I9: =IF('Credit Scoring'!E9=0,"N/A",('Credit Scoring'!I9*0.8)/'Credit Scoring'!E9*100) -> 35 | J9: =IF(G9<1,5,IF(G9<2,4,IF(G9<3,3,IF(G9<4,2,1))))*0.25+IF(H9>10,5,IF(H9>7,4,IF(H9>4,3,IF(H9>2,2,1))))*0.25+IF(I9>20,5,IF(I9>15,4,IF(I9>10,3,IF(I9>5,2,1))))*0.2+'Credit Scoring'!E25*0.1+'Credit Scoring'!F25*0.15+'Credit Scoring'!G25*0.05 -> 4.7 | K9: =IF(J9>=4.5,"A",IF(J9>=3.8,"BBB+",IF(J9>=3.2,"BBB",IF(J9>=2.6,"BBB-",IF(J9>=2,"BB+",IF(J9>=1.5,"BB","B+")))))) -> A | L9: =(('Credit Scoring'!E9*1.1)-'Credit Scoring'!F9)/('Credit Scoring'!C9*0.65) -> 0.61538462 | M9: =IF('Credit Scoring'!G9=0,"N/A",('Credit Scoring'!C9*0.65)/'Credit Scoring'!G9) -> 9.1 | N9: =IF(('Credit Scoring'!E9*1.1)=0,"N/A",('Credit Scoring'!I9*0.65)/('Credit Scoring'!E9*1.1)*100) -> 25.852273 | O9: =IF(L9<1,5,IF(L9<2,4,IF(L9<3,3,IF(L9<4,2,1))))*0.25+IF(M9>10,5,IF(M9>7,4,IF(M9>4,3,IF(M9>2,2,1))))*0.25+IF(N9>20,5,IF(N9>15,4,IF(N9>10,3,IF(N9>5,2,1))))*0.2+'Credit Scoring'!E25*0.1+'Credit Scoring'!F25*0.15+'Credit Scoring'!G25*0.05 -> 4.45 | P9: =IF(O9>=4.5,"A",IF(O9>=3.8,"BBB+",IF(O9>=3.2,"BBB",IF(O9>=2.6,"BBB-",IF(O9>=2,"BB+",IF(O9>=1.5,"BB","B+")))))) -> BBB+ | Q9: =('Credit Scoring'!$B$62*'Credit Scoring'!C9-('Credit Scoring'!E9-'Credit Scoring'!F9))/'Credit Scoring'!C9 -> 4.7142857 | R9: =IF(Q9>2,"Safe",IF(Q9>1,"Watch","⚑ DISTRESS RISK")) -> Safe
A10: Ford Motor Company | B10: =('Credit Scoring'!E10-'Credit Scoring'!F10)/'Credit Scoring'!C10 -> -0.71568627 | C10: =IF('Credit Scoring'!G10=0,"N/A",'Credit Scoring'!C10/'Credit Scoring'!G10) -> 6.8 | D10: =IF('Credit Scoring'!E10=0,"N/A",'Credit Scoring'!I10/'Credit Scoring'!E10*100) -> 12.727273 | E10: ='Credit Scoring'!H26 -> 3.4 | F10: ='Credit Scoring'!I26 -> BBB | G10: =('Credit Scoring'!E10-'Credit Scoring'!F10)/('Credit Scoring'!C10*0.8) -> -0.89460784 | H10: =IF('Credit Scoring'!G10=0,"N/A",('Credit Scoring'!C10*0.8)/'Credit Scoring'!G10) -> 5.44 | I10: =IF('Credit Scoring'!E10=0,"N/A",('Credit Scoring'!I10*0.8)/'Credit Scoring'!E10*100) -> 10.181818 | J10: =IF(G10<1,5,IF(G10<2,4,IF(G10<3,3,IF(G10<4,2,1))))*0.25+IF(H10>10,5,IF(H10>7,4,IF(H10>4,3,IF(H10>2,2,1))))*0.25+IF(I10>20,5,IF(I10>15,4,IF(I10>10,3,IF(I10>5,2,1))))*0.2+'Credit Scoring'!E26*0.1+'Credit Scoring'!F26*0.15+'Credit Scoring'!G26*0.05 -> 3.4 | K10: =IF(J10>=4.5,"A",IF(J10>=3.8,"BBB+",IF(J10>=3.2,"BBB",IF(J10>=2.6,"BBB-",IF(J10>=2,"BB+",IF(J10>=1.5,"BB","B+")))))) -> BBB | L10: =(('Credit Scoring'!E10*1.1)-'Credit Scoring'!F10)/('Credit Scoring'!C10*0.65) -> -0.76923077 | M10: =IF('Credit Scoring'!G10=0,"N/A",('Credit Scoring'!C10*0.65)/'Credit Scoring'!G10) -> 4.42 | N10: =IF(('Credit Scoring'!E10*1.1)=0,"N/A",('Credit Scoring'!I10*0.65)/('Credit Scoring'!E10*1.1)*100) -> 7.5206612 | O10: =IF(L10<1,5,IF(L10<2,4,IF(L10<3,3,IF(L10<4,2,1))))*0.25+IF(M10>10,5,IF(M10>7,4,IF(M10>4,3,IF(M10>2,2,1))))*0.25+IF(N10>20,5,IF(N10>15,4,IF(N10>10,3,IF(N10>5,2,1))))*0.2+'Credit Scoring'!E26*0.1+'Credit Scoring'!F26*0.15+'Credit Scoring'!G26*0.05 -> 3.2 | P10: =IF(O10>=4.5,"A",IF(O10>=3.8,"BBB+",IF(O10>=3.2,"BBB",IF(O10>=2.6,"BBB-",IF(O10>=2,"BB+",IF(O10>=1.5,"BB","B+")))))) -> BBB | Q10: =('Credit Scoring'!$B$62*'Credit Scoring'!C10-('Credit Scoring'!E10-'Credit Scoring'!F10))/'Credit Scoring'!C10 -> 5.7156863 | R10: =IF(Q10>2,"Safe",IF(Q10>1,"Watch","⚑ DISTRESS RISK")) -> Safe
A11: Telecom Italia | B11: =('Credit Scoring'!E11-'Credit Scoring'!F11)/'Credit Scoring'!C11 -> 2.1568627 | C11: =IF('Credit Scoring'!G11=0,"N/A",'Credit Scoring'!C11/'Credit Scoring'!G11) -> 2.8333333 | D11: =IF('Credit Scoring'!E11=0,"N/A",'Credit Scoring'!I11/'Credit Scoring'!E11*100) -> 8.4507042 | E11: ='Credit Scoring'!H27 -> 2.6 | F11: ='Credit Scoring'!I27 -> BBB- | G11: =('Credit Scoring'!E11-'Credit Scoring'!F11)/('Credit Scoring'!C11*0.8) -> 2.6960784 | H11: =IF('Credit Scoring'!G11=0,"N/A",('Credit Scoring'!C11*0.8)/'Credit Scoring'!G11) -> 2.2666667 | I11: =IF('Credit Scoring'!E11=0,"N/A",('Credit Scoring'!I11*0.8)/'Credit Scoring'!E11*100) -> 6.7605634 | J11: =IF(G11<1,5,IF(G11<2,4,IF(G11<3,3,IF(G11<4,2,1))))*0.25+IF(H11>10,5,IF(H11>7,4,IF(H11>4,3,IF(H11>2,2,1))))*0.25+IF(I11>20,5,IF(I11>15,4,IF(I11>10,3,IF(I11>5,2,1))))*0.2+'Credit Scoring'!E27*0.1+'Credit Scoring'!F27*0.15+'Credit Scoring'!G27*0.05 -> 2.6 | K11: =IF(J11>=4.5,"A",IF(J11>=3.8,"BBB+",IF(J11>=3.2,"BBB",IF(J11>=2.6,"BBB-",IF(J11>=2,"BB+",IF(J11>=1.5,"BB","B+")))))) -> BBB- | L11: =(('Credit Scoring'!E11*1.1)-'Credit Scoring'!F11)/('Credit Scoring'!C11*0.65) -> 3.7466063 | M11: =IF('Credit Scoring'!G11=0,"N/A",('Credit Scoring'!C11*0.65)/'Credit Scoring'!G11) -> 1.8416667 | N11: =IF(('Credit Scoring'!E11*1.1)=0,"N/A",('Credit Scoring'!I11*0.65)/('Credit Scoring'!E11*1.1)*100) -> 4.993598 | O11: =IF(L11<1,5,IF(L11<2,4,IF(L11<3,3,IF(L11<4,2,1))))*0.25+IF(M11>10,5,IF(M11>7,4,IF(M11>4,3,IF(M11>2,2,1))))*0.25+IF(N11>20,5,IF(N11>15,4,IF(N11>10,3,IF(N11>5,2,1))))*0.2+'Credit Scoring'!E27*0.1+'Credit Scoring'!F27*0.15+'Credit Scoring'!G27*0.05 -> 1.9 | P11: =IF(O11>=4.5,"A",IF(O11>=3.8,"BBB+",IF(O11>=3.2,"BBB",IF(O11>=2.6,"BBB-",IF(O11>=2,"BB+",IF(O11>=1.5,"BB","B+")))))) -> BB | Q11: =('Credit Scoring'!$B$62*'Credit Scoring'!C11-('Credit Scoring'!E11-'Credit Scoring'!F11))/'Credit Scoring'!C11 -> 2.8431373 | R11: =IF(Q11>2,"Safe",IF(Q11>1,"Watch","⚑ DISTRESS RISK")) -> Safe
A12: Marks & Spencer | B12: =('Credit Scoring'!E12-'Credit Scoring'!F12)/'Credit Scoring'!C12 -> 2.3076923 | C12: =IF('Credit Scoring'!G12=0,"N/A",'Credit Scoring'!C12/'Credit Scoring'!G12) -> 6.5 | D12: =IF('Credit Scoring'!E12=0,"N/A",'Credit Scoring'!I12/'Credit Scoring'!E12*100) -> 14.634146 | E12: ='Credit Scoring'!H28 -> 2.8 | F12: ='Credit Scoring'!I28 -> BBB- | G12: =('Credit Scoring'!E12-'Credit Scoring'!F12)/('Credit Scoring'!C12*0.8) -> 2.8846154 | H12: =IF('Credit Scoring'!G12=0,"N/A",('Credit Scoring'!C12*0.8)/'Credit Scoring'!G12) -> 5.2 | I12: =IF('Credit Scoring'!E12=0,"N/A",('Credit Scoring'!I12*0.8)/'Credit Scoring'!E12*100) -> 11.707317 | J12: =IF(G12<1,5,IF(G12<2,4,IF(G12<3,3,IF(G12<4,2,1))))*0.25+IF(H12>10,5,IF(H12>7,4,IF(H12>4,3,IF(H12>2,2,1))))*0.25+IF(I12>20,5,IF(I12>15,4,IF(I12>10,3,IF(I12>5,2,1))))*0.2+'Credit Scoring'!E28*0.1+'Credit Scoring'!F28*0.15+'Credit Scoring'!G28*0.05 -> 2.8 | K12: =IF(J12>=4.5,"A",IF(J12>=3.8,"BBB+",IF(J12>=3.2,"BBB",IF(J12>=2.6,"BBB-",IF(J12>=2,"BB+",IF(J12>=1.5,"BB","B+")))))) -> BBB- | L12: =(('Credit Scoring'!E12*1.1)-'Credit Scoring'!F12)/('Credit Scoring'!C12*0.65) -> 4.035503 | M12: =IF('Credit Scoring'!G12=0,"N/A",('Credit Scoring'!C12*0.65)/'Credit Scoring'!G12) -> 4.225 | N12: =IF(('Credit Scoring'!E12*1.1)=0,"N/A",('Credit Scoring'!I12*0.65)/('Credit Scoring'!E12*1.1)*100) -> 8.6474501 | O12: =IF(L12<1,5,IF(L12<2,4,IF(L12<3,3,IF(L12<4,2,1))))*0.25+IF(M12>10,5,IF(M12>7,4,IF(M12>4,3,IF(M12>2,2,1))))*0.25+IF(N12>20,5,IF(N12>15,4,IF(N12>10,3,IF(N12>5,2,1))))*0.2+'Credit Scoring'!E28*0.1+'Credit Scoring'!F28*0.15+'Credit Scoring'!G28*0.05 -> 2.1 | P12: =IF(O12>=4.5,"A",IF(O12>=3.8,"BBB+",IF(O12>=3.2,"BBB",IF(O12>=2.6,"BBB-",IF(O12>=2,"BB+",IF(O12>=1.5,"BB","B+")))))) -> BB+ | Q12: =('Credit Scoring'!$B$62*'Credit Scoring'!C12-('Credit Scoring'!E12-'Credit Scoring'!F12))/'Credit Scoring'!C12 -> 2.6923077 | R12: =IF(Q12>2,"Safe",IF(Q12>1,"Watch","⚑ DISTRESS RISK")) -> Safe
A13: Telefonica SA | B13: =('Credit Scoring'!E13-'Credit Scoring'!F13)/'Credit Scoring'!C13 -> 2.5307692 | C13: =IF('Credit Scoring'!G13=0,"N/A",'Credit Scoring'!C13/'Credit Scoring'!G13) -> 5.2 | D13: =IF('Credit Scoring'!E13=0,"N/A",'Credit Scoring'!I13/'Credit Scoring'!E13*100) -> 10.199005 | E13: ='Credit Scoring'!H29 -> 2.9 | F13: ='Credit Scoring'!I29 -> BBB- | G13: =('Credit Scoring'!E13-'Credit Scoring'!F13)/('Credit Scoring'!C13*0.8) -> 3.1634615 | H13: =IF('Credit Scoring'!G13=0,"N/A",('Credit Scoring'!C13*0.8)/'Credit Scoring'!G13) -> 4.16 | I13: =IF('Credit Scoring'!E13=0,"N/A",('Credit Scoring'!I13*0.8)/'Credit Scoring'!E13*100) -> 8.159204 | J13: =IF(G13<1,5,IF(G13<2,4,IF(G13<3,3,IF(G13<4,2,1))))*0.25+IF(H13>10,5,IF(H13>7,4,IF(H13>4,3,IF(H13>2,2,1))))*0.25+IF(I13>20,5,IF(I13>15,4,IF(I13>10,3,IF(I13>5,2,1))))*0.2+'Credit Scoring'!E29*0.1+'Credit Scoring'!F29*0.15+'Credit Scoring'!G29*0.05 -> 2.45 | K13: =IF(J13>=4.5,"A",IF(J13>=3.8,"BBB+",IF(J13>=3.2,"BBB",IF(J13>=2.6,"BBB-",IF(J13>=2,"BB+",IF(J13>=1.5,"BB","B+")))))) -> BB+ | L13: =(('Credit Scoring'!E13*1.1)-'Credit Scoring'!F13)/('Credit Scoring'!C13*0.65) -> 4.3692308 | M13: =IF('Credit Scoring'!G13=0,"N/A",('Credit Scoring'!C13*0.65)/'Credit Scoring'!G13) -> 3.38 | N13: =IF(('Credit Scoring'!E13*1.1)=0,"N/A",('Credit Scoring'!I13*0.65)/('Credit Scoring'!E13*1.1)*100) -> 6.0266848 | O13: =IF(L13<1,5,IF(L13<2,4,IF(L13<3,3,IF(L13<4,2,1))))*0.25+IF(M13>10,5,IF(M13>7,4,IF(M13>4,3,IF(M13>2,2,1))))*0.25+IF(N13>20,5,IF(N13>15,4,IF(N13>10,3,IF(N13>5,2,1))))*0.2+'Credit Scoring'!E29*0.1+'Credit Scoring'!F29*0.15+'Credit Scoring'!G29*0.05 -> 1.95 | P13: =IF(O13>=4.5,"A",IF(O13>=3.8,"BBB+",IF(O13>=3.2,"BBB",IF(O13>=2.6,"BBB-",IF(O13>=2,"BB+",IF(O13>=1.5,"BB","B+")))))) -> BB | Q13: =('Credit Scoring'!$B$62*'Credit Scoring'!C13-('Credit Scoring'!E13-'Credit Scoring'!F13))/'Credit Scoring'!C13 -> 2.4692308 | R13: =IF(Q13>2,"Safe",IF(Q13>1,"Watch","⚑ DISTRESS RISK")) -> Safe
A14: Carnival Corporation | B14: =('Credit Scoring'!E14-'Credit Scoring'!F14)/'Credit Scoring'!C14 -> 5.8965517 | C14: =IF('Credit Scoring'!G14=0,"N/A",'Credit Scoring'!C14/'Credit Scoring'!G14) -> 3.2222222 | D14: =IF('Credit Scoring'!E14=0,"N/A",'Credit Scoring'!I14/'Credit Scoring'!E14*100) -> 3.8997214 | E14: ='Credit Scoring'!H30 -> 1.55 | F14: ='Credit Scoring'!I30 -> BB | G14: =('Credit Scoring'!E14-'Credit Scoring'!F14)/('Credit Scoring'!C14*0.8) -> 7.3706897 | H14: =IF('Credit Scoring'!G14=0,"N/A",('Credit Scoring'!C14*0.8)/'Credit Scoring'!G14) -> 2.5777778 | I14: =IF('Credit Scoring'!E14=0,"N/A",('Credit Scoring'!I14*0.8)/'Credit Scoring'!E14*100) -> 3.1197772 | J14: =IF(G14<1,5,IF(G14<2,4,IF(G14<3,3,IF(G14<4,2,1))))*0.25+IF(H14>10,5,IF(H14>7,4,IF(H14>4,3,IF(H14>2,2,1))))*0.25+IF(I14>20,5,IF(I14>15,4,IF(I14>10,3,IF(I14>5,2,1))))*0.2+'Credit Scoring'!E30*0.1+'Credit Scoring'!F30*0.15+'Credit Scoring'!G30*0.05 -> 1.55 | K14: =IF(J14>=4.5,"A",IF(J14>=3.8,"BBB+",IF(J14>=3.2,"BBB",IF(J14>=2.6,"BBB-",IF(J14>=2,"BB+",IF(J14>=1.5,"BB","B+")))))) -> BB | L14: =(('Credit Scoring'!E14*1.1)-'Credit Scoring'!F14)/('Credit Scoring'!C14*0.65) -> 10.023873 | M14: =IF('Credit Scoring'!G14=0,"N/A",('Credit Scoring'!C14*0.65)/'Credit Scoring'!G14) -> 2.0944444 | N14: =IF(('Credit Scoring'!E14*1.1)=0,"N/A",('Credit Scoring'!I14*0.65)/('Credit Scoring'!E14*1.1)*100) -> 2.3043809 | O14: =IF(L14<1,5,IF(L14<2,4,IF(L14<3,3,IF(L14<4,2,1))))*0.25+IF(M14>10,5,IF(M14>7,4,IF(M14>4,3,IF(M14>2,2,1))))*0.25+IF(N14>20,5,IF(N14>15,4,IF(N14>10,3,IF(N14>5,2,1))))*0.2+'Credit Scoring'!E30*0.1+'Credit Scoring'!F30*0.15+'Credit Scoring'!G30*0.05 -> 1.55 | P14: =IF(O14>=4.5,"A",IF(O14>=3.8,"BBB+",IF(O14>=3.2,"BBB",IF(O14>=2.6,"BBB-",IF(O14>=2,"BB+",IF(O14>=1.5,"BB","B+")))))) -> BB | Q14: =('Credit Scoring'!$B$62*'Credit Scoring'!C14-('Credit Scoring'!E14-'Credit Scoring'!F14))/'Credit Scoring'!C14 -> -0.89655172 | R14: =IF(Q14>2,"Safe",IF(Q14>1,"Watch","⚑ DISTRESS RISK")) -> ⚑ DISTRESS RISK
A15: Kraft Heinz Company | B15: =('Credit Scoring'!E15-'Credit Scoring'!F15)/'Credit Scoring'!C15 -> 3.4237288 | C15: =IF('Credit Scoring'!G15=0,"N/A",'Credit Scoring'!C15/'Credit Scoring'!G15) -> 4.2142857 | D15: =IF('Credit Scoring'!E15=0,"N/A",'Credit Scoring'!I15/'Credit Scoring'!E15*100) -> 15.63981 | E15: ='Credit Scoring'!H31 -> 2.85 | F15: ='Credit Scoring'!I31 -> BBB- | G15: =('Credit Scoring'!E15-'Credit Scoring'!F15)/('Credit Scoring'!C15*0.8) -> 4.279661 | H15: =IF('Credit Scoring'!G15=0,"N/A",('Credit Scoring'!C15*0.8)/'Credit Scoring'!G15) -> 3.3714286 | I15: =IF('Credit Scoring'!E15=0,"N/A",('Credit Scoring'!I15*0.8)/'Credit Scoring'!E15*100) -> 12.511848 | J15: =IF(G15<1,5,IF(G15<2,4,IF(G15<3,3,IF(G15<4,2,1))))*0.25+IF(H15>10,5,IF(H15>7,4,IF(H15>4,3,IF(H15>2,2,1))))*0.25+IF(I15>20,5,IF(I15>15,4,IF(I15>10,3,IF(I15>5,2,1))))*0.2+'Credit Scoring'!E31*0.1+'Credit Scoring'!F31*0.15+'Credit Scoring'!G31*0.05 -> 2.15 | K15: =IF(J15>=4.5,"A",IF(J15>=3.8,"BBB+",IF(J15>=3.2,"BBB",IF(J15>=2.6,"BBB-",IF(J15>=2,"BB+",IF(J15>=1.5,"BB","B+")))))) -> BB+ | L15: =(('Credit Scoring'!E15*1.1)-'Credit Scoring'!F15)/('Credit Scoring'!C15*0.65) -> 5.8174707 | M15: =IF('Credit Scoring'!G15=0,"N/A",('Credit Scoring'!C15*0.65)/'Credit Scoring'!G15) -> 2.7392857 | N15: =IF(('Credit Scoring'!E15*1.1)=0,"N/A",('Credit Scoring'!I15*0.65)/('Credit Scoring'!E15*1.1)*100) -> 9.2417062 | O15: =IF(L15<1,5,IF(L15<2,4,IF(L15<3,3,IF(L15<4,2,1))))*0.25+IF(M15>10,5,IF(M15>7,4,IF(M15>4,3,IF(M15>2,2,1))))*0.25+IF(N15>20,5,IF(N15>15,4,IF(N15>10,3,IF(N15>5,2,1))))*0.2+'Credit Scoring'!E31*0.1+'Credit Scoring'!F31*0.15+'Credit Scoring'!G31*0.05 -> 1.95 | P15: =IF(O15>=4.5,"A",IF(O15>=3.8,"BBB+",IF(O15>=3.2,"BBB",IF(O15>=2.6,"BBB-",IF(O15>=2,"BB+",IF(O15>=1.5,"BB","B+")))))) -> BB | Q15: =('Credit Scoring'!$B$62*'Credit Scoring'!C15-('Credit Scoring'!E15-'Credit Scoring'!F15))/'Credit Scoring'!C15 -> 1.5762712 | R15: =IF(Q15>2,"Safe",IF(Q15>1,"Watch","⚑ DISTRESS RISK")) -> Watch
A16: Bombardier Inc | B16: =('Credit Scoring'!E16-'Credit Scoring'!F16)/'Credit Scoring'!C16 -> 3.6666667 | C16: =IF('Credit Scoring'!G16=0,"N/A",'Credit Scoring'!C16/'Credit Scoring'!G16) -> 2.25 | D16: =IF('Credit Scoring'!E16=0,"N/A",'Credit Scoring'!I16/'Credit Scoring'!E16*100) -> 8.3333333 | E16: ='Credit Scoring'!H32 -> 2.05 | F16: ='Credit Scoring'!I32 -> BB+ | G16: =('Credit Scoring'!E16-'Credit Scoring'!F16)/('Credit Scoring'!C16*0.8) -> 4.5833333 | H16: =IF('Credit Scoring'!G16=0,"N/A",('Credit Scoring'!C16*0.8)/'Credit Scoring'!G16) -> 1.8 | I16: =IF('Credit Scoring'!E16=0,"N/A",('Credit Scoring'!I16*0.8)/'Credit Scoring'!E16*100) -> 6.6666667 | J16: =IF(G16<1,5,IF(G16<2,4,IF(G16<3,3,IF(G16<4,2,1))))*0.25+IF(H16>10,5,IF(H16>7,4,IF(H16>4,3,IF(H16>2,2,1))))*0.25+IF(I16>20,5,IF(I16>15,4,IF(I16>10,3,IF(I16>5,2,1))))*0.2+'Credit Scoring'!E32*0.1+'Credit Scoring'!F32*0.15+'Credit Scoring'!G32*0.05 -> 1.55 | K16: =IF(J16>=4.5,"A",IF(J16>=3.8,"BBB+",IF(J16>=3.2,"BBB",IF(J16>=2.6,"BBB-",IF(J16>=2,"BB+",IF(J16>=1.5,"BB","B+")))))) -> BB | L16: =(('Credit Scoring'!E16*1.1)-'Credit Scoring'!F16)/('Credit Scoring'!C16*0.65) -> 6.3589744 | M16: =IF('Credit Scoring'!G16=0,"N/A",('Credit Scoring'!C16*0.65)/'Credit Scoring'!G16) -> 1.4625 | N16: =IF(('Credit Scoring'!E16*1.1)=0,"N/A",('Credit Scoring'!I16*0.65)/('Credit Scoring'!E16*1.1)*100) -> 4.9242424 | O16: =IF(L16<1,5,IF(L16<2,4,IF(L16<3,3,IF(L16<4,2,1))))*0.25+IF(M16>10,5,IF(M16>7,4,IF(M16>4,3,IF(M16>2,2,1))))*0.25+IF(N16>20,5,IF(N16>15,4,IF(N16>10,3,IF(N16>5,2,1))))*0.2+'Credit Scoring'!E32*0.1+'Credit Scoring'!F32*0.15+'Credit Scoring'!G32*0.05 -> 1.35 | P16: =IF(O16>=4.5,"A",IF(O16>=3.8,"BBB+",IF(O16>=3.2,"BBB",IF(O16>=2.6,"BBB-",IF(O16>=2,"BB+",IF(O16>=1.5,"BB","B+")))))) -> B+ | Q16: =('Credit Scoring'!$B$62*'Credit Scoring'!C16-('Credit Scoring'!E16-'Credit Scoring'!F16))/'Credit Scoring'!C16 -> 1.3333333 | R16: =IF(Q16>2,"Safe",IF(Q16>1,"Watch","⚑ DISTRESS RISK")) -> Watch
A17: Coty Inc | B17: =('Credit Scoring'!E17-'Credit Scoring'!F17)/'Credit Scoring'!C17 -> 4.7777778 | C17: =IF('Credit Scoring'!G17=0,"N/A",'Credit Scoring'!C17/'Credit Scoring'!G17) -> 2.25 | D17: =IF('Credit Scoring'!E17=0,"N/A",'Credit Scoring'!I17/'Credit Scoring'!E17*100) -> 6.25 | E17: ='Credit Scoring'!H33 -> 1.6 | F17: ='Credit Scoring'!I33 -> BB | G17: =('Credit Scoring'!E17-'Credit Scoring'!F17)/('Credit Scoring'!C17*0.8) -> 5.9722222 | H17: =IF('Credit Scoring'!G17=0,"N/A",('Credit Scoring'!C17*0.8)/'Credit Scoring'!G17) -> 1.8 | I17: =IF('Credit Scoring'!E17=0,"N/A",('Credit Scoring'!I17*0.8)/'Credit Scoring'!E17*100) -> 5 | J17: =IF(G17<1,5,IF(G17<2,4,IF(G17<3,3,IF(G17<4,2,1))))*0.25+IF(H17>10,5,IF(H17>7,4,IF(H17>4,3,IF(H17>2,2,1))))*0.25+IF(I17>20,5,IF(I17>15,4,IF(I17>10,3,IF(I17>5,2,1))))*0.2+'Credit Scoring'!E33*0.1+'Credit Scoring'!F33*0.15+'Credit Scoring'!G33*0.05 -> 1.15 | K17: =IF(J17>=4.5,"A",IF(J17>=3.8,"BBB+",IF(J17>=3.2,"BBB",IF(J17>=2.6,"BBB-",IF(J17>=2,"BB+",IF(J17>=1.5,"BB","B+")))))) -> B+ | L17: =(('Credit Scoring'!E17*1.1)-'Credit Scoring'!F17)/('Credit Scoring'!C17*0.65) -> 8.1709402 | M17: =IF('Credit Scoring'!G17=0,"N/A",('Credit Scoring'!C17*0.65)/'Credit Scoring'!G17) -> 1.4625 | N17: =IF(('Credit Scoring'!E17*1.1)=0,"N/A",('Credit Scoring'!I17*0.65)/('Credit Scoring'!E17*1.1)*100) -> 3.6931818 | O17: =IF(L17<1,5,IF(L17<2,4,IF(L17<3,3,IF(L17<4,2,1))))*0.25+IF(M17>10,5,IF(M17>7,4,IF(M17>4,3,IF(M17>2,2,1))))*0.25+IF(N17>20,5,IF(N17>15,4,IF(N17>10,3,IF(N17>5,2,1))))*0.2+'Credit Scoring'!E33*0.1+'Credit Scoring'!F33*0.15+'Credit Scoring'!G33*0.05 -> 1.15 | P17: =IF(O17>=4.5,"A",IF(O17>=3.8,"BBB+",IF(O17>=3.2,"BBB",IF(O17>=2.6,"BBB-",IF(O17>=2,"BB+",IF(O17>=1.5,"BB","B+")))))) -> B+ | Q17: =('Credit Scoring'!$B$62*'Credit Scoring'!C17-('Credit Scoring'!E17-'Credit Scoring'!F17))/'Credit Scoring'!C17 -> 0.22222222 | R17: =IF(Q17>2,"Safe",IF(Q17>1,"Watch","⚑ DISTRESS RISK")) -> ⚑ DISTRESS RISK

Sheet Relative Value
A1: RELATIVE VALUE MATRIX — CROSS-ISSUER SPREAD DIFFERENTIALS
A2: Spread differential matrix (Row spread minus Column spread, bps). Green = row bond cheap vs. column; Red = row bond rich vs. column.
A4: Issuer \ vs. | B4: MSFT | C4: JNJ | D4: VOD | E4: RR | F4: F | G4: TIT | H4: MKS | I4: TEF | J4: CCL | K4: KHC | L4: BBD | M4: COTY
A5: MSFT — Microsoft | B5: — | C5: -5 | D5: -135 | E5: -35 | F5: -180 | G5: -310 | H5: -125 | I5: -135 | J5: -255 | K5: -125 | L5: -260 | M5: -340
A6: JNJ — J&J | B6: 5 | C6: — | D6: -130 | E6: -30 | F6: -175 | G6: -305 | H6: -120 | I6: -130 | J6: -250 | K6: -120 | L6: -255 | M6: -335
A7: VOD — Vodafone | B7: 135 | C7: 130 | D7: — | E7: 100 | F7: -45 | G7: -175 | H7: 10 | I7: 0 | J7: -120 | K7: 10 | L7: -125 | M7: -205
A8: RR — Rolls-Royce | B8: 35 | C8: 30 | D8: -100 | E8: — | F8: -145 | G8: -275 | H8: -90 | I8: -100 | J8: -220 | K8: -90 | L8: -225 | M8: -305
A9: F — Ford | B9: 180 | C9: 175 | D9: 45 | E9: 145 | F9: — | G9: -130 | H9: 55 | I9: 45 | J9: -75 | K9: 55 | L9: -80 | M9: -160
A10: TIT — Telecom Italia | B10: 310 | C10: 305 | D10: 175 | E10: 275 | F10: 130 | G10: — | H10: 185 | I10: 175 | J10: 55 | K10: 185 | L10: 50 | M10: -30
A11: MKS — M&S | B11: 125 | C11: 120 | D11: -10 | E11: 90 | F11: -55 | G11: -185 | H11: — | I11: -10 | J11: -130 | K11: 0 | L11: -135 | M11: -215
A12: TEF — Telefonica | B12: 135 | C12: 130 | D12: 0 | E12: 100 | F12: -45 | G12: -175 | H12: 10 | I12: — | J12: -120 | K12: 10 | L12: -125 | M12: -205
A13: CCL — Carnival | B13: 255 | C13: 250 | D13: 120 | E13: 220 | F13: 75 | G13: -55 | H13: 130 | I13: 120 | J13: — | K13: 130 | L13: -5 | M13: -85
A14: KHC — Kraft Heinz | B14: 125 | C14: 120 | D14: -10 | E14: 90 | F14: -55 | G14: -185 | H14: 0 | I14: -10 | J14: -130 | K14: — | L14: -135 | M14: -215
A15: BBD — Bombardier | B15: 260 | C15: 255 | D15: 125 | E15: 225 | F15: 80 | G15: -50 | H15: 135 | I15: 125 | J15: 5 | K15: 135 | L15: — | M15: -80
A16: COTY — Coty | B16: 340 | C16: 335 | D16: 205 | E16: 305 | F16: 160 | G16: 30 | H16: 215 | I16: 205 | J16: 85 | K16: 215 | L16: 80 | M16: —
A18: COLOUR LEGEND:
A19: Dark Green (>50bps diff) | B19: Row issuer materially cheap vs. column — potential long/short pair
A20: Light Green (20-50bps) | B20: Row issuer modestly cheap vs. column — worth monitoring
A21: Light Pink (<20bps tight) | B21: Row issuer modestly rich vs. column
A22: Dark Red (>50bps tight) | B22: Row issuer materially rich vs. column — potential long/short pair
A24: SECTION 2 — TOP 3 RELATIVE VALUE PAIR TRADE OPPORTUNITIES
A25: Rank | B25: Long (Buy) | C25: Short (Sell) | D25: Spread Diff (bps) | E25: Rationale | F25: Expected Convergence
A26: 1 | B26: Bombardier (BBD) — BB, ~310bps FV | C26: Coty (COTY) — B+, ~390bps FV | D26: 80 | E26: Bombardier and Coty trade at similar spread levels (~310-400bps) but represent very different credit trajectories. Bombardier is a deleveraging story — Net Debt/EBITDA trending from 4.5x towards 3.5x with strong FCF generation and a business jet cycle tailwind. Coty is a re-leveraging consumer brand with Net Debt/EBITDA above 5x and limited near-term FCF after interest payments. On a risk-adjusted basis, Bombardier offers superior value. Long BBD / Short COTY is a convergence trade on credit trajectory divergence. | F26: 12-18 months; Bombardier upgrade catalyst
A28: 2 | B28: Telecom Italia (TIT) Short-dated — BB, ~360bps FV | C28: Carnival (CCL) — BB+, ~305bps FV | D28: 55 | E28: Telecom Italia (ServiceCo post-NetCo disposal) trades ~55bps wide of Carnival despite having a comparable shadow rating and significantly less cyclical exposure. Carnival remains deeply exposed to consumer discretionary spending, fuel costs, and geopolitical travel risk. TIT ServiceCo has a more stable recurring revenue base (enterprise mobile, B2B telecoms) with improving EBITDA margins post-separation. On short-dated paper (2026-2027 maturities), TIT offers superior carry with lower downside risk than comparable Carnival paper. | F28: 6-12 months; TIT ServiceCo stabilisation
A30: 3 | B30: Telefonica (TEF) — BBB-, ~185bps FV | C30: Vodafone (VOD) — BBB-, ~185bps FV | D30: 0 | E30: Telefonica and Vodafone trade at similar spread levels (~160-200bps) despite meaningfully different credit trajectories. Vodafone faces ongoing headwinds from its German cable integration, Vantage Towers earn-out obligations, and a balance sheet that remains stretched at ~2.8x Net Debt/EBITDA. Telefonica has made material progress deleveraging its domestic Spanish operations and its LatAm JV structures provide geographic diversification without full consolidation of debt. Long TEF / Short VOD is a relative value expression of divergent management execution risk within the same shadow rating band. | F30: 12-24 months; sector technicals driven
