Workbook

Sheet Cover
B7: ● | E7: STRICTLY CONFIDENTIAL — NOT FOR DISTRIBUTION
E8: MERGER & ACQUISITION ANALYSIS | ALL-CASH TRANSACTION
B10: H | E10: Hewlett Packard Enterprise
B11: P | E11: Acquisition of Juniper Networks
B12: E
E13: Project Olive · M&A Financial Model · January 2024
B14: ×
B16: J
B17: N | E17: This model presents a comprehensive merger & acquisition analysis of Hewlett Packard Enterprise Co. (NYSE: HPE) and its proposed acquisition of Juniper Networks, Inc. (NYSE: JNPR) for an aggregate consideration of approximately $13.7 billion, representing $40.00 per share in an all-cash transaction announced January 9, 2024.
B18: P
B19: R
E22: KEY DEAL STATISTICS
E23: 40 | G23: 0.324 | I23: $13,696mm
E24: Offer Price per Share | G24: Premium to 52-Week High | I24: Enterprise Value
E26: 2.5x / 2.4x | G26: 14.4x / 14.5x | I26: ~$500mm
E27: EV / LTM | NTM Revenue | G27: EV / LTM | NTM EBITDA | I27: Run-Rate Cost Synergies
E29: All-Cash | G29: $10,000mm | I29: $6,492mm
E30: Consideration Structure | G30: New Debt Financing | I30: Implied Goodwill

Sheet ToC
C4: STRICTLY CONFIDENTIAL — NOT FOR DISTRIBUTION
C7: Table of Contents
C8: HPE Acquisition of Juniper Networks — M&A Financial Model
C9: Project Olive · January 2024 · All-Cash Transaction · $13.7bn Enterprise Value
C12: # | D12: SECTION | E12: DESCRIPTION | F12: TAB
C13: 1 | D13: Executive Summary | E13: Transaction rationale, key highlights, deal structure and management overview | F13: Ex. Sum.
C14: 2 | D14: Transaction Assumptions | E14: Offer price, consideration structure, deal timeline and key deal terms | F14: Tx. Assum.
C15: 3 | D15: Sources & Uses | E15: Financing structure, debt tranches, pro forma capitalization and use of proceeds | F15: S&U
C16: 4 | D16: Acquirer Standalone | E16: HPE historical financials — income statement, balance sheet, cash flow statement | F16: Acq. SA
C17: 5 | D17: Target Standalone | E17: Juniper Networks historical financials, estimates and key operating metrics | F17: Tgt. SA
C18: 6 | D18: Synergy Assumptions | E18: Revenue and cost synergy build, phase-in schedule, integration costs and PV | F18: Synergies
C19: 7 | D19: PPA & BS Adjustments | E19: Purchase price allocation, intangible step-ups, DTL and amortization schedule | F19: PPA
C20: 8 | D20: Pro Forma Financials | E20: Combined pro forma income statement, balance sheet and cash flow statement | F20: PF Fins.
C21: 9 | D21: Accretion-Dilution Analysis | E21: EPS bridge, accretion / (dilution) summary, sensitivity and consideration mix | F21: Acc./Dil.
C22: 10 | D22: Valuation | E22: Trading comps, transaction comps, DCF analysis and football field summary | F22: Valuation
C24: This model has been prepared for internal purposes only. All projections are based on publicly available information and management assumptions.
F25: 45292

Sheet Executive Summary
M1: EPS Bridge
M2: Item | N2: Base | O2: Value
M3: SA EPS | N3: 0 | O3: ='Accretion-Dilution Analysis'!C34 -> 1.1336933
C4: STRICTLY CONFIDENTIAL — NOT FOR DISTRIBUTION | M4: {=+ JNPR NI} -> #NAME? | N4: ='Accretion-Dilution Analysis'!C34 -> 1.1336933 | O4: ='Target Standalone'!G31/'Accretion-Dilution Analysis'!C32 -> 0.50595563
M5: – PPA Amort | N5: ='Accretion-Dilution Analysis'!C34+'Target Standalone'!G31/'Accretion-Dilution Analysis'!C32 -> 1.639649 | O5: ='Accretion-Dilution Analysis'!C22/'Accretion-Dilution Analysis'!C32 -> -0.24906247
M6: – Interest | N6: 0 | O6: ='Accretion-Dilution Analysis'!C24/'Accretion-Dilution Analysis'!C32 -> -0.34817629
C7: Executive Summary | M7: {=+ Synergies} -> #NAME? | N7: 0 | O7: =('Accretion-Dilution Analysis'!C25+'Accretion-Dilution Analysis'!C26+'Accretion-Dilution Analysis'!C27)/'Accretion-Dilution Analysis'!C32 -> -0.025077275
C8: HPE Acquisition of Juniper Networks — Project Olive · $13.7bn All-Cash Transaction | M8: PF EPS | N8: 0 | O8: ='Accretion-Dilution Analysis'!C33 -> 0.48280284
C9: Announcement Date: January 9, 2024 · Expected Close: Q4 2024 · Offer: $40.00/share (All-Cash) · Premium: 32.4%
M10: Synergy Ramp
M11: Year | N11: Gross Synergies | O11: Net Synergies
C12: I. TRANSACTION OVERVIEW | M12: Year 1 | N12: ='Synergy Assumptions'!C20 -> 125.32289 | O12: ='Synergy Assumptions'!C35 -> -41.774296
C13: DEAL TERMS | H13: STRATEGIC RATIONALE | M13: Year 2 | N13: ='Synergy Assumptions'!D20 -> 250.64578 | O13: ='Synergy Assumptions'!D35 -> 83.548592
C14: Acquiror | D14: Hewlett Packard Enterprise Co. (HPE) | H14: ▪ AI-Driven Networking | I14: Positions HPE at the forefront of AI networking with Juniper's Mist AI platform | M14: Year 3 | N14: ='Synergy Assumptions'!E20 -> 401.03324 | O14: ='Synergy Assumptions'!E35 -> 401.03324
C15: Target | D15: Juniper Networks, Inc. (JNPR) | H15: ▪ Scale & Market Share | I15: Creates #2 enterprise networking player; combined revenue of ~$31.4bn | M15: Year 4 | N15: ='Synergy Assumptions'!F20 -> 501.29155 | O15: ='Synergy Assumptions'!F35 -> 501.29155
C16: Transaction Type | D16: All-Cash Acquisition | H16: ▪ Cost Synergies | I16: ~$500mm run-rate cost synergies by Year 4; 25% phased in Year 1 | M16: Steady State | N16: ='Synergy Assumptions'!G20 -> 501.29155 | O16: ='Synergy Assumptions'!G35 -> 167.09718
C17: Offer Price | D17: $40.00 per share | H17: ▪ Cross-Selling Upside | I17: Significant HPE/Aruba + Juniper portfolio bundling across shared enterprise base
C18: Enterprise Value | D18: $13,696mm | H18: ▪ Margin Expansion | I18: PF EBITDA margin expands from 13.7% to 15.3% at full synergy run-rate | M18: PF Revenue & EBITDA
M19: Entity | N19: Revenue ($mm) | O19: EBITDA ($mm)
C20: II. FINANCIAL SNAPSHOT — Key Pro Forma Metrics & Accretion Analysis | M20: HPE Standalone | N20: ='Acquirer Standalone'!G8 -> 30432.576 | O20: ='Acquirer Standalone'!G22 -> 4918.3825
M21: JNPR Standalone | N21: ='Target Standalone'!G8 -> 5731.435 | O21: ='Target Standalone'!G22 -> 941.98046
M22: Pro Forma | N22: ='Pro forma Financials'!H8 -> 31389.1 | O22: ='Pro forma Financials'!H21 -> 4298.8866
M23: PF + Synergies | N23: ='Pro forma Financials'!D87 -> 31890.392 | O23: ='Pro forma Financials'!D88 -> 4800.1782
C36: III. PRO FORMA FINANCIAL SUMMARY ($mm)
C37: METRIC | E37: HPE STANDALONE | F37: JNPR STANDALONE | H37: PRO FORMA (Y1) | I37: w/ RUN-RATE SYN.
C38: Revenue ($mm) | E38: ='Acquirer Standalone'!G8 -> 30432.576 | F38: ='Target Standalone'!G8 -> 5731.435 | H38: ='Pro forma Financials'!H8 -> 31389.1 | I38: ='Pro forma Financials'!D87 -> 31890.392
C39: Gross Profit ($mm) | E39: ='Acquirer Standalone'!G11 -> 10374.908 | F39: ='Target Standalone'!G11 -> 3497.5404 | H39: ='Pro forma Financials'!H11 -> 10869.6
C40: Gross Margin (%) | E40: ='Acquirer Standalone'!G12 -> 0.34091456 | F40: ='Target Standalone'!G12 -> 0.61023817 | H40: ='Pro forma Financials'!H12 -> 0.34628581
C41: EBITDA ($mm) | E41: ='Acquirer Standalone'!G22 -> 4918.3825 | F41: ='Target Standalone'!G22 -> 941.98046 | H41: ='Pro forma Financials'!H21 -> 4298.8866 | I41: ='Pro forma Financials'!D88 -> 4800.1782
C42: EBITDA Margin (%) | E42: ='Acquirer Standalone'!G23 -> 0.16161571 | F42: ='Target Standalone'!G23 -> 0.16435334 | H42: ='Pro forma Financials'!H22 -> 0.13695476 | I42: =IFERROR('Pro forma Financials'!D88/'Pro forma Financials'!D87,"-") -> 0.15052114
C43: EBIT ($mm) | E43: ='Acquirer Standalone'!G19 -> 2171.9371 | F43: ='Target Standalone'!G19 -> 751.46851 | H43: ='Pro forma Financials'!H18 -> 1052.1927
C44: IV. ACCRETION / (DILUTION) & CREDIT SUMMARY
C45: EPS METRIC | D45: YEAR 1E | E45: YEAR 2E | F45: YEAR 3E | H45: CREDIT METRIC | I45: PRE-SYN. | J45: RUN-RATE SYN.
C46: Standalone EPS ($) | D46: ='Accretion-Dilution Analysis'!C34 -> 1.1336933 | E46: ='Accretion-Dilution Analysis'!D34 -> 1.2240753 | F46: ='Accretion-Dilution Analysis'!E34 -> 1.3231461 | H46: Total Debt ($mm) | I46: ='Pro forma Financials'!C93 -> 25566.1 | J46: ='Pro forma Financials'!C93 -> 25566.1
C47: Pro Forma EPS ($) | D47: ='Accretion-Dilution Analysis'!C33 -> 0.48280284 | E47: ='Accretion-Dilution Analysis'!D33 -> 0.70556551 | F47: ='Accretion-Dilution Analysis'!E33 -> 0.99522359 | H47: Cash ($mm) | I47: ='Pro forma Financials'!C94 -> 3168.2 | J47: ='Pro forma Financials'!D94 -> 3168.2
C48: EPS Accretion / (Dil.) | D48: ='Accretion-Dilution Analysis'!C40 -> -0.65089051 | E48: ='Accretion-Dilution Analysis'!D40 -> -0.51850975 | F48: ='Accretion-Dilution Analysis'!E40 -> -0.32792246 | H48: Net Debt ($mm) | I48: ='Pro forma Financials'!C95 -> 22397.9 | J48: ='Pro forma Financials'!D95 -> 22397.9
C49: % Accretion / (Dil.) | D49: ='Accretion-Dilution Analysis'!C41 -> -0.57413278 | E49: ='Accretion-Dilution Analysis'!D41 -> -0.42359303 | F49: ='Accretion-Dilution Analysis'!E41 -> -0.24783542 | H49: EBITDA ($mm) | I49: ='Pro forma Financials'!C88 -> 4298.8866 | J49: ='Pro forma Financials'!D88 -> 4800.1782
H50: Gross Leverage (x) | I50: ='Pro forma Financials'!C96 -> 5.9471445 | J50: ='Pro forma Financials'!D96 -> 5.3260731
H51: Net Leverage (x) | I51: ='Pro forma Financials'!C97 -> 5.210163 | J51: ='Pro forma Financials'!D97 -> 4.666056
C52: This document is strictly confidential. Financial projections are based on publicly available information and management assumptions and do not constitute investment advice. · January 2024

Sheet Transaction Assumptions
B1: ■ Blue = Input | D1: ■ Black = Formula
A2: Transaction Assumptions
A4: I. DEAL OVERVIEW | G4: IV. CONSIDERATION MIX
B5: Item | D5: Entry | G5: Item | H5: Amount ($mm) | I5: % of Total | J5: Rate / Notes
B6: Acquiror | D6: Hewlett Packard Enterprise (HPE) | G6: Equity Consideration
B7: Target | D7: Juniper Networks | G7: Cash on Hand (Acquiror) | H7: 3036 | I7: =IF(H18=0,0,H7/H18) -> 0.23289353 | J7: Cash on hand + existing facilities
B8: Transaction Type | D8: All-Cash | G8: Stock Consideration | H8: 0 | I8: =IF(H18=0,0,H8/H18) -> 0 | J8: N/A — All-Cash Deal
B9: Announcement Date | D9: 45300 | G9: Total Equity Consideration | H9: =H7+H8 -> 3036 | I9: =IF(H18=0,0,H9/H18) -> 0.23289353 | J9: 100% Cash
B10: Expected Close Date | D10: 45363 | G10: Debt Financing
B11: Acquiror Fiscal Year-End | D11: 46326 | G11: Revolving Credit Facility (RCF) | H11: 0 | I11: =IF(H18=0,0,H11/H18) -> 0 | J11: Undrawn — backup liquidity
B12: Target Fiscal Year-End | D12: 46387 | G12: Term Loan A (TLA) | H12: 4000 | I12: =IF(H18=0,0,H12/H18) -> 0.30684259 | J12: SOFR + 125 bps
G13: Term Loan B (TLB) | H13: 0 | I13: =IF(H18=0,0,H13/H18) -> 0 | J13: N/A
A14: II. OFFER PRICE & PURCHASE PRICE | G14: Senior Unsecured Notes (5-Year) | H14: 3000 | I14: =IF(H18=0,0,H14/H18) -> 0.23013194 | J14: ~5.90% fixed
B15: Offer Price Analysis | G15: Senior Unsecured Notes (10-Year) | H15: 3000 | I15: =IF(H18=0,0,H15/H18) -> 0.23013194 | J15: ~6.10% fixed
B16: Reference | C16: 52-Wk High | D16: 1-Day Prior | E16: Offer Price | G16: Total Debt Financing | H16: =SUM(H11:H15) -> 10000 | I16: =1-I9 -> 0.76710647
B17: Share Price ($) | C17: 36.84 | D17: 30.3 | E17: 40
B18: Premium to Reference | C18: — | D18: =IF(D17=0,0,E17/D17-1) -> 0.32013201 | E18: =IF(C17=0,0,E17/C17-1) -> 0.08577633 | G18: Total Consideration | H18: =H9+H16 -> 13036 | I18: 1
B19: Purchase Price Calculation
B20: Shares Outstanding Basic (mm) | C20: ='Target Standalone'!F35 -> 320 | G20: Acquiror Equity Assumptions
B21: Diluted Shares Options/RSUs (mm) | C21: ='Target Standalone'!F36-C20 -> 5.9 | G21: Acquiror Share Price at Signing ($) | H21: 15.91
B22: Total Fully Diluted Shares (mm) | C22: =C20+C21 -> 325.9 | G22: Acquiror Shares to be Issued (mm) | H22: =IF(H21=0,0,H8/H21) -> 0
B23: Offer Price per Share ($) | C23: =E17 -> 40 | G23: Exchange Ratio | H23: =IF(H8=0,0,C23/H21) -> 0
B24: Equity Value ($mm) | C24: =C22*C23 -> 13036 | G24: Acquiror Shares Outstanding (Pre-Deal, mm) | H24: 1322.3
B25: (+) Target Total Debt ($mm) | C25: ='Target Standalone'!F55+'Target Standalone'!F60 -> 1746.1 | G25: Pro Forma Acquiror Dilution (%) | H25: =IF(H24+H22=0,0,H22/(H24+H22)) -> 0
B26: (–) Target Cash & Equivalents ($mm) | C26: ='Target Standalone'!F40 -> 1221.3
B27: Enterprise Value ($mm) | C27: =C24+C25-C26 -> 13560.8
A29: III. VALUATION MULTIPLES (IMPLIED)
B30: Metric | C30: LTM | D30: NTM | E30: FY+1E
B31: Revenue ($mm) | C31: ='Target Standalone'!F8 -> 5564.5 | D31: ='Target Standalone'!G8 -> 5731.435
B32: EBITDA ($mm) | C32: ='Target Standalone'!F22 -> 952.5 | D32: ='Target Standalone'!G22 -> 941.98046
B33: EBIT ($mm) | C33: ='Target Standalone'!F19 -> 760.3 | D33: ='Target Standalone'!G19 -> 751.46851
B34: EPS ($) | C34: ='Target Standalone'!F34 -> 0.9812826 | D34: ='Target Standalone'!G34 -> 2.0430734
B35: EV / Revenue | C35: =IF(C31=0,0,C27/C31) -> 2.4370204 | D35: =IF(D31=0,0,C27/D31) -> 2.3660392 | E35: =IF(E31=0,0,C27/E31) -> 0
B36: EV / EBITDA | C36: =IF(C32=0,0,C27/C32) -> 14.23706 | D36: =IF(D32=0,0,C27/D32) -> 14.396052 | E36: =IF(E32=0,0,C27/E32) -> 0
B37: EV / EBIT | C37: =IF(C33=0,0,C27/C33) -> 17.836117 | D37: =IF(D33=0,0,C27/D33) -> 18.045733 | E37: =IF(E33=0,0,C27/E33) -> 0
B38: P / E | C38: =IF(C34=0,0,C23/C34) -> 40.762977 | D38: =IF(D34=0,0,C23/D34) -> 19.578347 | E38: =IF(E34=0,0,C23/E34) -> 0
A40: V. TRANSACTION FEES & PPA ADJUSTMENTS | G40: VI. KEY DEAL TERMS & CONDITIONS
B41: Item | C41: Amount ($mm) | G41: Governing Agreement | H41: Definitive Agreement (Merger Agreement) signed January 9, 2024
B42: Advisory Fees — Sell-Side | C42: 65 | G42: Regulatory Approvals Required | H42: U.S. DOJ, EU (EC), China (SAMR), UK (CMA) : all cleared
B43: Advisory Fees — Buy-Side | C43: 40 | G43: Financing Condition | H43: No financing condition: HPE committed financing secured at signing
B44: Legal & Other Professional Fees | C44: 30 | G44: Termination / Break-Up Fee | H44: $550mm (~4.2% of Equity Value) payable by Juniper if deal terminated
B45: Total Transaction Fees | C45: =SUM(C42:C44) -> 135 | G45: Closing Conditions | H45: Juniper shareholder approval (obtained); regulatory clearances; no MAE
B46: Financing Fees (Debt Issuance Costs) | C46: 75 | G46: Accounting Treatment | H46: Acquisition Method (ASC 805); Juniper fully consolidated post-close
B47: Net Working Capital Adjustment | C47: 0 | G47: Post-Close Integration Notes | H47: HPE targeting $450mm+ in annualized synergies by Year 3; Juniper to operate as standalone BU
B48: Fair Value Step-Up (PPA Estimate)
B49: Estimated Goodwill | C49: =C27-(C25-C26+C48+C47) -> 13036

Sheet Synergy Assumptions
B1: ■ Blue = Input | D1: ■ Black = Formula
A2: Synergy Assumptions
A4: I. SYNERGY PHASE-IN SCHEDULE ($mm) | I4: IV. SYNERGY ASSUMPTIONS & NOTES
B5: Synergy Category | C5: Year 1 | D5: Year 2 | E5: Year 3 | F5: Year 4 | G5: Steady State | I5: Assumption / Driver | J5: Value | K5: Notes
B6: Revenue Synergies | I6: Revenue Synergy Ramp (% of SS) | J6: 0
B7: Cross-Selling Opportunities | C7: 0 | D7: 0 | E7: =D7 -> 0 | F7: =E7 -> 0 | G7: =F7 -> 0 | I7: Cost Synergy Ramp (% of SS) | J7: 25% / 50% / 80% / 100%
B8: New Product Bundling | C8: 0 | D8: 0 | E8: =D8 -> 0 | F8: =E8 -> 0 | G8: =F8 -> 0 | I8: Steady State Achieved (Year) | J8: 2028
B9: Geographic Expansion | C9: 0 | D9: =0 -> 0 | E9: =D9 -> 0 | F9: =E9 -> 0 | G9: =F9 -> 0 | I9: Synergy Discount Rate (%) | J9: =10% -> 0.1
B10: Total Revenue Synergies | C10: =SUM(C7:C9) -> 0 | D10: 0 | E10: =D10 -> 0 | F10: =E10 -> 0 | G10: =F10 -> 0 | I10: PV of Synergies ($mm) | J10: =IF(J9=0,0,(C20/(1+J9)^1 + D20/(1+J9)^2 + E20/(1+J9)^3 + F20/(1+J9)^4 + G20/J9/(1+J9)^4)) -> 4388.655
I11: Combined Pro Forma Revenue ($mm) | J11: ='Acquirer Standalone'!K8+'Target Standalone'!K8 -> 44003.862
B12: Cost Synergies | I12: Synergies as % of Combined Revenue | J12: =IF(J11=0,0,G20/J11) -> 0.01139199
B13: Headcount Reduction / Redundancies | C13: =25%*G13 -> 32.281601 | D13: =50%*G13 -> 64.563202 | E13: =80%*G13 -> 103.30112 | F13: =100%*(G13) -> 129.1264 | G13: =1%*('Acquirer Standalone'!K13+'Acquirer Standalone'!K15+'Target Standalone'!K13+'Target Standalone'!K15) -> 129.1264 | I13: Management Confidence Level | J13: HIGH
B14: Facilities Consolidation | C14: =25%*G14 -> 33.002897 | D14: =50%*G14 -> 66.005793 | E14: =80%*G14 -> 105.60927 | F14: =100%*G14 -> 132.01159 | G14: =0.3%*('Acquirer Standalone'!K8+'Target Standalone'!K8) -> 132.01159
B15: Procurement / Supply Chain | C15: =25%*G15 -> 27.035494 | D15: =50%*G15 -> 54.070988 | E15: =80%*G15 -> 86.513582 | F15: =100%*G15 -> 108.14198 | G15: =0.4%*('Acquirer Standalone'!K10+'Target Standalone'!K10) -> 108.14198 | I15: Synergy Value Attribution
B16: IT Systems Integration | C16: =25%*G16 -> 11.000966 | D16: =50%*G16 -> 22.001931 | E16: =80%*G16 -> 35.20309 | F16: =100%*G16 -> 44.003862 | G16: =0.1%*('Acquirer Standalone'!K8+'Target Standalone'!K8) -> 44.003862 | I16: Steady-State Gross Synergies ($mm) | J16: =G20 -> 501.29155
B17: G&A / Corporate Overhead | C17: =25%*G17 -> 22.001931 | D17: =50%*G17 -> 44.003862 | E17: =80%*G17 -> 70.40618 | F17: =100%*G17 -> 88.007724 | G17: =0.2%*('Acquirer Standalone'!K8+'Target Standalone'!K8) -> 88.007724 | I17: PV of Synergies (Perpetuity) | J17: =IF(J9=0,0,G20/J9) -> 5012.9155
B18: Total Cost Synergies | C18: =SUM(C13:C17) -> 125.32289 | D18: =SUM(D13:D17) -> 250.64578 | E18: =SUM(E13:E17) -> 401.03324 | F18: =SUM(F13:F17) -> 501.29155 | G18: =SUM(G13:G17) -> 501.29155 | I18: Transaction Premium Paid ($mm) | J18: ='Transaction Assumptions'!C24*('Transaction Assumptions'!D18) -> 4173.2409
I19: Implied Synergy Capture Required (%) | J19: =IF(J17=0,0,J18/J17) -> 0.83249775
B20: Total Gross Synergies | C20: =C10+C18 -> 125.32289 | D20: =D10+D18 -> 250.64578 | E20: =E10+E18 -> 401.03324 | F20: =F10+F18 -> 501.29155 | G20: =G10+G18 -> 501.29155
A22: II. INTEGRATION COSTS ($mm)
B23: Integration Cost Category | C23: Year 1 | D23: Year 2 | E23: Year 3 | F23: Year 4 | G23: Total
B24: Severance & Retention | C24: =ROUND(C29*0.45,0) -> 75 | D24: 0 | E24: 0 | F24: 0
B25: Facilities & Relocation | C25: =ROUND(C29*0.2,0) -> 33 | D25: 0 | E25: 0 | F25: 0
B26: IT Systems Integration | C26: =ROUND(C29*0.15,0) -> 25 | D26: 0 | E26: 0 | F26: 0
B27: Professional Fees (Integration) | C27: =ROUND(C29*0.15,0) -> 25 | D27: 0 | E27: 0 | F27: 0
B28: Other Integration Costs | C28: =C29-C24-C25-C26-C27 -> 9.0971849 | D28: 0 | E28: 0 | F28: 0
B29: Total Integration Costs | C29: =(G20/1.5)*(1/2) -> 167.09718 | D29: =C29 -> 167.09718 | E29: 0 | F29: 0 | G29: =SUM(C29:F29) -> 334.19437
A31: III. NET SYNERGIES SUMMARY ($mm)
B32: Summary | C32: Year 1 | D32: Year 2 | E32: Year 3 | F32: Year 4 | G32: Steady State
B33: Total Gross Synergies | C33: =C20 -> 125.32289 | D33: =D20 -> 250.64578 | E33: =E20 -> 401.03324 | F33: =F20 -> 501.29155 | G33: =G20 -> 501.29155
B34: (–) Integration Costs | C34: =C29 -> 167.09718 | D34: =D29 -> 167.09718 | E34: =E29 -> 0 | F34: =F29 -> 0 | G34: =G29 -> 334.19437
B35: Net Synergies | C35: =C33-C34 -> -41.774296 | D35: =D33-D34 -> 83.548592 | E35: =E33-E34 -> 401.03324 | F35: =F33-F34 -> 501.29155 | G35: =G33-G34 -> 167.09718
B36: Cumulative Net Synergies | C36: =C35 -> -41.774296 | D36: =C36+D35 -> 41.774296 | E36: =D36+E35 -> 442.80754 | F36: =E36+F35 -> 944.09909 | G36: =F36+G35 -> 1111.1963

Sheet Acquirer Standalone
B1: ■ Blue = Input (Actual or Assumption) | F1: ■ Black = Formula
A2: Acquirer Standalone Financials — Hewlett Packard Enterprise Co. (HPE)
B4: ($mm, Fiscal Year Ending October 31) | C4: ◄ Actuals ► | G4: ◄ Estimates / Forecasts ►
B5: in $mm | C5: FY2020A | D5: FY2021A | E5: FY2022A | F5: FY2023A | G5: FY2024E | H5: FY2025E | I5: FY2026E | J5: FY2027E | K5: FY2028E
A7: I. INCOME STATEMENT
B8: Revenue | C8: 26944 | D8: 27865 | E8: 28108 | F8: 29107 | G8: =F8*(1+G9) -> 30432.576 | H8: =G8*(1+H9) -> 32122.846 | I8: =H8*(1+I9) -> 34228.225 | J8: =I8*(1+J9) -> 35787.029 | K8: =J8*(1+K9) -> 36701.083
B9: YoY Growth (%) | C9: — | D9: =(D8/C8)-1 -> 0.034182007 | E9: =(E8/D8)-1 -> 0.0087206173 | F9: =(F8/E8)-1 -> 0.035541483 | G9: =F9+1% -> 0.045541483 | H9: =G9+1% -> 0.055541483 | I9: =H9+1% -> 0.065541483 | J9: =I9-2% -> 0.045541483 | K9: =J9-2% -> 0.025541483
B10: Cost of Revenue | C10: 18892 | D10: 18762 | E10: 19283 | F10: 19184 | G10: =G8-G11 -> 20057.668 | H10: =H8-H11 -> 21171.7 | I10: =I8-I11 -> 22559.325 | J10: =J8-J11 -> 23586.71 | K10: =K8-K11 -> 24189.15
B11: Gross Profit | C11: =C8-C10 -> 8052 | D11: =D8-D10 -> 9103 | E11: =E8-E10 -> 8825 | F11: =F8-F10 -> 9923 | G11: =G8*G12 -> 10374.908 | H11: =H8*H12 -> 10951.146 | I11: =I8*I12 -> 11668.9 | J11: =J8*J12 -> 12200.319 | K11: =K8*K12 -> 12511.934
B12: Gross Margin (%) | C12: =C11/C8 -> 0.29884204 | D12: =D11/D8 -> 0.32668222 | E12: =E11/E8 -> 0.31396755 | F12: =F11/F8 -> 0.34091456 | G12: =F12 -> 0.34091456 | H12: =G12 -> 0.34091456 | I12: =H12 -> 0.34091456 | J12: =I12 -> 0.34091456 | K12: =J12 -> 0.34091456
B13: Research & Development | C13: 1874 | D13: 1979 | E13: 2045 | F13: 2349 | G13: =G8*G14 -> 2455.9769 | H13: =H8*H14 -> 2592.3855 | I13: =I8*I14 -> 2762.2943 | J13: =J8*J14 -> 2888.0933 | K13: =K8*K14 -> 2961.8595
B14: as % of revenue | C14: =C13/C8 -> 0.069551663 | D14: =D13/D8 -> 0.071020994 | E14: =E13/E8 -> 0.072755088 | F14: =F13/F8 -> 0.080702237 | G14: =F14 -> 0.080702237 | H14: =G14 -> 0.080702237 | I14: =H14 -> 0.080702237 | J14: =I14 -> 0.080702237 | K14: =J14 -> 0.080702237
B15: Selling, General & Administrative | C15: 4624 | D15: 4929 | E15: 4941 | F15: 5160 | G15: =G16*G8 -> 5394.9941 | H15: =H16*H8 -> 5694.64 | I15: =I16*I8 -> 6067.8752 | J15: =J16*J8 -> 6344.2152 | K15: =K16*K8 -> 6506.2559
B16: as % of revenue | C16: =C15/C8 -> 0.1716152 | D16: =D15/D8 -> 0.17688857 | E16: =E15/E8 -> 0.17578625 | F16: =F15/F8 -> 0.17727694 | G16: =F16 -> 0.17727694 | H16: =G16 -> 0.17727694 | I16: =H16 -> 0.17727694 | J16: =I16 -> 0.17727694 | K16: =J16 -> 0.17727694
B17: Other Operating Expenses | C17: 1030 | D17: 966 | E17: 492 | F17: 352 | G17: =F17 -> 352 | H17: =G17 -> 352 | I17: =H17 -> 352 | J17: =I17 -> 352 | K17: =J17 -> 352
B18: Total Operating Expenses | C18: =C13+C15+C17+C10 -> 26420 | D18: =D13+D15+D17+D10 -> 26636 | E18: =E13+E15+E17+E10 -> 26761 | F18: =F13+F15+F17+F10 -> 27045 | G18: =G13+G15+G17+G10 -> 28260.639 | H18: =H13+H15+H17+H10 -> 29810.726 | I18: =I13+I15+I17+I10 -> 31741.495 | J18: =J13+J15+J17+J10 -> 33171.019 | K18: =K13+K15+K17+K10 -> 34009.265
B19: EBIT (Operating Income) | C19: =C8-C18 -> 524 | D19: =D8-D18 -> 1229 | E19: =E8-E18 -> 1347 | F19: =F8-F18 -> 2062 | G19: =G8-G18 -> 2171.9371 | H19: =H8-H18 -> 2312.1204 | I19: =I8-I18 -> 2486.7307 | J19: =J8-J18 -> 2616.0108 | K19: =K8-K18 -> 2691.8182
B20: EBIT Margin (%) | C20: =C19/C8 -> 0.019447743 | D20: =D19/D8 -> 0.044105509 | E20: =E19/E8 -> 0.0479223 | F20: =F19/F8 -> 0.070842065 | G20: =G19/G8 -> 0.071368823 | H20: =H19/H8 -> 0.071977443 | I20: =I19/I8 -> 0.072651466 | J20: =J19/J8 -> 0.073099411 | K20: =K19/K8 -> 0.073344379
B21: Depreciation & Amortization | C21: 2625 | D21: 2597 | E21: 2480 | F21: 2616 | G21: =-G140 -> 2746.4453 | H21: =-H140 -> 2832.4067 | I21: =-I140 -> 2993.1389 | J21: =-J140 -> 3237.6239 | K21: =-K140 -> 3580.8432
B22: EBITDA | C22: =C19+C21 -> 3149 | D22: =D19+D21 -> 3826 | E22: =E19+E21 -> 3827 | F22: =F19+F21 -> 4678 | G22: =G19+G21 -> 4918.3825 | H22: =H19+H21 -> 5144.527 | I22: =I19+I21 -> 5479.8696 | J22: =J19+J21 -> 5853.6347 | K22: =K19+K21 -> 6272.6614
B23: EBITDA Margin (%) | C23: =C22/C8 -> 0.11687203 | D23: =D22/D8 -> 0.13730486 | E23: =E22/E8 -> 0.13615341 | F23: =F22/F8 -> 0.16071735 | G23: =G22/G8 -> 0.16161571 | H23: =H22/H8 -> 0.16015166 | I23: =I22/I8 -> 0.16009798 | J23: =J22/J8 -> 0.16356861 | K23: =K22/K8 -> 0.17091216
B24: Interest Expense | C24: 256 | D24: 138 | E24: 1045 | F24: 0 | G24: =G170 -> 528.96075 | H24: =H170 -> 538.16026 | I24: =I170 -> 569.19482 | J24: =J170 -> 621.12001 | K24: =K170 -> 702.80865
B25: Interest Income | C25: 0 | D25: 0 | E25: 0 | F25: 0 | G25: =0 -> 0 | H25: =0 -> 0 | I25: =0 -> 0 | J25: =0 -> 0 | K25: =0 -> 0
B26: Other Non-Operating (Income) / Expense | C26: 56 | D26: -21 | E26: 1045 | F26: -64 | G26: =0 -> 0 | H26: =0 -> 0 | I26: =0 -> 0 | J26: =0 -> 0 | K26: =0 -> 0
B27: Pre-Tax Income (EBT) | C27: -442 | D27: 3587 | E27: 876 | F27: 2230 | G27: =G19-G24+G25-G26 -> 1642.9764 | H27: =H19-H24+H25-H26 -> 1773.9601 | I27: =I19-I24+I25-I26 -> 1917.5359 | J27: =J19-J24+J25-J26 -> 1994.8907 | K27: =K19-K24+K25-K26 -> 1989.0095
B28: Pre-Tax Margin (%) | C28: =C27/C8 -> -0.016404394 | D28: =D27/D8 -> 0.12872779 | E28: =E27/E8 -> 0.031165504 | F28: =F27/F8 -> 0.076613873 | G28: =G27/G8 -> 0.053987424 | H28: =H27/H8 -> 0.05522425 | I28: =I27/I8 -> 0.056022067 | J28: =J27/J8 -> 0.055743401 | K28: =K27/K8 -> 0.054194845
B29: Income Tax Expense | C29: -120 | D29: 160 | E29: 8 | F29: 205 | G29: =G27*G30 -> 151.03595 | H29: =H27*H30 -> 163.07705 | I29: =I27*I30 -> 176.27572 | J29: =J27*J30 -> 183.38682 | K29: =K27*K30 -> 182.84617
B30: Effective Tax Rate (%) | C30: =IF(C27=0,0,C29/C27) -> 0.27149321 | D30: =IF(D27=0,0,D29/D27) -> 0.04460552 | E30: =IF(E27=0,0,E29/E27) -> 0.0091324201 | F30: =IF(F27=0,0,F29/F27) -> 0.091928251 | G30: =F30 -> 0.091928251 | H30: =G30 -> 0.091928251 | I30: =H30 -> 0.091928251 | J30: =I30 -> 0.091928251 | K30: =J30 -> 0.091928251
B31: Net Income | C31: =C27-C29 -> -322 | D31: =D27-D29 -> 3427 | E31: =E27-E29 -> 868 | F31: =F27-F29 -> 2025 | G31: =G27-G29 -> 1491.9404 | H31: =H27-H29 -> 1610.883 | I31: =I27-I29 -> 1741.2602 | J31: =J27-J29 -> 1811.5039 | K31: =K27-K29 -> 1806.1633
B32: Net Margin (%) | C32: =C31/C8 -> -0.011950713 | D32: =D31/D8 -> 0.12298582 | E32: =E31/E8 -> 0.030880888 | F32: =F31/F8 -> 0.069570894 | G32: =G31/G8 -> 0.049024455 | H32: =H31/H8 -> 0.050147581 | I32: =I31/I8 -> 0.050872056 | J32: =J31/J8 -> 0.050619008 | K32: =K31/K8 -> 0.049212807
B33: EPS — Basic ($) | C33: -0.2488 | D33: 2.618 | E33: 0.6662 | F33: 1.5589 | G33: =G31/G35 -> 1.14853 | H33: =H31/H35 -> 1.2400947 | I33: =I31/I35 -> 1.340462 | J33: =J31/J35 -> 1.3945373 | K33: =K31/K35 -> 1.390426
B34: EPS — Diluted ($) | C34: -0.2488 | D34: 2.5767 | E34: 0.6566 | F34: 1.5388 | G34: =G31/G36 -> 1.1336933 | H34: =H31/H36 -> 1.2240753 | I34: =I31/I36 -> 1.3231461 | J34: =J31/J36 -> 1.3765227 | K34: =K31/K36 -> 1.3724645
B35: Shares Outstanding — Basic (mm) | C35: 1294 | D35: 1309 | E35: 1303 | F35: 1299 | G35: =F35 -> 1299 | H35: =G35 -> 1299 | I35: =H35 -> 1299 | J35: =I35 -> 1299 | K35: =J35 -> 1299
B36: Shares Outstanding — Diluted (mm) | C36: 1294 | D36: 1330 | E36: 1322 | F36: 1316 | G36: =F36 -> 1316 | H36: =G36 -> 1316 | I36: =H36 -> 1316 | J36: =I36 -> 1316 | K36: =J36 -> 1316
A38: II. BALANCE SHEET
B39: Current Assets
B40: Cash & Cash Equivalents | C40: 4621 | D40: 4332 | E40: 4763 | F40: 3676 | G40: =F40+G93 -> 3910.9874 | H40: =G40+H93 -> 3757.6623 | I40: =H40+I93 -> 3240.4196 | J40: =I40+J93 -> 2374.9998 | K40: =J40+K93 -> 1013.5226
B41: Accounts Receivable, net | C41: 7688 | D41: 7911 | E41: 7623 | F41: 7024 | G41: =G119 -> 7343.8834 | H41: =H119 -> 7751.7735 | I41: =I119 -> 8259.8363 | J41: =J119 -> 8636.0015 | K41: =K119 -> 8856.5778
B42: Inventories | C42: 2387 | D42: 4511 | E42: 5161 | F42: 4607 | G42: =G127 -> 4816.8096 | H42: =H127 -> 5084.3424 | I42: =I127 -> 5417.5777 | J42: =J127 -> 5664.3022 | K42: =K127 -> 5808.9769
B43: Prepaid Expenses & Other Current Assets | C43: 992 | D43: 2060 | E43: 2883 | F43: 2650 | G43: =G134 -> 2946.0568 | H43: =H134 -> 3109.6852 | I43: =I134 -> 3313.4985 | J43: =J134 -> 3464.4002 | K43: =K134 -> 3552.8861
B44: Total Current Assets | C44: =C40+C41+C42+C43 -> 15688 | D44: =D40+D41+D42+D43 -> 18814 | E44: =E40+E41+E42+E43 -> 20430 | F44: =F40+F41+F42+F43 -> 17957 | G44: =SUM(G40:G43) -> 19017.737 | H44: =SUM(H40:H43) -> 19703.463 | I44: =SUM(I40:I43) -> 20231.332 | J44: =SUM(J40:J43) -> 20139.704 | K44: =SUM(K40:K43) -> 19231.963
B45: Non-Current Assets
B46: Property, Plant & Equipment, net | C46: 6054 | D46: 6497 | E46: 6638 | F46: 6969 | G46: =G145 -> 7571.3646 | H46: =H145 -> 8452.9354 | I46: =I145 -> 9690.7399 | J46: =J145 -> 11400.524 | K46: =K145 -> 13753.99
B47: Goodwill | C47: 18306 | D47: 18017 | E47: 18306 | F47: 17988 | G47: =F47 -> 17988 | H47: =G47 -> 17988 | I47: =H47 -> 17988 | J47: =I47 -> 17988 | K47: =J47 -> 17988
B48: Intangible Assets, net | C48: 1128 | D48: 1103 | E48: 1022 | F48: 733 | G48: =F48 -> 733 | H48: =G48 -> 733 | I48: =H48 -> 733 | J48: =I48 -> 733 | K48: =J48 -> 733
B49: Long-Term Investments | C49: 7848 | D49: 7706 | E49: 7171 | F49: 7523 | G49: =F49 -> 7523 | H49: =G49 -> 7523 | I49: =H49 -> 7523 | J49: =I49 -> 7523 | K49: =J49 -> 7523
B50: Other Non-Current Assets | C50: 3324 | D50: 4200 | E50: 5354 | F50: 5157 | G50: =F50 -> 5157 | H50: =G50 -> 5157 | I50: =H50 -> 5157 | J50: =I50 -> 5157 | K50: =J50 -> 5157
B51: Total Non-Current Assets | C51: =C46+C47+C48+C49+C50 -> 36660 | D51: =D46+D47+D48+D49+D50 -> 37523 | E51: =E46+E47+E48+E49+E50 -> 38491 | F51: =F46+F47+F48+F49+F50 -> 38370 | G51: =SUM(G46:G50) -> 38972.365 | H51: =SUM(H46:H50) -> 39853.935 | I51: =SUM(I46:I50) -> 41091.74 | J51: =SUM(J46:J50) -> 42801.524 | K51: =SUM(K46:K50) -> 45154.99
B52: TOTAL ASSETS | C52: 51803 | D52: 54015 | E52: 57699 | F52: 57153 | G52: =G44+G51 -> 57990.102 | H52: =H44+H51 -> 59557.399 | I52: =I44+I51 -> 61323.072 | J52: =J44+J51 -> 62941.228 | K52: =K44+K51 -> 64386.953
B53: Current Liabilities
B54: Accounts Payable | C54: 5595 | D54: 5383 | E54: 7004 | F54: 7136 | G54: =G153 -> 7763.2163 | H54: =H153 -> 8212.0434 | I54: =I153 -> 8768.7231 | J54: =J153 -> 9129.1138 | K54: =K153 -> 9320.7821
B55: Short-Term Debt & Current Portion of LTD | C55: 4425 | D55: 3943 | E55: 3744 | F55: 4274 | G55: =F55 -> 4274 | H55: =G55 -> 4274 | I55: =H55 -> 4274 | J55: =I55 -> 4274 | K55: =J55 -> 4274
B56: Accrued Liabilities | C56: 1522 | D56: 1391 | E56: 1778 | F56: 1724 | G56: =F56 -> 1724 | H56: =G56 -> 1724 | I56: =H56 -> 1724 | J56: =I56 -> 1724 | K56: =J56 -> 1724
B57: Other Current Liabilities | C57: 7431 | D57: 7873 | E57: 7992 | F57: 7805 | G57: =F57 -> 7805 | H57: =G57 -> 7805 | I57: =H57 -> 7805 | J57: =I57 -> 7805 | K57: =J57 -> 7805
B58: Total Current Liabilities | C58: 19159 | D58: 18738 | E58: 20687 | F58: 21882 | G58: =SUM(G54:G57) -> 21566.216 | H58: =SUM(H54:H57) -> 22015.043 | I58: =SUM(I54:I57) -> 22571.723 | J58: =SUM(J54:J57) -> 22932.114 | K58: =SUM(K54:K57) -> 23123.782
B59: Non-Current Liabilities
B60: Long-Term Debt | C60: 9395 | D60: 13084 | E60: 10834 | F60: 8453 | G60: =F60 -> 8453 | H60: =G60 -> 8453 | I60: =H60 -> 8453 | J60: =I60 -> 8453 | K60: =J60 -> 8453
B61: Deferred Tax Liabilities | C61: 311 | D61: 0 | E61: 494 | F61: 326 | G61: =F61 -> 326 | H61: =G61 -> 326 | I61: =H61 -> 326 | J61: =I61 -> 326 | K61: =J61 -> 326
B62: Other Non-Current Liabilities | C62: 5789 | D62: 6097 | E62: 5667 | F62: 5371 | G62: =F62 -> 5371 | H62: =G62 -> 5371 | I62: =H62 -> 5371 | J62: =I62 -> 5371 | K62: =J62 -> 5371
B63: Total Non-Current Liabilities | C63: =C60+C61+C62 -> 15495 | D63: =D60+D61+D62 -> 19181 | E63: =E60+E61+E62 -> 16995 | F63: =F60+F61+F62 -> 14150 | G63: =SUM(G60:G62) -> 14150 | H63: =SUM(H60:H62) -> 14150 | I63: =SUM(I60:I62) -> 14150 | J63: =SUM(J60:J62) -> 14150 | K63: =SUM(K60:K62) -> 14150
B64: TOTAL LIABILITIES | C64: 34654 | D64: 37919 | E64: 37682 | F64: 35915 | G64: =G58+G63 -> 35716.216 | H64: =H58+H63 -> 36165.043 | I64: =I58+I63 -> 36721.723 | J64: =J58+J63 -> 37082.114 | K64: =K58+K63 -> 37273.782
B65: Shareholders' Equity
B66: Common Stock & Additional Paid-In Capital | C66: 28457 | D66: 28363 | E66: 28483 | F66: 28212
B67: Retained Earnings | C67: -7632 | D67: -8375 | E67: -5597 | F67: -5350
B68: Accumulated Other Comprehensive Income (Loss) | C68: -437 | D68: -477 | E68: -466 | F68: -638
B69: Treasury Stock | C69: -3313 | D69: -3480 | E69: -2464 | F69: -2487
B70: Total Shareholders' Equity | C70: =C52-C64 -> 17149 | D70: =D52-D64 -> 16096 | E70: =E52-E64 -> 20017 | F70: =F52-F64 -> 21238 | G70: =G163 -> 22273.886 | H70: =H163 -> 23392.355 | I70: =I163 -> 24601.349 | J70: =J163 -> 25859.114 | K70: =K163 -> 27113.171
B71: TOTAL LIABILITIES & EQUITY | C71: =C64+C70 -> 51803 | D71: =D64+D70 -> 54015 | E71: =E64+E70 -> 57699 | F71: =F64+F70 -> 57153 | G71: =G64+G70 -> 57990.102 | H71: =H64+H70 -> 59557.399 | I71: =I64+I70 -> 61323.072 | J71: =J64+J70 -> 62941.228 | K71: =K64+K70 -> 64386.953
B72: Balance Sheet Check (Assets = L+E) | C72: =IF(ABS(C52-C71)<1,"✓","✗ " & TEXT(C52-C71,"$#,##0")) -> ✓ | D72: =IF(ABS(D52-D71)<1,"✓","✗ " & TEXT(D52-D71,"$#,##0")) -> ✓ | E72: =IF(ABS(E52-E71)<1,"✓","✗ " & TEXT(E52-E71,"$#,##0")) -> ✓ | F72: =IF(ABS(F52-F71)<1,"✓","✗ " & TEXT(F52-F71,"$#,##0")) -> ✓ | G72: =IF(ABS(G52-G71)<1,"✓","✗ MISMATCH") -> ✓ | H72: =IF(ABS(H52-H71)<1,"✓","✗ MISMATCH") -> ✓ | I72: =IF(ABS(I52-I71)<1,"✓","✗ MISMATCH") -> ✓ | J72: =IF(ABS(J52-J71)<1,"✓","✗ MISMATCH") -> ✓ | K72: =IF(ABS(K52-K71)<1,"✓","✗ MISMATCH") -> ✓
A74: III. CASH FLOW STATEMENT
B75: Operating Activities
B76: Net Income | C76: =C31 -> -322 | D76: =D31 -> 3427 | E76: =E31 -> 868 | F76: =F31 -> 2025 | G76: =G31 -> 1491.9404 | H76: =H31 -> 1610.883 | I76: =I31 -> 1741.2602 | J76: =J31 -> 1811.5039 | K76: =K31 -> 1806.1633
B77: (+) Depreciation & Amortization | C77: =C21 -> 2625 | D77: =D21 -> 2597 | E77: =E21 -> 2480 | F77: =F21 -> 2616 | G77: =-G140 -> 2746.4453 | H77: =-H140 -> 2832.4067 | I77: =-I140 -> 2993.1389 | J77: =-J140 -> 3237.6239 | K77: =-K140 -> 3580.8432
B78: (+/–) Changes in Working Capital | C78: -2246 | D78: -1370 | E78: -570 | F78: -1032 | G78: =-(G41-F41)-(G42-F42)-(G43-F43)+(G54-F54) -> -198.53352 | H78: =-(H41-G41)-(H42-G42)-(H43-G43)+(H54-G54) -> -390.22418 | I78: =-(I41-H41)-(I42-H42)-(I43-H43)+(I54-H54) -> -488.43173 | J78: =-(J41-I41)-(J42-I42)-(J43-I43)+(J54-I54) -> -413.40064 | K78: =-(K41-J41)-(K42-J42)-(K43-J43)+(K54-J54) -> -262.06855
B79: (+/–) Other Operating Adjustments | C79: 2183 | D79: 1217 | E79: 1815 | F79: 819
B80: Cash Flow from Operations (CFO) | C80: =C76+C77+C78+C79 -> 2240 | D80: =D76+D77+D78+D79 -> 5871 | E80: =E76+E77+E78+E79 -> 4593 | F80: =F76+F77+F78+F79 -> 4428 | G80: =SUM(G76:G79) -> 4039.8522 | H80: =SUM(H76:H79) -> 4053.0655 | I80: =SUM(I76:I79) -> 4245.9673 | J80: =SUM(J76:J79) -> 4635.7272 | K80: =SUM(K76:K79) -> 5124.938
B81: Investing Activities
B82: Capital Expenditures (CapEx) | C82: -2383 | D82: -2502 | E82: -3122 | F82: -2828 | G82: =-G139 -> -3348.8099 | H82: =-H139 -> -3713.9775 | I82: =-I139 -> -4230.9433 | J82: =-J139 -> -4947.4084 | K82: =-K139 -> -5934.309
B83: Acquisitions, net of Cash | C83: -866 | D83: -505 | E83: 0 | F83: -761 | G83: 0 | H83: 0 | I83: 0 | J83: 0 | K83: 0
B84: Purchases / (Sales) of Investments | C84: -53 | D84: -45 | E84: 207 | F84: -6 | G84: 0 | H84: 0 | I84: 0 | J84: 0 | K84: 0
B85: Other Investing Activities | C85: 724 | D85: 256 | E85: 828 | F85: 311 | G85: 0 | H85: 0 | I85: 0 | J85: 0 | K85: 0
B86: Cash Flow from Investing (CFI) | C86: =C82+C83+C84+C85 -> -2578 | D86: =D82+D83+D84+D85 -> -2796 | E86: =E82+E83+E84+E85 -> -2087 | F86: =F82+F83+F84+F85 -> -3284 | G86: =SUM(G82:G85) -> -3348.8099 | H86: =SUM(H82:H85) -> -3713.9775 | I86: =SUM(I82:I85) -> -4230.9433 | J86: =SUM(J82:J85) -> -4947.4084 | K86: =SUM(K82:K85) -> -5934.309
B87: Financing Activities
B88: Debt Issuance / (Repayment) | C88: 1908 | D88: -2443 | E88: -696 | F88: -162 | G88: 0
B89: Share Issuance / (Repurchases) | C89: -355 | D89: -213 | E89: -512 | F89: -421 | G89: 0
B90: Dividends Paid | C90: -618 | D90: -625 | E90: -621 | F90: -619 | G90: =G159 -> -456.05488 | H90: =H159 -> -492.41314 | I90: =I159 -> -532.2667 | J90: =J159 -> -553.73873 | K90: =K159 -> -552.10623
B91: Other Financing Activities | C91: -43 | D91: -47 | E91: -67 | F91: -113
B92: Cash Flow from Financing (CFF) | C92: =C88+C89+C90+C91 -> 892 | D92: =D88+D89+D90+D91 -> -3328 | E92: =E88+E89+E90+E91 -> -1896 | F92: =F88+F89+F90+F91 -> -1315 | G92: =SUM(G88:G91) -> -456.05488 | H92: =SUM(H88:H91) -> -492.41314 | I92: =SUM(I88:I91) -> -532.2667 | J92: =SUM(J88:J91) -> -553.73873 | K92: =SUM(K88:K91) -> -552.10623
B93: Net Change in Cash | C93: =C80+C86+C92 -> 554 | D93: =D80+D86+D92 -> -253 | E93: =E80+E86+E92 -> 610 | F93: =F80+F86+F92 -> -171 | G93: =G80+G86+G92 -> 234.98744 | H93: =H80+H86+H92 -> -153.32511 | I93: =I80+I86+I92 -> -517.24272 | J93: =J80+J86+J92 -> -865.41986 | K93: =K80+K86+K92 -> -1361.4772
B94: Beginning Cash Balance | C94: 4076 | D94: =C95 -> 4630 | E94: =D95 -> 4377 | F94: =E95 -> 4987 | G94: =F95 -> 4816 | H94: =G95 -> 5050.9874 | I94: =H95 -> 4897.6623 | J94: =I95 -> 4380.4196 | K94: =J95 -> 3514.9998
B95: Ending Cash Balance | C95: =C94+C93 -> 4630 | D95: =D94+D93 -> 4377 | E95: =E94+E93 -> 4987 | F95: =F94+F93 -> 4816 | G95: =G93+G94 -> 5050.9874 | H95: =H93+H94 -> 4897.6623 | I95: =I93+I94 -> 4380.4196 | J95: =J93+J94 -> 3514.9998 | K95: =K93+K94 -> 2153.5226
A97: IV. KEY FINANCIAL METRICS & RATIOS
B98: Metric | C98: FY2020A | D98: FY2021A | E98: FY2022A | F98: FY2023A | G98: FY2024E | H98: FY2025E | I98: FY2026E | J98: FY2027E | K98: FY2028E
B99: Revenue Growth (%) | C99: =C9 -> — | D99: =D9 -> 0.034182007 | E99: =E9 -> 0.0087206173 | F99: =F9 -> 0.035541483 | G99: =IF(C8=0,0,G8/F8-1) -> 0.045541483 | H99: =IF(C8=0,0,H8/G8-1) -> 0.055541483 | I99: =IF(C8=0,0,I8/H8-1) -> 0.065541483 | J99: =IF(C8=0,0,J8/I8-1) -> 0.045541483 | K99: =IF(C8=0,0,K8/J8-1) -> 0.025541483
B100: Gross Margin (%) | C100: =C12 -> 0.29884204 | D100: =D12 -> 0.32668222 | E100: =E12 -> 0.31396755 | F100: =F12 -> 0.34091456 | G100: =G12 -> 0.34091456 | H100: =H12 -> 0.34091456 | I100: =I12 -> 0.34091456 | J100: =J12 -> 0.34091456 | K100: =K12 -> 0.34091456
B101: EBITDA Margin (%) | C101: =C23 -> 0.11687203 | D101: =D23 -> 0.13730486 | E101: =E23 -> 0.13615341 | F101: =F23 -> 0.16071735 | G101: =G23 -> 0.16161571 | H101: =H23 -> 0.16015166 | I101: =I23 -> 0.16009798 | J101: =J23 -> 0.16356861 | K101: =K23 -> 0.17091216
B102: EBIT Margin (%) | C102: =C20 -> 0.019447743 | D102: =D20 -> 0.044105509 | E102: =E20 -> 0.0479223 | F102: =F20 -> 0.070842065 | G102: =G20 -> 0.071368823 | H102: =H20 -> 0.071977443 | I102: =I20 -> 0.072651466 | J102: =J20 -> 0.073099411 | K102: =K20 -> 0.073344379
B103: Net Margin (%) | C103: =C32 -> -0.011950713 | D103: =D32 -> 0.12298582 | E103: =E32 -> 0.030880888 | F103: =F32 -> 0.069570894 | G103: =G32 -> 0.049024455 | H103: =H32 -> 0.050147581 | I103: =I32 -> 0.050872056 | J103: =J32 -> 0.050619008 | K103: =K32 -> 0.049212807
B104: CapEx / Revenue (%) | C104: =ABS(C82)/C8 -> 0.088442696 | D104: =ABS(D82)/D8 -> 0.089790059 | E104: =ABS(E82)/E8 -> 0.11107158 | F104: =ABS(F82)/F8 -> 0.097158759 | G104: =IF(G8=0,0,ABS(G82)/G8) -> 0.1100403 | H104: =IF(H8=0,0,ABS(H82)/H8) -> 0.11561795 | I104: =IF(I8=0,0,ABS(I82)/I8) -> 0.12360978 | J104: =IF(J8=0,0,ABS(J82)/J8) -> 0.13824585 | K104: =IF(K8=0,0,ABS(K82)/K8) -> 0.16169302
B105: Free Cash Flow ($mm) | C105: =C80+C82 -> -143 | D105: =D80+D82 -> 3369 | E105: =E80+E82 -> 1471 | F105: =F80+F82 -> 1600 | G105: =G80+G82 -> 691.04232 | H105: =H80+H82 -> 339.08803 | I105: =I80+I82 -> 15.023984 | J105: =J80+J82 -> -311.68113 | K105: =K80+K82 -> -809.37095
...

Sheet Target Standalone
B1: ■ Blue = Input (Actual or Assumption) | F1: ■ Black = Formula
A2: Target Standalone Financials : Juniper Networks, Inc. (JNPR)
B4: ($mm, Calendar Year Ending December 31) | C4: ◄ Actuals ► | G4: ◄ Estimates / Forecasts ►
B5: in $mm | C5: FY2020A | D5: FY2021A | E5: FY2022A | F5: FY2023A | G5: FY2024E | H5: FY2025E | I5: FY2026E | J5: FY2027E | K5: FY2028E
A7: I. INCOME STATEMENT
B8: Revenue | C8: 4445.1 | D8: 4735.4 | E8: 5301.2 | F8: 5564.5 | G8: =F8*(1+G9) -> 5731.435 | H8: =G8*(1+H9) -> 6189.9498 | I8: =H8*(1+I9) -> 6561.3468 | J8: =I8*(1+J9) -> 6955.0276 | K8: =J8*(1+K9) -> 7302.779
B9: YoY Growth (%) | C9: — | D9: =(D8/C8)-1 -> 0.065307867 | E9: =(E8/D8)-1 -> 0.11948304 | F9: =(F8/E8)-1 -> 0.049668 | G9: =3% -> 0.03 | H9: =G9+5% -> 0.08 | I9: =6% -> 0.06 | J9: =I9 -> 0.06 | K9: 0.05
B10: Cost of Revenue | C10: 1627.5 | D10: 1680.4 | E10: 2095.1 | F10: 2138.5 | G10: =G8-G11 -> 2233.8946 | H10: =H8-H11 -> 2412.6062 | I10: =I8-I11 -> 2557.3625 | J10: =J8-J11 -> 2710.8043 | K10: =K8-K11 -> 2846.3445
B11: Gross Profit | C11: =C8-C10 -> 2817.6 | D11: =D8-D10 -> 3055 | E11: =E8-E10 -> 3206.1 | F11: =F8-F10 -> 3426 | G11: =G8*G12 -> 3497.5404 | H11: =H8*H12 -> 3777.3436 | I11: =I8*I12 -> 4003.9842 | J11: =J8*J12 -> 4244.2233 | K11: =K8*K12 -> 4456.4345
B12: Gross Margin (%) | C12: =C11/C8 -> 0.6338665 | D12: =D11/D8 -> 0.64514085 | E12: =E11/E8 -> 0.6047876 | F12: =F11/F8 -> 0.61568874 | G12: =AVERAGE(E12:F12) -> 0.61023817 | H12: =G12 -> 0.61023817 | I12: =H12 -> 0.61023817 | J12: =I12 -> 0.61023817 | K12: =J12 -> 0.61023817
B13: Research & Development | C13: 958.4 | D13: 1007.2 | E13: 1036.1 | F13: 1144.4 | G13: =G14*G8 -> 1188.4292 | H13: =H14*H8 -> 1270.7284 | I13: =I14*I8 -> 1334.8223 | J13: =J14*J8 -> 1428.806 | K13: =K14*K8 -> 1499.8338
B14: as % of revenue | C14: =C13/C8 -> 0.2156082 | D14: =D13/D8 -> 0.21269587 | E14: =E13/E8 -> 0.19544631 | F14: =F13/F8 -> 0.20566089 | G14: =AVERAGE(C14:F14) -> 0.20735282 | H14: =AVERAGE(D14:G14) -> 0.20528897 | I14: =AVERAGE(E14:H14) -> 0.20343725 | J14: =AVERAGE(F14:I14) -> 0.20543498 | K14: =AVERAGE(G14:J14) -> 0.2053785
B15: Selling, General & Administrative | C15: 1169.6 | D15: 1293.6 | E15: 1382.9 | F15: 1489.4 | G15: =G16*G8 -> 1525.7427 | H15: =H16*H8 -> 1652.5759 | I15: =I16*I8 -> 1741.5616 | J15: =J16*J8 -> 1853.9875 | K15: =K16*K8 -> 1944.6913
B16: as % of revenue | C16: =C15/C8 -> 0.26312119 | D16: =D15/D8 -> 0.2731765 | E16: =E15/E8 -> 0.26086546 | F16: =F15/F8 -> 0.26766107 | G16: =AVERAGE(C16:F16) -> 0.26620606 | H16: =AVERAGE(D16:G16) -> 0.26697727 | I16: =AVERAGE(E16:H16) -> 0.26542746 | J16: =AVERAGE(F16:I16) -> 0.26656796 | K16: =AVERAGE(G16:J16) -> 0.26629469
B17: Other Operating Expenses | C17: 37.1 | D17: 39.5 | E17: 30.1 | F17: 31.9 | G17: =F17 -> 31.9 | H17: =G17 -> 31.9 | I17: =H17 -> 31.9 | J17: =I17 -> 31.9 | K17: =J17 -> 31.9
B18: Total Operating Expenses | C18: =C13+C15+C17 -> 2165.1 | D18: =D13+D15+D17 -> 2340.3 | E18: =E13+E15+E17 -> 2449.1 | F18: =F13+F15+F17 -> 2665.7 | G18: =G13+G15+G17 -> 2746.0719 | H18: =H13+H15+H17 -> 2955.2043 | I18: =I13+I15+I17 -> 3108.284 | J18: =J13+J15+J17 -> 3314.6935 | K18: =K13+K15+K17 -> 3476.4251
B19: EBIT (Operating Income) | C19: =C11-C18 -> 652.5 | D19: =D11-D18 -> 714.7 | E19: =E11-E18 -> 757 | F19: =F11-F18 -> 760.3 | G19: =G11-G18 -> 751.46851 | H19: =H11-H18 -> 822.1393 | I19: =I11-I18 -> 895.70028 | J19: =J11-J18 -> 929.5298 | K19: =K11-K18 -> 980.0094
B20: EBIT Margin (%) | C20: =C19/C8 -> 0.14679085 | D20: =D19/D8 -> 0.15092706 | E20: =E19/E8 -> 0.14279786 | F20: =F19/F8 -> 0.13663402 | G20: =G19/G8 -> 0.1311135 | H20: =H19/H8 -> 0.13281841 | I20: =I19/I8 -> 0.13651165 | J20: =J19/J8 -> 0.13364861 | K20: =K19/K8 -> 0.13419678
B21: Depreciation & Amortization | C21: 206.8 | D21: 275.4 | E21: 217.7 | F21: 192.2 | G21: =-G140 -> 190.51195 | H21: =-H140 -> 154.21901 | I21: =-I140 -> 127.98845 | J21: =-J140 -> 108.58422 | K21: =-K140 -> 93.846618
B22: EBITDA | C22: =C19+C21 -> 859.3 | D22: =D19+D21 -> 990.1 | E22: =E19+E21 -> 974.7 | F22: =F19+F21 -> 952.5 | G22: =G19+G21 -> 941.98046 | H22: =H19+H21 -> 976.35831 | I22: =I19+I21 -> 1023.6887 | J22: =J19+J21 -> 1038.114 | K22: =K19+K21 -> 1073.856
B23: EBITDA Margin (%) | C23: =C22/C8 -> 0.19331399 | D23: =D22/D8 -> 0.20908477 | E23: =E22/E8 -> 0.18386403 | F23: =F22/F8 -> 0.17117441 | G23: =G22/G8 -> 0.16435334 | H23: =H22/H8 -> 0.15773283 | I23: =I22/I8 -> 0.15601808 | J23: =J22/J8 -> 0.14926095 | K23: =K22/K8 -> 0.14704759
B24: Interest Expense | C24: 77 | D24: 50.8 | E24: 58.6 | F24: 80 | G24: =G168 -> 19.235218 | H24: =H168 -> 7.9266993 | I24: =0 -> 0 | J24: =0 -> 0 | K24: =0 -> 0
B25: Interest Income | C25: 36.3 | D25: 14.9 | E25: 19.6 | F25: 50.6 | G25: =0 -> 0 | H25: =0 -> 0 | I25: =-I168 -> 0.23795592 | J25: =-J168 -> 0.77100935 | K25: =-K168 -> 1.3546582
B26: Other Non-Operating (Income)/Expense | C26: 7.8 | D26: 19.1 | E26: 56.2 | F26: 5.6 | G26: =F26 -> 5.6 | H26: =G26 -> 5.6 | I26: =H26 -> 5.6 | J26: =I26 -> 5.6 | K26: =J26 -> 5.6
B27: Pre-Tax Income (EBT) | C27: 265.2 | D27: 310.1 | E27: 536.3 | F27: 349 | G27: =G19-G24+G25-G26 -> 726.63329 | H27: =H19-H24+H25-H26 -> 808.6126 | I27: =I19-I24+I25-I26 -> 890.33824 | J27: =J19-J24+J25-J26 -> 924.70081 | K27: =K19-K24+K25-K26 -> 975.76406
B28: Pre-Tax Margin (%) | C28: =C27/C8 -> 0.0596612 | D28: =D27/D8 -> 0.065485492 | E28: =E27/E8 -> 0.10116577 | F28: =F27/F8 -> 0.062719022 | G28: =G27/G8 -> 0.12678034 | H28: =H27/H8 -> 0.13063314 | I28: =I27/I8 -> 0.13569443 | J28: =J27/J8 -> 0.1329543 | K28: =K27/K8 -> 0.13361544
B29: Income Tax Expense | C29: 7.4 | D29: 57.4 | E29: 60.5 | F29: 29.2 | G29: =G27*G30 -> 60.795679 | H29: =H27*H30 -> 67.654693 | I29: =I27*I30 -> 74.492483 | J29: =J27*J30 -> 77.367518 | K29: =K27*K30 -> 81.639858
B30: Effective Tax Rate (%) | C30: =IF(C27=0,0,C29/C27) -> 0.027903469 | D30: =IF(D27=0,0,D29/D27) -> 0.18510158 | E30: =IF(E27=0,0,E29/E27) -> 0.11280999 | F30: =IF(F27=0,0,F29/F27) -> 0.083667622 | G30: =F30 -> 0.083667622 | H30: =G30 -> 0.083667622 | I30: =H30 -> 0.083667622 | J30: =I30 -> 0.083667622 | K30: =J30 -> 0.083667622
B31: Net Income | C31: =C27-C29 -> 257.8 | D31: =D27-D29 -> 252.7 | E31: =E27-E29 -> 475.8 | F31: =F27-F29 -> 319.8 | G31: =G27-G29 -> 665.83761 | H31: =H27-H29 -> 740.95791 | I31: =I27-I29 -> 815.84575 | J31: =J27-J29 -> 847.33329 | K31: =K27-K29 -> 894.1242
B32: Net Margin (%) | C32: =C31/C8 -> 0.057996446 | D32: =D31/D8 -> 0.053364024 | E32: =E31/E8 -> 0.089753263 | F32: =F31/F8 -> 0.057471471 | G32: =G31/G8 -> 0.11617293 | H32: =H31/H8 -> 0.11970338 | I32: =I31/I8 -> 0.1243412 | J32: =J31/J8 -> 0.12183033 | K32: =K31/K8 -> 0.12243616
B33: EPS — Basic ($) | C33: =IF(C35=0,0,C31/C35) -> 0.78026634 | D33: =IF(D35=0,0,D31/D35) -> 0.77897657 | E33: =IF(E35=0,0,E31/E35) -> 1.477181 | F33: =IF(F35=0,0,F31/F35) -> 0.999375 | G33: =IF(G35=0,0,G31/G35) -> 2.0807425 | H33: =IF(H35=0,0,H31/H35) -> 2.3154935 | I33: =IF(I35=0,0,I31/I35) -> 2.549518 | J33: =IF(J35=0,0,J31/J35) -> 2.6479165 | K33: =IF(K35=0,0,K31/K35) -> 2.7941381
B34: EPS — Diluted ($) | C34: =IF(C36=0,0,C31/C36) -> 0.76909308 | D34: =IF(D36=0,0,D31/D36) -> 0.76206273 | E34: =IF(E36=0,0,E31/E36) -> 1.4440061 | F34: =IF(F36=0,0,F31/F36) -> 0.9812826 | G34: =IF(G36=0,0,G31/G36) -> 2.0430734 | H34: =IF(H36=0,0,H31/H36) -> 2.2735744 | I34: =IF(I36=0,0,I31/I36) -> 2.5033622 | J34: =IF(J36=0,0,J31/J36) -> 2.5999794 | K34: =IF(K36=0,0,K31/K36) -> 2.7435538
B35: Shares Outstanding — Basic (mm) | C35: 330.4 | D35: 324.4 | E35: 322.1 | F35: 320 | G35: =F35 -> 320 | H35: =G35 -> 320 | I35: =H35 -> 320 | J35: =I35 -> 320 | K35: =J35 -> 320
B36: Shares Outstanding — Diluted (mm) | C36: 335.2 | D36: 331.6 | E36: 329.5 | F36: 325.9 | G36: =F36 -> 325.9 | H36: =G36 -> 325.9 | I36: =H36 -> 325.9 | J36: =I36 -> 325.9 | K36: =J36 -> 325.9
A38: II. BALANCE SHEET
B39: Current Assets
B40: Cash & Cash Equivalents | C40: 1793.2 | D40: 1255.2 | E40: 1105.6 | F40: 1221.3 | G40: =F40+G93 -> 1425.513 | H40: =G40+H93 -> 1613.9883 | I40: =H40+I93 -> 1841.2824 | J40: =I40+J93 -> 2054.5037 | K40: =J40+K93 -> 2287.9633
B41: Accounts Receivable, net | C41: 964.1 | D41: 994.4 | E41: 1227.3 | F41: 1044.1 | G41: =G119 -> 1075.423 | H41: =H119 -> 1161.4568 | I41: =I119 -> 1231.1443 | J41: =J119 -> 1305.0129 | K41: =K119 -> 1370.2636
B42: Inventories | C42: 221.9 | D42: 272.6 | E42: 619.4 | F42: 952.4 | G42: =G127 -> 994.88484 | H42: =H127 -> 1074.4756 | I42: =I127 -> 1138.9442 | J42: =J127 -> 1207.2808 | K42: =K127 -> 1267.6449
B43: Prepaid Expenses & Other Current Assets | C43: 292 | D43: 434.4 | E43: 664.8 | F43: 577.7 | G43: =G134 -> 656.89243 | H43: =H134 -> 709.44383 | I43: =I134 -> 752.01046 | J43: =J134 -> 797.13108 | K43: =K134 -> 836.98764
B44: Total Current Assets | C44: =C40+C41+C42+C43 -> 3271.2 | D44: =D40+D41+D42+D43 -> 2956.6 | E44: =E40+E41+E42+E43 -> 3617.1 | F44: =F40+F41+F42+F43 -> 3795.5 | G44: =SUM(G40:G43) -> 4152.7133 | H44: =SUM(H40:H43) -> 4559.3646 | I44: =SUM(I40:I43) -> 4963.3812 | J44: =SUM(J40:J43) -> 5363.9285 | K44: =SUM(K40:K43) -> 5762.8593
B45: Non-Current Assets
B46: Property, Plant & Equipment, net | C46: 946.9 | D46: 864.3 | E46: 808.4 | F46: 801.3 | G46: =G145 -> 708.22717 | H46: =H145 -> 647.21178 | I46: =I145 -> 610.86935 | J46: =J145 -> 594.89372 | K46: =K145 -> 597.1827
B47: Goodwill | C47: 3669.6 | D47: 3762.1 | E47: 3734.4 | F47: 3734.4 | G47: =F47 -> 3734.4 | H47: =G47 -> 3734.4 | I47: =H47 -> 3734.4 | J47: =I47 -> 3734.4 | K47: =J47 -> 3734.4
B48: Intangible Assets, net | C48: 266.7 | D48: 284.3 | E48: 160.5 | F48: 91.8 | G48: =F48 -> 91.8 | H48: =G48 -> 91.8 | I48: =H48 -> 91.8 | J48: =I48 -> 91.8 | K48: =J48 -> 91.8
B49: Long-Term Investments | C49: 901.9 | D49: 684.9 | E49: 467.3 | F49: 229.6 | G49: =F49 -> 229.6 | H49: =G49 -> 229.6 | I49: =H49 -> 229.6 | J49: =I49 -> 229.6 | K49: =J49 -> 229.6
B50: Other Non-Current Assets | C50: 322 | D50: 334.8 | E50: 539 | F50: 865.9 | G50: =F50 -> 865.9 | H50: =G50 -> 865.9 | I50: =H50 -> 865.9 | J50: =I50 -> 865.9 | K50: =J50 -> 865.9
B51: Total Non-Current Assets | C51: =C46+C47+C48+C49+C50 -> 6107.1 | D51: =D46+D47+D48+D49+D50 -> 5930.4 | E51: =E46+E47+E48+E49+E50 -> 5709.6 | F51: =F46+F47+F48+F49+F50 -> 5723 | G51: =SUM(G46:G50) -> 5629.9272 | H51: =SUM(H46:H50) -> 5568.9118 | I51: =SUM(I46:I50) -> 5532.5694 | J51: =SUM(J46:J50) -> 5516.5937 | K51: =SUM(K46:K50) -> 5518.8827
B52: TOTAL ASSETS | C52: 9378.3 | D52: 8887 | E52: 9326.7 | F52: 9518.5 | G52: =G44+G51 -> 9782.6405 | H52: =H44+H51 -> 10128.276 | I52: =I44+I51 -> 10495.951 | J52: =J44+J51 -> 10880.522 | K52: =K44+K51 -> 11281.742
B53: Current Liabilities
B54: Accounts Payable | C54: 277 | D54: 273.7 | E54: 347.4 | F54: 295.1 | G54: =G153 -> 271.80238 | H54: =H153 -> 297.57124 | I54: =I153 -> 313.04971 | J54: =J153 -> 331.83269 | K54: =K153 -> 347.06441
B55: Short-Term Debt & Current Portion of LTD | C55: 470.6 | D55: 47.2 | E55: 47.4 | F55: 46.4 | G55: =F55 -> 46.4 | H55: =G55 -> 46.4 | I55: =H55 -> 46.4 | J55: =I55 -> 46.4 | K55: =J55 -> 46.4
B56: Accrued Liabilities | C56: 270.7 | D56: 336 | E56: 306.1 | F56: 292.2 | G56: =F56 -> 292.2 | H56: =G56 -> 292.2 | I56: =H56 -> 292.2 | J56: =I56 -> 292.2 | K56: =J56 -> 292.2
B57: Other Current Liabilities | C57: 1142.8 | D57: 1219.6 | E57: 1378 | F57: 1470.3 | G57: =F57 -> 1470.3 | H57: =G57 -> 1470.3 | I57: =H57 -> 1470.3 | J57: =I57 -> 1470.3 | K57: =J57 -> 1470.3
B58: Total Current Liabilities | C58: 2161.1 | D58: 1876.5 | E58: 2078.9 | F58: 2104 | G58: =SUM(G54:G57) -> 2080.7024 | H58: =SUM(H54:H57) -> 2106.4712 | I58: =SUM(I54:I57) -> 2121.9497 | J58: =SUM(J54:J57) -> 2140.7327 | K58: =SUM(K54:K57) -> 2155.9644
B59: Non-Current Liabilities
B60: Long-Term Debt | C60: 1869.3 | D60: 1829 | E60: 1719 | F60: 1699.7 | G60: =F60 -> 1699.7 | H60: =G60 -> 1699.7 | I60: =H60 -> 1699.7 | J60: =I60 -> 1699.7 | K60: =J60 -> 1699.7
B61: Deferred Tax Liabilities | C61: 5.3 | D61: 8.1 | E61: 5.6 | F61: 12 | G61: =F61 -> 12 | H61: =G61 -> 12 | I61: =H61 -> 12 | J61: =I61 -> 12 | K61: =J61 -> 12
B62: Other Non-Current Liabilities | C62: 799.1 | D62: 856.5 | E62: 1048.1 | F62: 1210.1 | G62: =F62 -> 1210.1 | H62: =G62 -> 1210.1 | I62: =H62 -> 1210.1 | J62: =I62 -> 1210.1 | K62: =J62 -> 1210.1
B63: Total Non-Current Liabilities | C63: =C60+C61+C62 -> 2673.7 | D63: =D60+D61+D62 -> 2693.6 | E63: =E60+E61+E62 -> 2772.7 | F63: =F60+F61+F62 -> 2921.8 | G63: =SUM(G60:G62) -> 2921.8 | H63: =SUM(H60:H62) -> 2921.8 | I63: =SUM(I60:I62) -> 2921.8 | J63: =SUM(J60:J62) -> 2921.8 | K63: =SUM(K60:K62) -> 2921.8
B64: TOTAL LIABILITIES | C64: 4834.8 | D64: 4570.1 | E64: 4851.6 | F64: 5025.8 | G64: =G58+G63 -> 5002.5024 | H64: =H58+H63 -> 5028.2712 | I64: =I58+I63 -> 5043.7497 | J64: =J58+J63 -> 5062.5327 | K64: =K58+K63 -> 5077.7644
B65: Shareholders' Equity
B66: Common Stock & Additional Paid-In Capital | C66: 7156.9 | D66: 6972.6 | E66: 6846.4 | F66: 6740
B67: Retained Earnings | C67: -2669 | D67: -2653.6 | E67: -2375.5 | F67: -2296.4
B68: Accumulated Other Comprehensive Income (Loss) | C68: -36.2 | D68: -49 | E68: -79.1 | F68: -82.1
B69: Treasury Stock | C69: 57.7 | D69: 19 | E69: 61.5 | F69: 102.3
B70: Total Shareholders' Equity | C70: =C52-C64 -> 4543.5 | D70: =D52-D64 -> 4316.9 | E70: =E52-E64 -> 4475.1 | F70: =F52-F64 -> 4492.7 | G70: =G163 -> 4780.1381 | H70: =H163 -> 5100.0052 | I70: =I163 -> 5452.2009 | J70: =J163 -> 5817.9896 | K70: =K163 -> 6203.9776
B71: TOTAL LIABILITIES & EQUITY | C71: =C64+C70 -> 9378.3 | D71: =D64+D70 -> 8887 | E71: =E64+E70 -> 9326.7 | F71: =F64+F70 -> 9518.5 | G71: =G64+G70 -> 9782.6405 | H71: =H64+H70 -> 10128.276 | I71: =I64+I70 -> 10495.951 | J71: =J64+J70 -> 10880.522 | K71: =K64+K70 -> 11281.742
B72: Balance Sheet Check (Assets = L+E) | C72: =IF(ABS(C52-C71)<0.5,"✓","✗ " & TEXT(C52-C71,"$#,##0.0")) -> ✓ | D72: =IF(ABS(D52-D71)<0.5,"✓","✗ " & TEXT(D52-D71,"$#,##0.0")) -> ✓ | E72: =IF(ABS(E52-E71)<0.5,"✓","✗ " & TEXT(E52-E71,"$#,##0.0")) -> ✓ | F72: =IF(ABS(F52-F71)<0.5,"✓","✗ " & TEXT(F52-F71,"$#,##0.0")) -> ✓ | G72: =IF(ABS(G52-G71)<1,"✓","✗ MISMATCH") -> ✓ | H72: =IF(ABS(H52-H71)<1,"✓","✗ MISMATCH") -> ✓ | I72: =IF(ABS(I52-I71)<1,"✓","✗ MISMATCH") -> ✓ | J72: =IF(ABS(J52-J71)<1,"✓","✗ MISMATCH") -> ✓ | K72: =IF(ABS(K52-K71)<1,"✓","✗ MISMATCH") -> ✓
A74: III. CASH FLOW STATEMENT
B75: Operating Activities
B76: Net Income | C76: =C31 -> 257.8 | D76: =D31 -> 252.7 | E76: =E31 -> 475.8 | F76: =F31 -> 319.8 | G76: =G31 -> 665.83761 | H76: =H31 -> 740.95791 | I76: =I31 -> 815.84575 | J76: =J31 -> 847.33329 | K76: =K31 -> 894.1242
B77: (+) Depreciation & Amortization | C77: =C21 -> 206.8 | D77: =D21 -> 275.4 | E77: =E21 -> 217.7 | F77: =F21 -> 192.2 | G77: =G21 -> 190.51195 | H77: =H21 -> 154.21901 | I77: =I21 -> 127.98845 | J77: =J21 -> 108.58422 | K77: =K21 -> 93.846618
B78: (+/–) Changes in Working Capital | C78: -90.5 | D78: -199.1 | E78: -574.6 | F78: 70 | G78: =-(G41-F41)-(G42-F42)-(G43-F43)+(G54-F54) -> -176.29789 | H78: =-(H41-G41)-(H42-G42)-(H43-G43)+(H54-G54) -> -192.40716 | I78: =-(I41-H41)-(I42-H42)-(I43-H43)+(I54-H54) -> -161.24411 | J78: =-(J41-I41)-(J42-I42)-(J43-I43)+(J54-I54) -> -168.54295 | K78: =-(K41-J41)-(K42-J42)-(K43-J43)+(K54-J54) -> -150.23952
B79: (+/–) Other Operating Adjustments | C79: 232.3 | D79: 115.1 | E79: -16.5 | F79: 297.9
B80: Cash Flow from Operations (CFO) | C80: =C76+C77+C78+C79 -> 606.4 | D80: =D76+D77+D78+D79 -> 444.1 | E80: =E76+E77+E78+E79 -> 102.4 | F80: =F76+F77+F78+F79 -> 879.9 | G80: =SUM(G76:G78) -> 680.05167 | H80: =SUM(H76:H78) -> 702.76976 | I80: =SUM(I76:I78) -> 782.59009 | J80: =SUM(J76:J78) -> 787.37456 | K80: =SUM(K76:K78) -> 837.7313
B81: Investing Activities
B82: Capital Expenditures (CapEx) | C82: -100.4 | D82: -100 | E82: -105.1 | F82: -159.4 | G82: =-G139 -> -97.439118 | H82: =-H139 -> -93.203613 | I82: =-I139 -> -91.646026 | J82: =-J139 -> -92.608585 | K82: =-K139 -> -96.135596
B83: Acquisitions, net of Cash | C83: -484 | D83: -192.7 | E83: -14.6 | F83: -0.7 | G83: 0 | H83: 0 | I83: 0 | J83: 0 | K83: 0
B84: Purchases/(Sales) of Investments | C84: 250.7 | D84: 305.8 | E84: 435.6 | F84: 98.3 | G84: 0 | H84: 0 | I84: 0 | J84: 0 | K84: 0
B85: Other Investing Activities | C85: 44.8 | D85: 0.7 | E85: 2.5 | F85: -5.8 | G85: 0 | H85: 0 | I85: 0 | J85: 0 | K85: 0
B86: Cash Flow from Investing (CFI) | C86: =C82+C83+C84+C85 -> -288.9 | D86: =D82+D83+D84+D85 -> 13.8 | E86: =E82+E83+E84+E85 -> 318.4 | F86: =F82+F83+F84+F85 -> -67.6 | G86: =SUM(G82:G85) -> -97.439118 | H86: =SUM(H82:H85) -> -93.203613 | I86: =SUM(I82:I85) -> -91.646026 | J86: =SUM(J82:J85) -> -92.608585 | K86: =SUM(K82:K85) -> -96.135596
B87: Financing Activities
B88: Debt Issuance/(Repayment) | C88: 363.3 | D88: -423.8 | E88: 0 | F88: 0 | G88: =F88 -> 0 | H88: =G88 -> 0 | I88: =H88 -> 0 | J88: =I88 -> 0 | K88: =J88 -> 0
B89: Share Issuance/(Repurchases) | C89: -326.4 | D89: -387.1 | E89: -258 | F89: -335.7 | G89: =0 -> 0 | H89: =0 -> 0 | I89: =0 -> 0 | J89: =0 -> 0 | K89: =0 -> 0
B90: Dividends Paid | C90: -264.1 | D90: -259.1 | E90: -270.4 | F90: -280.8 | G90: =G159 -> -378.39952 | H90: =H159 -> -421.09083 | I90: =I159 -> -463.65005 | J90: =J159 -> -481.5446 | K90: =K159 -> -508.13616
B91: Other Financing Activities | C91: 4.8 | D91: -61.7 | E91: 0 | F91: -2.3 | G91: 0 | H91: 0 | I91: 0 | J91: 0 | K91: 0
B92: Cash Flow from Financing (CFF) | C92: =C88+C89+C90+C91 -> -222.4 | D92: =D88+D89+D90+D91 -> -1131.7 | E92: =E88+E89+E90+E91 -> -528.4 | F92: =F88+F89+F90+F91 -> -618.8 | G92: =SUM(G88:G91) -> -378.39952 | H92: =SUM(H88:H91) -> -421.09083 | I92: =SUM(I88:I91) -> -463.65005 | J92: =SUM(J88:J91) -> -481.5446 | K92: =SUM(K88:K91) -> -508.13616
B93: Net Change in Cash | D93: =D80+D86+D92 -> -673.8 | E93: =E80+E86+E92 -> -107.6 | F93: =F80+F86+F92 -> 193.5 | G93: =G92+G86+G80 -> 204.21303 | H93: =H92+H86+H80 -> 188.47531 | I93: =I92+I86+I80 -> 227.29402 | J93: =J92+J86+J80 -> 213.22137 | K93: =K92+K86+K80 -> 233.45955
B94: Beginning Cash Balance | D94: =C40 -> 1793.2 | E94: =D40 -> 1255.2 | F94: =E40 -> 1105.6 | G94: =F95 -> 1299.1 | H94: =G95 -> 1503.313 | I94: =H95 -> 1691.7883 | J94: =I95 -> 1919.0824 | K94: =J95 -> 2132.3037
B95: Ending Cash Balance | D95: =D94+D93 -> 1119.4 | E95: =E94+E93 -> 1147.6 | F95: =F94+F93 -> 1299.1 | G95: =G93+G94 -> 1503.313 | H95: =H93+H94 -> 1691.7883 | I95: =I93+I94 -> 1919.0824 | J95: =J93+J94 -> 2132.3037 | K95: =K93+K94 -> 2365.7633
A97: IV. KEY FINANCIAL METRICS & RATIOS
B98: Metric | C98: CY2020A | D98: CY2021A | E98: CY2022A | F98: CY2023A | G98: CY2024E | H98: CY2025E | I98: CY2026E | J98: CY2027E | K98: CY2028E
B99: Revenue Growth (%) | C99: =C9 -> — | D99: =D9 -> 0.065307867 | E99: =E9 -> 0.11948304 | F99: =F9 -> 0.049668 | G99: =IF(F8=0,0,G8/F8-1) -> 0.03 | H99: =IF(G8=0,0,H8/G8-1) -> 0.08 | I99: =IF(H8=0,0,I8/H8-1) -> 0.06 | J99: =IF(I8=0,0,J8/I8-1) -> 0.06 | K99: =IF(J8=0,0,K8/J8-1) -> 0.05
B100: Gross Margin (%) | C100: =C12 -> 0.6338665 | D100: =D12 -> 0.64514085 | E100: =E12 -> 0.6047876 | F100: =F12 -> 0.61568874 | G100: =G12 -> 0.61023817 | H100: =H12 -> 0.61023817 | I100: =I12 -> 0.61023817 | J100: =J12 -> 0.61023817 | K100: =K12 -> 0.61023817
B101: EBITDA Margin (%) | C101: =C23 -> 0.19331399 | D101: =D23 -> 0.20908477 | E101: =E23 -> 0.18386403 | F101: =F23 -> 0.17117441 | G101: =G23 -> 0.16435334 | H101: =H23 -> 0.15773283 | I101: =I23 -> 0.15601808 | J101: =J23 -> 0.14926095 | K101: =K23 -> 0.14704759
B102: EBIT Margin (%) | C102: =C20 -> 0.14679085 | D102: =D20 -> 0.15092706 | E102: =E20 -> 0.14279786 | F102: =F20 -> 0.13663402 | G102: =G20 -> 0.1311135 | H102: =H20 -> 0.13281841 | I102: =I20 -> 0.13651165 | J102: =J20 -> 0.13364861 | K102: =K20 -> 0.13419678
B103: Net Margin (%) | C103: =C32 -> 0.057996446 | D103: =D32 -> 0.053364024 | E103: =E32 -> 0.089753263 | F103: =F32 -> 0.057471471 | G103: =G32 -> 0.11617293 | H103: =H32 -> 0.11970338 | I103: =I32 -> 0.1243412 | J103: =J32 -> 0.12183033 | K103: =K32 -> 0.12243616
B104: CapEx / Revenue (%) | C104: =ABS(C82)/C8 -> 0.022586668 | D104: =ABS(D82)/D8 -> 0.02111754 | E104: =ABS(E82)/E8 -> 0.0198257 | F104: =ABS(F82)/F8 -> 0.02864588 | G104: =IF(G8=0,0,ABS(G82)/G8) -> 0.017000824 | H104: =IF(H8=0,0,ABS(H82)/H8) -> 0.015057249 | I104: =IF(I8=0,0,ABS(I82)/I8) -> 0.013967563 | J104: =IF(J8=0,0,ABS(J82)/J8) -> 0.013315344 | K104: =IF(K8=0,0,ABS(K82)/K8) -> 0.013164248
B105: Free Cash Flow ($mm) | C105: =C80+C82 -> 506 | D105: =D80+D82 -> 344.1 | E105: =E80+E82 -> -2.7 | F105: =F80+F82 -> 720.5 | G105: =G80+G82 -> 582.61255 | H105: =H80+H82 -> 609.56614 | I105: =I80+I82 -> 690.94407 | J105: =J80+J82 -> 694.76598 | K105: =K80+K82 -> 741.5957
...

Sheet Valuation
B1: ■ Blue = Input | D1: ■ Black = Formula | F1: ■ Yellow = Key Output
A2: Valuation Analysis : Juniper Networks, Inc. (JNPR)
A4: I. DISCOUNTED CASH FLOW (DCF) ANALYSIS
B5: A. Key DCF Assumptions
B6: Assumption | C6: Value | E6: Assumption | F6: Value
B7: Projection Period (Years) | C7: 5 | E7: Risk-Free Rate (%) | F7: 0.044
B8: WACC (%) | C8: =F12 -> 0.0920475 | E8: Equity Risk Premium (%) | F8: 0.055
B9: Terminal Growth Rate (%) | C9: 0.025 | E9: Beta (Levered) | F9: 1.15
B10: Tax Rate (%) | C10: 0.14 | E10: Cost of Debt (%) | F10: 0.054
B11: NTM EBITDA ($mm) | C11: 952.5 | E11: Target D / (D+E) (%) | F11: 0.25
B12: Exit EBITDA Multiple (x) | C12: 14 | E12: WACC Check (CAPM) | F12: =((F7+F9*F8)*(1-F11))+(F10*(1-C10)*F11) -> 0.0920475
B14: B. Unlevered Free Cash Flow Projections ($mm)
B15: FCF Build | C15: Year 1 | D15: Year 2 | E15: Year 3 | F15: Year 4 | G15: Year 5
B16: Revenue | C16: ='Target Standalone'!G8 -> 5731.435 | D16: ='Target Standalone'!H8 -> 6189.9498 | E16: ='Target Standalone'!I8 -> 6561.3468 | F16: ='Target Standalone'!J8 -> 6955.0276 | G16: ='Target Standalone'!K8 -> 7302.779
B17: YoY Growth (%) | C17: — | D17: =IF(C16=0,0,D16/C16-1) -> 0.08 | E17: =IF(D16=0,0,E16/D16-1) -> 0.06 | F17: =IF(E16=0,0,F16/E16-1) -> 0.06 | G17: =IF(F16=0,0,G16/F16-1) -> 0.05
B18: EBITDA | C18: ='Target Standalone'!G22 -> 941.98046 | D18: ='Target Standalone'!H22 -> 976.35831 | E18: ='Target Standalone'!I22 -> 1023.6887 | F18: ='Target Standalone'!J22 -> 1038.114 | G18: ='Target Standalone'!K22 -> 1073.856
B19: EBITDA Margin (%) | C19: =IF(C16=0,0,C18/C16) -> 0.16435334 | D19: =IF(D16=0,0,D18/D16) -> 0.15773283 | E19: =IF(E16=0,0,E18/E16) -> 0.15601808 | F19: =IF(F16=0,0,F18/F16) -> 0.14926095 | G19: =IF(G16=0,0,G18/G16) -> 0.14704759
B20: (–) D&A | C20: ='Target Standalone'!G21 -> 190.51195 | D20: ='Target Standalone'!H21 -> 154.21901 | E20: ='Target Standalone'!I21 -> 127.98845 | F20: ='Target Standalone'!J21 -> 108.58422 | G20: ='Target Standalone'!K21 -> 93.846618
B21: EBIT (NOPAT Pre-Tax) | C21: =C18-C20 -> 751.46851 | D21: =D18-D20 -> 822.1393 | E21: =E18-E20 -> 895.70028 | F21: =F18-F20 -> 929.5298 | G21: =G18-G20 -> 980.0094
B22: (–) Taxes on EBIT | C22: =C21*C10 -> 105.20559 | D22: =D21*C10 -> 115.0995 | E22: =E21*C10 -> 125.39804 | F22: =F21*C10 -> 130.13417 | G22: =G21*C10 -> 137.20132
B23: NOPAT (Net Operating Profit After Tax) | C23: =C21-C22 -> 646.26292 | D23: =D21-D22 -> 707.0398 | E23: =E21-E22 -> 770.30224 | F23: =F21-F22 -> 799.39563 | G23: =G21-G22 -> 842.80808
B24: (+) D&A Add-Back | C24: =C20 -> 190.51195 | D24: =D20 -> 154.21901 | E24: =E20 -> 127.98845 | F24: =F20 -> 108.58422 | G24: =G20 -> 93.846618
B25: (–) Capital Expenditures | C25: ='Target Standalone'!G82 -> -97.439118 | D25: ='Target Standalone'!H82 -> -93.203613 | E25: ='Target Standalone'!I82 -> -91.646026 | F25: ='Target Standalone'!J82 -> -92.608585 | G25: ='Target Standalone'!K82 -> -96.135596
B26: (–/+) Change in Working Capital | C26: =-('Target Standalone'!G26-'Target Standalone'!F26) -> 0 | D26: =-('Target Standalone'!H26-'Target Standalone'!G26) -> 0 | E26: =-('Target Standalone'!I26-'Target Standalone'!H26) -> 0 | F26: =-('Target Standalone'!J26-'Target Standalone'!I26) -> 0 | G26: =-('Target Standalone'!K26-'Target Standalone'!J26) -> 0
B27: Unlevered Free Cash Flow (UFCF) | C27: =C23+C24+C25+C26 -> 739.33575 | D27: =D23+D24+D25+D26 -> 768.05519 | E27: =E23+E24+E25+E26 -> 806.64467 | F27: =F23+F24+F25+F26 -> 815.37126 | G27: =G23+G24+G25+G26 -> 840.5191
B28: Discount Period | C28: =COLUMN()-2 -> 1 | D28: =COLUMN()-2 -> 2 | E28: =COLUMN()-2 -> 3 | F28: =COLUMN()-2 -> 4 | G28: =COLUMN()-2 -> 5
B29: Discount Factor (@ WACC) | C29: =1/(1+$C$8)^C28 -> 0.91571108 | D29: =1/(1+$C$8)^D28 -> 0.83852679 | E29: =1/(1+$C$8)^E28 -> 0.76784828 | F29: =1/(1+$C$8)^F28 -> 0.70312718 | G29: =1/(1+$C$8)^G28 -> 0.64386135
B30: PV of UFCF | C30: =C27*C29 -> 677.01794 | D30: =D27*D29 -> 644.03485 | E30: =E27*E29 -> 619.38072 | F30: =F27*F29 -> 573.30969 | G30: =G27*G29 -> 541.17776
B32: C. Terminal Value & Valuation Bridge ($mm)
B33: Method | C33: Value ($mm)
B34: Terminal Value — Exit Multiple Method | C34: =IFERROR(C11*C12,"-") -> 13335
B35: Terminal Value — Gordon Growth Model | C35: =IFERROR((G27*(1+C9))/(C8-C9),"-") -> 12849.578
B36: PV of Terminal Value (Exit Multiple) | C36: =IFERROR(C34/(1+C8)^C7,"-") -> 8585.8911
B37: PV of Terminal Value (Gordon Growth) | C37: =IFERROR(C35/(1+C8)^C7,"-") -> 8273.3466
B38: Sum of PV of UFCFs | C38: =IFERROR(SUM(C30:G30),"-") -> 3054.921
B39: Enterprise Value (Exit Multiple) | C39: =IFERROR(C36+C38,"-") -> 11640.812
B40: Enterprise Value (Gordon Growth) | C40: =IFERROR(C37+C38,"-") -> 11328.268
B42: D. Equity Value Bridge ($mm)
B43: Item | C43: Exit Multiple | D43: Gordon Growth
B44: Enterprise Value | C44: =IFERROR(C39,"-") -> 11640.812 | D44: =IFERROR(C40,"-") -> 11328.268
B45: (–) Total Debt | C45: ='Transaction Assumptions'!C25 -> 1746.1 | D45: ='Transaction Assumptions'!C25 -> 1746.1
B46: (+) Cash & Equivalents | C46: ='Transaction Assumptions'!C26 -> 1221.3 | D46: ='Transaction Assumptions'!C26 -> 1221.3
B47: (–) Minority Interest | C47: 0 | D47: 0
B48: Equity Value | C48: =IFERROR(C44-C45+C46-C47,"-") -> 11116.012 | D48: =IFERROR(D44-D45+D46-D47,"-") -> 10803.468
B49: Fully Diluted Shares (mm) | C49: ='Transaction Assumptions'!C22 -> 325.9 | D49: ='Transaction Assumptions'!C22 -> 325.9
B50: Implied Share Price ($) | C50: =IFERROR(IF(C49=0,"-",C48/C49),"-") -> 34.108659 | D50: =IFERROR(IF(D49=0,"-",D48/D49),"-") -> 33.14964
B51: Current Share Price ($) | C51: ='Transaction Assumptions'!D17 -> 30.3 | D51: ='Transaction Assumptions'!D17 -> 30.3
B52: Implied Premium / (Discount) | C52: =IFERROR(IF(C51=0,"-",C50/C51-1),"-") -> 0.12569833 | D52: =IFERROR(IF(D51=0,"-",D50/D51-1),"-") -> 0.094047517
B54: E. Sensitivity Analysis — Implied Share Price ($)
B55: EV — Exit Multiple Method | I55: EV — Gordon Growth Method
B56: WACC → | C56: 0.08 | D56: 0.09 | E56: 0.1 | F56: 0.11 | G56: 0.12 | I56: WACC → | J56: 0.08 | K56: 0.09 | L56: 0.1 | M56: 0.11 | N56: 0.12
B57: 12 | C57: =($C$11*B57/(1+C$56)^$C$7+$C$38-$C$45+$C$46-$C$47)/IF($C$49=0,1,$C$49) -> 31.632976 | D57: =($C$11*B57/(1+D$56)^$C$7+$C$38-$C$45+$C$46-$C$47)/IF($C$49=0,1,$C$49) -> 30.557952 | E57: =($C$11*B57/(1+E$56)^$C$7+$C$38-$C$45+$C$46-$C$47)/IF($C$49=0,1,$C$49) -> 29.540508 | F57: =($C$11*B57/(1+F$56)^$C$7+$C$38-$C$45+$C$46-$C$47)/IF($C$49=0,1,$C$49) -> 28.577078 | G57: =($C$11*B57/(1+G$56)^$C$7+$C$38-$C$45+$C$46-$C$47)/IF($C$49=0,1,$C$49) -> 27.664345 | I57: 0.01 | J57: =(($C$38+($G$27*(1+I57))/(J$56-I57))/(1+J$56)^$C$7)/IF($C$49=0,1,$C$49) -> 31.705719 | K57: =(($C$38+($G$27*(1+I57))/(K$56-I57))/(1+K$56)^$C$7)/IF($C$49=0,1,$C$49) -> 27.25459 | L57: =(($C$38+($G$27*(1+I57))/(L$56-I57))/(1+L$56)^$C$7)/IF($C$49=0,1,$C$49) -> 23.791657 | M57: =(($C$38+($G$27*(1+I57))/(M$56-I57))/(1+M$56)^$C$7)/IF($C$49=0,1,$C$49) -> 21.021477 | N57: =(($C$38+($G$27*(1+I57))/(N$56-I57))/(1+N$56)^$C$7)/IF($C$49=0,1,$C$49) -> 18.755929
B58: 13 | C58: =($C$11*B58/(1+C$56)^$C$7+$C$38-$C$45+$C$46-$C$47)/IF($C$49=0,1,$C$49) -> 33.6221 | D58: =($C$11*B58/(1+D$56)^$C$7+$C$38-$C$45+$C$46-$C$47)/IF($C$49=0,1,$C$49) -> 32.457491 | E58: =($C$11*B58/(1+E$56)^$C$7+$C$38-$C$45+$C$46-$C$47)/IF($C$49=0,1,$C$49) -> 31.35526 | F58: =($C$11*B58/(1+F$56)^$C$7+$C$38-$C$45+$C$46-$C$47)/IF($C$49=0,1,$C$49) -> 30.311544 | G58: =($C$11*B58/(1+G$56)^$C$7+$C$38-$C$45+$C$46-$C$47)/IF($C$49=0,1,$C$49) -> 29.322749 | I58: 0.02 | J58: =(($C$38+($G$27*(1+I58))/(J$56-I58))/(1+J$56)^$C$7)/IF($C$49=0,1,$C$49) -> 36.219276 | K58: =(($C$38+($G$27*(1+I58))/(K$56-I58))/(1+K$56)^$C$7)/IF($C$49=0,1,$C$49) -> 30.51723 | L58: =(($C$38+($G$27*(1+I58))/(L$56-I58))/(1+L$56)^$C$7)/IF($C$49=0,1,$C$49) -> 26.23824 | M58: =(($C$38+($G$27*(1+I58))/(M$56-I58))/(1+M$56)^$C$7)/IF($C$49=0,1,$C$49) -> 22.909159 | N58: =(($C$38+($G$27*(1+I58))/(N$56-I58))/(1+N$56)^$C$7)/IF($C$49=0,1,$C$49) -> 20.245971
B59: 14 | C59: =($C$11*B59/(1+C$56)^$C$7+$C$38-$C$45+$C$46-$C$47)/IF($C$49=0,1,$C$49) -> 35.611224 | D59: =($C$11*B59/(1+D$56)^$C$7+$C$38-$C$45+$C$46-$C$47)/IF($C$49=0,1,$C$49) -> 34.35703 | E59: =($C$11*B59/(1+E$56)^$C$7+$C$38-$C$45+$C$46-$C$47)/IF($C$49=0,1,$C$49) -> 33.170012 | F59: =($C$11*B59/(1+F$56)^$C$7+$C$38-$C$45+$C$46-$C$47)/IF($C$49=0,1,$C$49) -> 32.046009 | G59: =($C$11*B59/(1+G$56)^$C$7+$C$38-$C$45+$C$46-$C$47)/IF($C$49=0,1,$C$49) -> 30.981154 | I59: 0.03 | J59: =(($C$38+($G$27*(1+I59))/(J$56-I59))/(1+J$56)^$C$7)/IF($C$49=0,1,$C$49) -> 42.538255 | K59: =(($C$38+($G$27*(1+I59))/(K$56-I59))/(1+K$56)^$C$7)/IF($C$49=0,1,$C$49) -> 34.867417 | L59: =(($C$38+($G$27*(1+I59))/(L$56-I59))/(1+L$56)^$C$7)/IF($C$49=0,1,$C$49) -> 29.383847 | M59: =(($C$38+($G$27*(1+I59))/(M$56-I59))/(1+M$56)^$C$7)/IF($C$49=0,1,$C$49) -> 25.268761 | N59: =(($C$38+($G$27*(1+I59))/(N$56-I59))/(1+N$56)^$C$7)/IF($C$49=0,1,$C$49) -> 22.067133
B60: 15 | C60: =($C$11*B60/(1+C$56)^$C$7+$C$38-$C$45+$C$46-$C$47)/IF($C$49=0,1,$C$49) -> 37.600348 | D60: =($C$11*B60/(1+D$56)^$C$7+$C$38-$C$45+$C$46-$C$47)/IF($C$49=0,1,$C$49) -> 36.256568 | E60: =($C$11*B60/(1+E$56)^$C$7+$C$38-$C$45+$C$46-$C$47)/IF($C$49=0,1,$C$49) -> 34.984763 | F60: =($C$11*B60/(1+F$56)^$C$7+$C$38-$C$45+$C$46-$C$47)/IF($C$49=0,1,$C$49) -> 33.780475 | G60: =($C$11*B60/(1+G$56)^$C$7+$C$38-$C$45+$C$46-$C$47)/IF($C$49=0,1,$C$49) -> 32.639559 | I60: 0.04 | J60: =(($C$38+($G$27*(1+I60))/(J$56-I60))/(1+J$56)^$C$7)/IF($C$49=0,1,$C$49) -> 52.016725 | K60: =(($C$38+($G$27*(1+I60))/(K$56-I60))/(1+K$56)^$C$7)/IF($C$49=0,1,$C$49) -> 40.957679 | L60: =(($C$38+($G$27*(1+I60))/(L$56-I60))/(1+L$56)^$C$7)/IF($C$49=0,1,$C$49) -> 33.57799 | M60: =(($C$38+($G$27*(1+I60))/(M$56-I60))/(1+M$56)^$C$7)/IF($C$49=0,1,$C$49) -> 28.302536 | N60: =(($C$38+($G$27*(1+I60))/(N$56-I60))/(1+N$56)^$C$7)/IF($C$49=0,1,$C$49) -> 24.343586
B61: 16 | C61: =($C$11*B61/(1+C$56)^$C$7+$C$38-$C$45+$C$46-$C$47)/IF($C$49=0,1,$C$49) -> 39.589472 | D61: =($C$11*B61/(1+D$56)^$C$7+$C$38-$C$45+$C$46-$C$47)/IF($C$49=0,1,$C$49) -> 38.156107 | E61: =($C$11*B61/(1+E$56)^$C$7+$C$38-$C$45+$C$46-$C$47)/IF($C$49=0,1,$C$49) -> 36.799515 | F61: =($C$11*B61/(1+F$56)^$C$7+$C$38-$C$45+$C$46-$C$47)/IF($C$49=0,1,$C$49) -> 35.514941 | G61: =($C$11*B61/(1+G$56)^$C$7+$C$38-$C$45+$C$46-$C$47)/IF($C$49=0,1,$C$49) -> 34.297963 | I61: 0.05 | J61: =(($C$38+($G$27*(1+I61))/(J$56-I61))/(1+J$56)^$C$7)/IF($C$49=0,1,$C$49) -> 67.814173 | K61: =(($C$38+($G$27*(1+I61))/(K$56-I61))/(1+K$56)^$C$7)/IF($C$49=0,1,$C$49) -> 50.093073 | L61: =(($C$38+($G$27*(1+I61))/(L$56-I61))/(1+L$56)^$C$7)/IF($C$49=0,1,$C$49) -> 39.44979 | M61: =(($C$38+($G$27*(1+I61))/(M$56-I61))/(1+M$56)^$C$7)/IF($C$49=0,1,$C$49) -> 32.347568 | N61: =(($C$38+($G$27*(1+I61))/(N$56-I61))/(1+N$56)^$C$7)/IF($C$49=0,1,$C$49) -> 27.270454
A63: II. TRADING COMPARABLES ANALYSIS
B64: Company | C64: Ticker | D64: Equity Value ($mm) | E64: Net Debt ($mm) | F64: EV ($mm) | G64: LTM Rev ($mm) | H64: LTM EBITDA ($mm) | I64: EV/Rev (LTM) | J64: EV/EBITDA (LTM) | K64: NTM P/E (x) | L64: NTM Rev Growth (%)
B65: Cisco Systems | C65: CSCO | D65: 210462 | E65: -11200 | F65: =D65+E65 -> 199262 | G65: 57000 | H65: 16900 | I65: =IF(G65=0,0,F65/G65) -> 3.4958246 | J65: =IF(H65=0,0,F65/H65) -> 11.790651 | K65: 16.2 | L65: 0.02
B66: Extreme Networks | C66: EXTR | D66: 2613 | E66: 195 | F66: =D66+E66 -> 2808 | G66: 1410 | H66: 183 | I66: =IF(G66=0,0,F66/G66) -> 1.9914894 | J66: =IF(H66=0,0,F66/H66) -> 15.344262 | K66: 18.2 | L66: 0.08
B67: F5, Inc. | C67: FFIV | D67: 9912 | E67: -1450 | F67: =D67+E67 -> 8462 | G67: 2813 | H67: 840 | I67: =IF(G67=0,0,F67/G67) -> 3.0081763 | J67: =IF(H67=0,0,F67/H67) -> 10.07381 | K67: 14.8 | L67: 0.01
B68: Juniper Networks (Target) | C68: JNPR | D68: 13036 | E68: 525 | F68: =D68+E68 -> 13561 | G68: 5659 | H68: 932 | I68: =IF(G68=0,0,F68/G68) -> 2.3963598 | J68: =IF(H68=0,0,F68/H68) -> 14.550429 | K68: 17.5 | L68: 0.04
B69: [Add Comparable] | F69: =D69+E69 -> 0 | I69: =IF(G69=0,0,F69/G69) -> 0 | J69: =IF(H69=0,0,F69/H69) -> 0
B70: [Add Comparable] | F70: =D70+E70 -> 0 | I70: =IF(G70=0,0,F70/G70) -> 0 | J70: =IF(H70=0,0,F70/H70) -> 0
B72: Mean | I72: =AVERAGE(I65:I67) -> 2.8318301 | J72: =AVERAGE(J65:J67) -> 12.402908
B73: Median | I73: =MEDIAN(I65:I67) -> 3.0081763 | J73: =MEDIAN(J65:J67) -> 11.790651
B74: High | I74: =MAX(I65:I67) -> 3.4958246 | J74: =MAX(J65:J67) -> 15.344262
B75: Low | I75: {=MIN(IF(I65:I67>0,I65:I67))} -> 1.9914894 | J75: {=MIN(IF(J65:J67>0,J65:J67))} -> 10.07381
B76: 25th Pct | I76: =QUARTILE(I65:I67,1) -> 2.4998328 | J76: =QUARTILE(J65:J67,1) -> 10.93223
B77: 75th Pct | I77: =QUARTILE(I65:I67,3) -> 3.2520004 | J77: =QUARTILE(J65:J67,3) -> 13.567457
B79: Implied Valuation — Target (Based on Comps)
B80: Metric | C80: Multiple Applied | D80: LTM Metric ($mm) | E80: Implied EV ($mm) | F80: Implied Equity ($mm)
B81: EV / Revenue (Median) | C81: =MEDIAN(I65:I67) -> 3.0081763 | D81: =G68 -> 5659 | E81: =C81*D81 -> 17023.27 | F81: =E81 -> 17023.27
B82: EV / EBITDA (Median) | C82: =MEDIAN(J65:J67) -> 11.790651 | D82: =H68 -> 932 | E82: =C82*D82 -> 10988.887 | F82: =E82 -> 10988.887
B83: EV / Revenue (Mean) | C83: =AVERAGE(I65:I67) -> 2.8318301 | D83: =G68 -> 5659 | E83: =C83*D83 -> 16025.326 | F83: =E83 -> 16025.326
B84: EV / EBITDA (Mean) | C84: =AVERAGE(J65:J70) -> 8.6265253 | D84: =H68 -> 932 | E84: =C84*D84 -> 8039.9216 | F84: =E84 -> 8039.9216
A86: III. PRECEDENT TRANSACTIONS ANALYSIS
B87: Target | C87: Acquiror | D87: Date | E87: Transaction Value ($mm) | F87: EV ($mm) | G87: LTM Rev ($mm) | H87: LTM EBITDA ($mm) | I87: EV/Rev (x) | J87: EV/EBITDA (x)
I88: =IF(G88=0,0,F88/G88) -> 0 | J88: =IF(H88=0,0,F88/H88) -> 0
I89: =IF(G89=0,0,F89/G89) -> 0 | J89: =IF(H89=0,0,F89/H89) -> 0
I90: =IF(G90=0,0,F90/G90) -> 0 | J90: =IF(H90=0,0,F90/H90) -> 0
I91: =IF(G91=0,0,F91/G91) -> 0 | J91: =IF(H91=0,0,F91/H91) -> 0
I92: =IF(G92=0,0,F92/G92) -> 0 | J92: =IF(H92=0,0,F92/H92) -> 0
I93: =IF(G93=0,0,F93/G93) -> 0 | J93: =IF(H93=0,0,F93/H93) -> 0
B94: [Add Transaction] | I94: =IF(G94=0,0,F94/G94) -> 0 | J94: =IF(H94=0,0,F94/H94) -> 0
B95: [Add Transaction] | I95: =IF(G95=0,0,F95/G95) -> 0 | J95: =IF(H95=0,0,F95/H95) -> 0
B97: Mean | I97: =AVERAGE(I88:I95) -> 0 | J97: =AVERAGE(J88:J95) -> 0
B98: Median | I98: =MEDIAN(I88:I95) -> 0 | J98: =MEDIAN(J88:J95) -> 0
B99: High | I99: =MAX(I88:I95) -> 0 | J99: =MAX(J88:J95) -> 0
B100: Low | I100: {=MIN(IF(I88:I95>0,I88:I95))} -> 0 | J100: {=MIN(IF(J88:J95>0,J88:J95))} -> 0
B102: Implied Valuation — Target (Based on Precedents)
B103: Metric | C103: Multiple Applied | D103: LTM Metric ($mm) | E103: Implied EV ($mm) | F103: Implied Equity ($mm)
B104: EV / Revenue (Median) | C104: =MEDIAN(I88:I95) -> 0 | E104: =C104*D104 -> 0 | F104: =E104 -> 0
B105: EV / EBITDA (Median) | C105: =MEDIAN(J88:J95) -> 0 | E105: =C105*D105 -> 0 | F105: =E105 -> 0
B106: EV / Revenue (Mean) | C106: =AVERAGE(I88:I95) -> 0 | E106: =C106*D106 -> 0 | F106: =E106 -> 0
B107: EV / EBITDA (Mean) | C107: =AVERAGE(J88:J95) -> 0 | E107: =C107*D107 -> 0 | F107: =E107 -> 0
A109: IV. VALUATION SUMMARY — FOOTBALL FIELD
B110: Methodology | C110: Low ($mm) | D110: Median / Mid ($mm) | E110: High ($mm) | F110: Implied Share Price Low | G110: Implied Share Price Mid | H110: Implied Share Price High
B111: DCF : Exit Multiple | C111: =C39*0.9 -> 10476.731 | D111: =C39 -> 11640.812 | E111: =C39*1.1 -> 12804.893 | F111: =IFERROR(IF($C$49=0,"-",C39*0.9/$C$49),"-") -> 32.147072 | G111: =IFERROR(IF($C$49=0,"-",C39/$C$49),"-") -> 35.718969 | H111: =IFERROR(IF($C$49=0,"-",C39*1.1/$C$49),"-") -> 39.290866
B112: DCF : Gordon Growth | C112: =C40*0.9 -> 10195.441 | D112: =C40 -> 11328.268 | E112: =C40*1.1 -> 12461.094 | F112: =IFERROR(IF($C$49=0,"-",C40*0.9/$C$49),"-") -> 31.283955 | G112: =IFERROR(IF($C$49=0,"-",C40/$C$49),"-") -> 34.75995 | H112: =IFERROR(IF($C$49=0,"-",C40*1.1/$C$49),"-") -> 38.235945
...

Sheet Sources & Uses
B1: ■ Blue = Input | D1: ■ Black = Formula | F1: ■ Green = Cross-Tab Link
A2: Sources & Uses of Funds
A4: SOURCES OF FUNDS | F4: USES OF FUNDS
B5: Source | C5: Amount ($mm) | D5: % of Total | F5: Use | G5: Amount ($mm) | H5: % of Total
B6: Equity | F6: Purchase Price
B7: Cash on Hand (Acquiror) | C7: ='Transaction Assumptions'!H7+G16 -> 3246 | D7: =IF(C22=0,0,C7/C22) -> 0.24505511 | F7: Purchase Target Equity | G7: ='Transaction Assumptions'!C24 -> 13036 | H7: =IF(G22=0,0,G7/G22) -> 0.98414616
B8: Stock Consideration (Acquiror Shares) | C8: 0 | D8: =IF(C22=0,0,C8/C22) -> 0 | F8: Refinance / Retire Target Debt | G8: 0 | H8: =IF(G22=0,0,G8/G22) -> 0
B9: Rollover Equity (if applicable) | C9: 0 | D9: =IF(C22=0,0,C9/C22) -> 0 | F9: Total Purchase Price | G9: =SUM(G7:G8) -> 13036 | H9: =IF(G22=0,0,G9/G22) -> 0.98414616
B10: Total Equity Sources | C10: =SUM(C7:C9) -> 3246 | D10: =IF(C22=0,0,C10/C22) -> 0.24505511
F11: Fees & Expenses
B12: Debt | F12: Advisory Fees | G12: ='Transaction Assumptions'!C42+'Transaction Assumptions'!C43 -> 105 | H12: =IF(G22=0,0,G12/G22) -> 0.0079269213
B13: Revolving Credit Facility (RCF) | C13: 0 | D13: =IF(C22=0,0,C13/C22) -> 0 | F13: Legal & Professional Fees | G13: ='Transaction Assumptions'!C44 -> 30 | H13: =IF(G22=0,0,G13/G22) -> 0.0022648347
B14: Term Loan A (TLA) | C14: =4000 -> 4000 | D14: =IF(C22=0,0,C14/C22) -> 0.30197796 | F14: Financing Fees (Debt Issuance Costs) | G14: ='Transaction Assumptions'!C46 -> 75 | H14: =IF(G22=0,0,G14/G22) -> 0.0056620867
B15: Term Loan B (TLB) | C15: 0 | D15: =IF(C22=0,0,C15/C22) -> 0 | F15: Other Transaction Costs | G15: 0 | H15: =IF(G22=0,0,G15/G22) -> 0
B16: Senior Secured Notes | C16: 3000 | D16: =IF(C22=0,0,C16/C22) -> 0.22648347 | F16: Total Fees & Expenses | G16: =SUM(G12:G15) -> 210 | H16: =IF(G22=0,0,G16/G22) -> 0.015853843
B17: Senior Unsecured Notes | C17: 3000 | D17: =IF(C22=0,0,C17/C22) -> 0.22648347
B18: Subordinated / Mezzanine Debt | C18: 0 | D18: =IF(C22=0,0,C18/C22) -> 0 | F18: Other Uses
B19: Total Debt Sources | C19: =SUM(C13:C18) -> 10000 | F19: Cash to Balance Sheet (Minimum Cash) | G19: 0 | H19: =IF(G22=0,0,G19/G22) -> 0
F20: Working Capital Adjustment | G20: 0 | H20: =IF(G22=0,0,G20/G22) -> 0
B21: Other Sources (Target Cash Acquired, etc.) | D21: =IF(C22=0,0,C21/C22) -> 0 | F21: Total Other Uses | G21: =SUM(G19:G20) -> 0 | H21: =IF(G22=0,0,G21/G22) -> 0
B22: TOTAL SOURCES | C22: =C10+C19+C21 -> 13246 | D22: 1 | F22: TOTAL USES | G22: =G9+G16+G21 -> 13246 | H22: 1
A24: SOURCES & USES CHECK
B25: Total Sources | C25: =C22 -> 13246 | F25: Total Uses | G25: =G22 -> 13246
B26: Surplus / (Deficit) | C26: =C22-G22 -> 0 | F26: Check | G26: =IF(ABS(C26)<1,"✓ Balanced",IF(C26>0,"Surplus: "&TEXT(C26,"$#,##0"),"DEFICIT: "&TEXT(ABS(C26),"$#,##0"))) -> ✓ Balanced
A28: PRO FORMA CAPITALIZATION
B29: Item | C29: Amount ($mm) | D29: Multiple
B30: Pro Forma Total Debt | C30: =C19 -> 10000
B31: (–) Pro Forma Cash
B32: Pro Forma Net Debt | C32: =C30-C31 -> 10000
B33: LTM EBITDA (Enter) | C33: ='Target Standalone'!F22 -> 952.5
B34: Gross Leverage (Debt / EBITDA) | C34: =C30 -> 10000 | D34: =IF(C33=0,0,C30/C33) -> 10.498688
B35: Net Leverage (Net Debt / EBITDA) | C35: =C32 -> 10000 | D35: =IF(C33=0,0,C32/C33) -> 10.498688
B36: Pro Forma Equity Value
B37: Pro Forma Enterprise Value | C37: =C37+C32 -> 314100000

Sheet Accretion-Dilution Analysis
B1: ■ Blue = Input | D1: ■ Black = Formula | F1: ■ Green = Cross-Tab Link | H1: ■ Yellow = Key Output
A2: Accretion / Dilution Analysis — HPE Acquisition of Juniper Networks
A4: I. STANDALONE EPS — ACQUIRER (HPE)
B5: Item | C5: Year 1E | D5: Year 2E | E5: Year 3E
B6: Net Income — Standalone ($mm) | C6: ='Acquirer Standalone'!G31 -> 1491.9404 | D6: ='Acquirer Standalone'!H31 -> 1610.883 | E6: ='Acquirer Standalone'!I31 -> 1741.2602
B7: Shares Outstanding — Basic (mm) | C7: ='Acquirer Standalone'!G35 -> 1299 | D7: ='Acquirer Standalone'!H35 -> 1299 | E7: ='Acquirer Standalone'!I35 -> 1299
B8: Shares Outstanding — Diluted (mm) | C8: ='Acquirer Standalone'!G36 -> 1316 | D8: ='Acquirer Standalone'!H36 -> 1316 | E8: ='Acquirer Standalone'!I36 -> 1316
B9: EPS — Basic ($) | C9: =IFERROR(C6/C7,"-") -> 1.14853 | D9: =IFERROR(D6/D7,"-") -> 1.2400947 | E9: =IFERROR(E6/E7,"-") -> 1.340462
B10: EPS — Diluted ($) | C10: =IFERROR(C6/C8,"-") -> 1.1336933 | D10: =IFERROR(D6/D8,"-") -> 1.2240753 | E10: =IFERROR(E6/E8,"-") -> 1.3231461
B11: EPS — Consensus / Management ($)
B12: Difference (Model vs. Consensus) | C12: =IFERROR(C10-C11,"-") -> 1.1336933 | D12: =IFERROR(D10-D11,"-") -> 1.2240753 | E12: =IFERROR(E10-E11,"-") -> 1.3231461
A14: II. PRO FORMA EPS BRIDGE ($mm unless noted)
B15: Item | C15: Year 1E | D15: Year 2E | E15: Year 3E
B16: Step 1: Acquirer Standalone Net Income
B17: Net Income — Acquirer (Standalone) | C17: =C6 -> 1491.9404 | D17: =D6 -> 1610.883 | E17: =E6 -> 1741.2602
B18: Step 2: Add Target Net Income
B19: Net Income — Target (Standalone) | C19: ='Target Standalone'!G31 -> 665.83761 | D19: ='Target Standalone'!H31 -> 740.95791 | E19: ='Target Standalone'!I31 -> 815.84575
B20: (–) Remove Target Standalone EPS impact (elim.) | C20: =-C19 -> -665.83761 | D20: =-D19 -> -740.95791 | E20: =-E19 -> -815.84575
B21: Step 3: Pro Forma Adjustments
B22: (–) PPA Amortization (intangibles) | C22: =-'PPA & BS Adjustments'!C79*(1-0.21) -> -327.76621 | D22: =-'PPA & BS Adjustments'!D79*(1-0.21) -> -290.16221 | E22: =-'PPA & BS Adjustments'!E79*(1-0.21) -> -290.16221
B23: (–) Inventory Step-Up (Year 1 only) | C23: =-'PPA & BS Adjustments'!E28*(1-0.21) -> -37.604 | D23: 0 | E23: 0
B24: (+/–) Incremental Interest on New Debt | C24: =-('Sources & Uses'!C19*0.058)*(1-0.21) -> -458.2 | D24: =C24 -> -458.2 | E24: =C24 -> -458.2
B25: (+) Cost Synergies (after tax) | C25: ='Synergy Assumptions'!C18*(1-0.21) -> 99.005082 | D25: ='Synergy Assumptions'!D18*(1-0.21) -> 198.01016 | E25: ='Synergy Assumptions'!E18*(1-0.21) -> 316.81626
B26: (+) Revenue Synergies (after tax) | C26: ='Synergy Assumptions'!C10*(1-0.21) -> 0 | D26: ='Synergy Assumptions'!D10*(1-0.21) -> 0 | E26: ='Synergy Assumptions'!E10*(1-0.21) -> 0
B27: (–) Integration Costs (after tax) | C27: =-'Synergy Assumptions'!C29*(1-0.21) -> -132.00678 | D27: =-'Synergy Assumptions'!D29*(1-0.21) -> -132.00678 | E27: =-'Synergy Assumptions'!E29*(1-0.21) -> 0
B28: (+/–) Other Pro Forma Adjustments
B29: Total Pro Forma Adjustments | C29: =SUM(C22:C28) -> -856.57191 | D29: =SUM(D22:D28) -> -682.35883 | E29: =SUM(E22:E28) -> -431.54595
B30: Step 4: Pro Forma Net Income & EPS
B31: Pro Forma Net Income ($mm) | C31: =C17+C19+C20+C29 -> 635.36853 | D31: =D17+D19+D20+D29 -> 928.52422 | E31: =E17+E19+E20+E29 -> 1309.7142
B32: Pro Forma Shares — Diluted (mm) | C32: =C8 -> 1316 | D32: =D8 -> 1316 | E32: =E8 -> 1316
B33: Pro Forma EPS — Diluted ($) | C33: =IFERROR(C31/C32,"-") -> 0.48280284 | D33: =IFERROR(D31/D32,"-") -> 0.70556551 | E33: =IFERROR(E31/E32,"-") -> 0.99522359
B34: Acquirer Standalone EPS — Diluted ($) | C34: =IFERROR(C10,"-") -> 1.1336933 | D34: =IFERROR(D10,"-") -> 1.2240753 | E34: =IFERROR(E10,"-") -> 1.3231461
A36: III. ACCRETION / DILUTION SUMMARY
B37: Metric | C37: Year 1E | D37: Year 2E | E37: Year 3E
B38: Pro Forma EPS ($) | C38: =C33 -> 0.48280284 | D38: =D33 -> 0.70556551 | E38: =E33 -> 0.99522359
B39: Standalone EPS ($) | C39: =C34 -> 1.1336933 | D39: =D34 -> 1.2240753 | E39: =E34 -> 1.3231461
B40: EPS Accretion / (Dilution) ($) | C40: =IFERROR(C38-C39,"-") -> -0.65089051 | D40: =IFERROR(D38-D39,"-") -> -0.51850975 | E40: =IFERROR(E38-E39,"-") -> -0.32792246
B41: EPS Accretion / (Dilution) (%) | C41: =IFERROR(IF(C39=0,"-",C40/C39),"-") -> -0.57413278 | D41: =IFERROR(IF(D39=0,"-",D40/D39),"-") -> -0.42359303 | E41: =IFERROR(IF(E39=0,"-",E40/E39),"-") -> -0.24783542
B42: Pro Forma Net Income ($mm) | C42: =C31 -> 635.36853 | D42: =D31 -> 928.52422 | E42: =E31 -> 1309.7142
B43: Standalone Net Income ($mm) | C43: =C17 -> 1491.9404 | D43: =D17 -> 1610.883 | E43: =E17 -> 1741.2602
B44: NI Accretion / (Dilution) ($mm) | C44: =IFERROR(C42-C43,"-") -> -856.57191 | D44: =IFERROR(D42-D43,"-") -> -682.35883 | E44: =IFERROR(E42-E43,"-") -> -431.54595
B45: NI Accretion / (Dilution) (%) | C45: =IFERROR(IF(C43=0,"-",C44/C43),"-") -> -0.57413278 | D45: =IFERROR(IF(D43=0,"-",D44/D43),"-") -> -0.42359303 | E45: =IFERROR(IF(E43=0,"-",E44/E43),"-") -> -0.24783542
A47: IV. EPS ACCRETION / (DILUTION)
B48: Impact of Cash vs. Stock Mix on EPS
B49: Metric | C49: 100% Cash | D49: 50/50 Mix | E49: 100% Stock
B50: % Cash | C50: 1 | D50: 0.5 | E50: 0
B51: % Stock | C51: 0 | D51: 0.5 | E51: 1
B52: New Shares Issued (mm) | C52: 0 | D52: =ROUND(('Sources & Uses'!G7*0.5)/17,1) -> 383.4 | E52: =ROUND('Sources & Uses'!G7/17,1) -> 766.8
B53: Total PF Shares — Diluted | C53: =C32+C52 -> 1316 | D53: =C32+D52 -> 1699.4 | E53: =C32+E52 -> 2082.8
B54: Incremental Interest Exp. | C54: =C24 -> -458.2 | D54: =C24*0.5 -> -229.1
B55: Pro Forma Net Income ($mm) | C55: =C31 -> 635.36853 | D55: =C31-C24+D54 -> 864.46853 | E55: =C31-C24 -> 1093.5685
B56: Pro Forma EPS ($) | C56: =IFERROR(C55/C53,"-") -> 0.48280284 | D56: =IFERROR(D55/D53,"-") -> 0.50869044 | E56: =IFERROR(E55/E53,"-") -> 0.52504731
B57: Standalone EPS ($) | C57: =C34 -> 1.1336933 | D57: =C34 -> 1.1336933 | E57: =C34 -> 1.1336933
B58: EPS Accretion/(Dilution) | C58: =IFERROR(C56-C57,"-") -> -0.65089051 | D58: =IFERROR(D56-D57,"-") -> -0.62500291 | E58: =IFERROR(E56-E57,"-") -> -0.60864604

Sheet PPA & BS Adjustments
B1: ■ Blue = Input | D1: ■ Black = Formula | F1: ■ Yellow = Key Output
A2: Purchase Price Allocation (PPA) & Balance Sheet Adjustments
A4: I. PURCHASE PRICE SUMMARY ($mm)
B5: Item | C5: Amount ($mm) | D5: Note / Reference
B6: Equity Value (Offer Price × Diluted Shares) | C6: ='Transaction Assumptions'!C24 -> 13036 | D6: → Transaction Assumptions
B7: (+) Target Total Debt Assumed | C7: ='Transaction Assumptions'!C25 -> 1746.1 | D7: Enter from Target BS
B8: (–) Target Cash Acquired | C8: ='Transaction Assumptions'!C26 -> 1221.3 | D8: Enter from Target BS
B9: (+) Transaction Fees & Expenses | C9: ='Transaction Assumptions'!C45 -> 135 | D9: → Transaction Assumptions
B10: Total Purchase Price (Aggregate Consideration) | C10: =C6+C7-C8+C9 -> 13695.8
B11: (–) Book Value of Net Assets Acquired | C11: ='Target Standalone'!F70 -> 4492.7 | D11: Enter from Target latest BS
B12: Excess Purchase Price | C12: =C10-C11 -> 9203.1
B13: Total Identified Intangibles (PPA, see below) | C13: =E31+E27 -> 3431.788 | D13: → Section II
B14: Goodwill (Residual) | C14: =C12-C13+D54 -> 6491.9875 | D14: Key PPA output
A16: II. IDENTIFIED INTANGIBLES & FAIR VALUE STEP-UPS ($mm)
B17: Asset Category | C17: Book Value ($mm) | D17: Fair Value ($mm) | E17: Step-Up ($mm)
B18: Customer Relationships | C18: 0 | D18: =11%*(C6+C7-C8) -> 1491.688 | E18: =D18-C18 -> 1491.688 | I18: 12 | J18: =E18/I18 -> 124.30733
B19: Developed Technology / IP | C19: 0 | D19: =9%*(C6+C7-C8) -> 1220.472 | E19: =D19-C19 -> 1220.472 | I19: 7 | J19: =E19/I19 -> 174.35314
B20: Trade Names & Trademarks | C20: 0 | D20: =2%*(C6+C7-C8) -> 271.216 | E20: =D20-C20 -> 271.216 | I20: 15 | J20: =E20/I20 -> 18.081067
B21: Order Backlog | C21: 0 | D21: 0 | E21: =D21-C21 -> 0 | I21: 0 | J21: 0
B22: Non-Compete Agreements | C22: 0 | D22: 0 | E22: =D22-C22 -> 0 | I22: 0 | J22: 0
B23: In-Process R&D (IPR&D) | C23: 0 | D23: =1.5%*(C6+C7-C8) -> 203.412 | E23: =D23-C23 -> 203.412 | I23: 5 | J23: =E23/I23 -> 40.6824
B24: Favorable Leases / Contracts | C24: 0 | D24: 0 | E24: =D24-C24 -> 0 | I24: 0 | J24: 0
B25: Other Identified Intangibles | C25: ='Target Standalone'!F48 -> 91.8 | D25: =C25 -> 91.8 | E25: =D25-C25 -> 0 | I25: 0 | J25: 0
B26: Tangible Asset Fair Value Adjustments | I26: 0 | J26: 0
B27: PP&E Fair Value Step-Up | C27: ='Target Standalone'!F46 -> 801.3 | D27: =900 -> 900 | E27: =D27-C27 -> 98.7 | I27: 10 | J27: =E27/I27 -> 9.87
B28: Inventory Step-Up (to FMV) | C28: ='Target Standalone'!F42 -> 952.4 | D28: =1000 -> 1000 | E28: =D28-C28 -> 47.6 | I28: 1 | J28: =E28/I28 -> 47.6
B29: Deferred Revenue Write-Down | C29: 0 | D29: 0 | E29: =D29-C29 -> 0
B30: Debt Fair Value Adjustment | C30: 0 | D30: 0 | E30: =D30-C30 -> 0
B31: Total Identified PPA Adjustments | C31: =SUM(C18:C30) -> 1845.5 | D31: =SUM(D18:D30) -> 5178.588 | E31: =SUM(E18:E30) -> 3333.088
A33: III. OPENING BALANCE SHEET ADJUSTMENTS ($mm)
B34: Balance Sheet Item | C34: Target (Historical) | D34: PPA Adjustment | E34: Financing Adj. | F34: Elimination | G34: Pro Forma Opening
B35: Assets
B36: Cash & Cash Equivalents | C36: ='Target Standalone'!F40 -> 1221.3 | D36: 0 | E36: =-'Sources & Uses'!C7 -> -3246 | G36: =C36+D36+E36+F36 -> -2024.7
B37: Accounts Receivable, net | C37: ='Target Standalone'!F41 -> 1044.1 | D37: 0 | E37: 0 | G37: =C37+D37+E37+F37 -> 1044.1
B38: Inventories | C38: ='Target Standalone'!F42 -> 952.4 | E38: 0 | G38: =C38+D38+E38+F38 -> 952.4
B39: Other Current Assets | C39: ='Target Standalone'!F43 -> 577.7 | D39: 0 | E39: 0 | G39: =C39+D39+E39+F39 -> 577.7
B40: Total Current Assets | C40: =SUM(C36:C39) -> 3795.5 | D40: =SUM(D36:D39) -> 0 | E40: =SUM(E36:E39) -> -3246 | F40: =SUM(F36:F39) -> 0 | G40: =C40+D40+E40+F40 -> 549.5
B41: PP&E, net (incl. step-up) | C41: ='Target Standalone'!F46 -> 801.3 | D41: =E27 -> 98.7 | G41: =C41+D41+E41+F41 -> 900
B42: Goodwill | C42: ='Target Standalone'!F47 -> 3734.4 | D42: =C14 -> 6491.9875 | G42: =C42+D42+E42+F42 -> 10226.387
B43: Identified Intangibles, net | C43: ='Target Standalone'!F48 -> 91.8 | D43: =E31 -> 3333.088 | G43: =C43+D43+E43+F43 -> 3424.888
B44: Other Non-Current Assets | C44: ='Target Standalone'!F50 -> 865.9 | G44: =C44+D44+E44+F44 -> 865.9
B45: Long term Investments | C45: ='Target Standalone'!F49 -> 229.6
B46: Total Assets | C46: =SUM(C36:C39)+C41+C42+C43+C44+C45 -> 9518.5 | D46: =SUM(D36:D39)+D41+D42+D43+D44 -> 9923.7755 | E46: =SUM(E36:E39)+E41+E42+E43+E44 -> -3246 | F46: =SUM(F36:F39)+F41+F42+F43+F44 -> 0 | G46: =C46+D46+E46+F46 -> 16196.275
B47: Liabilities & Equity
B48: Accounts Payable | C48: ='Target Standalone'!F54 -> 295.1 | G48: =C48+D48+E48+F48 -> 295.1
B49: Short-Term Debt | C49: ='Target Standalone'!G55 -> 46.4 | G49: =C49+D49+E49+F49 -> 46.4
B50: Accrued Liabilities | C50: ='Target Standalone'!G56 -> 292.2 | F50: ='Sources & Uses'!G16 -> 210 | G50: =C50+D50+E50+F50 -> 502.2
B51: Other Current Liabilities | C51: ='Target Standalone'!F57 -> 1470.3 | G51: =C51+D51+E51+F51 -> 1470.3
B52: Total Current Liabilities | C52: =SUM(C48:C51) -> 2104 | D52: =SUM(D48:D51) -> 0 | E52: 0 | F52: =SUM(F48:F51) -> 210 | G52: =C52+D52+E52+F52 -> 2314
B53: Long-Term Debt (pro forma) | C53: ='Target Standalone'!F60 -> 1699.7 | E53: ='Sources & Uses'!C19 -> 10000 | G53: =C53+D53+E53+F53 -> 11699.7
B54: Deferred Tax Liabilities (PPA) | C54: ='Target Standalone'!F61 -> 12 | D54: =(D43+D41)*0.21 -> 720.67548 | G54: =C54+D54+E54+F54 -> 732.67548
B55: Other Non-Current Liabilities | C55: ='Target Standalone'!F62 -> 1210.1 | E55: 0 | G55: =C55+D55+E55+F55 -> 1210.1
B56: Total Liabilities | C56: =C52+C53+C54+C55 -> 5025.8 | D56: =D52+D53+D54+D55 -> 720.67548 | E56: =E52+E53+E54+E55 -> 10000 | F56: =F52+F53+F54+F55 -> 210 | G56: =C56+D56+E56+F56 -> 15956.475
B57: Common Equity (pro forma) | E57: 0 | G57: =C57+D57+E57+F57 -> 0
B58: Retained Earnings Adjustment | C58: ='Target Standalone'!F67 -> -2296.4 | D58: =-C62 -> -4492.7 | E58: 0 | F58: =-'Sources & Uses'!G16 -> -210 | G58: =C58+D58+E58+F58 -> -6999.1
B59: Common Stock & Additional Paid-In Capital | C59: ='Target Standalone'!F66 -> 6740 | D59: =C10 -> 13695.8 | E59: =-('Sources & Uses'!G9+'Sources & Uses'!G16) -> -13246 | F59: 0
B60: Accumulated Other Comprehensive Income (Loss) | C60: ='Target Standalone'!F68 -> -82.1 | E60: 0 | F60: 0
B61: Treasury Stock | C61: ='Target Standalone'!F69 -> 102.3 | D61: 0 | E61: 0 | F61: 0
B62: Total Equity | C62: =C46-C56 -> 4492.7 | D62: =SUM(D58:D61) -> 9203.1 | E62: =SUM(E58:E61) -> -13246 | F62: =F57+F58 -> -210 | G62: =C62+D62+E62+F62 -> 239.8
B63: Total Liabilities & Equity | C63: =C56+C62 -> 9518.5 | D63: =D56+D62 -> 9923.7755 | E63: =E56+E62 -> -3246 | F63: =F56+F62 -> 0 | G63: =C63+D63+E63+F63 -> 16196.275
B64: BS Check: Assets = Liabilities + Equity | C64: =IFERROR(IF(ABS(C46-C63)<1,"✓ Balanced","✗ CHECK: "&TEXT(C46-C63,"$#,##0")),"-") -> ✓ Balanced | D64: =IFERROR(IF(ABS(D46-D63)<1,"✓ Balanced","✗ CHECK: "&TEXT(D46-D63,"$#,##0")),"-") -> ✓ Balanced | E64: =IFERROR(IF(ABS(E46-E63)<1,"✓ Balanced","✗ CHECK: "&TEXT(E46-E63,"$#,##0")),"-") -> ✓ Balanced | F64: =IFERROR(IF(ABS(F46-F63)<1,"✓ Balanced","✗ CHECK: "&TEXT(F46-F63,"$#,##0")),"-") -> ✓ Balanced | G64: =IFERROR(IF(ABS(G46-G63)<1,"✓ Balanced","✗ CHECK: "&TEXT(G46-G63,"$#,##0")),"-") -> ✓ Balanced
A66: IV. PPA AMORTIZATION SCHEDULE — INCOME STATEMENT IMPACT ($mm)
B67: Asset Category | C67: Year 1 | D67: Year 2 | E67: Year 3 | F67: Year 4 | G67: Year 5 | H67: Year 6 | I67: Year 7 | J67: Year 8+
B68: Other Identified Intangibles | C68: =IFERROR(IF(1<=$I$25,$J$25,"-"),"-") -> - | D68: =IFERROR(IF(2<=$I$25,$J$25,"-"),"-") -> - | E68: =IFERROR(IF(3<=$I$25,$J$25,"-"),"-") -> - | F68: =IFERROR(IF(4<=$I$25,$J$25,"-"),"-") -> - | G68: =IFERROR(IF(5<=$I$25,$J$25,"-"),"-") -> - | H68: =IFERROR(IF(6<=$I$25,$J$25,"-"),"-") -> - | I68: =IFERROR(IF(7<=$I$25,$J$25,"-"),"-") -> - | J68: =IFERROR(IF(8<=$I$25,$J$25,"-"),"-") -> -
B69: Customer Relationships | C69: =IFERROR(IF(1<=$I$18,$J$18,0),"-") -> 124.30733 | D69: =IFERROR(IF(2<=$I$18,$J$18,0),"-") -> 124.30733 | E69: =IFERROR(IF(3<=$I$18,$J$18,0),"-") -> 124.30733 | F69: =IFERROR(IF(4<=$I$18,$J$18,0),"-") -> 124.30733 | G69: =IFERROR(IF(5<=$I$18,$J$18,0),"-") -> 124.30733 | H69: =IFERROR(IF(6<=$I$18,$J$18,0),"-") -> 124.30733 | I69: =IFERROR(IF(7<=$I$18,$J$18,0),"-") -> 124.30733 | J69: =IFERROR(IF(8<=$I$18,$J$18,0),"-") -> 124.30733
B70: Developed Technology / IP | C70: =IFERROR(IF(1<=$I$19,$J$19,0),"-") -> 174.35314 | D70: =IFERROR(IF(2<=$I$19,$J$19,0),"-") -> 174.35314 | E70: =IFERROR(IF(3<=$I$19,$J$19,0),"-") -> 174.35314 | F70: =IFERROR(IF(4<=$I$19,$J$19,0),"-") -> 174.35314 | G70: =IFERROR(IF(5<=$I$19,$J$19,0),"-") -> 174.35314 | H70: =IFERROR(IF(6<=$I$19,$J$19,0),"-") -> 174.35314 | I70: =IFERROR(IF(7<=$I$19,$J$19,0),"-") -> 174.35314 | J70: =IFERROR(IF(8<=$I$19,$J$19,0),"-") -> 0
B71: Trade Names & Trademarks | C71: =IFERROR(IF(1<=$I$20,$J$20,0),"-") -> 18.081067 | D71: =IFERROR(IF(2<=$I$20,$J$20,0),"-") -> 18.081067 | E71: =IFERROR(IF(3<=$I$20,$J$20,0),"-") -> 18.081067 | F71: =IFERROR(IF(4<=$I$20,$J$20,0),"-") -> 18.081067 | G71: =IFERROR(IF(5<=$I$20,$J$20,0),"-") -> 18.081067 | H71: =IFERROR(IF(6<=$I$20,$J$20,0),"-") -> 18.081067 | I71: =IFERROR(IF(7<=$I$20,$J$20,0),"-") -> 18.081067 | J71: =IFERROR(IF(8<=$I$20,$J$20,0),"-") -> 18.081067
B72: Order Backlog | C72: =IFERROR(IF(1<=$I$21,$J$21,0),"-") -> 0 | D72: =IFERROR(IF(2<=$I$21,$J$21,0),"-") -> 0 | E72: =IFERROR(IF(3<=$I$21,$J$21,0),"-") -> 0 | F72: =IFERROR(IF(4<=$I$21,$J$21,0),"-") -> 0 | G72: =IFERROR(IF(5<=$I$21,$J$21,0),"-") -> 0 | H72: =IFERROR(IF(6<=$I$21,$J$21,0),"-") -> 0 | I72: =IFERROR(IF(7<=$I$21,$J$21,0),"-") -> 0 | J72: =IFERROR(IF(8<=$I$21,$J$21,0),"-") -> 0
B73: Non-Compete Agreements | C73: =IFERROR(IF(1<=$I$22,$J$22,0),"-") -> 0 | D73: =IFERROR(IF(2<=$I$22,$J$22,0),"-") -> 0 | E73: =IFERROR(IF(3<=$I$22,$J$22,0),"-") -> 0 | F73: =IFERROR(IF(4<=$I$22,$J$22,0),"-") -> 0 | G73: =IFERROR(IF(5<=$I$22,$J$22,0),"-") -> 0 | H73: =IFERROR(IF(6<=$I$22,$J$22,0),"-") -> 0 | I73: =IFERROR(IF(7<=$I$22,$J$22,0),"-") -> 0 | J73: =IFERROR(IF(8<=$I$22,$J$22,0),"-") -> 0
B74: In-Process R&D (IPR&D) | C74: =IFERROR(IF(1<=$I$23,$J$23,0),"-") -> 40.6824 | D74: =IFERROR(IF(2<=$I$23,$J$23,0),"-") -> 40.6824 | E74: =IFERROR(IF(3<=$I$23,$J$23,0),"-") -> 40.6824 | F74: =IFERROR(IF(4<=$I$23,$J$23,0),"-") -> 40.6824 | G74: =IFERROR(IF(5<=$I$23,$J$23,0),"-") -> 40.6824 | H74: =IFERROR(IF(6<=$I$23,$J$23,0),"-") -> 0 | I74: =IFERROR(IF(7<=$I$23,$J$23,0),"-") -> 0 | J74: =IFERROR(IF(8<=$I$23,$J$23,0),"-") -> 0
B75: Favorable Leases / Contracts | C75: =IFERROR(IF(1<=$I$24,$J$24,0),"-") -> 0 | D75: =IFERROR(IF(2<=$I$24,$J$24,0),"-") -> 0 | E75: =IFERROR(IF(3<=$I$24,$J$24,0),"-") -> 0 | F75: =IFERROR(IF(4<=$I$24,$J$24,0),"-") -> 0 | G75: =IFERROR(IF(5<=$I$24,$J$24,0),"-") -> 0 | H75: =IFERROR(IF(6<=$I$24,$J$24,0),"-") -> 0 | I75: =IFERROR(IF(7<=$I$24,$J$24,0),"-") -> 0 | J75: =IFERROR(IF(8<=$I$24,$J$24,0),"-") -> 0
B76: Other Identified Intangibles | C76: =IFERROR(IF(1<=$I$25,$J$25,0),"-") -> 0 | D76: =IFERROR(IF(2<=$I$25,$J$25,0),"-") -> 0 | E76: =IFERROR(IF(3<=$I$25,$J$25,0),"-") -> 0 | F76: =IFERROR(IF(4<=$I$25,$J$25,0),"-") -> 0 | G76: =IFERROR(IF(5<=$I$25,$J$25,0),"-") -> 0 | H76: =IFERROR(IF(6<=$I$25,$J$25,0),"-") -> 0 | I76: =IFERROR(IF(7<=$I$25,$J$25,0),"-") -> 0 | J76: =IFERROR(IF(8<=$I$25,$J$25,0),"-") -> 0
B77: PP&E Incremental D&A (Step-Up) | C77: =IFERROR(IF(1<=$I$27,$J$27,0),"-") -> 9.87 | D77: =IFERROR(IF(2<=$I$27,$J$27,0),"-") -> 9.87 | E77: =IFERROR(IF(3<=$I$27,$J$27,0),"-") -> 9.87 | F77: =IFERROR(IF(4<=$I$27,$J$27,0),"-") -> 9.87 | G77: =IFERROR(IF(5<=$I$27,$J$27,0),"-") -> 9.87 | H77: =IFERROR(IF(6<=$I$27,$J$27,0),"-") -> 9.87 | I77: =IFERROR(IF(7<=$I$27,$J$27,0),"-") -> 9.87 | J77: =IFERROR(IF(8<=$I$27,$J$27,0),"-") -> 9.87
B78: Inventory Step-Up (Year 1 only) | C78: =IFERROR(IF(1<=$I$28,$J$28,0),"-") -> 47.6
B79: Total PPA Amortization Charge (IS Impact) | C79: =SUM(C69:C78) -> 414.89394 | D79: =SUM(D69:D78) -> 367.29394 | E79: =SUM(E69:E78) -> 367.29394 | F79: =SUM(F69:F78) -> 367.29394 | G79: =SUM(G69:G78) -> 367.29394 | H79: =SUM(H69:H78) -> 326.61154 | I79: =SUM(I69:I78) -> 326.61154 | J79: =SUM(J69:J78) -> 152.2584

Sheet Pro forma Financials
B1: ■ Blue = Input | D1: ■ Black = Formula | F1: ■ Green = Cross-Tab Link | H1: ■ Yellow = Key Output
A2: Pro Forma Combined Financial Statements : HPE + Juniper Networks
B4: Pro Forma Year (Select):
A6: I. PRO FORMA INCOME STATEMENT ($mm)
B7: Line Item | C7: Acquirer (HPE) | D7: Target (JNPR) | E7: Synergies | F7: PPA Adj. | G7: Eliminations | H7: Pro Forma Combined
B8: Revenue | C8: ='Acquirer Standalone'!C8 -> 26944 | D8: ='Target Standalone'!C8 -> 4445.1 | E8: ='Synergy Assumptions'!C10 -> 0 | H8: =SUM(C8:G8) -> 31389.1
B9: YoY Growth (%) | C9: — | D9: — | E9: — | F9: — | G9: — | H9: =IFERROR(H8/H8,"-") -> 1
B10: Cost of Revenue | C10: ='Acquirer Standalone'!C10 -> 18892 | D10: ='Target Standalone'!C10 -> 1627.5 | H10: =SUM(C10:G10) -> 20519.5
B11: Gross Profit | C11: ='Acquirer Standalone'!C11 -> 8052 | D11: ='Target Standalone'!C11 -> 2817.6 | E11: ='Synergy Assumptions'!C10 -> 0 | F11: =-'PPA & BS Adjustments'!E29 -> 0 | H11: =SUM(C8:G8)-SUM(C10:G10) -> 10869.6
B12: Gross Margin (%) | C12: — | D12: — | E12: — | F12: — | G12: — | H12: =IFERROR(H11/H8,"-") -> 0.34628581
B13: Research & Development | C13: ='Acquirer Standalone'!C13 -> 1874 | D13: ='Target Standalone'!C13 -> 958.4 | H13: =SUM(C13:G13) -> 2832.4
B14: Selling, General & Administrative | C14: ='Acquirer Standalone'!C15 -> 4624 | D14: ='Target Standalone'!C15 -> 1169.6 | H14: =SUM(C14:G14) -> 5793.6
B15: Other Operating Expenses | C15: ='Acquirer Standalone'!C17 -> 1030 | D15: ='Target Standalone'!C17 -> 37.1 | H15: =SUM(C15:G15) -> 1067.1
B16: PPA Amortization (Intangibles) | F16: ='PPA & BS Adjustments'!C69 -> 124.30733 | H16: =SUM(C16:G16) -> 124.30733
B17: Total Operating Expenses | C17: ='Acquirer Standalone'!C18 -> 26420 | D17: ='Target Standalone'!C18 -> 2165.1 | E17: =-'Synergy Assumptions'!C18 -> -125.32289 | H17: =SUM(C13:G16) -> 9817.4073
B18: EBIT (Operating Income) | C18: ='Acquirer Standalone'!C19 -> 524 | D18: ='Target Standalone'!C19 -> 652.5 | E18: ='Synergy Assumptions'!C20 -> 125.32289 | H18: =H11-H17 -> 1052.1927
B19: EBIT Margin (%) | C19: — | D19: — | E19: — | F19: — | G19: — | H19: =IFERROR(H18/H8,"-") -> 0.033520957
B20: Depreciation & Amortization | C20: ='Acquirer Standalone'!C21 -> 2625 | D20: ='Target Standalone'!C21 -> 206.8 | F20: ='PPA & BS Adjustments'!C79 -> 414.89394 | H20: =SUM(C20:G20) -> 3246.6939
B21: EBITDA | H21: =H18+H20 -> 4298.8866
B22: EBITDA Margin (%) | C22: — | D22: — | E22: — | F22: — | G22: — | H22: =IFERROR(H21/H8,"-") -> 0.13695476
B23: Interest Expense (pro forma) | C23: ='Acquirer Standalone'!C24 -> 256 | D23: ='Target Standalone'!C24 -> 77 | H23: =SUM(C23:G23) -> 333
B24: Interest Income | C24: ='Acquirer Standalone'!C25 -> 0 | D24: ='Target Standalone'!C25 -> 36.3 | H24: =SUM(C24:G24) -> 36.3
B25: Other Non-Operating (Income)/Expense | C25: ='Acquirer Standalone'!C26 -> 56 | D25: ='Target Standalone'!C26 -> 7.8 | H25: =SUM(C25:G25) -> 63.8
B26: Pre-Tax Income (EBT) | C26: ='Acquirer Standalone'!C27 -> -442 | D26: ='Target Standalone'!C27 -> 265.2 | E26: ='Synergy Assumptions'!C20 -> 125.32289 | H26: =H18-H23+H24-H25 -> 691.69267
B27: Pre-Tax Margin (%) | C27: — | D27: — | E27: — | F27: — | G27: — | H27: =IFERROR(H26/H8,"-") -> 0.022036078
B28: Income Tax Expense | C28: ='Acquirer Standalone'!C29 -> -120 | D28: ='Target Standalone'!C29 -> 7.4 | E28: =E26*0.21 -> 26.317807 | F28: =H16*0.21 -> 26.10454 | H28: =SUM(C28:G28) -> -60.177653
B29: Effective Tax Rate (%) | C29: — | D29: — | E29: — | F29: — | G29: — | H29: =IFERROR(H28/H26,"-") -> -0.087000566
B30: Net Income (Pro Forma) | C30: ='Acquirer Standalone'!C31 -> -322 | D30: ='Target Standalone'!C31 -> 257.8 | E30: =E26-E28 -> 99.005082 | H30: =H26-H28 -> 751.87032
B31: Net Margin (%) | C31: — | D31: — | E31: — | F31: — | G31: — | H31: =IFERROR(H30/H8,"-") -> 0.02395323
B33: Key Pro Forma Metrics
B34: EPS — Basic ($) | C34: ='Acquirer Standalone'!C33 -> -0.2488 | D34: ='Target Standalone'!C33 -> 0.78026634 | H34: =IF(H36=0,0,H30/H36) -> 0.58104352
B35: EPS — Diluted ($) | C35: ='Acquirer Standalone'!C34 -> -0.2488 | D35: ='Target Standalone'!C34 -> 0.76909308 | H35: =IF(H37=0,0,H30/H37) -> 0.58104352
B36: Shares — Basic (mm) | C36: ='Acquirer Standalone'!C35 -> 1294 | D36: ='Target Standalone'!C35 -> 330.4 | H36: =C36 -> 1294
B37: Shares — Diluted (mm) | C37: ='Acquirer Standalone'!C36 -> 1294 | D37: ='Target Standalone'!C36 -> 335.2 | H37: =C37 -> 1294
A39: II. PRO FORMA BALANCE SHEET SUMMARY ($mm)
B40: Balance Sheet Item | C40: Acquirer (HPE) | D40: Target (JNPR) | E40: PPA Adj. | F40: Financing Adj. | G40: Elimination | H40: Pro Forma Opening
B41: Assets
B42: Cash & Cash Equivalents | C42: ='Acquirer Standalone'!C40 -> 4621 | D42: ='Target Standalone'!C40 -> 1793.2 | E42: ='PPA & BS Adjustments'!D36 -> 0 | F42: ='PPA & BS Adjustments'!E36 -> -3246 | H42: =SUM(C42:G42) -> 3168.2
B43: Accounts Receivable, net | C43: ='Acquirer Standalone'!C41 -> 7688 | D43: ='Target Standalone'!C41 -> 964.1 | E43: ='PPA & BS Adjustments'!D37 -> 0 | F43: ='PPA & BS Adjustments'!E37 -> 0 | H43: =SUM(C43:G43) -> 8652.1
B44: Inventories | C44: ='Acquirer Standalone'!C42 -> 2387 | D44: ='Target Standalone'!C42 -> 221.9 | E44: ='PPA & BS Adjustments'!D38 -> 0 | F44: ='PPA & BS Adjustments'!E38 -> 0 | H44: =SUM(C44:G44) -> 2608.9
B45: Other Current Assets | C45: ='Acquirer Standalone'!C43 -> 992 | D45: ='Target Standalone'!C43 -> 292 | E45: ='PPA & BS Adjustments'!D39 -> 0 | F45: ='PPA & BS Adjustments'!E39 -> 0 | H45: =SUM(C45:G45) -> 1284
B46: Total Current Assets | C46: =SUM(C42:C45) -> 15688 | D46: =SUM(D42:D45) -> 3271.2 | E46: =SUM(E42:E45) -> 0 | F46: =SUM(F42:F45) -> -3246 | G46: =SUM(G42:G45) -> 0 | H46: =SUM(H42:H45) -> 15713.2
B47: PP&E, net | C47: ='Acquirer Standalone'!C46 -> 6054 | D47: ='Target Standalone'!C46 -> 946.9 | E47: ='PPA & BS Adjustments'!D41 -> 98.7 | F47: ='PPA & BS Adjustments'!E41 -> 0 | H47: =SUM(C47:G47) -> 7099.6
B48: Goodwill | C48: ='Acquirer Standalone'!C47 -> 18306 | D48: ='Target Standalone'!C47 -> 3669.6 | E48: ='PPA & BS Adjustments'!D42 -> 6491.9875 | F48: ='PPA & BS Adjustments'!E42 -> 0 | H48: =SUM(C48:G48) -> 28467.587
B49: Identified Intangibles, net | C49: ='Acquirer Standalone'!C48 -> 1128 | D49: ='Target Standalone'!C48 -> 266.7 | E49: ='PPA & BS Adjustments'!D43 -> 3333.088 | F49: ='PPA & BS Adjustments'!E43 -> 0 | H49: =SUM(C49:G49) -> 4727.788
B50: Other Non-Current Assets | C50: ='Acquirer Standalone'!C52-'Acquirer Standalone'!C44-'Acquirer Standalone'!C46-'Acquirer Standalone'!C47-'Acquirer Standalone'!C48 -> 10627 | D50: ='Target Standalone'!C49+'Target Standalone'!C50 -> 1223.9 | E50: ='PPA & BS Adjustments'!D44 -> 0 | F50: ='PPA & BS Adjustments'!E44 -> 0 | H50: =SUM(C50:G50) -> 11850.9
B51: Total Assets | C51: =C46+C47+C48+C49+C50 -> 51803 | D51: =D46+D47+D48+D49+D50 -> 9378.3 | E51: =E46+E47+E48+E49+E50 -> 9923.7755 | F51: =F46+F47+F48+F49+F50 -> -3246 | G51: =G46+G47+G48+G49+G50 -> 0 | H51: =H46+H47+H48+H49+H50 -> 67859.075
B52: Liabilities & Equity
B53: Accounts Payable | C53: ='Acquirer Standalone'!C54 -> 5595 | D53: ='PPA & BS Adjustments'!C48 -> 295.1 | E53: ='PPA & BS Adjustments'!D48 -> 0 | F53: ='PPA & BS Adjustments'!E48 -> 0 | H53: =SUM(C53:G53) -> 5890.1
B54: Short-Term Debt | C54: ='Acquirer Standalone'!C55 -> 4425 | D54: ='PPA & BS Adjustments'!C49 -> 46.4 | E54: ='PPA & BS Adjustments'!D49 -> 0 | F54: ='PPA & BS Adjustments'!E49 -> 0 | H54: =SUM(C54:G54) -> 4471.4
B55: Accrued Liabilities | C55: ='Acquirer Standalone'!C56 -> 1522 | D55: ='PPA & BS Adjustments'!C50 -> 292.2 | E55: ='PPA & BS Adjustments'!D50 -> 0 | F55: ='PPA & BS Adjustments'!E50 -> 0 | H55: =SUM(C55:G55) -> 1814.2
B56: Other Current Liabilities | C56: ='Acquirer Standalone'!C57 -> 7431 | D56: ='PPA & BS Adjustments'!C51 -> 1470.3 | E56: ='PPA & BS Adjustments'!D51 -> 0 | F56: ='PPA & BS Adjustments'!E51 -> 0 | H56: =SUM(C56:G56) -> 8901.3
B57: Total Current Liabilities | C57: =SUM(C53:C56) -> 18973 | D57: =SUM(D53:D56) -> 2104 | E57: =SUM(E53:E56) -> 0 | F57: =SUM(F53:F56) -> 0 | G57: =SUM(G53:G56) -> 0 | H57: =SUM(H53:H56) -> 21077
B58: Long-Term Debt (Pro Forma) | C58: ='Acquirer Standalone'!C60 -> 9395 | D58: ='PPA & BS Adjustments'!C53 -> 1699.7 | E58: ='PPA & BS Adjustments'!D53 -> 0 | F58: ='PPA & BS Adjustments'!E53 -> 10000 | H58: =SUM(C58:G58) -> 21094.7
B59: Deferred Tax Liabilities (PPA) | C59: ='Acquirer Standalone'!C61 -> 311 | D59: ='PPA & BS Adjustments'!C54 -> 12 | E59: ='PPA & BS Adjustments'!D54 -> 720.67548 | F59: ='PPA & BS Adjustments'!E54 -> 0 | H59: =SUM(C59:G59) -> 1043.6755
B60: Other Non-Current Liabilities | C60: ='Acquirer Standalone'!C62 -> 5789 | D60: ='PPA & BS Adjustments'!C55 -> 1210.1 | E60: ='PPA & BS Adjustments'!D55 -> 0 | F60: ='PPA & BS Adjustments'!E55 -> 0 | H60: =SUM(C60:G60) -> 6999.1
B61: Total Liabilities | C61: =C57+C58+C59+C60 -> 34468 | D61: =D57+D58+D59+D60 -> 5025.8 | E61: =E57+E58+E59+E60 -> 720.67548 | F61: =F57+F58+F59+F60 -> 10000 | G61: =G57+G58+G59+G60 -> 0 | H61: =H57+H58+H59+H60 -> 50214.475
B62: Total Equity (Pro Forma) | C62: =C51-C61 -> 17335 | D62: =D51-D61 -> 4352.5 | E62: ='PPA & BS Adjustments'!D62 -> 9203.1 | F62: ='PPA & BS Adjustments'!E62 -> -13246 | H62: =SUM(C62:G62) -> 17644.6
B63: Total Liabilities & Equity | C63: =C61+C62 -> 51803 | D63: =D61+D62 -> 9378.3 | E63: =E61+E62 -> 9923.7755 | F63: =F61+F62 -> -3246 | G63: =G61+G62 -> 0 | H63: =H61+H62 -> 67859.075
B64: Balance Sheet Check | C64: =IFERROR(IF(ABS(C51-C63)<1,"✓","✗ "&TEXT(C51-C63,"$#,##0")),"-") -> ✓ | D64: =IFERROR(IF(ABS(D51-D63)<1,"✓","✗ "&TEXT(D51-D63,"$#,##0")),"-") -> ✓ | E64: =IFERROR(IF(ABS(E51-E63)<1,"✓","✗ "&TEXT(E51-E63,"$#,##0")),"-") -> ✓ | F64: =IFERROR(IF(ABS(F51-F63)<1,"✓","✗ "&TEXT(F51-F63,"$#,##0")),"-") -> ✓ | G64: =IFERROR(IF(ABS(G51-G63)<1,"✓","✗ "&TEXT(G51-G63,"$#,##0")),"-") -> ✓ | H64: =IFERROR(IF(ABS(H51-H63)<1,"✓","✗ "&TEXT(H51-H63,"$#,##0")),"-") -> ✓
A66: III. PRO FORMA CASH FLOW SUMMARY ($mm)
B67: Cash Flow Item | C67: Acquirer (HPE) | D67: Target (JNPR) | E67: Synergies | F67: PPA Adj. | G67: Other Adj. | H67: Pro Forma
B68: Net Income (Pro Forma) | C68: ='Acquirer Standalone'!C76 -> -322 | D68: ='Target Standalone'!C76 -> 257.8 | F68: =-'PPA & BS Adjustments'!C79*(1-0.21) -> -327.76621 | H68: =SUM(C68:G68) -> -391.96621
B69: (+) D&A (incl. PPA amort.) | C69: ='Acquirer Standalone'!C77 -> 2625 | D69: ='Target Standalone'!C77 -> 206.8 | F69: ='PPA & BS Adjustments'!C79 -> 414.89394 | H69: =SUM(C69:G69) -> 3246.6939
B70: (+/–) Working Capital Changes | C70: ='Acquirer Standalone'!C78 -> -2246 | D70: ='Target Standalone'!C78 -> -90.5 | H70: =SUM(C70:G70) -> -2336.5
B71: Other Operating Adjustments | C71: ='Acquirer Standalone'!C79 -> 2183 | D71: ='Target Standalone'!C79 -> 232.3 | F71: ='Sources & Uses'!G16 -> 210 | H71: =SUM(C71:G71) -> 2625.3
B72: Cash Flow from Operations (CFO) | H72: =SUM(H68:H71) -> 3143.5277
B73: Capital Expenditures (CapEx) | C73: ='Acquirer Standalone'!C82 -> -2383 | D73: ='Target Standalone'!C82 -> -100.4 | H73: =SUM(C73:G73) -> -2483.4
B74: Other Investing Activities | C74: ='Acquirer Standalone'!C83+'Acquirer Standalone'!C84+'Acquirer Standalone'!C85 -> -195 | D74: ='Target Standalone'!C83+'Target Standalone'!C84+'Target Standalone'!C85 -> -188.5 | E74: =-('Sources & Uses'!G9) -> -13036 | H74: =SUM(C74:G74) -> -13419.5
B75: Cash Flow from Investing (CFI) | H75: =H73+H74 -> -15902.9
B76: Debt Issuance / (Repayment) | C76: ='Acquirer Standalone'!C88 -> 1908 | D76: ='Target Standalone'!C88 -> 363.3 | E76: ='Sources & Uses'!C19 -> 10000 | H76: =SUM(C76:G76) -> 12271.3
B77: Transaction Financing Adjustments | E77: =-'Sources & Uses'!G16 -> -210 | H77: =SUM(C77:G77) -> -210
B78: Dividends Paid | C78: ='Acquirer Standalone'!C90 -> -618 | D78: ='Target Standalone'!C90 -> -264.1 | H78: =SUM(C78:G78) -> -882.1
B79: Other Financing Activities | C79: ='Acquirer Standalone'!C89+'Acquirer Standalone'!C91 -> -398 | D79: ='Target Standalone'!C89+'Target Standalone'!C91 -> -321.6 | E79: =0 -> 0 | H79: =SUM(C79:G79) -> -719.6
B80: Cash Flow from Financing (CFF) | H80: =SUM(H76:H79) -> 10459.6
B81: Net Change in Cash | H81: =H72+H75+H80 -> -2299.7723
B82: Beginning Cash Balance | H82: =H42 -> 3168.2
B83: Ending Cash Balance | H83: =H81+H82 -> 868.42773
A85: IV. KEY PRO FORMA METRICS & CREDIT STATISTICS
B86: Metric | C86: Pre-Synergy | D86: Run-Rate Syn. | E86: Pro Forma
B87: Pro Forma Revenue ($mm) | C87: =H8 -> 31389.1 | D87: =H8+'Synergy Assumptions'!G20 -> 31890.392 | E87: =H8 -> 31389.1
B88: Pro Forma EBITDA ($mm) | C88: =H21 -> 4298.8866 | D88: =H21+'Synergy Assumptions'!G20 -> 4800.1782 | E88: =H21 -> 4298.8866
B89: Pro Forma EBITDA Margin (%) | C89: =IFERROR(H21/H8,0) -> 0.13695476 | D89: =IFERROR((H21+G27)/(H8+G27),0) -> 0 | E89: =IFERROR(H21/H8,0) -> 0.13695476
B90: Pro Forma EBIT ($mm) | C90: =H18 -> 1052.1927 | D90: =H18+'Synergy Assumptions'!G20 -> 1553.4842 | E90: =H18 -> 1052.1927
B91: Pro Forma Net Income ($mm) | C91: =H30 -> 751.87032 | D91: =H30+'Synergy Assumptions'!G20*(1-0.21) -> 1147.8906 | E91: =H30 -> 751.87032
B92: Pro Forma FCF ($mm) | C92: =H72+H73 -> 660.12773 | D92: =H72+H73 -> 660.12773 | E92: =H72+H73 -> 660.12773
B93: Total Debt ($mm) | C93: =H54+H58 -> 25566.1 | D93: =H54+H58 -> 25566.1 | E93: =H54+H58 -> 25566.1
B94: Cash & Equivalents ($mm) | C94: =H42 -> 3168.2 | D94: =H42 -> 3168.2 | E94: =H42 -> 3168.2
B95: Net Debt ($mm) | C95: =IFERROR(C93-C94,0) -> 22397.9 | D95: =IFERROR(D93-D94,0) -> 22397.9 | E95: =IFERROR(E93-E94,0) -> 22397.9
B96: Gross Leverage (Debt/EBITDA) | C96: =IFERROR(C93/H21,0) -> 5.9471445 | D96: =IFERROR(D93/(H21+'Synergy Assumptions'!G20),0) -> 5.3260731 | E96: =IFERROR(E93/H21,0) -> 5.9471445
B97: Net Leverage (Net Debt/EBITDA) | C97: =IFERROR(C95/H21,0) -> 5.210163 | D97: =IFERROR(D95/(H21+'Synergy Assumptions'!G20),0) -> 4.666056 | E97: =IFERROR(E95/H21,0) -> 5.210163
