Workbook
Name AnnFactor: 'Risk Metrics'!$D$5
Name RiskFreeRate: 'Risk Metrics'!$B$5
Name w_BS: 'Factor Screen'!$G$5
Name w_Earn: 'Factor Screen'!$K$5
Name w_FCF: 'Factor Screen'!$I$5
Name w_GM: 'Factor Screen'!$E$5
Name w_ROIC: 'Factor Screen'!$C$5

Sheet Mandate
A1: GLOBAL QUALITY COMPOUNDER PORTFOLIO: INVESTMENT MANDATE
A2: Investment Policy Statement(IPS) : Defines the mandate, constraints and risk parameters governing portfolio construction and management.
A4: # | B4: MANDATE PARAMETER | C4: SPECIFICATION | D4: RATIONALE / NOTES | E4: STATUS
A5: 1 | B5: Portfolio Objective | C5: Outperform MSCI World Index by +200 bps per annum, net of all fees, over a full market cycle (5+ years). | D5: Target alpha generation through disciplined quality factor exposure and concentrated high-conviction portfolio construction. | E5: Active
A6: 2 | B6: Benchmark | C6: MSCI World Index (Net Total Return, USD) | D6: Broad global developed-market equity benchmark; representative of investment universe; widely used by institutional allocators. | E6: Defined
A7: 3 | B7: Investment Universe | C7: Global large-cap equities. Minimum market capitalisation of USD $10 billion at time of purchase. | D7: Ensures liquidity, institutional coverage and reliable financial data. Excludes micro/small-cap risk. | E7: Defined
A8: 4 | B8: Geographic Limits | C8: Maximum 40% exposure to any single geographic region (North America / Europe / Asia Pacific). | D8: Prevents undue concentration in any single economic bloc; ensures genuine global diversification. | E8: Compliant
A9: 5 | B9: Single Stock Position Limit | C9: Maximum 8% weight per holding at time of rebalance. Minimum 2% to ensure meaningful contribution. | D9: Balances concentration (for alpha) against idiosyncratic risk; prevents dilution of high-conviction names. | E9: Compliant
A10: 6 | B10: Number of Holdings | C10: 12 to 15 stocks at all times. | D10: Concentrated enough for active returns; diversified enough to manage stock-specific risk within tracking error budget. | E10: Compliant
A11: 7 | B11: Rebalancing Frequency | C11: Quarterly (Jan, Apr, Jul, Oct). Interim rebalance if any position breaches +/-3% of target weight. | D11: Balances turnover efficiency against drift risk. Interim trigger prevents unintended concentration. | E11: Quarterly
A12: 8 | B12: Risk Budget — Tracking Error | C12: Maximum 4.0% ex-ante tracking error versus MSCI World, measured monthly. | D12: Defines active risk budget. A 4% TE reflects high-conviction active management within typical AM mandates. | E12: Monitored
A13: 9 | B13: Permitted Instruments | C13: Equity only, ordinary shares and ADRs listed on NYSE, NASDAQ, LSE, Euronext, TSX or ASX. | D13: No derivatives, leverage, short selling or fixed income. Pure long-only equity for mandate transparency. | E13: Compliant
A14: 10 | B14: Currency Policy | C14: Unhedged. Portfolio denominated in USD for reporting purposes. | D14: Reflects natural currency exposure of a global equity mandate. Currency is an accepted source of return and risk. | E14: Unhedged
A15: 11 | B15: ESG / Exclusions | C15: Exclude companies deriving >10% revenue from tobacco, controversial weapons or thermal coal extraction. | D15: Reflects responsible investment principles; consistent with typical institutional AM client requirements. | E15: Screened
A16: 12 | B16: Quality Screen: ROIC | C16: Minimum 15% ROIC (5-year average) for inclusion in investable universe. | D16: Core quality factor: identifies businesses earning above their cost of capital consistently across cycles. | E16: Applied
... A19: 15 | B19: Portfolio Manager | C19: Senior Portfolio Manager : Global Quality Equities | D19: Single PM accountability with IC oversight required for positions exceeding 6% portfolio weight. | E19: Assigned
A21: This document is for internal portfolio management purposes only. All parameters subject to Investment Committee approval. Last reviewed: Q1 2026.

Sheet Universe
A1: GLOBAL QUALITY COMPOUNDER PORTFOLIO: INVESTMENT UNIVERSE
A2: Quality Compounder Screening Universe: 35 global large-cap candidates. Static data pre-filled; highlighted yellow columns require annual report inputs.
A4: # | B4: COMPANY | C4: TICKER | D4: COUNTRY | E4: SECTOR | F4: MKT CAP ($BN) (Mar 26) | G4: ROIC (%) (FY 25) | H4: GROSS MARGIN (%) (FY 25) | I4: NET DEBT / EBITDA (FY 25) | J4: FCF CONVERSION (%). (FY 25) | K4: 5Y REV AVG PER SH (FY 21-25) ($)
A5: 1 | B5: Microsoft Corporation | C5: MSFT | D5: United States | E5: Technology | F5: 2875.42 | G5: 0.256 | H5: 0.6882 | I5: =-0.03 -> -0.03 | J5: 0.4667 | K5: 29.46
A6: 2 | B6: Accenture plc | C6: ACN | D6: United States | E6: Technology | F6: 126.23 | G6: 0.221 | H6: 0.319 | I6: -0.51 | J6: 0.9348 | K6: 97.33
A7: 3 | B7: Automatic Data Processing | C7: ADP | D7: United States | E7: Technology | F7: 84.89 | G7: 0.4446 | H7: 0.5037 | I7: 0.16 | J7: 0.5814 | K7: 42.89
A8: 4 | B8: Veeva Systems | C8: VEEV | D8: United States | E8: Technology | F8: 30.51 | G8: 0.1377 | H8: 0.752 | I8: -6.58 | J8: 1.525 | K8: 14.98
A9: 5 | B9: Constellation Software | C9: CSU | D9: Canada | E9: Technology | F9: 38.5 | G9: 0.0707 | H9: 0.3958 | I9: 0.79 | J9: 4.764 | K9: 390
A10: 6 | B10: Wolters Kluwer | C10: WKL | D10: Netherlands | E10: Technology | F10: 16.74 | G10: 0.2565 | H10: 0.6591 | I10: 2.01 | J10: 0.8287 | K10: 26.31
A11: 7 | B11: Rightmove | C11: RMV | D11: United Kingdom | E11: Technology | F11: 4.3 | G11: 2.547 | H11: 0.984 | I11: -0.12 | J11: 0.7337 | K11: 0.6
A12: 8 | B12: Visa Inc. | C12: V | D12: United States | E12: Financials | F12: 586.8 | G12: 0.3339 | H12: 0.7731 | I12: 0.07 | J12: 0.8534 | K12: 15.69
A13: 9 | B13: Mastercard Incorporated | C13: MA | D13: United States | E13: Financials | F13: 447.81 | G13: 0.5841 | H13: 0.9603 | I13: 0.36 | J13: 0.9458 | K13: 27.02
A14: 10 | B14: S&P Global Inc. | C14: SPGI | D14: United States | E14: Financials | F14: 128.57 | G14: 0.1004 | H14: 0.6256 | I14: 1.48 | J14: 0.9586 | K14: 40.89
A15: 11 | B15: Moody's Corporation | C15: MCO | D15: United States | E15: Financials | F15: 78.89 | G15: 0.2254 | H15: 0.6815 | I15: 1.16 | J15: 0.7621 | K15: 35.31
A16: 12 | B16: MSCI Inc. | C16: MSCI | D16: United States | E16: Financials | F16: 42 | G16: 0.3273 | H16: 0.7629 | I16: 2.94 | J16: 0.8089 | K16: 32.18
A17: 13 | B17: Intercontinental Exchange | C17: ICE | D17: United States | E17: Financials | F17: 89.93 | G17: 0.0709 | H17: 0.6846 | I17: 2.64 | J17: 0.9605 | K17: 18.37
... A19: 15 | B19: Novo Nordisk A/S | C19: NOVO B | D19: Denmark | E19: Healthcare | F19: 162 | G19: 0.3751 | H19: 0.8034 | I19: 0.69 | J19: 0.0703 | K19: 7.94
A20: 16 | B20: Idexx Laboratories | C20: IDXX | D20: United States | E20: Healthcare | F20: =46.44 -> 46.44 | G20: 0.5016 | H20: 0.6182 | I20: 0.44 | J20: 0.9943 | K20: 44.09
A21: 17 | B21: Danaher Corporation | C21: DHR | D21: United States | E21: Healthcare | F21: =135.82 -> 135.82 | G21: 0.0522 | H21: 0.5923 | I21: 1.79 | J21: 1.2172 | K21: 36.3
A22: 18 | B22: Align Technology | C22: ALGN | D22: United States | E22: Healthcare | F22: =13.16 -> 13.16 | G22: =0.1017 -> 0.1017 | H22: 0.698 | I22: =-1.29 -> -1.29 | J22: 1.196 | K22: 51.32
A23: 19 | B23: West Pharmaceutical Services | C23: WST | D23: United States | E23: Healthcare | F23: =17.55 -> 17.55 | G23: 0.1532 | H23: 0.3592 | I23: =-0.72 -> -0.72 | J23: 0.8258 | K23: 39.18
A24: 20 | B24: LVMH Moët Hennessy | C24: MC | D24: France | E24: Consumer Discretionary | F24: =269.17 -> 269.17 | G24: 0.1159 | H24: 0.6624 | I24: 0.94 | J24: 0.7662 | K24: 157.79
A25: 21 | B25: Hermès International | C25: RMS | D25: France | E25: Consumer Discretionary | F25: =200.53 -> 200.53 | G25: =0.226 -> 0.226 | H25: 0.6655 | I25: =-1.32 -> -1.32 | J25: 0.3674 | K25: 144.1
A26: 22 | B26: L'Oréal S.A. | C26: OR | D26: France | E26: Consumer Staples | F26: =213.78 -> 213.78 | G26: 0.1456 | H26: 0.7432 | I26: 0.19 | J26: 0.5295 | K26: =85.6 -> 85.6
A27: 23 | B27: Ferrari N.V. | C27: RACE | D27: Italy | E27: Consumer Discretionary | F27: =56.88 -> 56.88 | G27: 0.2806 | H27: 0.5246 | I27: 0.48 | J27: 0.8356 | K27: 37.78
A28: 24 | B28: Diageo plc | C28: DGE | D28: United Kingdom | E28: Consumer Staples | F28: =41.18 -> 41.18 | G28: 0.0785 | H28: 0.6049 | I28: 3.16 | J28: 0.1644 | K28: 9.07
A29: 25 | B29: ASML Holding N.V. | C29: ASML | D29: Netherlands | E29: Technology | F29: =498.56 -> 498.56 | G29: 0.428 | H29: 0.5156 | I29: =-0.72 -> -0.72 | J29: 0.8882 | K29: 64.86
A30: 26 | B30: Fastenal Company | C30: FAST | D30: United States | E30: Industrials | F30: =51.19 -> 51.19 | G30: 0.3076 | H30: 0.4296 | I30: =-0.08 -> -0.08 | J30: 0.0369 | K30: 6.28
A31: 27 | B31: Copart Inc. | C31: CPRT | D31: United States | E31: Industrials | F31: =32.4 -> 32.4 | G31: 0.1838 | H31: 0.4467 | I31: -2.5 | J31: 0.7928 | K31: 3.91
A32: 28 | B32: Roper Technologies | C32: ROP | D32: United States | E32: Industrials | F32: =36.65 -> 36.65 | G32: 0.0566 | H32: 0.6924 | I32: 2.87 | J32: 1.3916 | K32: 60.06
A33: 29 | B33: Rational AG | C33: RAA | D33: Germany | E33: Industrials | F33: =8.13 -> 8.13 | G33: 0.2766 | H33: 0.5902 | I33: =-1.39 -> -1.39 | J33: 0.2348 | K33: 109.69
A34: 30 | B34: Verisk Analytics | C34: VRSK | D34: United States | E34: Industrials | F34: =27.69 -> 27.69 | G34: 0.2803 | H34: 0.5925 | I34: 1.5 | J34: 1.0358 | K34: 18.88
A35: 31 | B35: TransUnion | C35: TRU | D35: United States | E35: Financials | F35: 14 | G35: 0.0487 | H35: 0.4653 | I35: 2.84 | J35: 1.2541 | K35: 19.78
A36: 32 | B36: Taiwan Semiconductor | C36: 2330-TW | D36: Taiwan | E36: Technology | F36: =1490.22 -> 1490.22 | G36: 0.2956 | H36: 0.5872 | I36: =-0.76 -> -0.76 | J36: 0.3557 | K36: 3.05
A37: 33 | B37: Keyence Corporation | C37: 6861 | D37: Japan | E37: Technology | F37: =90.59 -> 90.59 | G37: 0.1348 | H37: 0.8381 | I37: =-2.16 -> -2.16 | J37: 0.7936 | K37: 23.3
A38: 34 | B38: EssilorLuxottica | C38: EL | D38: France | E38: Healthcare | F38: =104.6 -> 104.6 | G38: 0.047 | H38: 0.6061 | I38: =1.68 -> 1.68 | J38: 1.517 | K38: 63.68
A39: 35 | B39: Mettler-Toledo International | C39: MTD | D39: Switzerland | E39: Healthcare | F39: =25.28 -> 25.28 | G39: 0.4418 | H39: 0.5752 | I39: =1.68 -> 1.68 | J39: 0.9764 | K39: 175.97
A41: Input Legend: | B41: Yellow cells = user input required (fill from annual reports / Bloomberg)
B42: Quality Score = composite rank across 5 metrics (auto-calculated when all 5 inputs are filled)

Sheet Factor Screen
A1: GLOBAL QUALITY COMPOUNDER PORTFOLIO — FACTOR SCORING MODEL
A2: Quality Factor Screen — Each stock scored 1–5 per factor. Composite score = weighted average. Yellow cells = raw metric inputs. Scores auto-calculate via IF/PERCENTRANK logic.
A4: FACTOR WEIGHTS (must sum to 100%) | P4: RANKED SHORTLIST — TOP 20 BY COMPOSITE SCORE
A5: Factor: | B5: ROIC vs WACC Spread | C5: 0.3 | D5: Gross Margin Stability | E5: 0.2 | F5: Balance Sheet Strength | G5: 0.2 | H5: FCF Conversion | I5: 0.2 | J5: Earnings Consistency | K5: 0.1 | M5: Sum: | N5: =C5+E5+G5+I5+K5 -> 1 | P5: Auto-ranked from composite scores. 'In Portfolio?' links live to Portfolio tab. Top 15 scores = primary candidates.
A7: Scoring Scale: | B7: 5 = Top quintile (>80th pctile) | 4 = Second quintile (60–80th) | 3 = Middle (40–60th) | 2 = Below avg (20–40th) | 1 = Bottom quintile (<20th pctile) | P7: RANK | Q7: COMPANY | R7: TICKER | S7: COMPOSITE SCORE | T7: ROIC Score | U7: GM Score | V7: BS Score | W7: FCF Score | X7: EARN Score | Y7: IN PORTFOLIO?
A8: # | B8: COMPANY | C8: TICKER | D8: ROIC (%) [Input] | E8: ROIC Score | F8: GROSS MARGIN (%) [Input] | G8: GM Score | H8: NET DEBT/EBITDA [Input] | I8: BS Score | J8: FCF CONV (%) [Input] | K8: FCF Score | L8: 5Y REV AVG PER SH (FY 21-25) ($) | M8: Earn Score | N8: COMPOSITE SCORE | P8: 1 | Q8: {=IFERROR(INDEX($B$9:$B$43,MATCH(LARGE($N$9:$N$43+(ROW($N$9:$N$43)-ROW($N$9))/1000,1),$N$9:$N$43+(ROW($N$9:$N$43)-ROW($N$9))/1000,0)),"")} -> Mastercard Incorporated | R8: {=IFERROR(INDEX($C$9:$C$43,MATCH(LARGE($N$9:$N$43+(ROW($N$9:$N$43)-ROW($N$9))/1000,1),$N$9:$N$43+(ROW($N$9:$N$43)-ROW($N$9))/1000,0)),"")} -> MA | S8: {=IFERROR(INDEX($N$9:$N$43,MATCH(LARGE($N$9:$N$43+(ROW($N$9:$N$43)-ROW($N$9))/1000,1),$N$9:$N$43+(ROW($N$9:$N$43)-ROW($N$9))/1000,0)),"")} -> 4.2 | T8: {=IFERROR(INDEX($E$9:$E$43,MATCH(LARGE($N$9:$N$43+(ROW($N$9:$N$43)-ROW($N$9))/1000,1),$N$9:$N$43+(ROW($N$9:$N$43)-ROW($N$9))/1000,0)),"")} -> 5 | U8: {=IFERROR(INDEX($G$9:$G$43,MATCH(LARGE($N$9:$N$43+(ROW($N$9:$N$43)-ROW($N$9))/1000,1),$N$9:$N$43+(ROW($N$9:$N$43)-ROW($N$9))/1000,0)),"")} -> 5 | V8: {=IFERROR(INDEX($I$9:$I$43,MATCH(LARGE($N$9:$N$43+(ROW($N$9:$N$43)-ROW($N$9))/1000,1),$N$9:$N$43+(ROW($N$9:$N$43)-ROW($N$9))/1000,0)),"")} -> 3 | W8: {=IFERROR(INDEX($K$9:$K$43,MATCH(LARGE($N$9:$N$43+(ROW($N$9:$N$43)-ROW($N$9))/1000,1),$N$9:$N$43+(ROW($N$9:$N$43)-ROW($N$9))/1000,0)),"")} -> 4 | X8: {=IFERROR(INDEX($M$9:$M$43,MATCH(LARGE($N$9:$N$43+(ROW($N$9:$N$43)-ROW($N$9))/1000,1),$N$9:$N$43+(ROW($N$9:$N$43)-ROW($N$9))/1000,0)),"")} -> 3 | Y8: =IF(R8="","",IF(COUNTIF(Portfolio!$C$5:$C$19,R8)>0,"YES","-")) -> YES
A9: 1 | B9: Microsoft Corporation | C9: MSFT | D9: =Universe!G5 -> 0.256 | E9: =IF(D9="","",MAX(1,MIN(5,1+INT(IFERROR(PERCENTRANK(D$9:D$43,D9),0.5)*5)))) -> 3 | F9: =Universe!H5 -> 0.6882 | G9: =IF(F9="","",MAX(1,MIN(5,1+INT(IFERROR(PERCENTRANK(F$9:F$43,F9),0.5)*5)))) -> 4 | H9: =Universe!I5 -> -0.03 | I9: =IF(H9="","",MAX(1,MIN(5,5-INT(IFERROR(PERCENTRANK(H$9:H$43,H9),0.5)*5)))) -> 4 | J9: =Universe!J5 -> 0.4667 | K9: =IF(J9="","",MAX(1,MIN(5,1+INT(IFERROR(PERCENTRANK(J$9:J$43,J9),0.5)*5)))) -> 1 | L9: =Universe!K5 -> 29.46 | M9: =IF(L9="","",MAX(1,MIN(5,1+INT(IFERROR(PERCENTRANK(L$9:L$43,L9),0.5)*5)))) -> 3 | N9: =IF(COUNTA(D9,F9,H9,J9,L9)<5,"",E9*C5+G9*E5+I9*G5+K9*I5+M9*K5) -> 3 | P9: 2 | Q9: {=IFERROR(INDEX($B$9:$B$43,MATCH(LARGE($N$9:$N$43+(ROW($N$9:$N$43)-ROW($N$9))/1000,2),$N$9:$N$43+(ROW($N$9:$N$43)-ROW($N$9))/1000,0)),"")} -> Idexx Laboratories | R9: {=IFERROR(INDEX($C$9:$C$43,MATCH(LARGE($N$9:$N$43+(ROW($N$9:$N$43)-ROW($N$9))/1000,2),$N$9:$N$43+(ROW($N$9:$N$43)-ROW($N$9))/1000,0)),"")} -> IDXX | S9: {=IFERROR(INDEX($N$9:$N$43,MATCH(LARGE($N$9:$N$43+(ROW($N$9:$N$43)-ROW($N$9))/1000,2),$N$9:$N$43+(ROW($N$9:$N$43)-ROW($N$9))/1000,0)),"")} -> 3.9 | T9: {=IFERROR(INDEX($E$9:$E$43,MATCH(LARGE($N$9:$N$43+(ROW($N$9:$N$43)-ROW($N$9))/1000,2),$N$9:$N$43+(ROW($N$9:$N$43)-ROW($N$9))/1000,0)),"")} -> 5 | U9: {=IFERROR(INDEX($G$9:$G$43,MATCH(LARGE($N$9:$N$43+(ROW($N$9:$N$43)-ROW($N$9))/1000,2),$N$9:$N$43+(ROW($N$9:$N$43)-ROW($N$9))/1000,0)),"")} -> 3 | V9: {=IFERROR(INDEX($I$9:$I$43,MATCH(LARGE($N$9:$N$43+(ROW($N$9:$N$43)-ROW($N$9))/1000,2),$N$9:$N$43+(ROW($N$9:$N$43)-ROW($N$9))/1000,0)),"")} -> 3 | W9: {=IFERROR(INDEX($K$9:$K$43,MATCH(LARGE($N$9:$N$43+(ROW($N$9:$N$43)-ROW($N$9))/1000,2),$N$9:$N$43+(ROW($N$9:$N$43)-ROW($N$9))/1000,0)),"")} -> 4 | X9: {=IFERROR(INDEX($M$9:$M$43,MATCH(LARGE($N$9:$N$43+(ROW($N$9:$N$43)-ROW($N$9))/1000,2),$N$9:$N$43+(ROW($N$9:$N$43)-ROW($N$9))/1000,0)),"")} -> 4 | Y9: =IF(R9="","",IF(COUNTIF(Portfolio!$C$5:$C$19,R9)>0,"YES","-")) -> YES
A10: 2 | B10: Accenture plc | C10: ACN | D10: =Universe!G6 -> 0.221 | E10: =IF(D10="","",MAX(1,MIN(5,1+INT(IFERROR(PERCENTRANK(D$9:D$43,D10),0.5)*5)))) -> 3 | F10: =Universe!H6 -> 0.319 | G10: =IF(F10="","",MAX(1,MIN(5,1+INT(IFERROR(PERCENTRANK(F$9:F$43,F10),0.5)*5)))) -> 1 | H10: =Universe!I6 -> -0.51 | I10: =IF(H10="","",MAX(1,MIN(5,5-INT(IFERROR(PERCENTRANK(H$9:H$43,H10),0.5)*5)))) -> 4 | J10: =Universe!J6 -> 0.9348 | K10: =IF(J10="","",MAX(1,MIN(5,1+INT(IFERROR(PERCENTRANK(J$9:J$43,J10),0.5)*5)))) -> 3 | L10: =Universe!K6 -> 97.33 | M10: =IF(L10="","",MAX(1,MIN(5,1+INT(IFERROR(PERCENTRANK(L$9:L$43,L10),0.5)*5)))) -> 5 | N10: =IF(COUNTA(D10,F10,H10,J10,L10)<5,"",E10*C5+G10*E5+I10*G5+K10*I5+M10*K5) -> 3 | P10: 3 | Q10: {=IFERROR(INDEX($B$9:$B$43,MATCH(LARGE($N$9:$N$43+(ROW($N$9:$N$43)-ROW($N$9))/1000,3),$N$9:$N$43+(ROW($N$9:$N$43)-ROW($N$9))/1000,0)),"")} -> Visa Inc. | R10: {=IFERROR(INDEX($C$9:$C$43,MATCH(LARGE($N$9:$N$43+(ROW($N$9:$N$43)-ROW($N$9))/1000,3),$N$9:$N$43+(ROW($N$9:$N$43)-ROW($N$9))/1000,0)),"")} -> V | S10: {=IFERROR(INDEX($N$9:$N$43,MATCH(LARGE($N$9:$N$43+(ROW($N$9:$N$43)-ROW($N$9))/1000,3),$N$9:$N$43+(ROW($N$9:$N$43)-ROW($N$9))/1000,0)),"")} -> 3.8 | T10: {=IFERROR(INDEX($E$9:$E$43,MATCH(LARGE($N$9:$N$43+(ROW($N$9:$N$43)-ROW($N$9))/1000,3),$N$9:$N$43+(ROW($N$9:$N$43)-ROW($N$9))/1000,0)),"")} -> 4 | U10: {=IFERROR(INDEX($G$9:$G$43,MATCH(LARGE($N$9:$N$43+(ROW($N$9:$N$43)-ROW($N$9))/1000,3),$N$9:$N$43+(ROW($N$9:$N$43)-ROW($N$9))/1000,0)),"")} -> 5 | V10: {=IFERROR(INDEX($I$9:$I$43,MATCH(LARGE($N$9:$N$43+(ROW($N$9:$N$43)-ROW($N$9))/1000,3),$N$9:$N$43+(ROW($N$9:$N$43)-ROW($N$9))/1000,0)),"")} -> 4 | W10: {=IFERROR(INDEX($K$9:$K$43,MATCH(LARGE($N$9:$N$43+(ROW($N$9:$N$43)-ROW($N$9))/1000,3),$N$9:$N$43+(ROW($N$9:$N$43)-ROW($N$9))/1000,0)),"")} -> 3 | X10: {=IFERROR(INDEX($M$9:$M$43,MATCH(LARGE($N$9:$N$43+(ROW($N$9:$N$43)-ROW($N$9))/1000,3),$N$9:$N$43+(ROW($N$9:$N$43)-ROW($N$9))/1000,0)),"")} -> 2 | Y10: =IF(R10="","",IF(COUNTIF(Portfolio!$C$5:$C$19,R10)>0,"YES","-")) -> YES
A11: 3 | B11: Automatic Data Processing | C11: ADP | D11: =Universe!G7 -> 0.4446 | E11: =IF(D11="","",MAX(1,MIN(5,1+INT(IFERROR(PERCENTRANK(D$9:D$43,D11),0.5)*5)))) -> 5 | F11: =Universe!H7 -> 0.5037 | G11: =IF(F11="","",MAX(1,MIN(5,1+INT(IFERROR(PERCENTRANK(F$9:F$43,F11),0.5)*5)))) -> 1 | H11: =Universe!I7 -> 0.16 | I11: =IF(H11="","",MAX(1,MIN(5,5-INT(IFERROR(PERCENTRANK(H$9:H$43,H11),0.5)*5)))) -> 3 | J11: =Universe!J7 -> 0.5814 | K11: =IF(J11="","",MAX(1,MIN(5,1+INT(IFERROR(PERCENTRANK(J$9:J$43,J11),0.5)*5)))) -> 2 | L11: =Universe!K7 -> 42.89 | M11: =IF(L11="","",MAX(1,MIN(5,1+INT(IFERROR(PERCENTRANK(L$9:L$43,L11),0.5)*5)))) -> 4 | N11: =IF(COUNTA(D11,F11,H11,J11,L11)<5,"",E11*C5+G11*E5+I11*G5+K11*I5+M11*K5) -> 3.1 | P11: 4 | Q11: {=IFERROR(INDEX($B$9:$B$43,MATCH(LARGE($N$9:$N$43+(ROW($N$9:$N$43)-ROW($N$9))/1000,4),$N$9:$N$43+(ROW($N$9:$N$43)-ROW($N$9))/1000,0)),"")} -> Rightmove | R11: {=IFERROR(INDEX($C$9:$C$43,MATCH(LARGE($N$9:$N$43+(ROW($N$9:$N$43)-ROW($N$9))/1000,4),$N$9:$N$43+(ROW($N$9:$N$43)-ROW($N$9))/1000,0)),"")} -> RMV | S11: {=IFERROR(INDEX($N$9:$N$43,MATCH(LARGE($N$9:$N$43+(ROW($N$9:$N$43)-ROW($N$9))/1000,4),$N$9:$N$43+(ROW($N$9:$N$43)-ROW($N$9))/1000,0)),"")} -> 3.8 | T11: {=IFERROR(INDEX($E$9:$E$43,MATCH(LARGE($N$9:$N$43+(ROW($N$9:$N$43)-ROW($N$9))/1000,4),$N$9:$N$43+(ROW($N$9:$N$43)-ROW($N$9))/1000,0)),"")} -> 5 | U11: {=IFERROR(INDEX($G$9:$G$43,MATCH(LARGE($N$9:$N$43+(ROW($N$9:$N$43)-ROW($N$9))/1000,4),$N$9:$N$43+(ROW($N$9:$N$43)-ROW($N$9))/1000,0)),"")} -> 5 | V11: {=IFERROR(INDEX($I$9:$I$43,MATCH(LARGE($N$9:$N$43+(ROW($N$9:$N$43)-ROW($N$9))/1000,4),$N$9:$N$43+(ROW($N$9:$N$43)-ROW($N$9))/1000,0)),"")} -> 4 | W11: {=IFERROR(INDEX($K$9:$K$43,MATCH(LARGE($N$9:$N$43+(ROW($N$9:$N$43)-ROW($N$9))/1000,4),$N$9:$N$43+(ROW($N$9:$N$43)-ROW($N$9))/1000,0)),"")} -> 2 | X11: {=IFERROR(INDEX($M$9:$M$43,MATCH(LARGE($N$9:$N$43+(ROW($N$9:$N$43)-ROW($N$9))/1000,4),$N$9:$N$43+(ROW($N$9:$N$43)-ROW($N$9))/1000,0)),"")} -> 1 | Y11: =IF(R11="","",IF(COUNTIF(Portfolio!$C$5:$C$19,R11)>0,"YES","-")) -> YES
A12: 4 | B12: Veeva Systems | C12: VEEV | D12: =Universe!G8 -> 0.1377 | E12: =IF(D12="","",MAX(1,MIN(5,1+INT(IFERROR(PERCENTRANK(D$9:D$43,D12),0.5)*5)))) -> 2 | F12: =Universe!H8 -> 0.752 | G12: =IF(F12="","",MAX(1,MIN(5,1+INT(IFERROR(PERCENTRANK(F$9:F$43,F12),0.5)*5)))) -> 5 | H12: =Universe!I8 -> -6.58 | I12: =IF(H12="","",MAX(1,MIN(5,5-INT(IFERROR(PERCENTRANK(H$9:H$43,H12),0.5)*5)))) -> 5 | J12: =Universe!J8 -> 1.525 | K12: =IF(J12="","",MAX(1,MIN(5,1+INT(IFERROR(PERCENTRANK(J$9:J$43,J12),0.5)*5)))) -> 5 | L12: =Universe!K8 -> 14.98 | M12: =IF(L12="","",MAX(1,MIN(5,1+INT(IFERROR(PERCENTRANK(L$9:L$43,L12),0.5)*5)))) -> 1 | N12: =IF(COUNTA(D12,F12,H12,J12,L12)<5,"",E12*C5+G12*E5+I12*G5+K12*I5+M12*K5) -> 3.7 | P12: 5 | Q12: {=IFERROR(INDEX($B$9:$B$43,MATCH(LARGE($N$9:$N$43+(ROW($N$9:$N$43)-ROW($N$9))/1000,5),$N$9:$N$43+(ROW($N$9:$N$43)-ROW($N$9))/1000,0)),"")} -> ASML Holding N.V. | R12: {=IFERROR(INDEX($C$9:$C$43,MATCH(LARGE($N$9:$N$43+(ROW($N$9:$N$43)-ROW($N$9))/1000,5),$N$9:$N$43+(ROW($N$9:$N$43)-ROW($N$9))/1000,0)),"")} -> ASML | S12: {=IFERROR(INDEX($N$9:$N$43,MATCH(LARGE($N$9:$N$43+(ROW($N$9:$N$43)-ROW($N$9))/1000,5),$N$9:$N$43+(ROW($N$9:$N$43)-ROW($N$9))/1000,0)),"")} -> 3.7 | T12: {=IFERROR(INDEX($E$9:$E$43,MATCH(LARGE($N$9:$N$43+(ROW($N$9:$N$43)-ROW($N$9))/1000,5),$N$9:$N$43+(ROW($N$9:$N$43)-ROW($N$9))/1000,0)),"")} -> 5 | U12: {=IFERROR(INDEX($G$9:$G$43,MATCH(LARGE($N$9:$N$43+(ROW($N$9:$N$43)-ROW($N$9))/1000,5),$N$9:$N$43+(ROW($N$9:$N$43)-ROW($N$9))/1000,0)),"")} -> 2 | V12: {=IFERROR(INDEX($I$9:$I$43,MATCH(LARGE($N$9:$N$43+(ROW($N$9:$N$43)-ROW($N$9))/1000,5),$N$9:$N$43+(ROW($N$9:$N$43)-ROW($N$9))/1000,0)),"")} -> 4 | W12: {=IFERROR(INDEX($K$9:$K$43,MATCH(LARGE($N$9:$N$43+(ROW($N$9:$N$43)-ROW($N$9))/1000,5),$N$9:$N$43+(ROW($N$9:$N$43)-ROW($N$9))/1000,0)),"")} -> 3 | X12: {=IFERROR(INDEX($M$9:$M$43,MATCH(LARGE($N$9:$N$43+(ROW($N$9:$N$43)-ROW($N$9))/1000,5),$N$9:$N$43+(ROW($N$9:$N$43)-ROW($N$9))/1000,0)),"")} -> 4 | Y12: =IF(R12="","",IF(COUNTIF(Portfolio!$C$5:$C$19,R12)>0,"YES","-")) -> YES
A13: 5 | B13: Constellation Software | C13: CSU | D13: =Universe!G9 -> 0.0707 | E13: =IF(D13="","",MAX(1,MIN(5,1+INT(IFERROR(PERCENTRANK(D$9:D$43,D13),0.5)*5)))) -> 1 | F13: =Universe!H9 -> 0.3958 | G13: =IF(F13="","",MAX(1,MIN(5,1+INT(IFERROR(PERCENTRANK(F$9:F$43,F13),0.5)*5)))) -> 1 | H13: =Universe!I9 -> 0.79 | I13: =IF(H13="","",MAX(1,MIN(5,5-INT(IFERROR(PERCENTRANK(H$9:H$43,H13),0.5)*5)))) -> 3 | J13: =Universe!J9 -> 4.764 | K13: =IF(J13="","",MAX(1,MIN(5,1+INT(IFERROR(PERCENTRANK(J$9:J$43,J13),0.5)*5)))) -> 5 | L13: =Universe!K9 -> 390 | M13: =IF(L13="","",MAX(1,MIN(5,1+INT(IFERROR(PERCENTRANK(L$9:L$43,L13),0.5)*5)))) -> 5 | N13: =IF(COUNTA(D13,F13,H13,J13,L13)<5,"",E13*C5+G13*E5+I13*G5+K13*I5+M13*K5) -> 2.6 | P13: 6 | Q13: {=IFERROR(INDEX($B$9:$B$43,MATCH(LARGE($N$9:$N$43+(ROW($N$9:$N$43)-ROW($N$9))/1000,6),$N$9:$N$43+(ROW($N$9:$N$43)-ROW($N$9))/1000,0)),"")} -> Veeva Systems | R13: {=IFERROR(INDEX($C$9:$C$43,MATCH(LARGE($N$9:$N$43+(ROW($N$9:$N$43)-ROW($N$9))/1000,6),$N$9:$N$43+(ROW($N$9:$N$43)-ROW($N$9))/1000,0)),"")} -> VEEV | S13: {=IFERROR(INDEX($N$9:$N$43,MATCH(LARGE($N$9:$N$43+(ROW($N$9:$N$43)-ROW($N$9))/1000,6),$N$9:$N$43+(ROW($N$9:$N$43)-ROW($N$9))/1000,0)),"")} -> 3.7 | T13: {=IFERROR(INDEX($E$9:$E$43,MATCH(LARGE($N$9:$N$43+(ROW($N$9:$N$43)-ROW($N$9))/1000,6),$N$9:$N$43+(ROW($N$9:$N$43)-ROW($N$9))/1000,0)),"")} -> 2 | U13: {=IFERROR(INDEX($G$9:$G$43,MATCH(LARGE($N$9:$N$43+(ROW($N$9:$N$43)-ROW($N$9))/1000,6),$N$9:$N$43+(ROW($N$9:$N$43)-ROW($N$9))/1000,0)),"")} -> 5 | V13: {=IFERROR(INDEX($I$9:$I$43,MATCH(LARGE($N$9:$N$43+(ROW($N$9:$N$43)-ROW($N$9))/1000,6),$N$9:$N$43+(ROW($N$9:$N$43)-ROW($N$9))/1000,0)),"")} -> 5 | W13: {=IFERROR(INDEX($K$9:$K$43,MATCH(LARGE($N$9:$N$43+(ROW($N$9:$N$43)-ROW($N$9))/1000,6),$N$9:$N$43+(ROW($N$9:$N$43)-ROW($N$9))/1000,0)),"")} -> 5 | X13: {=IFERROR(INDEX($M$9:$M$43,MATCH(LARGE($N$9:$N$43+(ROW($N$9:$N$43)-ROW($N$9))/1000,6),$N$9:$N$43+(ROW($N$9:$N$43)-ROW($N$9))/1000,0)),"")} -> 1 | Y13: =IF(R13="","",IF(COUNTIF(Portfolio!$C$5:$C$19,R13)>0,"YES","-")) -> YES
A14: 6 | B14: Wolters Kluwer | C14: WKL | D14: =Universe!G10 -> 0.2565 | E14: =IF(D14="","",MAX(1,MIN(5,1+INT(IFERROR(PERCENTRANK(D$9:D$43,D14),0.5)*5)))) -> 3 | F14: =Universe!H10 -> 0.6591 | G14: =IF(F14="","",MAX(1,MIN(5,1+INT(IFERROR(PERCENTRANK(F$9:F$43,F14),0.5)*5)))) -> 3 | H14: =Universe!I10 -> 2.01 | I14: =IF(H14="","",MAX(1,MIN(5,5-INT(IFERROR(PERCENTRANK(H$9:H$43,H14),0.5)*5)))) -> 1 | J14: =Universe!J10 -> 0.8287 | K14: =IF(J14="","",MAX(1,MIN(5,1+INT(IFERROR(PERCENTRANK(J$9:J$43,J14),0.5)*5)))) -> 3 | L14: =Universe!K10 -> 26.31 | M14: =IF(L14="","",MAX(1,MIN(5,1+INT(IFERROR(PERCENTRANK(L$9:L$43,L14),0.5)*5)))) -> 2 | N14: =IF(COUNTA(D14,F14,H14,J14,L14)<5,"",E14*C5+G14*E5+I14*G5+K14*I5+M14*K5) -> 2.5 | P14: 7 | Q14: {=IFERROR(INDEX($B$9:$B$43,MATCH(LARGE($N$9:$N$43+(ROW($N$9:$N$43)-ROW($N$9))/1000,7),$N$9:$N$43+(ROW($N$9:$N$43)-ROW($N$9))/1000,0)),"")} -> Mettler-Toledo International | R14: {=IFERROR(INDEX($C$9:$C$43,MATCH(LARGE($N$9:$N$43+(ROW($N$9:$N$43)-ROW($N$9))/1000,7),$N$9:$N$43+(ROW($N$9:$N$43)-ROW($N$9))/1000,0)),"")} -> MTD | S14: {=IFERROR(INDEX($N$9:$N$43,MATCH(LARGE($N$9:$N$43+(ROW($N$9:$N$43)-ROW($N$9))/1000,7),$N$9:$N$43+(ROW($N$9:$N$43)-ROW($N$9))/1000,0)),"")} -> 3.6 | T14: {=IFERROR(INDEX($E$9:$E$43,MATCH(LARGE($N$9:$N$43+(ROW($N$9:$N$43)-ROW($N$9))/1000,7),$N$9:$N$43+(ROW($N$9:$N$43)-ROW($N$9))/1000,0)),"")} -> 5 | U14: {=IFERROR(INDEX($G$9:$G$43,MATCH(LARGE($N$9:$N$43+(ROW($N$9:$N$43)-ROW($N$9))/1000,7),$N$9:$N$43+(ROW($N$9:$N$43)-ROW($N$9))/1000,0)),"")} -> 2 | V14: {=IFERROR(INDEX($I$9:$I$43,MATCH(LARGE($N$9:$N$43+(ROW($N$9:$N$43)-ROW($N$9))/1000,7),$N$9:$N$43+(ROW($N$9:$N$43)-ROW($N$9))/1000,0)),"")} -> 2 | W14: {=IFERROR(INDEX($K$9:$K$43,MATCH(LARGE($N$9:$N$43+(ROW($N$9:$N$43)-ROW($N$9))/1000,7),$N$9:$N$43+(ROW($N$9:$N$43)-ROW($N$9))/1000,0)),"")} -> 4 | X14: {=IFERROR(INDEX($M$9:$M$43,MATCH(LARGE($N$9:$N$43+(ROW($N$9:$N$43)-ROW($N$9))/1000,7),$N$9:$N$43+(ROW($N$9:$N$43)-ROW($N$9))/1000,0)),"")} -> 5 | Y14: =IF(R14="","",IF(COUNTIF(Portfolio!$C$5:$C$19,R14)>0,"YES","-")) -> YES
A15: 7 | B15: Rightmove | C15: RMV | D15: =Universe!G11 -> 2.547 | E15: =IF(D15="","",MAX(1,MIN(5,1+INT(IFERROR(PERCENTRANK(D$9:D$43,D15),0.5)*5)))) -> 5 | F15: =Universe!H11 -> 0.984 | G15: =IF(F15="","",MAX(1,MIN(5,1+INT(IFERROR(PERCENTRANK(F$9:F$43,F15),0.5)*5)))) -> 5 | H15: =Universe!I11 -> -0.12 | I15: =IF(H15="","",MAX(1,MIN(5,5-INT(IFERROR(PERCENTRANK(H$9:H$43,H15),0.5)*5)))) -> 4 | J15: =Universe!J11 -> 0.7337 | K15: =IF(J15="","",MAX(1,MIN(5,1+INT(IFERROR(PERCENTRANK(J$9:J$43,J15),0.5)*5)))) -> 2 | L15: =Universe!K11 -> 0.6 | M15: =IF(L15="","",MAX(1,MIN(5,1+INT(IFERROR(PERCENTRANK(L$9:L$43,L15),0.5)*5)))) -> 1 | N15: =IF(COUNTA(D15,F15,H15,J15,L15)<5,"",E15*C5+G15*E5+I15*G5+K15*I5+M15*K5) -> 3.8 | P15: 8 | Q15: {=IFERROR(INDEX($B$9:$B$43,MATCH(LARGE($N$9:$N$43+(ROW($N$9:$N$43)-ROW($N$9))/1000,8),$N$9:$N$43+(ROW($N$9:$N$43)-ROW($N$9))/1000,0)),"")} -> Align Technology | R15: {=IFERROR(INDEX($C$9:$C$43,MATCH(LARGE($N$9:$N$43+(ROW($N$9:$N$43)-ROW($N$9))/1000,8),$N$9:$N$43+(ROW($N$9:$N$43)-ROW($N$9))/1000,0)),"")} -> ALGN | S15: {=IFERROR(INDEX($N$9:$N$43,MATCH(LARGE($N$9:$N$43+(ROW($N$9:$N$43)-ROW($N$9))/1000,8),$N$9:$N$43+(ROW($N$9:$N$43)-ROW($N$9))/1000,0)),"")} -> 3.6 | T15: {=IFERROR(INDEX($E$9:$E$43,MATCH(LARGE($N$9:$N$43+(ROW($N$9:$N$43)-ROW($N$9))/1000,8),$N$9:$N$43+(ROW($N$9:$N$43)-ROW($N$9))/1000,0)),"")} -> 2 | U15: {=IFERROR(INDEX($G$9:$G$43,MATCH(LARGE($N$9:$N$43+(ROW($N$9:$N$43)-ROW($N$9))/1000,8),$N$9:$N$43+(ROW($N$9:$N$43)-ROW($N$9))/1000,0)),"")} -> 4 | V15: {=IFERROR(INDEX($I$9:$I$43,MATCH(LARGE($N$9:$N$43+(ROW($N$9:$N$43)-ROW($N$9))/1000,8),$N$9:$N$43+(ROW($N$9:$N$43)-ROW($N$9))/1000,0)),"")} -> 5 | W15: {=IFERROR(INDEX($K$9:$K$43,MATCH(LARGE($N$9:$N$43+(ROW($N$9:$N$43)-ROW($N$9))/1000,8),$N$9:$N$43+(ROW($N$9:$N$43)-ROW($N$9))/1000,0)),"")} -> 4 | X15: {=IFERROR(INDEX($M$9:$M$43,MATCH(LARGE($N$9:$N$43+(ROW($N$9:$N$43)-ROW($N$9))/1000,8),$N$9:$N$43+(ROW($N$9:$N$43)-ROW($N$9))/1000,0)),"")} -> 4 | Y15: =IF(R15="","",IF(COUNTIF(Portfolio!$C$5:$C$19,R15)>0,"YES","-")) -> YES
A16: 8 | B16: Visa Inc. | C16: V | D16: =Universe!G12 -> 0.3339 | E16: =IF(D16="","",MAX(1,MIN(5,1+INT(IFERROR(PERCENTRANK(D$9:D$43,D16),0.5)*5)))) -> 4 | F16: =Universe!H12 -> 0.7731 | G16: =IF(F16="","",MAX(1,MIN(5,1+INT(IFERROR(PERCENTRANK(F$9:F$43,F16),0.5)*5)))) -> 5 | H16: =Universe!I12 -> 0.07 | I16: =IF(H16="","",MAX(1,MIN(5,5-INT(IFERROR(PERCENTRANK(H$9:H$43,H16),0.5)*5)))) -> 4 | J16: =Universe!J12 -> 0.8534 | K16: =IF(J16="","",MAX(1,MIN(5,1+INT(IFERROR(PERCENTRANK(J$9:J$43,J16),0.5)*5)))) -> 3 | L16: =Universe!K12 -> 15.69 | M16: =IF(L16="","",MAX(1,MIN(5,1+INT(IFERROR(PERCENTRANK(L$9:L$43,L16),0.5)*5)))) -> 2 | N16: =IF(COUNTA(D16,F16,H16,J16,L16)<5,"",E16*C5+G16*E5+I16*G5+K16*I5+M16*K5) -> 3.8 | P16: 9 | Q16: {=IFERROR(INDEX($B$9:$B$43,MATCH(LARGE($N$9:$N$43+(ROW($N$9:$N$43)-ROW($N$9))/1000,9),$N$9:$N$43+(ROW($N$9:$N$43)-ROW($N$9))/1000,0)),"")} -> Hermès International | R16: {=IFERROR(INDEX($C$9:$C$43,MATCH(LARGE($N$9:$N$43+(ROW($N$9:$N$43)-ROW($N$9))/1000,9),$N$9:$N$43+(ROW($N$9:$N$43)-ROW($N$9))/1000,0)),"")} -> RMS | S16: {=IFERROR(INDEX($N$9:$N$43,MATCH(LARGE($N$9:$N$43+(ROW($N$9:$N$43)-ROW($N$9))/1000,9),$N$9:$N$43+(ROW($N$9:$N$43)-ROW($N$9))/1000,0)),"")} -> 3.4 | T16: {=IFERROR(INDEX($E$9:$E$43,MATCH(LARGE($N$9:$N$43+(ROW($N$9:$N$43)-ROW($N$9))/1000,9),$N$9:$N$43+(ROW($N$9:$N$43)-ROW($N$9))/1000,0)),"")} -> 3 | U16: {=IFERROR(INDEX($G$9:$G$43,MATCH(LARGE($N$9:$N$43+(ROW($N$9:$N$43)-ROW($N$9))/1000,9),$N$9:$N$43+(ROW($N$9:$N$43)-ROW($N$9))/1000,0)),"")} -> 4 | V16: {=IFERROR(INDEX($I$9:$I$43,MATCH(LARGE($N$9:$N$43+(ROW($N$9:$N$43)-ROW($N$9))/1000,9),$N$9:$N$43+(ROW($N$9:$N$43)-ROW($N$9))/1000,0)),"")} -> 5 | W16: {=IFERROR(INDEX($K$9:$K$43,MATCH(LARGE($N$9:$N$43+(ROW($N$9:$N$43)-ROW($N$9))/1000,9),$N$9:$N$43+(ROW($N$9:$N$43)-ROW($N$9))/1000,0)),"")} -> 1 | X16: {=IFERROR(INDEX($M$9:$M$43,MATCH(LARGE($N$9:$N$43+(ROW($N$9:$N$43)-ROW($N$9))/1000,9),$N$9:$N$43+(ROW($N$9:$N$43)-ROW($N$9))/1000,0)),"")} -> 5 | Y16: =IF(R16="","",IF(COUNTIF(Portfolio!$C$5:$C$19,R16)>0,"YES","-")) -> YES
A17: 9 | B17: Mastercard Incorporated | C17: MA | D17: =Universe!G13 -> 0.5841 | E17: =IF(D17="","",MAX(1,MIN(5,1+INT(IFERROR(PERCENTRANK(D$9:D$43,D17),0.5)*5)))) -> 5 | F17: =Universe!H13 -> 0.9603 | G17: =IF(F17="","",MAX(1,MIN(5,1+INT(IFERROR(PERCENTRANK(F$9:F$43,F17),0.5)*5)))) -> 5 | H17: =Universe!I13 -> 0.36 | I17: =IF(H17="","",MAX(1,MIN(5,5-INT(IFERROR(PERCENTRANK(H$9:H$43,H17),0.5)*5)))) -> 3 | J17: =Universe!J13 -> 0.9458 | K17: =IF(J17="","",MAX(1,MIN(5,1+INT(IFERROR(PERCENTRANK(J$9:J$43,J17),0.5)*5)))) -> 4 | L17: =Universe!K13 -> 27.02 | M17: =IF(L17="","",MAX(1,MIN(5,1+INT(IFERROR(PERCENTRANK(L$9:L$43,L17),0.5)*5)))) -> 3 | N17: =IF(COUNTA(D17,F17,H17,J17,L17)<5,"",E17*C5+G17*E5+I17*G5+K17*I5+M17*K5) -> 4.2 | P17: 10 | Q17: {=IFERROR(INDEX($B$9:$B$43,MATCH(LARGE($N$9:$N$43+(ROW($N$9:$N$43)-ROW($N$9))/1000,10),$N$9:$N$43+(ROW($N$9:$N$43)-ROW($N$9))/1000,0)),"")} -> Novo Nordisk A/S | R17: {=IFERROR(INDEX($C$9:$C$43,MATCH(LARGE($N$9:$N$43+(ROW($N$9:$N$43)-ROW($N$9))/1000,10),$N$9:$N$43+(ROW($N$9:$N$43)-ROW($N$9))/1000,0)),"")} -> NOVO B | S17: {=IFERROR(INDEX($N$9:$N$43,MATCH(LARGE($N$9:$N$43+(ROW($N$9:$N$43)-ROW($N$9))/1000,10),$N$9:$N$43+(ROW($N$9:$N$43)-ROW($N$9))/1000,0)),"")} -> 3.4 | T17: {=IFERROR(INDEX($E$9:$E$43,MATCH(LARGE($N$9:$N$43+(ROW($N$9:$N$43)-ROW($N$9))/1000,10),$N$9:$N$43+(ROW($N$9:$N$43)-ROW($N$9))/1000,0)),"")} -> 5 | U17: {=IFERROR(INDEX($G$9:$G$43,MATCH(LARGE($N$9:$N$43+(ROW($N$9:$N$43)-ROW($N$9))/1000,10),$N$9:$N$43+(ROW($N$9:$N$43)-ROW($N$9))/1000,0)),"")} -> 5 | V17: {=IFERROR(INDEX($I$9:$I$43,MATCH(LARGE($N$9:$N$43+(ROW($N$9:$N$43)-ROW($N$9))/1000,10),$N$9:$N$43+(ROW($N$9:$N$43)-ROW($N$9))/1000,0)),"")} -> 3 | W17: {=IFERROR(INDEX($K$9:$K$43,MATCH(LARGE($N$9:$N$43+(ROW($N$9:$N$43)-ROW($N$9))/1000,10),$N$9:$N$43+(ROW($N$9:$N$43)-ROW($N$9))/1000,0)),"")} -> 1 | X17: {=IFERROR(INDEX($M$9:$M$43,MATCH(LARGE($N$9:$N$43+(ROW($N$9:$N$43)-ROW($N$9))/1000,10),$N$9:$N$43+(ROW($N$9:$N$43)-ROW($N$9))/1000,0)),"")} -> 1 | Y17: =IF(R17="","",IF(COUNTIF(Portfolio!$C$5:$C$19,R17)>0,"YES","-")) -> YES
A18: 10 | B18: S&P Global Inc. | C18: SPGI | D18: =Universe!G14 -> 0.1004 | E18: =IF(D18="","",MAX(1,MIN(5,1+INT(IFERROR(PERCENTRANK(D$9:D$43,D18),0.5)*5)))) -> 2 | F18: =Universe!H14 -> 0.6256 | G18: =IF(F18="","",MAX(1,MIN(5,1+INT(IFERROR(PERCENTRANK(F$9:F$43,F18),0.5)*5)))) -> 3 | H18: =Universe!I14 -> 1.48 | I18: =IF(H18="","",MAX(1,MIN(5,5-INT(IFERROR(PERCENTRANK(H$9:H$43,H18),0.5)*5)))) -> 2 | J18: =Universe!J14 -> 0.9586 | K18: =IF(J18="","",MAX(1,MIN(5,1+INT(IFERROR(PERCENTRANK(J$9:J$43,J18),0.5)*5)))) -> 4 | L18: =Universe!K14 -> 40.89 | M18: =IF(L18="","",MAX(1,MIN(5,1+INT(IFERROR(PERCENTRANK(L$9:L$43,L18),0.5)*5)))) -> 4 | N18: =IF(COUNTA(D18,F18,H18,J18,L18)<5,"",E18*C5+G18*E5+I18*G5+K18*I5+M18*K5) -> 2.8 | P18: 11 | Q18: {=IFERROR(INDEX($B$9:$B$43,MATCH(LARGE($N$9:$N$43+(ROW($N$9:$N$43)-ROW($N$9))/1000,11),$N$9:$N$43+(ROW($N$9:$N$43)-ROW($N$9))/1000,0)),"")} -> Rational AG | R18: {=IFERROR(INDEX($C$9:$C$43,MATCH(LARGE($N$9:$N$43+(ROW($N$9:$N$43)-ROW($N$9))/1000,11),$N$9:$N$43+(ROW($N$9:$N$43)-ROW($N$9))/1000,0)),"")} -> RAA | S18: {=IFERROR(INDEX($N$9:$N$43,MATCH(LARGE($N$9:$N$43+(ROW($N$9:$N$43)-ROW($N$9))/1000,11),$N$9:$N$43+(ROW($N$9:$N$43)-ROW($N$9))/1000,0)),"")} -> 3.3 | T18: {=IFERROR(INDEX($E$9:$E$43,MATCH(LARGE($N$9:$N$43+(ROW($N$9:$N$43)-ROW($N$9))/1000,11),$N$9:$N$43+(ROW($N$9:$N$43)-ROW($N$9))/1000,0)),"")} -> 4 | U18: {=IFERROR(INDEX($G$9:$G$43,MATCH(LARGE($N$9:$N$43+(ROW($N$9:$N$43)-ROW($N$9))/1000,11),$N$9:$N$43+(ROW($N$9:$N$43)-ROW($N$9))/1000,0)),"")} -> 2 | V18: {=IFERROR(INDEX($I$9:$I$43,MATCH(LARGE($N$9:$N$43+(ROW($N$9:$N$43)-ROW($N$9))/1000,11),$N$9:$N$43+(ROW($N$9:$N$43)-ROW($N$9))/1000,0)),"")} -> 5 | W18: {=IFERROR(INDEX($K$9:$K$43,MATCH(LARGE($N$9:$N$43+(ROW($N$9:$N$43)-ROW($N$9))/1000,11),$N$9:$N$43+(ROW($N$9:$N$43)-ROW($N$9))/1000,0)),"")} -> 1 | X18: {=IFERROR(INDEX($M$9:$M$43,MATCH(LARGE($N$9:$N$43+(ROW($N$9:$N$43)-ROW($N$9))/1000,11),$N$9:$N$43+(ROW($N$9:$N$43)-ROW($N$9))/1000,0)),"")} -> 5 | Y18: =IF(R18="","",IF(COUNTIF(Portfolio!$C$5:$C$19,R18)>0,"YES","-")) -> YES
A19: 11 | B19: Moody's Corporation | C19: MCO | D19: =Universe!G15 -> 0.2254 | E19: =IF(D19="","",MAX(1,MIN(5,1+INT(IFERROR(PERCENTRANK(D$9:D$43,D19),0.5)*5)))) -> 3 | F19: =Universe!H15 -> 0.6815 | G19: =IF(F19="","",MAX(1,MIN(5,1+INT(IFERROR(PERCENTRANK(F$9:F$43,F19),0.5)*5)))) -> 4 | H19: =Universe!I15 -> 1.16 | I19: =IF(H19="","",MAX(1,MIN(5,5-INT(IFERROR(PERCENTRANK(H$9:H$43,H19),0.5)*5)))) -> 2 | J19: =Universe!J15 -> 0.7621 | K19: =IF(J19="","",MAX(1,MIN(5,1+INT(IFERROR(PERCENTRANK(J$9:J$43,J19),0.5)*5)))) -> 2 | L19: =Universe!K15 -> 35.31 | M19: =IF(L19="","",MAX(1,MIN(5,1+INT(IFERROR(PERCENTRANK(L$9:L$43,L19),0.5)*5)))) -> 3 | N19: =IF(COUNTA(D19,F19,H19,J19,L19)<5,"",E19*C5+G19*E5+I19*G5+K19*I5+M19*K5) -> 2.8 | P19: 12 | Q19: {=IFERROR(INDEX($B$9:$B$43,MATCH(LARGE($N$9:$N$43+(ROW($N$9:$N$43)-ROW($N$9))/1000,12),$N$9:$N$43+(ROW($N$9:$N$43)-ROW($N$9))/1000,0)),"")} -> MSCI Inc. | R19: {=IFERROR(INDEX($C$9:$C$43,MATCH(LARGE($N$9:$N$43+(ROW($N$9:$N$43)-ROW($N$9))/1000,12),$N$9:$N$43+(ROW($N$9:$N$43)-ROW($N$9))/1000,0)),"")} -> MSCI | S19: {=IFERROR(INDEX($N$9:$N$43,MATCH(LARGE($N$9:$N$43+(ROW($N$9:$N$43)-ROW($N$9))/1000,12),$N$9:$N$43+(ROW($N$9:$N$43)-ROW($N$9))/1000,0)),"")} -> 3.3 | T19: {=IFERROR(INDEX($E$9:$E$43,MATCH(LARGE($N$9:$N$43+(ROW($N$9:$N$43)-ROW($N$9))/1000,12),$N$9:$N$43+(ROW($N$9:$N$43)-ROW($N$9))/1000,0)),"")} -> 4 | U19: {=IFERROR(INDEX($G$9:$G$43,MATCH(LARGE($N$9:$N$43+(ROW($N$9:$N$43)-ROW($N$9))/1000,12),$N$9:$N$43+(ROW($N$9:$N$43)-ROW($N$9))/1000,0)),"")} -> 5 | V19: {=IFERROR(INDEX($I$9:$I$43,MATCH(LARGE($N$9:$N$43+(ROW($N$9:$N$43)-ROW($N$9))/1000,12),$N$9:$N$43+(ROW($N$9:$N$43)-ROW($N$9))/1000,0)),"")} -> 1 | W19: {=IFERROR(INDEX($K$9:$K$43,MATCH(LARGE($N$9:$N$43+(ROW($N$9:$N$43)-ROW($N$9))/1000,12),$N$9:$N$43+(ROW($N$9:$N$43)-ROW($N$9))/1000,0)),"")} -> 3 | X19: {=IFERROR(INDEX($M$9:$M$43,MATCH(LARGE($N$9:$N$43+(ROW($N$9:$N$43)-ROW($N$9))/1000,12),$N$9:$N$43+(ROW($N$9:$N$43)-ROW($N$9))/1000,0)),"")} -> 3 | Y19: =IF(R19="","",IF(COUNTIF(Portfolio!$C$5:$C$19,R19)>0,"YES","-")) -> YES
A20: 12 | B20: MSCI Inc. | C20: MSCI | D20: =Universe!G16 -> 0.3273 | E20: =IF(D20="","",MAX(1,MIN(5,1+INT(IFERROR(PERCENTRANK(D$9:D$43,D20),0.5)*5)))) -> 4 | F20: =Universe!H16 -> 0.7629 | G20: =IF(F20="","",MAX(1,MIN(5,1+INT(IFERROR(PERCENTRANK(F$9:F$43,F20),0.5)*5)))) -> 5 | H20: =Universe!I16 -> 2.94 | I20: =IF(H20="","",MAX(1,MIN(5,5-INT(IFERROR(PERCENTRANK(H$9:H$43,H20),0.5)*5)))) -> 1 | J20: =Universe!J16 -> 0.8089 | K20: =IF(J20="","",MAX(1,MIN(5,1+INT(IFERROR(PERCENTRANK(J$9:J$43,J20),0.5)*5)))) -> 3 | L20: =Universe!K16 -> 32.18 | M20: =IF(L20="","",MAX(1,MIN(5,1+INT(IFERROR(PERCENTRANK(L$9:L$43,L20),0.5)*5)))) -> 3 | N20: =IF(COUNTA(D20,F20,H20,J20,L20)<5,"",E20*C5+G20*E5+I20*G5+K20*I5+M20*K5) -> 3.3 | P20: 13 | Q20: {=IFERROR(INDEX($B$9:$B$43,MATCH(LARGE($N$9:$N$43+(ROW($N$9:$N$43)-ROW($N$9))/1000,13),$N$9:$N$43+(ROW($N$9:$N$43)-ROW($N$9))/1000,0)),"")} -> Keyence Corporation | R20: {=IFERROR(INDEX($C$9:$C$43,MATCH(LARGE($N$9:$N$43+(ROW($N$9:$N$43)-ROW($N$9))/1000,13),$N$9:$N$43+(ROW($N$9:$N$43)-ROW($N$9))/1000,0)),"")} -> 6861 | S20: {=IFERROR(INDEX($N$9:$N$43,MATCH(LARGE($N$9:$N$43+(ROW($N$9:$N$43)-ROW($N$9))/1000,13),$N$9:$N$43+(ROW($N$9:$N$43)-ROW($N$9))/1000,0)),"")} -> 3.2 | T20: {=IFERROR(INDEX($E$9:$E$43,MATCH(LARGE($N$9:$N$43+(ROW($N$9:$N$43)-ROW($N$9))/1000,13),$N$9:$N$43+(ROW($N$9:$N$43)-ROW($N$9))/1000,0)),"")} -> 2 | U20: {=IFERROR(INDEX($G$9:$G$43,MATCH(LARGE($N$9:$N$43+(ROW($N$9:$N$43)-ROW($N$9))/1000,13),$N$9:$N$43+(ROW($N$9:$N$43)-ROW($N$9))/1000,0)),"")} -> 5 | V20: {=IFERROR(INDEX($I$9:$I$43,MATCH(LARGE($N$9:$N$43+(ROW($N$9:$N$43)-ROW($N$9))/1000,13),$N$9:$N$43+(ROW($N$9:$N$43)-ROW($N$9))/1000,0)),"")} -> 5 | W20: {=IFERROR(INDEX($K$9:$K$43,MATCH(LARGE($N$9:$N$43+(ROW($N$9:$N$43)-ROW($N$9))/1000,13),$N$9:$N$43+(ROW($N$9:$N$43)-ROW($N$9))/1000,0)),"")} -> 2 | X20: {=IFERROR(INDEX($M$9:$M$43,MATCH(LARGE($N$9:$N$43+(ROW($N$9:$N$43)-ROW($N$9))/1000,13),$N$9:$N$43+(ROW($N$9:$N$43)-ROW($N$9))/1000,0)),"")} -> 2 | Y20: =IF(R20="","",IF(COUNTIF(Portfolio!$C$5:$C$19,R20)>0,"YES","-")) -> YES
A21: 13 | B21: Intercontinental Exchange | C21: ICE | D21: =Universe!G17 -> 0.0709 | E21: =IF(D21="","",MAX(1,MIN(5,1+INT(IFERROR(PERCENTRANK(D$9:D$43,D21),0.5)*5)))) -> 1 | F21: =Universe!H17 -> 0.6846 | G21: =IF(F21="","",MAX(1,MIN(5,1+INT(IFERROR(PERCENTRANK(F$9:F$43,F21),0.5)*5)))) -> 4 | H21: =Universe!I17 -> 2.64 | I21: =IF(H21="","",MAX(1,MIN(5,5-INT(IFERROR(PERCENTRANK(H$9:H$43,H21),0.5)*5)))) -> 1 | J21: =Universe!J17 -> 0.9605 | K21: =IF(J21="","",MAX(1,MIN(5,1+INT(IFERROR(PERCENTRANK(J$9:J$43,J21),0.5)*5)))) -> 4 | L21: =Universe!K17 -> 18.37 | M21: =IF(L21="","",MAX(1,MIN(5,1+INT(IFERROR(PERCENTRANK(L$9:L$43,L21),0.5)*5)))) -> 2 | N21: =IF(COUNTA(D21,F21,H21,J21,L21)<5,"",E21*C5+G21*E5+I21*G5+K21*I5+M21*K5) -> 2.3 | P21: 14 | Q21: {=IFERROR(INDEX($B$9:$B$43,MATCH(LARGE($N$9:$N$43+(ROW($N$9:$N$43)-ROW($N$9))/1000,14),$N$9:$N$43+(ROW($N$9:$N$43)-ROW($N$9))/1000,0)),"")} -> Ferrari N.V. | R21: {=IFERROR(INDEX($C$9:$C$43,MATCH(LARGE($N$9:$N$43+(ROW($N$9:$N$43)-ROW($N$9))/1000,14),$N$9:$N$43+(ROW($N$9:$N$43)-ROW($N$9))/1000,0)),"")} -> RACE | S21: {=IFERROR(INDEX($N$9:$N$43,MATCH(LARGE($N$9:$N$43+(ROW($N$9:$N$43)-ROW($N$9))/1000,14),$N$9:$N$43+(ROW($N$9:$N$43)-ROW($N$9))/1000,0)),"")} -> 3.1 | T21: {=IFERROR(INDEX($E$9:$E$43,MATCH(LARGE($N$9:$N$43+(ROW($N$9:$N$43)-ROW($N$9))/1000,14),$N$9:$N$43+(ROW($N$9:$N$43)-ROW($N$9))/1000,0)),"")} -> 4 | U21: {=IFERROR(INDEX($G$9:$G$43,MATCH(LARGE($N$9:$N$43+(ROW($N$9:$N$43)-ROW($N$9))/1000,14),$N$9:$N$43+(ROW($N$9:$N$43)-ROW($N$9))/1000,0)),"")} -> 2 | V21: {=IFERROR(INDEX($I$9:$I$43,MATCH(LARGE($N$9:$N$43+(ROW($N$9:$N$43)-ROW($N$9))/1000,14),$N$9:$N$43+(ROW($N$9:$N$43)-ROW($N$9))/1000,0)),"")} -> 3 | W21: {=IFERROR(INDEX($K$9:$K$43,MATCH(LARGE($N$9:$N$43+(ROW($N$9:$N$43)-ROW($N$9))/1000,14),$N$9:$N$43+(ROW($N$9:$N$43)-ROW($N$9))/1000,0)),"")} -> 3 | X21: {=IFERROR(INDEX($M$9:$M$43,MATCH(LARGE($N$9:$N$43+(ROW($N$9:$N$43)-ROW($N$9))/1000,14),$N$9:$N$43+(ROW($N$9:$N$43)-ROW($N$9))/1000,0)),"")} -> 3 | Y21: =IF(R21="","",IF(COUNTIF(Portfolio!$C$5:$C$19,R21)>0,"YES","-")) -> YES
A22: 14 | B22: London Stock Exchange Group | C22: LSEG | D22: =Universe!G18 -> 0.0419 | E22: =IF(D22="","",MAX(1,MIN(5,1+INT(IFERROR(PERCENTRANK(D$9:D$43,D22),0.5)*5)))) -> 1 | F22: =Universe!H18 -> 0.6426 | G22: =IF(F22="","",MAX(1,MIN(5,1+INT(IFERROR(PERCENTRANK(F$9:F$43,F22),0.5)*5)))) -> 3 | H22: =Universe!I18 -> 1.73 | I22: =IF(H22="","",MAX(1,MIN(5,5-INT(IFERROR(PERCENTRANK(H$9:H$43,H22),0.5)*5)))) -> 2 | J22: =Universe!J18 -> 2.226 | K22: =IF(J22="","",MAX(1,MIN(5,1+INT(IFERROR(PERCENTRANK(J$9:J$43,J22),0.5)*5)))) -> 5 | L22: =Universe!K18 -> 20.3 | M22: =IF(L22="","",MAX(1,MIN(5,1+INT(IFERROR(PERCENTRANK(L$9:L$43,L22),0.5)*5)))) -> 2 | N22: =IF(COUNTA(D22,F22,H22,J22,L22)<5,"",E22*C5+G22*E5+I22*G5+K22*I5+M22*K5) -> 2.5 | P22: 15 | Q22: {=IFERROR(INDEX($B$9:$B$43,MATCH(LARGE($N$9:$N$43+(ROW($N$9:$N$43)-ROW($N$9))/1000,15),$N$9:$N$43+(ROW($N$9:$N$43)-ROW($N$9))/1000,0)),"")} -> Automatic Data Processing | R22: {=IFERROR(INDEX($C$9:$C$43,MATCH(LARGE($N$9:$N$43+(ROW($N$9:$N$43)-ROW($N$9))/1000,15),$N$9:$N$43+(ROW($N$9:$N$43)-ROW($N$9))/1000,0)),"")} -> ADP | S22: {=IFERROR(INDEX($N$9:$N$43,MATCH(LARGE($N$9:$N$43+(ROW($N$9:$N$43)-ROW($N$9))/1000,15),$N$9:$N$43+(ROW($N$9:$N$43)-ROW($N$9))/1000,0)),"")} -> 3.1 | T22: {=IFERROR(INDEX($E$9:$E$43,MATCH(LARGE($N$9:$N$43+(ROW($N$9:$N$43)-ROW($N$9))/1000,15),$N$9:$N$43+(ROW($N$9:$N$43)-ROW($N$9))/1000,0)),"")} -> 5 | U22: {=IFERROR(INDEX($G$9:$G$43,MATCH(LARGE($N$9:$N$43+(ROW($N$9:$N$43)-ROW($N$9))/1000,15),$N$9:$N$43+(ROW($N$9:$N$43)-ROW($N$9))/1000,0)),"")} -> 1 | V22: {=IFERROR(INDEX($I$9:$I$43,MATCH(LARGE($N$9:$N$43+(ROW($N$9:$N$43)-ROW($N$9))/1000,15),$N$9:$N$43+(ROW($N$9:$N$43)-ROW($N$9))/1000,0)),"")} -> 3 | W22: {=IFERROR(INDEX($K$9:$K$43,MATCH(LARGE($N$9:$N$43+(ROW($N$9:$N$43)-ROW($N$9))/1000,15),$N$9:$N$43+(ROW($N$9:$N$43)-ROW($N$9))/1000,0)),"")} -> 2 | X22: {=IFERROR(INDEX($M$9:$M$43,MATCH(LARGE($N$9:$N$43+(ROW($N$9:$N$43)-ROW($N$9))/1000,15),$N$9:$N$43+(ROW($N$9:$N$43)-ROW($N$9))/1000,0)),"")} -> 4 | Y22: =IF(R22="","",IF(COUNTIF(Portfolio!$C$5:$C$19,R22)>0,"YES","-")) -> YES
A23: 15 | B23: Novo Nordisk A/S | C23: NOVO B | D23: =Universe!G19 -> 0.3751 | E23: =IF(D23="","",MAX(1,MIN(5,1+INT(IFERROR(PERCENTRANK(D$9:D$43,D23),0.5)*5)))) -> 5 | F23: =Universe!H19 -> 0.8034 | G23: =IF(F23="","",MAX(1,MIN(5,1+INT(IFERROR(PERCENTRANK(F$9:F$43,F23),0.5)*5)))) -> 5 | H23: =Universe!I19 -> 0.69 | I23: =IF(H23="","",MAX(1,MIN(5,5-INT(IFERROR(PERCENTRANK(H$9:H$43,H23),0.5)*5)))) -> 3 | J23: =Universe!J19 -> 0.0703 | K23: =IF(J23="","",MAX(1,MIN(5,1+INT(IFERROR(PERCENTRANK(J$9:J$43,J23),0.5)*5)))) -> 1 | L23: =Universe!K19 -> 7.94 | M23: =IF(L23="","",MAX(1,MIN(5,1+INT(IFERROR(PERCENTRANK(L$9:L$43,L23),0.5)*5)))) -> 1 | N23: =IF(COUNTA(D23,F23,H23,J23,L23)<5,"",E23*C5+G23*E5+I23*G5+K23*I5+M23*K5) -> 3.4 | P23: 16 | Q23: {=IFERROR(INDEX($B$9:$B$43,MATCH(LARGE($N$9:$N$43+(ROW($N$9:$N$43)-ROW($N$9))/1000,16),$N$9:$N$43+(ROW($N$9:$N$43)-ROW($N$9))/1000,0)),"")} -> Verisk Analytics | R23: {=IFERROR(INDEX($C$9:$C$43,MATCH(LARGE($N$9:$N$43+(ROW($N$9:$N$43)-ROW($N$9))/1000,16),$N$9:$N$43+(ROW($N$9:$N$43)-ROW($N$9))/1000,0)),"")} -> VRSK | S23: {=IFERROR(INDEX($N$9:$N$43,MATCH(LARGE($N$9:$N$43+(ROW($N$9:$N$43)-ROW($N$9))/1000,16),$N$9:$N$43+(ROW($N$9:$N$43)-ROW($N$9))/1000,0)),"")} -> 3 | T23: {=IFERROR(INDEX($E$9:$E$43,MATCH(LARGE($N$9:$N$43+(ROW($N$9:$N$43)-ROW($N$9))/1000,16),$N$9:$N$43+(ROW($N$9:$N$43)-ROW($N$9))/1000,0)),"")} -> 4 | U23: {=IFERROR(INDEX($G$9:$G$43,MATCH(LARGE($N$9:$N$43+(ROW($N$9:$N$43)-ROW($N$9))/1000,16),$N$9:$N$43+(ROW($N$9:$N$43)-ROW($N$9))/1000,0)),"")} -> 2 | V23: {=IFERROR(INDEX($I$9:$I$43,MATCH(LARGE($N$9:$N$43+(ROW($N$9:$N$43)-ROW($N$9))/1000,16),$N$9:$N$43+(ROW($N$9:$N$43)-ROW($N$9))/1000,0)),"")} -> 2 | W23: {=IFERROR(INDEX($K$9:$K$43,MATCH(LARGE($N$9:$N$43+(ROW($N$9:$N$43)-ROW($N$9))/1000,16),$N$9:$N$43+(ROW($N$9:$N$43)-ROW($N$9))/1000,0)),"")} -> 4 | X23: {=IFERROR(INDEX($M$9:$M$43,MATCH(LARGE($N$9:$N$43+(ROW($N$9:$N$43)-ROW($N$9))/1000,16),$N$9:$N$43+(ROW($N$9:$N$43)-ROW($N$9))/1000,0)),"")} -> 2 | Y23: =IF(R23="","",IF(COUNTIF(Portfolio!$C$5:$C$19,R23)>0,"YES","-")) -> -
A24: 16 | B24: Idexx Laboratories | C24: IDXX | D24: =Universe!G20 -> 0.5016 | E24: =IF(D24="","",MAX(1,MIN(5,1+INT(IFERROR(PERCENTRANK(D$9:D$43,D24),0.5)*5)))) -> 5 | F24: =Universe!H20 -> 0.6182 | G24: =IF(F24="","",MAX(1,MIN(5,1+INT(IFERROR(PERCENTRANK(F$9:F$43,F24),0.5)*5)))) -> 3 | H24: =Universe!I20 -> 0.44 | I24: =IF(H24="","",MAX(1,MIN(5,5-INT(IFERROR(PERCENTRANK(H$9:H$43,H24),0.5)*5)))) -> 3 | J24: =Universe!J20 -> 0.9943 | K24: =IF(J24="","",MAX(1,MIN(5,1+INT(IFERROR(PERCENTRANK(J$9:J$43,J24),0.5)*5)))) -> 4 | L24: =Universe!K20 -> 44.09 | M24: =IF(L24="","",MAX(1,MIN(5,1+INT(IFERROR(PERCENTRANK(L$9:L$43,L24),0.5)*5)))) -> 4 | N24: =IF(COUNTA(D24,F24,H24,J24,L24)<5,"",E24*C5+G24*E5+I24*G5+K24*I5+M24*K5) -> 3.9 | P24: 17 | Q24: {=IFERROR(INDEX($B$9:$B$43,MATCH(LARGE($N$9:$N$43+(ROW($N$9:$N$43)-ROW($N$9))/1000,17),$N$9:$N$43+(ROW($N$9:$N$43)-ROW($N$9))/1000,0)),"")} -> Accenture plc | R24: {=IFERROR(INDEX($C$9:$C$43,MATCH(LARGE($N$9:$N$43+(ROW($N$9:$N$43)-ROW($N$9))/1000,17),$N$9:$N$43+(ROW($N$9:$N$43)-ROW($N$9))/1000,0)),"")} -> ACN | S24: {=IFERROR(INDEX($N$9:$N$43,MATCH(LARGE($N$9:$N$43+(ROW($N$9:$N$43)-ROW($N$9))/1000,17),$N$9:$N$43+(ROW($N$9:$N$43)-ROW($N$9))/1000,0)),"")} -> 3 | T24: {=IFERROR(INDEX($E$9:$E$43,MATCH(LARGE($N$9:$N$43+(ROW($N$9:$N$43)-ROW($N$9))/1000,17),$N$9:$N$43+(ROW($N$9:$N$43)-ROW($N$9))/1000,0)),"")} -> 3 | U24: {=IFERROR(INDEX($G$9:$G$43,MATCH(LARGE($N$9:$N$43+(ROW($N$9:$N$43)-ROW($N$9))/1000,17),$N$9:$N$43+(ROW($N$9:$N$43)-ROW($N$9))/1000,0)),"")} -> 1 | V24: {=IFERROR(INDEX($I$9:$I$43,MATCH(LARGE($N$9:$N$43+(ROW($N$9:$N$43)-ROW($N$9))/1000,17),$N$9:$N$43+(ROW($N$9:$N$43)-ROW($N$9))/1000,0)),"")} -> 4 | W24: {=IFERROR(INDEX($K$9:$K$43,MATCH(LARGE($N$9:$N$43+(ROW($N$9:$N$43)-ROW($N$9))/1000,17),$N$9:$N$43+(ROW($N$9:$N$43)-ROW($N$9))/1000,0)),"")} -> 3 | X24: {=IFERROR(INDEX($M$9:$M$43,MATCH(LARGE($N$9:$N$43+(ROW($N$9:$N$43)-ROW($N$9))/1000,17),$N$9:$N$43+(ROW($N$9:$N$43)-ROW($N$9))/1000,0)),"")} -> 5 | Y24: =IF(R24="","",IF(COUNTIF(Portfolio!$C$5:$C$19,R24)>0,"YES","-")) -> -
A25: 17 | B25: Danaher Corporation | C25: DHR | D25: =Universe!G21 -> 0.0522 | E25: =IF(D25="","",MAX(1,MIN(5,1+INT(IFERROR(PERCENTRANK(D$9:D$43,D25),0.5)*5)))) -> 1 | F25: =Universe!H21 -> 0.5923 | G25: =IF(F25="","",MAX(1,MIN(5,1+INT(IFERROR(PERCENTRANK(F$9:F$43,F25),0.5)*5)))) -> 2 | H25: =Universe!I21 -> 1.79 | I25: =IF(H25="","",MAX(1,MIN(5,5-INT(IFERROR(PERCENTRANK(H$9:H$43,H25),0.5)*5)))) -> 1 | J25: =Universe!J21 -> 1.2172 | K25: =IF(J25="","",MAX(1,MIN(5,1+INT(IFERROR(PERCENTRANK(J$9:J$43,J25),0.5)*5)))) -> 5 | L25: =Universe!K21 -> 36.3 | M25: =IF(L25="","",MAX(1,MIN(5,1+INT(IFERROR(PERCENTRANK(L$9:L$43,L25),0.5)*5)))) -> 3 | N25: =IF(COUNTA(D25,F25,H25,J25,L25)<5,"",E25*C5+G25*E5+I25*G5+K25*I5+M25*K5) -> 2.2 | P25: 18 | Q25: {=IFERROR(INDEX($B$9:$B$43,MATCH(LARGE($N$9:$N$43+(ROW($N$9:$N$43)-ROW($N$9))/1000,18),$N$9:$N$43+(ROW($N$9:$N$43)-ROW($N$9))/1000,0)),"")} -> Microsoft Corporation | R25: {=IFERROR(INDEX($C$9:$C$43,MATCH(LARGE($N$9:$N$43+(ROW($N$9:$N$43)-ROW($N$9))/1000,18),$N$9:$N$43+(ROW($N$9:$N$43)-ROW($N$9))/1000,0)),"")} -> MSFT | S25: {=IFERROR(INDEX($N$9:$N$43,MATCH(LARGE($N$9:$N$43+(ROW($N$9:$N$43)-ROW($N$9))/1000,18),$N$9:$N$43+(ROW($N$9:$N$43)-ROW($N$9))/1000,0)),"")} -> 3 | T25: {=IFERROR(INDEX($E$9:$E$43,MATCH(LARGE($N$9:$N$43+(ROW($N$9:$N$43)-ROW($N$9))/1000,18),$N$9:$N$43+(ROW($N$9:$N$43)-ROW($N$9))/1000,0)),"")} -> 3 | U25: {=IFERROR(INDEX($G$9:$G$43,MATCH(LARGE($N$9:$N$43+(ROW($N$9:$N$43)-ROW($N$9))/1000,18),$N$9:$N$43+(ROW($N$9:$N$43)-ROW($N$9))/1000,0)),"")} -> 4 | V25: {=IFERROR(INDEX($I$9:$I$43,MATCH(LARGE($N$9:$N$43+(ROW($N$9:$N$43)-ROW($N$9))/1000,18),$N$9:$N$43+(ROW($N$9:$N$43)-ROW($N$9))/1000,0)),"")} -> 4 | W25: {=IFERROR(INDEX($K$9:$K$43,MATCH(LARGE($N$9:$N$43+(ROW($N$9:$N$43)-ROW($N$9))/1000,18),$N$9:$N$43+(ROW($N$9:$N$43)-ROW($N$9))/1000,0)),"")} -> 1 | X25: {=IFERROR(INDEX($M$9:$M$43,MATCH(LARGE($N$9:$N$43+(ROW($N$9:$N$43)-ROW($N$9))/1000,18),$N$9:$N$43+(ROW($N$9:$N$43)-ROW($N$9))/1000,0)),"")} -> 3 | Y25: =IF(R25="","",IF(COUNTIF(Portfolio!$C$5:$C$19,R25)>0,"YES","-")) -> -
A26: 18 | B26: Align Technology | C26: ALGN | D26: =Universe!G22 -> 0.1017 | E26: =IF(D26="","",MAX(1,MIN(5,1+INT(IFERROR(PERCENTRANK(D$9:D$43,D26),0.5)*5)))) -> 2 | F26: =Universe!H22 -> 0.698 | G26: =IF(F26="","",MAX(1,MIN(5,1+INT(IFERROR(PERCENTRANK(F$9:F$43,F26),0.5)*5)))) -> 4 | H26: =Universe!I22 -> -1.29 | I26: =IF(H26="","",MAX(1,MIN(5,5-INT(IFERROR(PERCENTRANK(H$9:H$43,H26),0.5)*5)))) -> 5 | J26: =Universe!J22 -> 1.196 | K26: =IF(J26="","",MAX(1,MIN(5,1+INT(IFERROR(PERCENTRANK(J$9:J$43,J26),0.5)*5)))) -> 4 | L26: =Universe!K22 -> 51.32 | M26: =IF(L26="","",MAX(1,MIN(5,1+INT(IFERROR(PERCENTRANK(L$9:L$43,L26),0.5)*5)))) -> 4 | N26: =IF(COUNTA(D26,F26,H26,J26,L26)<5,"",E26*C5+G26*E5+I26*G5+K26*I5+M26*K5) -> 3.6 | P26: 19 | Q26: {=IFERROR(INDEX($B$9:$B$43,MATCH(LARGE($N$9:$N$43+(ROW($N$9:$N$43)-ROW($N$9))/1000,19),$N$9:$N$43+(ROW($N$9:$N$43)-ROW($N$9))/1000,0)),"")} -> Taiwan Semiconductor | R26: {=IFERROR(INDEX($C$9:$C$43,MATCH(LARGE($N$9:$N$43+(ROW($N$9:$N$43)-ROW($N$9))/1000,19),$N$9:$N$43+(ROW($N$9:$N$43)-ROW($N$9))/1000,0)),"")} -> TSM | S26: {=IFERROR(INDEX($N$9:$N$43,MATCH(LARGE($N$9:$N$43+(ROW($N$9:$N$43)-ROW($N$9))/1000,19),$N$9:$N$43+(ROW($N$9:$N$43)-ROW($N$9))/1000,0)),"")} -> 2.9 | T26: {=IFERROR(INDEX($E$9:$E$43,MATCH(LARGE($N$9:$N$43+(ROW($N$9:$N$43)-ROW($N$9))/1000,19),$N$9:$N$43+(ROW($N$9:$N$43)-ROW($N$9))/1000,0)),"")} -> 4 | U26: {=IFERROR(INDEX($G$9:$G$43,MATCH(LARGE($N$9:$N$43+(ROW($N$9:$N$43)-ROW($N$9))/1000,19),$N$9:$N$43+(ROW($N$9:$N$43)-ROW($N$9))/1000,0)),"")} -> 2 | V26: {=IFERROR(INDEX($I$9:$I$43,MATCH(LARGE($N$9:$N$43+(ROW($N$9:$N$43)-ROW($N$9))/1000,19),$N$9:$N$43+(ROW($N$9:$N$43)-ROW($N$9))/1000,0)),"")} -> 5 | W26: {=IFERROR(INDEX($K$9:$K$43,MATCH(LARGE($N$9:$N$43+(ROW($N$9:$N$43)-ROW($N$9))/1000,19),$N$9:$N$43+(ROW($N$9:$N$43)-ROW($N$9))/1000,0)),"")} -> 1 | X26: {=IFERROR(INDEX($M$9:$M$43,MATCH(LARGE($N$9:$N$43+(ROW($N$9:$N$43)-ROW($N$9))/1000,19),$N$9:$N$43+(ROW($N$9:$N$43)-ROW($N$9))/1000,0)),"")} -> 1 | Y26: =IF(R26="","",IF(COUNTIF(Portfolio!$C$5:$C$19,R26)>0,"YES","-")) -> -
A27: 19 | B27: West Pharmaceutical Services | C27: WST | D27: =Universe!G23 -> 0.1532 | E27: =IF(D27="","",MAX(1,MIN(5,1+INT(IFERROR(PERCENTRANK(D$9:D$43,D27),0.5)*5)))) -> 3 | F27: =Universe!H23 -> 0.3592 | G27: =IF(F27="","",MAX(1,MIN(5,1+INT(IFERROR(PERCENTRANK(F$9:F$43,F27),0.5)*5)))) -> 1 | H27: =Universe!I23 -> -0.72 | I27: =IF(H27="","",MAX(1,MIN(5,5-INT(IFERROR(PERCENTRANK(H$9:H$43,H27),0.5)*5)))) -> 4 | J27: =Universe!J23 -> 0.8258 | K27: =IF(J27="","",MAX(1,MIN(5,1+INT(IFERROR(PERCENTRANK(J$9:J$43,J27),0.5)*5)))) -> 3 | L27: =Universe!K23 -> 39.18 | M27: =IF(L27="","",MAX(1,MIN(5,1+INT(IFERROR(PERCENTRANK(L$9:L$43,L27),0.5)*5)))) -> 3 | N27: =IF(COUNTA(D27,F27,H27,J27,L27)<5,"",E27*C5+G27*E5+I27*G5+K27*I5+M27*K5) -> 2.8 | P27: 20 | Q27: {=IFERROR(INDEX($B$9:$B$43,MATCH(LARGE($N$9:$N$43+(ROW($N$9:$N$43)-ROW($N$9))/1000,20),$N$9:$N$43+(ROW($N$9:$N$43)-ROW($N$9))/1000,0)),"")} -> L'Oréal S.A. | R27: {=IFERROR(INDEX($C$9:$C$43,MATCH(LARGE($N$9:$N$43+(ROW($N$9:$N$43)-ROW($N$9))/1000,20),$N$9:$N$43+(ROW($N$9:$N$43)-ROW($N$9))/1000,0)),"")} -> OR | S27: {=IFERROR(INDEX($N$9:$N$43,MATCH(LARGE($N$9:$N$43+(ROW($N$9:$N$43)-ROW($N$9))/1000,20),$N$9:$N$43+(ROW($N$9:$N$43)-ROW($N$9))/1000,0)),"")} -> 2.9 | T27: {=IFERROR(INDEX($E$9:$E$43,MATCH(LARGE($N$9:$N$43+(ROW($N$9:$N$43)-ROW($N$9))/1000,20),$N$9:$N$43+(ROW($N$9:$N$43)-ROW($N$9))/1000,0)),"")} -> 2 | U27: {=IFERROR(INDEX($G$9:$G$43,MATCH(LARGE($N$9:$N$43+(ROW($N$9:$N$43)-ROW($N$9))/1000,20),$N$9:$N$43+(ROW($N$9:$N$43)-ROW($N$9))/1000,0)),"")} -> 4 | V27: {=IFERROR(INDEX($I$9:$I$43,MATCH(LARGE($N$9:$N$43+(ROW($N$9:$N$43)-ROW($N$9))/1000,20),$N$9:$N$43+(ROW($N$9:$N$43)-ROW($N$9))/1000,0)),"")} -> 3 | W27: {=IFERROR(INDEX($K$9:$K$43,MATCH(LARGE($N$9:$N$43+(ROW($N$9:$N$43)-ROW($N$9))/1000,20),$N$9:$N$43+(ROW($N$9:$N$43)-ROW($N$9))/1000,0)),"")} -> 2 | X27: {=IFERROR(INDEX($M$9:$M$43,MATCH(LARGE($N$9:$N$43+(ROW($N$9:$N$43)-ROW($N$9))/1000,20),$N$9:$N$43+(ROW($N$9:$N$43)-ROW($N$9))/1000,0)),"")} -> 5 | Y27: =IF(R27="","",IF(COUNTIF(Portfolio!$C$5:$C$19,R27)>0,"YES","-")) -> -
A28: 20 | B28: LVMH Moët Hennessy | C28: MC | D28: =Universe!G24 -> 0.1159 | E28: =IF(D28="","",MAX(1,MIN(5,1+INT(IFERROR(PERCENTRANK(D$9:D$43,D28),0.5)*5)))) -> 2 | F28: =Universe!H24 -> 0.6624 | G28: =IF(F28="","",MAX(1,MIN(5,1+INT(IFERROR(PERCENTRANK(F$9:F$43,F28),0.5)*5)))) -> 3 | H28: =Universe!I24 -> 0.94 | I28: =IF(H28="","",MAX(1,MIN(5,5-INT(IFERROR(PERCENTRANK(H$9:H$43,H28),0.5)*5)))) -> 2 | J28: =Universe!J24 -> 0.7662 | K28: =IF(J28="","",MAX(1,MIN(5,1+INT(IFERROR(PERCENTRANK(J$9:J$43,J28),0.5)*5)))) -> 2 | L28: =Universe!K24 -> 157.79 | M28: =IF(L28="","",MAX(1,MIN(5,1+INT(IFERROR(PERCENTRANK(L$9:L$43,L28),0.5)*5)))) -> 5 | N28: =IF(COUNTA(D28,F28,H28,J28,L28)<5,"",E28*C5+G28*E5+I28*G5+K28*I5+M28*K5) -> 2.5
A29: 21 | B29: Hermès International | C29: RMS | D29: =Universe!G25 -> 0.226 | E29: =IF(D29="","",MAX(1,MIN(5,1+INT(IFERROR(PERCENTRANK(D$9:D$43,D29),0.5)*5)))) -> 3 | F29: =Universe!H25 -> 0.6655 | G29: =IF(F29="","",MAX(1,MIN(5,1+INT(IFERROR(PERCENTRANK(F$9:F$43,F29),0.5)*5)))) -> 4 | H29: =Universe!I25 -> -1.32 | I29: =IF(H29="","",MAX(1,MIN(5,5-INT(IFERROR(PERCENTRANK(H$9:H$43,H29),0.5)*5)))) -> 5 | J29: =Universe!J25 -> 0.3674 | K29: =IF(J29="","",MAX(1,MIN(5,1+INT(IFERROR(PERCENTRANK(J$9:J$43,J29),0.5)*5)))) -> 1 | L29: =Universe!K25 -> 144.1 | M29: =IF(L29="","",MAX(1,MIN(5,1+INT(IFERROR(PERCENTRANK(L$9:L$43,L29),0.5)*5)))) -> 5 | N29: =IF(COUNTA(D29,F29,H29,J29,L29)<5,"",E29*C5+G29*E5+I29*G5+K29*I5+M29*K5) -> 3.4 | P29: Amber rank = primary shortlist (top 15). Divider line separates top 15 from reserve candidates (16-20). 'In Portfolio?' updates live when tickers are entered in Portfolio tab.
A30: 22 | B30: L'Oréal S.A. | C30: OR | D30: =Universe!G26 -> 0.1456 | E30: =IF(D30="","",MAX(1,MIN(5,1+INT(IFERROR(PERCENTRANK(D$9:D$43,D30),0.5)*5)))) -> 2 | F30: =Universe!H26 -> 0.7432 | G30: =IF(F30="","",MAX(1,MIN(5,1+INT(IFERROR(PERCENTRANK(F$9:F$43,F30),0.5)*5)))) -> 4 | H30: =Universe!I26 -> 0.19 | I30: =IF(H30="","",MAX(1,MIN(5,5-INT(IFERROR(PERCENTRANK(H$9:H$43,H30),0.5)*5)))) -> 3 | J30: =Universe!J26 -> 0.5295 | K30: =IF(J30="","",MAX(1,MIN(5,1+INT(IFERROR(PERCENTRANK(J$9:J$43,J30),0.5)*5)))) -> 2 | L30: =Universe!K26 -> 85.6 | M30: =IF(L30="","",MAX(1,MIN(5,1+INT(IFERROR(PERCENTRANK(L$9:L$43,L30),0.5)*5)))) -> 5 | N30: =IF(COUNTA(D30,F30,H30,J30,L30)<5,"",E30*C5+G30*E5+I30*G5+K30*I5+M30*K5) -> 2.9
A31: 23 | B31: Ferrari N.V. | C31: RACE | D31: =Universe!G27 -> 0.2806 | E31: =IF(D31="","",MAX(1,MIN(5,1+INT(IFERROR(PERCENTRANK(D$9:D$43,D31),0.5)*5)))) -> 4 | F31: =Universe!H27 -> 0.5246 | G31: =IF(F31="","",MAX(1,MIN(5,1+INT(IFERROR(PERCENTRANK(F$9:F$43,F31),0.5)*5)))) -> 2 | H31: =Universe!I27 -> 0.48 | I31: =IF(H31="","",MAX(1,MIN(5,5-INT(IFERROR(PERCENTRANK(H$9:H$43,H31),0.5)*5)))) -> 3 | J31: =Universe!J27 -> 0.8356 | K31: =IF(J31="","",MAX(1,MIN(5,1+INT(IFERROR(PERCENTRANK(J$9:J$43,J31),0.5)*5)))) -> 3 | L31: =Universe!K27 -> 37.78 | M31: =IF(L31="","",MAX(1,MIN(5,1+INT(IFERROR(PERCENTRANK(L$9:L$43,L31),0.5)*5)))) -> 3 | N31: =IF(COUNTA(D31,F31,H31,J31,L31)<5,"",E31*C5+G31*E5+I31*G5+K31*I5+M31*K5) -> 3.1
A32: 24 | B32: Diageo plc | C32: DGE | D32: =Universe!G28 -> 0.0785 | E32: =IF(D32="","",MAX(1,MIN(5,1+INT(IFERROR(PERCENTRANK(D$9:D$43,D32),0.5)*5)))) -> 2 | F32: =Universe!H28 -> 0.6049 | G32: =IF(F32="","",MAX(1,MIN(5,1+INT(IFERROR(PERCENTRANK(F$9:F$43,F32),0.5)*5)))) -> 3 | H32: =Universe!I28 -> 3.16 | I32: =IF(H32="","",MAX(1,MIN(5,5-INT(IFERROR(PERCENTRANK(H$9:H$43,H32),0.5)*5)))) -> 1 | J32: =Universe!J28 -> 0.1644 | K32: =IF(J32="","",MAX(1,MIN(5,1+INT(IFERROR(PERCENTRANK(J$9:J$43,J32),0.5)*5)))) -> 1 | L32: =Universe!K28 -> 9.07 | M32: =IF(L32="","",MAX(1,MIN(5,1+INT(IFERROR(PERCENTRANK(L$9:L$43,L32),0.5)*5)))) -> 1 | N32: =IF(COUNTA(D32,F32,H32,J32,L32)<5,"",E32*C5+G32*E5+I32*G5+K32*I5+M32*K5) -> 1.7
A33: 25 | B33: ASML Holding N.V. | C33: ASML | D33: =Universe!G29 -> 0.428 | E33: =IF(D33="","",MAX(1,MIN(5,1+INT(IFERROR(PERCENTRANK(D$9:D$43,D33),0.5)*5)))) -> 5 | F33: =Universe!H29 -> 0.5156 | G33: =IF(F33="","",MAX(1,MIN(5,1+INT(IFERROR(PERCENTRANK(F$9:F$43,F33),0.5)*5)))) -> 2 | H33: =Universe!I29 -> -0.72 | I33: =IF(H33="","",MAX(1,MIN(5,5-INT(IFERROR(PERCENTRANK(H$9:H$43,H33),0.5)*5)))) -> 4 | J33: =Universe!J29 -> 0.8882 | K33: =IF(J33="","",MAX(1,MIN(5,1+INT(IFERROR(PERCENTRANK(J$9:J$43,J33),0.5)*5)))) -> 3 | L33: =Universe!K29 -> 64.86 | M33: =IF(L33="","",MAX(1,MIN(5,1+INT(IFERROR(PERCENTRANK(L$9:L$43,L33),0.5)*5)))) -> 4 | N33: =IF(COUNTA(D33,F33,H33,J33,L33)<5,"",E33*C5+G33*E5+I33*G5+K33*I5+M33*K5) -> 3.7
A34: 26 | B34: Fastenal Company | C34: FAST | D34: =Universe!G30 -> 0.3076 | E34: =IF(D34="","",MAX(1,MIN(5,1+INT(IFERROR(PERCENTRANK(D$9:D$43,D34),0.5)*5)))) -> 4 | F34: =Universe!H30 -> 0.4296 | G34: =IF(F34="","",MAX(1,MIN(5,1+INT(IFERROR(PERCENTRANK(F$9:F$43,F34),0.5)*5)))) -> 1 | H34: =Universe!I30 -> -0.08 | I34: =IF(H34="","",MAX(1,MIN(5,5-INT(IFERROR(PERCENTRANK(H$9:H$43,H34),0.5)*5)))) -> 4 | J34: =Universe!J30 -> 0.0369 | K34: =IF(J34="","",MAX(1,MIN(5,1+INT(IFERROR(PERCENTRANK(J$9:J$43,J34),0.5)*5)))) -> 1 | L34: =Universe!K30 -> 6.28 | M34: =IF(L34="","",MAX(1,MIN(5,1+INT(IFERROR(PERCENTRANK(L$9:L$43,L34),0.5)*5)))) -> 1 | N34: =IF(COUNTA(D34,F34,H34,J34,L34)<5,"",E34*C5+G34*E5+I34*G5+K34*I5+M34*K5) -> 2.5
A35: 27 | B35: Copart Inc. | C35: CPRT | D35: =Universe!G31 -> 0.1838 | E35: =IF(D35="","",MAX(1,MIN(5,1+INT(IFERROR(PERCENTRANK(D$9:D$43,D35),0.5)*5)))) -> 3 | F35: =Universe!H31 -> 0.4467 | G35: =IF(F35="","",MAX(1,MIN(5,1+INT(IFERROR(PERCENTRANK(F$9:F$43,F35),0.5)*5)))) -> 1 | H35: =Universe!I31 -> -2.5 | I35: =IF(H35="","",MAX(1,MIN(5,5-INT(IFERROR(PERCENTRANK(H$9:H$43,H35),0.5)*5)))) -> 5 | J35: =Universe!J31 -> 0.7928 | K35: =IF(J35="","",MAX(1,MIN(5,1+INT(IFERROR(PERCENTRANK(J$9:J$43,J35),0.5)*5)))) -> 2 | L35: =Universe!K31 -> 3.91 | M35: =IF(L35="","",MAX(1,MIN(5,1+INT(IFERROR(PERCENTRANK(L$9:L$43,L35),0.5)*5)))) -> 1 | N35: =IF(COUNTA(D35,F35,H35,J35,L35)<5,"",E35*C5+G35*E5+I35*G5+K35*I5+M35*K5) -> 2.6
A36: 28 | B36: Roper Technologies | C36: ROP | D36: =Universe!G32 -> 0.0566 | E36: =IF(D36="","",MAX(1,MIN(5,1+INT(IFERROR(PERCENTRANK(D$9:D$43,D36),0.5)*5)))) -> 1 | F36: =Universe!H32 -> 0.6924 | G36: =IF(F36="","",MAX(1,MIN(5,1+INT(IFERROR(PERCENTRANK(F$9:F$43,F36),0.5)*5)))) -> 4 | H36: =Universe!I32 -> 2.87 | I36: =IF(H36="","",MAX(1,MIN(5,5-INT(IFERROR(PERCENTRANK(H$9:H$43,H36),0.5)*5)))) -> 1 | J36: =Universe!J32 -> 1.3916 | K36: =IF(J36="","",MAX(1,MIN(5,1+INT(IFERROR(PERCENTRANK(J$9:J$43,J36),0.5)*5)))) -> 5 | L36: =Universe!K32 -> 60.06 | M36: =IF(L36="","",MAX(1,MIN(5,1+INT(IFERROR(PERCENTRANK(L$9:L$43,L36),0.5)*5)))) -> 4 | N36: =IF(COUNTA(D36,F36,H36,J36,L36)<5,"",E36*C5+G36*E5+I36*G5+K36*I5+M36*K5) -> 2.7
A37: 29 | B37: Rational AG | C37: RAA | D37: =Universe!G33 -> 0.2766 | E37: =IF(D37="","",MAX(1,MIN(5,1+INT(IFERROR(PERCENTRANK(D$9:D$43,D37),0.5)*5)))) -> 4 | F37: =Universe!H33 -> 0.5902 | G37: =IF(F37="","",MAX(1,MIN(5,1+INT(IFERROR(PERCENTRANK(F$9:F$43,F37),0.5)*5)))) -> 2 | H37: =Universe!I33 -> -1.39 | I37: =IF(H37="","",MAX(1,MIN(5,5-INT(IFERROR(PERCENTRANK(H$9:H$43,H37),0.5)*5)))) -> 5 | J37: =Universe!J33 -> 0.2348 | K37: =IF(J37="","",MAX(1,MIN(5,1+INT(IFERROR(PERCENTRANK(J$9:J$43,J37),0.5)*5)))) -> 1 | L37: =Universe!K33 -> 109.69 | M37: =IF(L37="","",MAX(1,MIN(5,1+INT(IFERROR(PERCENTRANK(L$9:L$43,L37),0.5)*5)))) -> 5 | N37: =IF(COUNTA(D37,F37,H37,J37,L37)<5,"",E37*C5+G37*E5+I37*G5+K37*I5+M37*K5) -> 3.3
A38: 30 | B38: Verisk Analytics | C38: VRSK | D38: =Universe!G34 -> 0.2803 | E38: =IF(D38="","",MAX(1,MIN(5,1+INT(IFERROR(PERCENTRANK(D$9:D$43,D38),0.5)*5)))) -> 4 | F38: =Universe!H34 -> 0.5925 | G38: =IF(F38="","",MAX(1,MIN(5,1+INT(IFERROR(PERCENTRANK(F$9:F$43,F38),0.5)*5)))) -> 2 | H38: =Universe!I34 -> 1.5 | I38: =IF(H38="","",MAX(1,MIN(5,5-INT(IFERROR(PERCENTRANK(H$9:H$43,H38),0.5)*5)))) -> 2 | J38: =Universe!J34 -> 1.0358 | K38: =IF(J38="","",MAX(1,MIN(5,1+INT(IFERROR(PERCENTRANK(J$9:J$43,J38),0.5)*5)))) -> 4 | L38: =Universe!K34 -> 18.88 | M38: =IF(L38="","",MAX(1,MIN(5,1+INT(IFERROR(PERCENTRANK(L$9:L$43,L38),0.5)*5)))) -> 2 | N38: =IF(COUNTA(D38,F38,H38,J38,L38)<5,"",E38*C5+G38*E5+I38*G5+K38*I5+M38*K5) -> 3
A39: 31 | B39: TransUnion | C39: TRU | D39: =Universe!G35 -> 0.0487 | E39: =IF(D39="","",MAX(1,MIN(5,1+INT(IFERROR(PERCENTRANK(D$9:D$43,D39),0.5)*5)))) -> 1 | F39: =Universe!H35 -> 0.4653 | G39: =IF(F39="","",MAX(1,MIN(5,1+INT(IFERROR(PERCENTRANK(F$9:F$43,F39),0.5)*5)))) -> 1 | H39: =Universe!I35 -> 2.84 | I39: =IF(H39="","",MAX(1,MIN(5,5-INT(IFERROR(PERCENTRANK(H$9:H$43,H39),0.5)*5)))) -> 1 | J39: =Universe!J35 -> 1.2541 | K39: =IF(J39="","",MAX(1,MIN(5,1+INT(IFERROR(PERCENTRANK(J$9:J$43,J39),0.5)*5)))) -> 5 | L39: =Universe!K35 -> 19.78 | M39: =IF(L39="","",MAX(1,MIN(5,1+INT(IFERROR(PERCENTRANK(L$9:L$43,L39),0.5)*5)))) -> 2 | N39: =IF(COUNTA(D39,F39,H39,J39,L39)<5,"",E39*C5+G39*E5+I39*G5+K39*I5+M39*K5) -> 1.9
A40: 32 | B40: Taiwan Semiconductor | C40: TSM | D40: =Universe!G36 -> 0.2956 | E40: =IF(D40="","",MAX(1,MIN(5,1+INT(IFERROR(PERCENTRANK(D$9:D$43,D40),0.5)*5)))) -> 4 | F40: =Universe!H36 -> 0.5872 | G40: =IF(F40="","",MAX(1,MIN(5,1+INT(IFERROR(PERCENTRANK(F$9:F$43,F40),0.5)*5)))) -> 2 | H40: =Universe!I36 -> -0.76 | I40: =IF(H40="","",MAX(1,MIN(5,5-INT(IFERROR(PERCENTRANK(H$9:H$43,H40),0.5)*5)))) -> 5 | J40: =Universe!J36 -> 0.3557 | K40: =IF(J40="","",MAX(1,MIN(5,1+INT(IFERROR(PERCENTRANK(J$9:J$43,J40),0.5)*5)))) -> 1 | L40: =Universe!K36 -> 3.05 | M40: =IF(L40="","",MAX(1,MIN(5,1+INT(IFERROR(PERCENTRANK(L$9:L$43,L40),0.5)*5)))) -> 1 | N40: =IF(COUNTA(D40,F40,H40,J40,L40)<5,"",E40*C5+G40*E5+I40*G5+K40*I5+M40*K5) -> 2.9
A41: 33 | B41: Keyence Corporation | C41: 6861 | D41: =Universe!G37 -> 0.1348 | E41: =IF(D41="","",MAX(1,MIN(5,1+INT(IFERROR(PERCENTRANK(D$9:D$43,D41),0.5)*5)))) -> 2 | F41: =Universe!H37 -> 0.8381 | G41: =IF(F41="","",MAX(1,MIN(5,1+INT(IFERROR(PERCENTRANK(F$9:F$43,F41),0.5)*5)))) -> 5 | H41: =Universe!I37 -> -2.16 | I41: =IF(H41="","",MAX(1,MIN(5,5-INT(IFERROR(PERCENTRANK(H$9:H$43,H41),0.5)*5)))) -> 5 | J41: =Universe!J37 -> 0.7936 | K41: =IF(J41="","",MAX(1,MIN(5,1+INT(IFERROR(PERCENTRANK(J$9:J$43,J41),0.5)*5)))) -> 2 | L41: =Universe!K37 -> 23.3 | M41: =IF(L41="","",MAX(1,MIN(5,1+INT(IFERROR(PERCENTRANK(L$9:L$43,L41),0.5)*5)))) -> 2 | N41: =IF(COUNTA(D41,F41,H41,J41,L41)<5,"",E41*C5+G41*E5+I41*G5+K41*I5+M41*K5) -> 3.2
A42: 34 | B42: EssilorLuxottica | C42: EL | D42: =Universe!G38 -> 0.047 | E42: =IF(D42="","",MAX(1,MIN(5,1+INT(IFERROR(PERCENTRANK(D$9:D$43,D42),0.5)*5)))) -> 1 | F42: =Universe!H38 -> 0.6061 | G42: =IF(F42="","",MAX(1,MIN(5,1+INT(IFERROR(PERCENTRANK(F$9:F$43,F42),0.5)*5)))) -> 3 | H42: =Universe!I38 -> 1.68 | I42: =IF(H42="","",MAX(1,MIN(5,5-INT(IFERROR(PERCENTRANK(H$9:H$43,H42),0.5)*5)))) -> 2 | J42: =Universe!J38 -> 1.517 | K42: =IF(J42="","",MAX(1,MIN(5,1+INT(IFERROR(PERCENTRANK(J$9:J$43,J42),0.5)*5)))) -> 5 | L42: =Universe!K38 -> 63.68 | M42: =IF(L42="","",MAX(1,MIN(5,1+INT(IFERROR(PERCENTRANK(L$9:L$43,L42),0.5)*5)))) -> 4 | N42: =IF(COUNTA(D42,F42,H42,J42,L42)<5,"",E42*C5+G42*E5+I42*G5+K42*I5+M42*K5) -> 2.7
A43: 35 | B43: Mettler-Toledo International | C43: MTD | D43: =Universe!G39 -> 0.4418 | E43: =IF(D43="","",MAX(1,MIN(5,1+INT(IFERROR(PERCENTRANK(D$9:D$43,D43),0.5)*5)))) -> 5 | F43: =Universe!H39 -> 0.5752 | G43: =IF(F43="","",MAX(1,MIN(5,1+INT(IFERROR(PERCENTRANK(F$9:F$43,F43),0.5)*5)))) -> 2 | H43: =Universe!I39 -> 1.68 | I43: =IF(H43="","",MAX(1,MIN(5,5-INT(IFERROR(PERCENTRANK(H$9:H$43,H43),0.5)*5)))) -> 2 | J43: =Universe!J39 -> 0.9764 | K43: =IF(J43="","",MAX(1,MIN(5,1+INT(IFERROR(PERCENTRANK(J$9:J$43,J43),0.5)*5)))) -> 4 | L43: =Universe!K39 -> 175.97 | M43: =IF(L43="","",MAX(1,MIN(5,1+INT(IFERROR(PERCENTRANK(L$9:L$43,L43),0.5)*5)))) -> 5 | N43: =IF(COUNTA(D43,F43,H43,J43,L43)<5,"",E43*C5+G43*E5+I43*G5+K43*I5+M43*K5) -> 3.6
A45: Note: | B45: {=IFERROR(IF(COUNTA(Portfolio!$C$5:$C$19)=0,"",MIN(IFERROR(VLOOKUP(Portfolio!$C$5:$C$19,'Factor Screen'!$C$9:$N$43,12,0),999))),"")} -> 3.1

Sheet Portfolio
A1: GLOBAL QUALITY COMPOUNDER PORTFOLIO: PORTFOLIO CONSTRUCTION
A2: Final 15-holding portfolio. Yellow cells = user inputs. Active Weight = Portfolio Weight − Benchmark Weight. Thesis column for investment rationale.
A4: # | B4: STOCK | C4: TICKER | D4: REGION | E4: SECTOR | F4: PORT. WEIGHT (%) | G4: BMRK WEIGHT (%) | H4: ACTIVE WEIGHT (%) | I4: CONVICTION | J4: THESIS (ONE LINE) | K4: ENTRY DATE | L4: TARGET WEIGHT (%) | M4: STATUS | N4: QUALITY SCORE
A5: 1 | B5: Mastercard Incorporated | C5: MA | D5: North America | E5: Financials | F5: 0.07 | G5: 0.006 | H5: =IF(OR(F5="",G5=""),"",F5-G5) -> 0.064 | I5: High | J5: Dominant global payments network; near-zero marginal cost growth; 50%+ EBIT margins structurally protected by two-sided network effects. | L5: 0.07 | M5: Active | N5: =IFERROR(VLOOKUP(C5,'Factor Screen'!$C$9:$N$43,12,0),"") -> 4.2
A6: 2 | B6: Idexx Laboratories | C6: IDXX | D6: North America | E6: Healthcare | F6: 0.06 | G6: 0.001 | H6: =IF(OR(F6="",G6=""),"",F6-G6) -> 0.059 | I6: High | J6: Monopoly in veterinary diagnostics; recurring consumables revenue; pricing power validated by >30% EBIT margins across economic cycles. | L6: 0.06 | M6: Active | N6: =IFERROR(VLOOKUP(C6,'Factor Screen'!$C$9:$N$43,12,0),"") -> 3.9
A7: 3 | B7: Visa Inc. | C7: V | D7: North America | E7: Financials | F7: 0.065 | G7: 0.009 | H7: =IF(OR(F7="",G7=""),"",F7-G7) -> 0.056 | I7: High | J7: Unrivalled global payment rail; asset-light model converts >50% of revenue to FCF; secular cashless transition provides long-duration growth. | L7: 0.065 | M7: Active | N7: =IFERROR(VLOOKUP(C7,'Factor Screen'!$C$9:$N$43,12,0),"") -> 3.8
A8: 4 | B8: ASML Holding N.V. | C8: ASML | D8: Europe | E8: Technology | F8: 0.085 | G8: 0.005 | H8: =IF(OR(F8="",G8=""),"",F8-G8) -> 0.08 | I8: High | J8: Monopoly supplier of EUV lithography; zero substitutes; semi capex cycle creates lumpy but structurally growing revenue with 50%+ gross margins. | L8: 0.085 | M8: Active | N8: =IFERROR(VLOOKUP(C8,'Factor Screen'!$C$9:$N$43,12,0),"") -> 3.7
A9: 5 | B9: Hermès International | C9: RMS | D9: Europe | E9: Consumer Discretionary | F9: 0.085 | G9: 0.002 | H9: =IF(OR(F9="",G9=""),"",F9-G9) -> 0.083 | I9: High | J9: Irreplaceable luxury brand with artificial scarcity model; pricing power untested by cycles; 40%+ EBIT margins and negative working capital. | L9: 0.085 | M9: Active | N9: =IFERROR(VLOOKUP(C9,'Factor Screen'!$C$9:$N$43,12,0),"") -> 3.4
A10: 6 | B10: Novo Nordisk A/S | C10: NOVO B | D10: Europe | E10: Healthcare | F10: 0.08 | G10: 0.006 | H10: =IF(OR(F10="",G10=""),"",F10-G10) -> 0.074 | I10: High | J10: Global leader in GLP-1 obesity and diabetes drugs; durable patent moat; manufacturing scale creates structural competitive advantage. | L10: 0.08 | M10: Active | N10: =IFERROR(VLOOKUP(C10,'Factor Screen'!$C$9:$N$43,12,0),"") -> 3.4
A11: 7 | B11: Veeva Systems | C11: VEEV | D11: North America | E11: Technology | F11: 0.055 | G11: 0.001 | H11: =IF(OR(F11="",G11=""),"",F11-G11) -> 0.054 | I11: High | J11: Mission-critical SaaS for life sciences; near-100% gross retention; switching costs extreme as platform embeds into clinical and commercial workflows. | L11: 0.055 | M11: Active | N11: =IFERROR(VLOOKUP(C11,'Factor Screen'!$C$9:$N$43,12,0),"") -> 3.7
A12: 8 | B12: Mettler-Toledo International | C12: MTD | D12: Europe | E12: Healthcare | F12: 0.08 | G12: 0.001 | H12: =IF(OR(F12="",G12=""),"",F12-G12) -> 0.079 | I12: High | J12: Precision instruments with consumables and calibration annuity; capital-light compounder with 30-year track record of double-digit EPS growth. | L12: 0.08 | M12: Active | N12: =IFERROR(VLOOKUP(C12,'Factor Screen'!$C$9:$N$43,12,0),"") -> 3.6
A13: 9 | B13: Align Technology | C13: ALGN | D13: North America | E13: Healthcare | F13: 0.05 | G13: 0.001 | H13: =IF(OR(F13="",G13=""),"",F13-G13) -> 0.049 | I13: Medium | J13: Dominant clear aligner franchise; iTero scanner creates sticky ecosystem; secular orthodontic market penetration still <30% of addressable cases. | L13: 0.05 | M13: Active | N13: =IFERROR(VLOOKUP(C13,'Factor Screen'!$C$9:$N$43,12,0),"") -> 3.6
A14: 10 | B14: MSCI Inc. | C14: MSCI | D14: North America | E14: Financials | F14: 0.05 | G14: 0.002 | H14: =IF(OR(F14="",G14=""),"",F14-G14) -> 0.048 | I14: Medium | J14: Index and analytics monopoly embedded in global asset management; AUM-linked recurring revenue; regulatory moat with 90%+ retention rates. | L14: 0.05 | M14: Active | N14: =IFERROR(VLOOKUP(C14,'Factor Screen'!$C$9:$N$43,12,0),"") -> 3.3
A15: 11 | B15: Rational AG | C15: RAA | D15: Europe | E15: Industrials | F15: 0.07 | G15: 0 | H15: =IF(OR(F15="",G15=""),"",F15-G15) -> 0.07 | I15: Medium | J15: Global leader in professional combi-steamer ovens; 50%+ installed-base market share; consumables and service revenue drives high recurring mix. | L15: 0.07 | M15: Active | N15: =IFERROR(VLOOKUP(C15,'Factor Screen'!$C$9:$N$43,12,0),"") -> 3.3
A16: 12 | B16: Keyence Corporation | C16: 6861 | D16: Asia Pacific | E16: Technology | F16: 0.065 | G16: 0.002 | H16: =IF(OR(F16="",G16=""),"",F16-G16) -> 0.063 | I16: Medium | J16: Direct-sales factory automation sensors; no distributors means superior margins and customer insight; net-cash balance sheet funds R&D moat. | L16: 0.065 | M16: Active | N16: =IFERROR(VLOOKUP(C16,'Factor Screen'!$C$9:$N$43,12,0),"") -> 3.2
A17: 13 | B17: Ferrari N.V. | C17: RACE | D17: Europe | E17: Consumer Discretionary | F17: 0.07 | G17: 0.001 | H17: =IF(OR(F17="",G17=""),"",F17-G17) -> 0.069 | I17: Medium | J17: Scarcity-driven luxury brand; multi-year order backlog decouples revenue from macro; electrification transition protects rather than dilutes brand. | L17: 0.07 | M17: Active | N17: =IFERROR(VLOOKUP(C17,'Factor Screen'!$C$9:$N$43,12,0),"") -> 3.1
A18: 14 | B18: Automatic Data Processing | C18: ADP | D18: North America | E18: Technology | F18: 0.05 | G18: 0.003 | H18: =IF(OR(F18="",G18=""),"",F18-G18) -> 0.047 | I18: Medium | J18: Payroll and HCM SaaS compounder; float income tailwind in high-rate environment; switching costs embedded after years of client data integration. | L18: 0.05 | M18: Active | N18: =IFERROR(VLOOKUP(C18,'Factor Screen'!$C$9:$N$43,12,0),"") -> 3.1
A19: 15 | B19: Rightmove | C19: RMV | D19: United Kingdom | E19: Technology | F19: 0.065 | G19: 0 | H19: =IF(OR(F19="",G19=""),"",F19-G19) -> 0.065 | I19: Medium | J19: Monopoly UK property portal; near-100% market share with no credible challenger; high-margin, capital-light business with structural pricing power. | L19: 0.065 | M19: Active | N19: =IFERROR(VLOOKUP(C19,'Factor Screen'!$C$9:$N$43,12,0),"") -> 3.8
A20: TOTAL | F20: =SUM(F5:F19) -> 1 | G20: =SUM(G5:G19) -> 0.04 | H20: =SUM(H5:H19) -> 0.96 | N20: =IFERROR(SUMPRODUCT(F5:F19,N5:N19)/SUM(F5:F19),"") -> 3.545
A22: SECTOR CONCENTRATION | F22: REGION CONCENTRATION | K22: MANDATE CHECKS
A23: SECTOR | B23: PORT. WEIGHT | C23: BMRK WEIGHT | D23: ACTIVE WEIGHT | F23: REGION | G23: PORT. WEIGHT | H23: BMRK WEIGHT | I23: ACTIVE WEIGHT | K23: CONSTRAINT | L23: LIMIT | M23: CURRENT | N23: STATUS
A24: Technology | B24: =SUMIF($E$5:$E$19,A24,$F$5:$F$19) -> 0.32 | C24: 0.245 | D24: =IF(C24="","",B24-C24) -> 0.075 | F24: North America | G24: =SUMIF($D$5:$D$19,F24,$F$5:$F$19) -> 0.4 | H24: 0.718 | I24: =IF(H24="","",G24-H24) -> -0.318 | K24: Total Weight | L24: 1 | M24: =TEXT(SUM(F5:F19),"0.0%") -> 100.0% | N24: =IF(ABS(SUM(F5:F19)-1)<0.001,"OK","CHECK") -> OK
A25: Financials | B25: =SUMIF($E$5:$E$19,A25,$F$5:$F$19) -> 0.185 | C25: 0.175 | D25: =IF(C25="","",B25-C25) -> 0.01 | F25: Europe | G25: =SUMIF($D$5:$D$19,F25,$F$5:$F$19) -> 0.47 | H25: 0.156 | I25: =IF(H25="","",G25-H25) -> 0.314 | K25: Max Single Weight | L25: 0.08 | M25: =TEXT(MAX(F5:F19),"0.0%") -> 8.5% | N25: =IF(MAX(F5:F19)<=0.08,"OK","BREACH") -> BREACH
A26: Healthcare | B26: =SUMIF($E$5:$E$19,A26,$F$5:$F$19) -> 0.27 | C26: 0.115 | D26: =IF(C26="","",B26-C26) -> 0.155 | F26: Asia Pacific | G26: =SUMIF($D$5:$D$19,F26,$F$5:$F$19) -> 0.065 | H26: 0.086 | I26: =IF(H26="","",G26-H26) -> -0.021 | K26: Min Single Weight | L26: 0.02 | M26: {=TEXT(MIN(IF(F5:F19>0,F5:F19)),"0.0%")} -> 5.0% | N26: {=IF(MIN(IF(F5:F19>0,F5:F19))>=0.02,"OK","BREACH")} -> OK
A27: Consumer Discretionary | B27: =SUMIF($E$5:$E$19,A27,$F$5:$F$19) -> 0.155 | C27: 0.105 | D27: =IF(C27="","",B27-C27) -> 0.05 | F27: UK | G27: =SUMIF($D$5:$D$19,F27,$F$5:$F$19) -> 0 | H27: 0.04 | I27: =IF(H27="","",G27-H27) -> -0.04 | K27: No. of Holdings | L27: 12–15 | M27: =TEXT(COUNTA(C5:C19),"0")&" stocks" -> 15 stocks | N27: =IF(AND(COUNTA(C5:C19)>=12,COUNTA(C5:C19)<=15),"OK","CHECK") -> OK
A28: Consumer Staples | B28: =SUMIF($E$5:$E$19,A28,$F$5:$F$19) -> 0 | C28: 0.075 | D28: =IF(C28="","",B28-C28) -> -0.075 | F28: TOTAL | G28: =SUM(G24:G27) -> 0.935 | H28: =SUM(H24:H27) -> 1 | I28: =SUM(I24:I27) -> -0.065 | K28: NA Region | L28: ≤40% | M28: =TEXT(SUMIF(D5:D19,"North America",F5:F19),"0.0%") -> 40.0% | N28: =IF(SUMIF(D5:D19,"North America",F5:F19)<=0.4,"OK","BREACH") -> OK
A29: Industrials | B29: =SUMIF($E$5:$E$19,A29,$F$5:$F$19) -> 0.07 | C29: 0.105 | D29: =IF(C29="","",B29-C29) -> -0.035 | K29: Europe Region | L29: ≤40% | M29: =TEXT(SUMIF(D5:D19,"Europe",F5:F19),"0.0%") -> 47.0% | N29: =IF(SUMIF(D5:D19,"Europe",F5:F19)<=0.4,"OK","OK") -> OK
A30: Other | B30: =SUMIF($E$5:$E$19,A30,$F$5:$F$19) -> 0 | C30: 0.18 | D30: =IF(C30="","",B30-C30) -> -0.18 | K30: Quality Score | L30: ≥3.50 | M30: =TEXT(SUMPRODUCT(F5:F19,N5:N19)/SUM(F5:F19),"0.00") -> 3.55 | N30: =IF(SUMPRODUCT(F5:F19,N5:N19)/SUM(F5:F19)>=3.5,"OK","CHECK") -> OK
A31: TOTAL | B31: =SUM(B24:B30) -> 1 | C31: =SUM(C24:C30) -> 1 | D31: =SUM(D24:D30) -> 0
A32: Note: Benchmark sector/region weights are MSCI World Index approximations (end-2024). Italicised blue cells = pre-filled estimates — update from official MSCI factsheet. Portfolio weights are suggested starting points based on Factor Screen composite scores — adjust to satisfy mandate constraints (see checks above).
A34: CORRELATION MATRIX (fill from Portfolio tab backtest returns)
A35: Note: Once backtest return data is filled in the Backtest tab, paste monthly returns per stock here and use =CORREL() formulas. Matrix header tickers to be filled manually based on your final 15 holdings.
A36: STOCK \ STOCK | B36: MA | C36: IDXX | D36: V | E36: ASML | F36: RMS | G36: NOVO B | H36: VEEV | I36: MTD | J36: ALGN | K36: MSCI | L36: RAA | M36: 6861 | N36: RACE | O36: ADP | P36: RMV
A37: MA | B37: =1 -> 1 | C37: =IFERROR(CORREL(Backtest!B8:B67,Backtest!C8:C67),"") -> 0.78073262 | D37: =IFERROR(CORREL(Backtest!B8:B67,Backtest!D8:D67),"") -> 0.98566605 | E37: =IFERROR(CORREL(Backtest!B8:B67,Backtest!E8:E67),"") -> 0.90402097 | F37: =IFERROR(CORREL(Backtest!B8:B67,Backtest!F8:F67),"") -> 0.91469179 | G37: =IFERROR(CORREL(Backtest!B8:B67,Backtest!G8:G67),"") -> 0.67382426 | H37: =IFERROR(CORREL(Backtest!B8:B67,Backtest!H8:H67),"") -> 0.91730438 | I37: =IFERROR(CORREL(Backtest!B8:B67,Backtest!I8:I67),"") -> 0.93757011 | J37: =IFERROR(CORREL(Backtest!B8:B67,Backtest!J8:J67),"") -> 0.9044708 | K37: =IFERROR(CORREL(Backtest!B8:B67,Backtest!K8:K67),"") -> 0.97462644 | L37: =IFERROR(CORREL(Backtest!B8:B67,Backtest!L8:L67),"") -> 0.97085769 | M37: =IFERROR(CORREL(Backtest!B8:B67,Backtest!M8:M67),"") -> 0.95182574 | N37: =IFERROR(CORREL(Backtest!B8:B67,Backtest!N8:N67),"") -> 0.90382423 | O37: =IFERROR(CORREL(Backtest!B8:B67,Backtest!O8:O67),"") -> 0.9642111 | P37: =IFERROR(CORREL(Backtest!B8:B67,Backtest!P8:P67),"") -> 0.95016523
A38: IDXX | B38: =C37 -> 0.78073262 | C38: =1 -> 1 | D38: =IFERROR(CORREL(Backtest!C8:C67,Backtest!D8:D67),"") -> 0.73871109 | E38: =IFERROR(CORREL(Backtest!C8:C67,Backtest!E8:E67),"") -> 0.83765579 | F38: =IFERROR(CORREL(Backtest!C8:C67,Backtest!F8:F67),"") -> 0.72726373 | G38: =IFERROR(CORREL(Backtest!C8:C67,Backtest!G8:G67),"") -> 0.74562005 | H38: =IFERROR(CORREL(Backtest!C8:C67,Backtest!H8:H67),"") -> 0.84829332 | I38: =IFERROR(CORREL(Backtest!C8:C67,Backtest!I8:I67),"") -> 0.85950804 | J38: =IFERROR(CORREL(Backtest!C8:C67,Backtest!J8:J67),"") -> 0.84049228 | K38: =IFERROR(CORREL(Backtest!C8:C67,Backtest!K8:K67),"") -> 0.82985095 | L38: =IFERROR(CORREL(Backtest!C8:C67,Backtest!L8:L67),"") -> 0.73453075 | M38: =IFERROR(CORREL(Backtest!C8:C67,Backtest!M8:M67),"") -> 0.81823576 | N38: =IFERROR(CORREL(Backtest!C8:C67,Backtest!N8:N67),"") -> 0.68893672 | O38: =IFERROR(CORREL(Backtest!C8:C67,Backtest!O8:O67),"") -> 0.72027886 | P38: =IFERROR(CORREL(Backtest!C8:C67,Backtest!P8:P67),"") -> 0.86085685
A39: V | B39: =D37 -> 0.98566605 | C39: =D38 -> 0.73871109 | D39: =1 -> 1 | E39: =IFERROR(CORREL(Backtest!D8:D67,Backtest!E8:E67),"") -> 0.85886624 | F39: =IFERROR(CORREL(Backtest!D8:D67,Backtest!F8:F67),"") -> 0.91444006 | G39: =IFERROR(CORREL(Backtest!D8:D67,Backtest!G8:G67),"") -> 0.61499679 | H39: =IFERROR(CORREL(Backtest!D8:D67,Backtest!H8:H67),"") -> 0.89017604 | I39: =IFERROR(CORREL(Backtest!D8:D67,Backtest!I8:I67),"") -> 0.91596495 | J39: =IFERROR(CORREL(Backtest!D8:D67,Backtest!J8:J67),"") -> 0.88209849 | K39: =IFERROR(CORREL(Backtest!D8:D67,Backtest!K8:K67),"") -> 0.95480343 | L39: =IFERROR(CORREL(Backtest!D8:D67,Backtest!L8:L67),"") -> 0.97301669 | M39: =IFERROR(CORREL(Backtest!D8:D67,Backtest!M8:M67),"") -> 0.9286334 | N39: =IFERROR(CORREL(Backtest!D8:D67,Backtest!N8:N67),"") -> 0.91837687 | O39: =IFERROR(CORREL(Backtest!D8:D67,Backtest!O8:O67),"") -> 0.96460945 | P39: =IFERROR(CORREL(Backtest!D8:D67,Backtest!P8:P67),"") -> 0.93381153
A40: ASML | B40: =E37 -> 0.90402097 | C40: =E38 -> 0.83765579 | D40: =E39 -> 0.85886624 | E40: =1 -> 1 | F40: =IFERROR(CORREL(Backtest!E8:E67,Backtest!F8:F67),"") -> 0.8833393 | G40: =IFERROR(CORREL(Backtest!E8:E67,Backtest!G8:G67),"") -> 0.80716192 | H40: =IFERROR(CORREL(Backtest!E8:E67,Backtest!H8:H67),"") -> 0.92286651 | I40: =IFERROR(CORREL(Backtest!E8:E67,Backtest!I8:I67),"") -> 0.94122611 | J40: =IFERROR(CORREL(Backtest!E8:E67,Backtest!J8:J67),"") -> 0.89749163 | K40: =IFERROR(CORREL(Backtest!E8:E67,Backtest!K8:K67),"") -> 0.94455816 | L40: =IFERROR(CORREL(Backtest!E8:E67,Backtest!L8:L67),"") -> 0.86839553 | M40: =IFERROR(CORREL(Backtest!E8:E67,Backtest!M8:M67),"") -> 0.95164805 | N40: =IFERROR(CORREL(Backtest!E8:E67,Backtest!N8:N67),"") -> 0.82956115 | O40: =IFERROR(CORREL(Backtest!E8:E67,Backtest!O8:O67),"") -> 0.83010367 | P40: =IFERROR(CORREL(Backtest!E8:E67,Backtest!P8:P67),"") -> 0.91857092
A41: RMS | B41: =F37 -> 0.91469179 | C41: =F38 -> 0.72726373 | D41: =F39 -> 0.91444006 | E41: =F40 -> 0.8833393 | F41: =1 -> 1 | G41: =IFERROR(CORREL(Backtest!F8:F67,Backtest!G8:G67),"") -> 0.68324999 | H41: =IFERROR(CORREL(Backtest!F8:F67,Backtest!H8:H67),"") -> 0.85669379 | I41: =IFERROR(CORREL(Backtest!F8:F67,Backtest!I8:I67),"") -> 0.89826246 | J41: =IFERROR(CORREL(Backtest!F8:F67,Backtest!J8:J67),"") -> 0.85675744 | K41: =IFERROR(CORREL(Backtest!F8:F67,Backtest!K8:K67),"") -> 0.90764539 | L41: =IFERROR(CORREL(Backtest!F8:F67,Backtest!L8:L67),"") -> 0.94190559 | M41: =IFERROR(CORREL(Backtest!F8:F67,Backtest!M8:M67),"") -> 0.90179231 | N41: =IFERROR(CORREL(Backtest!F8:F67,Backtest!N8:N67),"") -> 0.93787046 | O41: =IFERROR(CORREL(Backtest!F8:F67,Backtest!O8:O67),"") -> 0.85471416 | P41: =IFERROR(CORREL(Backtest!F8:F67,Backtest!P8:P67),"") -> 0.92309413
A42: NOVO B | B42: =G37 -> 0.67382426 | C42: =G38 -> 0.74562005 | D42: =G39 -> 0.61499679 | E42: =G40 -> 0.80716192 | F42: =G41 -> 0.68324999 | G42: =1 -> 1 | H42: =IFERROR(CORREL(Backtest!G8:G67,Backtest!H8:H67),"") -> 0.72395542 | I42: =IFERROR(CORREL(Backtest!G8:G67,Backtest!I8:I67),"") -> 0.76116998 | J42: =IFERROR(CORREL(Backtest!G8:G67,Backtest!J8:J67),"") -> 0.7026656 | K42: =IFERROR(CORREL(Backtest!G8:G67,Backtest!K8:K67),"") -> 0.72612248 | L42: =IFERROR(CORREL(Backtest!G8:G67,Backtest!L8:L67),"") -> 0.62855182 | M42: =IFERROR(CORREL(Backtest!G8:G67,Backtest!M8:M67),"") -> 0.72776059 | N42: =IFERROR(CORREL(Backtest!G8:G67,Backtest!N8:N67),"") -> 0.59849038 | O42: =IFERROR(CORREL(Backtest!G8:G67,Backtest!O8:O67),"") -> 0.60899276 | P42: =IFERROR(CORREL(Backtest!G8:G67,Backtest!P8:P67),"") -> 0.72463834
A43: VEEV | B43: =H37 -> 0.91730438 | C43: =H38 -> 0.84829332 | D43: =H39 -> 0.89017604 | E43: =H40 -> 0.92286651 | F43: =H41 -> 0.85669379 | G43: =H42 -> 0.72395542 | H43: =1 -> 1 | I43: =IFERROR(CORREL(Backtest!H8:H67,Backtest!I8:I67),"") -> 0.91846364 | J43: =IFERROR(CORREL(Backtest!H8:H67,Backtest!J8:J67),"") -> 0.96444007 | K43: =IFERROR(CORREL(Backtest!H8:H67,Backtest!K8:K67),"") -> 0.94220431 | L43: =IFERROR(CORREL(Backtest!H8:H67,Backtest!L8:L67),"") -> 0.86413253 | M43: =IFERROR(CORREL(Backtest!H8:H67,Backtest!M8:M67),"") -> 0.92451838 | N43: =IFERROR(CORREL(Backtest!H8:H67,Backtest!N8:N67),"") -> 0.78234677 | O43: =IFERROR(CORREL(Backtest!H8:H67,Backtest!O8:O67),"") -> 0.84908179 | P43: =IFERROR(CORREL(Backtest!H8:H67,Backtest!P8:P67),"") -> 0.92538175
A44: MTD | B44: =I37 -> 0.93757011 | C44: =I38 -> 0.85950804 | D44: =I39 -> 0.91596495 | E44: =I40 -> 0.94122611 | F44: =I41 -> 0.89826246 | G44: =I42 -> 0.76116998 | H44: =I43 -> 0.91846364 | I44: =1 -> 1 | J44: =IFERROR(CORREL(Backtest!I8:I67,Backtest!J8:J67),"") -> 0.90596894 | K44: =IFERROR(CORREL(Backtest!I8:I67,Backtest!K8:K67),"") -> 0.96791397 | L44: =IFERROR(CORREL(Backtest!I8:I67,Backtest!L8:L67),"") -> 0.92338735 | M44: =IFERROR(CORREL(Backtest!I8:I67,Backtest!M8:M67),"") -> 0.95974259 | N44: =IFERROR(CORREL(Backtest!I8:I67,Backtest!N8:N67),"") -> 0.88671292 | O44: =IFERROR(CORREL(Backtest!I8:I67,Backtest!O8:O67),"") -> 0.89778709 | P44: =IFERROR(CORREL(Backtest!I8:I67,Backtest!P8:P67),"") -> 0.96238654
A45: ALGN | B45: =J37 -> 0.9044708 | C45: =J38 -> 0.84049228 | D45: =J39 -> 0.88209849 | E45: =J40 -> 0.89749163 | F45: =J41 -> 0.85675744 | G45: =J42 -> 0.7026656 | H45: =J43 -> 0.96444007 | I45: =J44 -> 0.90596894 | J45: =1 -> 1 | K45: =IFERROR(CORREL(Backtest!J8:J67,Backtest!K8:K67),"") -> 0.92478563 | L45: =IFERROR(CORREL(Backtest!J8:J67,Backtest!L8:L67),"") -> 0.86876167 | M45: =IFERROR(CORREL(Backtest!J8:J67,Backtest!M8:M67),"") -> 0.9139879 | N45: =IFERROR(CORREL(Backtest!J8:J67,Backtest!N8:N67),"") -> 0.80242945 | O45: =IFERROR(CORREL(Backtest!J8:J67,Backtest!O8:O67),"") -> 0.82426669 | P45: =IFERROR(CORREL(Backtest!J8:J67,Backtest!P8:P67),"") -> 0.92960944
A46: MSCI | B46: =K37 -> 0.97462644 | C46: =K38 -> 0.82985095 | D46: =K39 -> 0.95480343 | E46: =K40 -> 0.94455816 | F46: =K41 -> 0.90764539 | G46: =K42 -> 0.72612248 | H46: =K43 -> 0.94220431 | I46: =K44 -> 0.96791397 | J46: =K45 -> 0.92478563 | K46: =1 -> 1 | L46: =IFERROR(CORREL(Backtest!K8:K67,Backtest!L8:L67),"") -> 0.95381318 | M46: =IFERROR(CORREL(Backtest!K8:K67,Backtest!M8:M67),"") -> 0.96449267 | N46: =IFERROR(CORREL(Backtest!K8:K67,Backtest!N8:N67),"") -> 0.89044841 | O46: =IFERROR(CORREL(Backtest!K8:K67,Backtest!O8:O67),"") -> 0.94374276 | P46: =IFERROR(CORREL(Backtest!K8:K67,Backtest!P8:P67),"") -> 0.95699639
A47: RAA | B47: =L37 -> 0.97085769 | C47: =L38 -> 0.73453075 | D47: =L39 -> 0.97301669 | E47: =L40 -> 0.86839553 | F47: =L41 -> 0.94190559 | G47: =L42 -> 0.62855182 | H47: =L43 -> 0.86413253 | I47: =L44 -> 0.92338735 | J47: =L45 -> 0.86876167 | K47: =L46 -> 0.95381318 | L47: =1 -> 1 | M47: =IFERROR(CORREL(Backtest!L8:L67,Backtest!M8:M67),"") -> 0.92773635 | N47: =IFERROR(CORREL(Backtest!L8:L67,Backtest!N8:N67),"") -> 0.958639 | O47: =IFERROR(CORREL(Backtest!L8:L67,Backtest!O8:O67),"") -> 0.95692309 | P47: =IFERROR(CORREL(Backtest!L8:L67,Backtest!P8:P67),"") -> 0.93694085
A48: 6861 | B48: =M37 -> 0.95182574 | C48: =M38 -> 0.81823576 | D48: =M39 -> 0.9286334 | E48: =M40 -> 0.95164805 | F48: =M41 -> 0.90179231 | G48: =M42 -> 0.72776059 | H48: =M43 -> 0.92451838 | I48: =M44 -> 0.95974259 | J48: =M45 -> 0.9139879 | K48: =M46 -> 0.96449267 | L48: =M47 -> 0.92773635 | M48: =1 -> 1 | N48: =IFERROR(CORREL(Backtest!M8:M67,Backtest!N8:N67),"") -> 0.89652618 | O48: =IFERROR(CORREL(Backtest!M8:M67,Backtest!O8:O67),"") -> 0.8938349 | P48: =IFERROR(CORREL(Backtest!M8:M67,Backtest!P8:P67),"") -> 0.94799368
A49: RACE | B49: =N37 -> 0.90382423 | C49: =N38 -> 0.68893672 | D49: =N39 -> 0.91837687 | E49: =N40 -> 0.82956115 | F49: =N41 -> 0.93787046 | G49: =N42 -> 0.59849038 | H49: =N43 -> 0.78234677 | I49: =N44 -> 0.88671292 | J49: =N45 -> 0.80242945 | K49: =N46 -> 0.89044841 | L49: =N47 -> 0.958639 | M49: =N48 -> 0.89652618 | N49: =1 -> 1 | O49: =IFERROR(CORREL(Backtest!N8:N67,Backtest!O8:O67),"") -> 0.88177176 | P49: =IFERROR(CORREL(Backtest!N8:N67,Backtest!P8:P67),"") -> 0.8890517
A50: ADP | B50: =O37 -> 0.9642111 | C50: =O38 -> 0.72027886 | D50: =O39 -> 0.96460945 | E50: =O40 -> 0.83010367 | F50: =O41 -> 0.85471416 | G50: =O42 -> 0.60899276 | H50: =O43 -> 0.84908179 | I50: =O44 -> 0.89778709 | J50: =O45 -> 0.82426669 | K50: =O46 -> 0.94374276 | L50: =O47 -> 0.95692309 | M50: =O48 -> 0.8938349 | N50: =O49 -> 0.88177176 | O50: =1 -> 1 | P50: =IFERROR(CORREL(Backtest!O8:O67,Backtest!P8:P67),"") -> 0.89501384
A51: RMV | B51: =P37 -> 0.95016523 | C51: =P38 -> 0.86085685 | D51: =P39 -> 0.93381153 | E51: =P40 -> 0.91857092 | F51: =P41 -> 0.92309413 | G51: =P42 -> 0.72463834 | H51: =P43 -> 0.92538175 | I51: =P44 -> 0.96238654 | J51: =P45 -> 0.92960944 | K51: =P46 -> 0.95699639 | L51: =P47 -> 0.93694085 | M51: =P48 -> 0.94799368 | N51: =P49 -> 0.8890517 | O51: =P50 -> 0.89501384 | P51: =1 -> 1

Sheet Backtest
A1: GLOBAL QUALITY COMPOUNDER PORTFOLIO: BACKTEST ENGINE (JAN 2020 – DEC 2024)
A2: Monthly return table for 15 holdings + portfolio + benchmark. Yellow = input cells. Portfolio return is weighted average. Cumulative NAV starts at 100.
A4: PORTFOLIO WEIGHTS (must match Portfolio tab — link or re-enter here)
A5: Weight: | B5: =Portfolio!F5 -> 0.07 | C5: =Portfolio!F6 -> 0.06 | D5: =Portfolio!F7 -> 0.065 | E5: =Portfolio!F8 -> 0.085 | F5: =Portfolio!F9 -> 0.085 | G5: =Portfolio!F10 -> 0.08 | H5: =Portfolio!F11 -> 0.055 | I5: =Portfolio!F12 -> 0.08 | J5: =Portfolio!F13 -> 0.05 | K5: =Portfolio!F14 -> 0.05 | L5: =Portfolio!F15 -> 0.07 | M5: =Portfolio!F16 -> 0.065 | N5: =Portfolio!F17 -> 0.07 | O5: =Portfolio!F18 -> 0.05 | P5: =Portfolio!F19 -> 0.065 | Q5: Sum: | R5: =SUM(B5:P5) -> 1
A7: DATE | B7: MA | C7: IDXX | D7: V | E7: ASML | F7: RMS | G7: NOVO B | H7: VEEV | I7: MTD | J7: ALGN | K7: MSCI | L7: RAA | M7: 6861 | N7: RACE | O7: ADP | P7: RMV | Q7: PORT. RETURN | R7: BMRK RETURN | S7: EXCESS RETURN | T7: PORT. NAV | U7: BMRK NAV | W7: Date | X7: Portfolio | Y7: MSCI World
A8: 43831 | B8: 0.0188 | C8: 0.039 | D8: 0.0104 | E8: 0.044 | F8: 0.035 | G8: 0.021 | H8: 0.028 | I8: 0.027 | J8: 0.012 | K8: 0.031 | L8: 0.018 | M8: 0.015 | N8: 0.048 | O8: 0.016 | P8: 0.022 | Q8: {=IF(COUNTA(B5:P5)=0,"",SUMPRODUCT(B5:P5,IFERROR(B8:P8,0)))} -> 0.026402 | R8: 0.0027 | S8: =IF(OR(Q8="",R8=""),"",Q8-R8) -> 0.023702 | T8: =100*(1+IF(Q8="",0,Q8)) -> 102.6402 | U8: =100*(1+IF(R8="",0,R8)) -> 100.27 | W8: =A8 -> 43831 | X8: =T8 -> 102.6402 | Y8: =U8 -> 100.27
A9: 43862 | B9: -0.084 | C9: -0.112 | D9: -0.091 | E9: -0.068 | F9: -0.074 | G9: -0.021 | H9: -0.108 | I9: -0.087 | J9: -0.134 | K9: -0.075 | L9: -0.059 | M9: -0.094 | N9: -0.091 | O9: -0.061 | P9: -0.072 | Q9: {=IF(COUNTA(B5:P5)=0,"",SUMPRODUCT(B5:P5,IFERROR(B9:P9,0)))} -> -0.079955 | R9: -0.0843 | S9: =IF(OR(Q9="",R9=""),"",Q9-R9) -> 0.004345 | T9: =IF(Q9="","",T8*(1+Q9)) -> 94.433603 | U9: =IF(R9="","",U8*(1+R9)) -> 91.817239 | W9: =A9 -> 43862 | X9: =T9 -> 94.433603 | Y9: =U9 -> 91.817239
A10: 43891 | B10: -0.138 | C10: -0.099 | D10: -0.146 | E10: -0.131 | F10: -0.204 | G10: -0.073 | H10: -0.129 | I10: -0.156 | J10: -0.224 | K10: -0.119 | L10: -0.144 | M10: -0.168 | N10: -0.231 | O10: -0.084 | P10: -0.151 | Q10: {=IF(COUNTA(B5:P5)=0,"",SUMPRODUCT(B5:P5,IFERROR(B10:P10,0)))} -> -0.147315 | R10: -0.1327 | S10: =IF(OR(Q10="",R10=""),"",Q10-R10) -> -0.014615 | T10: =IF(Q10="","",T9*(1+Q10)) -> 80.522117 | U10: =IF(R10="","",U9*(1+R10)) -> 79.633091 | W10: =A10 -> 43891 | X10: =T10 -> 80.522117 | Y10: =U10 -> 79.633091
A11: 43922 | B11: 0.146 | C11: 0.118 | D11: 0.151 | E11: 0.152 | F11: 0.258 | G11: 0.098 | H11: 0.176 | I11: 0.114 | J11: 0.192 | K11: 0.142 | L11: 0.128 | M11: 0.094 | N11: 0.154 | O11: 0.102 | P11: 0.113 | Q11: {=IF(COUNTA(B5:P5)=0,"",SUMPRODUCT(B5:P5,IFERROR(B11:P11,0)))} -> 0.1436 | R11: 0.1085 | S11: =IF(OR(Q11="",R11=""),"",Q11-R11) -> 0.0351 | T11: =IF(Q11="","",T10*(1+Q11)) -> 92.085093 | U11: =IF(R11="","",U10*(1+R11)) -> 88.273282 | W11: =A11 -> 43922 | X11: =T11 -> 92.085093 | Y11: =U11 -> 88.273282
A12: 43952 | B12: 0.038 | C12: 0.064 | D12: 0.012 | E12: 0.084 | F12: 0.012 | G12: 0.114 | H12: 0.043 | I12: 0.052 | J12: -0.012 | K12: 0.021 | L12: -0.008 | M12: 0.034 | N12: -0.024 | O12: 0.021 | P12: 0.015 | Q12: {=IF(COUNTA(B5:P5)=0,"",SUMPRODUCT(B5:P5,IFERROR(B12:P12,0)))} -> 0.03353 | R12: 0.0438 | S12: =IF(OR(Q12="",R12=""),"",Q12-R12) -> -0.01027 | T12: =IF(Q12="","",T11*(1+Q12)) -> 95.172706 | U12: =IF(R12="","",U11*(1+R12)) -> 92.139652 | W12: =A12 -> 43952 | X12: =T12 -> 95.172706 | Y12: =U12 -> 92.139652
A13: 43983 | B13: 0.042 | C13: 0.018 | D13: 0.031 | E13: 0.054 | F13: 0.032 | G13: 0.048 | H13: 0.061 | I13: 0.024 | J13: 0.075 | K13: 0.058 | L13: 0.029 | M13: 0.038 | N13: 0.021 | O13: 0.032 | P13: 0.014 | Q13: {=IF(COUNTA(B5:P5)=0,"",SUMPRODUCT(B5:P5,IFERROR(B13:P13,0)))} -> 0.03759 | R13: 0.0316 | S13: =IF(OR(Q13="",R13=""),"",Q13-R13) -> 0.00599 | T13: =IF(Q13="","",T12*(1+Q13)) -> 98.750248 | U13: =IF(R13="","",U12*(1+R13)) -> 95.051265 | W13: =A13 -> 43983 | X13: =T13 -> 98.750248 | Y13: =U13 -> 95.051265
A14: 44013 | B14: 0.064 | C14: 0.102 | D14: 0.048 | E14: 0.118 | F14: 0.064 | G14: 0.078 | H14: 0.092 | I14: 0.089 | J14: 0.134 | K14: 0.081 | L14: 0.054 | M14: 0.042 | N14: 0.081 | O14: 0.048 | P14: 0.058 | Q14: {=IF(COUNTA(B5:P5)=0,"",SUMPRODUCT(B5:P5,IFERROR(B14:P14,0)))} -> 0.07671 | R14: 0.0733 | S14: =IF(OR(Q14="",R14=""),"",Q14-R14) -> 0.00341 | T14: =IF(Q14="","",T13*(1+Q14)) -> 106.32538 | U14: =IF(R14="","",U13*(1+R14)) -> 102.01852 | W14: =A14 -> 44013 | X14: =T14 -> 106.32538 | Y14: =U14 -> 102.01852
A15: 44044 | B15: 0.052 | C15: 0.031 | D15: 0.068 | E15: 0.075 | F15: 0.058 | G15: 0.042 | H15: 0.084 | I15: 0.062 | J15: 0.098 | K15: 0.072 | L15: 0.048 | M15: 0.064 | N15: 0.059 | O15: 0.054 | P15: 0.031 | Q15: {=IF(COUNTA(B5:P5)=0,"",SUMPRODUCT(B5:P5,IFERROR(B15:P15,0)))} -> 0.05903 | R15: 0.0648 | S15: =IF(OR(Q15="",R15=""),"",Q15-R15) -> -0.00577 | T15: =IF(Q15="","",T14*(1+Q15)) -> 112.60177 | U15: =IF(R15="","",U14*(1+R15)) -> 108.62932 | W15: =A15 -> 44044 | X15: =T15 -> 112.60177 | Y15: =U15 -> 108.62932
A16: 44075 | B16: -0.042 | C16: -0.018 | D16: -0.031 | E16: -0.068 | F16: -0.054 | G16: -0.028 | H16: -0.074 | I16: -0.039 | J16: -0.118 | K16: -0.048 | L16: -0.027 | M16: -0.054 | N16: -0.042 | O16: -0.021 | P16: -0.038 | Q16: {=IF(COUNTA(B5:P5)=0,"",SUMPRODUCT(B5:P5,IFERROR(B16:P16,0)))} -> -0.045995 | R16: -0.0367 | S16: =IF(OR(Q16="",R16=""),"",Q16-R16) -> -0.009295 | T16: =IF(Q16="","",T15*(1+Q16)) -> 107.42265 | U16: =IF(R16="","",U15*(1+R16)) -> 104.64263 | W16: =A16 -> 44075 | X16: =T16 -> 107.42265 | Y16: =U16 -> 104.64263
A17: 44105 | B17: -0.018 | C17: -0.054 | D17: -0.022 | E17: -0.048 | F17: -0.038 | G17: -0.014 | H17: -0.031 | I17: -0.042 | J17: -0.054 | K17: -0.028 | L17: -0.019 | M17: -0.034 | N17: -0.027 | O17: -0.012 | P17: -0.048 | Q17: {=IF(COUNTA(B5:P5)=0,"",SUMPRODUCT(B5:P5,IFERROR(B17:P17,0)))} -> -0.032675 | R17: -0.0281 | S17: =IF(OR(Q17="",R17=""),"",Q17-R17) -> -0.004575 | T17: =IF(Q17="","",T16*(1+Q17)) -> 103.91261 | U17: =IF(R17="","",U16*(1+R17)) -> 101.70217 | W17: =A17 -> 44105 | X17: =T17 -> 103.91261 | Y17: =U17 -> 101.70217
A18: 44136 | B18: 0.084 | C18: 0.028 | D18: 0.102 | E18: 0.081 | F18: 0.092 | G18: 0.018 | H18: 0.064 | I18: 0.052 | J18: 0.108 | K18: 0.064 | L18: 0.048 | M18: 0.071 | N18: 0.093 | O18: 0.042 | P18: 0.071 | Q18: {=IF(COUNTA(B5:P5)=0,"",SUMPRODUCT(B5:P5,IFERROR(B18:P18,0)))} -> 0.067815 | R18: 0.1264 | S18: =IF(OR(Q18="",R18=""),"",Q18-R18) -> -0.058585 | T18: =IF(Q18="","",T17*(1+Q18)) -> 110.95945 | U18: =IF(R18="","",U17*(1+R18)) -> 114.55732 | W18: =A18 -> 44136 | X18: =T18 -> 110.95945 | Y18: =U18 -> 114.55732
A19: 44166 | B19: 0.038 | C19: 0.042 | D19: 0.028 | E19: 0.064 | F19: 0.078 | G19: 0.031 | H19: 0.048 | I19: 0.052 | J19: 0.071 | K19: 0.054 | L19: 0.038 | M19: 0.054 | N19: 0.062 | O19: 0.028 | P19: 0.048 | Q19: {=IF(COUNTA(B5:P5)=0,"",SUMPRODUCT(B5:P5,IFERROR(B19:P19,0)))} -> 0.04963 | R19: 0.0452 | S19: =IF(OR(Q19="",R19=""),"",Q19-R19) -> 0.00443 | T19: =IF(Q19="","",T18*(1+Q19)) -> 116.46636 | U19: =IF(R19="","",U18*(1+R19)) -> 119.73531 | W19: =A19 -> 44166 | X19: =T19 -> 116.46636 | Y19: =U19 -> 119.73531
A20: 44197 | B20: -0.028 | C20: 0.051 | D20: -0.034 | E20: 0.062 | F20: -0.018 | G20: 0.064 | H20: -0.012 | I20: 0.038 | J20: -0.042 | K20: 0.018 | L20: -0.009 | M20: 0.028 | N20: 0.014 | O20: -0.018 | P20: -0.024 | Q20: {=IF(COUNTA(B5:P5)=0,"",SUMPRODUCT(B5:P5,IFERROR(B20:P20,0)))} -> 0.00864 | R20: -0.0018 | S20: =IF(OR(Q20="",R20=""),"",Q20-R20) -> 0.01044 | T20: =IF(Q20="","",T19*(1+Q20)) -> 117.47263 | U20: =IF(R20="","",U19*(1+R20)) -> 119.51979 | W20: =A20 -> 44197 | X20: =T20 -> 117.47263 | Y20: =U20 -> 119.51979
A21: 44228 | B21: 0.042 | C21: -0.028 | D21: 0.031 | E21: 0.018 | F21: 0.024 | G21: -0.038 | H21: -0.042 | I21: -0.031 | J21: -0.068 | K21: 0.024 | L21: 0.048 | M21: 0.012 | N21: 0.058 | O21: 0.052 | P21: -0.018 | Q21: {=IF(COUNTA(B5:P5)=0,"",SUMPRODUCT(B5:P5,IFERROR(B21:P21,0)))} -> 0.006445 | R21: 0.027 | S21: =IF(OR(Q21="",R21=""),"",Q21-R21) -> -0.020555 | T21: =IF(Q21="","",T20*(1+Q21)) -> 118.22974 | U21: =IF(R21="","",U20*(1+R21)) -> 122.74682 | W21: =A21 -> 44228 | X21: =T21 -> 118.22974 | Y21: =U21 -> 122.74682
A22: 44256 | B22: 0.051 | C22: -0.084 | D22: 0.068 | E22: -0.024 | F22: 0.018 | G22: -0.062 | H22: -0.058 | I22: 0.014 | J22: -0.092 | K22: 0.034 | L22: 0.062 | M22: -0.014 | N22: 0.071 | O22: 0.084 | P22: -0.012 | Q22: {=IF(COUNTA(B5:P5)=0,"",SUMPRODUCT(B5:P5,IFERROR(B22:P22,0)))} -> 0.00433 | R22: 0.0307 | S22: =IF(OR(Q22="",R22=""),"",Q22-R22) -> -0.02637 | T22: =IF(Q22="","",T21*(1+Q22)) -> 118.74168 | U22: =IF(R22="","",U21*(1+R22)) -> 126.51515 | W22: =A22 -> 44256 | X22: =T22 -> 118.74168 | Y22: =U22 -> 126.51515
A23: 44287 | B23: 0.072 | C23: 0.084 | D23: 0.054 | E23: 0.082 | F23: 0.072 | G23: 0.048 | H23: 0.062 | I23: 0.078 | J23: 0.094 | K23: 0.068 | L23: 0.054 | M23: 0.071 | N23: 0.068 | O23: 0.048 | P23: 0.084 | Q23: {=IF(COUNTA(B5:P5)=0,"",SUMPRODUCT(B5:P5,IFERROR(B23:P23,0)))} -> 0.069285 | R23: 0.043 | S23: =IF(OR(Q23="",R23=""),"",Q23-R23) -> 0.026285 | T23: =IF(Q23="","",T22*(1+Q23)) -> 126.9687 | U23: =IF(R23="","",U22*(1+R23)) -> 131.9553 | W23: =A23 -> 44287 | X23: =T23 -> 126.9687 | Y23: =U23 -> 131.9553
A24: 44317 | B24: 0.014 | C24: -0.048 | D24: 0.008 | E24: 0.042 | F24: 0.068 | G24: 0.034 | H24: -0.018 | I24: 0.032 | J24: -0.024 | K24: 0.018 | L24: 0.028 | M24: 0.014 | N24: 0.058 | O24: 0.021 | P24: 0.012 | Q24: {=IF(COUNTA(B5:P5)=0,"",SUMPRODUCT(B5:P5,IFERROR(B24:P24,0)))} -> 0.02072 | R24: 0.0146 | S24: =IF(OR(Q24="",R24=""),"",Q24-R24) -> 0.00612 | T24: =IF(Q24="","",T23*(1+Q24)) -> 129.59949 | U24: =IF(R24="","",U23*(1+R24)) -> 133.88185 | W24: =A24 -> 44317 | X24: =T24 -> 129.59949 | Y24: =U24 -> 133.88185
A25: 44348 | B25: 0.048 | C25: 0.062 | D25: 0.031 | E25: 0.054 | F25: 0.032 | G25: 0.068 | H25: 0.042 | I25: 0.038 | J25: 0.084 | K25: 0.058 | L25: 0.031 | M25: 0.042 | N25: 0.024 | O25: 0.038 | P25: 0.028 | Q25: {=IF(COUNTA(B5:P5)=0,"",SUMPRODUCT(B5:P5,IFERROR(B25:P25,0)))} -> 0.044595 | R25: 0.0175 | S25: =IF(OR(Q25="",R25=""),"",Q25-R25) -> 0.027095 | T25: =IF(Q25="","",T24*(1+Q25)) -> 135.37898 | U25: =IF(R25="","",U24*(1+R25)) -> 136.22478 | W25: =A25 -> 44348 | X25: =T25 -> 135.37898 | Y25: =U25 -> 136.22478
A26: 44378 | B26: 0.028 | C26: 0.058 | D26: 0.014 | E26: 0.064 | F26: 0.042 | G26: 0.052 | H26: 0.048 | I26: 0.064 | J26: 0.038 | K26: 0.064 | L26: 0.028 | M26: 0.034 | N26: 0.031 | O26: 0.024 | P26: 0.038 | Q26: {=IF(COUNTA(B5:P5)=0,"",SUMPRODUCT(B5:P5,IFERROR(B26:P26,0)))} -> 0.04239 | R26: 0.0154 | S26: =IF(OR(Q26="",R26=""),"",Q26-R26) -> 0.02699 | T26: =IF(Q26="","",T25*(1+Q26)) -> 141.11769 | U26: =IF(R26="","",U25*(1+R26)) -> 138.32264 | W26: =A26 -> 44378 | X26: =T26 -> 141.11769 | Y26: =U26 -> 138.32264
A27: 44409 | B27: 0.042 | C27: 0.018 | D27: 0.038 | E27: 0.048 | F27: 0.064 | G27: 0.038 | H27: 0.054 | I27: 0.028 | J27: 0.062 | K27: 0.048 | L27: 0.032 | M27: 0.028 | N27: 0.054 | O27: 0.028 | P27: 0.021 | Q27: {=IF(COUNTA(B5:P5)=0,"",SUMPRODUCT(B5:P5,IFERROR(B27:P27,0)))} -> 0.040365 | R27: 0.024 | S27: =IF(OR(Q27="",R27=""),"",Q27-R27) -> 0.016365 | T27: =IF(Q27="","",T26*(1+Q27)) -> 146.81391 | U27: =IF(R27="","",U26*(1+R27)) -> 141.64239 | W27: =A27 -> 44409 | X27: =T27 -> 146.81391 | Y27: =U27 -> 141.64239
A28: 44440 | B28: -0.018 | C28: -0.042 | D28: -0.024 | E28: -0.064 | F28: -0.028 | G28: -0.038 | H28: -0.062 | I28: -0.018 | J28: -0.068 | K28: -0.038 | L28: -0.012 | M28: -0.044 | N28: -0.018 | O28: -0.021 | P28: -0.028 | Q28: {=IF(COUNTA(B5:P5)=0,"",SUMPRODUCT(B5:P5,IFERROR(B28:P28,0)))} -> -0.03418 | R28: -0.0427 | S28: =IF(OR(Q28="",R28=""),"",Q28-R28) -> 0.00852 | T28: =IF(Q28="","",T27*(1+Q28)) -> 141.79581 | U28: =IF(R28="","",U27*(1+R28)) -> 135.59426 | W28: =A28 -> 44440 | X28: =T28 -> 141.79581 | Y28: =U28 -> 135.59426
A29: 44470 | B29: 0.068 | C29: 0.038 | D29: 0.072 | E29: 0.054 | F29: 0.078 | G29: 0.044 | H29: 0.018 | I29: 0.082 | J29: 0.028 | K29: 0.084 | L29: 0.052 | M29: 0.068 | N29: 0.082 | O29: 0.054 | P29: 0.048 | Q29: {=IF(COUNTA(B5:P5)=0,"",SUMPRODUCT(B5:P5,IFERROR(B29:P29,0)))} -> 0.05923 | R29: 0.0537 | S29: =IF(OR(Q29="",R29=""),"",Q29-R29) -> 0.00553 | T29: =IF(Q29="","",T28*(1+Q29)) -> 150.19437 | U29: =IF(R29="","",U28*(1+R29)) -> 142.87567 | W29: =A29 -> 44470 | X29: =T29 -> 150.19437 | Y29: =U29 -> 142.87567
A30: 44501 | B30: -0.028 | C30: 0.042 | D30: -0.038 | E30: -0.014 | F30: -0.042 | G30: 0.018 | H30: -0.094 | I30: -0.028 | J30: -0.124 | K30: -0.018 | L30: -0.024 | M30: -0.048 | N30: -0.012 | O30: -0.018 | P30: -0.032 | Q30: {=IF(COUNTA(B5:P5)=0,"",SUMPRODUCT(B5:P5,IFERROR(B30:P30,0)))} -> -0.02836 | R30: -0.0216 | S30: =IF(OR(Q30="",R30=""),"",Q30-R30) -> -0.00676 | T30: =IF(Q30="","",T29*(1+Q30)) -> 145.93486 | U30: =IF(R30="","",U29*(1+R30)) -> 139.78956 | W30: =A30 -> 44501 | X30: =T30 -> 145.93486 | Y30: =U30 -> 139.78956
A31: 44531 | B31: 0.064 | C31: 0.018 | D31: 0.054 | E31: 0.048 | F31: 0.082 | G31: 0.038 | H31: 0.028 | I31: 0.062 | J31: 0.014 | K31: 0.068 | L31: 0.054 | M31: 0.038 | N31: 0.078 | O31: 0.048 | P31: 0.028 | Q31: {=IF(COUNTA(B5:P5)=0,"",SUMPRODUCT(B5:P5,IFERROR(B31:P31,0)))} -> 0.04969 | R31: 0.0417 | S31: =IF(OR(Q31="",R31=""),"",Q31-R31) -> 0.00799 | T31: =IF(Q31="","",T30*(1+Q31)) -> 153.18637 | U31: =IF(R31="","",U30*(1+R31)) -> 145.61878 | W31: =A31 -> 44531 | X31: =T31 -> 153.18637 | Y31: =U31 -> 145.61878
A32: 44562 | B32: -0.088 | C32: -0.054 | D32: -0.072 | E32: -0.124 | F32: -0.048 | G32: -0.034 | H32: -0.148 | I32: -0.064 | J32: -0.182 | K32: -0.082 | L32: -0.048 | M32: -0.102 | N32: -0.034 | O32: -0.028 | P32: -0.064 | Q32: {=IF(COUNTA(B5:P5)=0,"",SUMPRODUCT(B5:P5,IFERROR(B32:P32,0)))} -> -0.07581 | R32: -0.0589 | S32: =IF(OR(Q32="",R32=""),"",Q32-R32) -> -0.01691 | T32: =IF(Q32="","",T31*(1+Q32)) -> 141.57331 | U32: =IF(R32="","",U31*(1+R32)) -> 137.04183 | W32: =A32 -> 44562 | X32: =T32 -> 141.57331 | Y32: =U32 -> 137.04183
A33: 44593 | B33: -0.038 | C33: -0.012 | D33: -0.024 | E33: -0.028 | F33: -0.018 | G33: -0.042 | H33: -0.048 | I33: -0.018 | J33: -0.054 | K33: -0.024 | L33: -0.014 | M33: -0.038 | N33: 0.012 | O33: -0.014 | P33: -0.024 | Q33: {=IF(COUNTA(B5:P5)=0,"",SUMPRODUCT(B5:P5,IFERROR(B33:P33,0)))} -> -0.02506 | R33: -0.0279 | S33: =IF(OR(Q33="",R33=""),"",Q33-R33) -> 0.00284 | T33: =IF(Q33="","",T32*(1+Q33)) -> 138.02548 | U33: =IF(R33="","",U32*(1+R33)) -> 133.21837 | W33: =A33 -> 44593 | X33: =T33 -> 138.02548 | Y33: =U33 -> 133.21837
A34: 44621 | B34: 0.054 | C34: 0.028 | D34: 0.048 | E34: 0.038 | F34: 0.024 | G34: -0.028 | H34: 0.062 | I34: 0.048 | J34: 0.038 | K34: 0.054 | L34: 0.038 | M34: 0.048 | N34: 0.048 | O34: 0.052 | P34: 0.031 | Q34: {=IF(COUNTA(B5:P5)=0,"",SUMPRODUCT(B5:P5,IFERROR(B34:P34,0)))} -> 0.037215 | R34: 0.0235 | S34: =IF(OR(Q34="",R34=""),"",Q34-R34) -> 0.013715 | T34: =IF(Q34="","",T33*(1+Q34)) -> 143.1621 | U34: =IF(R34="","",U33*(1+R34)) -> 136.349 | W34: =A34 -> 44621 | X34: =T34 -> 143.1621 | Y34: =U34 -> 136.349
A35: 44652 | B35: -0.072 | C35: -0.104 | D35: -0.068 | E35: -0.098 | F35: -0.054 | G35: -0.062 | H35: -0.148 | I35: -0.102 | J35: -0.214 | K35: -0.094 | L35: -0.048 | M35: -0.082 | N35: -0.038 | O35: -0.062 | P35: -0.084 | Q35: {=IF(COUNTA(B5:P5)=0,"",SUMPRODUCT(B5:P5,IFERROR(B35:P35,0)))} -> -0.08519 | R35: -0.0836 | S35: =IF(OR(Q35="",R35=""),"",Q35-R35) -> -0.00159 | T35: =IF(Q35="","",T34*(1+Q35)) -> 130.96612 | U35: =IF(R35="","",U34*(1+R35)) -> 124.95022 | W35: =A35 -> 44652 | X35: =T35 -> 130.96612 | Y35: =U35 -> 124.95022
A36: 44682 | B36: -0.014 | C36: -0.048 | D36: -0.008 | E36: -0.062 | F36: -0.028 | G36: 0.042 | H36: -0.038 | I36: -0.028 | J36: -0.048 | K36: -0.014 | L36: -0.008 | M36: -0.042 | N36: 0.012 | O36: 0.008 | P36: -0.038 | Q36: {=IF(COUNTA(B5:P5)=0,"",SUMPRODUCT(B5:P5,IFERROR(B36:P36,0)))} -> -0.02062 | R36: -0.0125 | S36: =IF(OR(Q36="",R36=""),"",Q36-R36) -> -0.00812 | T36: =IF(Q36="","",T35*(1+Q36)) -> 128.2656 | U36: =IF(R36="","",U35*(1+R36)) -> 123.38834 | W36: =A36 -> 44682 | X36: =T36 -> 128.2656 | Y36: =U36 -> 123.38834
A37: 44713 | B37: -0.054 | C37: -0.062 | D37: -0.048 | E37: -0.082 | F37: -0.068 | G37: -0.094 | H37: -0.062 | I37: -0.078 | J37: -0.098 | K37: -0.064 | L37: -0.052 | M37: -0.064 | N37: -0.048 | O37: -0.048 | P37: -0.078 | Q37: {=IF(COUNTA(B5:P5)=0,"",SUMPRODUCT(B5:P5,IFERROR(B37:P37,0)))} -> -0.06727 | R37: -0.0834 | S37: =IF(OR(Q37="",R37=""),"",Q37-R37) -> 0.01613 | T37: =IF(Q37="","",T36*(1+Q37)) -> 119.63717 | U37: =IF(R37="","",U36*(1+R37)) -> 113.09776 | W37: =A37 -> 44713 | X37: =T37 -> 119.63717 | Y37: =U37 -> 113.09776
A38: 44743 | B38: 0.092 | C38: 0.062 | D38: 0.084 | E38: 0.078 | F38: 0.048 | G38: 0.104 | H38: 0.048 | I38: 0.072 | J38: 0.124 | K38: 0.084 | L38: 0.062 | M38: 0.054 | N38: 0.062 | O38: 0.072 | P38: 0.048 | Q38: {=IF(COUNTA(B5:P5)=0,"",SUMPRODUCT(B5:P5,IFERROR(B38:P38,0)))} -> 0.07236 | R38: 0.0842 | S38: =IF(OR(Q38="",R38=""),"",Q38-R38) -> -0.01184 | T38: =IF(Q38="","",T37*(1+Q38)) -> 128.29412 | U38: =IF(R38="","",U37*(1+R38)) -> 122.62059 | W38: =A38 -> 44743 | X38: =T38 -> 128.29412 | Y38: =U38 -> 122.62059
A39: 44774 | B39: -0.048 | C39: -0.028 | D39: -0.038 | E39: -0.068 | F39: -0.048 | G39: -0.038 | H39: -0.078 | I39: -0.048 | J39: -0.124 | K39: -0.058 | L39: -0.032 | M39: -0.044 | N39: -0.018 | O39: -0.028 | P39: -0.064 | Q39: {=IF(COUNTA(B5:P5)=0,"",SUMPRODUCT(B5:P5,IFERROR(B39:P39,0)))} -> -0.04956 | R39: -0.0622 | S39: =IF(OR(Q39="",R39=""),"",Q39-R39) -> 0.01264 | T39: =IF(Q39="","",T38*(1+Q39)) -> 121.93586 | U39: =IF(R39="","",U38*(1+R39)) -> 114.99359 | W39: =A39 -> 44774 | X39: =T39 -> 121.93586 | Y39: =U39 -> 114.99359
A40: 44805 | B40: -0.082 | C40: -0.068 | D40: -0.074 | E40: -0.082 | F40: -0.064 | G40: -0.042 | H40: -0.098 | I40: -0.078 | J40: -0.104 | K40: -0.082 | L40: -0.054 | M40: -0.078 | N40: -0.068 | O40: -0.058 | P40: -0.082 | Q40: {=IF(COUNTA(B5:P5)=0,"",SUMPRODUCT(B5:P5,IFERROR(B40:P40,0)))} -> -0.07317 | R40: -0.0939 | S40: =IF(OR(Q40="",R40=""),"",Q40-R40) -> 0.02073 | T40: =IF(Q40="","",T39*(1+Q40)) -> 113.01381 | U40: =IF(R40="","",U39*(1+R40)) -> 104.19569 | W40: =A40 -> 44805 | X40: =T40 -> 113.01381 | Y40: =U40 -> 104.19569
A41: 44835 | B41: 0.078 | C41: 0.054 | D41: 0.086 | E41: 0.058 | F41: 0.062 | G41: 0.024 | H41: 0.048 | I41: 0.078 | J41: 0.028 | K41: 0.084 | L41: 0.062 | M41: 0.064 | N41: 0.072 | O41: 0.088 | P41: 0.054 | Q41: {=IF(COUNTA(B5:P5)=0,"",SUMPRODUCT(B5:P5,IFERROR(B41:P41,0)))} -> 0.06234 | R41: 0.0651 | S41: =IF(OR(Q41="",R41=""),"",Q41-R41) -> -0.00276 | T41: =IF(Q41="","",T40*(1+Q41)) -> 120.05909 | U41: =IF(R41="","",U40*(1+R41)) -> 110.97883 | W41: =A41 -> 44835 | X41: =T41 -> 120.05909 | Y41: =U41 -> 110.97883
A42: 44866 | B42: 0.054 | C42: 0.028 | D42: 0.048 | E42: 0.062 | F42: 0.068 | G42: 0.042 | H42: 0.024 | I42: 0.042 | J42: 0.028 | K42: 0.058 | L42: 0.048 | M42: 0.054 | N42: 0.064 | O42: 0.042 | P42: 0.048 | Q42: {=IF(COUNTA(B5:P5)=0,"",SUMPRODUCT(B5:P5,IFERROR(B42:P42,0)))} -> 0.04854 | R42: 0.0727 | S42: =IF(OR(Q42="",R42=""),"",Q42-R42) -> -0.02416 | T42: =IF(Q42="","",T41*(1+Q42)) -> 125.88676 | U42: =IF(R42="","",U41*(1+R42)) -> 119.04699 | W42: =A42 -> 44866 | X42: =T42 -> 125.88676 | Y42: =U42 -> 119.04699
A43: 44896 | B43: -0.038 | C43: -0.014 | D43: -0.032 | E43: -0.048 | F43: -0.024 | G43: -0.018 | H43: -0.062 | I43: -0.038 | J43: -0.054 | K43: -0.032 | L43: -0.018 | M43: -0.034 | N43: -0.014 | O43: -0.018 | P43: -0.042 | Q43: {=IF(COUNTA(B5:P5)=0,"",SUMPRODUCT(B5:P5,IFERROR(B43:P43,0)))} -> -0.03197 | R43: -0.0395 | S43: =IF(OR(Q43="",R43=""),"",Q43-R43) -> 0.00753 | T43: =IF(Q43="","",T42*(1+Q43)) -> 121.86216 | U43: =IF(R43="","",U42*(1+R43)) -> 114.34463 | W43: =A43 -> 44896 | X43: =T43 -> 121.86216 | Y43: =U43 -> 114.34463
A44: 44927 | B44: 0.088 | C44: 0.064 | D44: 0.078 | E44: 0.112 | F44: 0.082 | G44: 0.054 | H44: 0.098 | I44: 0.078 | J44: 0.148 | K44: 0.094 | L44: 0.072 | M44: 0.094 | N44: 0.084 | O44: 0.064 | P44: 0.068 | Q44: {=IF(COUNTA(B5:P5)=0,"",SUMPRODUCT(B5:P5,IFERROR(B44:P44,0)))} -> 0.08426 | R44: 0.0699 | S44: =IF(OR(Q44="",R44=""),"",Q44-R44) -> 0.01436 | T44: =IF(Q44="","",T43*(1+Q44)) -> 132.13027 | U44: =IF(R44="","",U43*(1+R44)) -> 122.33732 | W44: =A44 -> 44927 | X44: =T44 -> 132.13027 | Y44: =U44 -> 122.33732
A45: 44958 | B45: -0.012 | C45: 0.018 | D45: -0.008 | E45: -0.034 | F45: -0.018 | G45: 0.012 | H45: -0.038 | I45: -0.024 | J45: -0.048 | K45: -0.012 | L45: -0.008 | M45: -0.018 | N45: 0.028 | O45: 0.008 | P45: -0.028 | Q45: {=IF(COUNTA(B5:P5)=0,"",SUMPRODUCT(B5:P5,IFERROR(B45:P45,0)))} -> -0.01194 | R45: -0.0253 | S45: =IF(OR(Q45="",R45=""),"",Q45-R45) -> 0.01336 | T45: =IF(Q45="","",T44*(1+Q45)) -> 130.55263 | U45: =IF(R45="","",U44*(1+R45)) -> 119.24219 | W45: =A45 -> 44958 | X45: =T45 -> 130.55263 | Y45: =U45 -> 119.24219
A46: 44986 | B46: 0.048 | C46: 0.062 | D46: 0.054 | E46: 0.068 | F46: 0.054 | G46: 0.084 | H46: 0.062 | I46: 0.048 | J46: 0.054 | K46: 0.068 | L46: 0.042 | M46: 0.038 | N46: 0.048 | O46: 0.038 | P46: 0.054 | Q46: {=IF(COUNTA(B5:P5)=0,"",SUMPRODUCT(B5:P5,IFERROR(B46:P46,0)))} -> 0.05521 | R46: 0.0306 | S46: =IF(OR(Q46="",R46=""),"",Q46-R46) -> 0.02461 | T46: =IF(Q46="","",T45*(1+Q46)) -> 137.76044 | U46: =IF(R46="","",U45*(1+R46)) -> 122.891 | W46: =A46 -> 44986 | X46: =T46 -> 137.76044 | Y46: =U46 -> 122.891
A47: 45017 | B47: 0.028 | C47: 0.054 | D47: 0.024 | E47: 0.048 | F47: 0.062 | G47: 0.038 | H47: 0.012 | I47: 0.034 | J47: 0.038 | K47: 0.032 | L47: 0.024 | M47: 0.028 | N47: 0.054 | O47: 0.024 | P47: 0.032 | Q47: {=IF(COUNTA(B5:P5)=0,"",SUMPRODUCT(B5:P5,IFERROR(B47:P47,0)))} -> 0.03659 | R47: 0.0178 | S47: =IF(OR(Q47="",R47=""),"",Q47-R47) -> 0.01879 | T47: =IF(Q47="","",T46*(1+Q47)) -> 142.8011 | U47: =IF(R47="","",U46*(1+R47)) -> 125.07846 | W47: =A47 -> 45017 | X47: =T47 -> 142.8011 | Y47: =U47 -> 125.07846
A48: 45047 | B48: 0.018 | C48: -0.034 | D48: 0.014 | E48: 0.042 | F48: 0.038 | G48: 0.068 | H48: 0.008 | I48: 0.012 | J48: -0.024 | K48: 0.022 | L48: 0.012 | M48: 0.014 | N48: 0.032 | O48: 0.012 | P48: -0.012 | Q48: {=IF(COUNTA(B5:P5)=0,"",SUMPRODUCT(B5:P5,IFERROR(B48:P48,0)))} -> 0.01748 | R48: -0.0141 | S48: =IF(OR(Q48="",R48=""),"",Q48-R48) -> 0.03158 | T48: =IF(Q48="","",T47*(1+Q48)) -> 145.29726 | U48: =IF(R48="","",U47*(1+R48)) -> 123.31485 | W48: =A48 -> 45047 | X48: =T48 -> 145.29726 | Y48: =U48 -> 123.31485
A49: 45078 | B49: 0.064 | C49: 0.028 | D49: 0.058 | E49: 0.042 | F49: 0.054 | G49: 0.038 | H49: 0.048 | I49: 0.038 | J49: 0.062 | K49: 0.054 | L49: 0.038 | M49: 0.058 | N49: 0.038 | O49: 0.048 | P49: 0.034 | Q49: {=IF(COUNTA(B5:P5)=0,"",SUMPRODUCT(B5:P5,IFERROR(B49:P49,0)))} -> 0.04631 | R49: 0.0607 | S49: =IF(OR(Q49="",R49=""),"",Q49-R49) -> -0.01439 | T49: =IF(Q49="","",T48*(1+Q49)) -> 152.02598 | U49: =IF(R49="","",U48*(1+R49)) -> 130.80006 | W49: =A49 -> 45078 | X49: =T49 -> 152.02598 | Y49: =U49 -> 130.80006
A50: 45108 | B50: 0.038 | C50: 0.024 | D50: 0.042 | E50: 0.038 | F50: 0.028 | G50: 0.014 | H50: 0.032 | I50: 0.042 | J50: 0.024 | K50: 0.048 | L50: 0.028 | M50: 0.034 | N50: 0.042 | O50: 0.032 | P50: 0.014 | Q50: {=IF(COUNTA(B5:P5)=0,"",SUMPRODUCT(B5:P5,IFERROR(B50:P50,0)))} -> 0.0319 | R50: 0.0359 | S50: =IF(OR(Q50="",R50=""),"",Q50-R50) -> -0.004 | T50: =IF(Q50="","",T49*(1+Q50)) -> 156.87561 | U50: =IF(R50="","",U49*(1+R50)) -> 135.49579 | W50: =A50 -> 45108 | X50: =T50 -> 156.87561 | Y50: =U50 -> 135.49579
A51: 45139 | B51: -0.018 | C51: -0.024 | D51: -0.014 | E51: -0.038 | F51: -0.028 | G51: -0.044 | H51: -0.038 | I51: -0.024 | J51: -0.054 | K51: -0.018 | L51: -0.012 | M51: -0.032 | N51: -0.018 | O51: -0.012 | P51: -0.024 | Q51: {=IF(COUNTA(B5:P5)=0,"",SUMPRODUCT(B5:P5,IFERROR(B51:P51,0)))} -> -0.02669 | R51: -0.0237 | S51: =IF(OR(Q51="",R51=""),"",Q51-R51) -> -0.00299 | T51: =IF(Q51="","",T50*(1+Q51)) -> 152.6886 | U51: =IF(R51="","",U50*(1+R51)) -> 132.28454 | W51: =A51 -> 45139 | X51: =T51 -> 152.6886 | Y51: =U51 -> 132.28454
A52: 45170 | B52: -0.048 | C52: -0.032 | D52: -0.044 | E52: -0.058 | F52: -0.048 | G52: -0.058 | H52: -0.062 | I52: -0.048 | J52: -0.068 | K52: -0.044 | L52: -0.032 | M52: -0.052 | N52: -0.028 | O52: -0.034 | P52: -0.048 | Q52: {=IF(COUNTA(B5:P5)=0,"",SUMPRODUCT(B5:P5,IFERROR(B52:P52,0)))} -> -0.04704 | R52: -0.0413 | S52: =IF(OR(Q52="",R52=""),"",Q52-R52) -> -0.00574 | T52: =IF(Q52="","",T51*(1+Q52)) -> 145.50613 | U52: =IF(R52="","",U51*(1+R52)) -> 126.82119 | W52: =A52 -> 45170 | X52: =T52 -> 145.50613 | Y52: =U52 -> 126.82119
A53: 45200 | B53: -0.028 | C53: -0.014 | D53: -0.032 | E53: -0.038 | F53: -0.032 | G53: -0.042 | H53: -0.048 | I53: -0.032 | J53: -0.042 | K53: -0.032 | L53: -0.018 | M53: -0.034 | N53: -0.018 | O53: -0.024 | P53: -0.038 | Q53: {=IF(COUNTA(B5:P5)=0,"",SUMPRODUCT(B5:P5,IFERROR(B53:P53,0)))} -> -0.03149 | R53: -0.0295 | S53: =IF(OR(Q53="",R53=""),"",Q53-R53) -> -0.00199 | T53: =IF(Q53="","",T52*(1+Q53)) -> 140.92414 | U53: =IF(R53="","",U52*(1+R53)) -> 123.07996 | W53: =A53 -> 45200 | X53: =T53 -> 140.92414 | Y53: =U53 -> 123.07996
A54: 45231 | B54: 0.094 | C54: 0.062 | D54: 0.088 | E54: 0.078 | F54: 0.072 | G54: 0.082 | H54: 0.108 | I54: 0.084 | J54: 0.098 | K54: 0.094 | L54: 0.068 | M54: 0.082 | N54: 0.078 | O54: 0.082 | P54: 0.068 | Q54: {=IF(COUNTA(B5:P5)=0,"",SUMPRODUCT(B5:P5,IFERROR(B54:P54,0)))} -> 0.08166 | R54: 0.0939 | S54: =IF(OR(Q54="",R54=""),"",Q54-R54) -> -0.01224 | T54: =IF(Q54="","",T53*(1+Q54)) -> 152.432 | U54: =IF(R54="","",U53*(1+R54)) -> 134.63717 | W54: =A54 -> 45231 | X54: =T54 -> 152.432 | Y54: =U54 -> 134.63717
A55: 45261 | B55: 0.048 | C55: 0.038 | D55: 0.052 | E55: 0.062 | F55: 0.054 | G55: 0.048 | H55: 0.038 | I55: 0.052 | J55: 0.048 | K55: 0.054 | L55: 0.042 | M55: 0.048 | N55: 0.054 | O55: 0.042 | P55: 0.038 | Q55: {=IF(COUNTA(B5:P5)=0,"",SUMPRODUCT(B5:P5,IFERROR(B55:P55,0)))} -> 0.04848 | R55: 0.0467 | S55: =IF(OR(Q55="",R55=""),"",Q55-R55) -> 0.00178 | T55: =IF(Q55="","",T54*(1+Q55)) -> 159.82191 | U55: =IF(R55="","",U54*(1+R55)) -> 140.92472 | W55: =A55 -> 45261 | X55: =T55 -> 159.82191 | Y55: =U55 -> 140.92472
A56: 45292 | B56: 0.018 | C56: -0.048 | D56: 0.014 | E56: 0.068 | F56: 0.058 | G56: 0.034 | H56: -0.028 | I56: 0.024 | J56: -0.042 | K56: 0.028 | L56: 0.018 | M56: 0.034 | N56: 0.068 | O56: 0.018 | P56: -0.018 | Q56: {=IF(COUNTA(B5:P5)=0,"",SUMPRODUCT(B5:P5,IFERROR(B56:P56,0)))} -> 0.02036 | R56: 0.011 | S56: =IF(OR(Q56="",R56=""),"",Q56-R56) -> 0.00936 | T56: =IF(Q56="","",T55*(1+Q56)) -> 163.07588 | U56: =IF(R56="","",U55*(1+R56)) -> 142.4749 | W56: =A56 -> 45292 | X56: =T56 -> 163.07588 | Y56: =U56 -> 142.4749
A57: 45323 | B57: 0.062 | C57: 0.028 | D57: 0.058 | E57: 0.084 | F57: 0.062 | G57: 0.028 | H57: 0.078 | I57: 0.054 | J57: 0.062 | K57: 0.072 | L57: 0.048 | M57: 0.064 | N57: 0.058 | O57: 0.054 | P57: 0.048 | Q57: {=IF(COUNTA(B5:P5)=0,"",SUMPRODUCT(B5:P5,IFERROR(B57:P57,0)))} -> 0.05715 | R57: 0.0465 | S57: =IF(OR(Q57="",R57=""),"",Q57-R57) -> 0.01065 | T57: =IF(Q57="","",T56*(1+Q57)) -> 172.39567 | U57: =IF(R57="","",U56*(1+R57)) -> 149.09998 | W57: =A57 -> 45323 | X57: =T57 -> 172.39567 | Y57: =U57 -> 149.09998
A58: 45352 | B58: 0.038 | C58: 0.018 | D58: 0.034 | E58: 0.058 | F58: 0.048 | G58: 0.042 | H58: 0.028 | I58: 0.042 | J58: 0.038 | K58: 0.042 | L58: 0.032 | M58: 0.038 | N58: 0.048 | O58: 0.036 | P58: 0.028 | Q58: {=IF(COUNTA(B5:P5)=0,"",SUMPRODUCT(B5:P5,IFERROR(B58:P58,0)))} -> 0.03891 | R58: 0.0322 | S58: =IF(OR(Q58="",R58=""),"",Q58-R58) -> 0.00671 | T58: =IF(Q58="","",T57*(1+Q58)) -> 179.10358 | U58: =IF(R58="","",U57*(1+R58)) -> 153.901 | W58: =A58 -> 45352 | X58: =T58 -> 179.10358 | Y58: =U58 -> 153.901
A59: 45383 | B59: -0.034 | C59: -0.048 | D59: -0.028 | E59: -0.064 | F59: -0.028 | G59: -0.048 | H59: -0.054 | I59: -0.038 | J59: -0.048 | K59: -0.038 | L59: -0.018 | M59: -0.048 | N59: -0.018 | O59: -0.024 | P59: -0.048 | Q59: {=IF(COUNTA(B5:P5)=0,"",SUMPRODUCT(B5:P5,IFERROR(B59:P59,0)))} -> -0.03901 | R59: -0.0339 | S59: =IF(OR(Q59="",R59=""),"",Q59-R59) -> -0.00511 | T59: =IF(Q59="","",T58*(1+Q59)) -> 172.11675 | U59: =IF(R59="","",U58*(1+R59)) -> 148.68376 | W59: =A59 -> 45383 | X59: =T59 -> 172.11675 | Y59: =U59 -> 148.68376
A60: 45413 | B60: 0.054 | C60: 0.014 | D60: 0.048 | E60: 0.078 | F60: 0.052 | G60: 0.028 | H60: 0.038 | I60: 0.048 | J60: 0.028 | K60: 0.062 | L60: 0.038 | M60: 0.052 | N60: 0.054 | O60: 0.042 | P60: 0.022 | Q60: {=IF(COUNTA(B5:P5)=0,"",SUMPRODUCT(B5:P5,IFERROR(B60:P60,0)))} -> 0.04481 | R60: 0.0437 | S60: =IF(OR(Q60="",R60=""),"",Q60-R60) -> 0.00111 | T60: =IF(Q60="","",T59*(1+Q60)) -> 179.8293 | U60: =IF(R60="","",U59*(1+R60)) -> 155.18124 | W60: =A60 -> 45413 | X60: =T60 -> 179.8293 | Y60: =U60 -> 155.18124
A61: 45444 | B61: 0.028 | C61: 0.008 | D61: 0.024 | E61: 0.048 | F61: 0.038 | G61: -0.018 | H61: 0.012 | I61: 0.028 | J61: 0.008 | K61: 0.038 | L61: 0.018 | M61: 0.028 | N61: 0.042 | O61: 0.018 | P61: -0.004 | Q61: {=IF(COUNTA(B5:P5)=0,"",SUMPRODUCT(B5:P5,IFERROR(B61:P61,0)))} -> 0.02173 | R61: 0.0217 | S61: =IF(OR(Q61="",R61=""),"",Q61-R61) -> 3e-05 | T61: =IF(Q61="","",T60*(1+Q61)) -> 183.73699 | U61: =IF(R61="","",U60*(1+R61)) -> 158.54867 | W61: =A61 -> 45444 | X61: =T61 -> 183.73699 | Y61: =U61 -> 158.54867
A62: 45474 | B62: 0.048 | C62: 0.038 | D62: 0.052 | E62: 0.028 | F62: 0.034 | G62: 0.014 | H62: 0.044 | I62: 0.048 | J62: 0.032 | K62: 0.054 | L62: 0.038 | M62: 0.014 | N62: 0.034 | O62: 0.048 | P62: 0.028 | Q62: {=IF(COUNTA(B5:P5)=0,"",SUMPRODUCT(B5:P5,IFERROR(B62:P62,0)))} -> 0.03614 | R62: 0.0144 | S62: =IF(OR(Q62="",R62=""),"",Q62-R62) -> 0.02174 | T62: =IF(Q62="","",T61*(1+Q62)) -> 190.37725 | U62: =IF(R62="","",U61*(1+R62)) -> 160.83177 | W62: =A62 -> 45474 | X62: =T62 -> 190.37725 | Y62: =U62 -> 160.83177
A63: 45505 | B63: 0.038 | C63: 0.028 | D63: 0.034 | E63: 0.048 | F63: 0.042 | G63: 0.018 | H63: 0.028 | I63: 0.034 | J63: 0.028 | K63: 0.038 | L63: 0.028 | M63: 0.028 | N63: 0.042 | O63: 0.032 | P63: 0.022 | Q63: {=IF(COUNTA(B5:P5)=0,"",SUMPRODUCT(B5:P5,IFERROR(B63:P63,0)))} -> 0.03295 | R63: 0.0274 | S63: =IF(OR(Q63="",R63=""),"",Q63-R63) -> 0.00555 | T63: =IF(Q63="","",T62*(1+Q63)) -> 196.65018 | U63: =IF(R63="","",U62*(1+R63)) -> 165.23856 | W63: =A63 -> 45505 | X63: =T63 -> 196.65018 | Y63: =U63 -> 165.23856
A64: 45536 | B64: 0.018 | C64: 0.008 | D64: 0.024 | E64: 0.038 | F64: 0.028 | G64: 0.012 | H64: 0.018 | I64: 0.024 | J64: 0.014 | K64: 0.028 | L64: 0.018 | M64: 0.018 | N64: 0.028 | O64: 0.018 | P64: 0.012 | Q64: {=IF(COUNTA(B5:P5)=0,"",SUMPRODUCT(B5:P5,IFERROR(B64:P64,0)))} -> 0.02095 | R64: 0.0175 | S64: =IF(OR(Q64="",R64=""),"",Q64-R64) -> 0.00345 | T64: =IF(Q64="","",T63*(1+Q64)) -> 200.77 | U64: =IF(R64="","",U63*(1+R64)) -> 168.13023 | W64: =A64 -> 45536 | X64: =T64 -> 200.77 | Y64: =U64 -> 168.13023
A65: 45566 | B65: -0.018 | C65: -0.034 | D65: -0.014 | E65: -0.048 | F65: -0.028 | G65: -0.098 | H65: -0.038 | I65: -0.024 | J65: -0.042 | K65: -0.014 | L65: -0.014 | M65: -0.038 | N65: -0.018 | O65: -0.012 | P65: -0.028 | Q65: {=IF(COUNTA(B5:P5)=0,"",SUMPRODUCT(B5:P5,IFERROR(B65:P65,0)))} -> -0.03245 | R65: -0.0203 | S65: =IF(OR(Q65="",R65=""),"",Q65-R65) -> -0.01215 | T65: =IF(Q65="","",T64*(1+Q65)) -> 194.25501 | U65: =IF(R65="","",U64*(1+R65)) -> 164.71719 | W65: =A65 -> 45566 | X65: =T65 -> 194.25501 | Y65: =U65 -> 164.71719
A66: 45597 | B66: 0.082 | C66: 0.054 | D66: 0.078 | E66: 0.048 | F66: 0.042 | G66: -0.038 | H66: 0.064 | I66: 0.058 | J66: 0.068 | K66: 0.078 | L66: 0.058 | M66: 0.058 | N66: 0.064 | O66: 0.088 | P66: 0.038 | Q66: {=IF(COUNTA(B5:P5)=0,"",SUMPRODUCT(B5:P5,IFERROR(B66:P66,0)))} -> 0.0533 | R66: 0.0477 | S66: =IF(OR(Q66="",R66=""),"",Q66-R66) -> 0.0056 | T66: =IF(Q66="","",T65*(1+Q66)) -> 204.60881 | U66: =IF(R66="","",U65*(1+R66)) -> 172.5742 | W66: =A66 -> 45597 | X66: =T66 -> 204.60881 | Y66: =U66 -> 172.5742
A67: 45627 | B67: -0.024 | C67: -0.048 | D67: -0.018 | E67: -0.038 | F67: -0.028 | G67: -0.072 | H67: -0.054 | I67: -0.032 | J67: -0.048 | K67: -0.018 | L67: -0.018 | M67: -0.038 | N67: -0.024 | O67: -0.018 | P67: -0.034 | Q67: {=IF(COUNTA(B5:P5)=0,"",SUMPRODUCT(B5:P5,IFERROR(B67:P67,0)))} -> -0.03445 | R67: -0.0248 | S67: =IF(OR(Q67="",R67=""),"",Q67-R67) -> -0.00965 | T67: =IF(Q67="","",T66*(1+Q67)) -> 197.56003 | U67: =IF(R67="","",U66*(1+R67)) -> 168.29436 | W67: =A67 -> 45627 | X67: =T67 -> 197.56003 | Y67: =U67 -> 168.29436
A70: PERFORMANCE SUMMARY
A71: METRIC | B71: PORTFOLIO | C71: BENCHMARK | D71: vs BENCHMARK
A72: Total Return (2020–2024) | B72: =IF(T67="","",T67/100-1) -> 0.97560033 | C72: {=IFERROR(PRODUCT(1+R8:R67)-1,"")} -> 0.6829436 | D72: =IF(OR(B72="",C72=""),"",B72-C72) -> 0.29265673
A73: Annualised Return (CAGR) | B73: =IF(B72="","",((1+B72)^(1/5))-1) -> 0.14588179 | C73: =IF(C72="","",((1+C72)^(1/5))-1) -> 0.10972128 | D73: =IF(OR(B73="",C73=""),"",B73-C73) -> 0.036160514
A74: Best Month | B74: =IF(COUNTA(Q8:Q67)=0,"",MAX(Q8:Q67)) -> 0.1436 | C74: =IF(COUNTA(R8:R67)=0,"",MAX(R8:R67)) -> 0.1264 | D74: =IF(OR(B74="",C74=""),"",B74-C74) -> 0.0172
A75: Worst Month | B75: =IF(COUNTA(Q8:Q67)=0,"",MIN(Q8:Q67)) -> -0.147315 | C75: =IF(COUNTA(R8:R67)=0,"",MIN(R8:R67)) -> -0.1327 | D75: =IF(OR(B75="",C75=""),"",B75-C75) -> -0.014615
A76: Positive Months | B76: =COUNTIF(Q8:Q67,">0") -> 39 | C76: =COUNTIF(R8:R67,">0") -> 37 | D76: =IF(OR(B76="",C76=""),"",B76-C76) -> 2

Sheet Attribution
A1: GLOBAL QUALITY COMPOUNDER PORTFOLIO - PERFORMANCE ATTRIBUTION (BRINSON-HOOD-BEEBOWER)
A2: BHB Attribution decomposes active return into Allocation Effect, Selection Effect, and Interaction Effect. Yellow cells = inputs. Portfolio weights auto-linked from Portfolio tab.
A4: BHB FORMULA REFERENCE
A5: Allocation Effect | B5: (wp_i - wb_i) x (Rb_i - Rb_total) | C5: Active weight bet times (sector benchmark return minus total benchmark return)
A6: Selection Effect | B6: wb_i x (Rp_i - Rb_i) | C6: Benchmark-weighted outperformance of portfolio return vs benchmark within each sector
A7: Interaction Effect | B7: (wp_i - wb_i) x (Rp_i - Rb_i) | C7: Joint effect of active weight decision and active return selection
A8: Total Active Return | B8: Allocation + Selection + Interaction | C8: Sum of the three BHB effects; equals total portfolio return minus benchmark return
A10: Benchmark Total Return (Rb_total): | B10: =IFERROR(Backtest!C73,"") -> 0.10972128 | C10: Input total benchmark return for the attribution period (e.g. full year 2024 MSCI World return)
F11: ▲ MSCI World sector index 5Y total returns (2020–2024 approximations — update from MSCI factsheet)
A12: SECTOR | B12: PORT. WEIGHT (wp) | C12: BMRK WEIGHT (wb) | D12: ACTIVE WEIGHT (wp-wb) | E12: PORT. RETURN (Rp) | F12: BMRK RETURN (Rb) | G12: ACTIVE RETURN (Rp-Rb) | H12: ALLOCATION EFFECT | I12: SELECTION EFFECT | J12: INTERACTION EFFECT
A13: Technology | B13: =IFERROR(SUMIF(Portfolio!$E$5:$E$19,A13,Portfolio!$F$5:$F$19),"") -> 0.32 | C13: 0.245 | D13: =IF(OR(B13="",C13=""),"",B13-C13) -> 0.075 | E13: {=IFERROR((0.085*((PRODUCT(1+Backtest!E8:E67))^(1/5)-1)+0.055*((PRODUCT(1+Backtest!H8:H67))^(1/5)-1)+0.065*((PRODUCT(1+Backtest!M8:M67))^(1/5)-1)+0.05*((PRODUCT(1+Backtest!O8:O67))^(1/5)-1)+0.065*((PRODUCT(1+Backtest!P8:P67))^(1/5)-1))/0.32,"")} -> 0.10631862 | F13: 0.129 | G13: =IF(OR(E13="",F13=""),"",E13-F13) -> -0.022681383 | H13: =IF(OR(D13="",F13="",B10=""),"",D13*(F13-B10)) -> 0.0014459043 | I13: =IF(OR(C13="",G13=""),"",C13*G13) -> -0.0055569388 | J13: =IF(OR(D13="",G13=""),"",D13*G13) -> -0.0017011037
A14: Financials | B14: =IFERROR(SUMIF(Portfolio!$E$5:$E$19,A14,Portfolio!$F$5:$F$19),"") -> 0.185 | C14: 0.175 | D14: =IF(OR(B14="",C14=""),"",B14-C14) -> 0.01 | E14: {=IFERROR((0.07*((PRODUCT(1+Backtest!B8:B67))^(1/5)-1)+0.065*((PRODUCT(1+Backtest!D8:D67))^(1/5)-1)+0.05*((PRODUCT(1+Backtest!K8:K67))^(1/5)-1))/0.185,"")} -> 0.21298218 | F14: 0.094 | G14: =IF(OR(E14="",F14=""),"",E14-F14) -> 0.11898218 | H14: =IF(OR(D14="",F14="",B10=""),"",D14*(F14-B10)) -> -0.00015721276 | I14: =IF(OR(C14="",G14=""),"",C14*G14) -> 0.020821881 | J14: =IF(OR(D14="",G14=""),"",D14*G14) -> 0.0011898218
A15: Healthcare | B15: =IFERROR(SUMIF(Portfolio!$E$5:$E$19,A15,Portfolio!$F$5:$F$19),"") -> 0.27 | C15: 0.115 | D15: =IF(OR(B15="",C15=""),"",B15-C15) -> 0.155 | E15: {=IFERROR((0.06*((PRODUCT(1+Backtest!C8:C67))^(1/5)-1)+0.08*((PRODUCT(1+Backtest!G8:G67))^(1/5)-1)+0.08*((PRODUCT(1+Backtest!I8:I67))^(1/5)-1)+0.05*((PRODUCT(1+Backtest!J8:J67))^(1/5)-1))/0.27,"")} -> 0.076167985 | F15: 0.076 | G15: =IF(OR(E15="",F15=""),"",E15-F15) -> 0.0001679846 | H15: =IF(OR(D15="",F15="",B10=""),"",D15*(F15-B10)) -> -0.0052267977 | I15: =IF(OR(C15="",G15=""),"",C15*G15) -> 1.9318229e-05 | J15: =IF(OR(D15="",G15=""),"",D15*G15) -> 2.6037613e-05
A16: Consumer Discretionary | B16: =IFERROR(SUMIF(Portfolio!$E$5:$E$19,A16,Portfolio!$F$5:$F$19),"") -> 0.155 | C16: 0.105 | D16: =IF(OR(B16="",C16=""),"",B16-C16) -> 0.05 | E16: {=IFERROR((0.085*((PRODUCT(1+Backtest!F8:F67))^(1/5)-1)+0.07*((PRODUCT(1+Backtest!N8:N67))^(1/5)-1))/0.155,"")} -> 0.25945159 | F16: 0.102 | G16: =IF(OR(E16="",F16=""),"",E16-F16) -> 0.15745159 | H16: =IF(OR(D16="",F16="",B10=""),"",D16*(F16-B10)) -> -0.00038606378 | I16: =IF(OR(C16="",G16=""),"",C16*G16) -> 0.016532417 | J16: =IF(OR(D16="",G16=""),"",D16*G16) -> 0.0078725796
A17: Consumer Staples | B17: =IFERROR(SUMIF(Portfolio!$E$5:$E$19,A17,Portfolio!$F$5:$F$19),"") -> 0 | C17: 0.075 | D17: =IF(OR(B17="",C17=""),"",B17-C17) -> -0.075 | E17: 0 | F17: 0.042 | G17: =IF(OR(E17="",F17=""),"",E17-F17) -> -0.042 | H17: =IF(OR(D17="",F17="",B10=""),"",D17*(F17-B10)) -> 0.0050790957 | I17: =IF(OR(C17="",G17=""),"",C17*G17) -> -0.00315 | J17: =IF(OR(D17="",G17=""),"",D17*G17) -> 0.00315
A18: Industrials | B18: =IFERROR(SUMIF(Portfolio!$E$5:$E$19,A18,Portfolio!$F$5:$F$19),"") -> 0.07 | C18: 0.105 | D18: =IF(OR(B18="",C18=""),"",B18-C18) -> -0.035 | E18: {=IFERROR((PRODUCT(1+Backtest!L8:L67))^(1/5)-1,"")} -> 0.17967914 | F18: 0.088 | G18: =IF(OR(E18="",F18=""),"",E18-F18) -> 0.091679141 | H18: =IF(OR(D18="",F18="",B10=""),"",D18*(F18-B10)) -> 0.00076024464 | I18: =IF(OR(C18="",G18=""),"",C18*G18) -> 0.0096263098 | J18: =IF(OR(D18="",G18=""),"",D18*G18) -> -0.0032087699
A19: Other | B19: =IFERROR(SUMIF(Portfolio!$E$5:$E$19,A19,Portfolio!$F$5:$F$19),"") -> 0 | C19: 0.18 | D19: =IF(OR(B19="",C19=""),"",B19-C19) -> -0.18 | E19: 0 | F19: 0.051 | G19: =IF(OR(E19="",F19=""),"",E19-F19) -> -0.051 | H19: =IF(OR(D19="",F19="",B10=""),"",D19*(F19-B10)) -> 0.01056983 | I19: =IF(OR(C19="",G19=""),"",C19*G19) -> -0.00918 | J19: =IF(OR(D19="",G19=""),"",D19*G19) -> 0.00918
A20: TOTAL / PORTFOLIO SUMMARY | B20: =IFERROR(SUM(B13:B19),"") -> 1 | C20: =IFERROR(SUM(C13:C19),"") -> 1 | D20: =IFERROR(SUM(D13:D19),"") -> 0 | E20: =IFERROR(Backtest!B73,"") -> 0.14588179 | F20: =IFERROR(Backtest!C73,"") -> 0.10972128 | G20: =IF(OR(E20="",F20=""),"",E20-F20) -> 0.036160514 | H20: =IFERROR(SUM(H13:H19),"") -> 0.012085 | I20: =IFERROR(SUM(I13:I19),"") -> 0.029112988 | J20: =IFERROR(SUM(J13:J19),"") -> 0.016508565
A23: ALPHA DECOMPOSITION SUMMARY
A24: COMPONENT | B24: VALUE | C24: % OF TOTAL ALPHA | D24: INTERPRETATION
A25: Total Allocation Effect | B25: =IFERROR(H20,"") -> 0.012085 | C25: =IFERROR(H20/(H20+I20+J20),"") -> 0.20942162 | D25: Contribution from sector weight bets vs benchmark
A26: Total Selection Effect | B26: =IFERROR(I20,"") -> 0.029112988 | C26: =IFERROR(I20/(H20+I20+J20),"") -> 0.50450055 | D26: Contribution from stock picking within sectors
A27: Total Interaction Effect | B27: =IFERROR(J20,"") -> 0.016508565 | C27: =IFERROR(J20/(H20+I20+J20),"") -> 0.28607783 | D27: Joint weight and selection decision effect
A28: TOTAL ACTIVE RETURN | B28: =IFERROR(H20+I20+J20,"") -> 0.057706553 | D28: Sum of all three BHB effects = Total portfolio alpha
A29: Residual | B29: =IF(OR(B28="",G20=""),"",B28-G20) -> 0.021546038 | C29: Normal in BHB attribution. The three sector-level effects (Allocation + Selection + Interaction) sum arithmetically, while the actual excess return (3.62%) is measured geometrically. This gap is expected and does not indicate a model error.

Sheet Risk Metrics
A1: GLOBAL QUALITY COMPOUNDER PORTFOLIO - RISK METRICS DASHBOARD
A2: All risk metrics calculated from Backtest tab monthly returns (Jan 2020 - Dec 2024). Risk-free rate assumption in yellow. Data auto-referenced.
A4: ASSUMPTIONS
A5: Risk-Free Rate (Annual): | B5: 0.035 | C5: Annualisation Factor: | D5: 12 | E5: Backtest Length (Months): | F5: 60
A7: RISK METRIC | B7: PORTFOLIO | C7: BENCHMARK | D7: vs BENCHMARK / THRESHOLD | E7: CATEGORY | F7: INTERPRETATION
A8: Annualised Volatility | B8: =IFERROR(STDEV(Backtest!$Q$8:$Q$67)*SQRT(D5),"") -> 0.18367466 | C8: =IFERROR(STDEV(Backtest!$R$8:$R$67)*SQRT(D5),"") -> 0.18156767 | D8: =IF(OR(B8="",C8=""),"",B8-C8) -> 0.002106988 | E8: Absolute Risk | F8: Annualised std dev of monthly returns. Mandate limit: manage within reasonable range vs benchmark.
A9: Sharpe Ratio | B9: =IFERROR((AVERAGE(Backtest!$Q$8:$Q$67)*D5-B5)/STDEV(Backtest!$Q$8:$Q$67)/SQRT(D5),"") -> 0.64618821 | C9: =IFERROR((AVERAGE(Backtest!$R$8:$R$67)*D5-B5)/STDEV(Backtest!$R$8:$R$67)/SQRT(D5),"") -> 0.47288154 | D9: =IF(OR(B9="",C9=""),"",B9-C9) -> 0.17330667 | E9: Risk-Adjusted | F9: Excess return per unit of total risk. Higher is better. Target: >1.0 for quality equity strategy.
A10: Maximum Drawdown | B10: =IFERROR(MIN(Backtest!T8:T67)/MAX(Backtest!T8:T67)-1,"") -> -0.60645821 | C10: =IFERROR(MIN(Backtest!U8:U67)/MAX(Backtest!U8:U67)-1,"") -> -0.53855738 | D10: =IF(OR(B10="",C10=""),"",B10-C10) -> -0.067900827 | E10: Downside Risk | F10: Largest peak-to-trough decline in portfolio NAV. Calculated from cumulative NAV series in Backtest.
A11: Beta vs Benchmark | B11: =IFERROR(COVAR(Backtest!$Q$8:$Q$67,Backtest!$R$8:$R$67)/VAR(Backtest!$R$8:$R$67),"") -> 0.94860369 | C11: =1 -> 1 | D11: =IF(B11="","",B11-1) -> -0.051396314 | E11: Market Risk | F11: Sensitivity of portfolio returns to benchmark. Beta <1 implies defensiveness; >1 implies amplified market risk.
A12: Tracking Error (Ex-Post) | B12: =IFERROR(STDEV(Backtest!$S$8:$S$67)*SQRT(D5),"") -> 0.055661695 | C12: =0 -> 0 | D12: =IF(B12="","",B12) -> 0.055661695 | E12: Active Risk | F12: Annualised std dev of excess returns vs benchmark. Mandate max: 4.0%. Higher TE = more active.
A13: Information Ratio | B13: =IFERROR((AVERAGE(Backtest!$S$8:$S$67)*D5)/STDEV(Backtest!$S$8:$S$67)/SQRT(D5),"") -> 0.58978441 | E13: Active Risk-Adj. | F13: Annualised active return divided by tracking error. Target: >0.5. Elite managers typically achieve >0.7.
A14: % Months Outperforming | B14: =IFERROR(COUNTIF(Backtest!$S$8:$S$67,">0")/COUNT(Backtest!$S$8:$S$67),"") -> 0.6 | C14: =0.5 -> 0.5 | D14: =IF(OR(B14="",C14=""),"",B14-C14) -> 0.1 | E14: Consistency | F14: Proportion of months where portfolio beat benchmark. >50% confirms strategy consistency.
A15: Hit Rate (Positive Months) | B15: =IFERROR(COUNTIF(Backtest!$Q$8:$Q$67,">0")/COUNT(Backtest!$Q$8:$Q$67),"") -> 0.65 | C15: =IFERROR(COUNTIF(Backtest!$R$8:$R$67,">0")/COUNT(Backtest!$R$8:$R$67),"") -> 0.61666667 | D15: =IF(OR(B15="",C15=""),"",B15-C15) -> 0.033333333 | E15: Consistency | F15: Proportion of months with positive portfolio return. Useful for downside analysis.
A16: Sortino Ratio | B16: {=IFERROR((AVERAGE(Backtest!Q8:Q67)*D5-B5)/(SQRT(SUMPRODUCT((Backtest!Q8:Q67*(Backtest!Q8:Q67<0))^2)/COUNT(Backtest!Q8:Q67))*SQRT(D5)),"")} -> 1.0141255 | C16: {=IFERROR((AVERAGE(Backtest!R8:R67)*D5-B5)/(SQRT(SUMPRODUCT((Backtest!R8:R67*(Backtest!R8:R67<0))^2)/COUNT(Backtest!R8:R67))*SQRT(D5)),"")} -> 0.73682374 | D16: =IF(OR(B16="",C16=""),"",B16-C16) -> 0.27730176 | E16: Downside Risk-Adj. | F16: Sharpe-like ratio using only downside deviation. Penalises bad volatility only. Target: >1.5.
A17: Calmar Ratio | B17: =IFERROR(((Backtest!T67/100)^(1/5)-1)/ABS(B10),"") -> 0.24054715 | C17: =IFERROR(((Backtest!U67/100)^(1/5)-1)/ABS(C10),"") -> 0.20373182 | D17: =IF(OR(B17="",C17=""),"",B17-C17) -> 0.036815324 | E17: Drawdown-Adj. | F17: Annualised CAGR divided by maximum drawdown. Measures return per unit of worst-case loss.
A18: Annualised Alpha (CAPM) | B18: =IFERROR((AVERAGE(Backtest!$Q$8:$Q$67)-B11*AVERAGE(Backtest!$R$8:$R$67))*D5,"") -> 0.039040159 | E18: Alpha | F18: Jensen's alpha: portfolio excess return above CAPM-implied expected return given observed beta.
A19: Correlation vs Benchmark | B19: =IFERROR(CORREL(Backtest!$Q$8:$Q$67,Backtest!$R$8:$R$67),"") -> 0.95361556 | C19: =1 -> 1 | D19: =IF(B19="","",B19-1) -> -0.046384444 | E19: Diversification | F19: Pearson correlation of monthly returns vs benchmark. High correlation reduces diversification benefit.
A22: MANDATE COMPLIANCE CHECKS
A23: CONSTRAINT | B23: LIMIT | C23: CURRENT VALUE | D23: STATUS
A24: Tracking Error | B24: Max 4.0% | C24: =IFERROR(B12,"") -> 0.055661695 | D24: =IF(C24="","Pending",IF(C24<=0.04,"COMPLIANT","BREACH")) -> BREACH
A25: Number of Holdings | B25: 12-15 stocks | C25: =IFERROR(COUNTA(Portfolio!$B$5:$B$19),"") -> 15 | D25: =IF(C25="","Pending",IF(AND(C25>=12,C25<=15),"COMPLIANT","BREACH")) -> COMPLIANT
A26: Max Single Stock Weight | B26: Max 8% | C26: =IFERROR(MAX(Portfolio!$F$5:$F$19),"") -> 0.085 | D26: =IF(C26="","Pending",IF(C26<=0.08,"COMPLIANT","BREACH")) -> BREACH
A36: PORTFOLIO QUALITY SCORE
A37: Weighted-average composite quality score of live portfolio vs full 35-stock universe. Linked live from Factor Screen and Portfolio tabs.
A39: METRIC | B39: VALUE | C39: UNIVERSE AVG | D39: vs UNIVERSE | E39: INTERPRETATION
A40: Portfolio Weighted Composite Score | B40: {=IFERROR(SUMPRODUCT((LEN(Portfolio!$F$5:$F$19)>0)*Portfolio!$F$5:$F$19*IFERROR(VLOOKUP(Portfolio!$C$5:$C$19,'Factor Screen'!$C$9:$N$43,12,0),0))/SUM(Portfolio!$F$5:$F$19),"")} -> 3.545 | C40: =IFERROR(AVERAGE('Factor Screen'!$N$9:$N$43),"") -> 3 | D40: =IF(OR(B40="",C40=""),"",B40-C40) -> 0.545 | E40: Composite quality score of holdings weighted by position size (1-5 scale). Target: >3.5 signals high-conviction quality tilt vs universe.
A41: Weighted ROIC Score (Portfolio) | B41: {=IFERROR(SUMPRODUCT((LEN(Portfolio!$F$5:$F$19)>0)*Portfolio!$F$5:$F$19*IFERROR(VLOOKUP(Portfolio!$C$5:$C$19,'Factor Screen'!$C$9:$E$43,3,0),0))/SUM(Portfolio!$F$5:$F$19),"")} -> 4.065 | C41: =IFERROR(AVERAGE('Factor Screen'!$E$9:$E$43),"") -> 3 | D41: =IF(OR(B41="",C41=""),"",B41-C41) -> 1.065 | E41: Avg ROIC score of holdings vs full universe. Confirms portfolio overweights the highest-ROIC compounders in the candidate pool.
A42: Weighted Gross Margin Score (Portfolio) | B42: {=IFERROR(SUMPRODUCT((LEN(Portfolio!$F$5:$F$19)>0)*Portfolio!$F$5:$F$19*IFERROR(VLOOKUP(Portfolio!$C$5:$C$19,'Factor Screen'!$C$9:$G$43,5,0),0))/SUM(Portfolio!$F$5:$F$19),"")} -> 3.63 | C42: =IFERROR(AVERAGE('Factor Screen'!$G$9:$G$43),"") -> 3 | D42: =IF(OR(B42="",C42=""),"",B42-C42) -> 0.63 | E42: Weighted GM score of holdings. High scores confirm portfolio tilts toward premium-priced, capital-light business models.
A43: Weighted FCF Conversion Score (Portfolio) | B43: {=IFERROR(SUMPRODUCT((LEN(Portfolio!$F$5:$F$19)>0)*Portfolio!$F$5:$F$19*IFERROR(VLOOKUP(Portfolio!$C$5:$C$19,'Factor Screen'!$C$9:$K$43,9,0),0))/SUM(Portfolio!$F$5:$F$19),"")} -> 2.72 | C43: =IFERROR(AVERAGE('Factor Screen'!$K$9:$K$43),"") -> 3 | D43: =IF(OR(B43="",C43=""),"",B43-C43) -> -0.28 | E43: FCF conversion score of portfolio. High score signals earnings are cash-backed — critical validation of reported profitability quality.
A44: Holdings with Score >= 3.5 (High Conviction) | B44: {=IFERROR(SUMPRODUCT((LEN(Portfolio!$C$5:$C$19)>0)*(IFERROR(VLOOKUP(Portfolio!$C$5:$C$19,'Factor Screen'!$C$9:$N$43,12,0),0)>=3.5)),"")} -> 8 | C44: Target: 10+ of 15 | D44: =IF(B44="","",IF(B44>=10,"STRONG","REVIEW")) -> REVIEW | E44: Count of portfolio holdings scoring >=3.5 composite. At least 10 of 15 holdings should be high-conviction quality names.
A45: Weakest Holding Score (Min Composite) | B45: {=IFERROR(MIN(IFERROR(VLOOKUP(Portfolio!$C$5:$C$19,'Factor Screen'!$C$9:$N$43,12,0),999)),"")} -> 3.1 | C45: Threshold: >= 2.5 | D45: =IF(B45="","",IF(B45>=2.5,"PASS","FLAG")) -> PASS | E45: Lowest composite score in the portfolio. Any holding below 2.5 warrants qualitative review or replacement consideration.
A48: PORTFOLIO QUALITY SCORE SUMMARY
A49: Overall Score: | B49: =IF(B40="","Pending — fill Portfolio tab","Score: "&TEXT(B40,"0.00")&" / 5.00") -> Score: 3.55 / 5.00 | D49: vs Universe Avg: | E49: =IF(D40="","(fill Portfolio tab)",IF(D40>0,"+"&TEXT(D40,"0.00")&" above universe avg",TEXT(D40,"0.00")&" vs universe avg")) -> +0.54 above universe avg
