Workbook

Sheet Cover
B6: HERMÈS INTERNATIONAL
B8: Equity Valuation & Financial Analysis
B11: RMS FP | Euronext Paris | Luxury Goods
D17: Prepared by | H17: Divij Budhiraja
D18: Date | H18: 45717
D19: Version | H19: v1.0
D20: Sources | H20: Company Filings (finance.hermes.com), FactSet, Bloomberg
D21: Classification | H21: Confidential
D22: Model Type | H22: DCF Valuation | Trading Comps | Scenario Analysis
B26: This document is prepared for informational purposes only and does not constitute investment advice. All projections are based on assumptions that may not reflect actual future performance. Please refer to Sources & Footnotes for full methodology and disclaimers.

Sheet TOC
B1: Hermes International S.A
B2: Comprehensive Valuation Model — Table of Contents
B4: Tab # | C4: Tab Name | D4: Description | E4: Status
B5: SECTION 1: EXECUTIVE SUMMARY & OVERVIEW
B6: 1 | C6: Cover | D6: Title page, version control, confidentiality notice | E6: Complete
B7: 2 | C7: TOC | D7: Table of contents & model map | E7: Complete
B8: 3 | C8: Executive Summary | D8: Investment thesis, highlights, key findings, target price | E8: Complete
B10: SECTION 2: HISTORICAL FINANCIALS & ANALYSIS
B11: 4 | C11: Historical Financials | D11: Historical IS + BS + CF (vertical 3-statement model) | E11: Complete
B12: 5 | C12: Historical Analysis | D12: Margins, growth rates, ratio analysis, trends | E12: Complete
B14: SECTION 3: ASSUMPTIONS & OTHER INPUTS
B15: 6 | C15: Master Assumptions | D15: Key drivers: revenue growth, margins, CapEx, tax, WACC | E15: Complete
B16: 7 | C16: Supporting Schedules | D16: Supporting analysis: TAM, benchmarks, comps backup | E16: Complete
B18: SECTION 4: FORECASTS & PROJECTIONS
B19: 8 | C19: Forecast Model | D19: Projected IS + BS + CF (vertical 3-statement model) | E19: Complete
B20: 9 | C20: Integration Check | D20: BS balances, CF reconciliation, error checks | E20: Complete
B22: SECTION 5: VALUATION
B23: 11 | C23: DCF Valuation | D23: Discounted Cash Flow analysis (WACC, terminal value) | E23: Complete
B24: 12 | C24: Trading Comps | D24: Public comparable company analysis (EV/Revenue, EV/EBITDA) | E24: Complete
B25: 13 | C25: Valuation Summary | D25: Combined valuation range across all methodologies | E25: Complete
B27: SECTION 6: OUTPUTS & ANALYSIS
B28: 14 | C28: Sensitivity Tables | D28: WACC vs. growth, revenue vs. margin data tables | E28: Complete
B30: SECTION 7: REFERENCE & DATA
B31: 15 | C31: Sources & Footnotes | D31: Data sources, methodology notes, disclaimers | E31: Complete
B34: COLOR CODING LEGEND
B35: 🔵 | C35: BLUE cells | D35: Hardcoded inputs / assumptions (user changes these)
B36: ⬛ | C36: BLACK cells | D36: Formulas & calculations (model calculates these)
B37: 🟢 | C37: GREEN cells | D37: Links from other worksheets within workbook
B38: 🟡 | C38: YELLOW cells | D38: Flags / checks / key assumptions needing attention
B39: 🔴 | C39: RED cells | D39: External links to other files

Sheet Executive Summary
B1: HERMÈS INTERNATIONAL
B2: Equity Research | Executive Summary | Valuation Analysis | Q2: RMS FP | Euronext Paris
B5: CURRENT PRICE | F5: MARKET CAP (€bn) | J5: ENTERPRISE VALUE (€bn) | N5: LTM REVENUE (€bn) | Q5: WACC
B6: €1,897.50 | F6: 200.4 | J6: 186.8 | N6: €16.0 | Q6: 0.094
B7: RMS FP Equity | F7: 105.6mm shares | N7: 5Y CAGR: 18.9% | Q7: Ke: 9.4% | Kd: 0%
B9: REVENUE & EBITDA TRAJECTORY (€mm) | K9: MARGIN EVOLUTION (%)
C10: 2020A | D10: 2021A | E10: 2022A | F10: 2023A | G10: 2024A | H10: 2025E | I10: 2026E | L10: 2020A | M10: 2021A | N10: 2022A | O10: 2023A | P10: 2024A | Q10: 2025E | R10: 2026E
B11: Revenue | C11: 6389 | D11: 8982 | E11: 11602 | F11: 13427 | G11: 15170 | H11: 16979 | I11: 18782 | K11: Gross Margin | L11: 0.691 | M11: 0.718 | N11: 0.713 | O11: 0.728 | P11: 0.71 | Q11: 0.717 | R11: 0.717
B12: EBITDA | C12: 2565 | D12: 4155 | E12: 5483 | F12: 6411 | G12: 7003 | H12: 7956 | I12: 8800 | K12: EBITDA Margin | L12: 0.401 | M12: 0.463 | N12: 0.473 | O12: 0.477 | P12: 0.462 | Q12: 0.469 | R12: 0.469
B13: Net Income | C13: 1385 | D13: 2446 | E13: 3367 | F13: 4311 | G13: 4603 | H13: 5058 | I13: 5617 | K13: Net Margin | L13: 0.217 | M13: 0.272 | N13: 0.29 | O13: 0.321 | P13: 0.303 | Q13: 0.298 | R13: 0.299
B29: VALUATION FOOTBALL FIELD — IMPLIED SHARE PRICE (€) | K29: DCF KEY ASSUMPTIONS & OUTPUT
C30: Low | D30: High
B31: DCF Valuation | C31: 946 | D31: 1515 | K31: CAPITAL STRUCTURE | P31: TERMINAL VALUE
B32: Trading Comps | C32: 986 | D32: 1014 | K32: Equity Risk Premium | M32: 0.05 | P32: Exit EV/EBITDA | Q32: 16.6x
K33: Levered Beta | M33: 1.23x | P33: Terminal Value (PV) | Q33: €66.0bn
K34: Cost of Equity (Ke) | M34: 0.094
K35: WACC | M35: 0.094 | P35: IMPLIED SHARE PRICE
P36: DCF Perpetuity | Q36: €944
P37: DCF Exit Multiple | Q37: €1,511
P38: Trading Comps | Q38: 1012
P39: Current Price | Q39: €1,898
B42: SENSITIVITY ANALYSIS — WACC vs. PERPETUAL GROWTH RATE | K42: PEER TRADING MULTIPLES (LTM)
K43: Company | M43: EV/Rev | N43: EV/EBITDA | O43: EV/EBIT | P43: P/E | Q43: Mkt Cap (€bn)
C44: Implied Price (Diluted) | D44: GROWTH RATE | K44: Hermès | M44: 11.7x | N44: 22.8x | O44: 25.7x | P44: 43.1x | Q44: 200.4
D45: 0.015 | E45: 0.02 | F45: 0.025 | G45: 0.03 | H45: 0.035 | K45: LVMH | M45: 3.2x | N45: 10.6x | O45: 14.5x | P45: 23.0x | Q45: 250
B46: WACC | C46: 0.0739 | D46: 1116.6943 | E46: 1194.4332 | F46: 1288.0695 | G46: 1403.0354 | H46: 1547.5554 | K46: Richemont | M46: 3.5x | N46: 12.4x | O46: 17.1x | P46: 22.4x | Q46: 84.2
C47: 0.0839 | D47: 968.90686 | E47: 1023.1735 | F47: 1086.6536 | G47: 1161.911 | H47: 1252.5585 | K47: Peer Median | M47: 3.4x | N47: 11.5x | O47: 15.8x | P47: 22.7x
C48: 0.0939 | D48: 858.66793 | E48: 898.34801 | F48: 943.78717 | G48: 996.33731 | H48: 1057.8094
C49: 0.104 | D49: 772.54646 | E49: 802.51424 | F49: 836.27542 | G49: 874.59891 | H49: 918.47653
C50: 0.1139 | D50: 705.26349 | E50: 728.64605 | F50: 754.65882 | G50: 783.77204 | H50: 816.57514
B53: CONFIDENTIAL — FOR INTERNAL USE ONLY | Q53: All figures are in EUR unless stated otherwise

Sheet Historical Financials
B4: INCOME STATEMENT
B6: All figures are in millions of Euro
B7: unless stated otherwise | F7: 2020A | G7: 2021A | H7: 2022A | I7: 2023A | J7: 2024A
B10: Revenue | F10: 6389.4 | G10: 8982 | H10: 11602 | I10: 13427 | J10: 15170
B11: COGS (excl. D&A) | F11: -1971.4 | G11: -2531 | H11: -3334 | I11: -3658 | J11: -4393
B12: Gross Profit (excl. D&A) | F12: =SUM(F10:F11) -> 4418 | G12: =SUM(G10:G11) -> 6451 | H12: =SUM(H10:H11) -> 8268 | I12: =SUM(I10:I11) -> 9769 | J12: =SUM(J10:J11) -> 10777
B14: SG&A Expense | F14: -1816.3 | G14: -2259 | H14: -2745 | I14: -3320 | J14: -3749
B15: D&A Expense | F15: -509.6 | G15: -561 | H15: -607 | I15: -666 | J15: -811
B16: Other Operating Expense | F16: -36.5 | G16: -37 | H16: -40 | I16: -38 | J16: -25
B17: EBIT | F17: =SUM(F12:F16) -> 2055.6 | G17: =SUM(G12:G16) -> 3594 | H17: =SUM(H12:H16) -> 4876 | I17: =SUM(I12:I16) -> 5745 | J17: =SUM(J12:J16) -> 6192
B19: Interest Income | F19: 10.6 | G19: 12 | H19: 67 | I19: 331 | J19: 400
B20: Interest Expense | F20: -29.9 | G20: -32 | H20: -43 | I20: -56 | J20: -59
B21: Other Income (Expense) | F21: 68.5 | G21: 6 | H21: -65 | I21: 20 | J21: 67
B22: Unusual Expense | F22: -118.4 | G22: -145 | H22: -200 | I22: -200 | J22: -168
B23: EBT | F23: =SUM(F17:F22) -> 1986.4 | G23: =SUM(G17:G22) -> 3435 | H23: =SUM(H17:H22) -> 4635 | I23: =SUM(I17:I22) -> 5840 | J23: =SUM(J17:J22) -> 6432
B25: Income Taxes | F25: -613 | G25: -1015 | H25: -1305 | I25: -1623 | J25: -1845
B26: Equity in Affiliates | F26: 16.1 | G26: 34 | H26: 50 | I26: 106 | J26: 44
B27: Consolidated Net Income | F27: =SUM(F23:F26) -> 1389.5 | G27: =SUM(G23:G26) -> 2454 | H27: =SUM(H23:H26) -> 3380 | I27: =SUM(I23:I26) -> 4323 | J27: =SUM(J23:J26) -> 4631
B29: Minority Interests | F29: -4.1 | G29: -8 | H29: -13 | I29: -12 | J29: -28
B30: Net Income | F30: =SUM(F27:F29) -> 1385.4 | G30: =SUM(G27:G29) -> 2446 | H30: =SUM(H27:H29) -> 3367 | I30: =SUM(I27:I29) -> 4311 | J30: =SUM(J27:J29) -> 4603
B32: BALANCE STATEMENT
F36: 2020A | G36: 2021A | H36: 2022A | I36: 2023A | J36: 2024A
B39: Assets
B40: Cash & Short-Term Investments | F40: 4732.7 | G40: 6696 | H40: 9225 | I40: 10625 | J40: 11642
B41: Accounts Receivable | F41: 249.7 | G41: 333 | H41: 383 | I41: 431 | J41: 478
B42: Other Receivables | F42: 256.5 | G42: 58 | H42: 19 | I42: 51 | J42: 28
B43: Inventories | F43: 1289.4 | G43: 1449 | H43: 1779 | I43: 2414 | J43: 2797
B44: Other Current Assets | F44: 121.4 | G44: 309 | H44: 422 | I44: 487 | J44: 531
B45: Total Current Assets | F45: =SUM(F40:F44) -> 6649.7 | G45: =SUM(G40:G44) -> 8845 | H45: =SUM(H40:H44) -> 11828 | I45: =SUM(I40:I44) -> 14008 | J45: =SUM(J40:J44) -> 15476
B47: Net PP&E | F47: 3092.2 | G47: 3398 | H47: 3589 | I47: 4056 | J47: 4766
B48: Goodwill | F48: 42.4 | G48: 42 | H48: 0 | I48: 72 | J48: 228
B49: Other Intangible Assets | F49: 221.3 | G49: 258 | H49: 213 | I49: 225 | J49: 237
B50: Long-Term Investments | F50: 515.4 | G50: 677 | H50: 1171 | I50: 1348 | J50: 1288
B51: Deferred Tax Assets | F51: 475.2 | G51: 546 | H51: 555 | I51: 631 | J51: 929
B52: Other Non-Current Assets | F52: 54.3 | G52: 81 | H52: 103 | I52: 107 | J52: 160
B53: Total Non-Current Assets | F53: =SUM(F47:F52) -> 4400.8 | G53: =SUM(G47:G52) -> 5002 | H53: =SUM(H47:H52) -> 5631 | I53: =SUM(I47:I52) -> 6439 | J53: =SUM(J47:J52) -> 7608
B55: Total Assets | F55: =F45+F53 -> 11050.5 | G55: =G45+G53 -> 13847 | H55: =H45+H53 -> 17459 | I55: =I45+I53 -> 20447 | J55: =J45+J53 -> 23084
B57: Liabilities
B58: Accounts Payable | F58: 372.5 | G58: 450 | H58: 659 | I58: 685 | J58: 683
B59: ST Debt & Curr. Portion of LT | F59: 220.1 | G59: 249 | H59: 270 | I59: 290 | J59: 332
B60: Income Tax Payable | F60: 217.8 | G60: 347 | H60: 496 | I60: 586 | J60: 773
B61: Other Current Liabilities | F61: 1028.2 | G61: 1529 | H61: 1579 | I61: 1622 | J61: 1841
B62: Total Current Liabilities | F62: =SUM(F58:F61) -> 1838.6 | G62: =SUM(G58:G61) -> 2575 | H62: =SUM(H58:H61) -> 3004 | I62: =SUM(I58:I61) -> 3183 | J62: =SUM(J58:J61) -> 3629
B64: Long-Term Debt | F64: 1465.9 | G64: 1553 | H64: 1664 | I64: 1770 | J64: 1842
B65: Deferred Tax Liabilities | F65: 21.9 | G65: 15 | H65: 20 | I65: 2 | J65: 5
B66: Other Non-Current Liabilities | F66: 36.2 | G66: 46 | H66: 104 | I66: 107 | J66: 68
B67: Provision for Risks & Charges | F67: 296.9 | G67: 246 | H67: 211 | I67: 182 | J67: 206
B68: Total Non-Current Liabilities | F68: =SUM(F64:F67) -> 1820.9 | G68: =SUM(G64:G67) -> 1860 | H68: =SUM(H64:H67) -> 1999 | I68: =SUM(I64:I67) -> 2061 | J68: =SUM(J64:J67) -> 2121
B70: Total Liabilities | F70: =F62+F68 -> 3659.5 | G70: =G62+G68 -> 4435 | H70: =H62+H68 -> 5003 | I70: =I62+I68 -> 5244 | J70: =J62+J68 -> 5750
B72: Shareholders' Equity
B73: Common Stock & APIC | F73: 103.4 | G73: 104 | H73: 104 | I73: 104 | J73: 104
B74: Retained Earnings | F74: 0 | G74: 0 | H74: 0 | I74: 0 | J74: 0
B75: Treasury Stock | F75: -463.7 | G75: -551 | H75: -674 | I75: -698 | J75: -670
B76: CTA / Unrealizaed for Exch Gain | F76: 5.2 | G76: 178 | H76: 303 | I76: 189 | J76: 355
B77: Unrealized Gain/Loss Marketable Securities | F77: 100.3 | G77: 188 | H77: 521 | I77: 521 | J77: 551
B78: Unappropriated Reserves | F78: 7732.1 | G78: 9711 | H78: 12246 | I78: 15128 | J78: 17162
B79: Other Appropriated Reserves | F79: -97.2 | G79: -230 | H79: -60 | I79: -43 | J79: -175
B80: Total Shareholders' Equity | F80: =SUM(F73:F79) -> 7380.1 | G80: =SUM(G73:G79) -> 9400 | H80: =SUM(H73:H79) -> 12440 | I80: =SUM(I73:I79) -> 15201 | J80: =SUM(J73:J79) -> 17327
B81: Accumulated Minority Interest | F81: 10.9 | G81: 12 | H81: 16 | I81: 2 | J81: 7
B82: Total Equity | F82: =SUM(F80:F81) -> 7391 | G82: =SUM(G80:G81) -> 9412 | H82: =SUM(H80:H81) -> 12456 | I82: =SUM(I80:I81) -> 15203 | J82: =SUM(J80:J81) -> 17334
B84: Total Liabilities & Equity | F84: =F70+F82 -> 11050.5 | G84: =G70+G82 -> 13847 | H84: =H70+H82 -> 17459 | I84: =I70+I82 -> 20447 | J84: =J70+J82 -> 23084
B87: CASH FLOW STATEMENT
F91: 2020A | G91: 2021A | H91: 2022A | I91: 2023A | J91: 2024A
B94: Operating Activities
B95: Net Income | F95: 1385.4 | G95: 2445 | H95: 3367 | I95: 4311 | J95: 4603
B96: D&A | F96: 512 | G96: 561 | H96: 607 | I96: 666 | J96: 811
B97: Deferred Taxes | F97: 5.4 | G97: -15 | H97: -16 | I97: -14 | J97: -93
B98: Other Funds | F98: 111.3 | G98: 115 | H98: 220 | I98: 271 | J98: 87
B99: Changes in Working Capital:
B100: (Increase) / Decrease in Receivables | F100: 38.4 | G100: -30 | H100: -54 | I100: -122 | J100: 4
B101: (Increase) / Decrease in Inventories | F101: -157.9 | G101: -116 | H101: -324 | I101: -662 | J101: -313
B102: Increase / (Decrease) in Accounts Payable | F102: -23.7 | G102: 71 | H102: 203 | I102: 42 | J102: -60
B103: Other Working Capital Changes | F103: -207.1 | G103: 421 | H103: 248 | I103: -52 | J103: 130
B104: Cash Flow from Operations | F104: =SUM(F95:F103) -> 1663.8 | G104: =SUM(G95:G103) -> 3452 | H104: =SUM(H95:H103) -> 4251 | I104: =SUM(I95:I103) -> 4440 | J104: =SUM(J95:J103) -> 5169
B106: Investing Activities
B107: Capital Expenditures | F107: -448.4 | G107: -532 | H107: -518 | I107: -859 | J107: -1067
B108: Acquisitions | F108: 0.2 | G108: 3 | H108: 0 | I108: -288 | J108: -228
B109: Purchase / Sale of Investments | F109: -16.3 | G109: -192 | H109: -160 | I109: -52 | J109: 118
B110: Other Investing Activities | F110: 10.9 | G110: 5 | H110: 32 | I110: 92 | J110: -48
B111: Cash Flow from Investing | F111: =SUM(F107:F110) -> -453.6 | G111: =SUM(G107:G110) -> -716 | H111: =SUM(H107:H110) -> -646 | I111: =SUM(I107:I110) -> -1107 | J111: =SUM(J107:J110) -> -1225
B113: Financing Activities
B114: Dividends Paid | F114: -485.1 | G114: -485 | H114: -845 | I114: -1376 | J114: -2642
B115: Change in Capital Stock | F115: -122.2 | G115: -158 | H115: -123 | I115: -130 | J115: -37
B116: Repayments of Operating Leases | F116: -198.7 | G116: -213 | H116: -261 | I116: -277 | J116: -305
B117: Debt Issuance / (Repayment) | F117: 0.3 | G117: -8 | H117: 0 | I117: -1 | J117: -1
B118: Other Funds | F118: -4.5 | G118: -5 | H118: -8 | I118: -10 | J118: -61
B119: Cash Flow from Financing | F119: =SUM(F114:F118) -> -810.2 | G119: =SUM(G114:G118) -> -869 | H119: =SUM(H114:H118) -> -1237 | I119: =SUM(I114:I118) -> -1794 | J119: =SUM(J114:J118) -> -3046
B121: Effect of Exchange Rate | F121: -54.6 | G121: 110 | H121: 159 | I121: -138 | J121: 119
B122: Net Change in Cash | F122: =F104+F111+F119+F121 -> 345.4 | G122: =G104+G111+G119+G121 -> 1977 | H122: =H104+H111+H119+H121 -> 2527 | I122: =I104+I111+I119+I121 -> 1401 | J122: =J104+J111+J119+J121 -> 1017

Sheet Historical Analysis
B3: SECTION A: GROWTH AND MARGIN ANALYSIS
B5: REVENUE GROWTH:
F6: 2020A | G6: 2021A | H6: 2022A | I6: 2023A | J6: 2024A | L6: Trend
B7: Total Revenue ($M) | F7: ='Historical Financials'!F10 -> 6389.4 | G7: ='Historical Financials'!G10 -> 8982 | H7: ='Historical Financials'!H10 -> 11602 | I7: ='Historical Financials'!I10 -> 13427 | J7: ='Historical Financials'!J10 -> 15170
B8: YoY Growth % | G8: =(G7/F7-1) -> 0.4057658 | H8: =(H7/G7-1) -> 0.2916945 | I8: =(I7/H7-1) -> 0.15730047 | J8: =(J7/I7-1) -> 0.12981306
B9: 5Y CAGR | J9: =(J7/F7)^(1/5)-1 -> 0.18878988 | L9: YoY Growth
B11: GROSS MARGIN:
F12: 2020A | G12: 2021A | H12: 2022A | I12: 2023A | J12: 2024A | L12: Trend
B13: Gross Profit ($M) | F13: ='Historical Financials'!F12 -> 4418 | G13: ='Historical Financials'!G12 -> 6451 | H13: ='Historical Financials'!H12 -> 8268 | I13: ='Historical Financials'!I12 -> 9769 | J13: ='Historical Financials'!J12 -> 10777
B14: Gross Profit % | F14: ='Historical Financials'!F12/'Historical Financials'!F10 -> 0.69145773 | G14: ='Historical Financials'!G12/'Historical Financials'!G10 -> 0.71821421 | H14: ='Historical Financials'!H12/'Historical Financials'!H10 -> 0.71263575 | I14: ='Historical Financials'!I12/'Historical Financials'!I10 -> 0.72756386 | J14: ='Historical Financials'!J12/'Historical Financials'!J10 -> 0.71041529
B17: OPEX ANALYSIS:
F18: 2020A | G18: 2021A | H18: 2022A | I18: 2023A | J18: 2024A | L18: Trend
B19: Other Opex % of Revenue | F19: ='Historical Financials'!F16*-1/'Historical Financials'!F10 -> 0.0057125865 | G19: ='Historical Financials'!G16*-1/'Historical Financials'!G10 -> 0.0041193498 | H19: ='Historical Financials'!H16*-1/'Historical Financials'!H10 -> 0.0034476814 | I19: ='Historical Financials'!I16*-1/'Historical Financials'!I10 -> 0.0028301184 | J19: ='Historical Financials'!J16*-1/'Historical Financials'!J10 -> 0.0016479895
B20: SG&A % of Revenue | F20: ='Historical Financials'!F14*-1/'Historical Financials'!F10 -> 0.28426769 | G20: ='Historical Financials'!G14*-1/'Historical Financials'!G10 -> 0.25150301 | H20: ='Historical Financials'!H14*-1/'Historical Financials'!H10 -> 0.23659714 | I20: ='Historical Financials'!I14*-1/'Historical Financials'!I10 -> 0.24726298 | J20: ='Historical Financials'!J14*-1/'Historical Financials'!J10 -> 0.2471325
B21: D&A % of Revenue | F21: ='Historical Financials'!F15*-1/'Historical Financials'!F10 -> 0.079757098 | G21: ='Historical Financials'!G15*-1/'Historical Financials'!G10 -> 0.06245825 | H21: ='Historical Financials'!H15*-1/'Historical Financials'!H10 -> 0.052318566 | I21: ='Historical Financials'!I15*-1/'Historical Financials'!I10 -> 0.049601549 | J21: ='Historical Financials'!J15*-1/'Historical Financials'!J10 -> 0.053460778
B22: Total Opex % of Revenue | F22: =(SUM('Historical Financials'!F14:F16)*-1)/'Historical Financials'!F10 -> 0.36973738 | G22: =(SUM('Historical Financials'!G14:G16)*-1)/'Historical Financials'!G10 -> 0.31808061 | H22: =(SUM('Historical Financials'!H14:H16)*-1)/'Historical Financials'!H10 -> 0.29236339 | I22: =(SUM('Historical Financials'!I14:I16)*-1)/'Historical Financials'!I10 -> 0.29969465 | J22: =(SUM('Historical Financials'!J14:J16)*-1)/'Historical Financials'!J10 -> 0.30224127
B25: PROFITABILITY:
F26: 2020A | G26: 2021A | H26: 2022A | I26: 2023A | J26: 2024A | L26: Trend
B27: Operating Margin % | F27: ='Historical Financials'!F17/'Historical Financials'!F10 -> 0.32172035 | G27: ='Historical Financials'!G17/'Historical Financials'!G10 -> 0.4001336 | H27: ='Historical Financials'!H17/'Historical Financials'!H10 -> 0.42027237 | I27: ='Historical Financials'!I17/'Historical Financials'!I10 -> 0.42786922 | J27: ='Historical Financials'!J17/'Historical Financials'!J10 -> 0.40817403
B28: EBITDA Margin % | F28: =('Historical Financials'!F17+'Historical Financials'!F15*-1)/'Historical Financials'!F10 -> 0.40147745 | G28: =('Historical Financials'!G17+'Historical Financials'!G15*-1)/'Historical Financials'!G10 -> 0.46259185 | H28: =('Historical Financials'!H17+'Historical Financials'!H15*-1)/'Historical Financials'!H10 -> 0.47259093 | I28: =('Historical Financials'!I17+'Historical Financials'!I15*-1)/'Historical Financials'!I10 -> 0.47747077 | J28: =('Historical Financials'!J17+'Historical Financials'!J15*-1)/'Historical Financials'!J10 -> 0.46163481
B29: Net Margin % | F29: ='Historical Financials'!F30/'Historical Financials'!F10 -> 0.21682787 | G29: ='Historical Financials'!G30/'Historical Financials'!G10 -> 0.27232242 | H29: ='Historical Financials'!H30/'Historical Financials'!H10 -> 0.29020858 | I29: ='Historical Financials'!I30/'Historical Financials'!I10 -> 0.32106949 | J29: ='Historical Financials'!J30/'Historical Financials'!J10 -> 0.30342782
B33: SECTION B: CASH GENERATION AND CAPITAL EFFICIENCY
B36: CASH FLOW QUALITY:
F37: 2020A | G37: 2021A | H37: 2022A | I37: 2023A | J37: 2024A | L37: Trend
B38: OCF | F38: ='Historical Financials'!F104 -> 1663.8 | G38: ='Historical Financials'!G104 -> 3452 | H38: ='Historical Financials'!H104 -> 4251 | I38: ='Historical Financials'!I104 -> 4440 | J38: ='Historical Financials'!J104 -> 5169
B39: FCF | F39: ='Historical Financials'!F104+'Historical Financials'!F107 -> 1215.4 | G39: ='Historical Financials'!G104+'Historical Financials'!G107 -> 2920 | H39: ='Historical Financials'!H104+'Historical Financials'!H107 -> 3733 | I39: ='Historical Financials'!I104+'Historical Financials'!I107 -> 3581 | J39: ='Historical Financials'!J104+'Historical Financials'!J107 -> 4102
B42: WC DYNAMICS:
F43: 2020A | G43: 2021A | H43: 2022A | I43: 2023A | J43: 2024A | L43: Trend
B44: Changes in WC ($M):
B45: Changes in AR | F45: ='Historical Financials'!F100 -> 38.4 | G45: ='Historical Financials'!G100 -> -30 | H45: ='Historical Financials'!H100 -> -54 | I45: ='Historical Financials'!I100 -> -122 | J45: ='Historical Financials'!J100 -> 4
B46: Changes in AP | F46: ='Historical Financials'!F102 -> -23.7 | G46: ='Historical Financials'!G102 -> 71 | H46: ='Historical Financials'!H102 -> 203 | I46: ='Historical Financials'!I102 -> 42 | J46: ='Historical Financials'!J102 -> -60
B47: Changes in Inventory | F47: ='Historical Financials'!F101 -> -157.9 | G47: ='Historical Financials'!G101 -> -116 | H47: ='Historical Financials'!H101 -> -324 | I47: ='Historical Financials'!I101 -> -662 | J47: ='Historical Financials'!J101 -> -313
B48: Other WC changes | F48: ='Historical Financials'!F103 -> -207.1 | G48: ='Historical Financials'!G103 -> 421 | H48: ='Historical Financials'!H103 -> 248 | I48: ='Historical Financials'!I103 -> -52 | J48: ='Historical Financials'!J103 -> 130
B50: Net WC Impact | F50: =SUM(F45:F48) -> -350.3 | G50: =SUM(G45:G48) -> 346 | H50: =SUM(H45:H48) -> 73 | I50: =SUM(I45:I48) -> -794 | J50: =SUM(J45:J48) -> -239
B52: DSO | F52: =('Historical Financials'!F41/'Historical Financials'!F10)*365 -> 14.264328 | G52: =('Historical Financials'!G41/'Historical Financials'!G10)*365 -> 13.532064 | H52: =('Historical Financials'!H41/'Historical Financials'!H10)*365 -> 12.049216 | I52: =('Historical Financials'!I41/'Historical Financials'!I10)*365 -> 11.716318 | J52: =('Historical Financials'!J41/'Historical Financials'!J10)*365 -> 11.500989
B53: DPO | F53: =('Historical Financials'!F58/-'Historical Financials'!F11)*365 -> 68.967485 | G53: =('Historical Financials'!G58/-'Historical Financials'!G11)*365 -> 64.895298 | H53: =('Historical Financials'!H58/-'Historical Financials'!H11)*365 -> 72.146071 | I53: =('Historical Financials'!I58/-'Historical Financials'!I11)*365 -> 68.350191 | J53: =('Historical Financials'!J58/-'Historical Financials'!J11)*365 -> 56.748236
B54: DIO | F54: =('Historical Financials'!F43/-'Historical Financials'!F11)*365 -> 238.72933 | G54: =('Historical Financials'!G43/-'Historical Financials'!G11)*365 -> 208.96286 | H54: =('Historical Financials'!H43/-'Historical Financials'!H11)*365 -> 194.76155 | I54: =('Historical Financials'!I43/-'Historical Financials'!I11)*365 -> 240.87206 | J54: =('Historical Financials'!J43/-'Historical Financials'!J11)*365 -> 232.39358
B56: CCC | F56: =F52+F54-F53 -> 184.02617 | G56: =G52+G54-G53 -> 157.59963 | H56: =H52+H54-H53 -> 134.66469 | I56: =I52+I54-I53 -> 184.23819 | J56: =J52+J54-J53 -> 187.14633
B58: CAPEX REQUIREMENTS:
F59: 2020A | G59: 2021A | H59: 2022A | I59: 2023A | J59: 2024A
B61: CapEx ($M) | F61: ='Historical Financials'!F107 -> -448.4 | G61: ='Historical Financials'!G107 -> -532 | H61: ='Historical Financials'!H107 -> -518 | I61: ='Historical Financials'!I107 -> -859 | J61: ='Historical Financials'!J107 -> -1067
B62: as % of Revenue | F62: =-'Historical Financials'!F107/'Historical Financials'!F10 -> 0.070178734 | G62: =-'Historical Financials'!G107/'Historical Financials'!G10 -> 0.05922957 | H62: =-'Historical Financials'!H107/'Historical Financials'!H10 -> 0.044647475 | I62: =-'Historical Financials'!I107/'Historical Financials'!I10 -> 0.063975572 | J62: =-'Historical Financials'!J107/'Historical Financials'!J10 -> 0.07033619
B64: CapEx / Depreciation | F64: ='Historical Financials'!F107/'Historical Financials'!F15 -> 0.87990581 | G64: ='Historical Financials'!G107/'Historical Financials'!G15 -> 0.9483066 | H64: ='Historical Financials'!H107/'Historical Financials'!H15 -> 0.85337727 | I64: ='Historical Financials'!I107/'Historical Financials'!I15 -> 1.2897898 | J64: ='Historical Financials'!J107/'Historical Financials'!J15 -> 1.3156597
B66: SECTION C: BALANCE SHEET HEALTH AND RETURN METRICS
B69: LIQUIDITY:
F70: 2020A | G70: 2021A | H70: 2022A | I70: 2023A | J70: 2024A | L70: Trend
B71: Current Ratio | F71: ='Historical Financials'!F45/'Historical Financials'!F62 -> 3.6167192 | G71: ='Historical Financials'!G45/'Historical Financials'!G62 -> 3.4349515 | H71: ='Historical Financials'!H45/'Historical Financials'!H62 -> 3.9374168 | I71: ='Historical Financials'!I45/'Historical Financials'!I62 -> 4.4008797 | J71: ='Historical Financials'!J45/'Historical Financials'!J62 -> 4.2645357
B72: Quick Ratio | F72: =('Historical Financials'!F45-'Historical Financials'!F43)/'Historical Financials'!F62 -> 2.9154248 | G72: =('Historical Financials'!G45-'Historical Financials'!G43)/'Historical Financials'!G62 -> 2.872233 | H72: =('Historical Financials'!H45-'Historical Financials'!H43)/'Historical Financials'!H62 -> 3.3452064 | I72: =('Historical Financials'!I45-'Historical Financials'!I43)/'Historical Financials'!I62 -> 3.6424757 | J72: =('Historical Financials'!J45-'Historical Financials'!J43)/'Historical Financials'!J62 -> 3.4937999
B75: LEVERAGE:
F76: 2020A | G76: 2021A | H76: 2022A | I76: 2023A | J76: 2024A
B77: Total Debt | F77: ='Historical Financials'!F59+'Historical Financials'!F64 -> 1686 | G77: ='Historical Financials'!G59+'Historical Financials'!G64 -> 1802 | H77: ='Historical Financials'!H59+'Historical Financials'!H64 -> 1934 | I77: ='Historical Financials'!I59+'Historical Financials'!I64 -> 2060 | J77: ='Historical Financials'!J59+'Historical Financials'!J64 -> 2174
B78: Equity | F78: ='Historical Financials'!F80 -> 7380.1 | G78: ='Historical Financials'!G80 -> 9400 | H78: ='Historical Financials'!H80 -> 12440 | I78: ='Historical Financials'!I80 -> 15201 | J78: ='Historical Financials'!J80 -> 17327
B80: Debt / Equity | F80: =F77/F78 -> 0.22845219 | G80: =G77/G78 -> 0.19170213 | H80: =H77/H78 -> 0.15546624 | I80: =I77/I78 -> 0.1355174 | J80: =J77/J78 -> 0.12546892
B81: ICR | F81: ='Historical Financials'!F17/-'Historical Financials'!F20 -> 68.749164 | G81: ='Historical Financials'!G17/-'Historical Financials'!G20 -> 112.3125 | H81: ='Historical Financials'!H17/-'Historical Financials'!H20 -> 113.39535 | I81: ='Historical Financials'!I17/-'Historical Financials'!I20 -> 102.58929 | J81: ='Historical Financials'!J17/-'Historical Financials'!J20 -> 104.94915
B83: EQUITY & RETAINED EARNINGS:
F84: 2020A | G84: 2021A | H84: 2022A | I84: 2023A | J84: 2024A
B85: Total Shareholder's Equity | F85: ='Historical Financials'!F80 -> 7380.1 | G85: ='Historical Financials'!G80 -> 9400 | H85: ='Historical Financials'!H80 -> 12440 | I85: ='Historical Financials'!I80 -> 15201 | J85: ='Historical Financials'!J80 -> 17327
B87: YoY equity Growth | G87: =(G85-F85)/F85 -> 0.27369548 | H87: =(H85-G85)/G85 -> 0.32340426 | I87: =(I85-H85)/H85 -> 0.22194534 | J87: =(J85-I85)/I85 -> 0.13985922
B90: RETURN METRICS:
F91: 2020A | G91: 2021A | H91: 2022A | I91: 2023A | J91: 2024A
B93: RoE(%) | F93: ='Historical Financials'!F30/'Historical Financials'!F80 -> 0.18772103 | G93: ='Historical Financials'!G30/'Historical Financials'!G80 -> 0.26021277 | H93: ='Historical Financials'!H30/'Historical Financials'!H80 -> 0.27065916 | I93: ='Historical Financials'!I30/'Historical Financials'!I80 -> 0.28359976 | J93: ='Historical Financials'!J30/'Historical Financials'!J80 -> 0.26565476
B94: =NI/Shareholder's Equity
B96: RoA(%) | F96: ='Historical Financials'!F30/'Historical Financials'!F55 -> 0.12536989 | G96: ='Historical Financials'!G30/'Historical Financials'!G55 -> 0.17664476 | H96: ='Historical Financials'!H30/'Historical Financials'!H55 -> 0.19285182 | I96: ='Historical Financials'!I30/'Historical Financials'!I55 -> 0.21083778 | J96: ='Historical Financials'!J30/'Historical Financials'!J55 -> 0.19940218
B97: =Net Income/Avg Assets
B99: ROIC(%)
B100: EBIT | F100: ='Historical Financials'!F17 -> 2055.6 | G100: ='Historical Financials'!G17 -> 3594 | H100: ='Historical Financials'!H17 -> 4876 | I100: ='Historical Financials'!I17 -> 5745 | J100: ='Historical Financials'!J17 -> 6192
B101: x (1-Tax rate) | F101: =1-(-'Historical Financials'!F25/'Historical Financials'!F23) -> 0.69140153 | G101: =1-(-'Historical Financials'!G25/'Historical Financials'!G23) -> 0.70451237 | H101: =1-(-'Historical Financials'!H25/'Historical Financials'!H23) -> 0.7184466 | I101: =1-(-'Historical Financials'!I25/'Historical Financials'!I23) -> 0.72208904 | J101: =1-(-'Historical Financials'!J25/'Historical Financials'!J23) -> 0.71315299
B102: =NOPAT | F102: =F100*F101 -> 1421.245 | G102: =G100*G101 -> 2532.0175 | H102: =H100*H101 -> 3503.1456 | I102: =I100*I101 -> 4148.4015 | J102: =J100*J101 -> 4415.8433
B104: Invested Capital
B105: Total Equity | F105: ='Historical Financials'!F82 -> 7391 | G105: ='Historical Financials'!G82 -> 9412 | H105: ='Historical Financials'!H82 -> 12456 | I105: ='Historical Financials'!I82 -> 15203 | J105: ='Historical Financials'!J82 -> 17334
B106: +Total Debt | F106: ='Historical Financials'!F59+'Historical Financials'!F64 -> 1686 | G106: ='Historical Financials'!G59+'Historical Financials'!G64 -> 1802 | H106: ='Historical Financials'!H59+'Historical Financials'!H64 -> 1934 | I106: ='Historical Financials'!I59+'Historical Financials'!I64 -> 2060 | J106: ='Historical Financials'!J59+'Historical Financials'!J64 -> 2174
B107: -Excess Cash | F107: =-'Historical Financials'!F40 -> -4732.7 | G107: =-'Historical Financials'!G40 -> -6696 | H107: =-'Historical Financials'!H40 -> -9225 | I107: =-'Historical Financials'!I40 -> -10625 | J107: =-'Historical Financials'!J40 -> -11642
B108: = Invested Capital | F108: =F105+F106+F107 -> 4344.3 | G108: =G105+G106+G107 -> 4518 | H108: =H105+H106+H107 -> 5165 | I108: =I105+I106+I107 -> 6638 | J108: =J105+J106+J107 -> 7866
B110: = NOPAT/Invested Capital | F110: =F102/F108 -> 0.32715167 | G110: =G102/G108 -> 0.56042883 | H110: =H102/H108 -> 0.67824698 | I110: =I102/I108 -> 0.62494751 | J110: =J102/J108 -> 0.56138359

Sheet Master Assumptions
B2: MASTER ASSUMPTIONS
B3: Hermes International S.A. (RMS-FR) | Forecast Assumptions
B5: SCENARIO SELECTOR
B6: Active Scenario: | C6: Base
B7: Scenario Code: | C7: =IF(C6="Bull",1,IF(C6="Base",2,3)) -> 2 | D7: (1=Bull, 2=Base, 3=Bear)
B9: ACTIVE ASSUMPTIONS | F9: 2025E | G9: 2026E | H9: 2027E | I9: 2028E | J9: 2029E
B10: REVENUE & MARGINS
B11: Revenue Growth % | F11: ='Supporting Schedules'!C9 -> 0.11925049 | G11: ='Supporting Schedules'!D9 -> 0.10615916 | H11: ='Supporting Schedules'!E9 -> 0.096119716 | I11: ='Supporting Schedules'!F9 -> 0.087935973 | J11: ='Supporting Schedules'!G9 -> 0.079241748
B12: Gross Margin % | F12: ='Supporting Schedules'!C120 -> 0.71720728 | G12: ='Supporting Schedules'!D120 -> 0.71720728 | H12: ='Supporting Schedules'!E120 -> 0.71720728 | I12: ='Supporting Schedules'!F120 -> 0.71720728 | J12: ='Supporting Schedules'!G120 -> 0.71720728
B14: OPERATING EXPENSES (% of Revenue)
B15: Other Opex % | F15: ='Supporting Schedules'!C138 -> 0.0030112848 | G15: ='Supporting Schedules'!D138 -> 0.0030112848 | H15: ='Supporting Schedules'!E138 -> 0.0030112848 | I15: ='Supporting Schedules'!F138 -> 0.0030112848 | J15: ='Supporting Schedules'!G138 -> 0.0030112848
B16: SG&A % | F16: ='Supporting Schedules'!C139 -> 0.24562391 | G16: ='Supporting Schedules'!D139 -> 0.24562391 | H16: ='Supporting Schedules'!E139 -> 0.24562391 | I16: ='Supporting Schedules'!F139 -> 0.24562391 | J16: ='Supporting Schedules'!G139 -> 0.24562391
B18: Depreciation (% of Beg. PPE )
B19: Depreciation % | F19: ='Supporting Schedules'!D219 -> 0.16666454 | G19: =F19 -> 0.16666454 | H19: =G19 -> 0.16666454 | I19: =H19 -> 0.16666454 | J19: =I19 -> 0.16666454
B22: TAX & OTHER
B23: Effective Tax Rate % | F23: ='Supporting Schedules'!C303 -> 0.29007949 | G23: =F23 -> 0.29007949 | H23: =G23 -> 0.29007949 | I23: =H23 -> 0.29007949 | J23: =I23 -> 0.29007949
B25: BALANCE SHEET & CAPEX
B26: DSO (Days) | F26: ='Supporting Schedules'!H173 -> 11.608653 | G26: ='Supporting Schedules'!I173 -> 11.608653 | H26: ='Supporting Schedules'!J173 -> 11.608653 | I26: ='Supporting Schedules'!K173 -> 11.608653 | J26: ='Supporting Schedules'!L173 -> 11.608653
B27: DIO (Days) | F27: ='Supporting Schedules'!H182 -> 236.63282 | G27: ='Supporting Schedules'!I182 -> 236.63282 | H27: ='Supporting Schedules'!J182 -> 236.63282 | I27: ='Supporting Schedules'!K182 -> 236.63282 | J27: ='Supporting Schedules'!L182 -> 236.63282
B28: DPO (Days) | F28: ='Supporting Schedules'!H190 -> 55.218802 | G28: ='Supporting Schedules'!I190 -> 55.218802 | H28: ='Supporting Schedules'!J190 -> 55.218802 | I28: ='Supporting Schedules'!K190 -> 55.218802 | J28: ='Supporting Schedules'!L190 -> 55.218802
B29: Other Current Assets % of Revenue | F29: ='Supporting Schedules'!$D$200 -> 0.045834556 | G29: ='Supporting Schedules'!$D$200 -> 0.045834556 | H29: ='Supporting Schedules'!$D$200 -> 0.045834556 | I29: ='Supporting Schedules'!$D$200 -> 0.045834556 | J29: ='Supporting Schedules'!$D$200 -> 0.045834556
B30: Income Tax Payable % of Tax Expense | F30: ='Supporting Schedules'!C290 -> 0.37145606 | G30: =F30 -> 0.37145606 | H30: =G30 -> 0.37145606 | I30: =H30 -> 0.37145606 | J30: =I30 -> 0.37145606
B31: Other CL % of Revenue | F31: ='Supporting Schedules'!$C$316 -> 0.12608551 | G31: ='Supporting Schedules'!$C$316 -> 0.12608551 | H31: ='Supporting Schedules'!$C$316 -> 0.12608551 | I31: ='Supporting Schedules'!$C$316 -> 0.12608551 | J31: ='Supporting Schedules'!$C$316 -> 0.12608551
B32: Capex as % of Revenue | F32: ='Supporting Schedules'!$C$211 -> 0.067155881 | G32: ='Supporting Schedules'!$C$211 -> 0.067155881 | H32: ='Supporting Schedules'!$C$211 -> 0.067155881 | I32: ='Supporting Schedules'!$C$211 -> 0.067155881 | J32: ='Supporting Schedules'!$C$211 -> 0.067155881
B35: Other Assumptions
B36: Other Funds (as % of Revenue) | F36: ='Supporting Schedules'!C358 -> 0.01734208 | G36: =F36 -> 0.01734208 | H36: =G36 -> 0.01734208 | I36: =H36 -> 0.01734208 | J36: =I36 -> 0.01734208
B37: Divident Payout % | F37: ='Supporting Schedules'!$C$329 -> 0.30676677 | G37: ='Supporting Schedules'!$C$329 -> 0.30676677 | H37: ='Supporting Schedules'!$C$329 -> 0.30676677 | I37: ='Supporting Schedules'!$C$329 -> 0.30676677 | J37: ='Supporting Schedules'!$C$329 -> 0.30676677
B38: Operating Leases(% of D&A) | F38: ='Supporting Schedules'!$C$371 -> 0.39831423 | G38: ='Supporting Schedules'!$C$371 -> 0.39831423 | H38: ='Supporting Schedules'!$C$371 -> 0.39831423 | I38: ='Supporting Schedules'!$C$371 -> 0.39831423 | J38: ='Supporting Schedules'!$C$371 -> 0.39831423
B40: VALUATION PARAMETERS
B41: Terminal Growth Rate | J41: =2.5% -> 0.025

Sheet Supporting Schedules
B2: SUPPORTING SCHEDULES
B3: Hermes International S.A. (RMS-FR)
B5: REVENUE SCHEDULE -SEGMENT BASED BOTTOM UP APPROACH
B7: Scenario Assumptions — Revenue Growth Rates
C8: 2025E | D8: 2026E | E8: 2027E | F8: 2028E | G8: 2029E
C9: =K95 -> 0.11925049 | D9: =L95 -> 0.10615916 | E9: =M95 -> 0.096119716 | F9: =N95 -> 0.087935973 | G9: =O95 -> 0.079241748
B12: Section A: Segment wise Revenue Data
B13: All figures in millions
B14: of Euro | D14: 2020A | E14: 2021A | F14: 2022A | G14: 2023A | H14: 2024A
B16: Leather Goods & Saddlery | D16: 3209.2 | E16: 4091 | F16: 4963 | G16: 5547 | H16: 6457
B17: Clothing & Accessories | D17: 1408.9 | E17: 2219 | F17: 3152 | G17: 3879 | H17: 4405
B18: Other Hermes Trades | D18: 642.6 | E18: 1001 | F18: 1371 | G18: 1653 | H18: 1909
B19: Silk & Textiles | D19: 452 | E19: 669 | F19: 842 | G19: 932 | H19: 950
B20: Watchmaking | D20: 195.9 | E20: 337 | F20: 519 | G20: 611 | H20: 577
B21: Perfume & Beauty | D21: 263.2 | E21: 385 | F21: 448 | G21: 492 | H21: 535
B22: Other | D22: 217.7 | E22: 279 | F22: 306 | G22: 313 | H22: 337
B23: Total | D23: =SUM(D16:D22) -> 6389.5 | E23: =SUM(E16:E22) -> 8981 | F23: =SUM(F16:F22) -> 11601 | G23: =SUM(G16:G22) -> 13427 | H23: =SUM(H16:H22) -> 15170
B26: YoY Growth (%) | D26: 2020A | E26: 2021A | F26: 2022A | G26: 2023A | H26: 2024A
B27: Leather Goods & Saddlery | D27: - | E27: =(E16-D16)/D16 -> 0.27477253 | F27: =(F16-E16)/E16 -> 0.21315082 | G27: =(G16-F16)/F16 -> 0.11767076 | H27: =(H16-G16)/G16 -> 0.16405264
B28: Clothing & Accessories | D28: - | E28: =(E17-D17)/D17 -> 0.57498758 | F28: =(F17-E17)/E17 -> 0.42045967 | G28: =(G17-F17)/F17 -> 0.23064721 | H28: =(H17-G17)/G17 -> 0.13560196
B29: Other Hermes Trades | D29: - | E29: =(E18-D18)/D18 -> 0.5577342 | F29: =(F18-E18)/E18 -> 0.36963037 | G29: =(G18-F18)/F18 -> 0.20568928 | H29: =(H18-G18)/G18 -> 0.15486993
B30: Silk & Textiles | D30: - | E30: =(E19-D19)/D19 -> 0.4800885 | F30: =(F19-E19)/E19 -> 0.25859492 | G30: =(G19-F19)/F19 -> 0.10688836 | H30: =(H19-G19)/G19 -> 0.019313305
B31: Watchmaking | D31: - | E31: =(E20-D20)/D20 -> 0.72026544 | F31: =(F20-E20)/E20 -> 0.54005935 | G31: =(G20-F20)/F20 -> 0.17726397 | H31: =(H20-G20)/G20 -> -0.055646481
B32: Perfume & Beauty | D32: - | E32: =(E21-D21)/D21 -> 0.46276596 | F32: =(F21-E21)/E21 -> 0.16363636 | G32: =(G21-F21)/F21 -> 0.098214286 | H32: =(H21-G21)/G21 -> 0.087398374
B33: Other | D33: - | E33: =(E22-D22)/D22 -> 0.28158016 | F33: =(F22-E22)/E22 -> 0.096774194 | G33: =(G22-F22)/F22 -> 0.022875817 | H33: =(H22-G22)/G22 -> 0.076677316
B34: Total Growth | D34: - | E34: =(E23-D23)/D23 -> 0.40558729 | F34: =(F23-E23)/E23 -> 0.29172698 | G34: =(G23-F23)/F23 -> 0.15740022 | H34: =(H23-G23)/G23 -> 0.12981306
B36: Segment Mix (%) | D36: 2020A | E36: 2021A | F36: 2022A | G36: 2023A | H36: 2024A
B37: Leather Goods & Saddlery | D37: =D16/D$23 -> 0.50226152 | E37: =E16/E$23 -> 0.4555172 | F37: =F16/F$23 -> 0.42780795 | G37: =G16/G$23 -> 0.41312281 | H37: =H16/H$23 -> 0.42564272
B38: Clothing & Accessories | D38: =D17/D$23 -> 0.22050239 | E38: =E17/E$23 -> 0.24707716 | F38: =F17/F$23 -> 0.27170072 | G38: =G17/G$23 -> 0.28889551 | H38: =H17/H$23 -> 0.29037574
B39: Other Hermes Trades | D39: =D18/D$23 -> 0.10057125 | E39: =E18/E$23 -> 0.11145752 | F39: =F18/F$23 -> 0.11817947 | G39: =G18/G$23 -> 0.12311015 | H39: =H18/H$23 -> 0.12584047
B40: Silk & Textiles | D40: =D19/D$23 -> 0.07074106 | E40: =E19/E$23 -> 0.074490591 | F40: =F19/F$23 -> 0.07257995 | G40: =G19/G$23 -> 0.069412378 | H40: =H19/H$23 -> 0.062623599
B41: Watchmaking | D41: =D20/D$23 -> 0.030659676 | E41: =E20/E$23 -> 0.037523661 | F41: =F20/F$23 -> 0.044737523 | G41: =G20/G$23 -> 0.045505325 | H41: =H20/H$23 -> 0.038035597
B42: Perfume & Beauty | D42: =D21/D$23 -> 0.041192582 | E42: =E21/E$23 -> 0.042868277 | F42: =F21/F$23 -> 0.038617361 | G42: =G21/G$23 -> 0.036642586 | H42: =H21/H$23 -> 0.035266974
B43: Other | D43: =D22/D$23 -> 0.034071524 | E43: =E22/E$23 -> 0.031065583 | F43: =F22/F$23 -> 0.026377036 | G43: =G22/G$23 -> 0.023311239 | H43: =H22/H$23 -> 0.022214898
B44: Check (=100%) | D44: =SUM(D37:D43) -> 1 | E44: =SUM(E37:E43) -> 1 | F44: =SUM(F37:F43) -> 1 | G44: =SUM(G37:G43) -> 1 | H44: =SUM(H37:H43) -> 1
B46: Historical Statistics | E46: 3Y CAGR | F46: 2Y CAGR | G46: 3Y Avg | H46: Last Yr
B47: Leather Goods & Saddlery | E47: =(H16/E16)^(1/3)-1 -> 0.16430591 | F47: =(H16/F16)^(1/2)-1 -> 0.14062597 | G47: =AVERAGE(F27:H27) -> 0.16495807 | H47: =H27 -> 0.16405264
B48: Clothing & Accessories | E48: =(H17/E17)^(1/3)-1 -> 0.25679044 | F48: =(H17/F17)^(1/2)-1 -> 0.18216978 | G48: =AVERAGE(F28:H28) -> 0.26223628 | H48: =H28 -> 0.13560196
B49: Other Hermes Trades | E49: =(H18/E18)^(1/3)-1 -> 0.24010165 | F49: =(H18/F18)^(1/2)-1 -> 0.18000606 | G49: =AVERAGE(F29:H29) -> 0.24339653 | H49: =H29 -> 0.15486993
B50: Silk & Textiles | E50: =(H19/E19)^(1/3)-1 -> 0.12399875 | F50: =(H19/F19)^(1/2)-1 -> 0.062198679 | G50: =AVERAGE(F30:H30) -> 0.12826553 | H50: =H30 -> 0.019313305
B51: Watchmaking | E51: =(H20/E20)^(1/3)-1 -> 0.19632351 | F51: =(H20/F20)^(1/2)-1 -> 0.05439716 | G51: =AVERAGE(F31:H31) -> 0.22055895 | H51: =H31 -> -0.055646481
B52: Perfume & Beauty | E52: =(H21/E21)^(1/3)-1 -> 0.11591475 | F52: =(H21/F21)^(1/2)-1 -> 0.092792949 | G52: =AVERAGE(F32:H32) -> 0.11641634 | H52: =H32 -> 0.087398374
B53: Other | E53: =(H22/E22)^(1/3)-1 -> 0.064981097 | F53: =(H22/F22)^(1/2)-1 -> 0.049431841 | G53: =AVERAGE(F33:H33) -> 0.065442442 | H53: =H33 -> 0.076677316
B54: Total | E54: =(H23/E23)^(1/3)-1 -> 0.19093199 | F54: =(H23/F23)^(1/2)-1 -> 0.14352346 | G54: =AVERAGE(F34:H34) -> 0.19298009 | H54: =H34 -> 0.12981306
B57: Section B: Growth Assumptions
B58: Growth Rate Assumptions
B59: (Blue = Input)
J60: 2025E | K60: 2026E | L60: 2027E | M60: 2028E | N60: 2029E
B61: Leather Goods & Saddlery | J61: 0.14 | K61: 0.12 | L61: 0.11 | M61: 0.1 | N61: 0.09
B62: Clothing & Accessories | J62: 0.12 | K62: 0.11 | L62: 0.1 | M62: 0.09 | N62: 0.08
B63: Other Hermes Trades | J63: 0.14 | K63: 0.12 | L63: 0.1 | M63: 0.09 | N63: 0.08
B64: Silk & Textiles | J64: 0.04 | K64: 0.04 | L64: 0.03 | M64: 0.03 | N64: 0.03
B65: Watchmaking | J65: 0.02 | K65: 0.03 | L65: 0.04 | M65: 0.04 | N65: 0.04
B66: Perfume & Beauty | J66: 0.08 | K66: 0.07 | L66: 0.06 | M66: 0.06 | N66: 0.05
B67: Other | J67: 0.05 | K67: 0.05 | L67: 0.04 | M67: 0.04 | N67: 0.04
B69: Implied Total Growth | J69: =(K84-I84)/I84 -> 0.11925049 | K69: =(L84-K84)/K84 -> 0.10615916 | L69: =(M84-L84)/L84 -> 0.096119716 | M69: =(N84-M84)/M84 -> 0.087935973 | N69: =(O84-N84)/N84 -> 0.079241748
B74: Section C: Projected Segment Revenue
B76: Revenue by Segment (€M) | E76: 2020A | F76: 2021A | G76: 2022A | H76: 2023A | I76: 2024A | K76: 2025E | L76: 2026E | M76: 2027E | N76: 2028E | O76: 2029E
B77: Leather Goods & Saddlery | E77: =D16 -> 3209.2 | F77: =E16 -> 4091 | G77: =F16 -> 4963 | H77: =G16 -> 5547 | I77: =H16 -> 6457 | K77: =I77*(1+J61) -> 7360.98 | L77: =K77*(1+K61) -> 8244.2976 | M77: =L77*(1+L61) -> 9151.1703 | N77: =M77*(1+M61) -> 10066.287 | O77: =N77*(1+N61) -> 10972.253
B78: Clothing & Accessories | E78: =D17 -> 1408.9 | F78: =E17 -> 2219 | G78: =F17 -> 3152 | H78: =G17 -> 3879 | I78: =H17 -> 4405 | K78: =I78*(1+J62) -> 4933.6 | L78: =K78*(1+K62) -> 5476.296 | M78: =L78*(1+L62) -> 6023.9256 | N78: =M78*(1+M62) -> 6566.0789 | O78: =N78*(1+N62) -> 7091.3652
B79: Other Hermes Trades | E79: =D18 -> 642.6 | F79: =E18 -> 1001 | G79: =F18 -> 1371 | H79: =G18 -> 1653 | I79: =H18 -> 1909 | K79: =I79*(1+J63) -> 2176.26 | L79: =K79*(1+K63) -> 2437.4112 | M79: =L79*(1+L63) -> 2681.1523 | N79: =M79*(1+M63) -> 2922.456 | O79: =N79*(1+N63) -> 3156.2525
B80: Silk & Textiles | E80: =D19 -> 452 | F80: =E19 -> 669 | G80: =F19 -> 842 | H80: =G19 -> 932 | I80: =H19 -> 950 | K80: =I80*(1+J64) -> 988 | L80: =K80*(1+K64) -> 1027.52 | M80: =L80*(1+L64) -> 1058.3456 | N80: =M80*(1+M64) -> 1090.096 | O80: =N80*(1+N64) -> 1122.7988
B81: Watchmaking | E81: =D20 -> 195.9 | F81: =E20 -> 337 | G81: =F20 -> 519 | H81: =G20 -> 611 | I81: =H20 -> 577 | K81: =I81*(1+J65) -> 588.54 | L81: =K81*(1+K65) -> 606.1962 | M81: =L81*(1+L65) -> 630.44405 | N81: =M81*(1+M65) -> 655.66181 | O81: =N81*(1+N65) -> 681.88828
B82: Perfume & Beauty | E82: =D21 -> 263.2 | F82: =E21 -> 385 | G82: =F21 -> 448 | H82: =G21 -> 492 | I82: =H21 -> 535 | K82: =I82*(1+J66) -> 577.8 | L82: =K82*(1+K66) -> 618.246 | M82: =L82*(1+L66) -> 655.34076 | N82: =M82*(1+M66) -> 694.66121 | O82: =N82*(1+N66) -> 729.39427
B83: Other | E83: =D22 -> 217.7 | F83: =E22 -> 279 | G83: =F22 -> 306 | H83: =G22 -> 313 | I83: =H22 -> 337 | K83: =I83*(1+J67) -> 353.85 | L83: =K83*(1+K67) -> 371.5425 | M83: =L83*(1+L67) -> 386.4042 | N83: =M83*(1+M67) -> 401.86037 | O83: =N83*(1+N67) -> 417.93478
B84: Total Revenue | E84: =SUM(E77:E83) -> 6389.5 | F84: =SUM(F77:F83) -> 8981 | G84: =SUM(G77:G83) -> 11601 | H84: =SUM(H77:H83) -> 13427 | I84: =SUM(I77:I83) -> 15170 | K84: =SUM(K77:K83) -> 16979.03 | L84: =SUM(L77:L83) -> 18781.51 | M84: =SUM(M77:M83) -> 20586.783 | N84: =SUM(N77:N83) -> 22397.102 | O84: =SUM(O77:O83) -> 24171.887
B86: YoY Growth (%) | K86: =(K84-I84)/I84 -> 0.11925049 | L86: =(L84-K84)/K84 -> 0.10615916 | M86: =(M84-L84)/L84 -> 0.096119716 | N86: =(N84-M84)/M84 -> 0.087935973 | O86: =(O84-N84)/N84 -> 0.079241748
B88: 5Y Projection CAGR (2024-2029) | O88: =(O84/I84)^(1/5)-1 -> 0.097652815
B91: Section D: Consolidated Revenue Output
B93: Revenue Summary | E93: 2020A | F93: 2021A | G93: 2022A | H93: 2023A | I93: 2024A | K93: 2025E | L93: 2026E | M93: 2027E | N93: 2028E | O93: 2029E
B94: Total Revenue (€M) | E94: =D23 -> 6389.5 | F94: =E23 -> 8981 | G94: =F23 -> 11601 | H94: =G23 -> 13427 | I94: =H23 -> 15170 | K94: =K84 -> 16979.03 | L94: =L84 -> 18781.51 | M94: =M84 -> 20586.783 | N94: =N84 -> 22397.102 | O94: =O84 -> 24171.887
B95: YoY Growth (%) | E95: - | F95: =(F94-E94)/E94 -> 0.40558729 | G95: =(G94-F94)/F94 -> 0.29172698 | H95: =(H94-G94)/G94 -> 0.15740022 | I95: =(I94-H94)/H94 -> 0.12981306 | K95: =(K94-I94)/I94 -> 0.11925049 | L95: =(L94-K94)/K94 -> 0.10615916 | M95: =(M94-L94)/L94 -> 0.096119716 | N95: =(N94-M94)/M94 -> 0.087935973 | O95: =(O94-N94)/N94 -> 0.079241748
B97: Key Metrics
B98: Historical 5Y CAGR (2020-2024) | H98: =(I94/E94)^(1/4)-1 -> 0.24130835
B99: Historical 3Y CAGR (2021-2024) | H99: =(I94/G94)^(1/2)-1 -> 0.14352346
B100: Projected 5Y CAGR (2024-2029) | O100: =(O94/I94)^(1/5)-1 -> 0.097652815
B102: Revenue Growth Deceleration
B103: Change vs Prior Year (bps) | F103: =(G95-F95)*10000 -> -1138.6031 | G103: =(H95-G95)*10000 -> -1343.2676 | H103: =(I95-H95)*10000 -> -275.87161 | K103: =(K95-I95)*10000 -> -105.62569 | L103: =(L95-K95)*10000 -> -130.91338 | M103: =(M95-L95)*10000 -> -100.3944 | N103: =(N95-M95)*10000 -> -81.837429 | O103: =(O95-N95)*10000 -> -86.942254
B106: Notes & Assumptions
B108: 1. All figures in €M unless otherwise stated
B109: 2. Historical data sourced from Hermès Annual Reports (URD) 2020-2024
B110: 3. Growth assumptions anchored to 2Y CAGR with fade toward long-term sustainable rates
B111: 4. Leather Goods growth constrained by artisan training and workshop expansion capacity
B112: 5. Watchmaking assumes gradual recovery from 2024 trough (-5.6% actual)
B113: 6. FX assumptions: Constant currency (no FX impact modeled)
B114: 7. Blue cells = Inputs (adjustable); Black cells = Formulas (calculated)
B116: GROSS MARGIN CALCULATIONS
B118: Scenario Assumptions
C119: 2025E | D119: 2026E | E119: 2027E | F119: 2028E | G119: 2029E
C120: =AVERAGE($D$126:$G$126) -> 0.71720728 | D120: =AVERAGE($D$126:$G$126) -> 0.71720728 | E120: =AVERAGE($D$126:$G$126) -> 0.71720728 | F120: =AVERAGE($D$126:$G$126) -> 0.71720728 | G120: =AVERAGE($D$126:$G$126) -> 0.71720728
B122: SECTION A : Historical Analysis
C123: 2020A | D123: 2021A | E123: 2022A | F123: 2023A | G123: 2024A
B125: Gross Proft($M) | C125: ='Historical Analysis'!F13 -> 4418 | D125: ='Historical Analysis'!G13 -> 6451 | E125: ='Historical Analysis'!H13 -> 8268 | F125: ='Historical Analysis'!I13 -> 9769 | G125: ='Historical Analysis'!J13 -> 10777
B126: Gross Margin% | C126: ='Historical Analysis'!F14 -> 0.69145773 | D126: ='Historical Analysis'!G14 -> 0.71821421 | E126: ='Historical Analysis'!H14 -> 0.71263575 | F126: ='Historical Analysis'!I14 -> 0.72756386 | G126: ='Historical Analysis'!J14 -> 0.71041529
B129: Notes & Assumptions
B131: 1. Gross Margin is stable so excluding COVID year taking average of last 4 years
B133: OTHER OPEX, SG&A CALCULATIONS
B135: Scenario Assumptions
C136: 2025E | D136: 2026E | E136: 2027E | F136: 2028E | G136: 2029E
B138: Other Opex | C138: =AVERAGE($D$145:$G$145) -> 0.0030112848 | D138: =AVERAGE($D$145:$G$145) -> 0.0030112848 | E138: =AVERAGE($D$145:$G$145) -> 0.0030112848 | F138: =AVERAGE($D$145:$G$145) -> 0.0030112848 | G138: =AVERAGE($D$145:$G$145) -> 0.0030112848
...

Sheet Forecast Model
B3: INCOME STATEMENT
B5: All figures in millions of euros | F5: 2020A | G5: 2021A | H5: 2022A | I5: 2023A | J5: 2024A | K5: 2025E | L5: 2026E | M5: 2027E | N5: 2028E | O5: 2029E
B6: unless stated otherwise
B8: Revenue | F8: 6389.4 | G8: 8982 | H8: 11602 | I8: 13427 | J8: 15170 | K8: =J8*(1+'Master Assumptions'!F11) -> 16979.03 | L8: =K8*(1+'Master Assumptions'!G11) -> 18781.51 | M8: =L8*(1+'Master Assumptions'!H11) -> 20586.783 | N8: =M8*(1+'Master Assumptions'!I11) -> 22397.102 | O8: =N8*(1+'Master Assumptions'!J11) -> 24171.887
B9: COGS (excl. D&A) | F9: -1971.4 | G9: -2531 | H9: -3334 | I9: -3658 | J9: -4393 | K9: =K10-K8 -> -4801.5461 | L9: =L10-L8 -> -5311.2742 | M9: =M10-M8 -> -5821.7923 | N9: =N10-N8 -> -6333.7373 | O9: =O10-O8 -> -6835.6337
B10: Gross Profit (excl. D&A) | F10: =SUM(F8:F9) -> 4418 | G10: =SUM(G8:G9) -> 6451 | H10: =SUM(H8:H9) -> 8268 | I10: =SUM(I8:I9) -> 9769 | J10: =SUM(J8:J9) -> 10777 | K10: ='Master Assumptions'!F12*'Forecast Model'!K8 -> 12177.484 | L10: ='Master Assumptions'!G12*'Forecast Model'!L8 -> 13470.235 | M10: ='Master Assumptions'!H12*'Forecast Model'!M8 -> 14764.991 | N10: ='Master Assumptions'!I12*'Forecast Model'!N8 -> 16063.364 | O10: ='Master Assumptions'!J12*'Forecast Model'!O8 -> 17336.253
B12: SG&A Expense | F12: -1816.3 | G12: -2259 | H12: -2745 | I12: -3320 | J12: -3749 | K12: =-'Master Assumptions'!F16*'Forecast Model'!K8 -> -4170.4557 | L12: =-'Master Assumptions'!G16*'Forecast Model'!L8 -> -4613.1877 | M12: =-'Master Assumptions'!H16*'Forecast Model'!M8 -> -5056.606 | N12: =-'Master Assumptions'!I16*'Forecast Model'!N8 -> -5501.2636 | O12: =-'Master Assumptions'!J16*'Forecast Model'!O8 -> -5937.1933
B13: D&A Expense | F13: -509.6 | G13: -561 | H13: -607 | I13: -666 | J13: -811 | K13: =-'Supporting Schedules'!C245 -> -794.32318 | L13: =-'Supporting Schedules'!D245 -> -851.97554 | M13: =-'Supporting Schedules'!E245 -> -920.19354 | N13: =-'Supporting Schedules'!F245 -> -997.24756 | O13: =-'Supporting Schedules'!G245 -> -1081.7214
B14: Other Operating Expense | F14: -36.5 | G14: -37 | H14: -40 | I14: -38 | J14: -25 | K14: =-'Master Assumptions'!F15*'Forecast Model'!K8 -> -51.128695 | L14: =-'Master Assumptions'!G15*'Forecast Model'!L8 -> -56.556474 | M14: =-'Master Assumptions'!H15*'Forecast Model'!M8 -> -61.992666 | N14: =-'Master Assumptions'!I15*'Forecast Model'!N8 -> -67.444051 | O14: =-'Master Assumptions'!J15*'Forecast Model'!O8 -> -72.788436
B15: EBIT | F15: =SUM(F10:F14) -> 2055.6 | G15: =SUM(G10:G14) -> 3594 | H15: =SUM(H10:H14) -> 4876 | I15: =SUM(I10:I14) -> 5745 | J15: =SUM(J10:J14) -> 6192 | K15: =SUM(K10:K14) -> 7161.5764 | L15: =SUM(L10:L14) -> 7948.5156 | M15: =SUM(M10:M14) -> 8726.1983 | ... O15: =SUM(O10:O14) -> 10244.55
B17: Interest Income | F17: 10.6 | G17: 12 | H17: 67 | I17: 331 | J17: 400
B18: Interest Expense | F18: -29.9 | G18: -32 | H18: -43 | I18: -56 | J18: -59 | K18: ='Supporting Schedules'!C275 -> -59.049515 | L18: ='Supporting Schedules'!D275 -> -59.049515 | M18: ='Supporting Schedules'!E275 -> -59.049515 | N18: ='Supporting Schedules'!F275 -> -59.049515 | O18: ='Supporting Schedules'!G275 -> -59.049515
B19: Other Income (Expense) | F19: 68.5 | G19: 6 | H19: -65 | I19: 20 | J19: 67 | K19: =0 -> 0 | L19: =0 -> 0 | M19: =0 -> 0 | N19: =0 -> 0 | O19: =0 -> 0
B20: Unusual Expense | F20: -118.4 | G20: -145 | H20: -200 | I20: -200 | J20: -168 | K20: =0 -> 0 | L20: =0 -> 0 | M20: =0 -> 0 | N20: =0 -> 0 | O20: =0 -> 0
B21: EBT | F21: =SUM(F15:F20) -> 1986.4 | G21: =SUM(G15:G20) -> 3435 | H21: =SUM(H15:H20) -> 4635 | I21: =SUM(I15:I20) -> 5840 | J21: =SUM(J15:J20) -> 6432 | K21: =SUM(K15:K20) -> 7102.5269 | L21: =SUM(L15:L20) -> 7889.4661 | M21: =SUM(M15:M20) -> 8667.1488 | ... O21: =SUM(O15:O20) -> 10185.501
B23: Income Taxes | F23: -613 | G23: -1015 | H23: -1305 | I23: -1623 | J23: -1845 | K23: =-K21*'Master Assumptions'!F23 -> -2060.2974 | L23: =-L21*'Master Assumptions'!G23 -> -2288.5723 | M23: =-M21*'Master Assumptions'!H23 -> -2514.1621 | N23: =-N21*'Master Assumptions'!I23 -> -2737.8746 | O23: =-O21*'Master Assumptions'!J23 -> -2954.6049
B24: Equity in Affiliates | F24: 16.1 | G24: 34 | H24: 50 | I24: 106 | J24: 44 | K24: =J24 -> 44 | L24: =K24 -> 44 | M24: =L24 -> 44 | N24: =M24 -> 44 | O24: =N24 -> 44
B25: Consolidated Net Income | F25: =SUM(F21:F24) -> 1389.5 | G25: =SUM(G21:G24) -> 2454 | H25: =SUM(H21:H24) -> 3380 | I25: =SUM(I21:I24) -> 4323 | J25: =SUM(J21:J24) -> 4631 | K25: =SUM(K21:K24) -> 5086.2295 | L25: =SUM(L21:L24) -> 5644.8938 | M25: =SUM(M21:M24) -> 6196.9867 | ... O25: =SUM(O21:O24) -> 7274.8958
B27: Minority Interests | F27: -4.1 | G27: -8 | H27: -13 | I27: -12 | J27: -28 | K27: =J27 -> -28 | L27: =K27 -> -28 | M27: =L27 -> -28 | N27: =M27 -> -28 | O27: =N27 -> -28
B28: Net Income | F28: =SUM(F25:F27) -> 1385.4 | G28: =SUM(G25:G27) -> 2446 | H28: =SUM(H25:H27) -> 3367 | I28: =SUM(I25:I27) -> 4311 | J28: =SUM(J25:J27) -> 4603 | K28: =SUM(K25:K27) -> 5058.2295 | L28: =SUM(L25:L27) -> 5616.8938 | M28: =SUM(M25:M27) -> 6168.9867 | ... O28: =SUM(O25:O27) -> 7246.8958
B31: BALANCE SHEET
B33: All figures in millions of euros | F33: 2020A | G33: 2021A | H33: 2022A | I33: 2023A | J33: 2024A | K33: 2025E | L33: 2026E | M33: 2027E | N33: 2028E | O33: 2029E
B34: unless stated otherwise
B36: Assets
B37: Cash & Short-Term Investments | F37: 4732.7 | G37: 6696 | H37: 9225 | I37: 10625 | J37: 11642 | K37: =J37+K120 -> 14337.799 | L37: =K37+L120 -> 17520.279 | M37: =L37+M120 -> 21029.088 | N37: =M37+N120 -> 24871.823 | O37: =N37+O120 -> 29047.096
B38: Accounts Receivable | F38: 249.7 | G38: 333 | H38: 383 | I38: 431 | J38: 478 | K38: ='Master Assumptions'!F26*('Forecast Model'!K8/365) -> 540.01006 | L38: ='Master Assumptions'!G26*('Forecast Model'!L8/365) -> 597.33708 | M38: ='Master Assumptions'!H26*('Forecast Model'!M8/365) -> 654.75295 | N38: ='Master Assumptions'!I26*('Forecast Model'!N8/365) -> 712.32928 | O38: ='Master Assumptions'!J26*('Forecast Model'!O8/365) -> 768.7755
B39: Other Receivables | F39: 256.5 | G39: 58 | H39: 19 | I39: 51 | J39: 28 | K39: =J39 -> 28 | L39: =K39 -> 28 | M39: =L39 -> 28 | N39: =M39 -> 28 | O39: =N39 -> 28
B40: Inventories | F40: 1289.4 | G40: 1449 | H40: 1779 | I40: 2414 | J40: 2797 | K40: ='Master Assumptions'!F27*(-'Forecast Model'!K9/365) -> 3112.886 | L40: ='Master Assumptions'!G27*(-'Forecast Model'!L9/365) -> 3443.3474 | M40: ='Master Assumptions'!H27*(-'Forecast Model'!M9/365) -> 3774.3209 | N40: ='Master Assumptions'!I27*(-'Forecast Model'!N9/365) -> 4106.2195 | O40: ='Master Assumptions'!J27*(-'Forecast Model'!O9/365) -> 4431.6035
B41: Other Current Assets | F41: 121.4 | G41: 309 | H41: 422 | I41: 487 | J41: 531 | K41: ='Master Assumptions'!F29*'Forecast Model'!K8 -> 778.2263 | L41: ='Master Assumptions'!G29*'Forecast Model'!L8 -> 860.84215 | M41: ='Master Assumptions'!H29*'Forecast Model'!M8 -> 943.58606 | N41: ='Master Assumptions'!I29*'Forecast Model'!N8 -> 1026.5612 | O41: ='Master Assumptions'!J29*'Forecast Model'!O8 -> 1107.9077
B42: Total Current Assets | F42: =SUM(F37:F41) -> 6649.7 | G42: =SUM(G37:G41) -> 8845 | H42: =SUM(H37:H41) -> 11828 | I42: =SUM(I37:I41) -> 14008 | J42: =SUM(J37:J41) -> 15476 | K42: =SUM(K37:K41) -> 18796.921 | L42: =SUM(L37:L41) -> 22449.805 | M42: =SUM(M37:M41) -> 26429.748 | ... O42: =SUM(O37:O41) -> 35383.383
B44: Net PP&E | F44: 3092.2 | G44: 3398 | H44: 3589 | I44: 4056 | J44: 4766 | K44: ='Supporting Schedules'!D228 -> 5111.9185 | L44: ='Supporting Schedules'!E228 -> 5521.2318 | M44: ='Supporting Schedules'!F228 -> 5983.5618 | N44: ='Supporting Schedules'!G228 -> 6490.4113 | O44: ='Supporting Schedules'!H228 -> 7031.9743
B45: Goodwill | F45: 42.4 | G45: 42 | H45: 0 | I45: 72 | J45: 228 | K45: =J45 -> 228 | L45: =K45 -> 228 | M45: =L45 -> 228 | N45: =M45 -> 228 | O45: =N45 -> 228
B46: Other Intangible Assets | F46: 221.3 | G46: 258 | H46: 213 | I46: 225 | J46: 237 | K46: =J46 -> 237 | L46: =K46 -> 237 | M46: =L46 -> 237 | N46: =M46 -> 237 | O46: =N46 -> 237
B47: Long-Term Investments | F47: 515.4 | G47: 677 | H47: 1171 | I47: 1348 | J47: 1288 | K47: =J47 -> 1288 | L47: =K47 -> 1288 | M47: =L47 -> 1288 | N47: =M47 -> 1288 | O47: =N47 -> 1288
B48: Deferred Tax Assets | F48: 475.2 | G48: 546 | H48: 555 | I48: 631 | J48: 929 | K48: =J48-K95 -> 1022 | L48: =K48-L95 -> 1115 | M48: =L48-M95 -> 1208 | N48: =M48-N95 -> 1301 | O48: =N48-O95 -> 1394
B49: Other Non-Current Assets | F49: 54.3 | G49: 81 | H49: 103 | I49: 107 | J49: 160 | K49: =J49 -> 160 | L49: =K49 -> 160 | M49: =L49 -> 160 | N49: =M49 -> 160 | O49: =N49 -> 160
B50: Total Non-Current Assets | F50: =SUM(F44:F49) -> 4400.8 | G50: =SUM(G44:G49) -> 5002 | H50: =SUM(H44:H49) -> 5631 | I50: =SUM(I44:I49) -> 6439 | J50: =SUM(J44:J49) -> 7608 | K50: =SUM(K44:K49) -> 8046.9185 | L50: =SUM(L44:L49) -> 8549.2318 | M50: =SUM(M44:M49) -> 9104.5618 | ... O50: =SUM(O44:O49) -> 10338.974
B52: Total Assets | F52: =F42+F50 -> 11050.5 | G52: =G42+G50 -> 13847 | H52: =H42+H50 -> 17459 | I52: =I42+I50 -> 20447 | J52: =J42+J50 -> 23084 | K52: =K50+K42 -> 26843.84 | L52: =L50+L42 -> 30999.037 | M52: =M50+M42 -> 35534.31 | N52: =N50+N42 -> 40449.344 | O52: =O50+O42 -> 45722.357
B55: Liabilities
B56: Accounts Payable | F56: 372.5 | G56: 450 | H56: 659 | I56: 685 | J56: 683 | K56: ='Master Assumptions'!F28*(('Forecast Model'!K40-'Forecast Model'!J40+(-'Forecast Model'!K9))/365) -> 774.18759 | L56: ='Master Assumptions'!G28*(('Forecast Model'!L40-'Forecast Model'!K40+(-'Forecast Model'!L9))/365) -> 853.50651 | M56: ='Master Assumptions'!H28*(('Forecast Model'!M40-'Forecast Model'!L40+(-'Forecast Model'!M9))/365) -> 930.81743 | N56: ='Master Assumptions'!I28*(('Forecast Model'!N40-'Forecast Model'!M40+(-'Forecast Model'!N9))/365) -> 1008.4067 | O56: ='Master Assumptions'!J28*(('Forecast Model'!O40-'Forecast Model'!N40+(-'Forecast Model'!O9))/365) -> 1083.3502
B57: ST Debt & Curr. Portion of LT | F57: 220.1 | G57: 249 | H57: 270 | I57: 290 | J57: 332 | K57: =J57 -> 332 | L57: =K57 -> 332 | M57: =L57 -> 332 | N57: =M57 -> 332 | O57: =N57 -> 332
B58: Income Tax Payable | F58: 217.8 | G58: 347 | H58: 496 | I58: 586 | J58: 773 | K58: =-'Master Assumptions'!F30*'Forecast Model'!K23 -> 765.30995 | L58: =-'Master Assumptions'!G30*'Forecast Model'!L23 -> 850.10406 | M58: =-'Master Assumptions'!H30*'Forecast Model'!M23 -> 933.90076 | N58: =-'Master Assumptions'!I30*'Forecast Model'!N23 -> 1017.0001 | O58: =-'Master Assumptions'!J30*'Forecast Model'!O23 -> 1097.5059
B59: Other Current Liabilities | F59: 1028.2 | G59: 1529 | H59: 1579 | I59: 1622 | J59: 1841 | K59: ='Master Assumptions'!F31*'Forecast Model'!K8 -> 2140.8097 | L59: ='Master Assumptions'!G31*'Forecast Model'!L8 -> 2368.0763 | M59: ='Master Assumptions'!H31*'Forecast Model'!M8 -> 2595.6951 | N59: ='Master Assumptions'!I31*'Forecast Model'!N8 -> 2823.95 | O59: ='Master Assumptions'!J31*'Forecast Model'!O8 -> 3047.7248
B60: Total Current Liabilities | F60: =SUM(F56:F59) -> 1838.6 | G60: =SUM(G56:G59) -> 2575 | H60: =SUM(H56:H59) -> 3004 | I60: =SUM(I56:I59) -> 3183 | J60: =SUM(J56:J59) -> 3629 | K60: =SUM(K56:K59) -> 4012.3072 | L60: =SUM(L56:L59) -> 4403.6868 | M60: =SUM(M56:M59) -> 4792.4133 | ... O60: =SUM(O56:O59) -> 5560.5809
B62: Long-Term Debt | F62: 1465.9 | G62: 1553 | H62: 1664 | I62: 1770 | J62: 1842 | K62: =J62 -> 1842 | L62: =K62 -> 1842 | M62: =L62 -> 1842 | N62: =M62 -> 1842 | O62: =N62 -> 1842
B63: Deferred Tax Liabilities | F63: 21.9 | G63: 15 | H63: 20 | I63: 2 | J63: 5 | K63: =J63 -> 5 | L63: =K63 -> 5 | M63: =L63 -> 5 | N63: =M63 -> 5 | O63: =N63 -> 5
B64: Other Non-Current Liabilities | F64: 36.2 | G64: 46 | H64: 104 | I64: 107 | J64: 68 | K64: =J64 -> 68 | L64: =K64 -> 68 | M64: =L64 -> 68 | N64: =M64 -> 68 | O64: =N64 -> 68
B65: Provision for Risks & Charges | F65: 296.9 | G65: 246 | H65: 211 | I65: 182 | J65: 206 | K65: =J65 -> 206 | L65: =K65 -> 206 | M65: =L65 -> 206 | N65: =M65 -> 206 | O65: =N65 -> 206
B66: Total Non-Current Liabilities | F66: =SUM(F62:F65) -> 1820.9 | G66: =SUM(G62:G65) -> 1860 | H66: =SUM(H62:H65) -> 1999 | I66: =SUM(I62:I65) -> 2061 | J66: =SUM(J62:J65) -> 2121 | K66: =SUM(K62:K65) -> 2121 | L66: =SUM(L62:L65) -> 2121 | M66: =SUM(M62:M65) -> 2121 | ... O66: =SUM(O62:O65) -> 2121
B68: Total Liabilities | F68: =F60+F66 -> 3659.5 | G68: =G60+G66 -> 4435 | H68: =H60+H66 -> 5003 | I68: =I60+I66 -> 5244 | J68: =J60+J66 -> 5750 | K68: =K60+K66 -> 6133.3072 | L68: =L60+L66 -> 6524.6868 | M68: =M60+M66 -> 6913.4133 | ... O68: =O60+O66 -> 7681.5809
B70: Shareholders' Equity
B71: Common Stock & APIC | F71: 103.4 | G71: 104 | H71: 104 | I71: 104 | J71: 104
B72: Retained Earnings | F72: 0 | G72: 0 | H72: 0 | I72: 0 | J72: 0
B73: Treasury Stock | F73: -463.7 | G73: -551 | H73: -674 | I73: -698 | J73: -670
B74: CTA / Unrealizaed for Exch Gain | F74: 5.2 | G74: 178 | H74: 303 | I74: 189 | J74: 355
B75: Unrealized Gain/Loss Marketable Securities | F75: 100.3 | G75: 188 | H75: 521 | I75: 521 | J75: 551
B76: Unappropriated Reserves | F76: 7732.1 | G76: 9711 | H76: 12246 | I76: 15128 | J76: 17162
B77: Other Appropriated Reserves | F77: -97.2 | G77: -230 | H77: -60 | I77: -43 | J77: -175
B78: Total Shareholders' Equity | F78: =SUM(F71:F77) -> 7380.1 | G78: =SUM(G71:G77) -> 9400 | H78: =SUM(H71:H77) -> 12440 | I78: =SUM(I71:I77) -> 15201 | J78: =SUM(J71:J77) -> 17327 | K78: ='Supporting Schedules'!D343 -> 20703.533 | L78: ='Supporting Schedules'!E343 -> 24467.35 | M78: ='Supporting Schedules'!F343 -> 28613.897 | N78: ='Supporting Schedules'!G343 -> 33139.987 | O78: ='Supporting Schedules'!H343 -> 38033.776
B79: Accumulated Minority Interest | F79: 10.9 | G79: 12 | H79: 16 | I79: 2 | J79: 7 | K79: =J79 -> 7 | L79: =K79 -> 7 | M79: =L79 -> 7 | N79: =M79 -> 7 | O79: =N79 -> 7
B80: Total Equity | F80: =SUM(F78:F79) -> 7391 | G80: =SUM(G78:G79) -> 9412 | H80: =SUM(H78:H79) -> 12456 | I80: =SUM(I78:I79) -> 15203 | J80: =SUM(J78:J79) -> 17334 | K80: =SUM(K78:K79) -> 20710.533 | L80: =SUM(L78:L79) -> 24474.35 | M80: =SUM(M78:M79) -> 28620.897 | ... O80: =SUM(O78:O79) -> 38040.776
B82: Total Liabilities & Equity | F82: =F68+F80 -> 11050.5 | G82: =G68+G80 -> 13847 | H82: =H68+H80 -> 17459 | I82: =I68+I80 -> 20447 | J82: =J68+J80 -> 23084 | K82: =K80+K68 -> 26843.84 | L82: =L80+L68 -> 30999.037 | M82: =M80+M68 -> 35534.31 | N82: =N80+N68 -> 40449.344 | O82: =O80+O68 -> 45722.357
B86: CASH FLOW STATEMENT
B88: All figures in millions of euros | F88: 2020A | G88: 2021A | H88: 2022A | I88: 2023A | J88: 2024A | K88: 2025E | L88: 2026E | M88: 2027E | N88: 2028E | O88: 2029E
B89: unless stated otherwise
B92: Operating Activities
B93: Net Income | F93: 1385.4 | G93: 2445 | H93: 3367 | I93: 4311 | J93: 4603 | K93: =K28 -> 5058.2295 | L93: =L28 -> 5616.8938 | M93: =M28 -> 6168.9867 | N93: =N28 -> 6716.4851 | O93: =O28 -> 7246.8958
B94: D&A | F94: 512 | G94: 561 | H94: 607 | I94: 666 | J94: 811 | K94: =-K13 -> 794.32318 | L94: =-L13 -> 851.97554 | M94: =-M13 -> 920.19354 | N94: =-N13 -> 997.24756 | O94: =-O13 -> 1081.7214
B95: Deferred Taxes | F95: 5.4 | G95: -15 | H95: -16 | I95: -14 | J95: -93 | K95: =$J$95 -> -93 | L95: =$J$95 -> -93 | M95: =$J$95 -> -93 | N95: =$J$95 -> -93 | O95: =$J$95 -> -93
B96: Other Funds | F96: 111.3 | G96: 115 | H96: 220 | I96: 271 | J96: 87 | K96: 0 | L96: 0 | M96: 0 | N96: 0 | O96: 0
B97: Changes in Working Capital:
B98: (Increase) / Decrease in Receivables | F98: 38.4 | G98: -30 | H98: -54 | I98: -122 | J98: 4 | K98: =-(K38-J38) -> -62.010063 | L98: =-(L38-K38) -> -57.327013 | M98: =-(M38-L38) -> -57.41587 | N98: =-(N38-M38) -> -57.576338 | O98: =-(O38-N38) -> -56.446218
B99: (Increase) / Decrease in Inventories | F99: -157.9 | G99: -116 | H99: -324 | I99: -662 | J99: -313 | K99: =-(K40-J40) -> -315.88602 | L99: =-(L40-K40) -> -330.46135 | M99: =-(M40-L40) -> -330.97357 | N99: =-(N40-M40) -> -331.89859 | O99: =-(O40-N40) -> -325.38401
B100: Increase / (Decrease) in Accounts Payable | F100: -23.7 | G100: 71 | H100: 203 | I100: 42 | J100: -60 | K100: =(K56-J56) -> 91.187591 | L100: =(L56-K56) -> 79.318922 | M100: =(M56-L56) -> 77.31092 | N100: =(N56-M56) -> 77.589223 | O100: =(O56-N56) -> 74.943539
B101: Other Working Capital Changes | F101: -207.1 | G101: 421 | H101: 248 | I101: -52 | J101: 130 | K101: =-(K41-J41)+(K58-J58)+(K59-J59) -> 44.893352 | L101: =-(L41-K41)+(L58-K58)+(L59-K59) -> 229.44481 | M101: =-(M41-L41)+(M58-L58)+(M59-L59) -> 228.67161 | N101: =-(N41-M41)+(N58-M58)+(N59-M59) -> 228.37916 | O101: =-(O41-N41)+(O58-N58)+(O59-N59) -> 222.93402
B102: Cash Flow from Operations | F102: =SUM(F93:F101) -> 1663.8 | G102: =SUM(G93:G101) -> 3452 | H102: =SUM(H93:H101) -> 4251 | I102: =SUM(I93:I101) -> 4440 | J102: =SUM(J93:J101) -> 5169 | K102: =SUM(K93:K101) -> 5517.7375 | L102: =SUM(L93:L101) -> 6296.8447 | M102: =SUM(M93:M101) -> 6913.7733 | ... O102: =SUM(O93:O101) -> 8151.6646
B104: Investing Activities
B105: Capital Expenditures | F105: -448.4 | G105: -532 | H105: -518 | I105: -859 | J105: -1067 | K105: =-'Master Assumptions'!F32*'Forecast Model'!K8 -> -1140.2417 | L105: =-'Master Assumptions'!G32*'Forecast Model'!L8 -> -1261.2888 | M105: =-'Master Assumptions'!H32*'Forecast Model'!M8 -> -1382.5235 | N105: =-'Master Assumptions'!I32*'Forecast Model'!N8 -> -1504.0971 | O105: =-'Master Assumptions'!J32*'Forecast Model'!O8 -> -1623.2844
B106: Acquisitions | F106: 0.2 | G106: 3 | H106: 0 | I106: -288 | J106: -228 | K106: 0 | L106: 0 | M106: 0 | N106: 0 | O106: 0
B107: Purchase / Sale of Investments | F107: -16.3 | G107: -192 | H107: -160 | I107: -52 | J107: 118 | K107: 0 | L107: 0 | M107: 0 | N107: 0 | O107: 0
B108: Other Investing Activities | F108: 10.9 | G108: 5 | H108: 32 | I108: 92 | J108: -48 | K108: 0 | L108: 0 | M108: 0 | N108: 0 | O108: 0
B109: Cash Flow from Investing | F109: =SUM(F105:F108) -> -453.6 | G109: =SUM(G105:G108) -> -716 | H109: =SUM(H105:H108) -> -646 | I109: =SUM(I105:I108) -> -1107 | J109: =SUM(J105:J108) -> -1225 | K109: =SUM(K105:K108) -> -1140.2417 | L109: =SUM(L105:L108) -> -1261.2888 | M109: =SUM(M105:M108) -> -1382.5235 | ... O109: =SUM(O105:O108) -> -1623.2844
B111: Financing Activities
B112: Dividends Paid | F112: -485.1 | G112: -485 | H112: -845 | I112: -1376 | J112: -2642 | K112: =-'Master Assumptions'!F37*'Forecast Model'!K28 -> -1551.6967 | L112: =-'Master Assumptions'!G37*'Forecast Model'!L28 -> -1723.0764 | M112: =-'Master Assumptions'!H37*'Forecast Model'!M28 -> -1892.4401 | N112: =-'Master Assumptions'!I37*'Forecast Model'!N28 -> -2060.3944 | O112: =-'Master Assumptions'!J37*'Forecast Model'!O28 -> -2223.1068
B113: Change in Capital Stock | F113: -122.2 | G113: -158 | H113: -123 | I113: -130 | J113: -37 | K113: =$I$113 -> -130 | L113: =$I$113 -> -130 | M113: =$I$113 -> -130 | N113: =$I$113 -> -130 | O113: =$I$113 -> -130
B114: Repayments of Operating Leases | F114: -198.7 | G114: -213 | H114: -261 | I114: -277 | J114: -305 | K114: 0 | L114: 0 | M114: 0 | N114: 0 | O114: 0
B115: Debt Issuance / (Repayment) | F115: 0.3 | G115: -8 | H115: 0 | I115: -1 | J115: -1 | K115: 0 | L115: 0 | M115: 0 | N115: 0 | O115: 0
B116: Other Funds | F116: -4.5 | G116: -5 | H116: -8 | I116: -10 | J116: -61 | K116: 0 | L116: 0 | M116: 0 | N116: 0 | O116: 0
B117: Cash Flow from Financing | F117: =SUM(F112:F116) -> -810.2 | G117: =SUM(G112:G116) -> -869 | H117: =SUM(H112:H116) -> -1237 | I117: =SUM(I112:I116) -> -1794 | J117: =SUM(J112:J116) -> -3046 | K117: =SUM(K112:K116) -> -1681.6967 | L117: =SUM(L112:L116) -> -1853.0764 | M117: =SUM(M112:M116) -> -2022.4401 | ... O117: =SUM(O112:O116) -> -2353.1068
B119: Effect of Exchange Rate | F119: -54.6 | G119: 110 | H119: 159 | I119: -138 | J119: 119 | K119: 0 | L119: 0 | M119: 0 | N119: 0 | O119: 0
B120: Net Change in Cash | F120: =F102+F109+F117+F119 -> 345.4 | G120: =G102+G109+G117+G119 -> 1977 | H120: =H102+H109+H117+H119 -> 2527 | I120: =I102+I109+I117+I119 -> 1401 | J120: =J102+J109+J117+J119 -> 1017 | K120: =K102+K109+K117 -> 2695.7991 | L120: =L102+L109+L117 -> 3182.4795 | M120: =M102+M109+M117 -> 3508.8096 | N120: =N102+N109+N117 -> 3842.7345 | O120: =O102+O109+O117 -> 4175.2734

Sheet Integration Check
B2: INTEGRATION CHECK
B3: Hermes International S.A.
B5: STATUS | C5: =IF(COUNTIF(D9:D14,"✗ FAIL")=0,"✓ ALL CHECKS PASSED",COUNTIF(D9:D14,"✗ FAIL")&" CHECK(S) FAILED") -> ✓ ALL CHECKS PASSED
B7: CHECK | C7: DESCRIPTION | D7: STATUS | E7: 2025E | F7: 2026E | G7: 2027E | H7: 2028E | I7: 2028E
B9: Balance Sheet Balances | C9: Assets = Liabilities + Equity | D9: =IF(AND(ABS(E9)<0.01,ABS(F9)<0.01,ABS(G9)<0.01,ABS(H9)<0.01,ABS(I9)<0.01),"✓ OK","✗ FAIL") -> ✓ OK | E9: ='Forecast Model'!K52-'Forecast Model'!K82 -> 0 | F9: ='Forecast Model'!L52-'Forecast Model'!L82 -> 0 | G9: ='Forecast Model'!M52-'Forecast Model'!M82 -> 0 | H9: ='Forecast Model'!N52-'Forecast Model'!N82 -> 0 | I9: ='Forecast Model'!O52-'Forecast Model'!O82 -> 0
B11: Net Income → Cash Flow | C11: NI (IS) = NI (CF Statement) | D11: =IF(AND(ABS(E11)<0.01,ABS(F11)<0.01,ABS(G11)<0.01,ABS(H11)<0.01,ABS(I11)<0.01),"✓ OK","✗ FAIL") -> ✓ OK | E11: ='Forecast Model'!K28-'Forecast Model'!K93 -> 0 | F11: ='Forecast Model'!L28-'Forecast Model'!L93 -> 0 | G11: ='Forecast Model'!M28-'Forecast Model'!M93 -> 0 | H11: ='Forecast Model'!N28-'Forecast Model'!N93 -> 0 | I11: ='Forecast Model'!O28-'Forecast Model'!O93 -> 0
B13: D&A Consistency | C13: D&A (IS) = D&A (CF add-back) | D13: =IF(AND(ABS(E13)<0.01,ABS(F13)<0.01,ABS(G13)<0.01,ABS(H13)<0.01,ABS(I13)<0.01),"✓ OK","✗ FAIL") -> ✓ OK | E13: ='Forecast Model'!K94+'Forecast Model'!K13 -> 0 | F13: ='Forecast Model'!L94+'Forecast Model'!L13 -> 0 | G13: ='Forecast Model'!M94+'Forecast Model'!M13 -> 0 | H13: ='Forecast Model'!N94+'Forecast Model'!N13 -> 0 | I13: ='Forecast Model'!O94+'Forecast Model'!O13 -> 0
B17: Note: | C17: Differences should be 0.000 (small rounding OK). Non-zero = broken link.

Sheet DCF Valuation
B3: DCF VALUATION
B5: SECTION 1: CAPITAL STRUCTURE
B7: Cost of Equity (CAPM): | H7: Cost of Debt:
B9: Risk-Free Rate (Rf) | E9: 0.0323 | H9: Pre-tax Cost of Debt (Kd) | J9: 0
B10: Equity risk premium (ERP) | E10: 0.0501 | H10: Tax rate | J10: 0
B11: Beta (Levered) | E11: 1.23 | H11: After-Tax Cost of Debt | J11: 0
B12: Cost of Equity(Ke) | E12: =E9+E11*E10 -> 0.093923
B15: Weight of Equity | E15: 1 | H15: Weight of Debt | J15: 0
B18: Weighted Average Cost of Capital | E18: =IF('Sensitivity Analysis'!K10="",'DCF Valuation'!E15*'DCF Valuation'!E12+'DCF Valuation'!J15*'DCF Valuation'!J11,'Sensitivity Analysis'!K10) -> 0.093923
B21: SECTION 2: FREE CASH FLOW SCHEDULE
E24: 2025E | F24: 2026E | G24: 2027E | H24: 2028E | I24: 2029E
B26: EBIT | E26: ='Forecast Model'!K15 -> 7161.5764 | F26: ='Forecast Model'!L15 -> 7948.5156 | G26: ='Forecast Model'!M15 -> 8726.1983 | H26: ='Forecast Model'!N15 -> 9497.4092 | I26: ='Forecast Model'!O15 -> 10244.55
B27: % Margin | E27: ='Forecast Model'!K15/'Forecast Model'!K8 -> 0.42178949 | F27: ='Forecast Model'!L15/'Forecast Model'!L8 -> 0.42320963 | G27: ='Forecast Model'!M15/'Forecast Model'!M8 -> 0.42387382 | H27: ='Forecast Model'!N15/'Forecast Model'!N8 -> 0.42404635 | I27: ='Forecast Model'!O15/'Forecast Model'!O8 -> 0.42382087
B28: Less: Taxes on EBIT | E28: =-E26*'Master Assumptions'!F23 -> -2077.4264 | F28: =-F26*'Master Assumptions'!G23 -> -2305.7014 | G28: =-G26*'Master Assumptions'!H23 -> -2531.2912 | H28: =-H26*'Master Assumptions'!I23 -> -2755.0036 | I28: =-I26*'Master Assumptions'!J23 -> -2971.734
B29: NOPAT (EBIT x (1-Tax rate) | E29: =E26+E28 -> 5084.1499 | F29: =F26+F28 -> 5642.8142 | G29: =G26+G28 -> 6194.9071 | H29: =H26+H28 -> 6742.4055 | I29: =I26+I28 -> 7272.8163
B32: Plus: D&A | E32: =-'Forecast Model'!K13 -> 794.32318 | F32: =-'Forecast Model'!L13 -> 851.97554 | G32: =-'Forecast Model'!M13 -> 920.19354 | H32: =-'Forecast Model'!N13 -> 997.24756 | I32: =-'Forecast Model'!O13 -> 1081.7214
B33: Less: CapEx | E33: ='Forecast Model'!K105 -> -1140.2417 | F33: ='Forecast Model'!L105 -> -1261.2888 | G33: ='Forecast Model'!M105 -> -1382.5235 | H33: ='Forecast Model'!N105 -> -1504.0971 | I33: ='Forecast Model'!O105 -> -1623.2844
B34: Less: Change in NWC | E34: =SUM('Forecast Model'!K98:K101) -> -241.81514 | F34: =SUM('Forecast Model'!L98:L101) -> -79.024633 | G34: =SUM('Forecast Model'!M98:M101) -> -82.406909 | H34: =SUM('Forecast Model'!N98:N101) -> -83.506541 | I34: =SUM('Forecast Model'!O98:O101) -> -83.952671
B37: Unlevered Free Cash Flow | E37: =SUM(E29:E34) -> 4496.4163 | F37: =SUM(F29:F34) -> 5154.4763 | G37: =SUM(G29:G34) -> 5650.1702 | H37: =SUM(H29:H34) -> 6152.0494 | I37: =SUM(I29:I34) -> 6647.3007
B38: % Conversion (UCF/NOPAT) | E38: =E37/E29 -> 0.88439883 | F38: =F37/F29 -> 0.91345845 | G38: =G37/G29 -> 0.91206698 | H38: =H37/H29 -> 0.91244133 | I38: =I37/I29 -> 0.91399265
B42: SECTION 3: DISCOUNTING & PRESENT VALUE
E43: 2025E | F43: 2026E | G43: 2027E | H43: 2028E | I43: 2029E
B44: Discount Period (Mid Year Convention) | E44: 0.5 | F44: 1.5 | G44: 2.5 | H44: 3.5 | I44: 4.5
B45: Discount Factor | E45: =1/(1+$E$18)^E44 -> 0.95610728 | F45: =1/(1+$E$18)^F44 -> 0.87401698 | G45: =1/(1+$E$18)^G44 -> 0.79897486 | H45: =1/(1+$E$18)^H44 -> 0.73037578 | I45: =1/(1+$E$18)^I44 -> 0.66766653
B47: PV of FCF | E47: =E45*E37 -> 4299.0563 | F47: =F45*F37 -> 4505.0998 | G47: =G45*G37 -> 4514.344 | H47: =H45*H37 -> 4493.3079 | I47: =I45*I37 -> 4438.1802
B49: Sum of FCF | E49: =SUM(E47:I47) -> 22249.988
B52: SECTION 4: TERMINAL VALUE CALCULATION
B53: Perpetual Growth Method | G53: Exit multiple Method
B55: Terminal Year FCF (2029E) | E55: =I37 -> 6647.3007 | G55: Terminal Year EBITDA (2029E) | J55: =('Forecast Model'!O15-'Forecast Model'!O13) -> 11326.272
B56: Perpetual Growth Rate | E56: =IF('Sensitivity Analysis'!K9="",0.025,'Sensitivity Analysis'!K9) -> 0.025 | G56: Exit EV/EBITDA Multiple | J56: =IF('Sensitivity Analysis'!K22="",16.6,'Sensitivity Analysis'!K22) -> 16.6
B57: Terminal Value (Perpetuity) | E57: =E55*(1+E56)/(E18-E56) -> 98856.451 | G57: Terminal Value | J57: =J55*J56 -> 188016.11
B58: PV of Terminal Value | E58: =E57/(1+$E$18)^I44 -> 66003.144 | G58: PV of Terminal Value | J58: =J57/(1+E18)^I44 -> 125532.06
B61: SECTION 5: ENTERPRISE VALUE TO EQUITY VALUE
B63: Perpetual Growth Method | G63: Exit multiple Method
B64: Sum of PV of FCF | E64: =E49 -> 22249.988 | G64: Sum of PV of FCF | J64: =E49 -> 22249.988
B65: PV of Terminal Value | E65: =E58 -> 66003.144 | G65: PV of Terminal Value | J65: =J58 -> 125532.06
B66: Enterprise Value | E66: =SUM(E64:E65) -> 88253.132 | G66: Enterprise Value | J66: =SUM(J64:J65) -> 147782.05
B68: Less: Total Debt | E68: =-('Forecast Model'!J57+'Forecast Model'!J62) -> -2174 | G68: Less: Total Debt | J68: =E68 -> -2174
B69: Plus: Cash & Equivalents | E69: ='Forecast Model'!J37 -> 11642 | G69: Plus: Cash & Equivalents | J69: =E69 -> 11642
B70: Less: Minority Interest | E70: =-'Forecast Model'!J79 -> -7 | G70: Less: Minority Interest | J70: =E70 -> -7
B71: Less: Preferred Stock | E71: =0 -> 0 | G71: Less: Preferred Stock | J71: =E71 -> 0
B72: Plus: Equity Investments | E72: ='Forecast Model'!J47 -> 1288 | G72: Plus: Equity Investments | J72: =E72 -> 1288
B73: Equity Value | E73: =SUM(E66:E72) -> 99002.132 | G73: Equity Value | J73: =SUM(J66:J72) -> 158531.05
B75: Shares Outstanding (mm) | E75: 104.64 | G75: Shares Outstanding (mm) | J75: =E75 -> 104.64
B76: Implied Share Price ($) | E76: =E73/E75 -> 946.1213 | G76: Implied Share Price ($) | J76: =J73/J75 -> 1515.0139
B78: Fully Diluted Shares Outstanding(mm) | E78: =104.93 -> 104.93 | G78: Fully Diluted Shares Outstanding(mm) | J78: =E78 -> 104.93
B79: Implied Share Price -Diluted ($) | E79: =E73/E78 -> 943.50646 | G79: Implied Share Price -Diluted ($) | J79: =J73/J78 -> 1510.8268

Sheet Trading Comps
A3: TRADING COMPARABLES ANALYSIS
A5: All figures in EUR millions unless stated otherwise
A8: SECTION 1: COMPANY OVERVIEW & MARKET DATA
B9: Company | C9: Ticker | D9: Exchange | E9: Currency | F9: Share Price | G9: Shares Out. (mm) | H9: Market Cap (€mm) | I9: (+) Total Debt (€mm) | J9: (-) Cash (€mm) | K9: Enterprise Value (€mm)
B10: Hermès International | C10: RMS FP | D10: Euronext Paris | E10: EUR | F10: 1897.5 | G10: 105.6 | H10: =F10*G10 -> 200376 | I10: 0 | J10: 12501 | K10: =H10+I10-J10 -> 187875
B11: LVMH Moët Hennessy | C11: MC FP | D11: Euronext Paris | E11: EUR | F11: 502.2 | G11: 497.7 | H11: =F11*G11 -> 249944.94 | I11: 20343 | J11: 13502 | K11: =H11+I11-J11 -> 256785.94
B12: Richemont | C12: CFR SW | D12: SIX Swiss Exchange | E12: CHF | F12: 156.6 | G12: 537.6 | H12: =F12*G12 -> 84188.16 | I12: 10150 | J12: 16669 | K12: =H12+I12-J12 -> 77669.16
A15: SECTION 2: FINANCIAL SUMMARY (LTM & 2025E)
B16: Company | D16: Revenue (€mm) | F16: EBITDA (€mm) | H16: EBITDA Margin | J16: EBIT (€mm) | L16: EBIT Margin | N16: Net Income (€mm) | P16: EPS (€)
D17: LTM | E17: 2025E | F17: LTM | G17: 2025E | H17: LTM | I17: 2025E | J17: LTM | K17: 2025E | L17: LTM | M17: 2025E | N17: LTM | O17: 2025E | P17: LTM | Q17: 2025E
B18: Hermès International | D18: 16002 | E18: ='Forecast Model'!K8 -> 16979.03 | F18: 8229 | G18: ='Forecast Model'!K15-'Forecast Model'!K13 -> 7955.8996 | H18: =IF(OR(F18="",D18=""),"-",F18/D18) -> 0.51424822 | I18: =IF(OR(G18="",E18=""),"-",G18/E18) -> 0.46857209 | J18: 7303 | K18: 7162 | L18: =IF(OR(J18="",D18=""),"-",J18/D18) -> 0.45638045 | M18: =IF(OR(K18="",E18=""),"-",K18/E18) -> 0.42181444 | N18: =4626.3 -> 4626.3 | O18: 5058 | P18: 44.06 | Q18: =5058/105 -> 48.171429
B19: LVMH Moët Hennessy | D19: 80807 | E19: 80807 | F19: 24302 | G19: 24302 | H19: =IF(OR(F19="",D19=""),"-",F19/D19) -> 0.30074127 | I19: =IF(OR(G19="",E19=""),"-",G19/E19) -> 0.30074127 | J19: 17680 | K19: 17680 | L19: =IF(OR(J19="",D19=""),"-",J19/D19) -> 0.21879293 | M19: =IF(OR(K19="",E19=""),"-",K19/E19) -> 0.21879293 | N19: 10878 | O19: 10878 | P19: =N19/G11 -> 21.85654 | Q19: =O19/G11 -> 21.85654
B20: Richemont | D20: 21942.45 | E20: 22345.78 | F20: 6274.9 | G20: 6077.78 | H20: =IF(OR(F20="",D20=""),"-",F20/D20) -> 0.2859708 | I20: =IF(OR(G20="",E20=""),"-",G20/E20) -> 0.27198782 | J20: 4549 | K20: =4587.49 -> 4587.49 | L20: =IF(OR(J20="",D20=""),"-",J20/D20) -> 0.20731504 | M20: =IF(OR(K20="",E20=""),"-",K20/E20) -> 0.20529559 | N20: 3763 | O20: 3659.9 | P20: =N20/G12 -> 6.999628 | Q20: =O20/G12 -> 6.8078497
A23: SECTION 3: TRADING MULTIPLES
B24: Company | D24: EV / Revenue | F24: EV / EBITDA | H24: EV / EBIT | J24: P / E
D25: LTM | E25: 2025E | F25: LTM | G25: 2025E | H25: LTM | I25: 2025E | J25: LTM | K25: 2025E
B26: Hermès International | D26: =IFERROR(K10/D18,"-") -> 11.74072 | E26: =IFERROR(K10/E18,"-") -> 11.06512 | F26: =IFERROR(K10/F18,"-") -> 22.830842 | G26: =IFERROR(K10/G18,"-") -> 23.614552 | H26: =IFERROR(K10/J18,"-") -> 25.725729 | I26: =IFERROR(K10/K18,"-") -> 26.232198 | J26: =IFERROR(F10/P18,"-") -> 43.066273 | K26: =IFERROR(F10/Q18,"-") -> 39.390569
B27: LVMH Moët Hennessy | D27: =IFERROR(K11/D19,"-") -> 3.1777685 | E27: =IFERROR(K11/E19,"-") -> 3.1777685 | F27: =IFERROR(K11/F19,"-") -> 10.566453 | G27: =IFERROR(K11/G19,"-") -> 10.566453 | H27: =IFERROR(K11/J19,"-") -> 14.524092 | I27: =IFERROR(K11/K19,"-") -> 14.524092 | J27: =IFERROR(F11/P19,"-") -> 22.977104 | K27: =IFERROR(F11/Q19,"-") -> 22.977104
B28: Richemont | D28: =IFERROR(K12/D20,"-") -> 3.5396758 | E28: =IFERROR(K12/E20,"-") -> 3.4757865 | F28: =IFERROR(K12/F20,"-") -> 12.377753 | G28: =IFERROR(K12/G20,"-") -> 12.779199 | H28: =IFERROR(K12/J20,"-") -> 17.073898 | I28: =IFERROR(K12/K20,"-") -> 16.930644 | J28: =IFERROR(F12/P20,"-") -> 22.372618 | K28: =IFERROR(F12/Q20,"-") -> 23.002858
A30: — Peer Summary Statistics (Comps Only — Excl. Hermès) —
B31: Mean | D31: =IFERROR(AVERAGE(D27:D28),"-") -> 3.3587222 | E31: =IFERROR(AVERAGE(E27:E28),"-") -> 3.3267775 | F31: =IFERROR(AVERAGE(F27:F28),"-") -> 11.472103 | G31: =IFERROR(AVERAGE(G27:G28),"-") -> 11.672826 | H31: =IFERROR(AVERAGE(H27:H28),"-") -> 15.798995 | I31: =IFERROR(AVERAGE(I27:I28),"-") -> 15.727368 | J31: =IFERROR(AVERAGE(J27:J28),"-") -> 22.674861 | K31: =IFERROR(AVERAGE(K27:K28),"-") -> 22.989981
B32: Median | D32: =IFERROR(MEDIAN(D27:D28),"-") -> 3.3587222 | E32: =IFERROR(MEDIAN(E27:E28),"-") -> 3.3267775 | F32: =IFERROR(MEDIAN(F27:F28),"-") -> 11.472103 | G32: =IFERROR(MEDIAN(G27:G28),"-") -> 11.672826 | H32: =IFERROR(MEDIAN(H27:H28),"-") -> 15.798995 | I32: =IFERROR(MEDIAN(I27:I28),"-") -> 15.727368 | J32: =IFERROR(MEDIAN(J27:J28),"-") -> 22.674861 | K32: =IFERROR(MEDIAN(K27:K28),"-") -> 22.989981
B33: High | D33: =IFERROR(MAX(D27:D28),"-") -> 3.5396758 | E33: =IFERROR(MAX(E27:E28),"-") -> 3.4757865 | F33: =IFERROR(MAX(F27:F28),"-") -> 12.377753 | G33: =IFERROR(MAX(G27:G28),"-") -> 12.779199 | H33: =IFERROR(MAX(H27:H28),"-") -> 17.073898 | I33: =IFERROR(MAX(I27:I28),"-") -> 16.930644 | J33: =IFERROR(MAX(J27:J28),"-") -> 22.977104 | K33: =IFERROR(MAX(K27:K28),"-") -> 23.002858
B34: Low | D34: =IFERROR(MIN(D27:D28),"-") -> 3.1777685 | E34: =IFERROR(MIN(E27:E28),"-") -> 3.1777685 | F34: =IFERROR(MIN(F27:F28),"-") -> 10.566453 | G34: =IFERROR(MIN(G27:G28),"-") -> 10.566453 | H34: =IFERROR(MIN(H27:H28),"-") -> 14.524092 | I34: =IFERROR(MIN(I27:I28),"-") -> 14.524092 | J34: =IFERROR(MIN(J27:J28),"-") -> 22.372618 | K34: =IFERROR(MIN(K27:K28),"-") -> 22.977104
A37: SECTION 4: IMPLIED VALUATION FOR HERMÈS
B38: Multiple Basis | D38: EV/Rev LTM | E38: EV/Rev 2025E | F38: EV/EBITDA LTM | G38: EV/EBITDA 2025E | H38: EV/EBIT LTM | I38: EV/EBIT 2025E | J38: P/E LTM | K38: P/E 2025E
B39: Median Multiple Applied | D39: =IFERROR(D32,"-") -> 3.3587222 | E39: =IFERROR(E32,"-") -> 3.3267775 | F39: =IFERROR(F32,"-") -> 11.472103 | G39: =IFERROR(G32,"-") -> 11.672826 | H39: =IFERROR(H32,"-") -> 15.798995 | I39: =IFERROR(I32,"-") -> 15.727368 | J39: =IFERROR(J32,"-") -> 22.674861 | K39: =IFERROR(K32,"-") -> 22.989981
B40: Hermès Metric (€mm) | D40: =IFERROR(D18,"-") -> 16002 | E40: =IFERROR(E18,"-") -> 16979.03 | F40: =IFERROR(F18,"-") -> 8229 | G40: =IFERROR(G18,"-") -> 7955.8996 | H40: =IFERROR(J18,"-") -> 7303 | I40: =IFERROR(K18,"-") -> 7162 | J40: =IFERROR(P18,"-") -> 44.06 | K40: =IFERROR(Q18,"-") -> 48.171429
B41: Implied Enterprise Value (€mm) | D41: =IFERROR(D39*D40,"-") -> 53746.272 | E41: =IFERROR(E39*E40,"-") -> 56485.455 | F41: =IFERROR(F39*F40,"-") -> 94403.934 | G41: =IFERROR(G39*G40,"-") -> 92867.831 | H41: =IFERROR(H39*H40,"-") -> 115380.06 | I41: =IFERROR(I39*I40,"-") -> 112639.41
B42: Implied Equity Value (€mm) | D42: =IFERROR(D41-I10+J10,"-") -> 66247.272 | E42: =IFERROR(E41-I10+J10,"-") -> 68986.455 | F42: =IFERROR(F41-I10+J10,"-") -> 106904.93 | G42: =IFERROR(G41-I10+J10,"-") -> 105368.83 | H42: =IFERROR(H41-I10+J10,"-") -> 127881.06 | I42: =IFERROR(I41-I10+J10,"-") -> 125140.41
B43: Implied Share Price (€) | D43: =IFERROR(D42/G10,"-") -> 627.34159 | E43: =IFERROR(E42/G10,"-") -> 653.28082 | F43: =IFERROR(F42/G10,"-") -> 1012.3573 | G43: =IFERROR(G42/G10,"-") -> 997.8109 | H43: =IFERROR(H42/G10,"-") -> 1210.9949 | I43: =IFERROR(I42/G10,"-") -> 1185.0417
A46: Notes: (1) Blue cells = manual inputs. (2) Margin % and multiples auto-calculate upon data entry. (3) EV-based multiples = EV / respective metric. (4) P/E = Market Cap / Net Income. (5) Kering multiples should be interpreted cautiously given recent Gucci-driven earnings compression.

Sheet Valuation Summary
B3: VALUATION SUMMARY
B25: VALUATION GRAPHING DATA
C27: Enterprise Value | I27: Share Price
D29: Low | E29: Delta | F29: High | G29: Mid | J29: Low | K29: Delta | L29: High | M29: Mid
C31: DCF Valuation | D31: =MIN('DCF Valuation'!E66,'DCF Valuation'!J66) -> 88253.132 | E31: =F31-D31 -> 59528.92 | F31: =MAX('DCF Valuation'!E66,'DCF Valuation'!J66) -> 147782.05 | G31: =(F31+D31)/2 -> 118017.59 | I31: DCF Valuation | J31: =MIN('DCF Valuation'!E76,'DCF Valuation'!J76) -> 946.1213 | K31: =L31-J31 -> 568.89259 | L31: =MAX('DCF Valuation'!J76,'DCF Valuation'!E76) -> 1515.0139 | M31: =(L31+J31)/2 -> 1230.5676
C32: Trading Comps | D32: =MIN('Trading Comps'!F34*'Trading Comps'!F18,'Trading Comps'!G18*'Trading Comps'!G34) -> 84065.638 | E32: =F32-D32 -> 17790.888 | F32: =MAX('Trading Comps'!F18*'Trading Comps'!F33,'Trading Comps'!G33*'Trading Comps'!G18) -> 101856.53 | G32: =(F32+D32)/2 -> 92961.082 | I32: Trading Comps | J32: =MIN('Trading Comps'!J34*'Trading Comps'!P18,'Trading Comps'!K34*'Trading Comps'!Q18) -> 985.73753 | K32: =L32-J32 -> 27.768392 | L32: =MAX('Trading Comps'!P18*'Trading Comps'!K33,'Trading Comps'!P18*'Trading Comps'!J33) -> 1013.5059 | M32: =(J32+L32)/2 -> 999.62173
C34: All figures are in millions of euros
B36: EV Chart Data | F36: SP Chart Data
B37: Method | C37: Low | D37: HighLabel | E37: Mid | G37: Low | H37: Delta | I37: HighLabel
B38: DCF Valuation | C38: =D31 -> 88253.132 | D38: 1 | E38: =G31 -> 118017.59 | F38: DCF Valuation | G38: =J31 -> 946.1213 | H38: =K31 -> 568.89259 | I38: 1
B39: Trading Comps | C39: =D32 -> 84065.638 | D39: 1 | E39: =G32 -> 92961.082 | F39: Trading Comps | G39: =J32 -> 985.73753 | H39: =K32 -> 27.768392 | I39: 1

Sheet Sensitivity Analysis
B2: SENSITIVITY ANALYSIS
B4: WACC vs. PERPETUAL GROWTH RATE
E7: Implied Price (Diluted) | F7: GROWTH RATE
E8: ='DCF Valuation'!E79 -> 943.50646 | F8: 0.015 | G8: 0.02 | H8: 0.025 | I8: 0.03 | J8: 0.035
D9: WACC | E9: 0.0739 | F9: 1116.6943 | G9: 1194.4332 | H9: 1288.0695 | I9: 1403.0354 | J9: 1547.5554
E10: 0.0839 | F10: 968.90686 | G10: 1023.1735 | H10: 1086.6536 | I10: 1161.911 | J10: 1252.5585
E11: 0.0939 | F11: 858.66793 | G11: 898.34801 | H11: 943.78717 | I11: 996.33731 | J11: 1057.8094
E12: 0.104 | F12: 772.54646 | G12: 802.51424 | H12: 836.27542 | I12: 874.59891 | J12: 918.47653
E13: 0.1139 | F13: 705.26349 | G13: 728.64605 | H13: 754.65882 | I13: 783.77204 | J13: 816.57514
B17: WACC vs EXIT MULTIPLE
E20: Implied Price (Diluted) | F20: EXIT MULTIPLE (EV/EBITDA)
E21: ='DCF Valuation'!J79 -> 1510.8268 | F21: 14.6 | G21: 15.6 | H21: 16.6 | I21: 17.6 | J21: 18.6
D22: WACC | E22: 0.0739 | F22: 1468.0447 | G22: 1546.3607 | H22: 1624.6766 | I22: 1702.9925 | J22: 1781.3084
E23: 0.0839 | F23: 1416.166 | G23: 1491.2826 | H23: 1566.3992 | I23: 1641.5158 | J23: 1716.6324
E24: 0.0939 | F24: 1366.8001 | G24: 1438.8756 | H24: 1510.9512 | I24: 1583.0267 | J24: 1655.1023
E25: 0.104 | F25: 1319.3442 | G25: 1388.4997 | H25: 1457.6551 | I25: 1526.8106 | J25: 1595.9661
E26: 0.1139 | F26: 1275.0394 | G26: 1341.4717 | H26: 1407.904 | I26: 1474.3364 | J26: 1540.7687

Sheet Sources & Footnotes
B2: SOURCES & FOOTNOTES
B3: Hermes International S.A. | Data Sources, Market Inputs, Methodology & Audit Trail
B5: SECTION 1: PRIMARY DATA SOURCES
B6: # | C6: Source Name | D6: Type | E6: Data Used For | F6: Tabs Referenced | G6: Access Date | H6: URL / Reference
B7: S1 | C7: Hermès Annual Report 2024 | D7: Company Filing | E7: IS, BS, CF statements; segment data | F7: Historical Financials | G7: 45717 | H7: https://finance.hermes.com/en/annual-reports
B8: S2 | C8: Hermès Universal Registration Document | D8: Company Filing | E8: Full financials; MD&A; risk factors | F8: Historical Financials, Forecast | G8: 45717 | H8: https://finance.hermes.com/en/regulated-information
B9: S3 | C9: Hermès Investor Relations | D9: Company IR | E9: Earnings releases, investor presentations, KPIs | F9: Historical Analysis, Assumptions | G9: 45717 | H9: https://finance.hermes.com/en/
B10: S4 | C10: FactSet | D10: Terminal | E10: Beta, trading data, consensus estimates, ERP | F10: DCF Valuation, Trading Comps | G10: 45717 | H10: FactSet: RMS-FR
B11: S5 | C11: Bloomberg Terminal | D11: Terminal | E11: Market data, trading multiples, comps | F11: Trading Comps, Valuation Summary | G11: 45717 | H11: RMS FP Equity
B12: S6 | C12: European Central Bank | D12: Govt | E12: Risk-free rate (Euro Govt Bond Yield) | F12: DCF Valuation | G12: 45717 | H12: https://www.ecb.europa.eu/stats/
B13: S7 | C13: Bain & Company Luxury Report | D13: 3rd Party | E13: Luxury market sizing, growth trends | F13: Forecast Model | G13: 45627 | H13: Bain Global Luxury Market Study 2024
B14: S8 | C14: LVMH, Kering, Richemont Filings | D14: Company Filing | E14: Peer financials for comparable analysis | F14: Trading Comps | G14: 45717 | H14: Company IR websites
B15: S9
B16: S10
B18: SECTION 2: EXTERNAL MARKET INPUTS USED
B19: Input | D19: Value Used | E19: Source / Basis | F19: Feeds Into | G19: As-Of Date | H19: Source Ref
B20: Risk-Free Rate (Rf) | D20: 0.0323 | E20: 10-Year Euro Govt Bond Yield (Bund) | F20: DCF: WACC | G20: 45717 | H20: S6
B21: Equity Risk Premium (ERP) | D21: 0.0501 | E21: FactSet implied ERP for Eurozone | F21: DCF: WACC | G21: 45717 | H21: S4
B22: Levered Beta | D22: 1.23 | E22: FactSet 5Y monthly regression vs. Euro Stoxx | F22: DCF: WACC | G22: 45717 | H22: S4
B23: Terminal Growth Rate (g) | D23: 0.025 | E23: Long-run nominal Eurozone GDP proxy | F23: DCF: Terminal Value | G23: N/A | H23: S4
B24: Marginal Tax Rate | D24: 0.29 | E24: Blended French corporate tax rate | F24: DCF: NOPAT | G24: FY2024 | H24: S1
B25: Luxury TAM ($bn) | D25: €1.5tn | E25: Bain Global Luxury Market Size 2024 | F25: Forecast: Revenue | G25: 45627 | H25: S7
B26: Consensus Revenue FY25E ($mm) | D26: €17.9bn | E26: FactSet consensus FY25E Revenue | F26: Benchmark | G26: 45717 | H26: S4
B27: Consensus EPS FY25E | D27: €51.20 | E27: FactSet consensus FY25E EPS | F27: Benchmark | G27: 45717 | H27: S4
B28: [Add rows as needed]
B30: SECTION 3: FOOTNOTES & ADJUSTMENTS
B31: Ref # | C31: Tab / Cell | D31: Footnote Description | E31: Source Ref | F31: Impact on Model
B32: [1] | C32: DCF Valuation, D9 | D32: Risk-free rate based on 10Y German Bund yield; Euro-denominated model | E32: S6 | F32: Core WACC input
B33: [2] | C33: DCF Valuation, D11 | D33: Beta sourced from FactSet 5Y monthly regression vs. Euro Stoxx 50; R-sq = 0.68 | E33: S4 | F33: Affects Ke and WACC
B34: [3] | C34: Master Assumptions, J38 | D34: Terminal growth = 2.5% reflects long-term Eurozone nominal GDP; conservative for luxury | E34: S4 | F34: Terminal value driver
B35: [4] | C35: DCF Valuation, D51 | D35: SBC added back to FCF as non-cash; dilution captured via fully diluted shares | E35: S1 | F35: Increases UCF
B36: [5] | C36: Forecast Model, Revenue | D36: Revenue growth driven by pricing power + volume; Asia-Pacific expansion assumed | E36: S3 | F36: Core revenue driver
B37: [6] | C37: Historical Financials, Margins | D37: Gross margin held flat at 71.7% historical average; reflects pricing discipline | E37: S1 | F37: Margin stability
B38: [7] | C38: Trading Comps, Multiples | D38: EV/EBITDA exit multiple of 16.6x based on peer median from Bloomberg | E38: S5 | F38: Alternative TV method
B39: [8] | C39: Master Assumptions, CapEx | D39: CapEx as 6.7% of revenue; includes store expansions and production facilities | E39: S1 | F39: FCF reduction
B40: [9] | C40: Supporting Schedules, NWC | D40: Working capital based on historical DSO/DIO/DPO averages; luxury inventory cycle | E40: S1 | F40: Cash conversion
B41: [10] | C41: DCF Valuation, Shares | D41: Fully Diluted Shares | E41: S4 | F41: Equity Value Bridge
B43: SECTION 4: METHODOLOGY NOTES
B44: Area | C44: Methodology Description | D44: Applicable Tab(s)
B45: Valuation Approach | C45: Unlevered DCF with perpetuity growth & exit multiple terminal values; mid-year convention applied | D45: DCF Valuation
B46: WACC Derivation | C46: CAPM-based Ke (Rf + β × ERP); 100% equity weight reflects near-zero net debt position | D46: DCF Valuation
B47: Revenue Forecast | C47: Revenue driven by 11.9% FY25 growth tapering to 7.9% by FY29; reflects luxury market maturation | D47: Forecast Model
B48: Margin Expansion | C48: Gross margin held constant at 71.7%; EBITDA margin ~42% reflecting operational excellence | D48: Master Assumptions
B49: Working Capital | C49: DSO 12 days, DIO 237 days (leather goods inventory), DPO 55 days; NWC as % of revenue delta | D49: Supporting Schedules
B50: CapEx Treatment | C50: CapEx at 6.7% of revenue; includes retail expansion, production capacity, and digital investment | D50: Supporting Schedules
B51: SBC Treatment | C51: SBC added back to FCF as non-cash expense; share dilution captured in fully diluted share count | D51: DCF Valuation
B52: Tax Assumptions | C52: Effective tax rate of 29% maintained; reflects French corporate tax regime | D52: Master Assumptions
B53: Terminal Value | C53: Gordon growth model at 2.5% perpetuity (Eurozone GDP proxy); Exit multiple at 16.6x EV/EBITDA | D53: DCF, Sensitivity
B54: Scenario Framework | C54: Bull/Base/Bear scenarios via CHOOSE function; assumptions linked from Master Assumptions tab | D54: Scenario Analysis
B56: SECTION 5: REVISION LOG
B57: Version | C57: Date | D57: Author | E57: Change Description | F57: Tabs Affected
B58: v1.0 | C58: [Date] | D58: [Initials] | E58: [e.g., Initial model build; historical financials + DCF] | F58: [All]
B59: v1.1 | C59: [Date] | D59: [Initials] | E59: [e.g., Updated beta + ERP; re-ran sensitivity tables] | F59: [DCF, Sensitivity]
B60: v1.2 | C60: [Date] | D60: [Initials] | E60: [e.g., Added scenario analysis; Bull/Base/Bear assumptions] | F60: [Scenarios, Assumptions]
B61: v2.0 | C61: [Date] | D61: [Initials] | E61: [e.g., Major revision: incorporated Q4 2024 actuals; revised forecast] | F61: [Hist. Fin., Forecast]
B62: v2.1 | C62: [Date] | D62: [Initials] | E62: [Change description] | F62: [Tab names]
B63: v3.0 | C63: [Date] | D63: [Initials] | E63: [Change description] | F63: [Tab names]
B64: [Add]
B66: SECTION 6: DISCLAIMER & LIMITATIONS
B67: IMPORTANT: This financial model is prepared for informational and analytical purposes only.
B68: [1] This model does not constitute investment advice, a recommendation, or a solicitation to buy or sell securities.
B69: [2] All projections are based on assumptions that may not reflect actual future performance.
B70: [3] Historical financial data is sourced from public SEC filings and may be subject to restatement.
B71: [4] Market data (prices, rates, betas) is point-in-time and subject to change.
B72: [5] Model outputs are highly sensitive to input assumptions; users should review the Sensitivity Analysis tab.
B73: [6] The author(s) make no warranty as to accuracy or completeness of data or projections.
B74: [7] Users should conduct independent due diligence before making any investment decisions.
