Workbook

Sheet Cover
C7: COMPREHENSIVE VALUATION MODEL
C8: Duolingo, Inc.
C9: NASDAQ: DUOL | Technology — Education Software
C13: Rating | D13: Price Target | E13: Enterprise Value | F13: Scenario Range
C14: BUY | D14: 164.5 | E14: $7,286mm | F14: $60 – $165
C15: Initiating Coverage | D15: DCF (5-Year) | E15: Equity: $8,164mm | F15: Bear | Base | Bull
C18: Model Details
C19: Date | D19: 45689
C20: Analyst | D20: [Analyst Name]
C21: WACC | D21: 11.14% (Rf: 4.05% | ERP: 4.46% | β: 1.59x | TGR: 2.5%)
C22: Methodology | D22: 5-Year DCF | Bull / Base / Bear Scenario Analysis | Sensitivity Testing
C23: Status | D23: Complete — All integration checks passed ✓
C26: CONFIDENTIAL
C27: This document is proprietary and intended solely for the use of the intended recipient(s). Do not distribute.

Sheet TOC
B1: [DUOLINGO] ([DUOL-US])
B2: Comprehensive Valuation Model — Table of Contents
B4: Tab # | C4: Tab Name | D4: Description | E4: Status
B5: SECTION 1: EXECUTIVE SUMMARY & OVERVIEW
B6: 1 | C6: Cover | D6: Title page, version control, confidentiality notice | E6: Complete
B7: 2 | C7: TOC | D7: Table of contents & model map | E7: Complete
B8: 3 | C8: Executive Summary | D8: Valuation, key metrics, scenario analysis, sensitivity, charts | E8: Complete
B9: 4 | C9: Key Metrics | D9: KPI dashboard, operating metrics, key ratios | E9: Pending
B10: 5 | C10: Investment Highlights | D10: Bull/bear case, catalysts, risks | E10: Pending
B12: SECTION 2: HISTORICAL FINANCIALS & ANALYSIS
B13: 6 | C13: Historical Financials | D13: Historical IS + BS + CF (vertical 3-statement) | E13: Complete
B14: 7 | C14: Historical Analysis | D14: Margins, growth rates, ratio analysis, trends | E14: Complete
B16: SECTION 3: ASSUMPTIONS & SUPPORTING SCHEDULES
B17: 8 | C17: Master Assumptions | D17: Key drivers: revenue growth, margins, CapEx, tax, WACC | E17: Complete
B18: 9 | C18: Supporting Schedules | D18: Supporting analysis, Bull/Bear cases | E18: Complete
B20: SECTION 4: FORECASTS & PROJECTIONS
B21: 11 | C21: Forecast Model | D21: Projected IS + BS + CF (vertical 3-statement model) | E21: Complete
B22: 12 | C22: Integration Check | D22: BS balances, CF reconciliation, error checks | E22: Complete
B24: SECTION 5: VALUATION
B25: 13 | C25: DCF Valuation | D25: Discounted Cash Flow analysis (WACC, terminal value) | E25: Complete
B27: SECTION 6: OUTPUTS & ANALYSIS
B28: 17 | C28: Sensitivity Analysis | D28: WACC vs. growth, revenue vs. margin data tables | E28: Complete
B29: 18 | C29: Scenario Analysis | D29: Bull / Base / Bear case outputs | E29: Complete
B31: SECTION 7: REFERENCE & DATA
B32: 19 | C32: Sources & Footnotes | D32: Data sources, market inputs, methodology, revision log, disclaimers | E32: Complete
B35: COLOR CODING LEGEND
B36: 🔵 | C36: BLUE cells | D36: Hardcoded inputs / assumptions (user changes these)
B37: ⬛ | C37: BLACK cells | D37: Formulas & calculations (model calculates these)
B38: 🟢 | C38: GREEN cells | D38: Links from other worksheets within workbook
B39: 🟡 | C39: YELLOW cells | D39: Flags / checks / key assumptions needing attention
B40: 🔴 | C40: RED cells | D40: External links to other files

Sheet Executive Summary
A1: DUOLINGO, INC. (NASDAQ: DUOL) | EQUITY RESEARCH | INITIATING COVERAGE
A2: Technology — Education Software | February 2025
B4: RATING | C4: PRICE TARGET | D4: METHODOLOGY | E4: WACC | F4: TGR | G4: EV ($mm) | H4: EQUITY ($mm) | I4: TV / EV | J4: SHARES (FD) | K4: SCENARIO
B5: BUY | C5: 164.5 | D5: DCF (5-Yr) | E5: 0.111 | F5: 0.025 | G5: 7286 | H5: 8164 | I5: 0.755 | J5: 49.62mm | K5: $60 – $165
B7: 🐂 BULL | C7: 25% Prob | E7: 📊 BASE | F7: 50% Prob | H7: 🐻 BEAR | I7: 25% Prob | K7: PROB-WTD
B8: 165 | C8: EV: $7.3B | E8: 97 | F8: EV: $3.9B | H8: 60 | I8: EV: $2.1B | K8: 105
A10: SENSITIVITY: WACC vs TGR ($) | H10: DCF VALUATION BRIDGE ($mm)
B11: 0.015 | C11: 0.02 | D11: 0.025 | E11: 0.03 | F11: 0.035 | H11: PV of FCFs ('25E–'29E) | J11: 1786 | K11: 0.245
A12: 0.091 | B12: 190 | C12: 200 | D12: 212 | E12: 226 | F12: 242 | H12: PV of Terminal Value | J12: 5500 | K12: 0.755
A13: 0.101 | B13: 169 | C13: 177 | D13: 185 | E13: 195 | F13: 206 | H13: Enterprise Value | J13: 7286
A14: 0.111 | B14: 152 | C14: 158 | D14: 165 | E14: 172 | F14: 180 | H14: (+) Net Cash | J14: 878
A15: 0.121 | B15: 138 | C15: 143 | D15: 148 | E15: 154 | F15: 160 | H15: Equity Value | J15: 8164
A16: 0.131 | B16: 127 | C16: 131 | D16: 135 | E16: 140 | F16: 145 | H16: Implied Share Price | J16: 164.5
A38: Source: Company 10-K/10-Q, DCF Model, Scenario Analysis. See Sources & Footnotes tab.

Sheet Historical Financials
B4: INCOME STATEMENT
B7: All figures in millions of | F7: 2020A | G7: 2021A | H7: 2022A | I7: 2023A | J7: 2024A
B8: U.S. Dollars unless stated
B10: Revenue | F10: 161.696 | G10: 250.772 | H10: 369.495 | I10: 531.109 | J10: 748.024
B11: COGS (excl. D&A) | F11: -44.277 | G11: -67.153 | H11: -98.561 | I11: -140.085 | J11: -198.335
B12: Gross Profit (excl. D&A) | F12: =SUM(F10:F11) -> 117.419 | G12: =SUM(G10:G11) -> 183.619 | H12: =SUM(H10:H11) -> 270.934 | I12: =SUM(I10:I11) -> 391.024 | J12: =SUM(J10:J11) -> 549.689
B14: R&D Expense | F14: -53.024 | G14: -103.787 | H14: -148.944 | I14: -192.702 | J14: -232.94
B15: SG&A Expense | F15: -77.868 | G15: -133.204 | H15: -181.679 | I15: -204.148 | J15: -242.326
B16: D&A Expense | F16: -2.256 | G16: -2.726 | H16: -4.87 | I16: -7.095 | J16: -10.854
B17: EBIT | F17: =SUM(F12:F16) -> -15.729 | G17: =SUM(G12:G16) -> -56.098 | H17: =SUM(H12:H16) -> -64.559 | I17: =SUM(I12:I16) -> -12.921 | J17: =SUM(J12:J16) -> 63.569
B19: Interest Income | F19: 0 | G19: 0 | H19: 7.235 | I19: 31.091 | J19: 42.697
B20: Unusual Expense | F20: -0.282 | G20: -3.909 | H20: -0.636 | I20: -0.338 | J20: -0.974
B21: Other Income | F21: 0.303 | G21: 0.049 | H21: -0.676 | I21: -0.055 | J21: -2.986
B22: EBT | F22: =SUM(F17:F21) -> -15.708 | G22: =SUM(G17:G21) -> -59.958 | H22: =SUM(H17:H21) -> -58.636 | I22: =SUM(I17:I21) -> 17.777 | J22: =SUM(J17:J21) -> 102.306
B24: Income Taxes | F24: -0.068 | G24: -0.177 | H24: -0.938 | I24: -1.71 | J24: -13.732
B25: Equity in Affiliates | F25: 0 | G25: 0 | H25: 0 | I25: 0 | J25: 0
B26: Net Income | F26: =SUM(F22:F25) -> -15.776 | G26: =SUM(G22:G25) -> -60.135 | H26: =SUM(H22:H25) -> -59.574 | I26: =SUM(I22:I25) -> 16.067 | J26: =SUM(J22:J25) -> 88.574
B29: BALANCE STATEMENT
B33: All figures in millions of | F33: 2020A | G33: 2021A | H33: 2022A | I33: 2023A | J33: 2024A
B34: U.S. Dollars unless stated
B36: Assets
B37: Cash & Short-Term Investments | F37: 120.49 | G37: 553.922 | H37: 608.18 | I37: 747.61 | J37: 877.645
B38: Accounts Receivable | F38: 20.45 | G38: 33.163 | H38: 46.728 | I38: 88.975 | J38: 128.923
B39: Other Receivables | F39: 13.585 | G39: 24.219 | H39: 35.041 | I39: 53.931 | J39: 80.162
B40: Inventories | F40: 0 | G40: 0 | H40: 0 | I40: 0 | J40: 0
B41: Other Current Assets | F41: 3.855 | G41: 7.967 | H41: 7.234 | I41: 7.282 | J41: 14.858
B42: Total Current Assets | F42: =SUM(F37:F41) -> 158.38 | G42: =SUM(G37:G41) -> 619.271 | H42: =SUM(H37:H41) -> 697.183 | I42: =SUM(I37:I41) -> 897.798 | J42: =SUM(J37:J41) -> 1101.588
B44: Net PP&E | F44: 14.501 | G44: 36.58 | H44: 35.477 | I44: 30.895 | J44: 66.438
B45: Goodwill | F45: 0 | G45: 0 | H45: 4.05 | I45: 4.05 | J45: 10.538
B46: Other Intangible Assets | F46: 2.296 | G46: 4.566 | H46: 8.497 | I46: 15.995 | J46: 19.899
B47: Long-Term Investments | F47: 0 | G47: 0 | H47: 0 | I47: 2.735 | J47: 101.027
B48: Deferred Tax Assets | F48: 0 | G48: 0 | H48: 10.247 | I48: 11.038 | J48: 0.675
B49: Other Non-Current Assets | F49: 0.562 | G49: 0.894 | H49: 1.507 | I49: 1.718 | J49: 1.563
B50: Total Non-Current Assets | F50: =SUM(F44:F49) -> 17.359 | G50: =SUM(G44:G49) -> 42.04 | H50: =SUM(H44:H49) -> 59.778 | I50: =SUM(I44:I49) -> 66.431 | J50: =SUM(J44:J49) -> 200.14
B52: Total Assets | F52: =F42+F50 -> 175.739 | G52: =G42+G50 -> 661.311 | H52: =H42+H50 -> 756.961 | I52: =I42+I50 -> 964.229 | J52: =J42+J50 -> 1301.728
B54: Liabilities
B55: Accounts Payable | F55: 2.196 | G55: 7.818 | H55: 1.177 | I55: 2.447 | J55: 6.381
B56: Short-Term Debt & Curr. LT Portion | F56: 1.111 | G56: 3.336 | H56: 4.903 | I56: 3.944 | J56: 2.581
B57: Income Tax Payable | F57: 0.068 | G57: 0.113 | H57: 1.069 | I57: 0.792 | J57: 6.591
B58: Other Current Liabilities | F58: 62.315 | G58: 107.864 | H58: 174.617 | I58: 270.179 | J58: 406.678
B59: Total Current Liabilities | F59: =SUM(F55:F58) -> 65.69 | G59: =SUM(G55:G58) -> 119.131 | H59: =SUM(H55:H58) -> 181.766 | I59: =SUM(I55:I58) -> 277.362 | J59: =SUM(J55:J58) -> 422.231
B61: Long-Term Debt | F61: 8.131 | G61: 29.124 | H61: 23.503 | I61: 21.094 | J61: 54.656
B62: Deferred Tax Liabilities | F62: 0 | G62: 0 | H62: 9.614 | I62: 10.272 | J62: 0.291
B63: Other Non-Current Liabilities | F63: 0 | G63: 0 | H63: 0 | I63: 0 | J63: 0
B64: Total Non-Current Liabilities | F64: =SUM(F61:F63) -> 8.131 | G64: =SUM(G61:G63) -> 29.124 | H64: =SUM(H61:H63) -> 33.117 | I64: =SUM(I61:I63) -> 31.366 | J64: =SUM(J61:J63) -> 54.947
B65: Total Liabilities | F65: =F64+F59 -> 73.821 | G65: =G64+G59 -> 148.255 | H65: =H64+H59 -> 214.883 | I65: =I64+I59 -> 308.728 | J65: =J64+J59 -> 477.178
B67: Shareholders' Equity
B68: Common Stock & APIC | F68: 30.087 | G68: 683.966 | H68: 772.562 | I68: 869.918 | J68: 950.393
B69: Retained Earnings | F69: -110.779 | G69: -170.914 | H69: -230.488 | I69: -214.421 | J69: -125.847
B70: Treasury Stock | F70: 0 | G70: 0 | H70: 0 | I70: 0 | J70: 0
B71: Other Comprehensive Income | F71: 0 | G71: 0 | H71: 0 | I71: 0 | J71: 0
B72: Preferred Stock | F72: 182.609 | G72: 0 | H72: 0 | I72: 0 | J72: 0
B73: Total Shareholders' Equity | F73: =SUM(F68:F72) -> 101.917 | G73: =SUM(G68:G72) -> 513.052 | H73: =SUM(H68:H72) -> 542.074 | I73: =SUM(I68:I72) -> 655.497 | J73: =SUM(J68:J72) -> 824.546
B75: Total Liabilities & Equity | F75: =F65+F73 -> 175.738 | G75: =G65+G73 -> 661.307 | H75: =H65+H73 -> 756.957 | I75: =I65+I73 -> 964.225 | J75: =J65+J73 -> 1301.724
B78: CASH FLOW STATEMENT
B82: All figures in millions of | F82: 2020A | G82: 2021A | H82: 2022A | I82: 2023A | J82: 2024A
B83: U.S. Dollars unless stated
B85: Operating Activities
B86: Net Income | F86: -15.776 | G86: -60.135 | H86: -59.574 | I86: 16.067 | J86: 88.574
B87: D&A | F87: 2.256 | G87: 2.726 | H87: 4.87 | I87: 7.095 | J87: 10.854
B88: Deferred Taxes | F88: 0 | G88: 0 | H88: 0 | I88: 0 | J88: 0
B89: Stock-Based Compensation & Other | F89: 17.031 | G89: 40.804 | H89: 73.82 | I89: 95.554 | J89: 110.164
B90: Changes in Working Capital:
B91: (Increase) / Decrease in Receivables | F91: 18.04 | G91: 30.762 | H91: 45.718 | I91: 49.395 | J91: 83.775
B92: (Increase) / Decrease in Inventories | F92: 0 | G92: 0 | H92: 0 | I92: 0 | J92: 0
B93: Increase / (Decrease) in Accounts Payable | F93: -1.615 | G93: 5.622 | H93: -6.655 | I93: 1.261 | J93: 3.934
B94: Other Working Capital Changes | F94: -8.441 | G94: -14.317 | H94: -13.243 | I94: -19.202 | J94: -28.638
B95: Other Accurals | F95: 6.213 | G95: 3.708 | H95: 8.72 | I95: 3.444 | J95: 16.85
B96: Cash Flow from Operations | F96: =SUM(F86:F95) -> 17.708 | G96: =SUM(G86:G95) -> 9.17 | H96: =SUM(H86:H95) -> 53.656 | I96: =SUM(I86:I95) -> 153.614 | J96: =SUM(J86:J95) -> 285.513
B98: Investing Activities
B99: Capital Expenditures | F99: -4.014 | G99: -6.206 | H99: -10.124 | I99: -13.684 | J99: -21.14
B100: Acquisitions | F100: 0 | G100: 0 | H100: -4.05 | I100: 0 | J100: -6.595
B101: Purchase / Sale of Investments | F101: 0 | G101: 0 | H101: 0 | I101: 0 | J101: -189.595
B102: Other Investing Activities | F102: 0 | G102: 0 | H102: 0 | I102: 0.1 | J102: 0
B103: Cash Flow from Investing | F103: =SUM(F99:F102) -> -4.014 | G103: =SUM(G99:G102) -> -6.206 | H103: =SUM(H99:H102) -> -14.174 | I103: =SUM(I99:I102) -> -13.584 | J103: =SUM(J99:J102) -> -217.33
B105: Financing Activities
B106: Dividends Paid | F106: 0 | G106: 0 | H106: 0 | I106: 0 | J106: 0
B107: Share Repurchases | F107: 0 | G107: -8.203 | H107: 0 | I107: 0 | J107: 0
B108: Stock Issuances | F108: 2.03 | G108: 438.671 | H108: 14.776 | I108: 13.617 | J108: 19.356
B109: Debt Issuance / (Repayment) | F109: 0 | G109: 0 | H109: 0 | I109: 0 | J109: 0
B110: Others | F110: 44.923 | G110: 0 | H110: 0 | I110: -11.482 | J110: -49.358
B111: Cash Flow from Financing | F111: =SUM(F106:F110) -> 46.953 | G111: =SUM(G106:G110) -> 430.468 | H111: =SUM(H106:H110) -> 14.776 | I111: =SUM(I106:I110) -> 2.135 | J111: =SUM(J106:J110) -> -30.002
B113: Effect of Exchange Rate | F113: 0 | G113: 0 | H113: 0 | I113: 0 | J113: 0
B114: Net Change in Cash | F114: =F96+F103+F111 -> 60.647 | G114: =G96+G103+G111 -> 433.432 | H114: =H96+H103+H111 -> 54.258 | I114: =I96+I103+I111 -> 142.165 | J114: =J96+J103+J111 -> 38.181

Sheet Historical Analysis
B3: SECTION A: GROWTH AND MARGIN ANALYSIS
B5: REVENUE GROWTH:
F6: 2020A | G6: 2021A | H6: 2022A | I6: 2023A | J6: 2024A | L6: Trend
B7: Total Revenue ($M) | F7: 161.696 | G7: 250.772 | H7: 369.495 | I7: 531.109 | J7: 748.024
B8: YoY Growth % | G8: =(G7/F7-1) -> 0.55088561 | H8: =(H7/G7-1) -> 0.47343005 | I8: =(I7/H7-1) -> 0.43739157 | J8: =(J7/I7-1) -> 0.40841899
B9: 5Y CAGR | J9: =(J7/F7)^(1/5)-1 -> 0.35844873
B11: GROSS MARGIN:
F12: 2020A | G12: 2021A | H12: 2022A | I12: 2023A | J12: 2024A | L12: Trend
B13: Gross Profit ($M) | F13: ='Historical Financials'!F12 -> 117.419 | G13: ='Historical Financials'!G12 -> 183.619 | H13: ='Historical Financials'!H12 -> 270.934 | I13: ='Historical Financials'!I12 -> 391.024 | J13: ='Historical Financials'!J12 -> 549.689
B14: Gross Profit % | F14: =F13/'Historical Financials'!F10 -> 0.72617133 | G14: =G13/'Historical Financials'!G10 -> 0.73221492 | H14: =H13/'Historical Financials'!H10 -> 0.73325485 | I14: =I13/'Historical Financials'!I10 -> 0.73624058 | J14: =J13/'Historical Financials'!J10 -> 0.73485476
B17: OPEX ANALYSIS:
F18: 2020A | G18: 2021A | H18: 2022A | I18: 2023A | J18: 2024A | L18: Trend
B19: R&D % of Revenue | F19: ='Historical Financials'!F14*-1/'Historical Financials'!F10 -> 0.32792401 | G19: ='Historical Financials'!G14*-1/'Historical Financials'!G10 -> 0.41386997 | H19: ='Historical Financials'!H14*-1/'Historical Financials'!H10 -> 0.40310153 | I19: ='Historical Financials'!I14*-1/'Historical Financials'!I10 -> 0.36282948 | J19: ='Historical Financials'!J14*-1/'Historical Financials'!J10 -> 0.31140712
B20: SG&A % of Revenue | F20: ='Historical Financials'!F15*-1/'Historical Financials'!F10 -> 0.48157035 | G20: ='Historical Financials'!G15*-1/'Historical Financials'!G10 -> 0.53117573 | H20: ='Historical Financials'!H15*-1/'Historical Financials'!H10 -> 0.49169542 | I20: ='Historical Financials'!I15*-1/'Historical Financials'!I10 -> 0.38438061 | J20: ='Historical Financials'!J15*-1/'Historical Financials'!J10 -> 0.32395485
B21: D&A % of Revenue | F21: ='Historical Financials'!F16*-1/'Historical Financials'!F10 -> 0.013952108 | G21: ='Historical Financials'!G16*-1/'Historical Financials'!G10 -> 0.010870432 | H21: ='Historical Financials'!H16*-1/'Historical Financials'!H10 -> 0.013180151 | I21: ='Historical Financials'!I16*-1/'Historical Financials'!I10 -> 0.01335884 | J21: ='Historical Financials'!J16*-1/'Historical Financials'!J10 -> 0.01451023
B22: Total Opex % of Revenue | F22: =SUM('Historical Financials'!F14:F16)*-1/'Historical Financials'!F10 -> 0.82344647 | G22: =SUM('Historical Financials'!G14:G16)*-1/'Historical Financials'!G10 -> 0.95591613 | H22: =SUM('Historical Financials'!H14:H16)*-1/'Historical Financials'!H10 -> 0.9079771 | I22: =SUM('Historical Financials'!I14:I16)*-1/'Historical Financials'!I10 -> 0.76056892 | J22: =SUM('Historical Financials'!J14:J16)*-1/'Historical Financials'!J10 -> 0.6498722
B25: PROFITABILITY:
F26: 2020A | G26: 2021A | H26: 2022A | I26: 2023A | J26: 2024A | L26: Trend
B27: Operating Margin % | F27: ='Historical Financials'!F17/'Historical Financials'!F10 -> -0.097275134 | G27: ='Historical Financials'!G17/'Historical Financials'!G10 -> -0.22370121 | H27: ='Historical Financials'!H17/'Historical Financials'!H10 -> -0.17472226 | I27: ='Historical Financials'!I17/'Historical Financials'!I10 -> -0.024328339 | J27: ='Historical Financials'!J17/'Historical Financials'!J10 -> 0.084982567
B28: EBITDA Margin % | F28: =('Historical Financials'!F17-'Historical Financials'!F16)/'Historical Financials'!F10 -> -0.083323026 | G28: =('Historical Financials'!G17-'Historical Financials'!G16)/'Historical Financials'!G10 -> -0.21283078 | H28: =('Historical Financials'!H17-'Historical Financials'!H16)/'Historical Financials'!H10 -> -0.1615421 | I28: =('Historical Financials'!I17-'Historical Financials'!I16)/'Historical Financials'!I10 -> -0.0109695 | J28: =('Historical Financials'!J17-'Historical Financials'!J16)/'Historical Financials'!J10 -> 0.099492797
B29: Net Margin % | F29: ='Historical Financials'!F26/'Historical Financials'!F10 -> -0.097565802 | G29: ='Historical Financials'!G26/'Historical Financials'!G10 -> -0.2397995 | H29: ='Historical Financials'!H26/'Historical Financials'!H10 -> -0.16123087 | I29: ='Historical Financials'!I26/'Historical Financials'!I10 -> 0.030251794 | J29: ='Historical Financials'!J26/'Historical Financials'!J10 -> 0.11841064
B32: SECTION B: CASH GENERATION AND CAPITAL EFFICIENCY
B35: CASH FLOW QUALITY:
F36: 2020A | G36: 2021A | H36: 2022A | I36: 2023A | J36: 2024A | L36: Trend
B37: OCF | F37: ='Historical Financials'!F96 -> 17.708 | G37: ='Historical Financials'!G96 -> 9.17 | H37: ='Historical Financials'!H96 -> 53.656 | I37: ='Historical Financials'!I96 -> 153.614 | J37: ='Historical Financials'!J96 -> 285.513
B38: FCF | F38: ='Historical Financials'!F96-ABS('Historical Financials'!F99) -> 13.694 | G38: ='Historical Financials'!G96-ABS('Historical Financials'!G99) -> 2.964 | H38: ='Historical Financials'!H96-ABS('Historical Financials'!H99) -> 43.532 | I38: ='Historical Financials'!I96-ABS('Historical Financials'!I99) -> 139.93 | J38: ='Historical Financials'!J96-ABS('Historical Financials'!J99) -> 264.373
B41: WC DYNAMICS:
F42: 2020A | G42: 2021A | H42: 2022A | I42: 2023A | J42: 2024A | L42: Trend
B43: Changes in WC ($M):
B44: Changes in AR | F44: ='Historical Financials'!F91 -> 18.04 | G44: ='Historical Financials'!G91 -> 30.762 | H44: ='Historical Financials'!H91 -> 45.718 | I44: ='Historical Financials'!I91 -> 49.395 | J44: ='Historical Financials'!J91 -> 83.775
B45: Changes in AP | F45: ='Historical Financials'!F93 -> -1.615 | G45: ='Historical Financials'!G93 -> 5.622 | H45: ='Historical Financials'!H93 -> -6.655 | I45: ='Historical Financials'!I93 -> 1.261 | J45: ='Historical Financials'!J93 -> 3.934
B46: Changes in Accurals | F46: {='Historical Financials'!F95:J95} -> 6.213 | G46: 3.708 | H46: 8.72 | I46: 3.444 | J46: 16.85
B47: Other WC changes | F47: ='Historical Financials'!F94 -> -8.441 | G47: ='Historical Financials'!G94 -> -14.317 | H47: ='Historical Financials'!H94 -> -13.243 | I47: ='Historical Financials'!I94 -> -19.202 | J47: ='Historical Financials'!J94 -> -28.638
B49: Net WC Impact | F49: =SUM(F44:F47) -> 14.197 | G49: =SUM(G44:G47) -> 25.775 | H49: =SUM(H44:H47) -> 34.54 | I49: =SUM(I44:I47) -> 34.898 | J49: =SUM(J44:J47) -> 75.921
B51: DSO | F51: =(365*'Historical Financials'!F38)/'Historical Financials'!F10 -> 46.162243 | G51: =(365*'Historical Financials'!G38)/'Historical Financials'!G10 -> 48.268926 | H51: =(365*'Historical Financials'!H38)/'Historical Financials'!H10 -> 46.159542 | I51: =(365*'Historical Financials'!I38)/'Historical Financials'!I10 -> 61.147288 | J51: =(365*'Historical Financials'!J38)/'Historical Financials'!J10 -> 62.908269
B52: DPO | F52: =(365*'Historical Financials'!F55)/'Historical Financials'!F11*-1 -> 18.102852 | G52: =(365*'Historical Financials'!G55)/'Historical Financials'!G11*-1 -> 42.493559 | H52: =(365*'Historical Financials'!H55)/'Historical Financials'!H11*-1 -> 4.3587727 | I52: =(365*'Historical Financials'!I55)/'Historical Financials'!I11*-1 -> 6.3758075 | J52: =(365*'Historical Financials'!J55)/'Historical Financials'!J11*-1 -> 11.743086
B54: CCC | F54: =F51-F52 -> 28.05939 | G54: =G51-G52 -> 5.7753661 | H54: =H51-H52 -> 41.800769 | I54: =I51-I52 -> 54.77148 | J54: =J51-J52 -> 51.165183
B56: CAPEX REQUIREMENTS:
F57: 2020A | G57: 2021A | H57: 2022A | I57: 2023A | J57: 2024A
B59: CapEx ($M) | F59: ='Historical Financials'!F99*-1 -> 4.014 | G59: ='Historical Financials'!G99*-1 -> 6.206 | H59: ='Historical Financials'!H99*-1 -> 10.124 | I59: ='Historical Financials'!I99*-1 -> 13.684 | J59: ='Historical Financials'!J99*-1 -> 21.14
B60: as % of Revenue | F60: =F59/'Historical Financials'!F10 -> 0.024824362 | G60: =G59/'Historical Financials'!G10 -> 0.024747579 | H60: =H59/'Historical Financials'!H10 -> 0.027399559 | I60: =I59/'Historical Financials'!I10 -> 0.025764956 | J60: =J59/'Historical Financials'!J10 -> 0.028261125
B62: CapEx / Depreciation | F62: ='Historical Analysis'!F59/'Historical Financials'!F87 -> 1.7792553 | G62: ='Historical Analysis'!G59/'Historical Financials'!G87 -> 2.2765957 | H62: ='Historical Analysis'!H59/'Historical Financials'!H87 -> 2.0788501 | I62: ='Historical Analysis'!I59/'Historical Financials'!I87 -> 1.9286822 | J62: ='Historical Analysis'!J59/'Historical Financials'!J87 -> 1.9476691
B65: SECTION C: BALANCE SHEET HEALTH AND RETURN METRICS
B68: LIQUIDITY:
F69: 2020A | G69: 2021A | H69: 2022A | I69: 2023A | J69: 2024A | L69: Trend
B70: Current Ratio | F70: ='Historical Financials'!F42/'Historical Financials'!F59 -> 2.4110215 | G70: ='Historical Financials'!G42/'Historical Financials'!G59 -> 5.1982356 | H70: ='Historical Financials'!H42/'Historical Financials'!H59 -> 3.8356073 | I70: ='Historical Financials'!I42/'Historical Financials'!I59 -> 3.2369178 | J70: ='Historical Financials'!J42/'Historical Financials'!J59 -> 2.60897
B71: Quick Ratio | F71: =('Historical Financials'!F37+'Historical Financials'!F38)/'Historical Financials'!F59 -> 2.145532 | G71: =('Historical Financials'!G37+'Historical Financials'!G38)/'Historical Financials'!G59 -> 4.9280624 | H71: =('Historical Financials'!H37+'Historical Financials'!H38)/'Historical Financials'!H59 -> 3.6030281 | I71: =('Historical Financials'!I37+'Historical Financials'!I38)/'Historical Financials'!I59 -> 3.0162207 | J71: =('Historical Financials'!J37+'Historical Financials'!J38)/'Historical Financials'!J59 -> 2.3839273
B74: LEVERAGE:
F75: 2020A | G75: 2021A | H75: 2022A | I75: 2023A | J75: 2024A
B76: Total Debt | F76: 0 | G76: 0 | H76: 0 | I76: 0 | J76: 0
B77: Equity | F77: ='Historical Financials'!F73 -> 101.917 | G77: ='Historical Financials'!G73 -> 513.052 | H77: ='Historical Financials'!H73 -> 542.074 | I77: ='Historical Financials'!I73 -> 655.497 | J77: ='Historical Financials'!J73 -> 824.546
B79: Debt / Equity | F79: =F76/F77 -> 0 | G79: =G76/G77 -> 0 | H79: =H76/H77 -> 0 | I79: =I76/I77 -> 0 | J79: =J76/J77 -> 0
B80: ICR | F80: N/A | G80: N/A | H80: N/A | I80: N/A | J80: N/A
B82: EQUITY & RETAINED EARNINGS:
F83: 2020A | G83: 2021A | H83: 2022A | I83: 2023A | J83: 2024A
B84: Total Shareholder's Equity | F84: ='Historical Financials'!F73 -> 101.917 | G84: ='Historical Financials'!G73 -> 513.052 | H84: ='Historical Financials'!H73 -> 542.074 | I84: ='Historical Financials'!I73 -> 655.497 | J84: ='Historical Financials'!J73 -> 824.546
B85: Retained Earnings | F85: ='Historical Financials'!F69 -> -110.779 | G85: ='Historical Financials'!G69 -> -170.914 | H85: ='Historical Financials'!H69 -> -230.488 | I85: ='Historical Financials'!I69 -> -214.421 | J85: ='Historical Financials'!J69 -> -125.847
B87: YoY equity Growth | G87: =(G84/F84-1) -> 4.0340179 | H87: =(H84/G84-1) -> 0.056567365 | I87: =(I84/H84-1) -> 0.20923896 | J87: =(J84/I84-1) -> 0.25789439
B90: RETURN METRICS:
F91: 2020A | G91: 2021A | H91: 2022A | I91: 2023A | J91: 2024A
B93: RoE(%)
B94: =NI/Shareholder's Equity | F94: ='Historical Financials'!F26/'Historical Financials'!F73 -> -0.15479263 | G94: ='Historical Financials'!G26/'Historical Financials'!G73 -> -0.11721034 | H94: ='Historical Financials'!H26/'Historical Financials'!H73 -> -0.10990012 | I94: ='Historical Financials'!I26/'Historical Financials'!I73 -> 0.024511172 | J94: ='Historical Financials'!J26/'Historical Financials'!J73 -> 0.10742154
B96: RoA(%)
B97: =Net Income/Avg Assets | F97: ='Historical Financials'!F26/'Historical Financials'!F52 -> -0.089769488 | G97: ='Historical Financials'!G26/'Historical Financials'!G52 -> -0.09093301 | H97: ='Historical Financials'!H26/'Historical Financials'!H52 -> -0.078701545 | I97: ='Historical Financials'!I26/'Historical Financials'!I52 -> 0.016663054 | J97: ='Historical Financials'!J26/'Historical Financials'!J52 -> 0.068043401
B99: ROIC(%)
B100: EBIT | F100: ='Historical Financials'!F17 -> -15.729 | G100: ='Historical Financials'!G17 -> -56.098 | H100: ='Historical Financials'!H17 -> -64.559 | I100: ='Historical Financials'!I17 -> -12.921 | J100: ='Historical Financials'!J17 -> 63.569
B101: x (1-Tax rate) | F101: =1-('Historical Financials'!F24/'Historical Financials'!F22) -> 0.995671 | G101: =1-('Historical Financials'!G24/'Historical Financials'!G22) -> 0.99704793 | H101: =1-('Historical Financials'!H24/'Historical Financials'!H22) -> 0.984003 | I101: =1-('Historical Financials'!I24/'Historical Financials'!I22) -> 1.0961917 | J101: =1-('Historical Financials'!J24/'Historical Financials'!J22) -> 1.1342248
B102: =NOPAT | F102: =F100*F101 -> -15.660909 | G102: =G100*G101 -> -55.932395 | H102: =H100*H101 -> -63.52625 | I102: =I100*I101 -> -14.163893 | J102: =J100*J101 -> 72.101535
B104: Invested Capital
B105: Total Equity | F105: ='Historical Financials'!F73 -> 101.917 | G105: ='Historical Financials'!G73 -> 513.052 | H105: ='Historical Financials'!H73 -> 542.074 | I105: ='Historical Financials'!I73 -> 655.497 | J105: ='Historical Financials'!J73 -> 824.546
B106: +Total Debt | F106: =0 -> 0 | G106: =0 -> 0 | H106: =0 -> 0 | I106: =0 -> 0 | J106: =0 -> 0
B107: -Excess Cash | F107: =-'Historical Financials'!F37 -> -120.49 | G107: =-'Historical Financials'!G37 -> -553.922 | H107: =-'Historical Financials'!H37 -> -608.18 | I107: =-'Historical Financials'!I37 -> -747.61 | J107: =-'Historical Financials'!J37 -> -877.645
B108: = Invested Capital | F108: =SUM(F105:F107) -> -18.573 | G108: =SUM(G105:G107) -> -40.87 | H108: =SUM(H105:H107) -> -66.106 | I108: =SUM(I105:I107) -> -92.113 | J108: =SUM(J105:J107) -> -53.099
B110: = NOPAT/Invested Capital | F110: =F102/F108 -> 0.84320837 | G110: =G102/G108 -> 1.368544 | H110: =H102/H108 -> 0.96097555 | I110: =I102/I108 -> 0.15376649 | J110: =J102/J108 -> -1.3578699

Sheet Master Assumptions
B2: MASTER ASSUMPTIONS
B3: Duolingo, Inc. (DUOL) | Scenario-Driven Forecast Assumptions
B5: SCENARIO SELECTOR
B6: Active Scenario: | C6: Bull
B7: Scenario Code: | C7: =IF(C6="Bull",1,IF(C6="Base",2,3)) -> 1 | D7: (1=Bull, 2=Base, 3=Bear)
B9: ACTIVE ASSUMPTIONS | F9: 2025E | G9: 2026E | H9: 2027E | I9: 2028E | J9: 2029E
B10: REVENUE & MARGINS
B11: Revenue Growth % | F11: =CHOOSE($C$7,'Supporting Schedules'!C9,'Supporting Schedules'!C11,'Supporting Schedules'!C13) -> 0.35 | G11: =CHOOSE($C$7,'Supporting Schedules'!D9,'Supporting Schedules'!D11,'Supporting Schedules'!D13) -> 0.3 | H11: =CHOOSE($C$7,'Supporting Schedules'!E9,'Supporting Schedules'!E11,'Supporting Schedules'!E13) -> 0.27 | I11: =CHOOSE($C$7,'Supporting Schedules'!F9,'Supporting Schedules'!F11,'Supporting Schedules'!F13) -> 0.24 | J11: =CHOOSE($C$7,'Supporting Schedules'!G9,'Supporting Schedules'!G11,'Supporting Schedules'!G13) -> 0.22
B12: Gross Margin % | F12: =CHOOSE($C$7,'Supporting Schedules'!C52,'Supporting Schedules'!C54,'Supporting Schedules'!C56) -> 0.745 | G12: =CHOOSE($C$7,'Supporting Schedules'!D52,'Supporting Schedules'!D54,'Supporting Schedules'!D56) -> 0.75 | H12: =CHOOSE($C$7,'Supporting Schedules'!E52,'Supporting Schedules'!E54,'Supporting Schedules'!E56) -> 0.755 | I12: =CHOOSE($C$7,'Supporting Schedules'!F52,'Supporting Schedules'!F54,'Supporting Schedules'!F56) -> 0.758 | J12: =CHOOSE($C$7,'Supporting Schedules'!G52,'Supporting Schedules'!G54,'Supporting Schedules'!G56) -> 0.76
B14: OPERATING EXPENSES (% of Revenue)
B15: R&D % | F15: =CHOOSE($C$7,'Supporting Schedules'!C67,'Supporting Schedules'!C69,'Supporting Schedules'!C71) -> 0.30140712 | G15: =CHOOSE($C$7,'Supporting Schedules'!D67,'Supporting Schedules'!D69,'Supporting Schedules'!D71) -> 0.29140712 | H15: =CHOOSE($C$7,'Supporting Schedules'!E67,'Supporting Schedules'!E69,'Supporting Schedules'!E71) -> 0.28140712 | I15: =CHOOSE($C$7,'Supporting Schedules'!F67,'Supporting Schedules'!F69,'Supporting Schedules'!F71) -> 0.27140712 | J15: =CHOOSE($C$7,'Supporting Schedules'!G67,'Supporting Schedules'!G69,'Supporting Schedules'!G71) -> 0.26140712
B16: SG&A % | F16: =CHOOSE($C$7,'Supporting Schedules'!C79,'Supporting Schedules'!C81,'Supporting Schedules'!C83) -> 0.31895485 | G16: =CHOOSE($C$7,'Supporting Schedules'!D79,'Supporting Schedules'!D81,'Supporting Schedules'!D83) -> 0.31395485 | H16: =CHOOSE($C$7,'Supporting Schedules'!E79,'Supporting Schedules'!E81,'Supporting Schedules'!E83) -> 0.30895485 | I16: =CHOOSE($C$7,'Supporting Schedules'!F79,'Supporting Schedules'!F81,'Supporting Schedules'!F83) -> 0.30395485 | J16: =CHOOSE($C$7,'Supporting Schedules'!G79,'Supporting Schedules'!G81,'Supporting Schedules'!G83) -> 0.29895485
B17: D&A % | F17: ='Supporting Schedules'!C93 -> 0.015 | G17: ='Supporting Schedules'!D93 -> 0.015 | H17: ='Supporting Schedules'!E93 -> 0.015 | I17: ='Supporting Schedules'!F93 -> 0.015 | J17: ='Supporting Schedules'!G93 -> 0.015
B19: TAX & OTHER
B20: Effective Tax Rate % | F20: ='Supporting Schedules'!C107 -> 0.15 | G20: ='Supporting Schedules'!D107 -> 0.17 | H20: ='Supporting Schedules'!E107 -> 0.18 | I20: ='Supporting Schedules'!F107 -> 0.19 | J20: ='Supporting Schedules'!G107 -> 0.2
B22: BALANCE SHEET & CAPEX
B23: DSO (Days) | F23: ='Supporting Schedules'!C122 -> 62.027779 | G23: ='Supporting Schedules'!D122 -> 62.027779 | H23: ='Supporting Schedules'!E122 -> 62.027779 | I23: ='Supporting Schedules'!F122 -> 62.027779 | J23: ='Supporting Schedules'!G122 -> 62.027779
B24: DPO (Days) | F24: ='Supporting Schedules'!C123 -> 11.743086 | G24: ='Supporting Schedules'!D123 -> 11.743086 | H24: ='Supporting Schedules'!E123 -> 11.743086 | I24: ='Supporting Schedules'!F123 -> 11.743086 | J24: ='Supporting Schedules'!G123 -> 11.743086
B25: Other Receivables % of Revenue | F25: ='Supporting Schedules'!C157 -> 0.096827486 | G25: ='Supporting Schedules'!D157 -> 0.096827486 | H25: ='Supporting Schedules'!E157 -> 0.096827486 | I25: ='Supporting Schedules'!F157 -> 0.096827486 | J25: ='Supporting Schedules'!G157 -> 0.096827486
B26: Other Current Assets % of Revenue | F26: ='Supporting Schedules'!C158 -> 0.021752587 | G26: ='Supporting Schedules'!D158 -> 0.021752587 | H26: ='Supporting Schedules'!E158 -> 0.021752587 | I26: ='Supporting Schedules'!F158 -> 0.021752587 | J26: ='Supporting Schedules'!G158 -> 0.021752587
B27: Income Tax Payable % of Tax Expense | F27: ='Supporting Schedules'!C215 -> 0.47997378 | G27: ='Supporting Schedules'!D215*-1 -> 0.47997378 | H27: ='Supporting Schedules'!E215*-1 -> 0.47997378 | I27: ='Supporting Schedules'!F215*-1 -> 0.47997378 | J27: ='Supporting Schedules'!G215*-1 -> 0.47997378
B28: Other CL % of Revenue | F28: ='Supporting Schedules'!C230 -> 0.54366972 | G28: ='Supporting Schedules'!D230 -> 0.54366972 | H28: ='Supporting Schedules'!E230 -> 0.54366972 | I28: ='Supporting Schedules'!F230 -> 0.54366972 | J28: ='Supporting Schedules'!G230 -> 0.54366972
B29: SBC % of Revenue | F29: ='Supporting Schedules'!$C$247 -> 0.10532728 | G29: ='Supporting Schedules'!$C$247 -> 0.10532728 | H29: ='Supporting Schedules'!$C$247 -> 0.10532728 | I29: ='Supporting Schedules'!$C$247 -> 0.10532728 | J29: ='Supporting Schedules'!$C$247 -> 0.10532728
B31: INTEREST INCOME
B32: Interest Income | F32: 0.045 | G32: 0.045 | H32: 0.045 | I32: 0.045 | J32: 0.045
B34: VALUATION PARAMETERS
B35: Terminal Growth Rate | J35: 0.025

Sheet Supporting Schedules
B2: SUPPORTING SCHEDULES
B3: Duolingo, Inc. (DUOL)
B5: REVENUE SCHEDULE
B7: Scenario Assumptions — Revenue Growth Rates
C8: 2025E | D8: 2026E | E8: 2027E | F8: 2028E | G8: 2029E | H8: Avg | I8: Logic
B9: Bull Case | C9: 0.35 | D9: 0.3 | E9: 0.27 | F9: 0.24 | G9: 0.22 | H9: =AVERAGE(C9:G9) -> 0.276 | I9: ~5 ppt/yr decel
B10: Deceleration (ppt) | C10: =C9-$G$19 -> -0.058397665 | D10: =D9-C9 -> -0.05 | E10: =E9-D9 -> -0.03 | F10: =F9-E9 -> -0.03 | G10: =G9-F9 -> -0.02 | H10: =AVERAGE(D10:G10) -> -0.0325
B11: Base Case | C11: 0.28 | D11: 0.24 | E11: 0.21 | F11: 0.18 | G11: 0.16 | H11: =AVERAGE(C11:G11) -> 0.214 | I11: ~6-7 ppt/yr decel
B12: Deceleration (ppt) | C12: =C11-$G$19 -> -0.12839767 | D12: =D11-C11 -> -0.04 | E12: =E11-D11 -> -0.03 | F12: =F11-E11 -> -0.03 | G12: =G11-F11 -> -0.02 | H12: =AVERAGE(D12:G12) -> -0.03
B13: Bear Case | C13: 0.2 | D13: 0.17 | E13: 0.14 | F13: 0.12 | G13: 0.1 | H13: =AVERAGE(C13:G13) -> 0.146 | I13: ~8-10 ppt/yr decel
B14: Deceleration (ppt) | C14: =C13-$G$19 -> -0.20839767 | D14: =D13-C13 -> -0.03 | E14: =E13-D13 -> -0.03 | F14: =F13-E13 -> -0.02 | G14: =G13-F13 -> -0.02 | H14: =AVERAGE(D14:G14) -> -0.025
B16: Historical Analysis
C17: 2020A | D17: 2021A | E17: 2022A | F17: 2023A | G17: 2024A | H17: 5Y CAGR
B18: Revenue ($M) | C18: 161.7 | D18: 250.8 | E18: 369.5 | F18: 531.1 | G18: 748 | H18: =(G18/C18)^(1/4)-1 -> 0.46655345
B19: YoY Growth % | D19: =(D18-C18)/C18 -> 0.55102041 | E19: =(E18-D18)/D18 -> 0.47328549 | F19: =(F18-E18)/E18 -> 0.43734777 | G19: =(G18-F18)/F18 -> 0.40839767
B20: Growth Deceleration (ppt) | E20: =E19-D19 -> -0.077734922 | F20: =F19-E19 -> -0.035937719 | G20: =G19-F19 -> -0.028950102 | H20: =AVERAGE(E20:G20) -> -0.047540914 | I20: avg
B21: Observation: Revenue growth decelerating ~5-8 ppt/year from 55% to 41%. Classic high-growth SaaS deceleration pattern as base grows.
B23: Driver-Based Revenue Build-Up
B24: Revenue = MAU × Paid Conversion % × ARPPU
C26: 2020A | D26: 2021A | E26: 2022A | F26: 2023A | G26: 2024A | H26: 4Y CAGR | I26: Trend
B27: MAU (M) | C27: 37 | D27: 42 | E27: 60 | F27: 88 | G27: 117 | H27: =(G27/C27)^(1/4)-1 -> 0.33350926 | I27: Slowing (33%→33%)
B28: YoY Growth % | D28: =(D27-C27)/C27 -> 0.13513514 | E28: =(E27-D27)/D27 -> 0.42857143 | F28: =(F27-E27)/E27 -> 0.46666667 | G28: =(G27-F27)/F27 -> 0.32954545
B29: DAU (M) | C29: 9 | D29: 11 | E29: 16 | F29: 27 | G29: 37 | H29: =(G29/C29)^(1/4)-1 -> 0.42393382 | I29: Faster than MAU
B30: DAU/MAU Ratio | C30: =C29/C27 -> 0.24324324 | D30: =D29/D27 -> 0.26190476 | E30: =E29/E27 -> 0.26666667 | F30: =F29/F27 -> 0.30681818 | G30: =G29/G27 -> 0.31623932 | H30: =G30-C30 -> 0.072996073 | I30: Improving engagement
B31: Paid Subscribers (M) | C31: 1.8 | D31: 2.9 | E31: 4.8 | F31: 7.6 | G31: 12.1 | H31: =(G31/C31)^(1/4)-1 -> 0.61019405 | I31: Strong sub growth
B32: Paid Conversion % | C32: =C31/C27 -> 0.048648649 | D32: =D31/D27 -> 0.069047619 | E32: =E31/E27 -> 0.08 | F32: =F31/F27 -> 0.086363636 | G32: =G31/G27 -> 0.1034188 | H32: =G32-C32 -> 0.054770155 | I32: Key driver: conversion ↑
B33: ARPPU ($/yr) | C33: =C18/C31 -> 89.833333 | D33: =D18/D31 -> 86.482759 | E33: =E18/E31 -> 76.979167 | F33: =F18/F31 -> 69.881579 | G33: =G18/G31 -> 61.818182 | H33: =(G33/C33)^(1/4)-1 -> -0.089207012 | I33: Declining (mix shift)
B35: Key Insight: Revenue growth driven by MAU growth + conversion improvement, partially offset by ARPPU decline (international mix shift).
B37: Scenario Rationale
B39: Bull Case (27.6% avg growth) | E39: Base Case (21.4% avg growth) | H39: Bear Case (14.6% avg growth)
B40: • Duolingo Max (AI tier) drives 2-3 ppt conversion uplift annually | E40: • Continues historical deceleration | H40: • Competitive pressure from free alternatives (ChatGPT, YouTube)
B41: • New verticals (Math, Music) expand TAM by 20-30% | E41: • Paid subscriber growth moderates | H41: • Macro headwinds reduce discretionary ed-tech spend
B42: • International expansion in Asia-Pacific accelerates MAU growth | E42: • ARPPU stable as geographic mix stabilizes | H42: • Conversion rate plateaus as casual users dominate growth
B43: • Gamification moat sustains engagement vs competitors | H43: • New verticals underperform vs core language learning
B45: Key Sensitivity: Each 1 ppt change in growth rate = ~$15M revenue impact in Year 1, compounding to ~$100M by Year 5
B48: GROSS MARGIN ASSUMPTIONS
B50: Scenario Assumptions — Gross Margin
C51: 2025E | D51: 2026E | E51: 2027E | F51: 2028E | G51: 2029E | H51: Avg | I51: Logic
B52: Bull Case | C52: 0.745 | D52: 0.75 | E52: 0.755 | F52: 0.758 | G52: 0.76 | H52: =AVERAGE(C52:G52) -> 0.7536 | I52: Scale leverage on AI/hosting
D53: =D52-C52 -> 0.005 | E53: =E52-D52 -> 0.005 | F53: =F52-E52 -> 0.003 | G53: =G52-F52 -> 0.002 | H53: =AVERAGE(D53:G53) -> 0.00375 | I53: ~50bps/yr expansion
B54: Base Case | C54: 0.738 | D54: 0.74 | E54: 0.742 | F54: 0.744 | G54: 0.745 | H54: =AVERAGE(C54:G54) -> 0.7418 | I54: Flat w/ slight improvement
D55: =D54-C54 -> 0.002 | E55: =E54-D54 -> 0.002 | F55: =F54-E54 -> 0.002 | G55: =G54-F54 -> 0.001 | H55: =AVERAGE(D55:G55) -> 0.00175 | I55: ~20bps/yr expansion
B56: Bear Case | C56: 0.73 | D56: 0.725 | E56: 0.72 | F56: 0.715 | G56: 0.71 | H56: =AVERAGE(C56:G56) -> 0.72 | I56: AI costs + new verticals
D57: =D56-C56 -> -0.005 | E57: =E56-D56 -> -0.005 | F57: =F56-E56 -> -0.005 | G57: =G56-F56 -> -0.005 | H57: =AVERAGE(D57:G57) -> -0.005 | I57: ~50bps/yr compression
B58: Historical Analysis
C59: 2020A | D59: 2021A | E59: 2022A | F59: 2023A | G59: 2024A
B60: Gross Proft($M) | C60: 117.419 | D60: 183.619 | E60: 270.934 | F60: 391.024 | G60: 549.689
B61: Gross Margin% | C61: 0.72617133 | D61: 0.73221492 | E61: 0.73325485 | F61: 0.73624058 | G61: 0.73485476
B63: OPERATING EXPENSES ASSUMPTIONS
B65: Scenario Assumptions — R&D % of Revenue
C66: 2025E | D66: 2026E | E66: 2027E | F66: 2028E | G66: 2029E | H66: Avg | I66: Logic
B67: Bull Case | C67: =G75-1% -> 0.30140712 | D67: =C67-1% -> 0.29140712 | E67: =D67-1% -> 0.28140712 | F67: =E67-1% -> 0.27140712 | G67: =F67-1% -> 0.26140712 | H67: =AVERAGE(C67:G67) -> 0.28140712 | I67: Strong leverage on eng costs
D68: =D67-C67 -> -0.01 | E68: =E67-D67 -> -0.01 | F68: =F67-E67 -> -0.01 | G68: =G67-F67 -> -0.01 | I68: ~100bps/yr decline
B69: Base Case | C69: =G75-0.5% -> 0.30640712 | D69: =C69-0.5% -> 0.30140712 | E69: =D69-0.5% -> 0.29640712 | F69: =E69-0.5% -> 0.29140712 | G69: =F69-0.5% -> 0.28640712 | H69: =AVERAGE(C69:G69) -> 0.29640712 | I69: Moderate leverage
D70: =D69-C69 -> -0.005 | E70: =E69-D69 -> -0.005 | F70: =F69-E69 -> -0.005 | G70: =G69-F69 -> -0.005 | I70: ~50bps/yr decline
B71: Bear Case | C71: =33% -> 0.33 | D71: =C71 -> 0.33 | E71: =D71 -> 0.33 | F71: =E71 -> 0.33 | G71: =F71 -> 0.33 | H71: =AVERAGE(C71:G71) -> 0.33 | I71: Higher Historical Cyclicality
D72: =D71-C71 -> 0 | E72: =E71-D71 -> 0 | F72: =F71-E71 -> 0 | G72: =G71-F71 -> 0
B73: Historical Analysis
C74: 2020A | D74: 2021A | E74: 2022A | F74: 2023A | G74: 2024A | H74: Avg
B75: R&D % of Revenue | C75: 0.32792401 | D75: 0.41386997 | E75: 0.40310153 | F75: 0.36282948 | G75: 0.31140712 | H75: =AVERAGE(C75:G75) -> 0.36382642
B77: Scenario Assumptions — SG&A % of Revenue
C78: 2025E | D78: 2026E | E78: 2027E | F78: 2028E | G78: 2029E | H78: Avg | I78: Logic
B79: Bull Case | C79: =G88-0.5% -> 0.31895485 | D79: =C79-0.5% -> 0.31395485 | E79: =D79-0.5% -> 0.30895485 | F79: =E79-0.5% -> 0.30395485 | G79: =F79-0.5% -> 0.29895485 | H79: =AVERAGE(C79:G79) -> 0.30895485 | I79: Marketing efficiency at scale
D80: =D79-C79 -> -0.005 | E80: =E79-D79 -> -0.005 | F80: =F79-E79 -> -0.005 | G80: =G79-F79 -> -0.005 | H80: =AVERAGE(D80:G80) -> -0.005 | I80: ~50bps/yr decline
B81: Base Case | C81: =$G$88 -> 0.32395485 | D81: =$G$88 -> 0.32395485 | E81: =$G$88 -> 0.32395485 | F81: =$G$88 -> 0.32395485 | G81: =$G$88 -> 0.32395485 | H81: =AVERAGE(C81:G81) -> 0.32395485 | I81: Can maintain current mix
D82: =D81-C81 -> 0 | E82: =E81-D81 -> 0 | F82: =F81-E81 -> 0 | G82: =G81-F81 -> 0 | H82: =AVERAGE(D82:G82) -> 0
B83: Bear Case | C83: =35% -> 0.35 | D83: =35% -> 0.35 | E83: =35% -> 0.35 | F83: =35% -> 0.35 | G83: =35% -> 0.35 | H83: =AVERAGE(C83:G83) -> 0.35 | I83: Higher Historical average
D84: =D83-C83 -> 0 | E84: =E83-D83 -> 0 | F84: =F83-E83 -> 0 | G84: =G83-F83 -> 0 | H84: =AVERAGE(D84:G84) -> 0
B86: Historical Analysis
C87: 2020A | D87: 2021A | E87: 2022A | F87: 2023A | G87: 2024A | H87: Avg
B88: SG&A % of Revenue | C88: 0.48157035 | D88: 0.53117573 | E88: 0.49169542 | F88: 0.38438061 | G88: 0.32395485 | H88: =AVERAGE(C88:G88) -> 0.44255539
B91: Scenario Assumptions — D&A % of Revenue
C92: 2025E | D92: 2026E | E92: 2027E | F92: 2028E | G92: 2029E | H92: Avg | I92: Logic
B93: All Scenarios | C93: 0.015 | D93: 0.015 | E93: 0.015 | F93: 0.015 | G93: 0.015 | H93: =AVERAGE(C93:G93) -> 0.015 | I93: Follows CapEx policy
B94: Note: D&A is constant across scenarios as it follows CapEx policy, not revenue scenario
B96: Historical Analysis
C97: 2020A | D97: 2021A | E97: 2022A | F97: 2023A | G97: 2024A
B98: D&A % of Revenue | C98: 0.013952108 | D98: 0.010870432 | E98: 0.013180151 | F98: 0.01335884 | G98: 0.01451023
B100: TAX SCHEDULE
B102: (Constant across all scenarios - tax policy driven)
B103: Historical Context
B104: 2023A ETR: 9.6% | 2024A ETR: 13.4% | US Statutory: 21%
B106: Year | C106: 2025E | D106: 2026E | E106: 2027E | F106: 2028E | G106: 2029E | H106: Avg | I106: Rationale / Logic
B107: Effective Tax Rate | C107: 0.15 | D107: 0.17 | E107: 0.18 | F107: 0.19 | G107: 0.2 | H107: =AVERAGE(C107:G107) -> 0.178 | I107: NOL phase-out; R&D credits persist
B109: Year-over-Year Change | D109: =D107-C107 -> 0.02 | E109: =E107-D107 -> 0.01 | F109: =F107-E107 -> 0.01 | G109: =G107-F107 -> 0.01
B111: Key Assumptions:
B112: • NOL carryforwards from 2020-2022 losses provide near-term benefit
B113: • R&D tax credits (~3-4% benefit) expected to persist through forecast
B116: WORKING CAPITAL SCHEDULE
B119: Scenario Assumptions - DSO, DIO, DPO
B120: Assuming they remain same for all scenarios
C121: 2025E | D121: 2026E | E121: 2027E | F121: 2028E | G121: 2029E
B122: DSO | C122: =H134 -> 62.027779 | D122: =I134 -> 62.027779 | E122: =J134 -> 62.027779 | F122: =K134 -> 62.027779 | G122: =L134 -> 62.027779
B123: DPO | C123: =H142 -> 11.743086 | D123: =I142 -> 11.743086 | E123: =J142 -> 11.743086 | F123: =K142 -> 11.743086 | G123: =L142 -> 11.743086
B125: WC Schedule
C126: 2020A | D126: 2021A | E126: 2022A | F126: 2023A | G126: 2024A | H126: 2025E | I126: 2026E | J126: 2027E | K126: 2028E | L126: 2029E
B127: Days in Period | C127: 365 | D127: 365 | E127: 365 | F127: 365 | G127: 365 | H127: 365 | I127: 365 | J127: 365 | K127: 365 | L127: 365
B129: Accounts Receivables:
B131: Receivables | C131: ='Historical Financials'!F38 -> 20.45 | D131: ='Historical Financials'!G38 -> 33.163 | E131: ='Historical Financials'!H38 -> 46.728 | F131: ='Historical Financials'!I38 -> 88.975 | G131: ='Historical Financials'!J38 -> 128.923 | H131: =H134*H133 -> 171.61003 | I131: =I134*I133 -> 223.09304 | J131: =J134*J133 -> 283.32816 | K131: =K134*K133 -> 351.32691 | L131: =L134*L133 -> 428.61884
B132: Revenue | C132: ='Historical Financials'!F10 -> 161.696 | D132: ='Historical Financials'!G10 -> 250.772 | E132: ='Historical Financials'!H10 -> 369.495 | F132: ='Historical Financials'!I10 -> 531.109 | G132: ='Historical Financials'!J10 -> 748.024 | H132: ='Forecast Model'!H8 -> 1009.8324 | I132: ='Forecast Model'!I8 -> 1312.7821 | J132: ='Forecast Model'!J8 -> 1667.2333 | K132: ='Forecast Model'!K8 -> 2067.3693 | L132: ='Forecast Model'!L8 -> 2522.1905
...

Sheet Forecast Model
B3: INCOME STATEMENT
B5: All figures in millions of euros | E5: 2022A | F5: 2023A | G5: 2024A | H5: 2025E | I5: 2026E | J5: 2027E | K5: 2028E | L5: 2029E
B6: unless stated otherwise
B8: Revenue | E8: 369.495 | F8: 531.109 | G8: 748.024 | H8: =G8*(1+'Master Assumptions'!F11) -> 1009.8324 | I8: =H8*(1+'Master Assumptions'!G11) -> 1312.7821 | J8: =I8*(1+'Master Assumptions'!H11) -> 1667.2333 | K8: =J8*(1+'Master Assumptions'!I11) -> 2067.3693 | L8: =K8*(1+'Master Assumptions'!J11) -> 2522.1905
B9: COGS (excl. D&A) | E9: -98.561 | F9: -140.085 | G9: -198.335 | H9: =H10-H8 -> -257.50726 | I9: =I10-I8 -> -328.19553 | J9: =J10-J8 -> -408.47216 | K9: =K10-K8 -> -500.30337 | L9: =L10-L8 -> -605.32573
B10: Gross Profit (excl. D&A) | E10: =SUM(E8:E9) -> 270.934 | F10: =SUM(F8:F9) -> 391.024 | G10: =SUM(G8:G9) -> 549.689 | H10: =H8*'Master Assumptions'!F12 -> 752.32514 | I10: =I8*'Master Assumptions'!G12 -> 984.58659 | J10: =J8*'Master Assumptions'!H12 -> 1258.7611 | K10: =K8*'Master Assumptions'!I12 -> 1567.0659 | L10: =L8*'Master Assumptions'!J12 -> 1916.8648
B12: R&D Expense | E12: -148.944 | F12: -192.702 | G12: -232.94 | H12: =-H8*'Master Assumptions'!F15 -> -304.37068 | I12: =-I8*'Master Assumptions'!G15 -> -382.55406 | J12: =-J8*'Master Assumptions'!H15 -> -469.17132 | K12: =-K8*'Master Assumptions'!I15 -> -561.09874 | L12: =-L8*'Master Assumptions'!J15 -> -659.31856
B13: SG&A Expense | E13: -181.679 | F13: -204.148 | G13: -242.326 | H13: =-H8*'Master Assumptions'!F16 -> -322.09094 | I13: =-I8*'Master Assumptions'!G16 -> -412.15431 | J13: =-J8*'Master Assumptions'!H16 -> -515.09981 | K13: =-K8*'Master Assumptions'!I16 -> -628.38691 | L13: =-L8*'Master Assumptions'!J16 -> -754.02108
B14: D&A Expense | E14: -4.87 | F14: -7.095 | G14: -10.854 | H14: =-H8*'Master Assumptions'!F17 -> -15.147486 | I14: =-I8*'Master Assumptions'!G17 -> -19.691732 | J14: =-J8*'Master Assumptions'!H17 -> -25.008499 | K14: =-K8*'Master Assumptions'!I17 -> -31.010539 | L14: =-L8*'Master Assumptions'!J17 -> -37.832858
B15: EBIT | E15: =SUM(E10:E14) -> -64.559 | F15: =SUM(F10:F14) -> -12.921 | G15: =SUM(G10:G14) -> 63.569 | H15: =SUM(H10:H14) -> 110.71604 | I15: =SUM(I10:I14) -> 170.18649 | J15: =SUM(J10:J14) -> 249.48151 | K15: =SUM(K10:K14) -> 346.56972 | L15: =SUM(L10:L14) -> 465.6923
B17: Interest Income | E17: 7.235 | F17: 31.091 | G17: 42.697 | H17: ='Supporting Schedules'!C275 -> 39.494025 | I17: ='Supporting Schedules'!D275 -> 53.840805 | J17: ='Supporting Schedules'!E275 -> 72.368858 | K17: ='Supporting Schedules'!F275 -> 96.602102 | L17: ='Supporting Schedules'!G275 -> 127.49171
B18: Unusual Expense | E18: -0.636 | F18: -0.338 | G18: -0.974 | H18: =AVERAGE(E18:G18) -> -0.64933333 | I18: =AVERAGE(F18:H18) -> -0.65377778 | J18: =AVERAGE(G18:I18) -> -0.75903704 | K18: =AVERAGE(H18:J18) -> -0.68738272 | L18: =AVERAGE(I18:K18) -> -0.70006584
B19: Other Income | E19: -0.676 | F19: -0.055 | G19: -2.986 | H19: =AVERAGE(E19:G19) -> -1.239 | I19: =H19 -> -1.239 | J19: =I19 -> -1.239 | K19: =J19 -> -1.239 | L19: =K19 -> -1.239
B20: EBT | E20: =SUM(E15:E19) -> -58.636 | F20: =SUM(F15:F19) -> 17.777 | G20: =SUM(G15:G19) -> 102.306 | H20: =SUM(H15:H19) -> 148.32173 | I20: =SUM(I15:I19) -> 222.13452 | J20: =SUM(J15:J19) -> 319.85233 | K20: =SUM(K15:K19) -> 441.24544 | L20: =SUM(L15:L19) -> 591.24494
B22: Income Taxes | E22: -0.938 | F22: -1.71 | G22: -13.732 | H22: =-H20*'Master Assumptions'!F20 -> -22.248259 | I22: =-I20*'Master Assumptions'!G20 -> -37.762868 | J22: =-J20*'Master Assumptions'!H20 -> -57.57342 | K22: =-K20*'Master Assumptions'!I20 -> -83.836634 | L22: =-L20*'Master Assumptions'!J20 -> -118.24899
B23: Equity in Affiliates | E23: 0 | F23: 0 | G23: 0 | H23: =G23 -> 0 | I23: =H23 -> 0 | J23: =I23 -> 0 | K23: =J23 -> 0 | L23: =K23 -> 0
B24: Net Income | E24: =SUM(E20:E23) -> -59.574 | F24: =SUM(F20:F23) -> 16.067 | G24: =SUM(G20:G23) -> 88.574 | H24: =SUM(H20:H23) -> 126.07347 | I24: =SUM(I20:I23) -> 184.37165 | J24: =SUM(J20:J23) -> 262.27891 | K24: =SUM(K20:K23) -> 357.40881 | L24: =SUM(L20:L23) -> 472.99595
B28: BALANCE SHEET
B30: All figures in millions of euros | E30: 2022A | F30: 2023A | G30: 2024A | H30: 2025E | I30: 2026E | J30: 2027E | K30: 2028E | L30: 2029E
B31: unless stated otherwise
B33: Assets
B34: Cash & Short-Term Investments | E34: 608.18 | F34: 747.61 | G34: 877.645 | H34: =G34+H110 -> 1196.4623 | I34: =H34+I110 -> 1608.1969 | J34: =I34+J110 -> 2146.7134 | K34: =J34+K110 -> 2833.1491 | L34: =K34+L110 -> 3696.272
B35: Accounts Receivable | E35: 46.728 | F35: 88.975 | G35: 128.923 | H35: ='Supporting Schedules'!H131 -> 171.61003 | I35: ='Supporting Schedules'!I131 -> 223.09304 | J35: ='Supporting Schedules'!J131 -> 283.32816 | K35: ='Supporting Schedules'!K131 -> 351.32691 | L35: ='Supporting Schedules'!L131 -> 428.61884
B36: Other Receivables | E36: 35.041 | F36: 53.931 | G36: 80.162 | H36: ='Master Assumptions'!F25*'Forecast Model'!H8 -> 97.779533 | I36: ='Master Assumptions'!G25*'Forecast Model'!I8 -> 127.11339 | J36: ='Master Assumptions'!H25*'Forecast Model'!J8 -> 161.43401 | K36: ='Master Assumptions'!I25*'Forecast Model'!K8 -> 200.17817 | L36: ='Master Assumptions'!J25*'Forecast Model'!L8 -> 244.21737
B37: Inventories | E37: 0 | F37: 0 | G37: 0 | H37: =G37 -> 0 | I37: =H37 -> 0 | J37: =I37 -> 0 | K37: =J37 -> 0 | L37: =K37 -> 0
B38: Other Current Assets | E38: 7.234 | F38: 7.282 | G38: 14.858 | H38: ='Master Assumptions'!F26*'Forecast Model'!H8 -> 21.966467 | I38: ='Master Assumptions'!G26*'Forecast Model'!I8 -> 28.556407 | J38: ='Master Assumptions'!H26*'Forecast Model'!J8 -> 36.266637 | K38: ='Master Assumptions'!I26*'Forecast Model'!K8 -> 44.97063 | L38: ='Master Assumptions'!J26*'Forecast Model'!L8 -> 54.864169
B39: Total Current Assets | E39: =SUM(E34:E38) -> 697.183 | F39: =SUM(F34:F38) -> 897.798 | G39: =SUM(G34:G38) -> 1101.588 | H39: =SUM(H34:H38) -> 1487.8184 | I39: =SUM(I34:I38) -> 1986.9597 | J39: =SUM(J34:J38) -> 2627.7422 | K39: =SUM(K34:K38) -> 3429.6248 | L39: =SUM(L34:L38) -> 4423.9723
B41: Net PP&E | E41: 35.477 | F41: 30.895 | G41: 66.438 | H41: ='Supporting Schedules'!D188 -> 77.747634 | I41: ='Supporting Schedules'!E188 -> 92.450159 | J41: ='Supporting Schedules'!F188 -> 111.12237 | K41: ='Supporting Schedules'!G188 -> 134.2759 | L41: ='Supporting Schedules'!H188 -> 162.52322
B42: Goodwill | E42: 4.05 | F42: 4.05 | G42: 10.538 | H42: =G42 -> 10.538 | I42: =H42 -> 10.538 | J42: =I42 -> 10.538 | K42: =J42 -> 10.538 | L42: =K42 -> 10.538
B43: Other Intangible Assets | E43: 8.497 | F43: 15.995 | G43: 19.899 | H43: =G43 -> 19.899 | I43: =H43 -> 19.899 | J43: =I43 -> 19.899 | K43: =J43 -> 19.899 | L43: =K43 -> 19.899
B44: Long-Term Investments | E44: 0 | F44: 2.735 | G44: 101.027 | H44: =G44 -> 101.027 | I44: =H44 -> 101.027 | J44: =I44 -> 101.027 | K44: =J44 -> 101.027 | L44: =K44 -> 101.027
B45: Deferred Tax Assets | E45: 10.247 | F45: 11.038 | G45: 0.675 | H45: =G45 -> 0.675 | I45: =H45 -> 0.675 | J45: =I45 -> 0.675 | K45: =J45 -> 0.675 | L45: =K45 -> 0.675
B46: Other Non-Current Assets | E46: 1.507 | F46: 1.718 | G46: 1.563 | H46: =G46 -> 1.563 | I46: =H46 -> 1.563 | J46: =I46 -> 1.563 | K46: =J46 -> 1.563 | L46: =K46 -> 1.563
B47: Total Non-Current Assets | E47: =SUM(E41:E46) -> 59.778 | F47: =SUM(F41:F46) -> 66.431 | G47: =SUM(G41:G46) -> 200.14 | H47: =SUM(H41:H46) -> 211.44963 | I47: =SUM(I41:I46) -> 226.15216 | J47: =SUM(J41:J46) -> 244.82437 | K47: =SUM(K41:K46) -> 267.9779 | L47: =SUM(L41:L46) -> 296.22522
B49: Total Assets | E49: =E39+E47 -> 756.961 | F49: =F39+F47 -> 964.229 | G49: =G39+G47 -> 1301.728 | H49: =H47+H39 -> 1699.268 | I49: =I47+I39 -> 2213.1119 | J49: =J47+J39 -> 2872.5666 | K49: =K47+K39 -> 3697.6027 | L49: =L47+L39 -> 4720.1975
B51: Liabilities
B52: Accounts Payable | E52: 1.177 | F52: 2.447 | G52: 6.381 | H52: ='Supporting Schedules'!H139 -> 8.2847397 | I52: ='Supporting Schedules'!I139 -> 10.558982 | J52: ='Supporting Schedules'!J139 -> 13.141709 | K52: ='Supporting Schedules'!K139 -> 16.09618 | L52: ='Supporting Schedules'!L139 -> 19.475047
B53: Short-Term Debt & Curr. LT Portion | E53: 4.903 | F53: 3.944 | G53: 2.581 | H53: ='Supporting Schedules'!D203 -> 2.581 | I53: ='Supporting Schedules'!E203 -> 2.581 | J53: ='Supporting Schedules'!F203 -> 2.581 | K53: ='Supporting Schedules'!G203 -> 2.581 | L53: ='Supporting Schedules'!H203 -> 2.581
B54: Income Tax Payable | E54: 1.069 | F54: 0.792 | G54: 6.591 | H54: ='Master Assumptions'!F27*'Forecast Model'!H22*-1 -> 10.678581 | I54: ='Master Assumptions'!G27*'Forecast Model'!I22*-1 -> 18.125187 | J54: ='Master Assumptions'!H27*'Forecast Model'!J22*-1 -> 27.633732 | K54: ='Master Assumptions'!I27*'Forecast Model'!K22*-1 -> 40.239386 | L54: ='Master Assumptions'!J27*'Forecast Model'!L22*-1 -> 56.756414
B55: Other Current Liabilities | E55: 174.617 | F55: 270.179 | G55: 406.678 | H55: ='Master Assumptions'!F28*'Forecast Model'!H8 -> 549.0153 | I55: ='Master Assumptions'!G28*'Forecast Model'!I8 -> 713.71989 | J55: ='Master Assumptions'!H28*'Forecast Model'!J8 -> 906.42426 | K55: ='Master Assumptions'!I28*'Forecast Model'!K8 -> 1123.9661 | L55: ='Master Assumptions'!J28*'Forecast Model'!L8 -> 1371.2386
B56: Total Current Liabilities | E56: =SUM(E52:E55) -> 181.766 | F56: =SUM(F52:F55) -> 277.362 | G56: =SUM(G52:G55) -> 422.231 | H56: =SUM(H52:H55) -> 570.55962 | I56: =SUM(I52:I55) -> 744.98506 | J56: =SUM(J52:J55) -> 949.7807 | K56: =SUM(K52:K55) -> 1182.8826 | L56: =SUM(L52:L55) -> 1450.0511
B58: Long-Term Debt | E58: 23.503 | F58: 21.094 | G58: 54.656 | H58: ='Supporting Schedules'!D208 -> 52.075 | I58: ='Supporting Schedules'!E208 -> 49.494 | J58: ='Supporting Schedules'!F208 -> 46.913 | K58: ='Supporting Schedules'!G208 -> 44.332 | L58: ='Supporting Schedules'!H208 -> 41.751
B59: Deferred Tax Liabilities | E59: 9.614 | F59: 10.272 | G59: 0.291 | H59: =G59 -> 0.291 | I59: =H59 -> 0.291 | J59: =I59 -> 0.291 | K59: =J59 -> 0.291 | L59: =K59 -> 0.291
B60: Other Non-Current Liabilities | E60: 0 | F60: 0 | G60: 0 | H60: =G60 -> 0 | I60: =H60 -> 0 | J60: =I60 -> 0 | K60: =J60 -> 0 | L60: =K60 -> 0
B61: Total Non-Current Liabilities | E61: =SUM(E58:E60) -> 33.117 | F61: =SUM(F58:F60) -> 31.366 | G61: =SUM(G58:G60) -> 54.947 | H61: =SUM(H58:H60) -> 52.366 | I61: =SUM(I58:I60) -> 49.785 | J61: =SUM(J58:J60) -> 47.204 | K61: =SUM(K58:K60) -> 44.623 | L61: =SUM(L58:L60) -> 42.042
B62: Total Liabilities | E62: =E61+E56 -> 214.883 | F62: =F61+F56 -> 308.728 | G62: =G61+G56 -> 477.178 | H62: =H61+H56 -> 622.92562 | I62: =I61+I56 -> 794.77006 | J62: =J61+J56 -> 996.9847 | K62: =K61+K56 -> 1227.5056 | L62: =L61+L56 -> 1492.0931
B64: Shareholders' Equity
B65: Common Stock & APIC | E65: 772.562 | F65: 869.918 | G65: 950.393 | H65: ='Supporting Schedules'!C257 -> 1076.1119 | I65: ='Supporting Schedules'!D257 -> 1233.7397 | J65: ='Supporting Schedules'!E257 -> 1428.7008 | K65: ='Supporting Schedules'!F257 -> 1665.8072 | L65: ='Supporting Schedules'!G257 -> 1950.8187
B66: Retained Earnings | E66: -230.488 | F66: -214.421 | G66: -125.847 | H66: ='Supporting Schedules'!C266 -> 0.22647022 | I66: ='Supporting Schedules'!D266 -> 184.59812 | J66: ='Supporting Schedules'!E266 -> 446.87703 | K66: ='Supporting Schedules'!F266 -> 804.28584 | L66: ='Supporting Schedules'!G266 -> 1277.2818
B67: Treasury Stock | E67: 0 | F67: 0 | G67: 0 | H67: =G67 -> 0 | I67: =H67 -> 0 | J67: =I67 -> 0 | K67: =J67 -> 0 | L67: =K67 -> 0
B68: Other Comprehensive Income | E68: 0 | F68: 0 | G68: 0 | H68: =G68 -> 0 | I68: =H68 -> 0 | J68: =I68 -> 0 | K68: =J68 -> 0 | L68: =K68 -> 0
B69: Preferred Stock | E69: 0 | F69: 0 | G69: 0 | H69: =G69 -> 0 | I69: =H69 -> 0 | J69: =I69 -> 0 | K69: =J69 -> 0 | L69: =K69 -> 0
B70: Total Shareholders' Equity | E70: =SUM(E65:E69) -> 542.074 | F70: =SUM(F65:F69) -> 655.497 | G70: =SUM(G65:G69) -> 824.546 | H70: =SUM(H65:H69) -> 1076.3384 | I70: =SUM(I65:I69) -> 1418.3378 | J70: =SUM(J65:J69) -> 1875.5779 | K70: =SUM(K65:K69) -> 2470.093 | L70: =SUM(L65:L69) -> 3228.1005
B72: Total Liabilities & Equity | E72: =E62+E70 -> 756.957 | F72: =F62+F70 -> 964.225 | G72: =G62+G70 -> 1301.724 | H72: =H62+H70 -> 1699.264 | I72: =I62+I70 -> 2213.1079 | J72: =J62+J70 -> 2872.5626 | K72: =K62+K70 -> 3697.5987 | L72: =L62+L70 -> 4720.1935
B76: CASH FLOW STATEMENT
B78: All figures in millions of euros | E78: 2022A | F78: 2023A | G78: 2024A | H78: 2025E | I78: 2026E | J78: 2027E | K78: 2028E | L78: 2029E
B79: unless stated otherwise
B81: Operating Activities
B82: Net Income | E82: -59.574 | F82: 16.067 | G82: 88.574 | H82: =H24 -> 126.07347 | I82: =I24 -> 184.37165 | J82: =J24 -> 262.27891 | K82: =K24 -> 357.40881 | L82: =L24 -> 472.99595
B83: D&A | E83: 4.87 | F83: 7.095 | G83: 10.854 | H83: =H14*-1 -> 15.147486 | I83: =I14*-1 -> 19.691732 | J83: =J14*-1 -> 25.008499 | K83: =K14*-1 -> 31.010539 | L83: =L14*-1 -> 37.832858
B84: Deferred Taxes | E84: 0 | F84: 0 | G84: 0 | H84: =G84 -> 0 | I84: =H84 -> 0 | J84: =I84 -> 0 | K84: =J84 -> 0 | L84: =K84 -> 0
B85: Stock-Based Compensation & Other | E85: 73.82 | F85: 95.554 | G85: 110.164 | H85: ='Master Assumptions'!F29*'Forecast Model'!H8 -> 106.3629 | I85: ='Master Assumptions'!G29*'Forecast Model'!I8 -> 138.27177 | J85: ='Master Assumptions'!H29*'Forecast Model'!J8 -> 175.60515 | K85: ='Master Assumptions'!I29*'Forecast Model'!K8 -> 217.75038 | L85: ='Master Assumptions'!J29*'Forecast Model'!L8 -> 265.65547
B86: Changes in Working Capital:
B87: (Increase) / Decrease in Receivables | E87: 45.718 | F87: 49.395 | G87: 83.775 | H87: =G35-H35 -> -42.687029 | I87: =H35-I35 -> -51.483009 | J87: =I35-J35 -> -60.23512 | K87: =J35-K35 -> -67.998758 | L87: =K35-L35 -> -77.291921
B88: (Increase) / Decrease in Inventories | E88: 0 | F88: 0 | G88: 0 | H88: =0 -> 0 | I88: =0 -> 0 | J88: =0 -> 0 | K88: =0 -> 0 | L88: =0 -> 0
B89: Increase / (Decrease) in Accounts Payable | E89: -6.655 | F89: 1.261 | G89: 3.934 | H89: =H52-G52 -> 1.9037397 | I89: =I52-H52 -> 2.2742423 | J89: =J52-I52 -> 2.582727 | K89: =K52-J52 -> 2.9544707 | L89: =L52-K52 -> 3.3788675
B90: Other Working Capital Changes | E90: -13.243 | F90: -19.202 | G90: -28.638 | H90: =-(H36-G36)-(H38-G38)+(H54-G54) -> -20.638419 | I90: =-(I36-H36)-(I38-H38)+(I54-H54) -> -28.477195 | J90: =-(J36-I36)-(J38-I38)+(J54-I54) -> -32.522301 | K90: =-(K36-J36)-(K38-J38)+(K54-J54) -> -34.842501 | L90: =-(L36-K36)-(L38-K38)+(L54-K54) -> -37.415708
B91: Other Accurals | E91: 8.72 | F91: 3.444 | G91: 16.85 | H91: =H55-G55 -> 142.3373 | I91: =I55-H55 -> 164.70459 | J91: =J55-I55 -> 192.70437 | K91: =K55-J55 -> 217.54182 | L91: =L55-K55 -> 247.27254
B92: Cash Flow from Operations | E92: =SUM(E82:E91) -> 53.656 | F92: =SUM(F82:F91) -> 153.614 | G92: =SUM(G82:G91) -> 285.513 | H92: =SUM(H82:H91) -> 328.49945 | I92: =SUM(I82:I91) -> 429.35378 | J92: =SUM(J82:J91) -> 565.42224 | K92: =SUM(K82:K91) -> 723.82476 | L92: =SUM(L82:L91) -> 912.42806
B94: Investing Activities
B95: Capital Expenditures | E95: -10.124 | F95: -13.684 | G95: -21.14 | H95: =-'Supporting Schedules'!D186 -> -26.45712 | I95: =-'Supporting Schedules'!E186 -> -34.394257 | J95: =-'Supporting Schedules'!F186 -> -43.680706 | K95: =-'Supporting Schedules'!G186 -> -54.164075 | L95: =-'Supporting Schedules'!H186 -> -66.080172
B96: Acquisitions | E96: -4.05 | F96: 0 | G96: -6.595 | H96: 0 | I96: 0 | J96: 0 | K96: 0 | L96: 0
B97: Purchase / Sale of Investments | E97: 0 | F97: 0 | G97: -189.595 | H97: 0 | I97: 0 | J97: 0 | K97: 0 | L97: 0
B98: Other Investing Activities | E98: 0 | F98: 0.1 | G98: 0 | H98: =G98 -> 0 | I98: =H98 -> 0 | J98: =I98 -> 0 | K98: =J98 -> 0 | L98: =K98 -> 0
B99: Cash Flow from Investing | E99: =SUM(E95:E98) -> -14.174 | F99: =SUM(F95:F98) -> -13.584 | G99: =SUM(G95:G98) -> -217.33 | H99: =SUM(H95:H98) -> -26.45712 | I99: =SUM(I95:I98) -> -34.394257 | J99: =SUM(J95:J98) -> -43.680706 | K99: =SUM(K95:K98) -> -54.164075 | L99: =SUM(L95:L98) -> -66.080172
B101: Financing Activities
B102: Dividends Paid | E102: 0 | F102: 0 | G102: 0 | H102: =-(G102) -> 0 | I102: =-(H102) -> 0 | J102: =-(I102) -> 0 | K102: =-(J102) -> 0 | L102: =-(K102) -> 0
B103: Share Repurchases | E103: 0 | F103: 0 | G103: 0 | H103: =G103 -> 0 | I103: =H103 -> 0 | J103: =I103 -> 0 | K103: =J103 -> 0 | L103: =K103 -> 0
B104: Stock Issuances | E104: 14.776 | F104: 13.617 | G104: 19.356 | H104: ='Forecast Model'!G104 -> 19.356 | I104: ='Forecast Model'!H104 -> 19.356 | J104: ='Forecast Model'!I104 -> 19.356 | K104: ='Forecast Model'!J104 -> 19.356 | L104: ='Forecast Model'!K104 -> 19.356
B105: Debt Issuance / (Repayment) | E105: 0 | F105: 0 | G105: 0 | H105: =H58-G58 -> -2.581 | I105: =I58-H58 -> -2.581 | J105: =J58-I58 -> -2.581 | K105: =K58-J58 -> -2.581 | L105: =L58-K58 -> -2.581
B106: Others | E106: 0 | F106: -11.482 | G106: -49.358 | H106: 0 | I106: 0 | J106: 0 | K106: 0 | L106: 0
B107: Cash Flow from Financing | E107: =SUM(E102:E106) -> 14.776 | F107: =SUM(F102:F106) -> 2.135 | G107: =SUM(G102:G106) -> -30.002 | H107: =SUM(H102:H106) -> 16.775 | I107: =SUM(I102:I106) -> 16.775 | J107: =SUM(J102:J106) -> 16.775 | K107: =SUM(K102:K106) -> 16.775 | L107: =SUM(L102:L106) -> 16.775
B109: Effect of Exchange Rate | E109: 0 | F109: 0 | G109: 0 | H109: =G109 -> 0 | I109: =H109 -> 0 | J109: =I109 -> 0 | K109: =J109 -> 0 | L109: =K109 -> 0
B110: Net Change in Cash | E110: =E92+E99+E107 -> 54.258 | F110: =F92+F99+F107 -> 142.165 | G110: =G92+G99+G107 -> 38.181 | H110: =H92+H99+H107 -> 318.81733 | I110: =I92+I99+I107 -> 411.73453 | J110: =J92+J99+J107 -> 538.51653 | K110: =K92+K99+K107 -> 686.43569 | L110: =L92+L99+L107 -> 863.12288

Sheet Integration Check
B2: INTEGRATION CHECK
B3: Duolingo, Inc. (DUOL)
B5: STATUS | C5: =IF(COUNTIF(D9:D15,"✗ FAIL")=0,"✓ ALL CHECKS PASSED",COUNTIF(D9:D15,"✗ FAIL")&" CHECK(S) FAILED") -> ✓ ALL CHECKS PASSED
B7: CHECK | C7: DESCRIPTION | D7: STATUS | E7: 2025E | F7: 2026E | G7: 2027E | H7: 2028E | I7: 2028E
B9: Balance Sheet Balances | C9: Assets = Liabilities + Equity | D9: =IF(AND(ABS(E9)<0.01,ABS(F9)<0.01,ABS(G9)<0.01,ABS(H9)<0.01,ABS(I9)<0.01),"✓ OK","✗ FAIL") -> ✓ OK | E9: ='Forecast Model'!H49-'Forecast Model'!H72 -> 0.004 | F9: ='Forecast Model'!I49-'Forecast Model'!I72 -> 0.004 | G9: ='Forecast Model'!J49-'Forecast Model'!J72 -> 0.004 | H9: ='Forecast Model'!K49-'Forecast Model'!K72 -> 0.004 | I9: ='Forecast Model'!L49-'Forecast Model'!L72 -> 0.004
B11: Net Income → Cash Flow | C11: NI (IS) = NI (CF Statement) | D11: =IF(AND(ABS(E11)<0.01,ABS(F11)<0.01,ABS(G11)<0.01,ABS(H11)<0.01,ABS(I11)<0.01),"✓ OK","✗ FAIL") -> ✓ OK
B13: D&A Consistency | C13: D&A (IS) = D&A (CF add-back) | D13: =IF(AND(ABS(E13)<0.01,ABS(F13)<0.01,ABS(G13)<0.01,ABS(H13)<0.01,ABS(I13)<0.01),"✓ OK","✗ FAIL") -> ✓ OK
B15: Cash Flow Foots | C15: CFO + CFI + CFF = Net Δ Cash | D15: =IF(AND(ABS(E15)<0.01,ABS(F15)<0.01,ABS(G15)<0.01,ABS(H15)<0.01,ABS(I15)<0.01),"✓ OK","✗ FAIL") -> ✓ OK
B18: Note: | C18: Differences should be 0.000 (small rounding OK). Non-zero = broken link.

Sheet DCF Valuation
B3: DCF VALUATION
B5: SECTION 1: CAPITAL STRUCTURE
B7: Cost of Equity (CAPM): | H7: Cost of Debt:
B9: Risk-Free Rate (Rf) | E9: 0.0405 | H9: Pre-tax Cost of Debt (Kd) | K9: 0
B10: Equity risk premium (ERP) | E10: 0.0446 | H10: Tax rate | K10: 0
B11: Beta (Levered) | E11: 1.59 | H11: After-Tax Cost of Debt | K11: 0
B12: Cost of Equity(Ke) | E12: =E9+E10*E11 -> 0.111414
B15: Weight of Equity | E15: 1 | H15: Weight of Debt | K15: 0
B18: Weighted Average Cost of Capital | E18: =IF('Sensitivity Analysis'!K8="",E15*E12,'Sensitivity Analysis'!K8) -> 0.111414
B21: SECTION 2: FREE CASH FLOW SCHEDULE
E24: 2025E | F24: 2026E | G24: 2027E | H24: 2028E | I24: 2029E
B26: EBIT | E26: ='Forecast Model'!H15 -> 110.71604 | F26: ='Forecast Model'!I15 -> 170.18649 | G26: ='Forecast Model'!J15 -> 249.48151 | H26: ='Forecast Model'!K15 -> 346.56972 | I26: ='Forecast Model'!L15 -> 465.6923
B27: % Margin | E27: =E26/'Forecast Model'!H8 -> 0.10963803 | F27: =F26/'Forecast Model'!I8 -> 0.12963803 | G27: =G26/'Forecast Model'!J8 -> 0.14963803 | H27: =H26/'Forecast Model'!K8 -> 0.16763803 | I27: =I26/'Forecast Model'!L8 -> 0.18463803
B28: Less: Taxes on EBIT | E28: =-(E26*'Master Assumptions'!F20) -> -16.607406 | F28: =-(F26*'Master Assumptions'!G20) -> -28.931704 | G28: =-(G26*'Master Assumptions'!H20) -> -44.906672 | H28: =-(H26*'Master Assumptions'!I20) -> -65.848247 | I28: =-(I26*'Master Assumptions'!J20) -> -93.138459
B29: NOPAT (EBIT x (1-Tax rate) | E29: =E26+E28 -> 94.108632 | F29: =F26+F28 -> 141.25479 | G29: =G26+G28 -> 204.57484 | H29: =H26+H28 -> 280.72147 | I29: =I26+I28 -> 372.55384
B32: Plus: D&A | E32: =-'Forecast Model'!H14 -> 15.147486 | F32: =-'Forecast Model'!I14 -> 19.691732 | G32: =-'Forecast Model'!J14 -> 25.008499 | H32: =-'Forecast Model'!K14 -> 31.010539 | I32: =-'Forecast Model'!L14 -> 37.832858
B33: Less: CapEx | E33: ='Forecast Model'!H95 -> -26.45712 | F33: ='Forecast Model'!I95 -> -34.394257 | G33: ='Forecast Model'!J95 -> -43.680706 | H33: ='Forecast Model'!K95 -> -54.164075 | I33: ='Forecast Model'!L95 -> -66.080172
B34: Less: Change in NWC | E34: =SUM('Forecast Model'!H87:H91) -> 80.915592 | F34: =SUM('Forecast Model'!I87:I91) -> 87.018629 | G34: =SUM('Forecast Model'!J87:J91) -> 102.52968 | H34: =SUM('Forecast Model'!K87:K91) -> 117.65503 | I34: =SUM('Forecast Model'!L87:L91) -> 135.94378
B35: Plus: SBC | E35: ='Forecast Model'!H85 -> 106.3629 | F35: ='Forecast Model'!I85 -> 138.27177 | G35: ='Forecast Model'!J85 -> 175.60515 | H35: ='Forecast Model'!K85 -> 217.75038 | I35: ='Forecast Model'!L85 -> 265.65547
B37: Unlevered Free Cash Flow | E37: =SUM(E29:E35) -> 270.07749 | F37: =SUM(F29:F35) -> 351.84266 | G37: =SUM(G29:G35) -> 464.03746 | H37: =SUM(H29:H35) -> 592.97336 | I37: =SUM(I29:I35) -> 745.90577
B38: % Conversion (UCF/NOPAT) | E38: =E37/E29 -> 2.8698482 | F38: =F37/F29 -> 2.4908371 | G38: =G37/G29 -> 2.2683017 | H38: =H37/H29 -> 2.1123192 | I38: =I37/I29 -> 2.0021422
B42: SECTION 3: DISCOUNTING & PRESENT VALUE
E43: 2025E | F43: 2026E | G43: 2027E | H43: 2028E | I43: 2029E
B44: Discount Period (Mid Year Convention) | E44: 0.5 | F44: 1.5 | G44: 2.5 | H44: 3.5 | I44: 4.5
B45: Discount Factor | E45: =1/(1+$E$18)^E44 -> 0.94855402 | F45: =1/(1+$E$18)^F44 -> 0.85346596 | G45: =1/(1+$E$18)^G44 -> 0.76791003 | H45: =1/(1+$E$18)^H44 -> 0.69093068 | I45: =1/(1+$E$18)^I44 -> 0.62166815
B47: PV of FCF | E47: =E45*E37 -> 256.18309 | F47: =F45*F37 -> 300.28574 | G47: =G45*G37 -> 356.33902 | H47: =H45*H37 -> 409.70349 | I47: =I45*I37 -> 463.70586
B49: Sum of FCF | E49: =SUM(E47:I47) -> 1786.2172
B52: SECTION 4: TERMINAL VALUE CALCULATION
B53: Perpetual Growth Method
B55: Terminal Year FCF (2029E) | E55: =I37 -> 745.90577
B56: Perpetual Growth Rate | E56: =IF('Sensitivity Analysis'!K9="",0.025,'Sensitivity Analysis'!K9) -> 0.025
B57: Terminal Value (Perpetuity) | E57: =E55*(1+E56)/(E18-E56) -> 8847.5642
B58: PV of Terminal Value | E58: =E57/(1+$E$18)^I44 -> 5500.2489
B61: SECTION 5: ENTERPRISE VALUE TO EQUITY VALUE
B64: Sum of PV of FCF | E64: =E49 -> 1786.2172
B65: PV of Terminal Value | E65: =E58 -> 5500.2489
B66: Enterprise Value | E66: =SUM(E64:E65) -> 7286.466
B68: Less: Total Debt | E68: 0
B69: Plus: Cash & Equivalents | E69: ='Historical Financials'!J37 -> 877.645
B70: Less: Minority Interest | E70: =0 -> 0
B71: Less: Preferred Stock | E71: =0 -> 0
B72: Plus: Equity Investments | E72: 0
B73: Equity Value | E73: =SUM(E66:E72) -> 8164.111
B75: Shares Outstanding (mm) | E75: 46.13
B76: Implied Share Price ($) | E76: =E73/E75 -> 176.98051
B78: Fully Diluted Shares Outstanding(mm) | E78: =49.62 -> 49.62
B79: Implied Share Price -Diluted ($) | E79: =E73/E78 -> 164.53267

Sheet Sensitivity Analysis
B2: SENSITIVITY ANALYSIS
B4: WACC vs. PERPETUAL GROWTH RATE
B5: Implied Diluted Share Price across WACC and Perpetual Growth Rate assumptions
D7: Implied Price (Diluted) | E7: GROWTH RATE
D8: ='DCF Valuation'!E79 -> 164.53267 | E8: 0.015 | F8: 0.02 | G8: 0.025 | H8: 0.03 | I8: 0.035
C9: WACC | D9: 0.0914 | E9: 190.30429 | F9: 200.44952 | G9: 212.12264 | H9: 225.69693 | I9: 241.678
D10: 0.1014 | E10: 168.95747 | F10: 176.57916 | G10: 185.19846 | H10: 195.02493 | I10: 206.3313
D11: 0.1114 | E11: 152.0875 | F11: 157.98174 | G11: 164.55818 | H11: 171.94254 | I11: 180.29344
D12: 0.1214 | E12: 138.4302 | F12: 143.09524 | G12: 148.24421 | H12: 153.95653 | I12: 160.32999
D13: 0.1314 | E13: 127.15589 | F13: 130.91862 | G13: 135.03498 | H13: 139.5573 | I13: 144.54873
B18: TERMINAL EBIT MARGIN vs. REVENUE CAGR
B19: Implied Diluted Share Price across Terminal EBIT Margin and Revenue CAGR (2024-2029E)
C21: EBIT Margin | D21: Implied Price (Diluted) | E21: REVENUE CAGR
D22: ='DCF Valuation'!E79 -> 164.53267 | E22: 0.2 | F22: 0.24 | G22: 0.275 | H22: 0.31 | I22: 0.35
D23: 0.12 | E23: =('DCF Valuation'!$E$49+(('Forecast Model'!$G$8*(1+E$22)^5*$D23*(1-'Master Assumptions'!$J$20)+'Forecast Model'!$G$8*(1+E$22)^5*SUM('DCF Valuation'!$I$32:$I$35)/'Forecast Model'!$L$8)*(1+'DCF Valuation'!$E$56)/('DCF Valuation'!$E$18-'DCF Valuation'!$E$56))/(1+'DCF Valuation'!$E$18)^'DCF Valuation'!$I$44+SUM('DCF Valuation'!$E$68:$E$72))/'DCF Valuation'!$E$78 -> 121.18482 | F23: =('DCF Valuation'!$E$49+(('Forecast Model'!$G$8*(1+F$22)^5*$D23*(1-'Master Assumptions'!$J$20)+'Forecast Model'!$G$8*(1+F$22)^5*SUM('DCF Valuation'!$I$32:$I$35)/'Forecast Model'!$L$8)*(1+'DCF Valuation'!$E$56)/('DCF Valuation'!$E$18-'DCF Valuation'!$E$56))/(1+'DCF Valuation'!$E$18)^'DCF Valuation'!$I$44+SUM('DCF Valuation'!$E$68:$E$72))/'DCF Valuation'!$E$78 -> 133.21016 | G23: =('DCF Valuation'!$E$49+(('Forecast Model'!$G$8*(1+G$22)^5*$D23*(1-'Master Assumptions'!$J$20)+'Forecast Model'!$G$8*(1+G$22)^5*SUM('DCF Valuation'!$I$32:$I$35)/'Forecast Model'!$L$8)*(1+'DCF Valuation'!$E$56)/('DCF Valuation'!$E$18-'DCF Valuation'!$E$56))/(1+'DCF Valuation'!$E$18)^'DCF Valuation'!$I$44+SUM('DCF Valuation'!$E$68:$E$72))/'DCF Valuation'!$E$78 -> 145.08515 | H23: =('DCF Valuation'!$E$49+(('Forecast Model'!$G$8*(1+H$22)^5*$D23*(1-'Master Assumptions'!$J$20)+'Forecast Model'!$G$8*(1+H$22)^5*SUM('DCF Valuation'!$I$32:$I$35)/'Forecast Model'!$L$8)*(1+'DCF Valuation'!$E$56)/('DCF Valuation'!$E$18-'DCF Valuation'!$E$56))/(1+'DCF Valuation'!$E$18)^'DCF Valuation'!$I$44+SUM('DCF Valuation'!$E$68:$E$72))/'DCF Valuation'!$E$78 -> 158.33815 | I23: =('DCF Valuation'!$E$49+(('Forecast Model'!$G$8*(1+I$22)^5*$D23*(1-'Master Assumptions'!$J$20)+'Forecast Model'!$G$8*(1+I$22)^5*SUM('DCF Valuation'!$I$32:$I$35)/'Forecast Model'!$L$8)*(1+'DCF Valuation'!$E$56)/('DCF Valuation'!$E$18-'DCF Valuation'!$E$56))/(1+'DCF Valuation'!$E$18)^'DCF Valuation'!$I$44+SUM('DCF Valuation'!$E$68:$E$72))/'DCF Valuation'!$E$78 -> 175.32167
D24: 0.14 | E24: =('DCF Valuation'!$E$49+(('Forecast Model'!$G$8*(1+E$22)^5*$D24*(1-'Master Assumptions'!$J$20)+'Forecast Model'!$G$8*(1+E$22)^5*SUM('DCF Valuation'!$I$32:$I$35)/'Forecast Model'!$L$8)*(1+'DCF Valuation'!$E$56)/('DCF Valuation'!$E$18-'DCF Valuation'!$E$56))/(1+'DCF Valuation'!$E$18)^'DCF Valuation'!$I$44+SUM('DCF Valuation'!$E$68:$E$72))/'DCF Valuation'!$E$78 -> 125.61053 | F24: =('DCF Valuation'!$E$49+(('Forecast Model'!$G$8*(1+F$22)^5*$D24*(1-'Master Assumptions'!$J$20)+'Forecast Model'!$G$8*(1+F$22)^5*SUM('DCF Valuation'!$I$32:$I$35)/'Forecast Model'!$L$8)*(1+'DCF Valuation'!$E$56)/('DCF Valuation'!$E$18-'DCF Valuation'!$E$56))/(1+'DCF Valuation'!$E$18)^'DCF Valuation'!$I$44+SUM('DCF Valuation'!$E$68:$E$72))/'DCF Valuation'!$E$78 -> 138.42434 | G24: =('DCF Valuation'!$E$49+(('Forecast Model'!$G$8*(1+G$22)^5*$D24*(1-'Master Assumptions'!$J$20)+'Forecast Model'!$G$8*(1+G$22)^5*SUM('DCF Valuation'!$I$32:$I$35)/'Forecast Model'!$L$8)*(1+'DCF Valuation'!$E$56)/('DCF Valuation'!$E$18-'DCF Valuation'!$E$56))/(1+'DCF Valuation'!$E$18)^'DCF Valuation'!$I$44+SUM('DCF Valuation'!$E$68:$E$72))/'DCF Valuation'!$E$78 -> 151.07792 | H24: =('DCF Valuation'!$E$49+(('Forecast Model'!$G$8*(1+H$22)^5*$D24*(1-'Master Assumptions'!$J$20)+'Forecast Model'!$G$8*(1+H$22)^5*SUM('DCF Valuation'!$I$32:$I$35)/'Forecast Model'!$L$8)*(1+'DCF Valuation'!$E$56)/('DCF Valuation'!$E$18-'DCF Valuation'!$E$56))/(1+'DCF Valuation'!$E$18)^'DCF Valuation'!$I$44+SUM('DCF Valuation'!$E$68:$E$72))/'DCF Valuation'!$E$78 -> 165.19988 | I24: =('DCF Valuation'!$E$49+(('Forecast Model'!$G$8*(1+I$22)^5*$D24*(1-'Master Assumptions'!$J$20)+'Forecast Model'!$G$8*(1+I$22)^5*SUM('DCF Valuation'!$I$32:$I$35)/'Forecast Model'!$L$8)*(1+'DCF Valuation'!$E$56)/('DCF Valuation'!$E$18-'DCF Valuation'!$E$56))/(1+'DCF Valuation'!$E$18)^'DCF Valuation'!$I$44+SUM('DCF Valuation'!$E$68:$E$72))/'DCF Valuation'!$E$78 -> 183.29695
D25: 0.16 | E25: =('DCF Valuation'!$E$49+(('Forecast Model'!$G$8*(1+E$22)^5*$D25*(1-'Master Assumptions'!$J$20)+'Forecast Model'!$G$8*(1+E$22)^5*SUM('DCF Valuation'!$I$32:$I$35)/'Forecast Model'!$L$8)*(1+'DCF Valuation'!$E$56)/('DCF Valuation'!$E$18-'DCF Valuation'!$E$56))/(1+'DCF Valuation'!$E$18)^'DCF Valuation'!$I$44+SUM('DCF Valuation'!$E$68:$E$72))/'DCF Valuation'!$E$78 -> 130.03625 | F25: =('DCF Valuation'!$E$49+(('Forecast Model'!$G$8*(1+F$22)^5*$D25*(1-'Master Assumptions'!$J$20)+'Forecast Model'!$G$8*(1+F$22)^5*SUM('DCF Valuation'!$I$32:$I$35)/'Forecast Model'!$L$8)*(1+'DCF Valuation'!$E$56)/('DCF Valuation'!$E$18-'DCF Valuation'!$E$56))/(1+'DCF Valuation'!$E$18)^'DCF Valuation'!$I$44+SUM('DCF Valuation'!$E$68:$E$72))/'DCF Valuation'!$E$78 -> 143.63851 | G25: =('DCF Valuation'!$E$49+(('Forecast Model'!$G$8*(1+G$22)^5*$D25*(1-'Master Assumptions'!$J$20)+'Forecast Model'!$G$8*(1+G$22)^5*SUM('DCF Valuation'!$I$32:$I$35)/'Forecast Model'!$L$8)*(1+'DCF Valuation'!$E$56)/('DCF Valuation'!$E$18-'DCF Valuation'!$E$56))/(1+'DCF Valuation'!$E$18)^'DCF Valuation'!$I$44+SUM('DCF Valuation'!$E$68:$E$72))/'DCF Valuation'!$E$78 -> 157.0707 | H25: =('DCF Valuation'!$E$49+(('Forecast Model'!$G$8*(1+H$22)^5*$D25*(1-'Master Assumptions'!$J$20)+'Forecast Model'!$G$8*(1+H$22)^5*SUM('DCF Valuation'!$I$32:$I$35)/'Forecast Model'!$L$8)*(1+'DCF Valuation'!$E$56)/('DCF Valuation'!$E$18-'DCF Valuation'!$E$56))/(1+'DCF Valuation'!$E$18)^'DCF Valuation'!$I$44+SUM('DCF Valuation'!$E$68:$E$72))/'DCF Valuation'!$E$78 -> 172.06161 | I25: =('DCF Valuation'!$E$49+(('Forecast Model'!$G$8*(1+I$22)^5*$D25*(1-'Master Assumptions'!$J$20)+'Forecast Model'!$G$8*(1+I$22)^5*SUM('DCF Valuation'!$I$32:$I$35)/'Forecast Model'!$L$8)*(1+'DCF Valuation'!$E$56)/('DCF Valuation'!$E$18-'DCF Valuation'!$E$56))/(1+'DCF Valuation'!$E$18)^'DCF Valuation'!$I$44+SUM('DCF Valuation'!$E$68:$E$72))/'DCF Valuation'!$E$78 -> 191.27223
D26: 0.185 | E26: =('DCF Valuation'!$E$49+(('Forecast Model'!$G$8*(1+E$22)^5*$D26*(1-'Master Assumptions'!$J$20)+'Forecast Model'!$G$8*(1+E$22)^5*SUM('DCF Valuation'!$I$32:$I$35)/'Forecast Model'!$L$8)*(1+'DCF Valuation'!$E$56)/('DCF Valuation'!$E$18-'DCF Valuation'!$E$56))/(1+'DCF Valuation'!$E$18)^'DCF Valuation'!$I$44+SUM('DCF Valuation'!$E$68:$E$72))/'DCF Valuation'!$E$78 -> 135.56839 | F26: =('DCF Valuation'!$E$49+(('Forecast Model'!$G$8*(1+F$22)^5*$D26*(1-'Master Assumptions'!$J$20)+'Forecast Model'!$G$8*(1+F$22)^5*SUM('DCF Valuation'!$I$32:$I$35)/'Forecast Model'!$L$8)*(1+'DCF Valuation'!$E$56)/('DCF Valuation'!$E$18-'DCF Valuation'!$E$56))/(1+'DCF Valuation'!$E$18)^'DCF Valuation'!$I$44+SUM('DCF Valuation'!$E$68:$E$72))/'DCF Valuation'!$E$78 -> 150.15623 | G26: =('DCF Valuation'!$E$49+(('Forecast Model'!$G$8*(1+G$22)^5*$D26*(1-'Master Assumptions'!$J$20)+'Forecast Model'!$G$8*(1+G$22)^5*SUM('DCF Valuation'!$I$32:$I$35)/'Forecast Model'!$L$8)*(1+'DCF Valuation'!$E$56)/('DCF Valuation'!$E$18-'DCF Valuation'!$E$56))/(1+'DCF Valuation'!$E$18)^'DCF Valuation'!$I$44+SUM('DCF Valuation'!$E$68:$E$72))/'DCF Valuation'!$E$78 -> 164.56167 | H26: =('DCF Valuation'!$E$49+(('Forecast Model'!$G$8*(1+H$22)^5*$D26*(1-'Master Assumptions'!$J$20)+'Forecast Model'!$G$8*(1+H$22)^5*SUM('DCF Valuation'!$I$32:$I$35)/'Forecast Model'!$L$8)*(1+'DCF Valuation'!$E$56)/('DCF Valuation'!$E$18-'DCF Valuation'!$E$56))/(1+'DCF Valuation'!$E$18)^'DCF Valuation'!$I$44+SUM('DCF Valuation'!$E$68:$E$72))/'DCF Valuation'!$E$78 -> 180.63877 | I26: =('DCF Valuation'!$E$49+(('Forecast Model'!$G$8*(1+I$22)^5*$D26*(1-'Master Assumptions'!$J$20)+'Forecast Model'!$G$8*(1+I$22)^5*SUM('DCF Valuation'!$I$32:$I$35)/'Forecast Model'!$L$8)*(1+'DCF Valuation'!$E$56)/('DCF Valuation'!$E$18-'DCF Valuation'!$E$56))/(1+'DCF Valuation'!$E$18)^'DCF Valuation'!$I$44+SUM('DCF Valuation'!$E$68:$E$72))/'DCF Valuation'!$E$78 -> 201.24133
D27: 0.21 | E27: =('DCF Valuation'!$E$49+(('Forecast Model'!$G$8*(1+E$22)^5*$D27*(1-'Master Assumptions'!$J$20)+'Forecast Model'!$G$8*(1+E$22)^5*SUM('DCF Valuation'!$I$32:$I$35)/'Forecast Model'!$L$8)*(1+'DCF Valuation'!$E$56)/('DCF Valuation'!$E$18-'DCF Valuation'!$E$56))/(1+'DCF Valuation'!$E$18)^'DCF Valuation'!$I$44+SUM('DCF Valuation'!$E$68:$E$72))/'DCF Valuation'!$E$78 -> 141.10053 | F27: =('DCF Valuation'!$E$49+(('Forecast Model'!$G$8*(1+F$22)^5*$D27*(1-'Master Assumptions'!$J$20)+'Forecast Model'!$G$8*(1+F$22)^5*SUM('DCF Valuation'!$I$32:$I$35)/'Forecast Model'!$L$8)*(1+'DCF Valuation'!$E$56)/('DCF Valuation'!$E$18-'DCF Valuation'!$E$56))/(1+'DCF Valuation'!$E$18)^'DCF Valuation'!$I$44+SUM('DCF Valuation'!$E$68:$E$72))/'DCF Valuation'!$E$78 -> 156.67395 | G27: =('DCF Valuation'!$E$49+(('Forecast Model'!$G$8*(1+G$22)^5*$D27*(1-'Master Assumptions'!$J$20)+'Forecast Model'!$G$8*(1+G$22)^5*SUM('DCF Valuation'!$I$32:$I$35)/'Forecast Model'!$L$8)*(1+'DCF Valuation'!$E$56)/('DCF Valuation'!$E$18-'DCF Valuation'!$E$56))/(1+'DCF Valuation'!$E$18)^'DCF Valuation'!$I$44+SUM('DCF Valuation'!$E$68:$E$72))/'DCF Valuation'!$E$78 -> 172.05264 | H27: =('DCF Valuation'!$E$49+(('Forecast Model'!$G$8*(1+H$22)^5*$D27*(1-'Master Assumptions'!$J$20)+'Forecast Model'!$G$8*(1+H$22)^5*SUM('DCF Valuation'!$I$32:$I$35)/'Forecast Model'!$L$8)*(1+'DCF Valuation'!$E$56)/('DCF Valuation'!$E$18-'DCF Valuation'!$E$56))/(1+'DCF Valuation'!$E$18)^'DCF Valuation'!$I$44+SUM('DCF Valuation'!$E$68:$E$72))/'DCF Valuation'!$E$78 -> 189.21593 | I27: =('DCF Valuation'!$E$49+(('Forecast Model'!$G$8*(1+I$22)^5*$D27*(1-'Master Assumptions'!$J$20)+'Forecast Model'!$G$8*(1+I$22)^5*SUM('DCF Valuation'!$I$32:$I$35)/'Forecast Model'!$L$8)*(1+'DCF Valuation'!$E$56)/('DCF Valuation'!$E$18-'DCF Valuation'!$E$56))/(1+'DCF Valuation'!$E$18)^'DCF Valuation'!$I$44+SUM('DCF Valuation'!$E$68:$E$72))/'DCF Valuation'!$E$78 -> 211.21043
D28: 0.23 | E28: =('DCF Valuation'!$E$49+(('Forecast Model'!$G$8*(1+E$22)^5*$D28*(1-'Master Assumptions'!$J$20)+'Forecast Model'!$G$8*(1+E$22)^5*SUM('DCF Valuation'!$I$32:$I$35)/'Forecast Model'!$L$8)*(1+'DCF Valuation'!$E$56)/('DCF Valuation'!$E$18-'DCF Valuation'!$E$56))/(1+'DCF Valuation'!$E$18)^'DCF Valuation'!$I$44+SUM('DCF Valuation'!$E$68:$E$72))/'DCF Valuation'!$E$78 -> 145.52625 | F28: =('DCF Valuation'!$E$49+(('Forecast Model'!$G$8*(1+F$22)^5*$D28*(1-'Master Assumptions'!$J$20)+'Forecast Model'!$G$8*(1+F$22)^5*SUM('DCF Valuation'!$I$32:$I$35)/'Forecast Model'!$L$8)*(1+'DCF Valuation'!$E$56)/('DCF Valuation'!$E$18-'DCF Valuation'!$E$56))/(1+'DCF Valuation'!$E$18)^'DCF Valuation'!$I$44+SUM('DCF Valuation'!$E$68:$E$72))/'DCF Valuation'!$E$78 -> 161.88812 | G28: =('DCF Valuation'!$E$49+(('Forecast Model'!$G$8*(1+G$22)^5*$D28*(1-'Master Assumptions'!$J$20)+'Forecast Model'!$G$8*(1+G$22)^5*SUM('DCF Valuation'!$I$32:$I$35)/'Forecast Model'!$L$8)*(1+'DCF Valuation'!$E$56)/('DCF Valuation'!$E$18-'DCF Valuation'!$E$56))/(1+'DCF Valuation'!$E$18)^'DCF Valuation'!$I$44+SUM('DCF Valuation'!$E$68:$E$72))/'DCF Valuation'!$E$78 -> 178.04541 | H28: =('DCF Valuation'!$E$49+(('Forecast Model'!$G$8*(1+H$22)^5*$D28*(1-'Master Assumptions'!$J$20)+'Forecast Model'!$G$8*(1+H$22)^5*SUM('DCF Valuation'!$I$32:$I$35)/'Forecast Model'!$L$8)*(1+'DCF Valuation'!$E$56)/('DCF Valuation'!$E$18-'DCF Valuation'!$E$56))/(1+'DCF Valuation'!$E$18)^'DCF Valuation'!$I$44+SUM('DCF Valuation'!$E$68:$E$72))/'DCF Valuation'!$E$78 -> 196.07766 | I28: =('DCF Valuation'!$E$49+(('Forecast Model'!$G$8*(1+I$22)^5*$D28*(1-'Master Assumptions'!$J$20)+'Forecast Model'!$G$8*(1+I$22)^5*SUM('DCF Valuation'!$I$32:$I$35)/'Forecast Model'!$L$8)*(1+'DCF Valuation'!$E$56)/('DCF Valuation'!$E$18-'DCF Valuation'!$E$56))/(1+'DCF Valuation'!$E$18)^'DCF Valuation'!$I$44+SUM('DCF Valuation'!$E$68:$E$72))/'DCF Valuation'!$E$78 -> 219.18571
D29: 0.25 | E29: =('DCF Valuation'!$E$49+(('Forecast Model'!$G$8*(1+E$22)^5*$D29*(1-'Master Assumptions'!$J$20)+'Forecast Model'!$G$8*(1+E$22)^5*SUM('DCF Valuation'!$I$32:$I$35)/'Forecast Model'!$L$8)*(1+'DCF Valuation'!$E$56)/('DCF Valuation'!$E$18-'DCF Valuation'!$E$56))/(1+'DCF Valuation'!$E$18)^'DCF Valuation'!$I$44+SUM('DCF Valuation'!$E$68:$E$72))/'DCF Valuation'!$E$78 -> 149.95196 | F29: =('DCF Valuation'!$E$49+(('Forecast Model'!$G$8*(1+F$22)^5*$D29*(1-'Master Assumptions'!$J$20)+'Forecast Model'!$G$8*(1+F$22)^5*SUM('DCF Valuation'!$I$32:$I$35)/'Forecast Model'!$L$8)*(1+'DCF Valuation'!$E$56)/('DCF Valuation'!$E$18-'DCF Valuation'!$E$56))/(1+'DCF Valuation'!$E$18)^'DCF Valuation'!$I$44+SUM('DCF Valuation'!$E$68:$E$72))/'DCF Valuation'!$E$78 -> 167.1023 | G29: =('DCF Valuation'!$E$49+(('Forecast Model'!$G$8*(1+G$22)^5*$D29*(1-'Master Assumptions'!$J$20)+'Forecast Model'!$G$8*(1+G$22)^5*SUM('DCF Valuation'!$I$32:$I$35)/'Forecast Model'!$L$8)*(1+'DCF Valuation'!$E$56)/('DCF Valuation'!$E$18-'DCF Valuation'!$E$56))/(1+'DCF Valuation'!$E$18)^'DCF Valuation'!$I$44+SUM('DCF Valuation'!$E$68:$E$72))/'DCF Valuation'!$E$78 -> 184.03819 | H29: =('DCF Valuation'!$E$49+(('Forecast Model'!$G$8*(1+H$22)^5*$D29*(1-'Master Assumptions'!$J$20)+'Forecast Model'!$G$8*(1+H$22)^5*SUM('DCF Valuation'!$I$32:$I$35)/'Forecast Model'!$L$8)*(1+'DCF Valuation'!$E$56)/('DCF Valuation'!$E$18-'DCF Valuation'!$E$56))/(1+'DCF Valuation'!$E$18)^'DCF Valuation'!$I$44+SUM('DCF Valuation'!$E$68:$E$72))/'DCF Valuation'!$E$78 -> 202.93939 | I29: =('DCF Valuation'!$E$49+(('Forecast Model'!$G$8*(1+I$22)^5*$D29*(1-'Master Assumptions'!$J$20)+'Forecast Model'!$G$8*(1+I$22)^5*SUM('DCF Valuation'!$I$32:$I$35)/'Forecast Model'!$L$8)*(1+'DCF Valuation'!$E$56)/('DCF Valuation'!$E$18-'DCF Valuation'!$E$56))/(1+'DCF Valuation'!$E$18)^'DCF Valuation'!$I$44+SUM('DCF Valuation'!$E$68:$E$72))/'DCF Valuation'!$E$78 -> 227.16099
C30: Summary | D30: MIN / BASE / MAX | E30: =MIN(E23:I29) -> 121.18482 | G30: =G26 -> 164.56167 | I30: =MAX(E23:I29) -> 227.16099
E31: MIN | G31: BASE | I31: MAX

Sheet Scenario Analysis
B3: SCENARIO ANALYSIS
B5: This analysis compares Bull, Base, and Bear scenarios for Duolingo's DCF valuation.
B8: SCENARIO VALUATION SUMMARY | J8: VALUATION AT A GLANCE
B10: Scenario | C10: Implied Share Price | D10: Enterprise Value | E10: Equity Value | F10: Terminal Value | G10: PV of FCFs | H10: 2029E Revenue | I10: 2029E EBIT Margin | J10: Current Stock: | K10: ~$112
B11: 🐂 Bull Case | C11: 165 | D11: $7,286M | E11: $8,164M | F11: $5,500M | G11: $1,786M | H11: $2,522M | I11: 0.185
B12: 📊 Base Case | C12: 97 | D12: $3,935M | E12: $4,813M | F12: $2,702M | G12: $1,234M | H12: $1,899M | I12: 0.113 | J12: Bull Upside: | K12: 0.47
B13: 🐻 Bear Case | C13: 60 | D13: $2,103M | E13: $2,981M | F13: $1,426M | G13: $677M | H13: $1,475M | I13: 0.015 | J13: Bear Downside: | K13: -0.46
J14: Base vs Current: | K14: -0.13
B16: CHART DATA - SHARE PRICE BY SCENARIO
B18: Scenario | C18: Share Price ($)
B19: Bull | C19: 165
B20: Base | C20: 97
B21: Bear | C21: 60
B24: CHART DATA - REVENUE TRAJECTORY ($M)
B26: Year | C26: Bull | D26: Base | E26: Bear
B27: 2024A | C27: 748 | D27: 748 | E27: 748
B28: 2025E | C28: 1010 | D28: 957 | E28: 898
B29: 2026E | C29: 1313 | D29: 1187 | E29: 1050
B30: 2027E | C30: 1667 | D30: 1437 | E30: 1197
B31: 2028E | C31: 2068 | D31: 1695 | E31: 1341
B32: 2029E | C32: 2522 | D32: 1963 | E32: 1475
B35: CHART DATA - EBIT MARGIN TRAJECTORY (%)
B37: Year | C37: Bull | D37: Base | E37: Bear
B38: 2025E | C38: 0.11 | D38: 0.064 | E38: 0.035
B39: 2026E | C39: 0.13 | D39: 0.079 | E39: 0.03
B40: 2027E | C40: 0.15 | D40: 0.095 | E40: 0.024
B41: 2028E | C41: 0.168 | D41: 0.108 | E41: 0.019
B42: 2029E | C42: 0.185 | D42: 0.118 | E42: 0.015
B45: CHART DATA - VALUE BRIDGE ($M)
B47: Component | C47: Bull | D47: Base | E47: Bear
B48: PV of FCFs | C48: 1786 | D48: 1234 | E48: 677
B49: PV of Terminal Value | C49: 5500 | D49: 2702 | E49: 1426
B70: KEY ASSUMPTIONS COMPARISON
B72: Assumption | C72: Bull | D72: Base | E72: Bear | G72: PROBABILITY-WEIGHTED VALUATION
B73: 5-Year Revenue CAGR | C73: 0.276 | D73: 0.214 | E73: 0.146
B74: Terminal EBIT Margin | C74: 0.185 | D74: 0.113 | E74: 0.015 | G74: Scenario | H74: Probability | I74: Share Price | J74: Weighted
B75: R&D % (2029E) | C75: 0.261 | D75: 0.286 | E75: 0.33 | G75: Bull | H75: 0.25 | I75: 165 | J75: =H75*I75 -> 41.25
B76: SG&A % (2029E) | C76: 0.299 | D76: 0.324 | E76: 0.35 | G76: Base | H76: 0.5 | I76: 97 | J76: =H76*I76 -> 48.5
B77: Gross Margin (2029E) | C77: 0.76 | D77: 0.745 | E77: 0.71 | G77: Bear | H77: 0.25 | I77: 60 | J77: =H77*I77 -> 15
G79: Expected Value | H79: =SUM(H75:H77) -> 1 | J79: =SUM(J75:J77) -> 104.75
B82: SCENARIO RANGE CHART DATA
B84: Metric | C84: Bear | D84: Base | E84: Bull
B85: Share Price ($) | C85: 60 | D85: 97 | E85: 165
B86: Enterprise Value ($M) | C86: 2103 | D86: 3935 | E86: 7286
B87: 2029E Revenue ($M) | C87: 1475 | D87: 1899 | E87: 2522
B90: FOOTBALL FIELD - VALUATION RANGE
B92: Valuation Range | C92: Low | D92: Range | E92: High
B93: DCF Valuation | C93: 60 | D93: 105 | E93: 165

Sheet Sources & Footnotes
B2: SOURCES & FOOTNOTES
B3: Duolingo, Inc. (DUOL) | Data Sources, Market Inputs, Methodology & Audit Trail
B5: SECTION 1: PRIMARY DATA SOURCES
B6: # | C6: Source Name | D6: Type | E6: Data Used For | F6: Tabs Referenced | G6: Access Date | H6: URL / Reference
B7: S1 | C7: SEC EDGAR — DUOL 10-K (FY2024) | D7: SEC Filing | E7: Full-year audited financial statements (IS, BS, CF); MD&A; risk factors | F7: Historical Financials | G7: 45689 | H7: https://www.sec.gov/cgi-bin/browse-edgar?action=getcompany&CIK=DUOL&type=10-K
B8: S2 | C8: SEC EDGAR — DUOL 10-K (FY2023) | D8: SEC Filing | E8: Prior-year audited financials; year-over-year growth derivation | F8: Historical Financials | G8: 45323 | H8: https://www.sec.gov/cgi-bin/browse-edgar?action=getcompany&CIK=DUOL&type=10-K
B9: S3 | C9: SEC EDGAR — DUOL 10-K (FY2020–2022) | D9: SEC Filing | E9: Historical trend analysis; 5-year CAGR computation; margin trajectory | F9: Historical Financials | G9: Various | H9: https://www.sec.gov/cgi-bin/browse-edgar?action=getcompany&CIK=DUOL&type=10-K
B10: S4 | C10: FactSet — CAPM Market Data | D10: Terminal / Data Provider | E10: Risk-free rate, equity risk premium, levered beta (5Y monthly regression) | F10: DCF Valuation | G10: 45689 | H10: FactSet Research Systems (subscription terminal)
B11: S5 | C11: FactSet — Consensus Estimates | D11: Terminal / Data Provider | E11: Sell-side consensus revenue & EPS for FY25E; used as benchmark only | F11: Benchmark / Validation | G11: 45689 | H11: FactSet Research Systems (subscription terminal)
B12: S6 | C12: Supporting Schedules (Internal) | D12: Model Calculation | E12: Scenario assumptions for revenue growth, margins, DSO/DPO, SBC, tax rate ramp | F12: Master Assumptions, Forecast Model | G12: N/A | H12: See Supporting Schedules tab within this workbook
B13: S7 | C13: U.S. Treasury / FRED | D13: Government | E13: 10-Year UST yield cross-reference for Rf validation | F13: DCF Valuation | G13: 45689 | H13: https://fred.stlouisfed.org/series/DGS10
B14: S8 | C14: Duolingo Investor Relations | D14: Company IR | E14: Earnings releases, investor presentations, KPI disclosures (MAU, DAU, ARPU) | F14: Key Metrics, Forecast Model | G14: 45689 | H14: https://investors.duolingo.com/
B15: S9 | C15: S&P Capital IQ / Peer Comps | D15: Terminal / Data Provider | E15: Comparable company trading multiples for valuation cross-check | F15: Valuation (if applicable) | G15: 45689 | H15: Capital IQ (subscription terminal)
B16: S10 | C16: — | D16: — | E16: Reserved for additional sources as model evolves | F16: — | G16: — | H16: —
B18: SECTION 2: EXTERNAL MARKET INPUTS USED
B19: Input | C19: Value Used | D19: Source / Basis | E19: Feeds Into | F19: As-Of Date | G19: Source Ref
B20: Risk-Free Rate (Rf) | C20: 0.0405 | D20: 10-Year U.S. Treasury yield at market close; sourced from FactSet | E20: DCF Valuation → WACC (E9) | F20: Feb 2025 | G20: S4, S7
B21: Equity Risk Premium (ERP) | C21: 0.0446 | D21: Historical implied equity risk premium; FactSet (consistent with Damodaran methodology) | E21: DCF Valuation → WACC (E10) | F21: Feb 2025 | G21: S4
B22: Levered Beta | C22: 1.59x | D22: 5-year monthly regression vs. S&P 500; FactSet terminal | E22: DCF Valuation → WACC (E11) | F22: Feb 2025 | G22: S4
B23: Terminal Growth Rate (g) | C23: 0.025 | D23: Long-run U.S. nominal GDP growth proxy (~2.0% real + ~0.5% inflation buffer) | E23: DCF Valuation → Terminal Value (E56) | F23: Analyst Assumption | G23: S6
B24: Marginal Tax Rate | C24: 15.0% – 20.0% | D24: Effective tax rate ramping over forecast horizon; per SEC filings & analyst judgment | E24: Master Assumptions → NOPAT (F20:J20) | F24: FY25E–FY29E | G24: S1, S6
B25: EdTech TAM ($bn) | C25: N/A | D25: Not independently sourced; internal revenue build-up in Supporting Schedules | E25: Forecast Model | F25: N/A | G25: S6
B26: Consensus Revenue FY25E ($mm) | C26: N/A | D26: Sell-side consensus used as benchmark only; not a direct model input | E26: Benchmark / Validation | F26: Feb 2025 | G26: S5
B27: Consensus EPS FY25E | C27: N/A | D27: Sell-side consensus EPS used as benchmark only; not a direct model input | E27: Benchmark / Validation | F27: Feb 2025 | G27: S5
B28: [Add rows as needed] | C28: — | D28: — | E28: — | F28: — | G28: —
B30: SECTION 3: FOOTNOTES & ADJUSTMENTS
B31: Ref # | C31: Tab / Cell | D31: Footnote Description | E31: Source Ref | F31: Impact on Model
B32: [1] | C32: DCF Valuation, E11 | D32: Beta (1.59x) sourced from FactSet 5-year monthly regression vs. S&P 500 index; represents levered beta for DUOL. No Blume or Vasicek adjustment applied. | E32: S4 | F32: Directly affects Ke (11.14%) and WACC
B33: [2] | C33: DCF Valuation, E15 | D33: Capital structure assumed 100% equity / 0% debt; consistent with DUOL's zero-debt balance sheet as of FY2024. Weight of Debt = 0%. | E33: S1 | F33: WACC = Ke (no debt cost component)
B34: [3] | C34: Master Assumptions, F20:J20 | D34: Effective tax rate ramped from 15% (FY25E) to 20% (FY29E); reflects increasing profitability, international tax normalization, and expiring R&D credits. | E34: S1, S6 | F34: Reduces FCF as profitability scales
B35: [4] | C35: DCF Valuation, E56 | D35: Terminal growth rate of 2.5% selected as proxy for long-run nominal GDP growth (~2.0% real GDP + ~0.5% inflation). | E35: Analyst | F35: Terminal value is ~67% of enterprise value
B36: [5] | C36: Supporting Schedules, SBC | D36: SBC added back to FCF as a non-cash expense; dilution impact captured through fully diluted share count (49.62mm shares) in equity bridge. | E36: S6 | F36: Increases UFCFs; offset by diluted shares
B37: [6] | C37: Historical Financials, J37 | D37: Cash & equivalents of $877.6mm used in equity bridge; sourced from DUOL 10-K (FY2024) balance sheet. | E37: S1 | F37: Increases equity value by $877.6mm
B38: [7] | C38: Supporting Schedules, Revenue | D38: Revenue growth rates derived via three scenario paths (Bull/Base/Bear) with annual deceleration logic; not consensus-dependent. | E38: S6 | F38: Core driver of all financial projections
B39: [8] | C39: Master Assumptions, F29 | D39: SBC % of revenue held constant at FY2020 rate (10.5%) for forecast years; conservative assumption pending further disclosure. | E39: S6 | F39: Impacts operating margins and FCF
B40: [9] | C40: DCF Valuation, E9 | D40: Risk-free rate of 4.05% based on 10-Year U.S. Treasury yield; cross-referenced against FRED (DGS10 series) for validation. | E40: S4, S7 | F40: Anchor for CAPM cost of equity
B41: [10] | C41: — | D41: Reserved for additional footnotes as model evolves. | E41: — | F41: —
B43: SECTION 4: METHODOLOGY NOTES
B44: Area | C44: Methodology Description | D44: Applicable Tab(s)
B45: Valuation Approach | C45: Unlevered DCF to firm; perpetuity growth terminal value method; mid-year discounting convention applied to all projected cash flows. | D45: DCF Valuation
B46: WACC Derivation | C46: CAPM-based Cost of Equity: Ke = Rf (4.05%) + Beta (1.59) x ERP (4.46%) = 11.14%. 100% equity weight; no debt cost component. No size or country risk premium. | D46: DCF Valuation
B47: Revenue Forecast | C47: Top-line driven by historical revenue growth deceleration framework; three scenarios (Bull: 35%→22%, Base: 28%→16%, Bear: 20%→10%) with ~3–6 ppt annual deceleration. | D47: Forecast Model, Supporting Schedules
B48: Margin Expansion | C48: Gross margin expansion from 74.5% (FY25E) to 76.0% (FY29E); operating leverage via declining R&D % and SG&A % as revenue scales. | D48: Master Assumptions, Supporting Schedules
B49: Working Capital | C49: DSO (62 days) and DPO (12 days) held constant at historical averages; NWC changes derived from period-over-period revenue deltas. | D49: Supporting Schedules
B50: CapEx Treatment | C50: D&A held constant at 1.5% of revenue across forecast; CapEx assumed equal to D&A (maintenance capex assumption for asset-light model). | D50: Supporting Schedules
B51: SBC Treatment | C51: SBC treated as non-cash: added back in FCF derivation. Dilution captured via fully diluted share count (49.62mm) in equity bridge to per-share price. | D51: DCF Valuation
B52: Tax Assumptions | C52: Effective tax rate ramped from 15% (FY25E) to 20% (FY29E); reflects path toward normalized profitability. No NOL carryforward or deferred tax modeled. | D52: Master Assumptions
B53: Terminal Value | C53: Gordon Growth Model: TV = FCF(2029E) x (1+g) / (WACC – g); g = 2.5%, WACC = 11.14%. Terminal value discounted back 5 years to present value. | D53: DCF Valuation, Sensitivity Analysis
B54: Scenario Framework | C54: Bull/Base/Bear scenarios controlled via CHOOSE() function referencing scenario code in Master Assumptions; all assumptions flow from Supporting Schedules. | D54: Scenario Analysis, Master Assumptions
B56: SECTION 5: REVISION LOG
B57: Version | C57: Date | D57: Author | E57: Change Description | F57: Tabs Affected
B58: v1.0 | C58: 45689 | D58: Analyst | E58: Initial model build: Historical financials (FY2020–2024A), DCF valuation, CAPM/WACC, 5-year forecast, scenario framework. | F58: All
B59: v1.1 | C59: — | D59: — | E59: [e.g., Updated beta + ERP; re-ran sensitivity tables] | F59: —
B60: v1.2 | C60: — | D60: — | E60: [e.g., Incorporated Q1 2025 actuals; revised near-term growth] | F60: —
B61: v2.0 | C61: — | D61: — | E61: [e.g., Major revision: new fiscal year data; reforecast all assumptions] | F61: —
B62: v2.1 | C62: — | D62: — | E62: [Change description] | F62: —
B63: v3.0 | C63: — | D63: — | E63: [Change description] | F63: —
B64: [Add] | C64: — | D64: — | E64: [Add] | F64: —
B66: SECTION 6: DISCLAIMER & LIMITATIONS
B67: IMPORTANT: This financial model is prepared for informational and analytical purposes only.
B68: [1] This model does not constitute investment advice, a recommendation, or a solicitation to buy or sell securities.
B69: [2] All projections are based on assumptions that may not reflect actual future performance.
B70: [3] Historical financial data is sourced from public SEC filings and may be subject to restatement.
B71: [4] Market data (prices, rates, betas) is point-in-time and subject to change.
B72: [5] Model outputs are highly sensitive to input assumptions; users should review the Sensitivity Analysis tab.
B73: [6] The author(s) make no warranty as to accuracy or completeness of data or projections.
B74: [7] Users should conduct independent due diligence before making any investment decisions.

Sheet _ChartData
A1: Year | B1: Revenue | C1: EBIT | D1: Net Income | E1: FCF
A2: 2020A | B2: 161.7 | C2: -15.7 | D2: -15.8 | E2: 13.7
A3: 2021A | B3: 250.8 | C3: -56.1 | D3: -60.1 | E3: 3
A4: 2022A | B4: 369.5 | C4: -64.6 | D4: -59.6 | E4: 43.5
A5: 2023A | B5: 531.1 | C5: -12.9 | D5: 16.1 | E5: 139.9
A6: 2024A | B6: 748 | C6: 63.6 | D6: 88.6 | E6: 264.4
A7: 2025E | B7: 1009.8 | C7: 110.7 | D7: 126.1 | E7: 328.5
A8: 2026E | B8: 1312.8 | C8: 170.2 | D8: 184.4 | E8: 429.4
A9: 2027E | B9: 1667.2 | C9: 249.5 | D9: 262.3 | E9: 565.4
A10: 2028E | B10: 2067.4 | C10: 346.6 | D10: 357.4 | E10: 723.8
A11: 2029E | B11: 2522.2 | C11: 465.7 | D11: 473 | E11: 912.4
A14: Year | B14: Gross Margin | C14: EBIT Margin | D14: Net Margin | E14: FCF Margin
A15: 2020A | B15: 0.726 | C15: -0.097 | D15: -0.098 | E15: 0.085
A16: 2021A | B16: 0.732 | C16: -0.224 | D16: -0.24 | E16: 0.012
A17: 2022A | B17: 0.733 | C17: -0.175 | D17: -0.161 | E17: 0.118
A18: 2023A | B18: 0.736 | C18: -0.024 | D18: 0.03 | E18: 0.264
A19: 2024A | B19: 0.735 | C19: 0.085 | D19: 0.118 | E19: 0.353
A20: 2025E | B20: 0.745 | C20: 0.11 | D20: 0.125 | E20: 0.325
A21: 2026E | B21: 0.75 | C21: 0.13 | D21: 0.14 | E21: 0.327
A22: 2027E | B22: 0.755 | C22: 0.15 | D22: 0.157 | E22: 0.339
A23: 2028E | B23: 0.758 | C23: 0.168 | D23: 0.173 | E23: 0.35
A24: 2029E | B24: 0.76 | C24: 0.185 | D24: 0.188 | E24: 0.362
A27: Year | B27: Bull | C27: Base | D27: Bear
A28: 2024A | B28: 748 | C28: 748 | D28: 748
A29: 2025E | B29: 1010 | C29: 957 | D29: 898
A30: 2026E | B30: 1313 | C30: 1187 | D30: 1050
A31: 2027E | B31: 1667 | C31: 1437 | D31: 1197
A32: 2028E | B32: 2068 | C32: 1695 | D32: 1341
A33: 2029E | B33: 2522 | C33: 1963 | D33: 1475
A35: Component | B35: Bull | C35: Base | D35: Bear
A36: PV of FCFs | B36: 1786 | C36: 1234 | D36: 677
A37: PV of Terminal Value | B37: 5500 | C37: 2702 | D37: 1426
A38: Net Cash | B38: 878 | C38: 878 | D38: 878
